Workbook

Sheet Annex A
A1: I. CHECK SỔ SÁCH VỚI DANH MỤC KIỂM KÊ
B3: TÀI SẢN | C3: Anex | D3: Theo sổ sách (23.3.2026) | F3: Theo Annex A | H3: Chênh lệch
D4: Số lượng | E4: Giá trị | F4: Số lượng | G4: Giá trị | H4: Số lượng | I4: Giá trị
B5: Tồn kho phim SX (Tk 15666) | C5: A | D5: =COUNTA('TK 15666. Phim SX'!$B$6:$B$13) | E5: 36977023489 | G5: =E5
B6: Tồn kho CT Phim (Tk 15661) | C6: A | D6: =COUNTA('TK 15661.Bản quyền phim '!$B$6:$B$497)+2 | E6: 55564486653 | F6: =COUNTIF('TK 15661.Bản quyền phim '!$AH$6:$AH$497,"OK")+2 | G6: =E6 | H6: =D6-F6 | I6: =SUMIF('TK 15661.Bản quyền phim '!$AH$6:$AH$497, 0, 'TK 15661.Bản quyền phim '!$X$6:$X$497) | J6: Cần kiểm kê bổ sung
B7: Bản quyền phim VOD | C7: A | E7: 0 | F7: =H20 | G7: 0 | H7: Đã ghi nhận thẳng vào P&L, không còn số dư trên BCĐKT
B8: Phim Barter | C8: A | E8: 0 | F8: =I20 | G8: 0
B9: Show tự sản xuất | C9: A | E9: 0 | F9: =J20 | G9: 0
A11: II. CHECK DANH MỤC KIỂM KÊ VỚI SỔ SÁCH
E12: Trong sổ sách | I12: Ngoài sổ sách
B13: Danh sách kiểm kê License | C13: Unit | D13: Number | E13: TK 15661 | F13: TK 242. Bản quyền phim hợp tác | G13: TK 15666. Bản quyền phim tự SX | H13: 242. Bản quyền phim VOD | I13: Phim Barter | J13: Show tự sản xuất | K13: Check | L13: VSTV's note
B14: KK1. Movies | C14: Titles | D14: =COUNTA('KK1. Movies'!A7:A343) | E14: =COUNTIF('KK1. Movies'!$AM$7:$AM$343,1) | F14: =COUNTIF('242.BQ Phim hợp tác'!$R:$R,1) | K14: =SUM(E14:J14)=D14 | L14: Gồm 331 phim trong sheet 15661 và 6 phim trong sheet 242 bản quyền Phim hợp tác
B15: KK2. Series | C15: Titles | D15: =COUNTA('KK2. Series'!A7:A174) | E15: =COUNTIF('KK2. Series'!$AR$7:$AR$174,1) | G15: =COUNTIF('KK2. Series'!$AQ$7:$AQ$174,1) | H15: =COUNTIF('KK2. Series'!$AP$7:$AP$174,1) | I15: =COUNTIF('KK2. Series'!$AS$7:$AS$174,1) | K15: =SUM(E15:J15)=D15 | L15: Gồm 331 phim trong sheet 15661 và 7 phim trong sheet 15666 Bản quyền phim tự SX
B16: KK3. Kids | C16: Titles | D16: =COUNTA('KK3. Kids'!$A$7:$A$57) | E16: =COUNTIF('KK3. Kids'!$AI$7:$AI$57,1) | K16: =SUM(E16:J16)=D16 | L16: Thực tế tăng 2 so với Annex A vì lỗi STT ở sheet Kids
B17: KK4. Show | C17: Titles | D17: =COUNTA('KK4. Show'!A7:A15) | J17: =COUNTIF('KK4. Show'!$O$6:$O$15,1) | K17: =SUM(E17:J17)=D17 | L17: Đây là các show K+ thuê bên thứ 3 hoặc tự sản xuất, không theo dõi tồn kho, đã tính vào chi phí khi phát sóng shows
B18: KK5. Doc | C18: Titles | D18: =COUNTA('KK5. Doc'!B7:B23) | E18: =COUNTIF('KK5. Doc'!$Y$7:$Y$23,1) | G18: =COUNTIF('KK5. Doc'!$Z$7:$Z$23,1) | I18: =COUNTIF('KK5. Doc'!$AA$7:$AA$23,1) | K18: =SUM(E18:J18)=D18 | L18: gồm 14 Docs free của Kênh DW + 3 Docs
B19: KK6. Bổ sung | C19: Titles | D19: =COUNTA('KK6. Bổ sung'!$A$7:$A$44) | E19: =COUNTIF('TK 15661.Bản quyền phim '!$AH$5:$AH$1048576,0) | K19: =SUM(E19:J19)=D19
B20: Total | D20: =SUM(D14:D19) | E20: =SUM(E14:E19) | F20: =SUM(F14:F19) | G20: =SUM(G14:G19) | H20: =SUM(H14:H19) | I20: =SUM(I14:I19) | J20: =SUM(J14:J19)

Sheet CodeRanMovies
A1: Clip Code | B1: Title EN | C1: Genres | D1: Rating | E1: Year | F1: Start Time | G1: End Time | H1: Data ID | I1: Stream URL | J1: Play Result | K1: Status
A2: MOV_DRA730 | B2: Shining for One Thing | C2: Movies | D2: 2 | E2: 2023 | F2: 2024-12-11T00:00:00+07:00 | H2: 99db7204-f12d-442e-be59-e8596a148abd | I2: https://censorship.kplus.vn/MediaAssets/Asset/6d095282-3fce-ef11-8593-0c42a12723cb/StreamPreview | J2: YES | K2: Success
A3: MOV_ACT_23__2691047 | B3: Rogue | C3: Movies | D3: 3 | E3: 2020 | F3: 2023-02-23T00:00:00+07:00 | H3: f2258306-4dcb-4197-a268-7896a7f70e45 | I3: https://censorship.kplus.vn/MediaAssets/Asset/c38272f7-e9ef-ee11-9144-f40270bf9ea7/StreamPreview | J3: YES | K3: Success
A4: MOV_ACT_22__2687284 | B4: Escape Plan 2: Hades | C4: Movies | D4: 4 | E4: 2018 | F4: 2022-12-22T00:00:00+07:00 | H4: f25fcdb0-2c40-4079-8fdd-3692aef3e45d | I4: https://censorship.kplus.vn/MediaAssets/Asset/239b2c3e-ceed-ee11-9144-f40270bf9ea7/StreamPreview | J4: YES | K4: Success
A5: MOV_ACT_23__2693370 | B5: Riam: Fighting Angel | C5: Movies | D5: 3 | E5: 2020 | F5: 2023-03-23T00:00:00+07:00 | H5: 8f92b6e0-a6ed-4c4f-b921-36b2f2694452 | I5: https://censorship.kplus.vn/MediaAssets/Asset/5a613a78-79f0-ee11-9144-f40270bf9ea7/StreamPreview | J5: YES | K5: Success
A6: MOV_ANI_23__2697127 | B6: Happy family | C6: Movies | D6: 5 | E6: 2017 | F6: 2023-05-12T00:00:00+07:00 | H6: dfc52e23-1a10-4573-9e16-6a589266ea2c | I6: https://censorship.kplus.vn/MediaAssets/Asset/c8311c8f-6ff0-ee11-9144-f40270bf9ea7/StreamPreview | J6: YES | K6: Success
A7: MOV_DRA739 | B7: Memoirs of a Geisha | C7: Movies | D7: 3 | E7: 2005 | F7: 2024-12-28T00:00:00+07:00 | H7: a65b5116-7df4-49d5-ad87-c2a0ac2f9ef3 | I7: https://censorship.kplus.vn/MediaAssets/Asset/49e59ea8-d5e9-ef11-8593-0c42a12723cb/StreamPreview | J7: YES | K7: Success
A8: MOV_DRA_23__2695077 | B8: The Courier | C8: Movies | D8: 3 | E8: 2021 | F8: 2023-04-20T00:00:00+07:00 | H8: 390f2015-66be-4d5d-bd86-5a292b9e17f9 | I8: https://censorship.kplus.vn/MediaAssets/Asset/fbac9cea-8ff3-ee11-9144-f40270bf9ea7/StreamPreview | J8: YES | K8: Success
A9: MOV_ACT_22__2686885 | B9: Hitman's Wife's Bodyguard | C9: Movies | D9: 4 | E9: 2021 | F9: 2022-12-16T00:00:00+07:00 | H9: ff3ed7b0-ee55-4648-83bb-4a44f4c0e853 | I9: https://censorship.kplus.vn/MediaAssets/Asset/e3f612f7-d2ed-ee11-9144-f40270bf9ea7/StreamPreview | J9: YES | K9: Success
A10: MOV_HOR_24__2713435 | B10: Guimoon: The lightless door | C10: Movies | D10: 4 | E10: 2021 | F10: 2024-02-28T00:00:00+07:00 | H10: 848b5a96-9f0e-4f95-ab59-a5ccb66fa8b2 | I10: https://censorship.kplus.vn/MediaAssets/Asset/0e72dc39-2077-ef11-8593-0c42a12723cb/StreamPreview | J10: YES | K10: Success
A11: MOV_DRA_23__2696593 | B11: Greta | C11: Movies | D11: 3 | E11: 2018 | F11: 2023-05-05T00:00:00+07:00 | H11: d8c4c337-36ec-40eb-9bb5-a0696eb79df5 | I11: https://censorship.kplus.vn/MediaAssets/Asset/6e78c7e1-54f0-ee11-9144-f40270bf9ea7/StreamPreview | J11: YES | K11: Success
A12: MOV_FAN_22__2686869 | B12: HOUSE WITH A CLOCK IN ITS WALLS | C12: Movies | D12: 5 | E12: 2018 | F12: 2022-12-15T00:00:00+07:00 | H12: 1be7d597-9d3f-4099-a11c-2aecd70ca673 | I12: https://censorship.kplus.vn/MediaAssets/Asset/d1884a75-d3f4-ee11-9144-f40270bf9ea7/StreamPreview | J12: YES | K12: Success
A13: MOV_CRI_21__2648182 | B13: MOZU | C13: Movies | D13: 3 | E13: 2015 | F13: 2021-04-13T00:00:00+07:00 | H13: bebd0816-a009-4c32-8999-c855c0c8140f | I13: https://censorship.kplus.vn/MediaAssets/Asset/318eb5ad-58ea-ee11-9144-f40270bf9ea7/StreamPreview | J13: YES | K13: Success
... A63: MOV_DRA_24__2712649 | B63: Phantom Thread | C63: Movies | D63: 3 | E63: 2017 | F63: 2024-02-16T00:00:00+07:00 | H63: 11bc91f4-93af-4874-a792-255ca791e5cb | I63: https://censorship.kplus.vn/MediaAssets/Asset/19783d90-0bf8-ee11-9144-f40270bf9ea7/StreamPreview | J63: YES | K63: Success
A64: MOV_ACT608 | B64: Elysium | C64: Movies | D64: 3 | F64: 2025-02-26T00:00:00+07:00 | H64: ecd81622-b53c-4a29-a8d5-a9929542c4e4 | I64: https://censorship.kplus.vn/MediaAssets/Asset/76172eb6-a90b-f011-8593-0c42a12723cb/StreamPreview | J64: YES | K64: Success
A65: MOV_HOR_22__2686491 | B65: Countdown (US) | C65: Movies | D65: 4 | E65: 2019 | F65: 2022-12-08T00:00:00+07:00 | H65: e89dcc78-bd41-48a5-a443-11ed62874399 | I65: https://censorship.kplus.vn/MediaAssets/Asset/7ca6779f-d0ed-ee11-9144-f40270bf9ea7/StreamPreview | J65: YES | K65: Success
A66: MOV_DRA_23__2698013 | B66: The Woman Who Ran | C66: Movies | D66: 2 | E66: 2020 | F66: 2023-05-24T00:00:00+07:00 | H66: 5fa4df1f-2b28-4402-96dc-eb65e637ebf0 | I66: https://censorship.kplus.vn/MediaAssets/Asset/089e84fb-4af0-ee11-9144-f40270bf9ea7/StreamPreview | J66: YES | K66: Success
A67: MOV_ADV_22__2686513 | B67: Arctic | C67: Movies | D67: 2 | E67: 2018 | F67: 2022-12-08T00:00:00+07:00 | H67: 0bb30b57-9133-40d7-800a-319415635db2 | I67: https://censorship.kplus.vn/MediaAssets/Asset/060fe2bf-cbed-ee11-9144-f40270bf9ea7/StreamPreview | J67: YES | K67: Success
A68: MOV_ACT_24__2713785 | B68: The bravest | C68: Movies | D68: 2 | E68: 2019 | F68: 2024-03-05T00:00:00+07:00 | H68: c71c93a1-6d09-4288-a386-98bc7c9d8cb4 | I68: https://censorship.kplus.vn/MediaAssets/Asset/abc5582b-3df8-ee11-9144-f40270bf9ea7/StreamPreview | J68: YES | K68: Success
A69: MOV_ACT588 | B69: Ride Along 2 | C69: Movies | D69: 3 | E69: 2016 | F69: 2024-07-17T00:00:00+07:00 | H69: d10d2da7-1b5d-4056-996d-32589caa938d | I69: https://censorship.kplus.vn/MediaAssets/Asset/e63c2091-9788-ef11-8593-0c42a12723cb/StreamPreview | J69: YES | K69: Success
A70: MOV_COM_22__2686870 | B70: Love again | C70: Movies | D70: 3 | E70: 2019 | F70: 2022-12-15T00:00:00+07:00 | H70: 1678f8ff-bd0b-4e92-8d00-dc310f15e4f9 | I70: https://censorship.kplus.vn/MediaAssets/Asset/ee2e91b2-cced-ee11-9144-f40270bf9ea7/StreamPreview | J70: YES | K70: Success
A71: MOV_COM290 | B71: The Royal Bride | C71: Movies | D71: 3 | E71: 2020 | F71: 2024-12-11T00:00:00+07:00 | H71: f070a445-e563-427e-a25d-f36acc0302ef | I71: https://censorship.kplus.vn/MediaAssets/Asset/cd5e0583-71bf-ef11-8593-0c42a12723cb/StreamPreview | J71: YES | K71: Success
A72: MOV_COM_23__2697133 | B72: More than family | C72: Movies | D72: 3 | E72: 2020 | F72: 2023-05-12T00:00:00+07:00 | H72: ff87254e-a32c-4fad-a344-f1cf8e6efca2 | I72: https://censorship.kplus.vn/MediaAssets/Asset/edf5e806-6ef0-ee11-9144-f40270bf9ea7/StreamPreview | J72: YES | K72: Success
A73: MOV_ACT610 | B73: Good job | C73: Movies | D73: 3 | E73: 2023 | F73: 2025-03-19T00:00:00+07:00 | H73: cec9ab68-c716-4c5f-aefe-59d90b65cccb | I73: https://censorship.kplus.vn/MediaAssets/Asset/ffaff898-c415-f011-8593-0c42a12723cb/StreamPreview | J73: YES | K73: Success
A74: MOV_ACT_24__2714420 | B74: The Age of Blood | C74: Movies | D74: 3 | E74: 2017 | F74: 2024-03-15T00:00:00+07:00 | H74: 9c66f642-f344-4e09-a4ea-39d3a909aca3 | I74: https://censorship.kplus.vn/MediaAssets/Asset/a5bbd01c-4f01-ef11-9144-f40270bf9ea7/StreamPreview | J74: YES | K74: Success
A75: MOV_BIO_24__2713783 | B75: A Beautiful Day in the Neighborhood | C75: Movies | D75: 2 | E75: 2019 | F75: 2024-03-05T00:00:00+07:00 | H75: edb0cf65-3881-4096-8b68-5dd8459e3a8a | I75: https://censorship.kplus.vn/MediaAssets/Asset/1f66ab66-ef0d-ef11-9144-f40270bf9ea7/StreamPreview | J75: YES | K75: Success
A76: MOV_ACT576 | B76: Hanna | C76: Movies | D76: 3 | E76: 2011 | F76: 2024-06-19T00:00:00+07:00 | H76: 25430911-4471-4510-82ca-aae7360731fb | I76: https://censorship.kplus.vn/MediaAssets/Asset/640403e3-6c58-ef11-914a-f40270bf9ea7/StreamPreview | J76: YES | K76: Success
... A92: MOV_ACT593 | B92: Twilight of the Warriors: Walled In | C92: Movies | D92: 4 | E92: 2024 | F92: 2024-12-11T00:00:00+07:00 | H92: 2711eb79-2611-464e-9a98-179a5c6afd9b | I92: https://censorship.kplus.vn/MediaAssets/Asset/2fece511-5fb6-f011-8593-0c42a12723cb/StreamPreview | J92: YES | K92: Success
A93: MOV_FAN_LNVM__15__2467819 | B93: THE LOST DRAGON | C93: Movies | D93: 2 | F93: 2017-09-09T00:00:00+07:00 | H93: 2ef968d7-5467-4bfe-bd28-8614b5d174ee | I93: https://censorship.kplus.vn/MediaAssets/Asset/9e1b17fc-d37c-ef11-8593-0c42a12723cb/StreamPreview | J93: YES | K93: Success
A94: MOV_ACT_23__2695915 | B94: AVA (Eve) | C94: Movies | D94: 3 | E94: 2020 | F94: 2023-04-27T00:00:00+07:00 | H94: 9ab6bef3-c5a6-4dd1-81e8-f4adfe487714 | I94: https://censorship.kplus.vn/MediaAssets/Asset/79cf8027-70f0-ee11-9144-f40270bf9ea7/StreamPreview | J94: YES | K94: Success
A95: MOV_COM_23__2697132 | B95: Seven Sundays | C95: Movies | D95: 2 | E95: 2017 | F95: 2023-05-12T00:00:00+07:00 | H95: 138cc898-277f-4a2b-8320-ffa2f47fc165 | I95: https://censorship.kplus.vn/MediaAssets/Asset/71d37d0f-57f0-ee11-9144-f40270bf9ea7/StreamPreview | J95: YES | K95: Success
A96: MOV_ACT_24__2711608 | B96: Hypnotic | C96: Movies | D96: 4 | E96: 2023 | F96: 2024-01-24T00:00:00+07:00 | H96: de6d52f6-3d28-4941-88e4-c000b2a2ae43 | I96: https://censorship.kplus.vn/MediaAssets/Asset/3bbc123b-1e43-ef11-9145-f40270bf9ea7/StreamPreview | J96: YES | K96: Success
A97: MOV_COM_22__2686514 | B97: Bye Bye Morons | C97: Movies | D97: 2 | E97: 2020 | F97: 2022-12-08T00:00:00+07:00 | H97: 10246818-6f63-4b6f-ba52-a5b7eb094a23 | I97: https://censorship.kplus.vn/MediaAssets/Asset/47077827-d1ed-ee11-9144-f40270bf9ea7/StreamPreview | J97: YES | K97: Success
A98: MOV_DRA741 | B98: Blood Moon Party | C98: Movies | D98: 4 | E98: 2020 | F98: 2025-01-01T00:00:00+07:00 | H98: 9fd13652-1fd2-4cbe-b076-38da98160612 | I98: https://censorship.kplus.vn/MediaAssets/Asset/fe8e37f4-4ac7-ef11-8593-0c42a12723cb/StreamPreview | J98: YES | K98: Success
A99: MOV_THR168 | B99: Watcher | C99: Movies | D99: 3 | E99: 2022 | F99: 2025-04-09T00:00:00+07:00 | H99: 1532c171-aba4-47bf-a7f4-af637fb54a76 | I99: https://censorship.kplus.vn/MediaAssets/Asset/d6e9ed2a-b021-f011-8593-0c42a12723cb/StreamPreview | J99: YES | K99: Success
A100: MOV_ANI87 | B100: SONIC THE HEDGEHOG 2 | C100: Movies | D100: 1 | E100: 2022 | F100: 2025-04-29T00:00:00+07:00 | H100: 6967569f-89fb-45b6-98f9-d4d1394574bd | I100: https://censorship.kplus.vn/MediaAssets/Asset/78c141b2-d036-f011-8593-0c42a12723cb/StreamPreview | J100: YES | K100: Success
A101: MOV_BIO_24__2715624 | B101: Get on up | C101: Movies | D101: 3 | E101: 2014 | F101: 2024-04-02T00:00:00+07:00 | H101: 93f7a5c2-5625-4ce5-926e-0aff01acff52 | I101: https://censorship.kplus.vn/MediaAssets/Asset/92a688d2-3a13-ef11-9144-f40270bf9ea7/StreamPreview | J101: YES | K101: Success
A102: MOV_ACT_24__2710435 | B102: The King's Daughter | C102: Movies | D102: 2 | E102: 2022 | F102: 2024-01-09T00:00:00+07:00 | H102: 838c3d6e-3ec6-4621-9b24-35916537001a | I102: https://censorship.kplus.vn/MediaAssets/Asset/3759c88d-2ef8-ee11-9144-f40270bf9ea7/StreamPreview | J102: YES | K102: Success
A103: MOV_FAN27 | B103: The Journey Of Flower | C103: Movies | D103: 2 | E103: 2024 | F103: 2025-04-02T00:00:00+07:00 | H103: b46e5f46-e328-4434-82af-6ae09321466d | I103: https://censorship.kplus.vn/MediaAssets/Asset/74287a46-f21f-f011-8593-0c42a12723cb/StreamPreview | J103: YES | K103: Success
A104: MOV_COM_21__2662692 | B104: Mother Gamer | C104: Movies | D104: 3 | E104: 2020 | F104: 2021-12-07T00:00:00+07:00 | H104: 753ce577-a1b1-40d1-b20b-67ab1f802870 | I104: https://censorship.kplus.vn/MediaAssets/Asset/b99881be-ede9-ee11-9144-f40270bf9ea7/StreamPreview | J104: YES | K104: Success
A105: MOV_SCI_23__2709731 | B105: Moonfall | C105: Movies | D105: 3 | E105: 2022 | F105: 2023-12-22T00:00:00+07:00 | H105: 5a19170e-a646-4da7-bf46-be91fa1236f4 | I105: https://censorship.kplus.vn/MediaAssets/Asset/aff6ce78-2af1-ee11-9144-f40270bf9ea7/StreamPreview | J105: YES | K105: Success
... A160: MOV_ROM101 | B160: Waiting for Rain | C160: Movies | D160: 1 | E160: 2021 | F160: 2024-12-28T00:00:00+07:00 | H160: d99eaa76-defa-4ca0-8eb0-cdf237bb130f | I160: https://censorship.kplus.vn/MediaAssets/Asset/ce8f0da6-78e4-ef11-8593-0c42a12723cb/StreamPreview | J160: YES | K160: Success
A161: MOV_COM_22__2686868 | B161: 16589 | C161: Movies | D161: 2 | E161: 2022 | F161: 2022-12-15T00:00:00+07:00 | H161: 85f9956c-e998-4170-89fe-63403bb648e5 | I161: https://censorship.kplus.vn/MediaAssets/Asset/84fca436-ceed-ee11-9144-f40270bf9ea7/StreamPreview | J161: YES | K161: Success
A162: MOV_THR_24__2711445 | B162: Livestream | C162: Movies | D162: 3 | E162: 2023 | F162: 2024-01-22T00:00:00+07:00 | H162: a4e6c559-06df-4907-a21a-457885d12fae | I162: https://censorship.kplus.vn/MediaAssets/Asset/cec8f151-24f8-ee11-9144-f40270bf9ea7/StreamPreview | J162: YES | K162: Success
A163: MOV_ACT603 | B163: Brotherhood | C163: Movies | D163: 3 | E163: 2022 | F163: 2025-02-13T00:00:00+07:00 | H163: dc6a577a-84a0-4654-928b-1b40f3766d68 | I163: https://censorship.kplus.vn/MediaAssets/Asset/b2c83e75-1311-f011-8593-0c42a12723cb/StreamPreview | J163: YES | K163: Success
A164: MOV_CRI_22__2668483 | B164: Hand Rolled Cigarette | C164: Movies | D164: 3 | E164: 2020 | F164: 2022-02-23T00:00:00+07:00 | H164: da9308c6-7ae2-48a5-bd94-ffa661d4d9db | I164: https://censorship.kplus.vn/MediaAssets/Asset/8ae0af79-f3eb-ee11-9144-f40270bf9ea7/StreamPreview | J164: YES | K164: Success
A165: MOV_ACT586 | B165: In A Valley Of Violence | C165: Movies | D165: 3 | E165: 2016 | F165: 2024-07-09T00:00:00+07:00 | H165: c344b26e-74a7-4fd9-831d-014cde723326 | I165: https://censorship.kplus.vn/MediaAssets/Asset/7103d253-5559-ef11-914a-f40270bf9ea7/StreamPreview | J165: YES | K165: Success
A166: MOV_CRI_24__2710430 | B166: Calm With Horses | C166: Movies | D166: 4 | E166: 2019 | F166: 2024-01-09T00:00:00+07:00 | H166: e43a8a5d-5a7a-4ff2-9bf1-2b26156934f5 | I166: https://censorship.kplus.vn/MediaAssets/Asset/8b6cd0a5-3df8-ee11-9144-f40270bf9ea7/StreamPreview | J166: YES | K166: Success
A167: MOV_ROM_21__2652260 | B167: WHAT WE FORGOT TO REMEMBER | C167: Movies | D167: 3 | E167: 2020 | F167: 2021-07-13T00:00:00+07:00 | H167: 5ba8242b-fdb4-4935-acea-d9ad671e6250 | I167: https://censorship.kplus.vn/MediaAssets/Asset/4c851aac-19ea-ee11-9144-f40270bf9ea7/StreamPreview | J167: YES | K167: Success
A168: MOV_COM292 | B168: Bad Moms | C168: Movies | D168: 3 | E168: 2016 | F168: 2024-12-28T00:00:00+07:00 | H168: a86161d4-563d-4cc5-98e8-d84a87a2e33b | I168: https://censorship.kplus.vn/MediaAssets/Asset/fea9042a-2afb-ef11-8593-0c42a12723cb/StreamPreview | J168: YES | K168: Success
A169: MOV_DRA757 | B169: In Our Prime | C169: Movies | D169: 3 | E169: 2022 | F169: 2025-04-05T00:00:00+07:00 | H169: 7e32c061-7a13-4ce4-a2a5-aed0ea3c5ebc | I169: https://censorship.kplus.vn/MediaAssets/Asset/c7ba7280-b130-f011-8593-0c42a12723cb/StreamPreview | J169: YES | K169: Success
A170: MOV_ACT596 | B170: The Desperate Chase | C170: Movies | D170: 3 | E170: 2024 | F170: 2024-12-21T00:00:00+07:00 | H170: e9911e91-058b-4af8-bcd7-4c901f5ba656 | I170: https://censorship.kplus.vn/MediaAssets/Asset/fd75f156-8cc9-ef11-8593-0c42a12723cb/StreamPreview | J170: YES | K170: Success
A171: MOV_CRI109 | B171: Revival | C171: Movies | D171: 3 | E171: 2023 | F171: 2025-02-05T00:00:00+07:00 | H171: 6bdb1942-fc99-4d9a-b9b9-ef1d3fc2a194 | I171: https://censorship.kplus.vn/MediaAssets/Asset/206c7f21-6034-f011-8593-0c42a12723cb/StreamPreview | J171: YES | K171: Success
A172: MOV_ACT606 | B172: Hijack 1971 | C172: Movies | D172: 3 | F172: 2025-02-19T00:00:00+07:00 | H172: 18e2c918-d9bc-40c2-a4bd-506864965ddd | I172: https://censorship.kplus.vn/MediaAssets/Asset/33130919-ec02-f011-8593-0c42a12723cb/StreamPreview | J172: YES | K172: Success
A173: MOV_ROM97 | B173: The Ex-Files 4: Marriage Plan | C173: Movies | D173: 1 | E173: 2023 | F173: 2024-12-11T00:00:00+07:00 | H173: 6f39de3c-86c3-423f-acfc-9b5f3e445061 | I173: https://censorship.kplus.vn/MediaAssets/Asset/19d20ce4-cd36-f011-8593-0c42a12723cb/StreamPreview | J173: YES | K173: Success
A174: MOV_ACT_23__2710032 | B174: Ransomed | C174: Movies | D174: 3 | E174: 2023 | F174: 2023-12-28T00:00:00+07:00 | H174: a102fbe0-afda-418a-96c7-543868c92cb5 | I174: https://censorship.kplus.vn/MediaAssets/Asset/d1da8c6d-30f1-ee11-9144-f40270bf9ea7/StreamPreview | J174: YES | K174: Success
A175: MOV_BIO_24__2713781 | B175: The best of enemies | C175: Movies | D175: 3 | E175: 2019 | F175: 2024-03-05T00:00:00+07:00 | H175: 793242bc-494c-435d-9c65-6f2c18a2cb7e | I175: https://censorship.kplus.vn/MediaAssets/Asset/d4ba7560-4608-ef11-9144-f40270bf9ea7/StreamPreview | J175: YES | K175: Success
A176: MOV_DRA728 | B176: The Billionaire | C176: Movies | D176: 1 | E176: 2011 | F176: 2024-08-20T00:00:00+07:00 | H176: 41dbc1e9-17a0-487c-bfc5-6d1859bbdf7f | I176: https://censorship.kplus.vn/MediaAssets/Asset/cd135931-175e-ef11-8593-0c42a12723cb/StreamPreview | J176: YES | K176: Success
A177: MOV_ADV52 | B177: Everest | C177: Movies | D177: 1 | E177: 2015 | F177: 2024-09-19T00:00:00+07:00 | H177: 6b76e1b0-9aba-47c8-bf47-4daedfd3462a | I177: https://censorship.kplus.vn/MediaAssets/Asset/4c69e56e-ecb5-ef11-8593-0c42a12723cb/StreamPreview | J177: YES | K177: Success
A178: MOV_DRA744 | B178: Mrs. Harris goes to Paris | C178: Movies | D178: 1 | E178: 2022 | F178: 2025-01-03T00:00:00+07:00 | H178: 37ea9615-3fee-470f-b0df-802ed9f8b311 | I178: https://censorship.kplus.vn/MediaAssets/Asset/a76b7ecf-c5ea-ef11-8593-0c42a12723cb/StreamPreview | J178: YES | K178: Success
A179: MOV_ACT_21__2648728 | B179: LIBRARY WARS: THE LAST MISSION | C179: Movies | D179: 3 | F179: 2021-04-23T00:00:00+07:00 | H179: 03b31232-2ba8-4abd-90c6-dd4fbd47fc72 | I179: https://censorship.kplus.vn/MediaAssets/Asset/323370b4-40f8-ee11-9144-f40270bf9ea7/StreamPreview | J179: YES | K179: Success
A180: MOV_CRI_24__2711294 | B180: Devils | C180: Movies | D180: 4 | E180: 2023 | F180: 2024-01-18T00:00:00+07:00 | H180: 0bbc0d61-d2eb-4ee4-ab84-a62a7cdeac8b | I180: https://censorship.kplus.vn/MediaAssets/Asset/a83878de-25f8-ee11-9144-f40270bf9ea7/StreamPreview | J180: YES | K180: Success
A181: MOV_CRI108 | B181: Everybody Knows | C181: Movies | D181: 3 | E181: 2018 | F181: 2024-12-11T00:00:00+07:00 | H181: 50064e6b-dafb-4aba-a9f7-0feb5c315a24 | I181: https://censorship.kplus.vn/MediaAssets/Asset/b4bc198c-eacc-ef11-8593-0c42a12723cb/StreamPreview | J181: YES | K181: Success
A182: MOV_ROM98 | B182: Single in Seoul | C182: Movies | D182: 3 | E182: 2023 | F182: 2024-12-11T00:00:00+07:00 | H182: 9634a0de-81f6-4f83-a085-9854e2eb8c5c | I182: https://censorship.kplus.vn/MediaAssets/Asset/5222b54c-01d7-ef11-8593-0c42a12723cb/StreamPreview | J182: YES | K182: Success
A183: MOV_DRA737 | B183: Better man | C183: Movies | D183: 5 | E183: 2022 | F183: 2024-12-19T00:00:00+07:00 | H183: ceae8bb0-c996-4fb4-bfa7-92de1bba14c0 | I183: https://censorship.kplus.vn/MediaAssets/Asset/a4a3ef10-95d1-ef11-8593-0c42a12723cb/StreamPreview | J183: YES | K183: Success
A184: MOV_ACT_23__2691046 | B184: SKYLIN3S | C184: Movies | D184: 3 | E184: 2020 | F184: 2023-02-23T00:00:00+07:00 | H184: a9eee5e1-6db2-476c-829c-539d1b155fd0 | I184: https://censorship.kplus.vn/MediaAssets/Asset/c2de4724-edef-ee11-9144-f40270bf9ea7/StreamPreview | J184: YES | K184: Success
A185: MOV_DRA_18__2558894 | B185: THE TAILOR | C185: Movies | D185: 1 | E185: 2017 | F185: 2018-07-14T00:00:00+07:00 | H185: 06364595-a7ef-4668-bb55-31c9fa76fc4e | I185: https://censorship.kplus.vn/MediaAssets/Asset/a038abe0-a3b0-ef11-8593-0c42a12723cb/StreamPreview | J185: YES | K185: Success
A186: MOV_ACT604 | B186: 12 hours | C186: Movies | D186: 3 | E186: 2022 | F186: 2025-02-13T00:00:00+07:00 | H186: c2b8effa-94f5-481a-ad86-736c4bb1522d | I186: https://censorship.kplus.vn/MediaAssets/Asset/c86b7a67-31fb-ef11-8593-0c42a12723cb/StreamPreview | J186: YES | K186: Success
A187: MOV_CRI113 | B187: Suspect | C187: Movies | D187: 3 | E187: 2024 | F187: 2025-04-24T00:00:00+07:00 | H187: ae115b90-5021-4dc3-9de4-0e61bebe31cd | I187: https://censorship.kplus.vn/MediaAssets/Asset/10f0f87d-f93a-f011-8593-0c42a12723cb/StreamPreview | J187: YES | K187: Success
A188: MOV_SCI_23__2689053 | B188: Arrival | C188: Movies | D188: 2 | E188: 2016 | F188: 2023-01-19T00:00:00+07:00 | H188: eab9f5db-b2b8-4e01-9405-32627af10c74 | I188: https://censorship.kplus.vn/MediaAssets/Asset/1a43555a-bee9-ef11-8593-0c42a12723cb/StreamPreview | J188: YES | K188: Success
A189: MOV_BIO26 | B189: Whitney Houston: I Wanna Dance with Somebody | C189: Movies | D189: 3 | E189: 2022 | F189: 2025-02-26T00:00:00+07:00 | H189: 3bdd1f79-8d21-412d-91f8-4b11b4339cbc | I189: https://censorship.kplus.vn/MediaAssets/Asset/c9ff5d38-3409-f011-8593-0c42a12723cb/StreamPreview | J189: YES | K189: Success
A190: MOV_CRI_21__2650084 | B190: THE CRIMES THAT BIND | C190: Movies | D190: 2 | E190: 2018 | F190: 2021-05-17T00:00:00+07:00 | H190: b3018c4b-6116-4605-9e04-a17bc5cdb512 | I190: https://censorship.kplus.vn/MediaAssets/Asset/e2075f78-48f6-ee11-9144-f40270bf9ea7/StreamPreview | J190: YES | K190: Success
A191: MOV_ACT583 | B191: Upgrade | C191: Movies | D191: 4 | E191: 2018 | F191: 2024-07-09T00:00:00+07:00 | H191: cf863ae4-d2fa-4606-9153-76c2ea99044d | I191: https://censorship.kplus.vn/MediaAssets/Asset/2f1a92ed-3e4b-ef11-914a-f40270bf9ea7/StreamPreview | J191: YES | K191: Success
... A207: MOV_ANI_24__2711444 | B207: Moonbound | C207: Movies | D207: 1 | E207: 2021 | F207: 2024-01-22T00:00:00+07:00 | H207: 465fd68e-36cb-4203-b3ec-8f1dadf1941a | I207: https://censorship.kplus.vn/MediaAssets/Asset/79428666-28f8-ee11-9144-f40270bf9ea7/StreamPreview | J207: YES | K207: Success
A208: MOV_DRA_LNVM__15__2471197 | B208: FAREWELL BERLIN WALL | C208: Movies | D208: 3 | F208: 2016-10-14T00:00:00+07:00 | H208: cfa848c9-a43b-4fed-a21b-4f12096ac383 | I208: https://censorship.kplus.vn/MediaAssets/Asset/ef607b27-d67c-ef11-8593-0c42a12723cb/StreamPreview | J208: YES | K208: Success
A209: MOV_COM_19__2614753 | B209: BUTTERFLY HOUSE | C209: Movies | D209: 3 | E209: 2019 | F209: 2019-10-23T00:00:00+07:00 | H209: ef3e2c89-bb6e-4fe1-a2a3-ab6256defb08 | I209: https://censorship.kplus.vn/MediaAssets/Asset/04905413-5de8-ee11-9144-f40270bf9ea7/StreamPreview | J209: YES | K209: Success
A210: MOV_BIO22 | B210: Moneyball | C210: Movies | D210: 2 | E210: 2011 | F210: 2024-06-19T00:00:00+07:00 | H210: d1cae900-f428-4f7d-a23b-1fe0b54c42f7 | I210: https://censorship.kplus.vn/MediaAssets/Asset/0d0e6504-746e-ef11-8593-0c42a12723cb/StreamPreview | J210: YES | K210: Success
A211: MOV_DRA742 | B211: Gyul-Baek | C211: Movies | D211: 3 | E211: 2020 | F211: 2025-01-03T00:00:00+07:00 | H211: b2d507c5-bbb7-4f76-8f06-23506265f58c | I211: https://censorship.kplus.vn/MediaAssets/Asset/d3ffa582-d2e9-ef11-8593-0c42a12723cb/StreamPreview | J211: YES | K211: Success
A212: MOV_THR_21__2644512 | B212: THE INSTRUMENT OF MURDER | C212: Movies | D212: 4 | E212: 2020 | F212: 2021-02-05T00:00:00+07:00 | H212: 958e2583-21a3-478e-8f9e-3ea2dc9e742c | I212: https://censorship.kplus.vn/MediaAssets/Asset/7a5500be-a4ea-ee11-9144-f40270bf9ea7/StreamPreview | J212: YES | K212: Success
A213: MOV_DRA729 | B213: Downton Abbey: A New Era | C213: Movies | D213: 5 | E213: 2021 | F213: 2024-09-19T00:00:00+07:00 | H213: 77e15b3b-a928-43ff-8298-59cae26e8931 | I213: https://censorship.kplus.vn/MediaAssets/Asset/6d4f6d16-4ebc-ef11-8593-0c42a12723cb/StreamPreview | J213: YES | K213: Success
A214: MOV_ACT_24__2710440 | B214: The White Storm 3: Heaven Or Hell | C214: Movies | D214: 4 | E214: 2023 | F214: 2024-01-09T00:00:00+07:00 | H214: 261143d4-c372-4912-821a-0ce8b4baabcd | I214: https://censorship.kplus.vn/MediaAssets/Asset/39ffbd93-0af8-ee11-9144-f40270bf9ea7/StreamPreview | J214: YES | K214: Success
A215: MOV_ACT602 | B215: The Plot | C215: Movies | D215: 3 | E215: 2024 | F215: 2025-02-12T00:00:00+07:00 | H215: 36114f34-2b97-4bd5-a638-698bda3dd5c2 | I215: https://censorship.kplus.vn/MediaAssets/Asset/53734cf4-ccf5-ef11-8593-0c42a12723cb/StreamPreview | J215: YES | K215: Success
A216: MOV_ACT577 | B216: Miss Bala | C216: Movies | D216: 3 | E216: 2019 | F216: 2024-06-19T00:00:00+07:00 | H216: f7849b81-73ac-42c4-87bf-a97d7e26b3a0 | I216: https://censorship.kplus.vn/MediaAssets/Asset/67492056-1a65-ef11-8593-0c42a12723cb/StreamPreview | J216: YES | K216: Success
A217: MOV_ACT_LNVM__16__2486863 | B217: BITCOIN HEIST | C217: Movies | D217: 3 | E217: 2016 | F217: 2018-07-28T00:00:00+07:00 | H217: 4b833cde-a18b-40c8-800d-8f91732310b0 | I217: https://censorship.kplus.vn/MediaAssets/Asset/f9eb6dff-ff7e-ef11-8593-0c42a12723cb/StreamPreview | J217: YES | K217: Success
A218: MOV_COM_24__2714425 | B218: Death at a funeral | C218: Movies | D218: 3 | E218: 2010 | F218: 2024-03-15T00:00:00+07:00 | H218: a34c871e-af5a-4c14-87ff-df7fa527fa36 | I218: https://censorship.kplus.vn/MediaAssets/Asset/a94b67c0-3b4f-ef11-914a-f40270bf9ea7/StreamPreview | J218: YES | K218: Success
A219: MOV_HOR_24__2716635 | B219: Last Night in Soho | C219: Movies | D219: 3 | E219: 2021 | F219: 2024-04-23T00:00:00+07:00 | H219: d4a2cd97-9c89-430f-b878-9f17b2072a86 | I219: https://censorship.kplus.vn/MediaAssets/Asset/884bbfca-5616-ef11-9144-f40270bf9ea7/StreamPreview | J219: YES | K219: Success
A220: MOV_ANI_23__2695078 | B220: Ainbo | C220: Movies | D220: 1 | E220: 2021 | F220: 2023-04-20T00:00:00+07:00 | H220: c5229b12-38ca-4779-b55b-021e031fb0db | I220: https://censorship.kplus.vn/MediaAssets/Asset/0cc11a5d-6ef0-ee11-9144-f40270bf9ea7/StreamPreview | J220: YES | K220: Success
... A238: MOV_CRI_24__2714939 | B238: Detective Vs. Sleuths | C238: Movies | D238: 3 | E238: 2022 | F238: 2024-03-26T00:00:00+07:00 | H238: 9f99e4e6-8edb-47d3-866b-923943c59b4a | I238: https://censorship.kplus.vn/MediaAssets/Asset/68764632-5d13-ef11-9144-f40270bf9ea7/StreamPreview | J238: YES | K238: Success
A239: MOV_COM289 | B239: Miss Fortune | C239: Movies | D239: 2 | F239: 2024-12-11T00:00:00+07:00 | H239: 333edc5a-85ea-4761-87d5-0bc5f9b9bcbf | I239: https://censorship.kplus.vn/MediaAssets/Asset/382f0fe5-6afd-ef11-8593-0c42a12723cb/StreamPreview | J239: YES | K239: Success
A240: MOV_FAN__16__2492574 | B240: TAM CAM: THE UNTOLD STORY | C240: Movies | D240: 1 | E240: 2016 | F240: 2018-04-21T00:00:00+07:00 | H240: d75f0469-e8cc-4e8b-98f5-79c07696422f | I240: https://censorship.kplus.vn/MediaAssets/Asset/c4464389-15d3-ef11-8593-0c42a12723cb/StreamPreview | J240: YES | K240: Success
A241: MOV_ACT_23__2689674 | B241: 7 days in Entebbe | C241: Movies | D241: 2 | E241: 2017 | F241: 2023-02-02T00:00:00+07:00 | H241: 76ed25f0-a936-44d7-b4c0-ff55a3feed79 | I241: https://censorship.kplus.vn/MediaAssets/Asset/a9237b43-edef-ee11-9144-f40270bf9ea7/StreamPreview | J241: YES | K241: Success
A242: MOV_ACT_23__2691049 | B242: Horizon Line | C242: Movies | D242: 3 | E242: 2020 | F242: 2023-02-23T00:00:00+07:00 | H242: b70ab95e-ed0f-4f6a-bd51-67aa2185ece2 | I242: https://censorship.kplus.vn/MediaAssets/Asset/84eda8f6-bbf4-ee11-9144-f40270bf9ea7/StreamPreview | J242: YES | K242: Success
A243: MOV_ACT607 | B243: Battle Los Angeles | C243: Movies | D243: 2 | E243: 2011 | F243: 2025-02-26T00:00:00+07:00 | H243: 82993f56-abae-42ce-82ba-e7d51b359793 | I243: https://censorship.kplus.vn/MediaAssets/Asset/a07c9fe0-0419-f011-8593-0c42a12723cb/StreamPreview | J243: YES | K243: Success
A244: MOV_CRI114 | B244: Hovering Blade | C244: Movies | D244: 3 | E244: 2024 | F244: 2025-04-24T00:00:00+07:00 | H244: 0e5a226d-464c-4dd9-9187-9bc94e206b2d | I244: https://censorship.kplus.vn/MediaAssets/Asset/cf965b7b-1342-f011-8593-0c42a12723cb/StreamPreview | J244: YES | K244: Success
A245: MOV_COM__2686867 | B245: FAMILY SWAP | C245: Movies | D245: 3 | E245: 2021 | F245: 2022-12-15T00:00:00+07:00 | H245: e71aec97-b02d-4345-a987-03bbc48920e2 | I245: https://censorship.kplus.vn/MediaAssets/Asset/71e623e3-d5ed-ee11-9144-f40270bf9ea7/StreamPreview | J245: YES | K245: Success
A246: MOV_MUS8 | B246: Cats | C246: Movies | D246: 1 | E246: 2019 | F246: 2024-07-17T00:00:00+07:00 | H246: 43682661-84e6-4fda-b00a-20feecac1848 | I246: https://censorship.kplus.vn/MediaAssets/Asset/76ef5597-8c9d-ef11-8593-0c42a12723cb/StreamPreview | J246: YES | K246: Success
A247: MOV_DRA_22__2686502 | B247: The Upside | C247: Movies | D247: 3 | E247: 2017 | F247: 2022-12-08T00:00:00+07:00 | H247: a0675418-78d7-4cdd-85d2-6b9e14192c0c | I247: https://censorship.kplus.vn/MediaAssets/Asset/03de7fd9-c9ed-ee11-9144-f40270bf9ea7/StreamPreview | J247: YES | K247: Success
A248: MOV_HIS10 | B248: Black '47 | C248: Movies | D248: 3 | E248: 2018 | F248: 2024-12-11T00:00:00+07:00 | H248: 5178fb45-6f8b-4947-a437-8cbc6016a5ee | I248: https://censorship.kplus.vn/MediaAssets/Asset/39f7fab2-65d1-ef11-8593-0c42a12723cb/StreamPreview | J248: YES | K248: Success
A249: MOV_DRA_24__2713877 | B249: The Fabelmans | C249: Movies | D249: 2 | E249: 2022 | F249: 2024-03-07T00:00:00+07:00 | H249: 41b96d1a-ab61-4e94-a12f-81cf9a6e0a14 | I249: https://censorship.kplus.vn/MediaAssets/Asset/a905b669-83a8-ef11-8593-0c42a12723cb/StreamPreview | J249: YES | K249: Success
A250: MOV_ANI86 | B250: PAW PATROL: THE MOVIE | C250: Movies | D250: 1 | E250: 2021 | F250: 2025-04-29T00:00:00+07:00 | H250: c06ca263-ae4c-426d-9dea-729e0c412db0 | I250: https://censorship.kplus.vn/MediaAssets/Asset/f15564ac-8334-f011-8593-0c42a12723cb/StreamPreview | J250: YES | K250: Success
...

Sheet KK1. Movies
A1: CÔNG TY: | C1: Công ty TNHH Truyền hình số vệ tinh Việt Nam | AO1: Cộng Hòa Xã Hội Chủ Nghĩa Việt Nam
AO2: Độc Lập - Tự Do - Hạnh Phúc
A3: BÁO CÁO KIỂM KÊ BẢN QUYỀN MOVIES
A4: Thời điểm:….......giờ, ngày…....tháng.........năm 2026
AD5: Lưu trữ | AI5: Ref File Kế toán | AN5: Check | AO5: SỐ LIỆU KIỂM KÊ | AR5: Giải trình chênh lệch | AS5: Đề xuất Phương án xử lý
A6: STT | B6: Content Rating | C6: Clip Code | D6: ENGLISH Title | E6: VIET Title | F6: Main Genre | G6: Provider | H6: Contract number | I6: Year of Production | J6: Origin | K6: Duration (minute) | L6: From (DTH) | M6: To (DTH) | N6: VSTV's 1st airing date | O6: Channel | P6: Exclusive (month) | Q6: Sub-license | R6: OTT rights | S6: Catch-up | T6: SVOD | U6: FVOD | V6: AVOD | W6: TVOD | X6: Internet Streaming | Y6: Internet Downloading | Z6: From (VOD) | AA6: To (VOD) | AB6: Runs No. | AC6: Broadcasted runs | AD6: HD Censorship | AE6: LTO | AF6: Drive ( ổ cứng) | AG6: Note | AI6: Tên trên file Kế toán | AJ6: details kế toán | AK6: Giá trị còn lại (15661) | AL6: Check ref "TK 242.BQ Phim hợp tác" | AM6: Check ref "TK 15661. Bản quyền phim" | AO6: Số lượng | AP6: From (VOD) | AQ6: To (VOD) | AR6: Giải trình chênh lệch | AS6: Đề xuất Phương án xử lý | AT6: Kết quả tìm
A7: =_xlfn.AGGREGATE(3,3,$D$7:D7) | B7: 13+ | C7: MOV_DRA730 | D7: SHINING FOR ONE THING | E7: Ngôi Sao Lấp Lánh | F7: Thriller, Mystery, Romance, Fantasy | G7: Skyline Media | H7: 36/2025/HDBQ/VSTV-SM | I7: 2023 | J7: China | K7: 107 | L7: 45674 | M7: 47169 | N7: 45674 | P7: 12 | Q7: No | R7: Yes | S7: Yes | T7: Yes | U7: Yes | V7: Yes | W7: Yes | X7: Yes | Y7: No | Z7: 45674 | AA7: 47169 | AB7: 24 | AC7: 3 | AD7: Yes | AE7: Yes | AG7: Phim còn hạn từ 2026 | AI7: SHINING FOR ONE THING | AJ7: =SUMIF('TK 15661.Bản quyền phim '!F:F,'KK1. Movies'!D7,'TK 15661.Bản quyền phim '!X:X) | AK7: =SUMIF('TK 15661.Bản quyền phim '!F:F,'KK1. Movies'!AI7,'TK 15661.Bản quyền phim '!X:X) | AL7: =COUNTIF('242.BQ Phim hợp tác'!$C:$C,'KK1. Movies'!AI7) | AM7: =COUNTIF('TK 15661.Bản quyền phim '!F:F,'KK1. Movies'!AI7) | AN7: =AL7+AM7 | AT7: =IFERROR(VLOOKUP(C7, CodeRanMovies!$A:$K, 11, 0), "Not found")
A8: =_xlfn.AGGREGATE(3,3,$D$7:D8) | B8: 16+ | C8: MOV_ACT_23__2691047 | D8: ROGUE | E8: Biệt đội săn mồi | F8: Action, Adventure | G8: Roses Media | H8: 140/2022/HDBQ/VSTV-RM | I8: 2020 | J8: US | K8: 105 | L8: 45077 | M8: 46172 | N8: 45077 | O8: K+CINE | P8: Exclusive All Pay TV Rights for first 12 months. Non exclusive All VOD during LP | Q8: No | R8: Yes | S8: No | T8: Yes | U8: Yes | V8: Yes | W8: Yes | X8: Yes | Y8: No | Z8: 45077 | AA8: 46172 | AB8: 24 | AC8: 14 | AD8: Yes | AE8: Yes | AG8: Phim còn hạn từ 2026 | AI8: ROGUE HEROS | AJ8: =SUMIF('TK 15661.Bản quyền phim '!F:F,'KK1. Movies'!D8,'TK 15661.Bản quyền phim '!X:X) | AK8: =SUMIF('TK 15661.Bản quyền phim '!F:F,'KK1. Movies'!AI8,'TK 15661.Bản quyền phim '!X:X) | AL8: =COUNTIF('242.BQ Phim hợp tác'!$C:$C,'KK1. Movies'!AI8) | AM8: =COUNTIF('TK 15661.Bản quyền phim '!F:F,'KK1. Movies'!AI8) | AN8: =AL8+AM8 | AT8: =IFERROR(VLOOKUP(C8, CodeRanMovies!$A:$K, 11, 0), "Not found")
A9: =_xlfn.AGGREGATE(3,3,$D$7:D9) | B9: 16+ | C9: MOV_ACT_22__2687284 | D9: Escape Plan 2: Hades | E9: Kế hoạch đào tẩu 2: Địa ngục | F9: Crime, Thriller | G9: Roses Media | H9: 140/2022/HDBQ/VSTV-RM | I9: 2018 | J9: US | K9: 96 | L9: 44967 | M9: 46062 | N9: 44967 | O9: K+CINE | P9: Exclusive All Pay TV Rights for first 12 months. Non exclusive All VOD during LP | Q9: No | R9: Yes | S9: No | T9: Yes | U9: Yes | V9: Yes | W9: Yes | X9: Yes | Y9: no | Z9: 44967 | AA9: 46062 | AB9: 24 | AC9: 22 | AD9: Yes | AE9: Yes | AG9: Phim còn hạn từ 2026 | AI9: Escape Plan 2: Hades | AJ9: =SUMIF('TK 15661.Bản quyền phim '!F:F,'KK1. Movies'!D9,'TK 15661.Bản quyền phim '!X:X) | AK9: =SUMIF('TK 15661.Bản quyền phim '!F:F,'KK1. Movies'!AI9,'TK 15661.Bản quyền phim '!X:X) | AL9: =COUNTIF('242.BQ Phim hợp tác'!$C:$C,'KK1. Movies'!AI9) | AM9: =COUNTIF('TK 15661.Bản quyền phim '!F:F,'KK1. Movies'!AI9) | AN9: =AL9+AM9 | AT9: =IFERROR(VLOOKUP(C9, CodeRanMovies!$A:$K, 11, 0), "Not found")
A10: =_xlfn.AGGREGATE(3,3,$D$7:D10) | B10: 16+ | C10: MOV_ACT_23__2693370 | D10: Riam: Fighting Angel | E10: Riam: Nữ quái nổi loạn | F10: Comedy | G10: Roses Media | H10: 140/2022/HDBQ/VSTV-RM | I10: 2020 | J10: Thailand | K10: 108 | L10: 45064 | M10: 46159 | N10: 45064 | O10: K+CINE | P10: Exclusive All Pay TV Rights for first 12 months. Non exclusive All VOD during LP | Q10: No | R10: Yes | S10: No | T10: Yes | U10: Yes | V10: Yes | W10: Yes | X10: Yes | Y10: No | Z10: 45064 | AA10: 46159 | AB10: 24 | AC10: 16 | AD10: Yes | AE10: Yes | AG10: Phim còn hạn từ 2026 | AI10: Riam: Fighting Angel | AJ10: =SUMIF('TK 15661.Bản quyền phim '!F:F,'KK1. Movies'!D10,'TK 15661.Bản quyền phim '!X:X) | AK10: =SUMIF('TK 15661.Bản quyền phim '!F:F,'KK1. Movies'!AI10,'TK 15661.Bản quyền phim '!X:X) | AL10: =COUNTIF('242.BQ Phim hợp tác'!$C:$C,'KK1. Movies'!AI10) | AM10: =COUNTIF('TK 15661.Bản quyền phim '!F:F,'KK1. Movies'!AI10) | AN10: =AL10+AM10 | AT10: =IFERROR(VLOOKUP(C10, CodeRanMovies!$A:$K, 11, 0), "Not found")
A11: =_xlfn.AGGREGATE(3,3,$D$7:D11) | B11: P | C11: MOV_ANI_23__2697127 | D11: Happy Family | E11: Gia đình là tất cả | F11: Comedy | G11: Roses Media | H11: 140/2022/HDBQ/VSTV-RM | I11: 2017 | J11: Germany | K11: 96 | L11: 45227 | M11: 46322 | N11: 45227 | O11: K+KIDS | Q11: No | R11: Yes | S11: No | T11: Yes | U11: Yes | V11: Yes | W11: Yes | X11: Yes | Y11: No | Z11: 45227 | AA11: 46322 | AB11: 24 | AC11: 16 | AD11: Yes | AE11: Yes | AG11: Phim còn hạn từ 2026 | AI11: Happy Family | AJ11: =SUMIF('TK 15661.Bản quyền phim '!F:F,'KK1. Movies'!D11,'TK 15661.Bản quyền phim '!X:X) | AK11: =SUMIF('TK 15661.Bản quyền phim '!F:F,'KK1. Movies'!AI11,'TK 15661.Bản quyền phim '!X:X) | AL11: =COUNTIF('242.BQ Phim hợp tác'!$C:$C,'KK1. Movies'!AI11) | AM11: =COUNTIF('TK 15661.Bản quyền phim '!F:F,'KK1. Movies'!AI11) | AN11: =AL11+AM11 | AT11: =IFERROR(VLOOKUP(C11, CodeRanMovies!$A:$K, 11, 0), "Not found")
A12: =_xlfn.AGGREGATE(3,3,$D$7:D12) | B12: 16+ | C12: MOV_DRA739 | D12: MEMOIRS OF A GEISHA | E12: Hồi ức của một Geisha | F12: Drama | G12: SONY | H12: Sony/K+Vietnam PayBasic SVOD Package Agmt D3A FE (Feb-5-24) | I12: 2005 | J12: U.S.A.[excluding Territories & Possessions] | K12: 145 | L12: 45701 | M12: 46430 | Q12: No | R12: Yes | S12: Yes | T12: Yes | U12: No | V12: No | W12: No | X12: Yes | Y12: No | Z12: 45701 | AA12: 46246 | AB12: 7 | AC12: 1 | AD12: Yes | AE12: Yes | AG12: Phim còn hạn từ 2026 | AI12: MEMOIRS OF A GEISHA | AJ12: =SUMIF('TK 15661.Bản quyền phim '!F:F,'KK1. Movies'!D12,'TK 15661.Bản quyền phim '!X:X) | AK12: =SUMIF('TK 15661.Bản quyền phim '!F:F,'KK1. Movies'!AI12,'TK 15661.Bản quyền phim '!X:X) | AL12: =COUNTIF('242.BQ Phim hợp tác'!$C:$C,'KK1. Movies'!AI12) | AM12: =COUNTIF('TK 15661.Bản quyền phim '!F:F,'KK1. Movies'!AI12) | AN12: =AL12+AM12 | AT12: =IFERROR(VLOOKUP(C12, CodeRanMovies!$A:$K, 11, 0), "Not found")
A13: =_xlfn.AGGREGATE(3,3,$D$7:D13) | B13: 16+ | C13: MOV_DRA_23__2695077 | D13: Ironbark/ The Courier | E13: Người đưa tin | F13: Crime, Thriller | G13: Roses Media | H13: 140/2022/HDBQ/VSTV-RM | I13: 2021 | J13: US | K13: 112 | L13: 45191 | M13: 46286 | N13: 45191 | O13: K+CINE | P13: Exclusive All Pay TV Rights for first 12 months. Non exclusive All VOD during LP | Q13: No | R13: Yes | S13: No | T13: Yes | U13: Yes | V13: Yes | W13: Yes | X13: Yes | Y13: Yes | Z13: 45191 | AA13: 46286 | AB13: 24 | AC13: 12 | AD13: Yes | AE13: Yes | AG13: Phim còn hạn từ 2026 | AI13: Ironbark/The Courier | AJ13: =SUMIF('TK 15661.Bản quyền phim '!F:F,'KK1. Movies'!D13,'TK 15661.Bản quyền phim '!X:X) | AK13: =SUMIF('TK 15661.Bản quyền phim '!F:F,'KK1. Movies'!AI13,'TK 15661.Bản quyền phim '!X:X) | AL13: =COUNTIF('242.BQ Phim hợp tác'!$C:$C,'KK1. Movies'!AI13) | AM13: =COUNTIF('TK 15661.Bản quyền phim '!F:F,'KK1. Movies'!AI13) | AN13: =AL13+AM13 | AT13: =IFERROR(VLOOKUP(C13, CodeRanMovies!$A:$K, 11, 0), "Not found")
A14: =_xlfn.AGGREGATE(3,3,$D$7:D14) | B14: 16+ | C14: MOV_ACT_22__2686885 | D14: Hitman's Wife's Bodyguard | E14: Vệ sĩ sát thủ 2: Nhà có nóc | F14: Action, Adventure | G14: Roses Media | H14: 140/2022/HDBQ/VSTV-RM | I14: 2021 | J14: US | K14: 89 | L14: 44951 | M14: 46046 | N14: 44951 | O14: K+CINE | P14: Exclusive All Pay TV Rights for first 12 months. Non exclusive All VOD during LP | Q14: No | R14: Yes | S14: Yes | T14: Yes | U14: Yes | V14: Yes | W14: Yes | X14: Yes | Y14: no | Z14: 44951 | AA14: 46046 | AB14: 24 | AC14: 13 | AD14: Yes | AE14: Yes | AG14: Phim còn hạn từ 2026 | AI14: Hitman's Wife's Bodyguard | AJ14: =SUMIF('TK 15661.Bản quyền phim '!F:F,'KK1. Movies'!D14,'TK 15661.Bản quyền phim '!X:X) | AK14: =SUMIF('TK 15661.Bản quyền phim '!F:F,'KK1. Movies'!AI14,'TK 15661.Bản quyền phim '!X:X) | AL14: =COUNTIF('242.BQ Phim hợp tác'!$C:$C,'KK1. Movies'!AI14) | AM14: =COUNTIF('TK 15661.Bản quyền phim '!F:F,'KK1. Movies'!AI14) | AN14: =AL14+AM14 | AT14: =IFERROR(VLOOKUP(C14, CodeRanMovies!$A:$K, 11, 0), "Not found")
A15: =_xlfn.AGGREGATE(3,3,$D$7:D15) | B15: 16+ | C15: MOV_HOR_24__2713435 | D15: GUIMOON: THE LIGHTLESS DOOR | E15: CỔNG ĐỊA NGỤC | F15: Horror | G15: CJ HK | H15: 180/2024/HDBQ/VSTV-CJHK | I15: 2021 | J15: Korea | K15: 85 | L15: 45566 | M15: 46660 | N15: 45568 | O15: K+ACTION | P15: 12 | Q15: No | R15: Yes | S15: Yes | T15: Yes | U15: Yes | V15: Yes | W15: Yes | X15: No | Y15: Yes | Z15: 45566 | AA15: 46660 | AB15: Unlimited | AC15: 11 | AD15: Yes | AE15: Yes | AG15: Phim còn hạn từ 2026 | AI15: GUIMOON: THE LIGHTLESS DOOR (CỔNG ĐỊA NGỤC) | AJ15: =SUMIF('TK 15661.Bản quyền phim '!F:F,'KK1. Movies'!D15,'TK 15661.Bản quyền phim '!X:X) | AK15: =SUMIF('TK 15661.Bản quyền phim '!F:F,'KK1. Movies'!AI15,'TK 15661.Bản quyền phim '!X:X) | AL15: =COUNTIF('242.BQ Phim hợp tác'!$C:$C,'KK1. Movies'!AI15) | AM15: =COUNTIF('TK 15661.Bản quyền phim '!F:F,'KK1. Movies'!AI15) | AN15: =AL15+AM15 | AT15: =IFERROR(VLOOKUP(C15, CodeRanMovies!$A:$K, 11, 0), "Not found")
A16: =_xlfn.AGGREGATE(3,3,$D$7:D16) | B16: 16+ | C16: MOV_DRA_23__2696593 | D16: Greta | E16: Góa phụ Greta | F16: Crime, Thriller | G16: Roses Media | H16: 140/2022/HDBQ/VSTV-RM | I16: 2018 | J16: US | K16: 98 | L16: 45217 | M16: 46312 | N16: 45217 | O16: K+CINE | P16: Exclusive All Pay TV Rights for first 12 months. Non exclusive All VOD during LP | Q16: No | R16: Yes | S16: No | T16: Yes | U16: Yes | V16: Yes | W16: Yes | X16: Yes | Y16: No | Z16: 45217 | AA16: 46312 | AB16: 24 | AC16: 18 | AD16: Yes | AE16: Yes | AG16: Phim còn hạn từ 2026 | AH16: MOV_DRA_23__2696593 | AI16: Greta | AJ16: =SUMIF('TK 15661.Bản quyền phim '!F:F,'KK1. Movies'!D16,'TK 15661.Bản quyền phim '!X:X) | AK16: =SUMIF('TK 15661.Bản quyền phim '!F:F,'KK1. Movies'!AI16,'TK 15661.Bản quyền phim '!X:X) | AL16: =COUNTIF('242.BQ Phim hợp tác'!$C:$C,'KK1. Movies'!AI16) | AM16: =COUNTIF('TK 15661.Bản quyền phim '!F:F,'KK1. Movies'!AI16) | AN16: =AL16+AM16 | AT16: =IFERROR(VLOOKUP(C16, CodeRanMovies!$A:$K, 11, 0), "Not found")
A17: =_xlfn.AGGREGATE(3,3,$D$7:D17) | B17: K | C17: MOV_FAN_22__2686869 | D17: HOUSE WITH A CLOCK IN ITS WALLS | E17: Ngôi nhà có chiếc đồng hồ ma thuật | F17: Comedy | G17: CJ HK | H17: 135/2022/HDBQ/VSTV-CJHK | I17: 2018 | J17: US | K17: 105 | L17: 44952 | M17: 46047 | N17: 44952 | O17: K+CINE | P17: 12 | Q17: No | R17: Yes | S17: Yes | T17: Yes | U17: Yes | V17: Yes | W17: Yes | X17: No | Y17: Yes | Z17: 44952 | AA17: 46047 | AB17: unlimited | AC17: 22 | AD17: Yes | AE17: Yes | AG17: Phim còn hạn từ 2026 | AH17: MOV_FAN_22__2686869 | AI17: HOUSE WITH A CLOCK IN ITS WALLS (Ngôi nhà có chiếc đồng hồ ma thuật) | AJ17: =SUMIF('TK 15661.Bản quyền phim '!F:F,'KK1. Movies'!D17,'TK 15661.Bản quyền phim '!X:X) | AK17: =SUMIF('TK 15661.Bản quyền phim '!F:F,'KK1. Movies'!AI17,'TK 15661.Bản quyền phim '!X:X) | AL17: =COUNTIF('242.BQ Phim hợp tác'!$C:$C,'KK1. Movies'!AI17) | AM17: =COUNTIF('TK 15661.Bản quyền phim '!F:F,'KK1. Movies'!AI17) | AN17: =AL17+AM17 | AT17: =IFERROR(VLOOKUP(C17, CodeRanMovies!$A:$K, 11, 0), "Not found")
A18: =_xlfn.AGGREGATE(3,3,$D$7:D18) | B18: 16+ | C18: MOV_DRA730 | D18: HUNT, THE | E18: Cuộc săn lùng | F18: action | G18: NBC Universal | H18: 5049540-2/161434-3 | I18: 2019 | J18: US | K18: 90 | L18: 45414 | M18: 46143 | N18: 45442 | O18: K+ACTION | P18: Non exclusive | Q18: No | R18: Yes | S18: Yes | T18: Yes | U18: No | V18: No | W18: No | X18: No | Y18: Yes | Z18: 45414 | AA18: 46143 | AB18: 6 | AC18: 4 | AD18: Yes | AE18: Yes | AG18: Phim còn hạn từ 2026 | AI18: HUNT, THE | AJ18: =SUMIF('TK 15661.Bản quyền phim '!F:F,'KK1. Movies'!D18,'TK 15661.Bản quyền phim '!X:X) | AK18: =SUMIF('TK 15661.Bản quyền phim '!F:F,'KK1. Movies'!AI18,'TK 15661.Bản quyền phim '!X:X) | AL18: =COUNTIF('242.BQ Phim hợp tác'!$C:$C,'KK1. Movies'!AI18) | AM18: =COUNTIF('TK 15661.Bản quyền phim '!F:F,'KK1. Movies'!AI18) | AN18: =AL18+AM18 | AT18: =IFERROR(VLOOKUP(C18, CodeRanMovies!$A:$K, 11, 0), "Not found")
A19: =_xlfn.AGGREGATE(3,3,$D$7:D19) | B19: 16+ | C19: MOV_CRI_21__2648182 | D19: MOZU | E19: Sát thủ Mozu | F19: Crime, Thriller | G19: TBS | H19: 202104013 | I19: 2015 | J19: Japan | K19: 116 | L19: 44284 | M19: 46109 | N19: 44349 | O19: K+CINE | Q19: No | R19: Yes | S19: Yes | T19: Yes | U19: Yes | V19: Yes | W19: Yes | X19: Yes | Y19: Yes | Z19: 44284 | AA19: 46109 | AB19: 50 | AC19: 34 | AD19: Yes | AE19: Yes | AG19: Phim còn hạn từ 2026 | AH19: MOV_CRI_21__2648182 | AI19: MOZU | AJ19: =SUMIF('TK 15661.Bản quyền phim '!F:F,'KK1. Movies'!D19,'TK 15661.Bản quyền phim '!X:X) | AK19: =SUMIF('TK 15661.Bản quyền phim '!F:F,'KK1. Movies'!AI19,'TK 15661.Bản quyền phim '!X:X) | AL19: =COUNTIF('242.BQ Phim hợp tác'!$C:$C,'KK1. Movies'!AI19) | AM19: =COUNTIF('TK 15661.Bản quyền phim '!F:F,'KK1. Movies'!AI19) | AN19: =AL19+AM19 | AT19: =IFERROR(VLOOKUP(C19, CodeRanMovies!$A:$K, 11, 0), "Not found")
A20: =_xlfn.AGGREGATE(3,3,$D$7:D20) | B20: 16+ | C20: MOV_ACT556 | D20: Caught In Time | E20: Trừ Gian Diệt Ác | F20: action | G20: Hỏa Thổ | H20: 25A/2024/HDBQ/VSTV-Hoa tho | I20: 2020 | J20: China | K20: 95 | L20: 45443 | M20: 46537 | N20: 45443 | O20: K+CINE | Q20: No | R20: Yes | S20: Yes | T20: Yes | U20: No | V20: Yes | W20: Yes | X20: No | Y20: No | Z20: 45443 | AA20: 46537 | AB20: Unlimited run | AC20: 14 | AD20: Yes | AE20: Yes | AG20: Phim còn hạn từ 2026 | AH20: MOV_ACT556 | AI20: Caught In Time (Trừ Gian Diệt Ác) | AJ20: =SUMIF('TK 15661.Bản quyền phim '!F:F,'KK1. Movies'!D20,'TK 15661.Bản quyền phim '!X:X) | AK20: =SUMIF('TK 15661.Bản quyền phim '!F:F,'KK1. Movies'!AI20,'TK 15661.Bản quyền phim '!X:X) | AL20: =COUNTIF('242.BQ Phim hợp tác'!$C:$C,'KK1. Movies'!AI20) | AM20: =COUNTIF('TK 15661.Bản quyền phim '!F:F,'KK1. Movies'!AI20) | AN20: =AL20+AM20 | AT20: =IFERROR(VLOOKUP(C20, CodeRanMovies!$A:$K, 11, 0), "Not found")
A21: =_xlfn.AGGREGATE(3,3,$D$7:D21) | B21: 16+ | C21: MOV_HOR_24__2713878 | D21: CONTORTED | E21: NHÀ KHO CHẾT CHÓC | F21: Horror | G21: CJ HK | H21: 180/2024/HDBQ/VSTV-CJHK | I21: 2022 | J21: Korea | K21: 90 | L21: 45566 | M21: 46660 | N21: 45589 | O21: K+ACTION | P21: 12 | Q21: No | R21: Yes | S21: Yes | T21: Yes | U21: Yes | V21: Yes | W21: Yes | X21: No | Y21: No | Z21: 45566 | AA21: 46660 | AB21: Unlimited | AC21: 11 | AD21: Yes | AE21: Yes | AG21: Phim còn hạn từ 2026 | AH21: MOV_HOR_24__2713878 | AI21: CONTORTED (NHÀ KHO CHẾT CHÓC) | AJ21: =SUMIF('TK 15661.Bản quyền phim '!F:F,'KK1. Movies'!D21,'TK 15661.Bản quyền phim '!X:X) | AK21: =SUMIF('TK 15661.Bản quyền phim '!F:F,'KK1. Movies'!AI21,'TK 15661.Bản quyền phim '!X:X) | AL21: =COUNTIF('242.BQ Phim hợp tác'!$C:$C,'KK1. Movies'!AI21) | AM21: =COUNTIF('TK 15661.Bản quyền phim '!F:F,'KK1. Movies'!AI21) | AN21: =AL21+AM21 | AT21: =IFERROR(VLOOKUP(C21, CodeRanMovies!$A:$K, 11, 0), "Not found")
A22: =_xlfn.AGGREGATE(3,3,$D$7:D22) | B22: 16+ | C22: MOV_SCI20 | D22: LONG DISTANCE | E22: Tín hiệu vũ trụ | F22: Others | G22: CJ HK | H22: 15/2025/HDBQ/VSTV-CJHK | I22: 2024 | J22: US | K22: 91 | L22: 45722 | M22: 46817 | P22: 12 | Q22: No | R22: Yes | S22: Yes | T22: Yes | U22: Yes | V22: Yes | W22: Yes | X22: Yes | Y22: Yes | Z22: 45722 | AA22: 46817 | AB22: Unlimited | AC22: 8 | AD22: Yes | AE22: Yes | AG22: Phim còn hạn từ 2026 | AI22: LONG DISTANCE | AJ22: =SUMIF('TK 15661.Bản quyền phim '!F:F,'KK1. Movies'!D22,'TK 15661.Bản quyền phim '!X:X) | AK22: =SUMIF('TK 15661.Bản quyền phim '!F:F,'KK1. Movies'!AI22,'TK 15661.Bản quyền phim '!X:X) | AL22: =COUNTIF('242.BQ Phim hợp tác'!$C:$C,'KK1. Movies'!AI22) | AM22: =COUNTIF('TK 15661.Bản quyền phim '!F:F,'KK1. Movies'!AI22) | AN22: =AL22+AM22 | AT22: =IFERROR(VLOOKUP(C22, CodeRanMovies!$A:$K, 11, 0), "Not found")
A23: =_xlfn.AGGREGATE(3,3,$D$7:D23) | B23: 16+ | C23: MOV_CRI_22__2686505 | D23: The Night Clerk | E23: Người trực đêm | F23: Crime, Thriller | G23: Skyline Media | H23: 66/2023/HDBQ/VSTV-SM | I23: 2020 | J23: US | K23: 90 | L23: 44937 | M23: 46032 | N23: 44937 | O23: K+CINE | P23: Exclusive All TV Rights the first 12 months of LP Non-exclusive with All Catch-up TV Rights; All VOD Rights during LP | Q23: No | R23: Yes | S23: Yes | T23: Yes | U23: Yes | V23: Yes | W23: Yes | X23: Yes | Y23: Yes | Z23: 44937 | AA23: 46032 | AB23: 24 | AC23: 21 | AD23: Yes | AE23: Yes | AG23: Phim còn hạn từ 2026 | AI23: The Night Clerk | AJ23: =SUMIF('TK 15661.Bản quyền phim '!F:F,'KK1. Movies'!D23,'TK 15661.Bản quyền phim '!X:X) | AK23: =SUMIF('TK 15661.Bản quyền phim '!F:F,'KK1. Movies'!AI23,'TK 15661.Bản quyền phim '!X:X) | AL23: =COUNTIF('242.BQ Phim hợp tác'!$C:$C,'KK1. Movies'!AI23) | AM23: =COUNTIF('TK 15661.Bản quyền phim '!F:F,'KK1. Movies'!AI23) | AN23: =AL23+AM23 | AT23: =IFERROR(VLOOKUP(C23, CodeRanMovies!$A:$K, 11, 0), "Not found")
A24: =_xlfn.AGGREGATE(3,3,$D$7:D24) | B24: 13+ | C24: MOV_ACT_24__2710733 | D24: Journey to China: The Mystery of the Dragon Seal | E24: Long ẩn cơ mật | F24: Action, Adventure | G24: Rose media | H24: 5/2022/HDBQ/VSTV-RM | I24: 2019 | J24: China | K24: 120 | L24: 45338 | M24: 46433 | N24: 45338 | O24: K+CINE | Q24: No | R24: Yes | S24: Yes | T24: Yes | U24: Yes | V24: Yes | W24: Yes | X24: Yes | Y24: No | Z24: 45338 | AA24: 46433 | AB24: 24 | AC24: 18 | AD24: Yes | AE24: Yes | AG24: Phim còn hạn từ 2026 | AI24: Journey to China: The Mystery of the Dragon Seal | AJ24: =SUMIF('TK 15661.Bản quyền phim '!F:F,'KK1. Movies'!D24,'TK 15661.Bản quyền phim '!X:X) | AK24: =SUMIF('TK 15661.Bản quyền phim '!F:F,'KK1. Movies'!AI24,'TK 15661.Bản quyền phim '!X:X) | AL24: =COUNTIF('242.BQ Phim hợp tác'!$C:$C,'KK1. Movies'!AI24) | AM24: =COUNTIF('TK 15661.Bản quyền phim '!F:F,'KK1. Movies'!AI24) | AN24: =AL24+AM24 | AT24: =IFERROR(VLOOKUP(C24, CodeRanMovies!$A:$K, 11, 0), "Not found")
A25: =_xlfn.AGGREGATE(3,3,$D$7:D25) | B25: 16+ | C25: MOV_ACT_22__2686478 | D25: Gringo | E25: Nhọ gặp hên | F25: Action, Adventure | G25: Pro Partner | H25: 56/2023/HDBQ/VSTV-Pro Partner | I25: 2018 | J25: US | K25: 111 | L25: 44930 | M25: 46025 | N25: 44930 | O25: K+CINE | P25: Exclusive All TV Rights the first 9 months of LP Non-exclusive with All Catch-up TV Rights; All VOD Rights during LP | Q25: No | R25: Yes | S25: Yes | T25: Yes | U25: Yes | V25: Yes | W25: Yes | X25: Yes | Y25: Yes | Z25: 44930 | AA25: 46025 | AB25: unlimited | AC25: 27 | AD25: Yes | AE25: Yes | AG25: Phim còn hạn từ 2026 | AI25: Gringo | AJ25: =SUMIF('TK 15661.Bản quyền phim '!F:F,'KK1. Movies'!D25,'TK 15661.Bản quyền phim '!X:X) | AK25: =SUMIF('TK 15661.Bản quyền phim '!F:F,'KK1. Movies'!AI25,'TK 15661.Bản quyền phim '!X:X) | AL25: =COUNTIF('242.BQ Phim hợp tác'!$C:$C,'KK1. Movies'!AI25) | AM25: =COUNTIF('TK 15661.Bản quyền phim '!F:F,'KK1. Movies'!AI25) | AN25: =AL25+AM25 | AT25: =IFERROR(VLOOKUP(C25, CodeRanMovies!$A:$K, 11, 0), "Not found")
A26: =_xlfn.AGGREGATE(3,3,$D$7:D26) | B26: 16+ | C26: MOV_CRI_23__2694717 | D26: THE GIRL ON THE TRAIN | E26: Cô gái trên tàu | F26: Crime, Thriller | G26: CJ HK | H26: 135/2022/HDBQ/VSTV-CJHK | I26: 2016 | J26: US | K26: 112 | L26: 45275 | M26: 46370 | N26: 45275 | O26: K+CINE | P26: 12 | Q26: No | R26: Yes | S26: Yes | T26: Yes | U26: Yes | V26: Yes | W26: Yes | X26: No | Y26: Yes | Z26: 45275 | AA26: 46370 | AB26: unlimited | AC26: 23 | AD26: Yes | AE26: Yes | AG26: Phim còn hạn từ 2026 | AI26: THE GIRL ON THE TRAIN (Cô gái trên tàu) | AJ26: =SUMIF('TK 15661.Bản quyền phim '!F:F,'KK1. Movies'!D26,'TK 15661.Bản quyền phim '!X:X) | AK26: =SUMIF('TK 15661.Bản quyền phim '!F:F,'KK1. Movies'!AI26,'TK 15661.Bản quyền phim '!X:X) | AL26: =COUNTIF('242.BQ Phim hợp tác'!$C:$C,'KK1. Movies'!AI26) | AM26: =COUNTIF('TK 15661.Bản quyền phim '!F:F,'KK1. Movies'!AI26) | AN26: =AL26+AM26 | AT26: =IFERROR(VLOOKUP(C26, CodeRanMovies!$A:$K, 11, 0), "Not found")
A27: =_xlfn.AGGREGATE(3,3,$D$7:D27) | B27: 16+ | C27: MOV_ACT_23__2691050 | D27: Triple Threat | E27: Bộ ba vệ sĩ | F27: Crime, Thriller | G27: Roses Media | H27: 140/2022/HDBQ/VSTV-RM | I27: 2019 | J27: US, Thailand, China, France | K27: 96 | L27: 45161 | M27: 46256 | N27: 45161 | O27: K+CINE | P27: Exclusive All Pay TV Rights for first 12 months. Non exclusive All VOD during LP | Q27: No | R27: Yes | S27: No | T27: Yes | U27: Yes | V27: Yes | W27: Yes | X27: Yes | Y27: No | Z27: 45161 | AA27: 46256 | AB27: 24 | AC27: 15 | AD27: Yes | AE27: Yes | AG27: Phim còn hạn từ 2026 | AI27: Triple Threat | AJ27: =SUMIF('TK 15661.Bản quyền phim '!F:F,'KK1. Movies'!D27,'TK 15661.Bản quyền phim '!X:X) | AK27: =SUMIF('TK 15661.Bản quyền phim '!F:F,'KK1. Movies'!AI27,'TK 15661.Bản quyền phim '!X:X) | AL27: =COUNTIF('242.BQ Phim hợp tác'!$C:$C,'KK1. Movies'!AI27) | AM27: =COUNTIF('TK 15661.Bản quyền phim '!F:F,'KK1. Movies'!AI27) | AN27: =AL27+AM27 | AT27: =IFERROR(VLOOKUP(C27, CodeRanMovies!$A:$K, 11, 0), "Not found")
A28: =_xlfn.AGGREGATE(3,3,$D$7:D28) | B28: 16+ | C28: MOV_THR_24__2712729 | D28: RECALLED | E28: TRIỆU HỒI | F28: Horror | G28: CJ HK | H28: 180/2024/HDBQ/VSTV-CJHK | I28: 2021 | J28: Korea | K28: 99 | L28: 45358 | M28: 46452 | N28: 45358 | O28: K+ACTION | P28: 12 | Q28: No | R28: Yes | S28: Yes | T28: Yes | U28: Yes | V28: Yes | W28: Yes | X28: No | Y28: Yes | Z28: 45358 | AA28: 46452 | AB28: Unlimited | AC28: 18 | AD28: Yes | AE28: Yes | AG28: Phim còn hạn từ 2026 | AI28: RECALLED (TRIỆU HỒI) | AJ28: =SUMIF('TK 15661.Bản quyền phim '!F:F,'KK1. Movies'!D28,'TK 15661.Bản quyền phim '!X:X) | AK28: =SUMIF('TK 15661.Bản quyền phim '!F:F,'KK1. Movies'!AI28,'TK 15661.Bản quyền phim '!X:X) | AL28: =COUNTIF('242.BQ Phim hợp tác'!$C:$C,'KK1. Movies'!AI28) | AM28: =COUNTIF('TK 15661.Bản quyền phim '!F:F,'KK1. Movies'!AI28) | AN28: =AL28+AM28 | AT28: =IFERROR(VLOOKUP(C28, CodeRanMovies!$A:$K, 11, 0), "Not found")
A29: =_xlfn.AGGREGATE(3,3,$D$7:D29) | B29: 13+ | C29: MOV_ADV_23__2694718 | D29: A DOG'S PURPOSE | E29: Mục đích sống của một chú chó | F29: Drama | G29: CJ HK | H29: 135/2022/HDBQ/VSTV-CJHK | I29: 2016 | J29: US | K29: 100 | L29: 45281 | M29: 46376 | N29: 45281 | O29: K+CINE | P29: 12 | Q29: No | R29: Yes | S29: Yes | T29: Yes | U29: Yes | V29: Yes | W29: Yes | X29: No | Y29: Yes | Z29: 45281 | AA29: 46376 | AB29: unlimited | AC29: 16 | AD29: Yes | AE29: Yes | AG29: Phim còn hạn từ 2026 | AI29: A DOG'S PURPOSE (Mục đích sống của một chú chó) | AJ29: =SUMIF('TK 15661.Bản quyền phim '!F:F,'KK1. Movies'!D29,'TK 15661.Bản quyền phim '!X:X) | AK29: =SUMIF('TK 15661.Bản quyền phim '!F:F,'KK1. Movies'!AI29,'TK 15661.Bản quyền phim '!X:X) | AL29: =COUNTIF('242.BQ Phim hợp tác'!$C:$C,'KK1. Movies'!AI29) | AM29: =COUNTIF('TK 15661.Bản quyền phim '!F:F,'KK1. Movies'!AI29) | AN29: =AL29+AM29 | AT29: =IFERROR(VLOOKUP(C29, CodeRanMovies!$A:$K, 11, 0), "Not found")
A30: =_xlfn.AGGREGATE(3,3,$D$7:D30) | B30: 13+ | C30: MOV_MUS7 | D30: BURLESQUE | E30: Vũ nữ | F30: Drama | G30: SONY PICTURES | H30: Sony/K+Vietnam PayBasic SVOD Package Agmt D2D per JK (19-01-2024) | I30: 2010 | J30: US | K30: 118 | L30: 45505 | M30: 46234 | N30: 45602 | O30: K+CINE | Q30: No | R30: Yes | S30: Yes | T30: Yes | U30: No | V30: No | W30: No | X30: No | Y30: No | Z30: 45505 | AA30: 46234 | AB30: 7 | AC30: 2 | AD30: Yes | AE30: Yes | AG30: Phim còn hạn từ 2026 | AI30: BURLESQUE | AJ30: =SUMIF('TK 15661.Bản quyền phim '!F:F,'KK1. Movies'!D30,'TK 15661.Bản quyền phim '!X:X) | AK30: =SUMIF('TK 15661.Bản quyền phim '!F:F,'KK1. Movies'!AI30,'TK 15661.Bản quyền phim '!X:X) | AL30: =COUNTIF('242.BQ Phim hợp tác'!$C:$C,'KK1. Movies'!AI30) | AM30: =COUNTIF('TK 15661.Bản quyền phim '!F:F,'KK1. Movies'!AI30) | AN30: =AL30+AM30 | AT30: =IFERROR(VLOOKUP(C30, CodeRanMovies!$A:$K, 11, 0), "Not found")
A31: =_xlfn.AGGREGATE(3,3,$D$7:D31) | B31: 13+ | C31: MOV_ACT_23__2695079 | D31: My Spy | E31: Điệp viên tí hon | F31: Comedy | G31: Roses Media | H31: 140/2022/HDBQ/VSTV-RM | I31: 2020 | J31: US | K31: 99 | L31: 45197 | M31: 46292 | N31: 45197 | O31: K+CINE | P31: Exclusive All Pay TV Rights for first 12 months. Non exclusive All VOD during LP | Q31: No | R31: Yes | S31: No | T31: Yes | U31: Yes | V31: Yes | W31: Yes | X31: Yes | Y31: No | Z31: 45197 | AA31: 46292 | AB31: 24 | AC31: 14 | AD31: Yes | AE31: Yes | AG31: Phim còn hạn từ 2026 | AI31: My Spy | AJ31: =SUMIF('TK 15661.Bản quyền phim '!F:F,'KK1. Movies'!D31,'TK 15661.Bản quyền phim '!X:X) | AK31: =SUMIF('TK 15661.Bản quyền phim '!F:F,'KK1. Movies'!AI31,'TK 15661.Bản quyền phim '!X:X) | AL31: =COUNTIF('242.BQ Phim hợp tác'!$C:$C,'KK1. Movies'!AI31) | AM31: =COUNTIF('TK 15661.Bản quyền phim '!F:F,'KK1. Movies'!AI31) | AN31: =AL31+AM31 | AT31: =IFERROR(VLOOKUP(C31, CodeRanMovies!$A:$K, 11, 0), "Not found")
A32: =_xlfn.AGGREGATE(3,3,$D$7:D32) | B32: 16+ | C32: MOV_CRI107 | D32: EMILY THE CRIMINAL | E32: Tội phạm Emily | F32: action | G32: NBC Universal | H32: 5049540-2/161434-3 | I32: 2022 | J32: US | K32: 96 | L32: 45554 | M32: 46283 | N32: 45554 | O32: K+ACTION | Q32: No | R32: Yes | S32: Yes | T32: Yes | U32: No | V32: No | W32: No | X32: No | Y32: Yes | Z32: 45554 | AA32: 46283 | AB32: 6 | AC32: 3 | AD32: Yes | AE32: Yes | AG32: Phim còn hạn từ 2026 | AI32: EMILY THE CRIMINAL | AJ32: =SUMIF('TK 15661.Bản quyền phim '!F:F,'KK1. Movies'!D32,'TK 15661.Bản quyền phim '!X:X) | AK32: =SUMIF('TK 15661.Bản quyền phim '!F:F,'KK1. Movies'!AI32,'TK 15661.Bản quyền phim '!X:X) | AL32: =COUNTIF('242.BQ Phim hợp tác'!$C:$C,'KK1. Movies'!AI32) | AM32: =COUNTIF('TK 15661.Bản quyền phim '!F:F,'KK1. Movies'!AI32) | AN32: =AL32+AM32 | AT32: =IFERROR(VLOOKUP(C32, CodeRanMovies!$A:$K, 11, 0), "Not found")
A33: =_xlfn.AGGREGATE(3,3,$D$7:D33) | B33: 16+ | C33: MOV_COM_24__2710443 | D33: A LONG WAY DOWN | E33: Còn lâu mới chết | F33: Drama | G33: Skyline Media | H33: 28/2024/HDBQ/VSTV-SM | I33: 2014 | J33: UK | K33: 96 | L33: 45385 | M33: 46479 | N33: 45506 | O33: K+CINE | P33: 12 | Q33: No | R33: Yes | S33: Yes | T33: Yes | U33: Yes | V33: Yes | W33: Yes | X33: Yes | Y33: No | Z33: 45385 | AA33: 46479 | AB33: 24 | AC33: 14 | AD33: Yes | AE33: Yes | AG33: Phim còn hạn từ 2026 | AI33: A LONG WAY DOWN | AJ33: =SUMIF('TK 15661.Bản quyền phim '!F:F,'KK1. Movies'!D33,'TK 15661.Bản quyền phim '!X:X) | AK33: =SUMIF('TK 15661.Bản quyền phim '!F:F,'KK1. Movies'!AI33,'TK 15661.Bản quyền phim '!X:X) | AL33: =COUNTIF('242.BQ Phim hợp tác'!$C:$C,'KK1. Movies'!AI33) | AM33: =COUNTIF('TK 15661.Bản quyền phim '!F:F,'KK1. Movies'!AI33) | AN33: =AL33+AM33 | AT33: =IFERROR(VLOOKUP(C33, CodeRanMovies!$A:$K, 11, 0), "Not found")
A34: =_xlfn.AGGREGATE(3,3,$D$7:D34) | B34: 16+ | C34: MOV_HOR68 | D34: WITCH, THE | E34: Phù thủy | F34: Horror | G34: NBC Universal | H34: 5049540-2/161434-3 | I34: 2016 | J34: US | K34: 90 | L34: 45596 | M34: 46325 | N34: 45596 | O34: K+ACTION | Q34: No | R34: Yes | S34: Yes | T34: Yes | U34: No | V34: No | W34: No | X34: No | Y34: Yes | Z34: 45596 | AA34: 46325 | AB34: 6 | AC34: 2 | AD34: Yes | AE34: Yes | AG34: Phim còn hạn từ 2026 | AI34: WITCH, THE | AJ34: =SUMIF('TK 15661.Bản quyền phim '!F:F,'KK1. Movies'!D34,'TK 15661.Bản quyền phim '!X:X) | AK34: =SUMIF('TK 15661.Bản quyền phim '!F:F,'KK1. Movies'!AI34,'TK 15661.Bản quyền phim '!X:X) | AL34: =COUNTIF('242.BQ Phim hợp tác'!$C:$C,'KK1. Movies'!AI34) | AM34: =COUNTIF('TK 15661.Bản quyền phim '!F:F,'KK1. Movies'!AI34) | AN34: =AL34+AM34 | AT34: =IFERROR(VLOOKUP(C34, CodeRanMovies!$A:$K, 11, 0), "Not found")
A35: =_xlfn.AGGREGATE(3,3,$D$7:D35) | B35: 16+ | C35: MOV_ACT584 | D35: AMBULANCE (2022) | E35: Xe cấp cứu | F35: action | G35: NBC Universal | H35: 5049540-2/161434-3 | I35: 2022 | J35: US | K35: 136 | L35: 45513 | M35: 46242 | N35: 45513 | O35: K+CINE | P35: 12 | Q35: No | R35: Yes | S35: Yes | T35: Yes | U35: No | V35: No | W35: No | X35: No | Y35: Yes | Z35: 45513 | AA35: 46242 | AB35: 6 | AC35: 3 | AD35: Yes | AE35: Yes | AG35: Phim còn hạn từ 2026 | AI35: AMBULANCE (2022) | AJ35: =SUMIF('TK 15661.Bản quyền phim '!F:F,'KK1. Movies'!D35,'TK 15661.Bản quyền phim '!X:X) | AK35: =SUMIF('TK 15661.Bản quyền phim '!F:F,'KK1. Movies'!AI35,'TK 15661.Bản quyền phim '!X:X) | AL35: =COUNTIF('242.BQ Phim hợp tác'!$C:$C,'KK1. Movies'!AI35) | AM35: =COUNTIF('TK 15661.Bản quyền phim '!F:F,'KK1. Movies'!AI35) | AN35: =AL35+AM35 | AT35: =IFERROR(VLOOKUP(C35, CodeRanMovies!$A:$K, 11, 0), "Not found")
A36: =_xlfn.AGGREGATE(3,3,$D$7:D36) | B36: 16+ | C36: MOV_COM_22__2686480 | D36: Best Friend | E36: Láng giềng gần | F36: Drama | G36: Pro Partner | H36: 56/2023/HDBQ/VSTV-Pro Partner | I36: 2020 | J36: Korea | K36: 130 | L36: 44938 | M36: 46033 | N36: 44938 | O36: K+CINE | P36: Exclusive All TV Rights the first 9 months of LP Non-exclusive with All Catch-up TV Rights; All VOD Rights during LP | Q36: No | R36: Yes | S36: Yes | T36: Yes | U36: Yes | V36: Yes | W36: Yes | X36: Yes | Y36: Yes | Z36: 44938 | AA36: 46033 | AB36: unlimited | AC36: 26 | AD36: Yes | AE36: Yes | AG36: Phim còn hạn từ 2026 | AI36: Best Friend | AJ36: =SUMIF('TK 15661.Bản quyền phim '!F:F,'KK1. Movies'!D36,'TK 15661.Bản quyền phim '!X:X) | AK36: =SUMIF('TK 15661.Bản quyền phim '!F:F,'KK1. Movies'!AI36,'TK 15661.Bản quyền phim '!X:X) | AL36: =COUNTIF('242.BQ Phim hợp tác'!$C:$C,'KK1. Movies'!AI36) | AM36: =COUNTIF('TK 15661.Bản quyền phim '!F:F,'KK1. Movies'!AI36) | AN36: =AL36+AM36 | AT36: =IFERROR(VLOOKUP(C36, CodeRanMovies!$A:$K, 11, 0), "Not found")
A37: =_xlfn.AGGREGATE(3,3,$D$7:D37) | B37: P | C37: MOV_ANI_23__2709986 | D37: AROUND THE WORLD IN 80 DAYS | E37: KHỈ CON LON TON THẾ GIỚI | F37: Comedy | G37: CJ HK | H37: 180/2024/HDBQ/VSTV-CJHK | I37: 2021 | J37: France | K37: 82 | L37: 45304 | M37: 46399 | N37: 45304 | O37: K+KIDS | P37: 12 | Q37: No | R37: Yes | S37: Yes | T37: Yes | U37: Yes | V37: Yes | W37: Yes | X37: No | Y37: Yes | Z37: 45304 | AA37: 46399 | AB37: Unlimited | AC37: 31 | AD37: Yes | AE37: Yes | AG37: Phim còn hạn từ 2026 | AI37: AROUND THE WORLD IN 80 DAYS (KHỈ CON LON TON THẾ GIỚI) | AJ37: =SUMIF('TK 15661.Bản quyền phim '!F:F,'KK1. Movies'!D37,'TK 15661.Bản quyền phim '!X:X) | AK37: =SUMIF('TK 15661.Bản quyền phim '!F:F,'KK1. Movies'!AI37,'TK 15661.Bản quyền phim '!X:X) | AL37: =COUNTIF('242.BQ Phim hợp tác'!$C:$C,'KK1. Movies'!AI37) | AM37: =COUNTIF('TK 15661.Bản quyền phim '!F:F,'KK1. Movies'!AI37) | AN37: =AL37+AM37 | AT37: =IFERROR(VLOOKUP(C37, CodeRanMovies!$A:$K, 11, 0), "Not found")
A38: =_xlfn.AGGREGATE(3,3,$D$7:D38) | B38: 16+ | C38: MOV_DRA_23__2696805 | D38: The Last Princess | E38: Công chúa cuối cùng | F38: Drama | G38: King Content | H38: 52/2023/HDBQ/VSTV-KC | I38: 2016 | J38: Korea | K38: 127 | L38: 45147 | M38: 46242 | N38: 45226 | O38: K+CINE | P38: Exclusive All PayTV rights and Non-Exclusive VOD rights | Q38: Yes | R38: Yes | S38: No | T38: Yes | U38: Yes | V38: Yes | W38: Yes | X38: Yes | Y38: No | Z38: 45147 | AA38: 46242 | AB38: unlimited | AC38: 15 | AD38: Yes | AE38: Yes | AG38: Phim còn hạn từ 2026 | AI38: Last princess | AJ38: =SUMIF('TK 15661.Bản quyền phim '!F:F,'KK1. Movies'!D38,'TK 15661.Bản quyền phim '!X:X) | AK38: =SUMIF('TK 15661.Bản quyền phim '!F:F,'KK1. Movies'!AI38,'TK 15661.Bản quyền phim '!X:X) | AL38: =COUNTIF('242.BQ Phim hợp tác'!$C:$C,'KK1. Movies'!AI38) | AM38: =COUNTIF('TK 15661.Bản quyền phim '!F:F,'KK1. Movies'!AI38) | AN38: =AL38+AM38 | AT38: =IFERROR(VLOOKUP(C38, CodeRanMovies!$A:$K, 11, 0), "Not found")
A39: =_xlfn.AGGREGATE(3,3,$D$7:D39) | B39: P | C39: MOV_ANI_23__2698580 | D39: Space dogs: Tropical adventure | E39: Biệt đội phi hành cún | F39: Comedy | G39: Roses Media | H39: 82/2023/HDBQ/VSTV-Roses Media | I39: 2020 | J39: Russia | K39: 80 | L39: 45206 | M39: 46301 | N39: 45206 | O39: K+KIDS | P39: Exclusive All Pay TV Rights for first 12 months. Non exclusive All VOD during LP | Q39: No | R39: Yes | S39: Yes | T39: Yes | U39: Yes | V39: Yes | W39: Yes | X39: Yes | Y39: No | Z39: 45206 | AA39: 46301 | AB39: 24 | AC39: 16 | AD39: Yes | AE39: Yes | AG39: Phim còn hạn từ 2026 | AI39: Space Dogs: Return to Earth | AJ39: =SUMIF('TK 15661.Bản quyền phim '!F:F,'KK1. Movies'!D39,'TK 15661.Bản quyền phim '!X:X) | AK39: =SUMIF('TK 15661.Bản quyền phim '!F:F,'KK1. Movies'!AI39,'TK 15661.Bản quyền phim '!X:X) | AL39: =COUNTIF('242.BQ Phim hợp tác'!$C:$C,'KK1. Movies'!AI39) | AM39: =COUNTIF('TK 15661.Bản quyền phim '!F:F,'KK1. Movies'!AI39) | AN39: =AL39+AM39 | AT39: =IFERROR(VLOOKUP(C39, CodeRanMovies!$A:$K, 11, 0), "Not found")
A40: =_xlfn.AGGREGATE(3,3,$D$7:D40) | B40: 16+ | C40: MOV_ACT_23__2693252 | D40: The Ice Road | E40: Con đường băng | F40: Action, Adventure | G40: Roses Media | H40: 140/2022/HDBQ/VSTV-RM | I40: 2021 | J40: US | K40: 103 | L40: 45133 | M40: 46228 | N40: 45133 | O40: K+CINE | P40: Exclusive All Pay TV Rights for first 12 months. Non exclusive All VOD during LP | Q40: No | R40: Yes | S40: No | T40: Yes | U40: Yes | V40: Yes | W40: Yes | X40: Yes | Y40: No | Z40: 45133 | AA40: 46228 | AB40: 24 | AC40: 15 | AD40: Yes | AE40: Yes | AG40: Phim còn hạn từ 2026 | AI40: The Ice Road | AJ40: =SUMIF('TK 15661.Bản quyền phim '!F:F,'KK1. Movies'!D40,'TK 15661.Bản quyền phim '!X:X) | AK40: =SUMIF('TK 15661.Bản quyền phim '!F:F,'KK1. Movies'!AI40,'TK 15661.Bản quyền phim '!X:X) | AL40: =COUNTIF('242.BQ Phim hợp tác'!$C:$C,'KK1. Movies'!AI40) | AM40: =COUNTIF('TK 15661.Bản quyền phim '!F:F,'KK1. Movies'!AI40) | AN40: =AL40+AM40 | AT40: =IFERROR(VLOOKUP(C40, CodeRanMovies!$A:$K, 11, 0), "Not found")
A41: =_xlfn.AGGREGATE(3,3,$D$7:D41) | B41: 16+ | C41: MOV_HOR_24__2711609 | D41: Talk To Me | E41: Gọi hồn quỷ dữ | F41: Horror | G41: Rose media | H41: 5/2022/HDBQ/VSTV-RM | I41: 2023 | J41: US | K41: 93 | L41: 45575 | M41: 46669 | N41: 45575 | O41: K+ACTION | Q41: No | R41: Yes | S41: Yes | T41: Yes | U41: Yes | V41: Yes | W41: Yes | X41: Yes | Y41: No | Z41: 45575 | AA41: 46669 | AB41: 24 | AC41: 6 | AD41: Yes | AE41: Yes | AG41: Phim còn hạn từ 2026 | AI41: Talk To Me | AJ41: =SUMIF('TK 15661.Bản quyền phim '!F:F,'KK1. Movies'!D41,'TK 15661.Bản quyền phim '!X:X) | AK41: =SUMIF('TK 15661.Bản quyền phim '!F:F,'KK1. Movies'!AI41,'TK 15661.Bản quyền phim '!X:X) | AL41: =COUNTIF('242.BQ Phim hợp tác'!$C:$C,'KK1. Movies'!AI41) | AM41: =COUNTIF('TK 15661.Bản quyền phim '!F:F,'KK1. Movies'!AI41) | AN41: =AL41+AM41 | AT41: =IFERROR(VLOOKUP(C41, CodeRanMovies!$A:$K, 11, 0), "Not found")
A42: =_xlfn.AGGREGATE(3,3,$D$7:D42) | B42: 16+ | C42: MOV_ROM_22__2686516 | D42: We Made A Beautiful Bouquet | E42: Tình ta đẹp tựa đóa hoa | F42: Romance | G42: Skyline Media | H42: 66/2023/HDBQ/VSTV-SM | I42: 2021 | J42: Japan | K42: 124 | L42: 45065 | M42: 46160 | N42: 45162 | O42: K+CINE | P42: Exclusive All TV Rights the first 12 months of LP Non-exclusive with All Catch-up TV Rights; All VOD Rights during LP | Q42: No | R42: Yes | S42: Yes | T42: Yes | U42: Yes | V42: Yes | W42: Yes | X42: Yes | Y42: Yes | Z42: 45065 | AA42: 46160 | AB42: unlimited | AC42: 21 | AD42: Yes | AE42: Yes | AG42: Phim còn hạn từ 2026 | AI42: We Made A Beautiful Bouquet | AJ42: =SUMIF('TK 15661.Bản quyền phim '!F:F,'KK1. Movies'!D42,'TK 15661.Bản quyền phim '!X:X) | AK42: =SUMIF('TK 15661.Bản quyền phim '!F:F,'KK1. Movies'!AI42,'TK 15661.Bản quyền phim '!X:X) | AL42: =COUNTIF('242.BQ Phim hợp tác'!$C:$C,'KK1. Movies'!AI42) | AM42: =COUNTIF('TK 15661.Bản quyền phim '!F:F,'KK1. Movies'!AI42) | AN42: =AL42+AM42 | AT42: =IFERROR(VLOOKUP(C42, CodeRanMovies!$A:$K, 11, 0), "Not found")
A43: =_xlfn.AGGREGATE(3,3,$D$7:D43) | B43: n/a | C43: MOV_DRA752 | D43: LITTLE WOMEN (2019) | E43: Những người phụ nữ bé nhỏ | F43: Drama | G43: SONY | H43: Sony/K+Vietnam PayBasic SVOD Package Agmt D3A FE (Feb-5-24) | I43: 2019 | J43: U.S.A.[excluding Territories & Possessions] | K43: 134 | L43: 45736 | M43: 46465 | Q43: No | R43: Yes | S43: Yes | T43: Yes | U43: No | V43: No | W43: No | X43: Yes | Y43: No | Z43: 45736 | AA43: 46284 | AB43: 7 | AC43: 1 | AD43: Yes | AE43: Yes | AG43: Phim còn hạn từ 2026 | AI43: LITTLE WOMEN (2019) | AJ43: =SUMIF('TK 15661.Bản quyền phim '!F:F,'KK1. Movies'!D43,'TK 15661.Bản quyền phim '!X:X) | AK43: =SUMIF('TK 15661.Bản quyền phim '!F:F,'KK1. Movies'!AI43,'TK 15661.Bản quyền phim '!X:X) | AL43: =COUNTIF('242.BQ Phim hợp tác'!$C:$C,'KK1. Movies'!AI43) | AM43: =COUNTIF('TK 15661.Bản quyền phim '!F:F,'KK1. Movies'!AI43) | AN43: =AL43+AM43 | AT43: =IFERROR(VLOOKUP(C43, CodeRanMovies!$A:$K, 11, 0), "Not found")
A44: =_xlfn.AGGREGATE(3,3,$D$7:D44) | B44: 16+ | C44: MOV_ACT587 | D44: RIDE ALONG | E44: Bộ đôi cảnh sát | F44: action | G44: NBC Universal | H44: 5049540-2/161434-3 | I44: 2014 | J44: US | K44: 100 | L44: 45562 | M44: 46291 | N44: 45562 | O44: K+CINE | P44: Non exclusive | Q44: No | R44: Yes | S44: Yes | T44: Yes | U44: No | V44: No | W44: No | X44: No | Y44: Yes | Z44: 45562 | AA44: 46291 | AB44: 6 | AC44: 3 | AD44: Yes | AE44: Yes | AG44: Phim còn hạn từ 2026 | AH44: MOV_ACT587 | AI44: RIDE ALONG | AJ44: =SUMIF('TK 15661.Bản quyền phim '!F:F,'KK1. Movies'!D44,'TK 15661.Bản quyền phim '!X:X) | AK44: =SUMIF('TK 15661.Bản quyền phim '!F:F,'KK1. Movies'!AI44,'TK 15661.Bản quyền phim '!X:X) | AL44: =COUNTIF('242.BQ Phim hợp tác'!$C:$C,'KK1. Movies'!AI44) | AM44: =COUNTIF('TK 15661.Bản quyền phim '!F:F,'KK1. Movies'!AI44) | AN44: =AL44+AM44 | AT44: =IFERROR(VLOOKUP(C44, CodeRanMovies!$A:$K, 11, 0), "Not found")
A45: =_xlfn.AGGREGATE(3,3,$D$7:D45) | B45: 13+ | C45: MOV_ROM_23__2697130 | D45: Time Freak | E45: Ngược dòng thời gian | F45: Romance | G45: Roses Media | H45: 140/2022/HDBQ/VSTV-RM | I45: 2018 | J45: US | K45: 104 | L45: 45232 | M45: 46327 | N45: 45232 | O45: K+CINE | P45: Exclusive All Pay TV Rights for first 12 months. Non exclusive All VOD during LP | Q45: No | R45: Yes | S45: No | T45: Yes | U45: Yes | V45: Yes | W45: Yes | X45: Yes | Y45: No | Z45: 45232 | AA45: 46327 | AB45: 24 | AC45: 7 | AD45: Yes | AE45: Yes | AG45: Phim còn hạn từ 2026 | AH45: MOV_ROM_23__2697130 | AI45: Time Freak | AJ45: =SUMIF('TK 15661.Bản quyền phim '!F:F,'KK1. Movies'!D45,'TK 15661.Bản quyền phim '!X:X) | AK45: =SUMIF('TK 15661.Bản quyền phim '!F:F,'KK1. Movies'!AI45,'TK 15661.Bản quyền phim '!X:X) | AL45: =COUNTIF('242.BQ Phim hợp tác'!$C:$C,'KK1. Movies'!AI45) | AM45: =COUNTIF('TK 15661.Bản quyền phim '!F:F,'KK1. Movies'!AI45) | AN45: =AL45+AM45 | AT45: =IFERROR(VLOOKUP(C45, CodeRanMovies!$A:$K, 11, 0), "Not found")
A46: =_xlfn.AGGREGATE(3,3,$D$7:D46) | B46: 13+ | C46: MOV_ACT_24__2715853 | D46: Cloudy Mountain | E46: Chiều Sâu Vô Hạn | F46: action | G46: Hỏa Thổ | H46: 25A/2024/HDBQ/VSTV-Hoa tho | I46: 2021 | J46: China | K46: 104 | L46: 45429 | M46: 46523 | N46: 45429 | O46: K+CINE | Q46: No | R46: Yes | S46: Yes | T46: Yes | U46: No | V46: Yes | W46: Yes | X46: No | Y46: No | Z46: 45429 | AA46: 46523 | AB46: Unlimited run | AC46: 16 | AD46: Yes | AE46: Yes | AG46: Phim còn hạn từ 2026 | AH46: MOV_ACT_24__2715853 | AI46: Cloudy Mountain (Chiều Sâu Vô Hạn) | AJ46: =SUMIF('TK 15661.Bản quyền phim '!F:F,'KK1. Movies'!D46,'TK 15661.Bản quyền phim '!X:X) | AK46: =SUMIF('TK 15661.Bản quyền phim '!F:F,'KK1. Movies'!AI46,'TK 15661.Bản quyền phim '!X:X) | AL46: =COUNTIF('242.BQ Phim hợp tác'!$C:$C,'KK1. Movies'!AI46) | AM46: =COUNTIF('TK 15661.Bản quyền phim '!F:F,'KK1. Movies'!AI46) | AN46: =AL46+AM46 | AT46: =IFERROR(VLOOKUP(C46, CodeRanMovies!$A:$K, 11, 0), "Not found")
A47: =_xlfn.AGGREGATE(3,3,$D$7:D47) | B47: 16+ | C47: MOV_ADV_23__2691048 | D47: THE LEDGE | E47: Vực thẳm | F47: Crime, Thriller | G47: Roses Media | H47: 140/2022/HDBQ/VSTV-RM | I47: 2022 | J47: US | K47: 86 | L47: 45127 | M47: 46222 | N47: 45127 | O47: K+CINE | P47: Exclusive All Pay TV Rights for first 12 months. Non exclusive All VOD during LP | Q47: No | R47: Yes | S47: No | T47: Yes | U47: Yes | V47: Yes | W47: Yes | X47: Yes | Y47: No | Z47: 45127 | AA47: 46222 | AB47: 24 | AC47: 15 | AD47: Yes | AE47: Yes | AG47: Phim còn hạn từ 2026 | AH47: MOV_ADV_23__2691048 | AI47: THE LEDGE | AJ47: =SUMIF('TK 15661.Bản quyền phim '!F:F,'KK1. Movies'!D47,'TK 15661.Bản quyền phim '!X:X) | AK47: =SUMIF('TK 15661.Bản quyền phim '!F:F,'KK1. Movies'!AI47,'TK 15661.Bản quyền phim '!X:X) | AL47: =COUNTIF('242.BQ Phim hợp tác'!$C:$C,'KK1. Movies'!AI47) | AM47: =COUNTIF('TK 15661.Bản quyền phim '!F:F,'KK1. Movies'!AI47) | AN47: =AL47+AM47 | AT47: =IFERROR(VLOOKUP(C47, CodeRanMovies!$A:$K, 11, 0), "Not found")
A48: =_xlfn.AGGREGATE(3,3,$D$7:D48) | B48: 16+ | C48: MOV_CRI_22__2686512 | D48: The Voice Of Sin | E48: Thanh âm tội ác | F48: Crime, Thriller | G48: Skyline Media | H48: 66/2023/HDBQ/VSTV-SM | I48: 2020 | J48: Japan | K48: 142 | L48: 45065 | M48: 46160 | N48: 45065 | O48: K+CINE | P48: Exclusive All TV Rights the first 12 months of LP Non-exclusive with All Catch-up TV Rights; All VOD Rights during LP | Q48: No | R48: Yes | S48: Yes | T48: Yes | U48: Yes | V48: Yes | W48: Yes | X48: Yes | Y48: Yes | Z48: 45065 | AA48: 46160 | AB48: unlimited | AC48: 30 | AD48: Yes | AE48: Yes | AG48: Phim còn hạn từ 2026 | AH48: MOV_CRI_22__2686512 | AI48: The Voice Of Sin | AJ48: =SUMIF('TK 15661.Bản quyền phim '!F:F,'KK1. Movies'!D48,'TK 15661.Bản quyền phim '!X:X) | AK48: =SUMIF('TK 15661.Bản quyền phim '!F:F,'KK1. Movies'!AI48,'TK 15661.Bản quyền phim '!X:X) | AL48: =COUNTIF('242.BQ Phim hợp tác'!$C:$C,'KK1. Movies'!AI48) | AM48: =COUNTIF('TK 15661.Bản quyền phim '!F:F,'KK1. Movies'!AI48) | AN48: =AL48+AM48 | AT48: =IFERROR(VLOOKUP(C48, CodeRanMovies!$A:$K, 11, 0), "Not found")
A49: =_xlfn.AGGREGATE(3,3,$D$7:D49) | B49: K | C49: MOV_DRA_24__2710444 | D49: ALL ABOUT MY MOTHER | E49: Chân dung mẹ tôi | F49: Drama | G49: Skyline Media | H49: 28/2024/HDBQ/VSTV-SM | I49: 2021 | J49: US | K49: 120 | L49: 45567 | M49: 46661 | N49: 45573 | O49: K+CINE | P49: 12 | Q49: No | R49: Yes | S49: Yes | T49: Yes | U49: Yes | V49: Yes | W49: Yes | X49: Yes | Y49: No | Z49: 45567 | AA49: 46661 | AB49: 24 | AC49: 7 | AD49: Yes | AE49: Yes | AG49: Phim còn hạn từ 2026 | AI49: ALL ABOUT MY MOTHER | AJ49: =SUMIF('TK 15661.Bản quyền phim '!F:F,'KK1. Movies'!D49,'TK 15661.Bản quyền phim '!X:X) | AK49: =SUMIF('TK 15661.Bản quyền phim '!F:F,'KK1. Movies'!AI49,'TK 15661.Bản quyền phim '!X:X) | AL49: =COUNTIF('242.BQ Phim hợp tác'!$C:$C,'KK1. Movies'!AI49) | AM49: =COUNTIF('TK 15661.Bản quyền phim '!F:F,'KK1. Movies'!AI49) | AN49: =AL49+AM49 | AT49: =IFERROR(VLOOKUP(C49, CodeRanMovies!$A:$K, 11, 0), "Not found")
A50: =_xlfn.AGGREGATE(3,3,$D$7:D50) | B50: 16+ | C50: MOV_ACT_24__2713163 | D50: BLACK AND BLUE (2019) | E50: Cảnh sát da màu | F50: Crime, Thriller | G50: SONY PICTURES | H50: Sony/K+Vietnam PayBasic SVOD Package Agmt D2D per JK (19-01-2024) | I50: 2019 | J50: US | K50: 107 | L50: 45382 | M50: 46111 | N50: 45393 | O50: K+ACTION | Q50: No | R50: Yes | S50: Yes | T50: Yes | U50: No | V50: No | W50: No | X50: No | Y50: No | Z50: 45382 | AA50: 46111 | AB50: 7 | AC50: 6 | AD50: Yes | AE50: Yes | AG50: Phim còn hạn từ 2026 | AI50: BLACK AND BLUE (2019) | AJ50: =SUMIF('TK 15661.Bản quyền phim '!F:F,'KK1. Movies'!D50,'TK 15661.Bản quyền phim '!X:X) | AK50: =SUMIF('TK 15661.Bản quyền phim '!F:F,'KK1. Movies'!AI50,'TK 15661.Bản quyền phim '!X:X) | AL50: =COUNTIF('242.BQ Phim hợp tác'!$C:$C,'KK1. Movies'!AI50) | AM50: =COUNTIF('TK 15661.Bản quyền phim '!F:F,'KK1. Movies'!AI50) | AN50: =AL50+AM50 | AT50: =IFERROR(VLOOKUP(C50, CodeRanMovies!$A:$K, 11, 0), "Not found")
A51: =_xlfn.AGGREGATE(3,3,$D$7:D51) | B51: 16+ | C51: MOV_CRI_24__2710437 | D51: THE WHISTLERS | E51: Vụ cướp đảo La Gomera | F51: Crime, Thriller | G51: Skyline Media | H51: 28/2024/HDBQ/VSTV-SM | I51: 2019 | J51: Romania, France | K51: 97 | L51: 45365 | M51: 46459 | N51: 45498 | O51: K+ACTION | P51: 12 | Q51: No | R51: Yes | S51: Yes | T51: Yes | U51: Yes | V51: Yes | W51: Yes | X51: Yes | Y51: No | Z51: 45365 | AA51: 46459 | AB51: 24 | AC51: 12 | AD51: Yes | AE51: Yes | AG51: Phim còn hạn từ 2026 | AH51: MOV_CRI_24__2710437 | AI51: THE WHISTLERS | AJ51: =SUMIF('TK 15661.Bản quyền phim '!F:F,'KK1. Movies'!D51,'TK 15661.Bản quyền phim '!X:X) | AK51: =SUMIF('TK 15661.Bản quyền phim '!F:F,'KK1. Movies'!AI51,'TK 15661.Bản quyền phim '!X:X) | AL51: =COUNTIF('242.BQ Phim hợp tác'!$C:$C,'KK1. Movies'!AI51) | AM51: =COUNTIF('TK 15661.Bản quyền phim '!F:F,'KK1. Movies'!AI51) | AN51: =AL51+AM51 | AT51: =IFERROR(VLOOKUP(C51, CodeRanMovies!$A:$K, 11, 0), "Not found")
A52: =_xlfn.AGGREGATE(3,3,$D$7:D52) | B52: 16+ | C52: MOV_THR_21__2651058 | D52: STOLEN IDENTITY 2 | E52: Kẻ trộm danh tính - Phần 2 | F52: Crime, Thriller | G52: TBS | H52: 202104013 | I52: 2020 | J52: Japan | K52: 118 | L52: 44284 | M52: 46109 | N52: 44377 | O52: K+CINE | Q52: No | R52: Yes | S52: Yes | T52: Yes | U52: Yes | V52: Yes | W52: Yes | X52: Yes | Y52: Yes | Z52: 44284 | AA52: 46109 | AB52: 50 | AC52: 30 | AD52: Yes | AE52: Yes | AG52: Phim còn hạn từ 2026 | AI52: STOLEN IDENTITY 2 | AJ52: =SUMIF('TK 15661.Bản quyền phim '!F:F,'KK1. Movies'!D52,'TK 15661.Bản quyền phim '!X:X) | AK52: =SUMIF('TK 15661.Bản quyền phim '!F:F,'KK1. Movies'!AI52,'TK 15661.Bản quyền phim '!X:X) | AL52: =COUNTIF('242.BQ Phim hợp tác'!$C:$C,'KK1. Movies'!AI52) | AM52: =COUNTIF('TK 15661.Bản quyền phim '!F:F,'KK1. Movies'!AI52) | AN52: =AL52+AM52 | AT52: =IFERROR(VLOOKUP(C52, CodeRanMovies!$A:$K, 11, 0), "Not found")
A53: =_xlfn.AGGREGATE(3,3,$D$7:D53) | B53: 13+ | C53: MOV_BIO_23__2689673 | D53: THE POST | E53: Bí mật Lầu Năm Góc | F53: Drama | G53: CJ HK | H53: 135/2022/HDBQ/VSTV-CJHK | I53: 2017 | J53: US | K53: 117 | L53: 44987 | M53: 46082 | N53: 44987 | O53: K+CINE | P53: 12 | Q53: No | R53: Yes | S53: Yes | T53: Yes | U53: Yes | V53: Yes | W53: Yes | X53: No | Y53: Yes | Z53: 44987 | AA53: 46082 | AB53: unlimited | AC53: 22 | AD53: Yes | AE53: Yes | AG53: Phim còn hạn từ 2026 | AH53: MOV_BIO_23__2689673 | AI53: THE POST (Bí mật Lầu Năm Góc) | AJ53: =SUMIF('TK 15661.Bản quyền phim '!F:F,'KK1. Movies'!D53,'TK 15661.Bản quyền phim '!X:X) | AK53: =SUMIF('TK 15661.Bản quyền phim '!F:F,'KK1. Movies'!AI53,'TK 15661.Bản quyền phim '!X:X) | AL53: =COUNTIF('242.BQ Phim hợp tác'!$C:$C,'KK1. Movies'!AI53) | AM53: =COUNTIF('TK 15661.Bản quyền phim '!F:F,'KK1. Movies'!AI53) | AN53: =AL53+AM53 | AT53: =IFERROR(VLOOKUP(C53, CodeRanMovies!$A:$K, 11, 0), "Not found")
A54: =_xlfn.AGGREGATE(3,3,$D$7:D54) | B54: 16+ | C54: MOV_CRI_23__2697555 | D54: The Faceless Boss | E54: Vô diện đại ca | F54: Drama | G54: King Content | H54: 52/2023/HDBQ/VSTV-KC | I54: 2019 | J54: Korea | K54: 100 | L54: 45147 | M54: 46242 | N54: 45147 | O54: K+CINE | P54: Exclusive All PayTV rights and Non-Exclusive VOD rights | Q54: Yes | R54: Yes | S54: No | T54: Yes | U54: Yes | V54: Yes | W54: Yes | X54: Yes | Y54: No | Z54: 45147 | AA54: 46242 | AB54: unlimited | AC54: 23 | AD54: Yes | AE54: Yes | AG54: Phim còn hạn từ 2026 | AI54: Faceless Boss | AJ54: =SUMIF('TK 15661.Bản quyền phim '!F:F,'KK1. Movies'!D54,'TK 15661.Bản quyền phim '!X:X) | AK54: =SUMIF('TK 15661.Bản quyền phim '!F:F,'KK1. Movies'!AI54,'TK 15661.Bản quyền phim '!X:X) | AL54: =COUNTIF('242.BQ Phim hợp tác'!$C:$C,'KK1. Movies'!AI54) | AM54: =COUNTIF('TK 15661.Bản quyền phim '!F:F,'KK1. Movies'!AI54) | AN54: =AL54+AM54 | AT54: =IFERROR(VLOOKUP(C54, CodeRanMovies!$A:$K, 11, 0), "Not found")
A55: =_xlfn.AGGREGATE(3,3,$D$7:D55) | B55: K | C55: MOV_ACT_22__2686483 | D55: Superwho? | E55: Giả danh anh hùng | F55: Action, Adventure | G55: Pro Partner | H55: 56/2023/HDBQ/VSTV-Pro Partner | I55: 2021 | J55: France | K55: 82 | L55: 44945 | M55: 46040 | N55: 44945 | O55: K+CINE | P55: Exclusive All TV Rights the first 9 months of LP Non-exclusive with All Catch-up TV Rights; All VOD Rights during LP | Q55: No | R55: Yes | S55: Yes | T55: Yes | U55: Yes | V55: Yes | W55: Yes | X55: Yes | Y55: Yes | Z55: 44945 | AA55: 46040 | AB55: unlimited | AC55: 29 | AD55: Yes | AE55: Yes | AG55: Phim còn hạn từ 2026 | AI55: Superwho? | AJ55: =SUMIF('TK 15661.Bản quyền phim '!F:F,'KK1. Movies'!D55,'TK 15661.Bản quyền phim '!X:X) | AK55: =SUMIF('TK 15661.Bản quyền phim '!F:F,'KK1. Movies'!AI55,'TK 15661.Bản quyền phim '!X:X) | AL55: =COUNTIF('242.BQ Phim hợp tác'!$C:$C,'KK1. Movies'!AI55) | AM55: =COUNTIF('TK 15661.Bản quyền phim '!F:F,'KK1. Movies'!AI55) | AN55: =AL55+AM55 | AT55: =IFERROR(VLOOKUP(C55, CodeRanMovies!$A:$K, 11, 0), "Not found")
A56: =_xlfn.AGGREGATE(3,3,$D$7:D56) | B56: 16+ | C56: MOV_ACT_22__2668484 | D56: Signal: The Movie | E56: Tín hiệu chết chóc | F56: Crime, Thriller | G56: Skyline Media | H56: 1/2022/HDBQ/VSTV-SM | I56: 2021 | J56: Japan | K56: 122 | L56: 44755 | M56: 46216 | N56: 44755 | O56: K+CINE | P56: Exclusive All Pay TV Rights for the first 12 months of LP. Non exclusive SVOD Right during LP | Q56: No | R56: Yes | S56: Yes | T56: Yes | U56: no | V56: no | W56: no | X56: Yes | Y56: no | Z56: 44755 | AA56: 46216 | AB56: 50 | AC56: 25 | AD56: Yes | AE56: Yes | AG56: Phim còn hạn từ 2026 | AI56: Signal: The Movie | AJ56: =SUMIF('TK 15661.Bản quyền phim '!F:F,'KK1. Movies'!D56,'TK 15661.Bản quyền phim '!X:X) | AK56: =SUMIF('TK 15661.Bản quyền phim '!F:F,'KK1. Movies'!AI56,'TK 15661.Bản quyền phim '!X:X) | AL56: =COUNTIF('242.BQ Phim hợp tác'!$C:$C,'KK1. Movies'!AI56) | AM56: =COUNTIF('TK 15661.Bản quyền phim '!F:F,'KK1. Movies'!AI56) | AN56: =AL56+AM56 | AT56: =IFERROR(VLOOKUP(C56, CodeRanMovies!$A:$K, 11, 0), "Not found")
A57: =_xlfn.AGGREGATE(3,3,$D$7:D57) | B57: P | C57: MOV_ANI_22__2674850 | D57: Two Buddies And A Badger: The Great Big Beast | E57: Chuyến Phiêu Lưu Trời Ơi Đất Hỡi | F57: Comedy | G57: Pro Partner | H57: 30/2025/HDBQ/VSTV-Pro Partner | I57: 2020 | J57: Norway | K57: 78 | L57: 44730 | M57: 46190 | N57: 44730 | O57: K+KIDS | P57: Non-Exclusive All TV Rights and All VOD Rights during LP | Q57: No | R57: Yes | S57: Yes | T57: Yes | U57: Yes | V57: Yes | W57: Yes | X57: Yes | Y57: Yes | Z57: 44730 | AA57: 46190 | AB57: unlimited | AC57: 38 | AD57: Yes | AE57: Yes | AG57: Phim còn hạn từ 2026 | AI57: Two Buddies and a Badger: The Great Big Beast(Chuyến Phiêu Lưu Trời Ơi Đất Hỡi) | AJ57: =SUMIF('TK 15661.Bản quyền phim '!F:F,'KK1. Movies'!D57,'TK 15661.Bản quyền phim '!X:X) | AK57: =SUMIF('TK 15661.Bản quyền phim '!F:F,'KK1. Movies'!AI57,'TK 15661.Bản quyền phim '!X:X) | AL57: =COUNTIF('242.BQ Phim hợp tác'!$C:$C,'KK1. Movies'!AI57) | AM57: =COUNTIF('TK 15661.Bản quyền phim '!F:F,'KK1. Movies'!AI57) | AN57: =AL57+AM57 | AT57: =IFERROR(VLOOKUP(C57, CodeRanMovies!$A:$K, 11, 0), "Not found")
A58: =_xlfn.AGGREGATE(3,3,$D$7:D58) | B58: n/a | C58: MOV_ACT598 | D58: Misanthrope | E58: Truy bắt sát nhân | F58: Thriller | G58: Rose | H58: 4/2025/HDBQ/VSTV-RM | I58: 2023 | J58: US | K58: 119 | L58: 45750 | M58: 46998 | N58: n/a | P58: 12 | Q58: No | R58: Yes | S58: Yes | T58: Yes | U58: Yes | V58: Yes | W58: Yes | X58: Yes | Y58: Yes | Z58: 45750 | AA58: 46998 | AB58: 24 | AC58: 3 | AD58: Yes | AE58: Yes | AG58: Phim còn hạn từ 2026 | AH58: MOV_ACT598 | AI58: Misanthrope | AJ58: =SUMIF('TK 15661.Bản quyền phim '!F:F,'KK1. Movies'!D58,'TK 15661.Bản quyền phim '!X:X) | AK58: =SUMIF('TK 15661.Bản quyền phim '!F:F,'KK1. Movies'!AI58,'TK 15661.Bản quyền phim '!X:X) | AL58: =COUNTIF('242.BQ Phim hợp tác'!$C:$C,'KK1. Movies'!AI58) | AM58: =COUNTIF('TK 15661.Bản quyền phim '!F:F,'KK1. Movies'!AI58) | AN58: =AL58+AM58 | AT58: =IFERROR(VLOOKUP(C58, CodeRanMovies!$A:$K, 11, 0), "Not found")
A59: =_xlfn.AGGREGATE(3,3,$D$7:D59) | B59: 16+ | C59: MOV_ACT__2651375 | D59: S: THE LAST POLICEMAN-RECOVERY OF OUR FUTURE | E59: Đội cảnh sát S | F59: Crime, Thriller | G59: TBS | H59: 202104013 | I59: 2015 | J59: Japan | K59: 120 | L59: 44284 | M59: 46109 | N59: 44391 | O59: K+CINE | Q59: No | R59: Yes | S59: Yes | T59: Yes | U59: Yes | V59: Yes | W59: Yes | X59: Yes | Y59: Yes | Z59: 44284 | AA59: 46109 | AB59: 50 | AC59: 38 | AD59: Yes | AE59: Yes | AG59: Phim còn hạn từ 2026 | AI59: S: THE LAST POLICEMAN-Recovery of Our Future- | AJ59: =SUMIF('TK 15661.Bản quyền phim '!F:F,'KK1. Movies'!D59,'TK 15661.Bản quyền phim '!X:X) | AK59: =SUMIF('TK 15661.Bản quyền phim '!F:F,'KK1. Movies'!AI59,'TK 15661.Bản quyền phim '!X:X) | AL59: =COUNTIF('242.BQ Phim hợp tác'!$C:$C,'KK1. Movies'!AI59) | AM59: =COUNTIF('TK 15661.Bản quyền phim '!F:F,'KK1. Movies'!AI59) | AN59: =AL59+AM59 | AT59: =IFERROR(VLOOKUP(C59, CodeRanMovies!$A:$K, 11, 0), "Not found")
A60: =_xlfn.AGGREGATE(3,3,$D$7:D60) | B60: n/a | C60: MOV_CRI111 | D60: Longlegs | E60: Thảm kịch dị giáo | F60: Horror | G60: Mocking Bird | H60: 10/2025/HDBQ/VSTV-Mockingbird | I60: 2024 | J60: Korea | K60: 101 | L60: 45751 | M60: 46846 | N60: n/a | Q60: No | R60: Yes | S60: Yes | T60: Yes | U60: Yes | V60: Yes | W60: Yes | X60: Yes | Y60: Yes | Z60: 45948 | AA60: 47043 | AB60: 24 | AC60: 3 | AD60: Yes | AE60: Yes | AG60: Phim còn hạn từ 2026 | AH60: MOV_CRI111 | AI60: Longlegs | AJ60: =SUMIF('TK 15661.Bản quyền phim '!F:F,'KK1. Movies'!D60,'TK 15661.Bản quyền phim '!X:X) | AK60: =SUMIF('TK 15661.Bản quyền phim '!F:F,'KK1. Movies'!AI60,'TK 15661.Bản quyền phim '!X:X) | AL60: =COUNTIF('242.BQ Phim hợp tác'!$C:$C,'KK1. Movies'!AI60) | AM60: =COUNTIF('TK 15661.Bản quyền phim '!F:F,'KK1. Movies'!AI60) | AN60: =AL60+AM60 | AT60: =IFERROR(VLOOKUP(C60, CodeRanMovies!$A:$K, 11, 0), "Not found")
A61: =_xlfn.AGGREGATE(3,3,$D$7:D61) | B61: 13+ | C61: MOV_DRA727 | D61: DEAR EVAN HANSEN | E61: Evan Hansen thân mến | F61: Drama | G61: NBC Universal | H61: 5049540-2/161434-3 | I61: 2021 | J61: US | K61: 137 | L61: 45623 | M61: 46352 | N61: 45623 | O61: K+CINE | P61: 12 | Q61: No | R61: Yes | S61: Yes | T61: Yes | U61: No | V61: No | W61: No | X61: No | Y61: Yes | Z61: 45623 | AA61: 46352 | AB61: 6 | AC61: 2 | AD61: Yes | AE61: Yes | AG61: Phim còn hạn từ 2026 | AI61: DEAR EVAN HANSEN | AJ61: =SUMIF('TK 15661.Bản quyền phim '!F:F,'KK1. Movies'!D61,'TK 15661.Bản quyền phim '!X:X) | AK61: =SUMIF('TK 15661.Bản quyền phim '!F:F,'KK1. Movies'!AI61,'TK 15661.Bản quyền phim '!X:X) | AL61: =COUNTIF('242.BQ Phim hợp tác'!$C:$C,'KK1. Movies'!AI61) | AM61: =COUNTIF('TK 15661.Bản quyền phim '!F:F,'KK1. Movies'!AI61) | AN61: =AL61+AM61 | AT61: =IFERROR(VLOOKUP(C61, CodeRanMovies!$A:$K, 11, 0), "Not found")
A62: =_xlfn.AGGREGATE(3,3,$D$7:D62) | B62: 16+ | C62: MOV_ACT_22__2686484 | D62: Sicario: Day of the Soldado | E62: Chiến binh Mexico | F62: Action, Adventure | G62: Pro Partner | H62: 56/2023/HDBQ/VSTV-Pro Partner | I62: 2018 | J62: US | K62: 122 | L62: 44960 | M62: 46055 | N62: 44960 | O62: K+CINE | P62: Exclusive All TV Rights the first 9 months of LP Non-exclusive with All Catch-up TV Rights; All VOD Rights during LP | Q62: No | R62: Yes | S62: Yes | T62: Yes | U62: Yes | V62: Yes | W62: Yes | X62: Yes | Y62: Yes | Z62: 44960 | AA62: 46055 | AB62: unlimited | AC62: 31 | AD62: Yes | AE62: Yes | AG62: Phim còn hạn từ 2026 | AI62: Sicario: Day of the Soldado | AJ62: =SUMIF('TK 15661.Bản quyền phim '!F:F,'KK1. Movies'!D62,'TK 15661.Bản quyền phim '!X:X) | AK62: =SUMIF('TK 15661.Bản quyền phim '!F:F,'KK1. Movies'!AI62,'TK 15661.Bản quyền phim '!X:X) | AL62: =COUNTIF('242.BQ Phim hợp tác'!$C:$C,'KK1. Movies'!AI62) | AM62: =COUNTIF('TK 15661.Bản quyền phim '!F:F,'KK1. Movies'!AI62) | AN62: =AL62+AM62 | AT62: =IFERROR(VLOOKUP(C62, CodeRanMovies!$A:$K, 11, 0), "Not found")
A63: =_xlfn.AGGREGATE(3,3,$D$7:D63) | B63: 16+ | C63: MOV_CRI_24__2710436 | D63: DEATH NOTICE | E63: Bản thông báo tử vong | F63: Crime, Thriller | G63: Skyline Media | H63: 28/2024/HDBQ/VSTV-SM | I63: 2023 | J63: Hong Kong | K63: 100 | L63: 45352 | M63: 46446 | N63: 45554 | O63: K+CINE | P63: 12 | Q63: No | R63: Yes | S63: Yes | T63: Yes | U63: Yes | V63: Yes | W63: Yes | X63: Yes | Y63: No | Z63: 45352 | AA63: 46446 | AB63: 24 | AC63: 15 | AD63: Yes | AE63: Yes | AG63: Phim còn hạn từ 2026 | AI63: DEATH NOTICE | AJ63: =SUMIF('TK 15661.Bản quyền phim '!F:F,'KK1. Movies'!D63,'TK 15661.Bản quyền phim '!X:X) | AK63: =SUMIF('TK 15661.Bản quyền phim '!F:F,'KK1. Movies'!AI63,'TK 15661.Bản quyền phim '!X:X) | AL63: =COUNTIF('242.BQ Phim hợp tác'!$C:$C,'KK1. Movies'!AI63) | AM63: =COUNTIF('TK 15661.Bản quyền phim '!F:F,'KK1. Movies'!AI63) | AN63: =AL63+AM63 | AT63: =IFERROR(VLOOKUP(C63, CodeRanMovies!$A:$K, 11, 0), "Not found")
A64: =_xlfn.AGGREGATE(3,3,$D$7:D64) | B64: 16+ | C64: MOV_DRA_23__2694714 | D64: MY GIRL | E64: Điều ước cuối của tù nhân 2037 | F64: Drama | G64: CJ HK | H64: 135/2022/HDBQ/VSTV-CJHK | I64: 2022 | J64: Korea | K64: 111 | L64: 45190 | M64: 46285 | N64: 45190 | O64: K+CINE | P64: 12 | Q64: No | R64: Yes | S64: Yes | T64: Yes | U64: Yes | V64: Yes | W64: Yes | X64: No | Y64: Yes | Z64: 45190 | AA64: 46285 | AB64: unlimited | AC64: 26 | AD64: Yes | AE64: Yes | AG64: Phim còn hạn từ 2026 | AI64: MY GIRL (Điều ước cuối của tù nhân 2037) | AJ64: =SUMIF('TK 15661.Bản quyền phim '!F:F,'KK1. Movies'!D64,'TK 15661.Bản quyền phim '!X:X) | AK64: =SUMIF('TK 15661.Bản quyền phim '!F:F,'KK1. Movies'!AI64,'TK 15661.Bản quyền phim '!X:X) | AL64: =COUNTIF('242.BQ Phim hợp tác'!$C:$C,'KK1. Movies'!AI64) | AM64: =COUNTIF('TK 15661.Bản quyền phim '!F:F,'KK1. Movies'!AI64) | AN64: =AL64+AM64 | AT64: =IFERROR(VLOOKUP(C64, CodeRanMovies!$A:$K, 11, 0), "Not found")
A65: =_xlfn.AGGREGATE(3,3,$D$7:D65) | B65: 13+ | C65: MOV_ROM99 | D65: ONE WEEK FRIENDS | E65: Người bạn một tuần | F65: Drama/Youth | G65: STK | H65: 134/2024/HDBQ/VSTV-STK | I65: 2022 | J65: China | K65: 106 | L65: 45693 | M65: 46787 | N65: 45693 | P65: 12 | Q65: No | R65: Yes | S65: Yes | T65: Yes | U65: Yes | V65: Yes | W65: Yes | X65: Yes | Y65: Yes | Z65: 45778 | AA65: 46873 | AB65: 24 | AC65: 5 | AD65: Yes | AE65: Yes | AG65: Phim còn hạn từ 2026 | AI65: ONE WEEK FRIENDS | AJ65: =SUMIF('TK 15661.Bản quyền phim '!F:F,'KK1. Movies'!D65,'TK 15661.Bản quyền phim '!X:X) | AK65: =SUMIF('TK 15661.Bản quyền phim '!F:F,'KK1. Movies'!AI65,'TK 15661.Bản quyền phim '!X:X) | AL65: =COUNTIF('242.BQ Phim hợp tác'!$C:$C,'KK1. Movies'!AI65) | AM65: =COUNTIF('TK 15661.Bản quyền phim '!F:F,'KK1. Movies'!AI65) | AN65: =AL65+AM65 | AT65: =IFERROR(VLOOKUP(C65, CodeRanMovies!$A:$K, 11, 0), "Not found")
A66: =_xlfn.AGGREGATE(3,3,$D$7:D66) | B66: n/a | C66: MOV_BIO25 | D66: MARSHALL | E66: Thẩm phán Marshall | F66: Drama | G66: SONY | H66: Sony/K+Vietnam PayBasic SVOD Package Agmt D3A FE (Feb-5-24) | I66: 2017 | J66: U.S.A.[excluding Territories & Possessions] | K66: 118 | L66: 45747 | M66: 46485 | Q66: No | R66: Yes | S66: Yes | T66: Yes | U66: No | V66: No | W66: No | X66: Yes | Y66: No | Z66: 45747 | AA66: 46303 | AB66: 7 | AC66: 1 | AD66: Yes | AE66: Yes | AG66: Phim còn hạn từ 2026 | AI66: MARSHALL | AJ66: =SUMIF('TK 15661.Bản quyền phim '!F:F,'KK1. Movies'!D66,'TK 15661.Bản quyền phim '!X:X) | AK66: =SUMIF('TK 15661.Bản quyền phim '!F:F,'KK1. Movies'!AI66,'TK 15661.Bản quyền phim '!X:X) | AL66: =COUNTIF('242.BQ Phim hợp tác'!$C:$C,'KK1. Movies'!AI66) | AM66: =COUNTIF('TK 15661.Bản quyền phim '!F:F,'KK1. Movies'!AI66) | AN66: =AL66+AM66 | AT66: =IFERROR(VLOOKUP(C66, CodeRanMovies!$A:$K, 11, 0), "Not found")
A67: =_xlfn.AGGREGATE(3,3,$D$7:D67) | B67: 13+ | C67: MOV_DRA_24__2710431 | D67: LAST NIGHT | E67: Đêm tình cuối | F67: Romance | G67: Skyline Media | H67: 28/2024/HDBQ/VSTV-SM | I67: 2010 | J67: US | K67: 93 | L67: 45323 | M67: 46418 | N67: 45542 | O67: K+CINE | P67: 12 | Q67: No | R67: Yes | S67: Yes | T67: Yes | U67: Yes | V67: Yes | W67: Yes | X67: Yes | Y67: No | Z67: 45323 | AA67: 46418 | AB67: 24 | AC67: 11 | AD67: Yes | AE67: Yes | AG67: Phim còn hạn từ 2026 | AI67: LAST NIGHT | AJ67: =SUMIF('TK 15661.Bản quyền phim '!F:F,'KK1. Movies'!D67,'TK 15661.Bản quyền phim '!X:X) | AK67: =SUMIF('TK 15661.Bản quyền phim '!F:F,'KK1. Movies'!AI67,'TK 15661.Bản quyền phim '!X:X) | AL67: =COUNTIF('242.BQ Phim hợp tác'!$C:$C,'KK1. Movies'!AI67) | AM67: =COUNTIF('TK 15661.Bản quyền phim '!F:F,'KK1. Movies'!AI67) | AN67: =AL67+AM67 | AT67: =IFERROR(VLOOKUP(C67, CodeRanMovies!$A:$K, 11, 0), "Not found")
A68: =_xlfn.AGGREGATE(3,3,$D$7:D68) | B68: n/a | C68: MOV_CRI112 | D68: Woman Of The Hour | E68: Hẹn hò với sát nhân | F68: Crime, Thriller | G68: Mocking Bird | H68: 10/2025/HDBQ/VSTV-Mockingbird | I68: 2024 | J68: US | K68: 95 | L68: 45757 | M68: 46852 | N68: n/a | Q68: No | R68: Yes | S68: Yes | T68: Yes | U68: Yes | V68: Yes | W68: Yes | X68: Yes | Y68: Yes | Z68: 45757 | AA68: 46852 | AB68: 24 | AC68: 3 | AD68: Yes | AE68: Yes | AG68: Phim còn hạn từ 2026 | AI68: The Women Of The Hour | AJ68: =SUMIF('TK 15661.Bản quyền phim '!F:F,'KK1. Movies'!D68,'TK 15661.Bản quyền phim '!X:X) | AK68: =SUMIF('TK 15661.Bản quyền phim '!F:F,'KK1. Movies'!AI68,'TK 15661.Bản quyền phim '!X:X) | AL68: =COUNTIF('242.BQ Phim hợp tác'!$C:$C,'KK1. Movies'!AI68) | AM68: =COUNTIF('TK 15661.Bản quyền phim '!F:F,'KK1. Movies'!AI68) | AN68: =AL68+AM68 | AT68: =IFERROR(VLOOKUP(C68, CodeRanMovies!$A:$K, 11, 0), "Not found")
A69: =_xlfn.AGGREGATE(3,3,$D$7:D69) | B69: 16+ | C69: MOV_DRA_24__2712649 | D69: PHANTOM THREAD | E69: Bóng ma sợi chỉ | F69: drama | G69: NBC Universal | H69: 5049540-2/161434-3 | I69: 2017 | J69: US | K69: 115 | L69: 45359 | M69: 46088 | N69: 45359 | O69: K+CINE | Q69: No | R69: Yes | S69: Yes | T69: Yes | U69: No | V69: No | W69: No | X69: No | Y69: Yes | Z69: 45359 | AA69: 46088 | AB69: 6 | AC69: 4 | AD69: Yes | AE69: Yes | AG69: Phim còn hạn từ 2026 | AI69: PHANTOM THREAD | AJ69: =SUMIF('TK 15661.Bản quyền phim '!F:F,'KK1. Movies'!D69,'TK 15661.Bản quyền phim '!X:X) | AK69: =SUMIF('TK 15661.Bản quyền phim '!F:F,'KK1. Movies'!AI69,'TK 15661.Bản quyền phim '!X:X) | AL69: =COUNTIF('242.BQ Phim hợp tác'!$C:$C,'KK1. Movies'!AI69) | AM69: =COUNTIF('TK 15661.Bản quyền phim '!F:F,'KK1. Movies'!AI69) | AN69: =AL69+AM69 | AT69: =IFERROR(VLOOKUP(C69, CodeRanMovies!$A:$K, 11, 0), "Not found")
A70: =_xlfn.AGGREGATE(3,3,$D$7:D70) | B70: n/a | C70: MOV_ACT608 | D70: ELYSIUM | E70: Kỷ nguyên Elysium | F70: Action, Adventure | G70: SONY | H70: Sony/K+Vietnam PayBasic SVOD Package Agmt D3A FE (Feb-5-24) | I70: 2013 | J70: U.S.A.[excluding Territories & Possessions] | K70: 109 | L70: 45747 | M70: 46492 | Q70: No | R70: Yes | S70: Yes | T70: Yes | U70: No | V70: No | W70: No | X70: Yes | Y70: No | Z70: 45747 | AA70: 46310 | AB70: 7 | AC70: 1 | AD70: Yes | AE70: Yes | AG70: Phim còn hạn từ 2026 | AI70: ELYSIUM | AJ70: =SUMIF('TK 15661.Bản quyền phim '!F:F,'KK1. Movies'!D70,'TK 15661.Bản quyền phim '!X:X) | AK70: =SUMIF('TK 15661.Bản quyền phim '!F:F,'KK1. Movies'!AI70,'TK 15661.Bản quyền phim '!X:X) | AL70: =COUNTIF('242.BQ Phim hợp tác'!$C:$C,'KK1. Movies'!AI70) | AM70: =COUNTIF('TK 15661.Bản quyền phim '!F:F,'KK1. Movies'!AI70) | AN70: =AL70+AM70 | AT70: =IFERROR(VLOOKUP(C70, CodeRanMovies!$A:$K, 11, 0), "Not found")
A71: =_xlfn.AGGREGATE(3,3,$D$7:D71) | B71: 16+ | C71: MOV_HOR_22__2686491 | D71: Countdown | E71: Ứng dụng tử thần | F71: Horror | G71: Pro Partner | H71: 56/2023/HDBQ/VSTV-Pro Partner | I71: 2019 | J71: US | K71: 90 | L71: 45014 | M71: 46109 | N71: 45014 | O71: K+CINE | P71: Exclusive All TV Rights the first 9 months of LP Non-exclusive with All Catch-up TV Rights; All VOD Rights during LP | Q71: No | R71: Yes | S71: Yes | T71: Yes | U71: Yes | V71: Yes | W71: Yes | X71: Yes | Y71: Yes | Z71: 45014 | AA71: 46109 | AB71: unlimited | AC71: 32 | AD71: Yes | AE71: Yes | AG71: Phim còn hạn từ 2026 | AI71: Countdown (US) | AJ71: =SUMIF('TK 15661.Bản quyền phim '!F:F,'KK1. Movies'!D71,'TK 15661.Bản quyền phim '!X:X) | AK71: =SUMIF('TK 15661.Bản quyền phim '!F:F,'KK1. Movies'!AI71,'TK 15661.Bản quyền phim '!X:X) | AL71: =COUNTIF('242.BQ Phim hợp tác'!$C:$C,'KK1. Movies'!AI71) | AM71: =COUNTIF('TK 15661.Bản quyền phim '!F:F,'KK1. Movies'!AI71) | AN71: =AL71+AM71 | AT71: =IFERROR(VLOOKUP(C71, CodeRanMovies!$A:$K, 11, 0), "Not found")
A72: =_xlfn.AGGREGATE(3,3,$D$7:D72) | B72: 16+ | C72: MOV_DRA_23__2698013 | D72: The woman who ran | E72: Người phụ nữ bỏ trốn | F72: Drama | G72: King Content | H72: 52/2023/HDBQ/VSTV-KC | I72: 2020 | J72: Korea | K72: 77 | L72: 45147 | M72: 46242 | N72: 45148 | O72: K+CINE | P72: Exclusive All PayTV rights and Non-Exclusive VOD rights | Q72: Yes | R72: Yes | S72: No | T72: Yes | U72: Yes | V72: Yes | W72: Yes | X72: Yes | Y72: No | Z72: 45147 | AA72: 46242 | AB72: unlimited | AC72: 23 | AD72: Yes | AE72: Yes | AG72: Phim còn hạn từ 2026 | AI72: The woman who ran away | AJ72: =SUMIF('TK 15661.Bản quyền phim '!F:F,'KK1. Movies'!D72,'TK 15661.Bản quyền phim '!X:X) | AK72: =SUMIF('TK 15661.Bản quyền phim '!F:F,'KK1. Movies'!AI72,'TK 15661.Bản quyền phim '!X:X) | AL72: =COUNTIF('242.BQ Phim hợp tác'!$C:$C,'KK1. Movies'!AI72) | AM72: =COUNTIF('TK 15661.Bản quyền phim '!F:F,'KK1. Movies'!AI72) | AN72: =AL72+AM72 | AT72: =IFERROR(VLOOKUP(C72, CodeRanMovies!$A:$K, 11, 0), "Not found")
A73: =_xlfn.AGGREGATE(3,3,$D$7:D73) | B73: 13+ | C73: MOV_ADV_22__2686513 | D73: Arctic | E73: Bắc cực | F73: Drama | G73: Skyline Media | H73: 66/2023/HDBQ/VSTV-SM | I73: 2018 | J73: Iceland | K73: 98 | L73: 45065 | M73: 46160 | N73: 45120 | O73: K+CINE | P73: Exclusive All TV Rights the first 12 months of LP Non-exclusive with All Catch-up TV Rights; All VOD Rights during LP | Q73: No | R73: Yes | S73: Yes | T73: Yes | U73: Yes | V73: Yes | W73: Yes | X73: Yes | Y73: Yes | Z73: 45065 | AA73: 46160 | AB73: 24 | AC73: 12 | AD73: Yes | AE73: Yes | AG73: Phim còn hạn từ 2026 | AI73: Arctic | AJ73: =SUMIF('TK 15661.Bản quyền phim '!F:F,'KK1. Movies'!D73,'TK 15661.Bản quyền phim '!X:X) | AK73: =SUMIF('TK 15661.Bản quyền phim '!F:F,'KK1. Movies'!AI73,'TK 15661.Bản quyền phim '!X:X) | AL73: =COUNTIF('242.BQ Phim hợp tác'!$C:$C,'KK1. Movies'!AI73) | AM73: =COUNTIF('TK 15661.Bản quyền phim '!F:F,'KK1. Movies'!AI73) | AN73: =AL73+AM73 | AT73: =IFERROR(VLOOKUP(C73, CodeRanMovies!$A:$K, 11, 0), "Not found")
A74: =_xlfn.AGGREGATE(3,3,$D$7:D74) | B74: 13+ | C74: MOV_ACT_24__2713785 | D74: BRAVEST, THE (2019) | E74: Liệt hỏa anh hùng | F74: Action, Adventure | G74: SONY PICTURES | H74: Sony/K+Vietnam PayBasic SVOD Package Agmt D2D per JK (19-01-2024) | I74: 2019 | J74: China | K74: 118 | L74: 45382 | M74: 46476 | N74: 45434 | O74: K+ACTION | Q74: No | R74: Yes | S74: Yes | T74: Yes | U74: No | V74: No | W74: No | X74: No | Y74: No | Z74: 45747 | AA74: 46294 | AB74: 7 | AC74: 3 | AD74: Yes | AE74: Yes | AG74: Phim còn hạn từ 2026 | AI74: BRAVEST, THE (2019) | AJ74: =SUMIF('TK 15661.Bản quyền phim '!F:F,'KK1. Movies'!D74,'TK 15661.Bản quyền phim '!X:X) | AK74: =SUMIF('TK 15661.Bản quyền phim '!F:F,'KK1. Movies'!AI74,'TK 15661.Bản quyền phim '!X:X) | AL74: =COUNTIF('242.BQ Phim hợp tác'!$C:$C,'KK1. Movies'!AI74) | AM74: =COUNTIF('TK 15661.Bản quyền phim '!F:F,'KK1. Movies'!AI74) | AN74: =AL74+AM74 | AT74: =IFERROR(VLOOKUP(C74, CodeRanMovies!$A:$K, 11, 0), "Not found")
A75: =_xlfn.AGGREGATE(3,3,$D$7:D75) | B75: 16+ | C75: MOV_ACT588 | D75: RIDE ALONG 2 | E75: Bộ đôi cảnh sát 2 | F75: Action, Adventure | G75: NBC Universal | H75: 5049540-2/161434-3 | I75: 2016 | J75: US | K75: 101 | L75: 45590 | M75: 46319 | N75: 45593 | O75: K+CINE | P75: Non exclusive | Q75: No | R75: Yes | S75: Yes | T75: Yes | U75: No | V75: No | W75: No | X75: No | Y75: Yes | Z75: 45590 | AA75: 46319 | AB75: 6 | AC75: 3 | AD75: Yes | AE75: Yes | AG75: Phim còn hạn từ 2026 | AI75: RIDE ALONG 2 | AJ75: =SUMIF('TK 15661.Bản quyền phim '!F:F,'KK1. Movies'!D75,'TK 15661.Bản quyền phim '!X:X) | AK75: =SUMIF('TK 15661.Bản quyền phim '!F:F,'KK1. Movies'!AI75,'TK 15661.Bản quyền phim '!X:X) | AL75: =COUNTIF('242.BQ Phim hợp tác'!$C:$C,'KK1. Movies'!AI75) | AM75: =COUNTIF('TK 15661.Bản quyền phim '!F:F,'KK1. Movies'!AI75) | AN75: =AL75+AM75 | AT75: =IFERROR(VLOOKUP(C75, CodeRanMovies!$A:$K, 11, 0), "Not found")
A76: =_xlfn.AGGREGATE(3,3,$D$7:D76) | B76: 13+ | C76: MOV_COM_22__2686870 | D76: LOVE AGAIN | E76: Chồng cũ, tình mới | F76: Romance | G76: CJ HK | H76: 135/2022/HDBQ/VSTV-CJHK | I76: 2019 | J76: Korea | K76: 112 | L76: 44966 | M76: 46061 | N76: 44966 | O76: K+CINE | P76: 12 | Q76: No | R76: Yes | S76: Yes | T76: Yes | U76: Yes | V76: Yes | W76: Yes | X76: No | Y76: Yes | Z76: 44966 | AA76: 46061 | AB76: unlimited | AC76: 28 | AD76: Yes | AE76: Yes | AG76: Phim còn hạn từ 2026 | AI76: LOVE AGAIN (Chồng cũ tình mới) | AJ76: =SUMIF('TK 15661.Bản quyền phim '!F:F,'KK1. Movies'!D76,'TK 15661.Bản quyền phim '!X:X) | AK76: =SUMIF('TK 15661.Bản quyền phim '!F:F,'KK1. Movies'!AI76,'TK 15661.Bản quyền phim '!X:X) | AL76: =COUNTIF('242.BQ Phim hợp tác'!$C:$C,'KK1. Movies'!AI76) | AM76: =COUNTIF('TK 15661.Bản quyền phim '!F:F,'KK1. Movies'!AI76) | AN76: =AL76+AM76 | AT76: =IFERROR(VLOOKUP(C76, CodeRanMovies!$A:$K, 11, 0), "Not found")
A77: =_xlfn.AGGREGATE(3,3,$D$7:D77) | B77: 16+ | C77: MOV_COM290 | D77: THE ROYAL BRIDE | E77: GÁI GIÀ LẮM CHIÊU 3 | F77: Comedy, Romace | G77: Skyline Media | H77: 36/2025/HDBQ/VSTV-SM | I77: 2020 | J77: Việt Nam | K77: 120 | L77: 45686 | M77: 46780 | N77: 45686 | P77: 0 | Q77: No | R77: Yes | S77: Yes | T77: Yes | U77: Yes | V77: Yes | W77: Yes | X77: Yes | Y77: No | Z77: 45686 | AA77: 46780 | AB77: 24 | AC77: 6 | AD77: Yes | AE77: Yes | AG77: Phim còn hạn từ 2026 | AI77: THE ROYAL BRIDE (GÁI GIÀ LẮM CHIÊU 3) | AJ77: =SUMIF('TK 15661.Bản quyền phim '!F:F,'KK1. Movies'!D77,'TK 15661.Bản quyền phim '!X:X) | AK77: =SUMIF('TK 15661.Bản quyền phim '!F:F,'KK1. Movies'!AI77,'TK 15661.Bản quyền phim '!X:X) | AL77: =COUNTIF('242.BQ Phim hợp tác'!$C:$C,'KK1. Movies'!AI77) | AM77: =COUNTIF('TK 15661.Bản quyền phim '!F:F,'KK1. Movies'!AI77) | AN77: =AL77+AM77 | AT77: =IFERROR(VLOOKUP(C77, CodeRanMovies!$A:$K, 11, 0), "Not found")
A78: =_xlfn.AGGREGATE(3,3,$D$7:D78) | B78: 16+ | C78: MOV_COM_23__2697133 | D78: More Than Family | E78: Mẹ bầu siêu ngầu | F78: Drama | G78: Roses Media | H78: 140/2022/HDBQ/VSTV-RM | I78: 2020 | J78: Korea | K78: 108 | L78: 45274 | M78: 46369 | N78: 45274 | O78: K+CINE | P78: Exclusive All Pay TV Rights for first 12 months. Non exclusive All VOD during LP | Q78: No | R78: Yes | S78: No | T78: Yes | U78: Yes | V78: Yes | W78: Yes | X78: Yes | Y78: No | Z78: 45274 | AA78: 46369 | AB78: 24 | AC78: 9 | AD78: Yes | AE78: Yes | AG78: Phim còn hạn từ 2026 | AH78: MOV_COM_23__2697133 | AI78: More Than Family | AJ78: =SUMIF('TK 15661.Bản quyền phim '!F:F,'KK1. Movies'!D78,'TK 15661.Bản quyền phim '!X:X) | AK78: =SUMIF('TK 15661.Bản quyền phim '!F:F,'KK1. Movies'!AI78,'TK 15661.Bản quyền phim '!X:X) | AL78: =COUNTIF('242.BQ Phim hợp tác'!$C:$C,'KK1. Movies'!AI78) | AM78: =COUNTIF('TK 15661.Bản quyền phim '!F:F,'KK1. Movies'!AI78) | AN78: =AL78+AM78 | AT78: =IFERROR(VLOOKUP(C78, CodeRanMovies!$A:$K, 11, 0), "Not found")
A79: =_xlfn.AGGREGATE(3,3,$D$7:D79) | B79: n/a | C79: MOV_ACT610 | D79: Good Job | E79: Đối tác hoàn hảo | F79: Drama | G79: Mocking Bird | H79: 10/2025/HDBQ/VSTV-Mockingbird | I79: 2024 | J79: Korea | K79: 95 | L79: 45764 | M79: 46859 | N79: n/a | Q79: No | R79: Yes | S79: Yes | T79: Yes | U79: Yes | V79: Yes | W79: Yes | X79: Yes | Y79: Yes | Z79: 45765 | AA79: 46860 | AB79: 24 | AC79: 3 | AD79: Yes | AE79: Yes | AG79: Phim còn hạn từ 2026 | AI79: Good Job (Movie-KOR) | AJ79: =SUMIF('TK 15661.Bản quyền phim '!F:F,'KK1. Movies'!D79,'TK 15661.Bản quyền phim '!X:X) | AK79: =SUMIF('TK 15661.Bản quyền phim '!F:F,'KK1. Movies'!AI79,'TK 15661.Bản quyền phim '!X:X) | AL79: =COUNTIF('242.BQ Phim hợp tác'!$C:$C,'KK1. Movies'!AI79) | AM79: =COUNTIF('TK 15661.Bản quyền phim '!F:F,'KK1. Movies'!AI79) | AN79: =AL79+AM79 | AT79: =IFERROR(VLOOKUP(C79, CodeRanMovies!$A:$K, 11, 0), "Not found")
A80: =_xlfn.AGGREGATE(3,3,$D$7:D80) | B80: 16+ | C80: MOV_ACT_24__2714420 | D80: The Age of Blood | E80: Thời Kỳ Phiến Loạn | F80: action | G80: Hỏa Thổ | H80: 25A/2024/HDBQ/VSTV-Hoa tho | I80: 2017 | J80: Korea | K80: 102 | L80: 45414 | M80: 46508 | N80: 45415 | O80: K+CINE | Q80: No | R80: Yes | S80: Yes | T80: Yes | U80: Yes | V80: Yes | W80: Yes | X80: No | Y80: No | Z80: 45414 | AA80: 46508 | AB80: Unlimited run | AC80: 19 | AD80: Yes | AE80: Yes | AG80: Phim còn hạn từ 2026 | AI80: The Age of Blood (Thời Kỳ Phiến Loạn) | AJ80: =SUMIF('TK 15661.Bản quyền phim '!F:F,'KK1. Movies'!D80,'TK 15661.Bản quyền phim '!X:X) | AK80: =SUMIF('TK 15661.Bản quyền phim '!F:F,'KK1. Movies'!AI80,'TK 15661.Bản quyền phim '!X:X) | AL80: =COUNTIF('242.BQ Phim hợp tác'!$C:$C,'KK1. Movies'!AI80) | AM80: =COUNTIF('TK 15661.Bản quyền phim '!F:F,'KK1. Movies'!AI80) | AN80: =AL80+AM80 | AT80: =IFERROR(VLOOKUP(C80, CodeRanMovies!$A:$K, 11, 0), "Not found")
A81: =_xlfn.AGGREGATE(3,3,$D$7:D81) | B81: 13+ | C81: MOV_BIO_24__2713783 | D81: A BEAUTIFUL DAY IN THE NEIGHBORHOOD | E81: Một ngày đẹp đẽ trong khu phố | F81: Drama | G81: SONY PICTURES | H81: Sony/K+Vietnam PayBasic SVOD Package Agmt D2D per JK (19-01-2024) | I81: 2019 | J81: US | K81: 108 | L81: 45382 | M81: 46111 | N81: 45427 | O81: K+CINE | Q81: No | R81: Yes | S81: Yes | T81: Yes | U81: No | V81: No | W81: No | X81: No | Y81: No | Z81: 45382 | AA81: 46111 | AB81: 7 | AC81: 4 | AD81: Yes | AE81: Yes | AG81: Phim còn hạn từ 2026 | AH81: MOV_BIO_24__2713783 | AI81: BEAUTIFUL DAY IN THE NEIGHBORHOOD, A | AJ81: =SUMIF('TK 15661.Bản quyền phim '!F:F,'KK1. Movies'!D81,'TK 15661.Bản quyền phim '!X:X) | AK81: =SUMIF('TK 15661.Bản quyền phim '!F:F,'KK1. Movies'!AI81,'TK 15661.Bản quyền phim '!X:X) | AL81: =COUNTIF('242.BQ Phim hợp tác'!$C:$C,'KK1. Movies'!AI81) | AM81: =COUNTIF('TK 15661.Bản quyền phim '!F:F,'KK1. Movies'!AI81) | AN81: =AL81+AM81 | AT81: =IFERROR(VLOOKUP(C81, CodeRanMovies!$A:$K, 11, 0), "Not found")
A82: =_xlfn.AGGREGATE(3,3,$D$7:D82) | B82: 16+ | C82: MOV_ACT576 | D82: HANNA (2011) | E82: Hanna bí ẩn | F82: Action, Adventure | G82: SONY PICTURES | H82: Sony/K+Vietnam PayBasic SVOD Package Agmt D2D per JK (19-01-2024) | I82: 2011 | J82: Germany;United Kingdom | K82: 110 | L82: 45505 | M82: 46234 | N82: 45540 | O82: K+ACTION | Q82: No | R82: Yes | S82: Yes | T82: Yes | U82: No | V82: No | W82: No | X82: No | Y82: No | Z82: 45505 | AA82: 46053 | AB82: 7 | AC82: 3 | AD82: Yes | AE82: Yes | AG82: Phim còn hạn từ 2026 | AI82: HANNA (2011) | AJ82: =SUMIF('TK 15661.Bản quyền phim '!F:F,'KK1. Movies'!D82,'TK 15661.Bản quyền phim '!X:X) | AK82: =SUMIF('TK 15661.Bản quyền phim '!F:F,'KK1. Movies'!AI82,'TK 15661.Bản quyền phim '!X:X) | AL82: =COUNTIF('242.BQ Phim hợp tác'!$C:$C,'KK1. Movies'!AI82) | AM82: =COUNTIF('TK 15661.Bản quyền phim '!F:F,'KK1. Movies'!AI82) | AN82: =AL82+AM82 | AT82: =IFERROR(VLOOKUP(C82, CodeRanMovies!$A:$K, 11, 0), "Not found")
A83: =_xlfn.AGGREGATE(3,3,$D$7:D83) | B83: 13+ | C83: MOV_ROM_22__2686497 | D83: My Love | E83: Hôn lễ của em | F83: Romance | G83: Pro Partner | H83: 56/2023/HDBQ/VSTV-Pro Partner | I83: 2021 | J83: China | K83: 115 | L83: 45051 | M83: 46146 | N83: 45051 | O83: K+CINE | P83: Exclusive All TV Rights the first 9 months of LP Non-exclusive with All Catch-up TV Rights; All VOD Rights during LP | Q83: No | R83: Yes | S83: Yes | T83: Yes | U83: Yes | V83: Yes | W83: Yes | X83: Yes | Y83: Yes | Z83: 45051 | AA83: 46146 | AB83: unlimited | AC83: 26 | AD83: Yes | AE83: Yes | AG83: Phim còn hạn từ 2026 | AI83: My Love | AJ83: =SUMIF('TK 15661.Bản quyền phim '!F:F,'KK1. Movies'!D83,'TK 15661.Bản quyền phim '!X:X) | AK83: =SUMIF('TK 15661.Bản quyền phim '!F:F,'KK1. Movies'!AI83,'TK 15661.Bản quyền phim '!X:X) | AL83: =COUNTIF('242.BQ Phim hợp tác'!$C:$C,'KK1. Movies'!AI83) | AM83: =COUNTIF('TK 15661.Bản quyền phim '!F:F,'KK1. Movies'!AI83) | AN83: =AL83+AM83 | AT83: =IFERROR(VLOOKUP(C83, CodeRanMovies!$A:$K, 11, 0), "Not found")
A84: =_xlfn.AGGREGATE(3,3,$D$7:D84) | B84: P | C84: MOV_ANI_23__2698581 | D84: Paws of Fury: The Legend of Hank | E84: Môn phái Võ Mèo: Huyền thoại một chú chó | F84: Comedy | G84: Roses Media | H84: 82/2023/HDBQ/VSTV-Roses Media | I84: 2022 | J84: US | K84: 98 | L84: 45157 | M84: 46252 | N84: 45157 | O84: K+KIDS | P84: Exclusive All Pay TV Rights for first 12 months. Non exclusive All VOD during LP | Q84: No | R84: Yes | S84: Yes | T84: Yes | U84: Yes | V84: Yes | W84: Yes | X84: Yes | Y84: No | Z84: 45170 | AA84: 46252 | AB84: 24 | AC84: 21 | AD84: Yes | AE84: Yes | AG84: Phim còn hạn từ 2026 | AI84: Blazing Samurai/ Paws of Fury: The Legend of Hank | AJ84: =SUMIF('TK 15661.Bản quyền phim '!F:F,'KK1. Movies'!D84,'TK 15661.Bản quyền phim '!X:X) | AK84: =SUMIF('TK 15661.Bản quyền phim '!F:F,'KK1. Movies'!AI84,'TK 15661.Bản quyền phim '!X:X) | AL84: =COUNTIF('242.BQ Phim hợp tác'!$C:$C,'KK1. Movies'!AI84) | AM84: =COUNTIF('TK 15661.Bản quyền phim '!F:F,'KK1. Movies'!AI84) | AN84: =AL84+AM84 | AT84: =IFERROR(VLOOKUP(C84, CodeRanMovies!$A:$K, 11, 0), "Not found")
A85: =_xlfn.AGGREGATE(3,3,$D$7:D85) | B85: 16+ | C85: MOV_ACT_22__2686498 | D85: Pipeline | E85: Đường ống | F85: Action, Adventure | G85: Pro Partner | H85: 56/2023/HDBQ/VSTV-Pro Partner | I85: 2021 | J85: Korea | K85: 108 | L85: 45058 | M85: 46153 | N85: 45058 | O85: K+CINE | P85: Exclusive All TV Rights the first 9 months of LP Non-exclusive with All Catch-up TV Rights; All VOD Rights during LP | Q85: No | R85: Yes | S85: Yes | T85: Yes | U85: Yes | V85: Yes | W85: Yes | X85: Yes | Y85: Yes | Z85: 45058 | AA85: 46153 | AB85: unlimited | AC85: 34 | AD85: Yes | AE85: Yes | AG85: Phim còn hạn từ 2026 | AI85: Pipeline | AJ85: =SUMIF('TK 15661.Bản quyền phim '!F:F,'KK1. Movies'!D85,'TK 15661.Bản quyền phim '!X:X) | AK85: =SUMIF('TK 15661.Bản quyền phim '!F:F,'KK1. Movies'!AI85,'TK 15661.Bản quyền phim '!X:X) | AL85: =COUNTIF('242.BQ Phim hợp tác'!$C:$C,'KK1. Movies'!AI85) | AM85: =COUNTIF('TK 15661.Bản quyền phim '!F:F,'KK1. Movies'!AI85) | AN85: =AL85+AM85 | AT85: =IFERROR(VLOOKUP(C85, CodeRanMovies!$A:$K, 11, 0), "Not found")
A86: =_xlfn.AGGREGATE(3,3,$D$7:D86) | C86: MOV_DRA753 | D86: TÁR | E86: TÁR | F86: Drama, Biography, Drama, Women, Music | G86: NBC Universal | H86: 5051370-3/166015-3 | I86: 2022 | J86: US | K86: 158 | L86: 45770 | M86: 46499 | P86: 12 | Q86: No | R86: Yes | S86: Yes | T86: Yes | U86: No | V86: No | W86: No | X86: Yes | Y86: Yes | Z86: 45770 | AA86: 46499 | AB86: 6 | AC86: 1 | AD86: Yes | AE86: Yes | AG86: Phim còn hạn từ 2026 | AH86: MOV_DRA753 | AI86: TAR | AJ86: =SUMIF('TK 15661.Bản quyền phim '!F:F,'KK1. Movies'!D86,'TK 15661.Bản quyền phim '!X:X) | AK86: =SUMIF('TK 15661.Bản quyền phim '!F:F,'KK1. Movies'!AI86,'TK 15661.Bản quyền phim '!X:X) | AL86: =COUNTIF('242.BQ Phim hợp tác'!$C:$C,'KK1. Movies'!AI86) | AM86: =COUNTIF('TK 15661.Bản quyền phim '!F:F,'KK1. Movies'!AI86) | AN86: =AL86+AM86 | AT86: =IFERROR(VLOOKUP(C86, CodeRanMovies!$A:$K, 11, 0), "Not found")
A87: =_xlfn.AGGREGATE(3,3,$D$7:D87) | B87: 16+ | C87: MOV_THR_21__2648729 | D87: PROPHECY | E87: Lời tiên tri | F87: Crime, Thriller | G87: TBS | H87: 202104013 | I87: 2015 | J87: Japan | K87: 119 | L87: 44284 | M87: 46109 | N87: 44342 | O87: K+CINE | Q87: No | R87: Yes | S87: Yes | T87: Yes | U87: Yes | V87: Yes | W87: Yes | X87: Yes | Y87: Yes | Z87: 44284 | AA87: 46109 | AB87: 40 | AC87: 29 | AD87: Yes | AE87: Yes | AG87: Phim còn hạn từ 2026 | AI87: PROPHECY | AJ87: =SUMIF('TK 15661.Bản quyền phim '!F:F,'KK1. Movies'!D87,'TK 15661.Bản quyền phim '!X:X) | AK87: =SUMIF('TK 15661.Bản quyền phim '!F:F,'KK1. Movies'!AI87,'TK 15661.Bản quyền phim '!X:X) | AL87: =COUNTIF('242.BQ Phim hợp tác'!$C:$C,'KK1. Movies'!AI87) | AM87: =COUNTIF('TK 15661.Bản quyền phim '!F:F,'KK1. Movies'!AI87) | AN87: =AL87+AM87 | AT87: =IFERROR(VLOOKUP(C87, CodeRanMovies!$A:$K, 11, 0), "Not found")
A88: =_xlfn.AGGREGATE(3,3,$D$7:D88) | B88: n/a | C88: MOV_ACT600 | D88: HONEYSWEET | E88: Nhân duyên tiền đình | F88: Romance | G88: CJ HK | H88: 15/2025/HDBQ/VSTV-CJHK | I88: 2024 | J88: Korea | K88: 106 | L88: 45690 | M88: 46784 | P88: 12 | Q88: No | R88: Yes | S88: Yes | T88: Yes | U88: Yes | V88: Yes | W88: Yes | X88: Yes | Y88: Yes | Z88: 45690 | AA88: 46784 | AB88: Unlimited | AC88: 6 | AD88: Yes | AE88: Yes | AG88: Phim còn hạn từ 2026 | AI88: HONEYSWEET | AJ88: =SUMIF('TK 15661.Bản quyền phim '!F:F,'KK1. Movies'!D88,'TK 15661.Bản quyền phim '!X:X) | AK88: =SUMIF('TK 15661.Bản quyền phim '!F:F,'KK1. Movies'!AI88,'TK 15661.Bản quyền phim '!X:X) | AL88: =COUNTIF('242.BQ Phim hợp tác'!$C:$C,'KK1. Movies'!AI88) | AM88: =COUNTIF('TK 15661.Bản quyền phim '!F:F,'KK1. Movies'!AI88) | AN88: =AL88+AM88 | AT88: =IFERROR(VLOOKUP(C88, CodeRanMovies!$A:$K, 11, 0), "Not found")
A89: =_xlfn.AGGREGATE(3,3,$D$7:D89) | B89: 13+ | C89: MOV_COM291 | D89: GODSPEED | E89: Chưa thạo đường đời | F89: Comedy/Drama | G89: STK | H89: 134/2024/HDBQ/VSTV-STK | I89: 2023 | J89: China | K89: 100 | L89: 45689 | M89: 46783 | N89: 45689 | P89: 12 | Q89: No | R89: Yes | S89: Yes | T89: Yes | U89: Yes | V89: Yes | W89: Yes | X89: Yes | Y89: Yes | Z89: 45778 | AA89: 46873 | AB89: 24 | AC89: 5 | AD89: Yes | AE89: Yes | AG89: Phim còn hạn từ 2026 | AH89: MOV_COM291 | AI89: GODSPEED | AJ89: =SUMIF('TK 15661.Bản quyền phim '!F:F,'KK1. Movies'!D89,'TK 15661.Bản quyền phim '!X:X) | AK89: =SUMIF('TK 15661.Bản quyền phim '!F:F,'KK1. Movies'!AI89,'TK 15661.Bản quyền phim '!X:X) | AL89: =COUNTIF('242.BQ Phim hợp tác'!$C:$C,'KK1. Movies'!AI89) | AM89: =COUNTIF('TK 15661.Bản quyền phim '!F:F,'KK1. Movies'!AI89) | AN89: =AL89+AM89 | AT89: =IFERROR(VLOOKUP(C89, CodeRanMovies!$A:$K, 11, 0), "Not found")
A90: =_xlfn.AGGREGATE(3,3,$D$7:D90) | B90: 16+ | C90: MOV_ACT_22__2686499 | D90: Hard Hit | E90: Cuộc gọi bí ẩn | F90: Crime, Thriller | G90: Pro Partner | H90: 56/2023/HDBQ/VSTV-Pro Partner | I90: 2021 | J90: Korea | K90: 94 | L90: 45072 | M90: 46167 | N90: 45072 | O90: K+CINE | P90: Exclusive All TV Rights the first 9 months of LP Non-exclusive with All Catch-up TV Rights; All VOD Rights during LP | Q90: No | R90: Yes | S90: Yes | T90: Yes | U90: Yes | V90: Yes | W90: Yes | X90: Yes | Y90: Yes | Z90: 45072 | AA90: 46167 | AB90: unlimited | AC90: 30 | AD90: Yes | AE90: Yes | AG90: Phim còn hạn từ 2026 | AI90: Hard Hit | AJ90: =SUMIF('TK 15661.Bản quyền phim '!F:F,'KK1. Movies'!D90,'TK 15661.Bản quyền phim '!X:X) | AK90: =SUMIF('TK 15661.Bản quyền phim '!F:F,'KK1. Movies'!AI90,'TK 15661.Bản quyền phim '!X:X) | AL90: =COUNTIF('242.BQ Phim hợp tác'!$C:$C,'KK1. Movies'!AI90) | AM90: =COUNTIF('TK 15661.Bản quyền phim '!F:F,'KK1. Movies'!AI90) | AN90: =AL90+AM90 | AT90: =IFERROR(VLOOKUP(C90, CodeRanMovies!$A:$K, 11, 0), "Not found")
A91: =_xlfn.AGGREGATE(3,3,$D$7:D91) | B91: P | C91: MOV_ANI_22__2686853 | D91: Minions (2015) | E91: Minions | F91: animation | G91: NBC Universal | H91: 5051370-3/166015-3 | I91: 2015 | J91: US | K91: 91 | L91: 45686 | M91: 46416 | N91: 44950 | Q91: No | R91: Yes | S91: Yes | T91: Yes | U91: No | V91: No | W91: No | X91: Yes | Y91: No | Z91: 45686 | AA91: 46416 | AB91: 3 | AD91: Yes | AE91: Yes | AG91: Phim còn hạn từ 2026 | AI91: MINIONS (2) | AJ91: =SUMIF('TK 15661.Bản quyền phim '!F:F,'KK1. Movies'!D91,'TK 15661.Bản quyền phim '!X:X) | AK91: =SUMIF('TK 15661.Bản quyền phim '!F:F,'KK1. Movies'!AI91,'TK 15661.Bản quyền phim '!X:X) | AL91: =COUNTIF('242.BQ Phim hợp tác'!$C:$C,'KK1. Movies'!AI91) | AM91: =COUNTIF('TK 15661.Bản quyền phim '!F:F,'KK1. Movies'!AI91) | AN91: =AL91+AM91 | AT91: =IFERROR(VLOOKUP(C91, CodeRanMovies!$A:$K, 11, 0), "Not found")
A92: =_xlfn.AGGREGATE(3,3,$D$7:D92) | B92: 13+ | C92: MOV_COM_22__2686517 | D92: Blithe Spirit | E92: Người vợ quá cố | F92: Comedy | G92: Skyline Media | H92: 66/2023/HDBQ/VSTV-SM | I92: 2020 | J92: UK | K92: 99 | L92: 45065 | M92: 46160 | N92: 45260 | O92: K+CINE | P92: Exclusive All TV Rights the first 12 months of LP Non-exclusive with All Catch-up TV Rights; All VOD Rights during LP | Q92: No | R92: Yes | S92: Yes | T92: Yes | U92: Yes | V92: Yes | W92: Yes | X92: Yes | Y92: Yes | Z92: 45065 | AA92: 46160 | AB92: 24 | AC92: 11 | AD92: Yes | AE92: Yes | AG92: Phim còn hạn từ 2026 | AI92: Blithe Spirit | AJ92: =SUMIF('TK 15661.Bản quyền phim '!F:F,'KK1. Movies'!D92,'TK 15661.Bản quyền phim '!X:X) | AK92: =SUMIF('TK 15661.Bản quyền phim '!F:F,'KK1. Movies'!AI92,'TK 15661.Bản quyền phim '!X:X) | AL92: =COUNTIF('242.BQ Phim hợp tác'!$C:$C,'KK1. Movies'!AI92) | AM92: =COUNTIF('TK 15661.Bản quyền phim '!F:F,'KK1. Movies'!AI92) | AN92: =AL92+AM92 | AT92: =IFERROR(VLOOKUP(C92, CodeRanMovies!$A:$K, 11, 0), "Not found")
A93: =_xlfn.AGGREGATE(3,3,$D$7:D93) | B93: 16+ | C93: MOV_HOR_24__2710433 | D93: VIVARIUM | E93: Chỗ sống | F93: Horror | G93: Skyline Media | H93: 28/2024/HDBQ/VSTV-SM | I93: 2019 | J93: US | K93: 97 | L93: 45337 | M93: 46432 | N93: 45583 | O93: K+ACTION | P93: 12 | Q93: No | R93: Yes | S93: Yes | T93: Yes | U93: Yes | V93: Yes | W93: Yes | X93: Yes | Y93: No | Z93: 45337 | AA93: 46432 | AB93: 24 | AC93: 16 | AD93: Yes | AE93: Yes | AG93: Phim còn hạn từ 2026 | AI93: VIVARIUM | AJ93: =SUMIF('TK 15661.Bản quyền phim '!F:F,'KK1. Movies'!D93,'TK 15661.Bản quyền phim '!X:X) | AK93: =SUMIF('TK 15661.Bản quyền phim '!F:F,'KK1. Movies'!AI93,'TK 15661.Bản quyền phim '!X:X) | AL93: =COUNTIF('242.BQ Phim hợp tác'!$C:$C,'KK1. Movies'!AI93) | AM93: =COUNTIF('TK 15661.Bản quyền phim '!F:F,'KK1. Movies'!AI93) | AN93: =AL93+AM93 | AT93: =IFERROR(VLOOKUP(C93, CodeRanMovies!$A:$K, 11, 0), "Not found")
A94: =_xlfn.AGGREGATE(3,3,$D$7:D94) | B94: P | C94: MOV_ANI__2715680 | D94: SING 2 | E94: Đấu trường âm nhạc 2 | F94: animation | G94: NBC Universal | H94: 5049540-2/161434-3 | I94: 2021 | J94: US | K94: 110 | L94: 45449 | M94: 46178 | N94: 45458 | O94: K+KIDS | Q94: No | R94: Yes | S94: Yes | T94: Yes | U94: No | V94: No | W94: No | X94: No | Y94: Yes | Z94: 45449 | AA94: 46178 | AB94: 6 | AC94: 6 | AD94: Yes | AE94: Yes | AG94: Phim còn hạn từ 2026 | AI94: SING 2 | AJ94: =SUMIF('TK 15661.Bản quyền phim '!F:F,'KK1. Movies'!D94,'TK 15661.Bản quyền phim '!X:X) | AK94: =SUMIF('TK 15661.Bản quyền phim '!F:F,'KK1. Movies'!AI94,'TK 15661.Bản quyền phim '!X:X) | AL94: =COUNTIF('242.BQ Phim hợp tác'!$C:$C,'KK1. Movies'!AI94) | AM94: =COUNTIF('TK 15661.Bản quyền phim '!F:F,'KK1. Movies'!AI94) | AN94: =AL94+AM94 | AT94: =IFERROR(VLOOKUP(C94, CodeRanMovies!$A:$K, 11, 0), "Not found")
A95: =_xlfn.AGGREGATE(3,3,$D$7:D95) | C95: MOV_THR166 | D95: INSIDE (2023) | E95: Mắc kẹt | F95: Drama, Thriller | G95: NBC Universal | H95: 5051370-3/166015-3 | I95: 2021 | J95: Greece | K95: 105 | L95: 45771 | M95: 46500 | P95: 12 | Q95: No | R95: Yes | S95: Yes | T95: Yes | U95: No | V95: No | W95: No | X95: Yes | Y95: Yes | Z95: 45771 | AA95: 46500 | AB95: 6 | AC95: 1 | AD95: Yes | AE95: Yes | AG95: Phim còn hạn từ 2026 | AI95: INSIDE (2023) | AJ95: =SUMIF('TK 15661.Bản quyền phim '!F:F,'KK1. Movies'!D95,'TK 15661.Bản quyền phim '!X:X) | AK95: =SUMIF('TK 15661.Bản quyền phim '!F:F,'KK1. Movies'!AI95,'TK 15661.Bản quyền phim '!X:X) | AL95: =COUNTIF('242.BQ Phim hợp tác'!$C:$C,'KK1. Movies'!AI95) | AM95: =COUNTIF('TK 15661.Bản quyền phim '!F:F,'KK1. Movies'!AI95) | AN95: =AL95+AM95 | AT95: =IFERROR(VLOOKUP(C95, CodeRanMovies!$A:$K, 11, 0), "Not found")
A96: =_xlfn.AGGREGATE(3,3,$D$7:D96) | B96: 16+ | C96: MOV_ACT589 | D96: Iceman (2014) | E96: Cuồng Phong Nộ Hỏa | F96: action | G96: Hỏa Thổ | H96: 25A/2024/HDBQ/VSTV-Hoa tho | I96: 2021 | J96: China | K96: 125 | L96: 45520 | M96: 46614 | N96: 45520 | O96: K+CINE | P96: non exclusive | Q96: No | R96: Yes | S96: Yes | T96: Yes | U96: No | V96: Yes | W96: Yes | X96: No | Y96: No | Z96: 45520 | AA96: 46614 | AB96: Unlimited run | AC96: 20 | AD96: Yes | AE96: Yes | AG96: Phim còn hạn từ 2026 | AI96: Iceman (Người Băng) | AJ96: =SUMIF('TK 15661.Bản quyền phim '!F:F,'KK1. Movies'!D96,'TK 15661.Bản quyền phim '!X:X) | AK96: =SUMIF('TK 15661.Bản quyền phim '!F:F,'KK1. Movies'!AI96,'TK 15661.Bản quyền phim '!X:X) | AL96: =COUNTIF('242.BQ Phim hợp tác'!$C:$C,'KK1. Movies'!AI96) | AM96: =COUNTIF('TK 15661.Bản quyền phim '!F:F,'KK1. Movies'!AI96) | AN96: =AL96+AM96 | AT96: =IFERROR(VLOOKUP(C96, CodeRanMovies!$A:$K, 11, 0), "Not found")
A97: =_xlfn.AGGREGATE(3,3,$D$7:D97) | B97: 13+ | C97: MOV_ACT590 | D97: JURASSIC WORLD DOMINION | E97: Thế giới khủng long: Lãnh địa | F97: Action, Adventure | G97: NBC Universal | H97: 5049540-2/161434-3 | I97: 2021 | J97: US | K97: 147 | L97: 45639 | M97: 46368 | N97: 45639 | O97: K+CINE | Q97: No | R97: Yes | S97: Yes | T97: Yes | U97: No | V97: No | W97: No | X97: No | Y97: Yes | Z97: 45639 | AA97: 46368 | AB97: 6 | AC97: 3 | AD97: Yes | AE97: Yes | AG97: Phim còn hạn từ 2026 | AI97: JURASSIC WORLD DOMINION | AJ97: =SUMIF('TK 15661.Bản quyền phim '!F:F,'KK1. Movies'!D97,'TK 15661.Bản quyền phim '!X:X) | AK97: =SUMIF('TK 15661.Bản quyền phim '!F:F,'KK1. Movies'!AI97,'TK 15661.Bản quyền phim '!X:X) | AL97: =COUNTIF('242.BQ Phim hợp tác'!$C:$C,'KK1. Movies'!AI97) | AM97: =COUNTIF('TK 15661.Bản quyền phim '!F:F,'KK1. Movies'!AI97) | AN97: =AL97+AM97 | AT97: =IFERROR(VLOOKUP(C97, CodeRanMovies!$A:$K, 11, 0), "Not found")
A98: =_xlfn.AGGREGATE(3,3,$D$7:D98) | B98: n/a | C98: MOV_ACT593 | D98: TWILIGHT OF THE WARRIORS: WALLED IN | E98: Cửu Long Thành Trại: Vây Thành | F98: Action, Historical, Crime, Drama | G98: Skyline Media | H98: 36/2025/HDBQ/VSTV-SM | I98: 2024 | J98: Hong Kong | K98: 125 | L98: 45737 | M98: 47197 | N98: n/a | P98: 12 | Q98: No | R98: Yes | S98: Yes | T98: Yes | U98: Yes | V98: Yes | W98: Yes | X98: Yes | Y98: No | Z98: 45737 | AA98: 47197 | AB98: 24 | AC98: 6 | AD98: Yes | AE98: Yes | AG98: Phim còn hạn từ 2026 | AH98: MOV_ACT593 | AI98: TWILIGHT OF THE WARRIORS: WALLED IN | AJ98: =SUMIF('TK 15661.Bản quyền phim '!F:F,'KK1. Movies'!D98,'TK 15661.Bản quyền phim '!X:X) | AK98: =SUMIF('TK 15661.Bản quyền phim '!F:F,'KK1. Movies'!AI98,'TK 15661.Bản quyền phim '!X:X) | AL98: =COUNTIF('242.BQ Phim hợp tác'!$C:$C,'KK1. Movies'!AI98) | AM98: =COUNTIF('TK 15661.Bản quyền phim '!F:F,'KK1. Movies'!AI98) | AN98: =AL98+AM98 | AT98: =IFERROR(VLOOKUP(C98, CodeRanMovies!$A:$K, 11, 0), "Not found")
A99: =_xlfn.AGGREGATE(3,3,$D$7:D99) | B99: 13+ | C99: MOV_FAN_LNVM__15__2467819 | D99: The Lost Dragon | E99: NGÀY NẢY NGÀY NAY | F99: Comedy | G99: BHD | H99: 90/2015/HDBQ/VSTV-BHD | I99: 2015 | J99: Việt Nam | K99: 109 | L99: 42160 | M99: Vĩnh viễn | N99: 42160 | P99: 24 | Q99: No | R99: Yes | S99: Yes | T99: Yes | U99: Yes | V99: Yes | W99: Yes | X99: No | Y99: yes | Z99: 42160 | AA99: Vĩnh viễn | AB99: 6 | AC99: 2 | AG99: Phim còn hạn từ 2026 | AI99: Film hợp tác - Ngày nảy ngày nay | AJ99: =SUMIF('TK 15661.Bản quyền phim '!F:F,'KK1. Movies'!D99,'TK 15661.Bản quyền phim '!X:X) | AK99: =SUMIF('TK 15661.Bản quyền phim '!F:F,'KK1. Movies'!AI99,'TK 15661.Bản quyền phim '!X:X) | AL99: =COUNTIF('242.BQ Phim hợp tác'!$C:$C,'KK1. Movies'!AI99) | AM99: =COUNTIF('TK 15661.Bản quyền phim '!F:F,'KK1. Movies'!AI99) | AN99: =AL99+AM99 | AT99: =IFERROR(VLOOKUP(C99, CodeRanMovies!$A:$K, 11, 0), "Not found")
A100: =_xlfn.AGGREGATE(3,3,$D$7:D100) | B100: 16+ | C100: MOV_ACT_23__2695915 | D100: AVA | E100: Nữ sát thủ | F100: Crime, Thriller | G100: Roses Media | H100: 140/2022/HDBQ/VSTV-RM | I100: 2020 | J100: US | K100: 96 | L100: 45203 | M100: 46298 | N100: 45203 | O100: K+CINE | P100: Exclusive All Pay TV Rights for first 12 months. Non exclusive All VOD during LP | Q100: No | R100: Yes | S100: Yes | T100: Yes | U100: Yes | V100: Yes | W100: Yes | X100: Yes | Y100: No | Z100: 45203 | AA100: 46298 | AB100: 24 | AC100: 16 | AD100: Yes | AE100: Yes | AG100: Phim còn hạn từ 2026 | AI100: AVA | AJ100: =SUMIF('TK 15661.Bản quyền phim '!F:F,'KK1. Movies'!D100,'TK 15661.Bản quyền phim '!X:X) | AK100: =SUMIF('TK 15661.Bản quyền phim '!F:F,'KK1. Movies'!AI100,'TK 15661.Bản quyền phim '!X:X) | AL100: =COUNTIF('242.BQ Phim hợp tác'!$C:$C,'KK1. Movies'!AI100) | AM100: =COUNTIF('TK 15661.Bản quyền phim '!F:F,'KK1. Movies'!AI100) | AN100: =AL100+AM100 | AT100: =IFERROR(VLOOKUP(C100, CodeRanMovies!$A:$K, 11, 0), "Not found")
...

Sheet KK6. Bổ sung
A1: CÔNG TY: | B1: Công ty TNHH Truyền hình số vệ tinh Việt Nam | T1: Cộng Hòa Xã Hội Chủ Nghĩa Việt Nam
T2: Độc Lập - Tự Do - Hạnh Phúc
Q4: =COUNTIF(Q7:Q44,1) | R4: =COUNTIF(R7:R44,1)
N5: Ref File Kế toán | S5: Check | T5: SỐ LIỆU KIỂM KÊ | W5: Giải trình chênh lệch | X5: Đề xuất Phương án xử lý
A6: Inventory code | B6: Contract currency | C6: Contractor code | D6: Contractor name | E6: Program name | F6: Nature Programme | G6: No of EPS (Initially) | H6: Starting Date of right | I6: Ending date of right | J6: From (DTH) | K6: To (DTH) | L6: Note | N6: Tên trên file Kế toán | O6: details kế toán | P6: Giá trị còn lại (15661) | Q6: Check ref "TK 242.BQ Phim hợp tác" | R6: Check ref "TK 15661. Bản quyền phim" | T6: Số lượng | U6: From (VOD) | V6: To (VOD) | Y6: Kết quả kiểm tra VOD
A7: K+1MOV021273 | B7: VND | C7: S0001502 | D7: Công ty TNHH Đối tác Chuyên nghiệp | E7: THE BREAKUP GURU | F7: Movies International | G7: 1 | H7: 5 | I7: 5 | J7: 44519 | K7: 46160 | L7: Phim còn hạn từ 2026 | N7: SHINING FOR ONE THING | O7: =SUMIF('TK 15661.Bản quyền phim '!F:F,'KK6. Bổ sung'!D7,'TK 15661.Bản quyền phim '!X:X) | P7: =SUMIF('TK 15661.Bản quyền phim '!F:F,'KK6. Bổ sung'!N7,'TK 15661.Bản quyền phim '!X:X) | R7: =COUNTIF('TK 15661.Bản quyền phim '!F:F,'KK6. Bổ sung'!N7) | S7: =Q7+R7 | Y7: ✗ Not Found
A8: K+1MOV021274 | B8: VND | C8: S0001502 | D8: Công ty TNHH Đối tác Chuyên nghiệp | E8: FALL IN LOVE LIKE A STAR | F8: Movies International | G8: 1 | H8: 5 | I8: 5 | J8: 44491 | K8: 46133 | L8: Phim còn hạn từ 2026 | N8: ROGUE HEROS | O8: =SUMIF('TK 15661.Bản quyền phim '!F:F,'KK6. Bổ sung'!D8,'TK 15661.Bản quyền phim '!X:X) | P8: =SUMIF('TK 15661.Bản quyền phim '!F:F,'KK6. Bổ sung'!N8,'TK 15661.Bản quyền phim '!X:X) | R8: =COUNTIF('TK 15661.Bản quyền phim '!F:F,'KK6. Bổ sung'!N8) | S8: =Q8+R8 | Y8: ✗ Not Found
A9: K+1MOV021275 | B9: VND | C9: S0001502 | D9: Công ty TNHH Đối tác Chuyên nghiệp | E9: NE ZHA | F9: Movies International | G9: 1 | H9: 5 | I9: 5 | J9: 44533 | K9: 46175 | L9: Phim còn hạn từ 2026 | N9: Escape Plan 2: Hades | O9: =SUMIF('TK 15661.Bản quyền phim '!F:F,'KK6. Bổ sung'!D9,'TK 15661.Bản quyền phim '!X:X) | P9: =SUMIF('TK 15661.Bản quyền phim '!F:F,'KK6. Bổ sung'!N9,'TK 15661.Bản quyền phim '!X:X) | R9: =COUNTIF('TK 15661.Bản quyền phim '!F:F,'KK6. Bổ sung'!N9) | S9: =Q9+R9 | Y9: ✗ Not Found
A10: K+1MOV021276 | B10: VND | C10: S0001502 | D10: Công ty TNHH Đối tác Chuyên nghiệp | E10: SOUL SNATCHER | F10: Movies International | G10: 1 | H10: 5 | I10: 5 | J10: 44517 | K10: 46158 | L10: Phim còn hạn từ 2026 | N10: Riam: Fighting Angel | O10: =SUMIF('TK 15661.Bản quyền phim '!F:F,'KK6. Bổ sung'!D10,'TK 15661.Bản quyền phim '!X:X) | P10: =SUMIF('TK 15661.Bản quyền phim '!F:F,'KK6. Bổ sung'!N10,'TK 15661.Bản quyền phim '!X:X) | R10: =COUNTIF('TK 15661.Bản quyền phim '!F:F,'KK6. Bổ sung'!N10) | S10: =Q10+R10 | Y10: ✗ Not Found
A11: K+1MOV021279 | B11: VND | C11: S0001502 | D11: Công ty TNHH Đối tác Chuyên nghiệp | E11: RAT DISASTER | F11: Movies International | G11: 1 | H11: 5 | I11: 5 | J11: 44538 | K11: 46180 | L11: Phim còn hạn từ 2026 | N11: Happy Family | O11: =SUMIF('TK 15661.Bản quyền phim '!F:F,'KK6. Bổ sung'!D11,'TK 15661.Bản quyền phim '!X:X) | P11: =SUMIF('TK 15661.Bản quyền phim '!F:F,'KK6. Bổ sung'!N11,'TK 15661.Bản quyền phim '!X:X) | R11: =COUNTIF('TK 15661.Bản quyền phim '!F:F,'KK6. Bổ sung'!N11) | S11: =Q11+R11 | Y11: ✗ Not Found
A12: K+1MOV021282 | B12: VND | C12: S0001502 | D12: Công ty TNHH Đối tác Chuyên nghiệp | E12: FEARLESS KUNGFU KING | F12: Movies International | G12: 1 | H12: 5 | I12: 5 | J12: 44531 | K12: 46356 | L12: Phim còn hạn từ 2026 | N12: MEMOIRS OF A GEISHA | O12: =SUMIF('TK 15661.Bản quyền phim '!F:F,'KK6. Bổ sung'!D12,'TK 15661.Bản quyền phim '!X:X) | P12: =SUMIF('TK 15661.Bản quyền phim '!F:F,'KK6. Bổ sung'!N12,'TK 15661.Bản quyền phim '!X:X) | R12: =COUNTIF('TK 15661.Bản quyền phim '!F:F,'KK6. Bổ sung'!N12) | S12: =Q12+R12 | Y12: ✗ Not Found
A13: K+1MOV021283 | B13: VND | C13: S0001502 | D13: Công ty TNHH Đối tác Chuyên nghiệp | E13: MATCHLESS MULAN | F13: Movies International | G13: 1 | H13: 5 | I13: 5 | J13: 44489 | K13: 46131 | L13: Phim còn hạn từ 2026 | N13: Ironbark/The Courier | O13: =SUMIF('TK 15661.Bản quyền phim '!F:F,'KK6. Bổ sung'!D13,'TK 15661.Bản quyền phim '!X:X) | P13: =SUMIF('TK 15661.Bản quyền phim '!F:F,'KK6. Bổ sung'!N13,'TK 15661.Bản quyền phim '!X:X) | R13: =COUNTIF('TK 15661.Bản quyền phim '!F:F,'KK6. Bổ sung'!N13) | S13: =Q13+R13 | Y13: ✗ Not Found
A14: K+1MOV021284 | B14: VND | C14: S0001502 | D14: Công ty TNHH Đối tác Chuyên nghiệp | E14: LOVE IN BLOOD | F14: Movies International | G14: 1 | H14: 5 | I14: 5 | J14: 44461 | K14: 46102 | L14: Phim còn hạn từ 2026 | N14: Hitman's Wife's Bodyguard | O14: =SUMIF('TK 15661.Bản quyền phim '!F:F,'KK6. Bổ sung'!D14,'TK 15661.Bản quyền phim '!X:X) | P14: =SUMIF('TK 15661.Bản quyền phim '!F:F,'KK6. Bổ sung'!N14,'TK 15661.Bản quyền phim '!X:X) | R14: =COUNTIF('TK 15661.Bản quyền phim '!F:F,'KK6. Bổ sung'!N14) | S14: =Q14+R14 | Y14: ✗ Not Found
A15: K+1MOV021285 | B15: VND | C15: S0001502 | D15: Công ty TNHH Đối tác Chuyên nghiệp | E15: GOD OF WAR | F15: Movies International | G15: 1 | H15: 5 | I15: 5 | J15: 44475 | K15: 46117 | L15: Phim còn hạn từ 2026 | N15: GUIMOON: THE LIGHTLESS DOOR (CỔNG ĐỊA NGỤC) | O15: =SUMIF('TK 15661.Bản quyền phim '!F:F,'KK6. Bổ sung'!D15,'TK 15661.Bản quyền phim '!X:X) | P15: =SUMIF('TK 15661.Bản quyền phim '!F:F,'KK6. Bổ sung'!N15,'TK 15661.Bản quyền phim '!X:X) | R15: =COUNTIF('TK 15661.Bản quyền phim '!F:F,'KK6. Bổ sung'!N15) | S15: =Q15+R15 | Y15: ✗ Not Found
A16: K+1MOV021287 | B16: VND | C16: S0001502 | D16: Công ty TNHH Đối tác Chuyên nghiệp | E16: THE RISE OF HERO | F16: Movies International | G16: 1 | H16: 5 | I16: 5 | J16: 44559 | K16: 46201 | L16: Phim còn hạn từ 2026 | M16: MOV_DRA_23__2696593 | N16: Greta | O16: =SUMIF('TK 15661.Bản quyền phim '!F:F,'KK6. Bổ sung'!D16,'TK 15661.Bản quyền phim '!X:X) | P16: =SUMIF('TK 15661.Bản quyền phim '!F:F,'KK6. Bổ sung'!N16,'TK 15661.Bản quyền phim '!X:X) | R16: =COUNTIF('TK 15661.Bản quyền phim '!F:F,'KK6. Bổ sung'!N16) | S16: =Q16+R16 | Y16: ✗ Not Found
A17: K+1MOV021288 | B17: VND | C17: S0001502 | D17: Công ty TNHH Đối tác Chuyên nghiệp | E17: SWORDSMAN | F17: Movies International | G17: 1 | H17: 5 | I17: 5 | J17: 44503 | K17: 46144 | L17: Phim còn hạn từ 2026 | M17: MOV_FAN_22__2686869 | N17: HOUSE WITH A CLOCK IN ITS WALLS (Ngôi nhà có chiếc đồng hồ ma thuật) | O17: =SUMIF('TK 15661.Bản quyền phim '!F:F,'KK6. Bổ sung'!D17,'TK 15661.Bản quyền phim '!X:X) | P17: =SUMIF('TK 15661.Bản quyền phim '!F:F,'KK6. Bổ sung'!N17,'TK 15661.Bản quyền phim '!X:X) | R17: =COUNTIF('TK 15661.Bản quyền phim '!F:F,'KK6. Bổ sung'!N17) | S17: =Q17+R17 | Y17: ✗ Not Found
A18: K+2SER022116 | B18: USD | C18: S0002262 | D18: IQIYI INTERNATIONAL SINGAPORE PTE. LTD. | E18: Ideal City | F18: Series Asian | G18: 40 | H18: 4 | I18: 160 | J18: 44642 | K18: 46102 | L18: Phim còn hạn từ 2026 | N18: HUNT, THE | O18: =SUMIF('TK 15661.Bản quyền phim '!F:F,'KK6. Bổ sung'!D18,'TK 15661.Bản quyền phim '!X:X) | P18: =SUMIF('TK 15661.Bản quyền phim '!F:F,'KK6. Bổ sung'!N18,'TK 15661.Bản quyền phim '!X:X) | R18: =COUNTIF('TK 15661.Bản quyền phim '!F:F,'KK6. Bổ sung'!N18) | S18: =Q18+R18 | Y18: ✓ Found
A19: K+1MOV023009 | B19: VND | C19: S0001804 | D19: CÔNG TY TNHH TRUYỀN THÔNG ROSES | E19: ROGUE | F19: Movies International | G19: 1 | H19: 3 | I19: 3 | J19: 45077 | K19: 46172 | L19: Phim còn hạn từ 2026 | M19: MOV_CRI_21__2648182 | N19: MOZU | O19: =SUMIF('TK 15661.Bản quyền phim '!F:F,'KK6. Bổ sung'!D19,'TK 15661.Bản quyền phim '!X:X) | P19: =SUMIF('TK 15661.Bản quyền phim '!F:F,'KK6. Bổ sung'!N19,'TK 15661.Bản quyền phim '!X:X) | R19: =COUNTIF('TK 15661.Bản quyền phim '!F:F,'KK6. Bổ sung'!N19) | S19: =Q19+R19 | Y19: ✗ Not Found
A20: K+5KID023239 | B20: USD | C20: S0002484 | D20: GULLANE (THOMAS) LIMITED | E20: Thomas & Friends Series 25 Special – Race for the Sodor Cup | F20: KIDS | G20: 1 | H20: 3 | I20: 3 | J20: 45200 | K20: 46295 | L20: Phim còn hạn từ 2026 | M20: MOV_HOR_24__2713878 | N20: CONTORTED (NHÀ KHO CHẾT CHÓC) | O20: =SUMIF('TK 15661.Bản quyền phim '!F:F,'KK6. Bổ sung'!D20,'TK 15661.Bản quyền phim '!X:X) | P20: =SUMIF('TK 15661.Bản quyền phim '!F:F,'KK6. Bổ sung'!N20,'TK 15661.Bản quyền phim '!X:X) | R20: =COUNTIF('TK 15661.Bản quyền phim '!F:F,'KK6. Bổ sung'!N20) | S20: =Q20+R20 | Y20: ✗ Not Found
A21: K+1MOV024126 | B21: VND | C21: S0002365 | D21: CÔNG TY CỔ PHẦN TRUYỀN THÔNG HỎA THỔ | E21: The Hot-Blooded (Tử Chiến) | F21: Movies International | G21: 1 | H21: 3 | I21: 3 | J21: 45435 | K21: 46529 | L21: Phim còn hạn từ 2026 | N21: The Night Clerk | O21: =SUMIF('TK 15661.Bản quyền phim '!F:F,'KK6. Bổ sung'!D21,'TK 15661.Bản quyền phim '!X:X) | P21: =SUMIF('TK 15661.Bản quyền phim '!F:F,'KK6. Bổ sung'!N21,'TK 15661.Bản quyền phim '!X:X) | R21: =COUNTIF('TK 15661.Bản quyền phim '!F:F,'KK6. Bổ sung'!N21) | S21: =Q21+R21 | Y21: ✗ Not Found
A22: K+1MOV024132 | B22: VND | C22: S0002365 | D22: CÔNG TY CỔ PHẦN TRUYỀN THÔNG HỎA THỔ | E22: Z Storm (Đội Chống Tham Nhũng) | F22: Movies International | G22: 1 | H22: 3 | I22: 3 | J22: 45506 | K22: 46600 | L22: Phim còn hạn từ 2026 | N22: Journey to China: The Mystery of the Dragon Seal | O22: =SUMIF('TK 15661.Bản quyền phim '!F:F,'KK6. Bổ sung'!D22,'TK 15661.Bản quyền phim '!X:X) | P22: =SUMIF('TK 15661.Bản quyền phim '!F:F,'KK6. Bổ sung'!N22,'TK 15661.Bản quyền phim '!X:X) | R22: =COUNTIF('TK 15661.Bản quyền phim '!F:F,'KK6. Bổ sung'!N22) | S22: =Q22+R22 | Y22: ✗ Not Found
A23: K+1MOV024133 | B23: VND | C23: S0002365 | D23: CÔNG TY CỔ PHẦN TRUYỀN THÔNG HỎA THỔ | E23: Raging Fire (Cuồng Phong Nộ Hỏa) | F23: Movies International | G23: 1 | H23: 3 | I23: 3 | J23: 45520 | K23: 46614 | L23: Phim còn hạn từ 2026 | N23: Gringo | O23: =SUMIF('TK 15661.Bản quyền phim '!F:F,'KK6. Bổ sung'!D23,'TK 15661.Bản quyền phim '!X:X) | P23: =SUMIF('TK 15661.Bản quyền phim '!F:F,'KK6. Bổ sung'!N23,'TK 15661.Bản quyền phim '!X:X) | R23: =COUNTIF('TK 15661.Bản quyền phim '!F:F,'KK6. Bổ sung'!N23) | S23: =Q23+R23 | Y23: ✗ Not Found
A24: K+1MOV024134 | B24: VND | C24: S0002365 | D24: CÔNG TY CỔ PHẦN TRUYỀN THÔNG HỎA THỔ | E24: Ip Man 3 (Diệp Vấn 3) | F24: Movies International | G24: 1 | H24: 3 | I24: 3 | J24: 45548 | K24: 46642 | L24: Phim còn hạn từ 2026 | N24: THE GIRL ON THE TRAIN (Cô gái trên tàu) | O24: =SUMIF('TK 15661.Bản quyền phim '!F:F,'KK6. Bổ sung'!D24,'TK 15661.Bản quyền phim '!X:X) | P24: =SUMIF('TK 15661.Bản quyền phim '!F:F,'KK6. Bổ sung'!N24,'TK 15661.Bản quyền phim '!X:X) | R24: =COUNTIF('TK 15661.Bản quyền phim '!F:F,'KK6. Bổ sung'!N24) | S24: =Q24+R24 | Y24: ✗ Not Found
A25: K+1MOV024135 | B25: USD | C25: S0002438 | D25: Paramount Pictures International Limited | E25: CRAWL | F25: Movies International | G25: 1 | H25: 2 | I25: 2 | J25: 45609 | K25: 46154 | L25: Phim còn hạn từ 2026 | N25: Triple Threat | O25: =SUMIF('TK 15661.Bản quyền phim '!F:F,'KK6. Bổ sung'!D25,'TK 15661.Bản quyền phim '!X:X) | P25: =SUMIF('TK 15661.Bản quyền phim '!F:F,'KK6. Bổ sung'!N25,'TK 15661.Bản quyền phim '!X:X) | R25: =COUNTIF('TK 15661.Bản quyền phim '!F:F,'KK6. Bổ sung'!N25) | S25: =Q25+R25 | Y25: ✗ Not Found
A26: K+2MOV024138 | B26: USD | C26: S0002438 | D26: Paramount Pictures International Limited | E26: GHOST IN THE SHELL (2017) | F26: Movies International | G26: 1 | H26: 2 | I26: 2 | J26: 45609 | K26: 46154 | L26: Phim còn hạn từ 2026 | N26: RECALLED (TRIỆU HỒI) | O26: =SUMIF('TK 15661.Bản quyền phim '!F:F,'KK6. Bổ sung'!D26,'TK 15661.Bản quyền phim '!X:X) | P26: =SUMIF('TK 15661.Bản quyền phim '!F:F,'KK6. Bổ sung'!N26,'TK 15661.Bản quyền phim '!X:X) | R26: =COUNTIF('TK 15661.Bản quyền phim '!F:F,'KK6. Bổ sung'!N26) | S26: =Q26+R26 | Y26: ✗ Not Found
A27: K+1MOV024140 | B27: USD | C27: S0002438 | D27: Paramount Pictures International Limited | E27: JACK RYAN: SHADOW RECRUIT | F27: Movies International | G27: 1 | H27: 2 | I27: 2 | J27: 45569 | K27: 46115 | L27: Phim còn hạn từ 2026 | N27: A DOG'S PURPOSE (Mục đích sống của một chú chó) | O27: =SUMIF('TK 15661.Bản quyền phim '!F:F,'KK6. Bổ sung'!D27,'TK 15661.Bản quyền phim '!X:X) | P27: =SUMIF('TK 15661.Bản quyền phim '!F:F,'KK6. Bổ sung'!N27,'TK 15661.Bản quyền phim '!X:X) | R27: =COUNTIF('TK 15661.Bản quyền phim '!F:F,'KK6. Bổ sung'!N27) | S27: =Q27+R27 | Y27: ✗ Not Found
A28: K+1MOV024141 | B28: USD | C28: S0002438 | D28: Paramount Pictures International Limited | E28: MISSION: IMPOSSIBLE | F28: Movies International | G28: 1 | H28: 2 | I28: 2 | J28: 45597 | K28: 46142 | L28: Phim còn hạn từ 2026 | N28: BURLESQUE | O28: =SUMIF('TK 15661.Bản quyền phim '!F:F,'KK6. Bổ sung'!D28,'TK 15661.Bản quyền phim '!X:X) | P28: =SUMIF('TK 15661.Bản quyền phim '!F:F,'KK6. Bổ sung'!N28,'TK 15661.Bản quyền phim '!X:X) | R28: =COUNTIF('TK 15661.Bản quyền phim '!F:F,'KK6. Bổ sung'!N28) | S28: =Q28+R28 | Y28: ✗ Not Found
A29: K+1MOV024142 | B29: USD | C29: S0002438 | D29: Paramount Pictures International Limited | E29: MISSION: IMPOSSIBLE - GHOST PROTOCOL | F29: Movies International | G29: 1 | H29: 2 | I29: 2 | J29: 45597 | K29: 46142 | L29: Phim còn hạn từ 2026 | N29: My Spy | O29: =SUMIF('TK 15661.Bản quyền phim '!F:F,'KK6. Bổ sung'!D29,'TK 15661.Bản quyền phim '!X:X) | P29: =SUMIF('TK 15661.Bản quyền phim '!F:F,'KK6. Bổ sung'!N29,'TK 15661.Bản quyền phim '!X:X) | R29: =COUNTIF('TK 15661.Bản quyền phim '!F:F,'KK6. Bổ sung'!N29) | S29: =Q29+R29 | Y29: ✗ Not Found
A30: K+1MOV024143 | B30: USD | C30: S0002438 | D30: Paramount Pictures International Limited | E30: MISSION: IMPOSSIBLE - ROGUE NATION | F30: Movies International | G30: 1 | H30: 2 | I30: 2 | J30: 45597 | K30: 46142 | L30: Phim còn hạn từ 2026 | N30: EMILY THE CRIMINAL | O30: =SUMIF('TK 15661.Bản quyền phim '!F:F,'KK6. Bổ sung'!D30,'TK 15661.Bản quyền phim '!X:X) | P30: =SUMIF('TK 15661.Bản quyền phim '!F:F,'KK6. Bổ sung'!N30,'TK 15661.Bản quyền phim '!X:X) | R30: =COUNTIF('TK 15661.Bản quyền phim '!F:F,'KK6. Bổ sung'!N30) | S30: =Q30+R30 | Y30: ✗ Not Found
A31: K+1MOV024144 | B31: USD | C31: S0002438 | D31: Paramount Pictures International Limited | E31: MISSION: IMPOSSIBLE II | F31: Movies International | G31: 1 | H31: 2 | I31: 2 | J31: 45597 | K31: 46142 | L31: Phim còn hạn từ 2026 | N31: A LONG WAY DOWN | O31: =SUMIF('TK 15661.Bản quyền phim '!F:F,'KK6. Bổ sung'!D31,'TK 15661.Bản quyền phim '!X:X) | P31: =SUMIF('TK 15661.Bản quyền phim '!F:F,'KK6. Bổ sung'!N31,'TK 15661.Bản quyền phim '!X:X) | R31: =COUNTIF('TK 15661.Bản quyền phim '!F:F,'KK6. Bổ sung'!N31) | S31: =Q31+R31 | Y31: ✗ Not Found
A32: K+1MOV024145 | B32: USD | C32: S0002438 | D32: Paramount Pictures International Limited | E32: MISSION: IMPOSSIBLE III | F32: Movies International | G32: 1 | H32: 2 | I32: 2 | J32: 45597 | K32: 46142 | L32: Phim còn hạn từ 2026 | N32: WITCH, THE | O32: =SUMIF('TK 15661.Bản quyền phim '!F:F,'KK6. Bổ sung'!D32,'TK 15661.Bản quyền phim '!X:X) | P32: =SUMIF('TK 15661.Bản quyền phim '!F:F,'KK6. Bổ sung'!N32,'TK 15661.Bản quyền phim '!X:X) | R32: =COUNTIF('TK 15661.Bản quyền phim '!F:F,'KK6. Bổ sung'!N32) | S32: =Q32+R32 | Y32: ✗ Not Found
... A41: K+1MOV025037 | B41: VND | C41: S0001883 | D41: Công Ty TNHH HÌNH ẢNH CON CHIM NHẠI | E41: Anti -piracy-contract 8 movies Mockingbird 2025 | F41: Movies International | G41: 1 | H41: 1 | I41: 1 | J41: 45688 | K41: 46052 | L41: Phim còn hạn từ 2026 | N41: LITTLE WOMEN (2019) | O41: =SUMIF('TK 15661.Bản quyền phim '!F:F,'KK6. Bổ sung'!D41,'TK 15661.Bản quyền phim '!X:X) | P41: =SUMIF('TK 15661.Bản quyền phim '!F:F,'KK6. Bổ sung'!N41,'TK 15661.Bản quyền phim '!X:X) | R41: =COUNTIF('TK 15661.Bản quyền phim '!F:F,'KK6. Bổ sung'!N41) | S41: =Q41+R41 | Y41: ✗ Not Found
A42: K+1MOV025053 | B42: VND | C42: S0001328 | D42: Công ty TNHH Skyline Media | E42: ARTICLE 20 | F42: Movies International | G42: 1 | H42: 3 | I42: 3 | J42: 45807 | K42: 46902 | L42: Phim còn hạn từ 2026 | M42: MOV_ACT587 | N42: RIDE ALONG | O42: =SUMIF('TK 15661.Bản quyền phim '!F:F,'KK6. Bổ sung'!D42,'TK 15661.Bản quyền phim '!X:X) | P42: =SUMIF('TK 15661.Bản quyền phim '!F:F,'KK6. Bổ sung'!N42,'TK 15661.Bản quyền phim '!X:X) | R42: =COUNTIF('TK 15661.Bản quyền phim '!F:F,'KK6. Bổ sung'!N42) | S42: =Q42+R42 | Y42: ✗ Not Found
A43: K+1DOC025186 | B43: USD | C43: S0001082 | D43: FCCE BV | E43: End Of Year Special 2025 | F43: Doc-Art | G43: 1 | H43: 1 | I43: 1 | J43: 45806 | K43: 46170 | L43: Phim còn hạn từ 2026 | M43: MOV_ROM_23__2697130 | N43: Time Freak | O43: =SUMIF('TK 15661.Bản quyền phim '!F:F,'KK6. Bổ sung'!D43,'TK 15661.Bản quyền phim '!X:X) | P43: =SUMIF('TK 15661.Bản quyền phim '!F:F,'KK6. Bổ sung'!N43,'TK 15661.Bản quyền phim '!X:X) | R43: =COUNTIF('TK 15661.Bản quyền phim '!F:F,'KK6. Bổ sung'!N43) | S43: =Q43+R43 | Y43: ✗ Not Found
A44: K+2SER025189 | B44: USD | C44: S0002419 | D44: PCCW Vuclip (Singapore) Pte. Ltd. | E44: Love's ambition (Hãy để tôi tỏa sáng) | F44: Series Asian | G44: 32 | H44: 5 | I44: 160 | J44: 45926 | K44: 47751 | L44: Phim còn hạn từ 2026 | M44: MOV_ACT_24__2715853 | N44: Cloudy Mountain (Chiều Sâu Vô Hạn) | O44: =SUMIF('TK 15661.Bản quyền phim '!F:F,'KK6. Bổ sung'!D44,'TK 15661.Bản quyền phim '!X:X) | P44: =SUMIF('TK 15661.Bản quyền phim '!F:F,'KK6. Bổ sung'!N44,'TK 15661.Bản quyền phim '!X:X) | R44: =COUNTIF('TK 15661.Bản quyền phim '!F:F,'KK6. Bổ sung'!N44) | S44: =Q44+R44 | Y44: ✗ Not Found

Sheet KK2. Series
A1: CÔNG TY: | B1: Công ty TNHH Truyền hình số vệ tinh Việt Nam | AO1: Cộng Hòa Xã Hội Chủ Nghĩa Việt Nam | AU1: Cộng Hòa Xã Hội Chủ Nghĩa Việt Nam
AO2: Độc Lập - Tự Do - Hạnh Phúc | AU2: Độc Lập - Tự Do - Hạnh Phúc
A3: BÁO CÁO KIỂM KÊ BẢN QUYỀN SERIES
A4: Thời điểm:….......giờ, ngày…....tháng.........năm 2026 | AT4: Check
A5: No. | B5: Clip code | C5: ENGLISH Title | D5: VIET Title | E5: Provider | F5: Contract number | G5: Origin | H5: Year of production | I5: No. of eps | J5: Duration (minute) | K5: Duration ( Hour) | L5: No. of eps (after Cut) | M5: Genre | N5: Main Genre | O5: From (DTH) | P5: To (DTH) | Q5: VSTV's 1st airing date | R5: Channel | S5: Exclusive (month) | T5: Sub-license | U5: OTT rights | V5: Catch-up | W5: SVOD | X5: FVOD | Y5: AVOD | Z5: TVOD | AA5: Internet Streaming | AB5: Internet Downloading | AC5: From (VOD) | AD5: To (VOD) | AE5: Runs No. | AF5: Broadcasted runs | AG5: Last broadcast date | AH5: Remain Run | AI5: HD Censorship | AJ5: LTO | AK5: Day And Date | AL5: Note | AM5: Tên trên file Kế toán | AN5: details kế toán | AO5: Giá trị còn lại (15661) | AP5: Check ref "242. BQ Phim VOD" | AQ5: Check ref "TK 15666. Phim SX" | AR5: Check ref "TK 15661. Bản quyền phim" | AS5: Phim Barter | AU5: SỐ LIỆU KIỂM KÊ | AX5: Giải trình chênh lệch | AY5: Đề xuất Phương án xử lý
AP6: =COUNTIF(AP7:AP174,1) | AQ6: =COUNTIF(AQ7:AQ174,1) | AR6: =COUNTIF(AR7:AR174,1) | AU6: Số lượng | AV6: From (VOD) | AW6: To (VOD) | AX6: Giải trình chênh lệch | AY6: Đề xuất Phương án xử lý | AZ6: Kết quả tìm
A7: 1 | B7: Voice: EP01 – SER_DRA_2656765 EP02 – SER_DRA_2656766 EP03 – SER_DRA_2656767 EP04 – SER_DRA_2656768 EP05 – SER_DRA_2656769 EP06 – SER_DRA_2656770 EP07 – SER_DRA_2656771 EP08 – SER_DRA_2656772 EP09 – SER_DRA_2656773 EP10 – SER_DRA_2656774 EP11 – SER_DRA_2656775 EP12 – SER_DRA_2656776 EP13 – SER_DRA_2656777 EP14 – SER_DRA_2656778 EP15 – SER_DRA_2656779 EP16 – SER_DRA_2656780 EP17 – SER_DRA_2656781 EP18 – SER_DRA_2656782 EP19 – SER_DRA_2656783 EP20 – SER_DRA_2656784 EP21 – SER_DRA_2656785 EP22 – SER_DRA_2656786 EP23 – SER_DRA_2656787 EP24 – SER_DRA_2656788 EP25 – SER_DRA_2656789 EP26 – SER_DRA_2656790 EP27 – SER_DRA_2656791 EP28 – SER_DRA_2656792 EP29 – SER_DRA_2656793 EP30 – SER_DRA_2656794 EP31 – SER_DRA_2656795 EP32 – SER_DRA_2656796 EP33 – SER_DRA_2656797 EP34 – SER_DRA_2656798 EP35 – SER_DRA_2656799 EP36 – SER_DRA_2656800 EP37 – SER_DRA_2656801 EP38 – SER_DRA_2656802 EP39 – SER_DRA_2656803 EP40 – SER_DRA_2656804 Sub: SER_DRA_21_2652587 LOVE IS TRUE, EP40 (VOD) SER_DRA_21_2652586 LOVE IS TRUE, EP39 (VOD) SER_DRA_21_2652585 LOVE IS TRUE, EP38 (VOD) SER_DRA_21_2652584 LOVE IS TRUE, EP37 (VOD) SER_DRA_21_2652581 LOVE IS TRUE, EP34 (VOD) SER_DRA_21_2652583 LOVE IS TRUE, EP36 (VOD) SER_DRA_21_2652582 LOVE IS TRUE, EP35 (VOD) SER_DRA_21_2652580 LOVE IS TRUE, EP33 (VOD) SER_DRA_21_2652579 LOVE IS TRUE, EP32 (VOD) SER_DRA_21_2652578 LOVE IS TRUE, EP31 (VOD) SER_DRA_21_2652577 LOVE IS TRUE, EP30 (VOD) SER_DRA_21_2652576 LOVE IS TRUE, EP29 (VOD) SER_DRA_21_2652575 LOVE IS TRUE, EP28 (VOD) SER_DRA_21_2652574 LOVE IS TRUE, EP27 (VOD) SER_DRA_21_2652572 LOVE IS TRUE, EP25 (VOD) SER_DRA_21_2652573 LOVE IS TRUE, EP26 (VOD) SER_DRA_21_2652571 LOVE IS TRUE, EP24 (VOD) SER_DRA_21_2652569 LOVE IS TRUE, EP22 (VOD) SER_DRA_21_2652570 LOVE IS TRUE, EP23 (VOD) SER_DRA_21_2652568 LOVE IS TRUE, EP21 (VOD) SER_DRA_21_2652567 LOVE IS TRUE, EP20 (VOD) SER_DRA_21_2652565 LOVE IS TRUE, EP18 (VOD) SER_DRA_21_2652566 LOVE IS TRUE, EP19 (VOD) SER_DRA_21_2652564 LOVE IS TRUE, EP17 (VOD) SER_DRA_21_2652563 LOVE IS TRUE, EP16 (VOD) SER_DRA_21_2652562 LOVE IS TRUE, EP15 (VOD) SER_DRA_21_2652561 LOVE IS TRUE, EP14 (VOD) SER_DRA_21_2652560 LOVE IS TRUE, EP13 (VOD) SER_DRA_21_2652558 LOVE IS TRUE, EP11 (VOD) SER_DRA_21_2652559 LOVE IS TRUE, EP12 (VOD) SER_DRA_21_2652557 LOVE IS TRUE, EP10 (VOD) SER_DRA_21_2652555 LOVE IS TRUE, EP08 (VOD) SER_DRA_21_2652556 LOVE IS TRUE, EP09 (VOD) SER_DRA_21_2652554 LOVE IS TRUE, EP07 (VOD) SER_DRA_21_2652553 LOVE IS TRUE, EP06 (VOD) SER_DRA_21_2652551 LOVE IS TRUE, EP04 (VOD) SER_DRA_21_2652552 LOVE IS TRUE, EP05 (VOD) SER_DRA_21_2652550 LOVE IS TRUE, EP03 (VOD) SER_DRA_21_2652549 LOVE IS TRUE, EP02 (VOD) SER_DRA__2652548 LOVE IS TRUE, EP01 (VOD) | C7: LOVE IS TRUE | D7: THẬT LÒNG YÊU EM | E7: Hangzhou IX Media | F7: IX Media/Love is True | G7: China | H7: 2021 | I7: 40 | J7: 45 | K7: =(I7*J7)/60 | L7: =I7 | M7: Drama, Romance | N7: Romance | O7: 44394 | P7: 46219 | Q7: 44595 | R7: K+LIFE | S7: Exclusive All TV Rights and All VOD Rights during LP | T7: Yes | U7: Yes | V7: Yes | W7: Yes | X7: Yes | Y7: Yes | Z7: Yes | AA7: No | AB7: No | AC7: 44394 | AD7: 46219 | AE7: Unlimited | AF7: 3 | AG7: 44600 | AH7: Unlimited | AI7: Yes | AJ7: Yes | AL7: Phim còn hạn từ 2026 | AM7: LOVE IS TRUE | AO7: =SUMIF('TK 15661.Bản quyền phim '!F:F,'KK2. Series'!C7,'TK 15661.Bản quyền phim '!K:K) | AP7: =COUNTIF('242.BQ Phim VOD'!$C$5:$C$8,'KK2. Series'!AM7) | AQ7: =COUNTIF('TK 15666. Phim SX'!$C$6:$C$13,'KK2. Series'!AM7) | AR7: =COUNTIF('TK 15661.Bản quyền phim '!F:F,'KK2. Series'!AM7) | AT7: =SUM(AP7:AS7) | AZ7: ✓ Found
A8: 2 | B8: EP01 – SER_DRA_21_2646178 EP02 – SER_DRA_21_1615510795318_2646179 EP03 – SER_DRA_21_1615510795319_2646180 EP04 – SER_DRA_21_1615510795320_2646181 EP05 – SER_DRA_21_1615510795321_2646182 EP06 – SER_DRA_21_1615510795322_2646183 EP07 – SER_DRA_21_1615510795323_2646184 EP08 – SER_DRA_21_1615510795324_2646185 EP09 – SER_DRA_21_1615510795325_2646186 EP10 – SER_DRA_21_1615510795326_2646187 EP11 – SER_DRA_21_1615510795327_2646188 EP12 – SER_DRA_21_1615510795328_2646189 EP13 – SER_DRA_21_1615510795329_2646190 EP14 – SER_DRA_21_2647854 EP15 – SER_DRA_21_1615510795331_2646192 EP16 – SER_DRA_21_1615510795332_2646193 EP17 – SER_DRA_21_1615510795333_2646194 EP18 – SER_DRA_21_1615510795334_2646195 EP19 – SER_DRA_21_1615510795335_2646196 EP20 – SER_DRA_21_1615510795336_2646197 EP21 – SER_DRA_21_1615510795337_2646198 EP22 – SER_DRA_21_1615510795338_2646199 EP23 – SER_DRA_21_1615510795339_2646200 | C8: Mother To Be | D8: Hành trang làm mẹ | E8: IX Media | F8: IX Media/Mother to be | G8: Taiwan | H8: 2020 | I8: 24 | J8: 45 | K8: =(I8*J8)/60 | L8: =I8 | M8: Romance x Drama x Family | N8: Drama | O8: 44286 | P8: 46111 | Q8: 44291 | R8: K+LIFE | T8: Yes | U8: Yes | V8: Yes | W8: Yes | X8: Yes | Y8: Yes | Z8: Yes | AA8: No | AB8: No | AC8: 44286 | AD8: 46111 | AE8: Unlimited | AF8: 8 | AG8: 44703 | AH8: Unlimited | AI8: Yes | AJ8: Yes | AL8: Phim còn hạn từ 2026 | AM8: Mother To Be | AO8: =SUMIF('TK 15661.Bản quyền phim '!F:F,'KK2. Series'!C8,'TK 15661.Bản quyền phim '!K:K) | AP8: =COUNTIF('242.BQ Phim VOD'!$C$5:$C$8,'KK2. Series'!AM8) | AQ8: =COUNTIF('TK 15666. Phim SX'!$C$6:$C$13,'KK2. Series'!AM8) | AR8: =COUNTIF('TK 15661.Bản quyền phim '!F:F,'KK2. Series'!AM8) | AT8: =SUM(AP8:AS8) | AZ8: ✓ Found
A9: 3 | B9: EP01 – SER_HIS_2688539 EP02 – SER_HIS_2688540 EP03 – SER_HIS_2688541 EP04 – SER_HIS_2688542 EP05 – SER_HIS_2688543 EP06 – SER_HIS_2688544 EP07 – SER_HIS_2688545 EP08 – SER_HIS_2688546 EP09 – SER_HIS_2688547 EP10 – SER_HIS_2688548 EP11 – SER_HIS_2688549 EP12 – SER_HIS_2688550 EP13 – SER_HIS_2688551 EP14 – SER_HIS_2688552 EP15 – SER_HIS_2688553 EP16 – SER_HIS_2688554 EP17 – SER_HIS_2688555 EP18 – SER_HIS_2688556 EP19 – SER_HIS_2688557 EP20 – SER_HIS_2688558 EP21 – SER_HIS_2688559 EP22 – SER_HIS_2688560 EP23 – SER_HIS_2688561 EP24 – SER_HIS_2688562 EP25 – SER_HIS_2688563 EP26 – SER_HIS_2688564 EP27 – SER_HIS_2688565 EP28 – SER_HIS_2688566 EP29 – SER_HIS_2688567 EP30 – SER_HIS_2688568 EP31 – SER_HIS_2689763 EP32 – SER_HIS_2688570 | C9: King of tears – Lee Bangwon | D9: Vương quyền đẫm máu | E9: King Content | F9: 130/2022/HDBQ/VSTV-KC | G9: Korea | H9: 2021 | I9: 32 | J9: 45 | K9: =(I9*J9)/60 | L9: =I9 | M9: Costume, historical | N9: Drama | O9: 44971 | P9: 46066 | Q9: 44971 | R9: K+LIFE | S9: Exclusive All Pay TV Rights and Non exclusive All VOD during LP | T9: Yes | U9: Yes | V9: Yes | W9: Yes | X9: Yes | Y9: Yes | Z9: Yes | AA9: Yes | AB9: Yes | AC9: 44971 | AD9: 46066 | AE9: Unlimited | AF9: 8 | AG9: 45738 | AH9: Unlimited | AI9: Yes | AJ9: Yes | AL9: Phim còn hạn từ 2026 | AM9: King of tears - Lee Bangwon | AO9: =SUMIF('TK 15661.Bản quyền phim '!F:F,'KK2. Series'!C9,'TK 15661.Bản quyền phim '!K:K) | AP9: =COUNTIF('242.BQ Phim VOD'!$C$5:$C$8,'KK2. Series'!AM9) | AQ9: =COUNTIF('TK 15666. Phim SX'!$C$6:$C$13,'KK2. Series'!AM9) | AR9: =COUNTIF('TK 15661.Bản quyền phim '!F:F,'KK2. Series'!AM9) | AT9: =SUM(AP9:AS9) | AZ9: ✓ Found
A10: 4 | B10: EP01 – SER_DRA_2693039 EP02 – SER_DRA_2693040 EP03 – SER_DRA_2693041 EP04 – SER_DRA_2693042 EP05 – SER_DRA_2693043 EP06 – SER_DRA_2693044 EP07 – SER_DRA_2693045 EP08 – SER_DRA_2693046 EP09 – SER_DRA_2693047 EP10 – SER_DRA_2693048 EP11 – SER_DRA_2693049 EP12 – SER_DRA_2693050 EP13 – SER_DRA_2693051 EP14 – SER_DRA_2693052 EP15 – SER_DRA_2693053 EP16 – SER_DRA_2693054 EP17 – SER_DRA_2693055 EP18 – SER_DRA_2693056 EP19 – SER_DRA_2693057 EP20 – SER_DRA_2693058 EP21 – SER_DRA_2693059 EP22 – SER_DRA_2693060 EP23 – SER_DRA_2693061 EP24 – SER_DRA_2693062 EP25 – SER_DRA_2693063 EP26 – SER_DRA_2693064 EP27 – SER_DRA_2693065 EP28 – SER_DRA_2693066 EP29 – SER_DRA_2693067 EP30 – SER_DRA_2693068 EP31 – SER_DRA_2693069 EP32 – SER_DRA_2693070 EP33 – SER_DRA_2693071 EP34 – SER_DRA_2693072 EP35 – SER_DRA_2693073 EP36 – SER_DRA_2693074 EP37 – SER_DRA_2693075 EP38 – SER_DRA_2693076 | C10: Ordinary Greatness | D10: Cảnh sát vinh dự | E10: iQiYi | F10: 46/2023/HDBQ/VSTV-IQIYI | G10: China | H10: 2022 | I10: 38 | J10: 45 | K10: =(I10*J10)/60 | L10: =I10 | M10: Drama, Youth, Action | N10: Drama | O10: 45041 | P10: 46501 | Q10: 45055 | R10: K+LIFE | S10: Exclusive all Pay TV rights; Non exclusive SVOD + TVOD rights | T10: No | U10: Yes | V10: Yes | W10: Yes | X10: No | Y10: No | Z10: Yes | AA10: No | AB10: No | AC10: 45041 | AD10: 46501 | AE10: Unlimited | AF10: 5 | AG10: 45059 | AH10: Unlimited | AI10: Yes | AJ10: Yes | AL10: Phim còn hạn từ 2026 | AM10: Greatness Ordinary | AO10: =SUMIF('TK 15661.Bản quyền phim '!F:F,'KK2. Series'!C10,'TK 15661.Bản quyền phim '!K:K) | AP10: =COUNTIF('242.BQ Phim VOD'!$C$5:$C$8,'KK2. Series'!AM10) | AQ10: =COUNTIF('TK 15666. Phim SX'!$C$6:$C$13,'KK2. Series'!AM10) | AR10: =COUNTIF('TK 15661.Bản quyền phim '!F:F,'KK2. Series'!AM10) | AT10: =SUM(AP10:AS10) | AZ10: ✓ Found
A11: 5 | B11: Voice: EP01 – SER_ROM_2693823 EP02 – SER_ROM_2693829 EP03 – SER_ROM_2693830 EP04 – SER_ROM_2693831 EP05 – SER_ROM_2693832 EP06 – SER_ROM_2693833 EP07 – SER_ROM_2693834 EP08 – SER_ROM_2693835 EP09 – SER_ROM_2693836 EP10 – SER_ROM_2693837 EP11 – SER_ROM_2693838 EP12 – SER_ROM_2693839 EP13 – SER_ROM_2693840 EP14 – SER_ROM_2693841 EP15 – SER_ROM_2693842 EP16 – SER_ROM_2693843 EP17 – SER_ROM_2693844 EP18 – SER_ROM_2693845 EP19 – SER_ROM_2693846 EP20 – SER_ROM_2693847 EP21 – SER_ROM_2693848 EP22 – SER_ROM_2693849 EP23 – SER_ROM_2693850 EP24 – SER_ROM_2693851 EP25 – SER_ROM_2693852 EP26 – SER_ROM_2693853 EP27 – SER_ROM_2693854 Sub: SER_ROM_23_2693392 The secret romantic guesthouse, Ep18 SER_ROM_23_2693391 The secret romantic guesthouse, Ep17 SER_ROM_23_2693390 The secret romantic guesthouse, Ep16 SER_ROM_23_2693388 The secret romantic guesthouse, Ep14 SER_ROM_23_2693389 The secret romantic guesthouse, Ep15 SER_ROM_23_2693387 The secret romantic guesthouse, Ep13 SER_ROM_23_2693386 The secret romantic guesthouse, Ep12 SER_ROM_23_2693383 The secret romantic guesthouse, Ep09 SER_ROM_23_2693385 The secret romantic guesthouse, Ep11 SER_ROM_23_2693384 The secret romantic guesthouse, Ep10 SER_ROM_23_2693381 The secret romantic guesthouse, Ep07 SER_ROM_23_2693382 The secret romantic guesthouse, Ep08 SER_ROM_23_2693380 The secret romantic guesthouse, Ep06 SER_ROM_23_2693379 The secret romantic guesthouse, Ep05 SER_ROM_23_2693377 The secret romantic guesthouse, Ep03 SER_ROM_23_2693378 The secret romantic guesthouse, Ep04 SER_ROM_23_2693376 The secret romantic guesthouse, Ep02 SER_ROM_23__2693375 The secret romantic guesthouse, Ep01 | C11: The Secret Romantic Guesthouse | D11: Quán trọ tình yêu | E11: PCCW VUCLIP | F11: PCCW VUCLIP/2023/HDBQ The Secret Romantic Guesthouse | G11: Korea | H11: 2023 | I11: 18 | J11: 70 | K11: =(I11*J11)/60 | L11: 26 | M11: Costume, historical | N11: Romance | O11: 45005 | P11: 46100 | Q11: 45065 | R11: K+LIFE | S11: Exclusive All TV Rights during LP and Exclusive All VOD rights for first 3 months | T11: Yes | U11: Yes | V11: Yes | W11: Yes | X11: Yes | Y11: Yes | Z11: Yes | AA11: Yes | AB11: Yes | AC11: 45005 | AD11: 46100 | AE11: 8 | AF11: 3 | AG11: 45071 | AH11: =AE11-AF11 | AI11: Yes | AJ11: Yes | AK11: Phim Song song | AL11: Phim còn hạn từ 2026 | AM11: The Secret Romantic Guesthouse | AO11: =SUMIF('TK 15661.Bản quyền phim '!F:F,'KK2. Series'!C11,'TK 15661.Bản quyền phim '!K:K) | AP11: =COUNTIF('242.BQ Phim VOD'!$C$5:$C$8,'KK2. Series'!AM11) | AQ11: =COUNTIF('TK 15666. Phim SX'!$C$6:$C$13,'KK2. Series'!AM11) | AR11: =COUNTIF('TK 15661.Bản quyền phim '!F:F,'KK2. Series'!AM11) | AT11: =SUM(AP11:AS11) | AZ11: ✓ Found
A12: 6 | B12: Voice: EP01 – SER_FAN_23_2702437 EP02 – SER_FAN_23_2702438 EP03 – SER_FAN_23_2702439 EP04 – SER_FAN_23_2702440 EP05 – SER_FAN_23_2702441 EP06 – SER_FAN_23_2702442 EP07 – SER_FAN_23_2702443 EP08 – SER_FAN_23_2702444 EP09 – SER_FAN_23_2702445 EP10 – SER_FAN_23_2702446 EP11 – SER_FAN_23_2702447 EP12 – SER_FAN_23_2702448 EP13 – SER_FAN_23_2702449 EP14 – SER_FAN_23_2702450 EP15 – SER_FAN_23_2702451 EP16 – SER_FAN_23_2702452 EP17 – SER_FAN_23_2702453 EP18 – SER_FAN_23_2702454 EP19 – SER_FAN_23_2702455 EP20 – SER_FAN_23_2702456 EP21 – SER_FAN_23_2702457 EP22 – SER_FAN_23_2702458 EP23 – SER_FAN_23_2702459 EP24 – SER_FAN_23_2702460 EP25 – SER_FAN_23_2702461 Sub: SER_FAN_23_2699038 (KHÔNG DÙNG) Durian's Affair, Ep16 SER_FAN_23_2699037 (KHÔNG DÙNG) Durian's Affair, Ep15 SER_FAN_23_2699034 (KHÔNG DÙNG) Durian's Affair, Ep12 SER_FAN_23_2699035 (KHÔNG DÙNG) Durian's Affair, Ep13 SER_FAN_23_2699036 (KHÔNG DÙNG) Durian's Affair, Ep14 SER_FAN_23_2699032 (KHÔNG DÙNG) Durian's Affair, Ep10 SER_FAN_23_2699033 (KHÔNG DÙNG) Durian's Affair, Ep11 SER_FAN_23_2699030 (KHÔNG DÙNG) Durian's Affair, Ep08 SER_FAN_23_2699029 (KHÔNG DÙNG) Durian's Affair, Ep07 SER_FAN_23_2699026 (KHÔNG DÙNG) Durian's Affair, Ep04 SER_FAN_23_2699027 (KHÔNG DÙNG) Durian's Affair, Ep05 SER_FAN_23_2699028 (KHÔNG DÙNG) Durian's Affair, Ep06 SER_FAN_23_2699025 (KHÔNG DÙNG) Durian's Affair, Ep03 SER_FAN_23_2699024 (KHÔNG DÙNG) Durian's Affair, Ep02 SER_FAN_23__2699023 (KHÔNG DÙNG) Durian's Affair, Ep01 | C12: Durian's Affair | D12: Phu nhân Du Ri An | E12: LIAN Contents | F12: 90A/2023/HDBQ/VSTV_Lian Contents | G12: Korea | H12: 2023 | I12: 16 | J12: 70 | K12: =(I12*J12)/60 | L12: 25 | M12: Fantasy/ Melodrama/ Time Travel | N12: Drama | O12: 45101 | P12: 46561 | Q12: 45101 | R12: K+LIFE | S12: Exclusive All TV and All VOD Rights during LP. | T12: Yes | U12: Yes | V12: Yes | W12: Yes | X12: Yes | Y12: Yes | Z12: Yes | AA12: Yes | AB12: Yes | AC12: 45101 | AD12: 46561 | AE12: Unlimited | AF12: 1 | AG12: 45101 | AH12: Unlimited | AI12: Yes | AJ12: Yes | AK12: Phim Song song | AL12: Phim còn hạn từ 2026 | AM12: Durian’s Affair | AO12: =SUMIF('TK 15661.Bản quyền phim '!F:F,'KK2. Series'!C12,'TK 15661.Bản quyền phim '!K:K) | AP12: =COUNTIF('242.BQ Phim VOD'!$C$5:$C$8,'KK2. Series'!AM12) | AQ12: =COUNTIF('TK 15666. Phim SX'!$C$6:$C$13,'KK2. Series'!AM12) | AR12: =COUNTIF('TK 15661.Bản quyền phim '!F:F,'KK2. Series'!AM12) | AT12: =SUM(AP12:AS12) | AZ12: ✓ Found
A13: 7 | B13: EP01 – SER_THR_23_2695781 EP02 – SER_THR_23_2695782 EP03 – SER_THR_23_2695783 EP04 – SER_THR_23_2695784 EP05 – SER_THR_23_2695785 EP06 – SER_THR_23_2695786 EP07 – SER_THR_23_2695787 EP08 – SER_THR_23_2695788 EP09 – SER_THR_23_2695789 EP10 – SER_THR_23_2695790 EP11 – SER_THR_23_2695791 EP12 – SER_THR_23_2695792 EP13 – SER_THR_23_2695793 EP14 – SER_THR_23_2695794 EP15 – SER_THR_23_2695795 EP16 – SER_THR_23_2695796 EP17 – SER_THR_23_2695797 EP18 – SER_THR_23_2695798 EP19 – SER_THR_23_2695799 EP20 – SER_THR_23_2695800 EP21 – SER_THR_23_2695801 EP22 – SER_THR_23_2695802 EP23 – SER_THR_23_2695803 EP24 – SER_THR_23_2695804 EP25 – SER_THR_23_2695805 EP26 – SER_THR_23_2695806 EP27 – SER_THR_23_2695807 EP28 – SER_THR_23_2695808 EP29 – SER_THR_23_2695809 EP30 – SER_THR_23_2695810 EP31 – SER_THR_23_2695811 EP32 – SER_THR_23_2695812 | C13: DAY AND NIGHT | D13: Bạch dạ truy hung | E13: YouKu | F13: 73/2023/HDBQ/VSTV-Youku | G13: China | H13: 2017 | I13: 32 | J13: 45 | K13: =(I13*J13)/60 | L13: =I13 | M13: Crime, Thriller | N13: Crime, Thriller | O13: 45107 | P13: 46567 | Q13: 45110 | R13: K+LIFE | S13: Exclusive all Pay TV rights; Non exclusive all VOD rights | T13: No | U13: Yes | V13: Yes | W13: Yes | X13: No | Y13: No | Z13: Yes | AA13: No | AB13: No | AC13: 45107 | AD13: 46567 | AE13: Unlimited | AF13: 5 | AG13: 45115 | AH13: Unlimited | AI13: Yes | AJ13: Yes | AL13: Phim còn hạn từ 2026 | AM13: DAY AND NIGHT | AO13: =SUMIF('TK 15661.Bản quyền phim '!F:F,'KK2. Series'!C13,'TK 15661.Bản quyền phim '!K:K) | AP13: =COUNTIF('242.BQ Phim VOD'!$C$5:$C$8,'KK2. Series'!AM13) | AQ13: =COUNTIF('TK 15666. Phim SX'!$C$6:$C$13,'KK2. Series'!AM13) | AR13: =COUNTIF('TK 15661.Bản quyền phim '!F:F,'KK2. Series'!AM13) | AT13: =SUM(AP13:AS13) | AZ13: ✓ Found
A14: 8 | B14: EP01 – SER_COM_22_2687297 EP02 – SER_COM_22_2687298 EP03 – SER_COM_22_2687299 EP04 – SER_COM_22_2687300 EP05 – SER_COM_22_2687301 EP06 – SER_COM_22_2687359 EP07 – SER_COM_22_2687303 EP08 – SER_COM_22_2687304 EP09 – SER_COM_22_2687305 EP10 – SER_COM_22_2687306 EP11 – SER_COM_22_2687307 EP12 – SER_COM_22_2687308 EP13 – SER_COM_22_2687309 EP14 – SER_COM_22_2687310 EP15 – SER_COM_22_2687311 EP16 – SER_COM_22_2687312 EP17 – SER_COM_22_2687313 EP18 – SER_COM_22_2687314 | C14: Good Job | D14: Đối tác hoàn hảo | E14: King Content | F14: 130/2022/HDBQ/VSTV-KC | G14: Korea | H14: 2022 | I14: 18 | J14: 45 | K14: =(I14*J14)/60 | L14: =I14 | M14: Romance, comedy, investigates | N14: Romance | O14: 44945 | P14: 46040 | Q14: 44959 | R14: K+LIFE | S14: Exclusive All Pay TV Rights and Non exclusive All VOD during LP | T14: Yes | U14: Yes | V14: Yes | W14: Yes | X14: Yes | Y14: Yes | Z14: Yes | AA14: Yes | AB14: Yes | AC14: 44945 | AD14: 46040 | AE14: Unlimited | AF14: 11 | AG14: 45714 | AH14: Unlimited | AI14: Yes | AJ14: Yes | AL14: Phim còn hạn từ 2026 | AM14: Good Job | AO14: =SUMIF('TK 15661.Bản quyền phim '!F:F,'KK2. Series'!C14,'TK 15661.Bản quyền phim '!K:K) | AP14: =COUNTIF('242.BQ Phim VOD'!$C$5:$C$8,'KK2. Series'!AM14) | AQ14: =COUNTIF('TK 15666. Phim SX'!$C$6:$C$13,'KK2. Series'!AM14) | AR14: =COUNTIF('TK 15661.Bản quyền phim '!F:F,'KK2. Series'!AM14) | AT14: =SUM(AP14:AS14) | AZ14: ✓ Found
A15: 9 | B15: Voice: EP01 – SER_ROM_23_2702541 EP02 – SER_ROM_23_2702542 EP03 – SER_ROM_23_2702543 EP04 – SER_ROM_23_2702544 EP05 – SER_ROM_23_2702545 EP06 – SER_ROM_23_2702546 EP07 – SER_ROM_23_2702547 EP08 – SER_ROM_23_2702548 EP09 – SER_ROM_23_2702549 EP10 – SER_ROM_23_2702550 EP11 – SER_ROM_23_2702551 EP12 – SER_ROM_23_2702552 EP13 – SER_ROM_23_2702553 EP14 – SER_ROM_23_2702554 EP15 – SER_ROM_23_2702555 EP16 – SER_ROM_23_2702556 EP17 – SER_ROM_23_2702557 EP18 – SER_ROM_23_2702558 EP19 – SER_ROM_23_2702559 EP20 – SER_ROM_23_2702560 EP21 – SER_ROM_23_2702561 EP22 – SER_ROM_23_2702562 EP23 – SER_ROM_23_2702563 EP24 – SER_ROM_23_2702564 EP25 – SER_ROM_23_2702565 EP26 – SER_ROM_23_2702566 EP27 – SER_ROM_23_2702567 EP28 – SER_ROM_23_2702568 EP29 – SER_ROM_23_2702569 EP30 – SER_ROM_23_2702570 EP31 – SER_ROM_23_2702571 EP32 – SER_ROM_23_2702572 EP33 – SER_ROM_23_2702573 EP34 – SER_ROM_23_2702574 EP35 – SER_ROM_23_2702575 EP36 – SER_ROM_23_2702576 EP37 – SER_ROM_23_2702577 EP38 – SER_ROM_23_2702578 EP39 – SER_ROM_23_2702579 EP40 – SER_ROM_23_2702580 Sub: SER_ROM_23_2699474 (SUB) Fireworks of my heart, Ep40 SER_ROM_23_2699473 (SUB) Fireworks of my heart, Ep39 SER_ROM_23_2699472 (SUB) Fireworks of my heart, Ep38 SER_ROM_23_2699471 (SUB) Fireworks of my heart, Ep37 SER_ROM_23_2699468 (SUB) Fireworks of my heart, Ep34 SER_ROM_23_2699470 (SUB) Fireworks of my heart, Ep36 SER_ROM_23_2699469 (SUB) Fireworks of my heart, Ep35 SER_ROM_23_2699466 (SUB) Fireworks of my heart, Ep32 SER_ROM_23_2699467 (SUB) Fireworks of my heart, Ep33 SER_ROM_23_2699464 (SUB) Fireworks of my heart, Ep30 SER_ROM_23_2699463 (SUB) Fireworks of my heart, Ep29 SER_ROM_23_2699465 (SUB) Fireworks of my heart, Ep31 SER_ROM_23_2699461 (SUB) Fireworks of my heart, Ep27 SER_ROM_23_2699462 (SUB) Fireworks of my heart, Ep28 SER_ROM_23_2699460 (SUB) Fireworks of my heart, Ep26 SER_ROM_23_2699459 (SUB) Fireworks of my heart, Ep25 SER_ROM_23_2699458 (SUB) Fireworks of my heart, Ep24 SER_ROM_23_2699455 (SUB) Fireworks of my heart, Ep21 SER_ROM_23_2699457 (SUB) Fireworks of my heart, Ep23 SER_ROM_23_2699456 (SUB) Fireworks of my heart, Ep22 SER_ROM_23_2699453 (SUB) Fireworks of my heart, Ep19 SER_ROM_23_2699454 (SUB) Fireworks of my heart, Ep20 SER_ROM_23_2699451 (SUB) Fireworks of my heart, Ep17 SER_ROM_23_2699452 (SUB) Fireworks of my heart, Ep18 SER_ROM_23_2699450 (SUB) Fireworks of my heart, Ep16 SER_ROM_23_2699449 (SUB) Fireworks of my heart, Ep15 SER_ROM_23_2699448 (SUB) Fireworks of my heart, Ep14 SER_ROM_23_2699446 (SUB) Fireworks of my heart, Ep12 SER_ROM_23_2699447 (SUB) Fireworks of my heart, Ep13 SER_ROM_23_2699445 (SUB) Fireworks of my heart, Ep11 SER_ROM_23_2699444 (SUB) Fireworks of my heart, Ep10 SER_ROM_23_2699443 (SUB) Fireworks of my heart, Ep09 SER_ROM_23_2699441 (SUB) Fireworks of my heart, Ep07 SER_ROM_23_2699442 (SUB) Fireworks of my heart, Ep08 SER_ROM_23_2699440 (SUB) Fireworks of my heart, Ep06 SER_ROM_23_2699439 (SUB) Fireworks of my heart, Ep05 SER_ROM_23_2699438 (SUB) Fireworks of my heart, Ep04 SER_ROM_23_2699437 (SUB) Fireworks of my heart, Ep03 SER_ROM_23_2699436 (SUB) Fireworks of my heart, Ep02 SER_ROM__2699435 (SUB) Fireworks of my heart, Ep01 | C15: Fireworks of My Heart | D15: Khói lửa nhân gian của tôi | E15: Youhug Media | F15: 95/2023/HDBQ/VSTV_Youhug media | G15: China | H15: 2023 | I15: 40 | J15: 45 | K15: =(I15*J15)/60 | L15: =I15 | M15: Action, Romance, Medical | N15: Romance | O15: 45110 | P15: 46936 | Q15: 45124 | R15: K+LIFE | S15: Exclusive All TV and All VOD Rights during LP. | T15: Yes | U15: Yes | V15: Yes | W15: Yes | X15: Yes | Y15: Yes | Z15: Yes | AA15: Yes | AB15: Yes | AC15: 45110 | AD15: 46936 | AE15: Unlimited | AF15: 4 | AG15: 45138 | AH15: Unlimited | AI15: Yes | AJ15: Yes | AK15: Phim Song song | AL15: Phim còn hạn từ 2026 | AM15: My Fireworks on Earth/Fireworks of My Heart (Khói lửa nhân gian của tôi) | AO15: =SUMIF('TK 15661.Bản quyền phim '!F:F,'KK2. Series'!C15,'TK 15661.Bản quyền phim '!K:K) | AP15: =COUNTIF('242.BQ Phim VOD'!$C$5:$C$8,'KK2. Series'!AM15) | AQ15: =COUNTIF('TK 15666. Phim SX'!$C$6:$C$13,'KK2. Series'!AM15) | AR15: =COUNTIF('TK 15661.Bản quyền phim '!F:F,'KK2. Series'!AM15) | AT15: =SUM(AP15:AS15) | AZ15: ✓ Found
A16: 10 | B16: EP01 – SER_COM_23_2699233 EP02 – SER_COM_23_2699234 EP03 – SER_COM_23_2699235 EP04 – SER_COM_23_2699236 EP05 – SER_COM_23_2699237 | C16: Nemesis | D16: Biệt đội mỹ nhân báo thù | E16: KT StudioGenie | F16: KT StudioGenie/Nemesis Crime Puzzle | G16: Korea | H16: 2021 | I16: 3 | J16: 70 | K16: =(I16*J16)/60 | L16: 5 | M16: Comedy, Drama, Melodrama | N16: Comedy | O16: 45107 | P16: 46933 | Q16: 45143 | R16: K+LIFE | S16: Exclusive All TV and All VOD Rights during LP. | T16: No | U16: Yes | V16: Yes | W16: Yes | X16: Yes | Y16: Yes | Z16: Yes | AA16: Yes | AB16: Yes | AC16: 45107 | AD16: 46933 | AE16: Unlimited | AF16: 1 | AG16: 45143 | AH16: Unlimited | AI16: Yes | AJ16: Yes | AL16: Phim còn hạn từ 2026 | AM16: Nemesis | AO16: =SUMIF('TK 15661.Bản quyền phim '!F:F,'KK2. Series'!C16,'TK 15661.Bản quyền phim '!K:K) | AP16: =COUNTIF('242.BQ Phim VOD'!$C$5:$C$8,'KK2. Series'!AM16) | AQ16: =COUNTIF('TK 15666. Phim SX'!$C$6:$C$13,'KK2. Series'!AM16) | AR16: =COUNTIF('TK 15661.Bản quyền phim '!F:F,'KK2. Series'!AM16) | AT16: =SUM(AP16:AS16) | AZ16: ✓ Found
A17: 11 | B17: EP01 – SER_DRA_22_2686542 EP02 – SER_DRA_22_2686543 EP03 – SER_DRA_22_2686544 EP04 – SER_DRA_22_2691063 EP05 – SER_DRA_22_2686546 EP06 – SER_DRA_22_2686547 EP07 – SER_DRA_22_2686548 EP08 – SER_DRA_22_2686549 EP09 – SER_DRA_22_2686550 EP10 – SER_DRA_22_2691064 EP11 – SER_DRA_22_2686552 EP12 – SER_DRA_22_2691065 EP13 – SER_DRA_22_2686554 EP14 – SER_DRA_22_2686555 EP15 – SER_DRA_22_2686556 EP16 – SER_DRA_22_2686557 EP17 – SER_DRA_22_2686558 EP18 – SER_DRA_22_2686559 EP19 – SER_DRA_22_2686560 EP20 – SER_DRA_22_2686561 EP21 – SER_DRA_22_2686562 EP22 – SER_DRA_22_2686563 EP23 – SER_DRA_22_2686564 EP24 – SER_DRA_22_2686565 EP25 – SER_DRA_22_2686566 EP26 – SER_DRA_22_2686567 | C17: Reborn Rich (VIU) | D17: Cậu út nhà tài phiệt | E17: Pro Partner | F17: 55/2023/HDBQ/VSTV_Pro Partner | G17: Korea | H17: 2022 | I17: 26 | J17: 45 | K17: =(I17*J17)/60 | L17: =I17 | M17: Drama , Fantasy , Revenge | N17: Drama | O17: 45005 | P17: 46100 | Q17: 45019 | R17: K+LIFE | S17: Exclusive All TV Rights the first 9 months of LP Non-exclusive with All Catch-up TV Rights; All VOD Rights during LP | T17: No | U17: Yes | V17: Yes | W17: Yes | X17: Yes | Y17: Yes | Z17: Yes | AA17: Yes | AB17: Yes | AC17: 45005 | AD17: 46100 | AE17: Unlimited | AF17: 8 | AG17: 45160 | AH17: Unlimited | AI17: Yes | AJ17: Yes | AL17: Phim còn hạn từ 2026 | AM17: Reborn Rich (Cậu út nhà tài phiệt) | AO17: =SUMIF('TK 15661.Bản quyền phim '!F:F,'KK2. Series'!C17,'TK 15661.Bản quyền phim '!K:K) | AP17: =COUNTIF('242.BQ Phim VOD'!$C$5:$C$8,'KK2. Series'!AM17) | AQ17: =COUNTIF('TK 15666. Phim SX'!$C$6:$C$13,'KK2. Series'!AM17) | AR17: =COUNTIF('TK 15661.Bản quyền phim '!F:F,'KK2. Series'!AM17) | AT17: =SUM(AP17:AS17) | AZ17: ⚠ Partial (25/26 clips)
A18: 12 | B18: Sub: SER_ROM_23_2697871 (Old) One day off, Ep08 SER_ROM_23_2697869 (Old) One day off, Ep06 SER_ROM_23_2697870 (Old) One day off, Ep07 SER_ROM_23_2697868 (Old) One day off, Ep05 SER_ROM_23_2697867 (Old) One day off, Ep04 SER_ROM_23_2697866 (Old) One day off, Ep03 SER_ROM_23_2697865 (Old) One day off, Ep02 SER_ROM_23__2697864 (Old) One day off, Ep01 Voice: SER_ROM_23_2698231 One day off, Ep07 SER_ROM_23_2698232 One day off, Ep08 SER_ROM_23_2698228 One day off, Ep04 SER_ROM_23_2698229 One day off, Ep05 SER_ROM_23_2698230 One day off, Ep06 SER_ROM_23_2698227 One day off, Ep03 SER_ROM_23_2698226 One day off, Ep02 SER_ROM_23__2698225 One day off, Ep01 | C18: One Day Off | D18: Nhật ký lãng du | E18: wavve | F18: 90A/2023/HDBQ/VSTV_Wave | G18: Korea | H18: 2023 | I18: 8 | J18: 25 | K18: =(I18*J18)/60 | L18: =I18 | M18: Romance, Drama, Travel, Slice-of-life | N18: Drama | O18: 45070 | P18: 46530 | Q18: 45108 | R18: K+LIFE | S18: Exclusive All TV Rights during LP. Exclusive All VOD during first year of LP. Non-exclusive All VOD Rights the remaining 3 years of LP | T18: Yes | U18: Yes | V18: Yes | W18: Yes | X18: Yes | Y18: Yes | Z18: Yes | AA18: Yes | AB18: Yes | AC18: 45070 | AD18: 46530 | AE18: Unlimited | AF18: 3 | AG18: 45202 | AH18: Unlimited | AI18: Yes | AJ18: Yes | AK18: Phim Song song | AL18: Phim còn hạn từ 2026 | AM18: One Day Off | AO18: =SUMIF('TK 15661.Bản quyền phim '!F:F,'KK2. Series'!C18,'TK 15661.Bản quyền phim '!K:K) | AP18: =COUNTIF('242.BQ Phim VOD'!$C$5:$C$8,'KK2. Series'!AM18) | AQ18: =COUNTIF('TK 15666. Phim SX'!$C$6:$C$13,'KK2. Series'!AM18) | AR18: =COUNTIF('TK 15661.Bản quyền phim '!F:F,'KK2. Series'!AM18) | AT18: =SUM(AP18:AS18) | AZ18: ✓ Found
A19: 13 | B19: Sub: SER_ROM_23_2706323 (SUB) Only For Love, Ep36 SER_ROM_23_2706322 (SUB) Only For Love, Ep35 SER_ROM_23_2706320 (SUB) Only For Love, Ep33 SER_ROM_23_2706321 (SUB) Only For Love, Ep34 SER_ROM_23_2706318 (SUB) Only For Love, Ep31 SER_ROM_23_2706319 (SUB) Only For Love, Ep32 SER_ROM_23_2706317 (SUB) Only For Love, Ep30 SER_ROM_23_2706314 (SUB) Only For Love, Ep27 SER_ROM_23_2706316 (SUB) Only For Love, Ep29 SER_ROM_23_2706315 (SUB) Only For Love, Ep28 SER_ROM_23_2706313 (SUB) Only For Love, Ep26 SER_ROM_23_2706312 (SUB) Only For Love, Ep25 SER_ROM_23_2706309 (SUB) Only For Love, Ep22 SER_ROM_23_2706310 (SUB) Only For Love, Ep23 SER_ROM_23_2706311 (SUB) Only For Love, Ep24 SER_ROM_23_2706308 (SUB) Only For Love, Ep21 SER_ROM_23_2706307 (SUB) Only For Love, Ep20 SER_ROM_23_2706306 (SUB) Only For Love, Ep19 SER_ROM_23_2706305 (SUB) Only For Love, Ep18 SER_ROM_23_2706304 (SUB) Only For Love, Ep17 SER_ROM_23_2706303 (SUB) Only For Love, Ep16 SER_ROM_23_2706302 (SUB) Only For Love, Ep15 SER_ROM_23_2706301 (SUB) Only For Love, Ep14 SER_ROM_23_2706300 (SUB) Only For Love, Ep13 SER_ROM_23_2706298 (SUB) Only For Love, Ep11 SER_ROM_23_2706299 (SUB) Only For Love, Ep12 SER_ROM_23_2706297 (SUB) Only For Love, Ep10 SER_ROM_23_2706296 (SUB) Only For Love, Ep09 SER_ROM_23_2706295 (SUB) Only For Love, Ep08 SER_ROM_23_2706293 (SUB) Only For Love, Ep06 SER_ROM_23_2706294 (SUB) Only For Love, Ep07 SER_ROM_23_2706292 (SUB) Only For Love, Ep05 SER_ROM_23_2706291 (SUB) Only For Love, Ep04 SER_ROM_23_2706290 (SUB) Only For Love, Ep03 SER_ROM_23_2706289 (SUB) Only For Love, Ep02 SER_ROM_23__2706288 (SUB) Only For Love, Ep01 Voice: SER_ROM_23_2707694 Only For Love, Ep34 SER_ROM_23_2707696 Only For Love, Ep36 SER_ROM_23_2707695 Only For Love, Ep35 SER_ROM_23_2707692 Only For Love, Ep32 SER_ROM_23_2707693 Only For Love, Ep33 SER_ROM_23_2707691 Only For Love, Ep31 SER_ROM_23_2707689 Only For Love, Ep29 SER_ROM_23_2707690 Only For Love, Ep30 SER_ROM_23_2707687 Only For Love, Ep27 SER_ROM_23_2707688 Only For Love, Ep28 SER_ROM_23_2707684 Only For Love, Ep24 SER_ROM_23_2707685 Only For Love, Ep25 SER_ROM_23_2707686 Only For Love, Ep26 SER_ROM_23_2707682 Only For Love, Ep22 SER_ROM_23_2707683 Only For Love, Ep23 SER_ROM_23_2707680 Only For Love, Ep20 SER_ROM_23_2707681 Only For Love, Ep21 SER_ROM_23_2707678 Only For Love, Ep18 SER_ROM_23_2707679 Only For Love, Ep19 SER_ROM_23_2707677 Only For Love, Ep17 SER_ROM_23_2707676 Only For Love, Ep16 SER_ROM_23_2707675 Only For Love, Ep15 SER_ROM_23_2707674 Only For Love, Ep14 SER_ROM_23_2707672 Only For Love, Ep12 SER_ROM_23_2707673 Only For Love, Ep13 SER_ROM_23_2707670 Only For Love, Ep10 SER_ROM_23_2707671 Only For Love, Ep11 SER_ROM_23_2707669 Only For Love, Ep09 SER_ROM_23_2707668 Only For Love, Ep08 SER_ROM_23_2707666 Only For Love, Ep06 SER_ROM_23_2707665 Only For Love, Ep05 SER_ROM_23_2707667 Only For Love, Ep07 SER_ROM_23_2707663 Only For Love, Ep03 SER_ROM_23_2707664 Only For Love, Ep04 SER_ROM_23_2707662 Only For Love, Ep02 SER_ROM_23_2707661 Only For Love, Ep01 | C19: Only For Love | D19: Trêu nhầm yêu thật | E19: Huace Media | F19: Huace Media/Only For Love | G19: China | H19: 2023 | I19: 36 | J19: 45 | K19: =(I19*J19)/60 | L19: =I19 | M19: Romance, Drama, Comedy | N19: Romance | O19: 45231 | P19: 47057 | Q19: 45237 | R19: K+ACTION | S19: Exclusive All TV and All VOD Rights during LP. | T19: Yes | U19: Yes | V19: Yes | W19: Yes | X19: Yes | Y19: Yes | Z19: Yes | AA19: Yes | AB19: Yes | AC19: 45231 | AD19: 47057 | AE19: Unlimited | AF19: 3 | AG19: 45241 | AI19: Yes | AJ19: Yes | AK19: Phim Song song | AL19: Phim còn hạn từ 2026 | AM19: ONLY FOR LOVE (TRÊU NHẦM YÊU THẬT) | AO19: =SUMIF('TK 15661.Bản quyền phim '!F:F,'KK2. Series'!C19,'TK 15661.Bản quyền phim '!K:K) | AP19: =COUNTIF('242.BQ Phim VOD'!$C$5:$C$8,'KK2. Series'!AM19) | AQ19: =COUNTIF('TK 15666. Phim SX'!$C$6:$C$13,'KK2. Series'!AM19) | AR19: =COUNTIF('TK 15661.Bản quyền phim '!F:F,'KK2. Series'!AM19) | AT19: =SUM(AP19:AS19) | AZ19: ✓ Found
A20: 14 | B20: S01 EP01 – SER_DRA_22_2678186 S01 EP02 – SER_DRA_22_2678187 S01 EP03 – SER_DRA_22_2678188 S01 EP04 – SER_DRA_22_2678189 S01 EP05 – SER_DRA_22_2678190 S01 EP06 – SER_DRA_22_2678191 S01 EP07 – SER_DRA_22_2678192 S01 EP08 – SER_DRA_22_2678193 S01 EP09 – SER_DRA_22_2678194 | C20: All Those Things We Never Said | D20: Mọi Điều Ta Chưa Nói | E20: Studio Canal TV | F20: Scale_SC+/All those things | G20: France | H20: 2022 | I20: 9 | J20: 30 | K20: =(I20*J20)/60 | L20: =I20 | M20: Romance Drama | N20: Drama | O20: 44886 | P20: 48538 | Q20: 44963 | R20: K+CINE | S20: Exclusive all rights | T20: Yes | U20: Yes | V20: Yes | W20: Yes | X20: Yes | Y20: Yes | Z20: Yes | AA20: Yes | AB20: Yes | AC20: 44886 | AD20: 48538 | AE20: Unlimited | AF20: 18 | AG20: 45789 | AH20: Unlimited | AI20: Yes | AJ20: Yes | AL20: Phim còn hạn từ 2026 | AM20: All those things we never said - season 1 | AO20: =SUMIF('TK 15661.Bản quyền phim '!F:F,'KK2. Series'!C20,'TK 15661.Bản quyền phim '!K:K) | AP20: =COUNTIF('242.BQ Phim VOD'!$C$5:$C$8,'KK2. Series'!AM20) | AQ20: =COUNTIF('TK 15666. Phim SX'!$C$6:$C$13,'KK2. Series'!AM20) | AR20: =COUNTIF('TK 15661.Bản quyền phim '!F:F,'KK2. Series'!AM20) | AT20: =SUM(AP20:AS20) | AZ20: ✓ Found
A21: 15 | B21: Voice: SER_COS_24_2710320 A Journey to Love, Ep01 SER_COS_24_2710321 A Journey to Love, Ep02 SER_COS_24_2710322 A Journey to Love, Ep03 SER_COS_24_2710323 A Journey to Love, Ep04 SER_COS_24_2710324 A Journey to Love, Ep05 SER_COS_24_2710325 A Journey to Love, Ep06 SER_COS_24_2710326 A Journey to Love, Ep07 SER_COS_24_2710327 A Journey to Love, Ep08 SER_COS_24_2710328 A Journey to Love, Ep09 SER_COS_24_2710329 A Journey to Love, Ep10 SER_COS_24_2710330 A Journey to Love, Ep11 SER_COS_24_2710331 A Journey to Love, Ep12 SER_COS_24_2710332 A Journey to Love, Ep13 SER_COS_24_2710333 A Journey to Love, Ep14 SER_COS_24_2710334 A Journey to Love, Ep15 SER_COS_24_2710335 A Journey to Love, Ep16 SER_COS_24_2710336 A Journey to Love, Ep17 SER_COS_24_2710337 A Journey to Love, Ep18 SER_COS_24_2710338 A Journey to Love, Ep19 SER_COS_24_2710339 A Journey to Love, Ep20 SER_COS_24_2710340 A Journey to Love, Ep21 SER_COS_24_2710341 A Journey to Love, Ep22 SER_COS_24_2710342 A Journey to Love, Ep23 SER_COS_24_2710343 A Journey to Love, Ep24 SER_COS_24_2710344 A Journey to Love, Ep25 SER_COS_24_2710345 A Journey to Love, Ep26 SER_COS_24_2710346 A Journey to Love, Ep27 SER_COS_24_2710347 A Journey to Love, Ep28 SER_COS_24_2710348 A Journey to Love, Ep29 SER_COS_24_2710349 A Journey to Love, Ep30 SER_COS_24_2710350 A Journey to Love, Ep31 SER_COS_24_2710351 A Journey to Love, Ep32 SER_COS_24_2710352 A Journey to Love, Ep33 SER_COS_24_2710353 A Journey to Love, Ep34 SER_COS_24_2710354 A Journey to Love, Ep35 SER_COS_24_2710355 A Journey to Love, Ep36 SER_COS_24_2710356 A Journey to Love, Ep37 SER_COS_24_2710357 A Journey to Love, Ep38 SER_COS_24_2710358 A Journey to Love, Ep39 SER_COS_24_2710359 A Journey to Love, Ep40 sub: SER_COS_23_2709564 (SUB) A Journey to Love, Ep01 SER_COS_23_2709565 (SUB) A Journey to Love, Ep02 SER_COS_23_2709566 (SUB) A Journey to Love, Ep03 SER_COS_23_2709567 (SUB) A Journey to Love, Ep04 SER_COS_23_2709568 (SUB) A Journey to Love, Ep05 SER_COS_23_2709569 (SUB) A Journey to Love, Ep06 SER_COS_23_2709570 (SUB) A Journey to Love, Ep07 SER_COS_23_2709571 (SUB) A Journey to Love, Ep08 SER_COS_23_2709572 (SUB) A Journey to Love, Ep09 SER_COS_23_2709573 (SUB) A Journey to Love, Ep10 SER_COS_23_2709574 (SUB) A Journey to Love, Ep11 SER_COS_23_2709575 (SUB) A Journey to Love, Ep12 SER_COS_23_2709576 (SUB) A Journey to Love, Ep13 SER_COS_23_2709577 (SUB) A Journey to Love, Ep14 SER_COS_23_2709578 (SUB) A Journey to Love, Ep15 SER_COS_23_2709579 (SUB) A Journey to Love, Ep16 SER_COS_23_2709580 (SUB) A Journey to Love, Ep17 SER_COS_23_2709581 (SUB) A Journey to Love, Ep18 SER_COS_23_2709582 (SUB) A Journey to Love, Ep19 SER_COS_23_2709583 (SUB) A Journey to Love, Ep20 SER_COS_23_2709584 (SUB) A Journey to Love, Ep21 SER_COS_23_2709585 (SUB) A Journey to Love, Ep22 SER_COS_23_2709586 (SUB) A Journey to Love, Ep23 SER_COS_23_2709587 (SUB) A Journey to Love, Ep24 SER_COS_23_2709588 (SUB) A Journey to Love, Ep25 SER_COS_23_2709589 (SUB) A Journey to Love, Ep26 SER_COS_23_2709590 (SUB) A Journey to Love, Ep27 SER_COS_23_2709591 (SUB) A Journey to Love, Ep28 SER_COS_23_2709592 (SUB) A Journey to Love, Ep29 SER_COS_23_2709593 (SUB) A Journey to Love, Ep30 SER_COS_23_2709594 (SUB) A Journey to Love, Ep31 SER_COS_23_2709595 (SUB) A Journey to Love, Ep32 SER_COS_23_2709596 (SUB) A Journey to Love, Ep33 SER_COS_23_2709597 (SUB) A Journey to Love, Ep34 SER_COS_23_2709598 (SUB) A Journey to Love, Ep35 SER_COS_23_2709599 (SUB) A Journey to Love, Ep36 SER_COS_23_2709600 (SUB) A Journey to Love, Ep37 SER_COS_23_2709601 (SUB) A Journey to Love, Ep38 SER_COS_23_2709602 (SUB) A Journey to Love, Ep39 SER_COS_23_2709603 (SUB) A Journey to Love, Ep40 | C21: A Journey to Love | D21: Nhất Niệm Quan Sơn | E21: Linmon Media | F21: Linmon Media/ A journey to Love | G21: China | H21: 2023 | I21: 40 | J21: 45 | K21: =(I21*J21)/60 | L21: =I21 | M21: Romance, Wuxia, Drama, Political | N21: Action | O21: 45653 | P21: 47478 | Q21: 45313 | R21: K+ACTION | S21: 60 | T21: Yes | U21: Yes | V21: Yes | W21: Yes | X21: Yes | Y21: Yes | Z21: Yes | AA21: Yes | AB21: Yes | AC21: 45653 | AD21: 47478 | AE21: Unlimited run | AF21: 5 | AG21: 45597 | AI21: Yes | AJ21: Yes | AL21: Phim còn hạn từ 2026 | AM21: A JOURNEY TO LOVE (Nhất niệm quan sơn) | AO21: =SUMIF('TK 15661.Bản quyền phim '!F:F,'KK2. Series'!C21,'TK 15661.Bản quyền phim '!K:K) | AP21: =COUNTIF('242.BQ Phim VOD'!$C$5:$C$8,'KK2. Series'!AM21) | AQ21: =COUNTIF('TK 15666. Phim SX'!$C$6:$C$13,'KK2. Series'!AM21) | AR21: =COUNTIF('TK 15661.Bản quyền phim '!F:F,'KK2. Series'!AM21) | AT21: =SUM(AP21:AS21) | AZ21: ✓ Found
A22: 16 | B22: the legend of shen li – bản voice SER_ROM_24_2716199 (VOICE) The Legend of Shen Li, Ep01 SER_ROM_24_2716200 (VOICE) The Legend of Shen Li, Ep02 SER_ROM_24_2716201 (VOICE) The Legend of Shen Li, Ep03 SER_ROM_24_2716202 (VOICE) The Legend of Shen Li, Ep04 SER_ROM_24_2716203 (VOICE) The Legend of Shen Li, Ep05 SER_ROM_24_2716204 (VOICE) The Legend of Shen Li, Ep06 SER_ROM_24_2716205 (VOICE) The Legend of Shen Li, Ep07 SER_ROM_24_2716206 (VOICE) The Legend of Shen Li, Ep08 SER_ROM_24_2716207 (VOICE) The Legend of Shen Li, Ep09 SER_ROM_24_2716208 (VOICE) The Legend of Shen Li, Ep10 SER_ROM_24_2716209 (VOICE) The Legend of Shen Li, Ep11 SER_ROM_24_2716210 (VOICE) The Legend of Shen Li, Ep12 SER_ROM_24_2716211 (VOICE) The Legend of Shen Li, Ep13 SER_ROM_24_2716212 (VOICE) The Legend of Shen Li, Ep14 SER_ROM_24_2716213 (VOICE) The Legend of Shen Li, Ep15 SER_ROM_24_2716214 (VOICE) The Legend of Shen Li, Ep16 SER_ROM_24_2716215 (VOICE) The Legend of Shen Li, Ep17 SER_ROM_24_2716216 (VOICE) The Legend of Shen Li, Ep18 SER_ROM_24_2716217 (VOICE) The Legend of Shen Li, Ep19 SER_ROM_24_2716218 (VOICE) The Legend of Shen Li, Ep20 SER_ROM_24_2716219 (VOICE) The Legend of Shen Li, Ep21 SER_ROM_24_2716220 (VOICE) The Legend of Shen Li, Ep22 SER_ROM_24_2716221 (VOICE) The Legend of Shen Li, Ep23 SER_ROM_24_2716222 (VOICE) The Legend of Shen Li, Ep24 SER_ROM_24_2716223 (VOICE) The Legend of Shen Li, Ep25 SER_ROM_24_2716224 (VOICE) The Legend of Shen Li, Ep26 SER_ROM_24_2716225 (VOICE) The Legend of Shen Li, Ep27 SER_ROM_24_2716226 (VOICE) The Legend of Shen Li, Ep28 SER_ROM_24_2716227 (VOICE) The Legend of Shen Li, Ep29 SER_ROM_24_2716228 (VOICE) The Legend of Shen Li, Ep30 SER_ROM_24_2716229 (VOICE) The Legend of Shen Li, Ep31 SER_ROM_24_2716230 (VOICE) The Legend of Shen Li, Ep32 SER_ROM_24_2716231 (VOICE) The Legend of Shen Li, Ep33 SER_ROM_24_2716232 (VOICE) The Legend of Shen Li, Ep34 SER_ROM_24_2716233 (VOICE) The Legend of Shen Li, Ep35 SER_ROM_24_2716234 (VOICE) The Legend of Shen Li, Ep36 SER_ROM_24_2716235 (VOICE) The Legend of Shen Li, Ep37 SER_ROM_24_2716236 (VOICE) The Legend of Shen Li, Ep38 SER_ROM_24_2716237 (VOICE) The Legend of Shen Li, Ep39 the legend of shen li – bản sub SER_ROM_24_2713881 The Legend of Shen Li, Ep01 SER_ROM_24_2713882 The Legend of Shen Li, Ep02 SER_ROM_24_2713883 The Legend of Shen Li, Ep03 SER_ROM_24_2713884 The Legend of Shen Li, Ep04 SER_ROM_24_2713885 The Legend of Shen Li, Ep05 SER_ROM_24_2713886 The Legend of Shen Li, Ep06 SER_ROM_24_2713887 The Legend of Shen Li, Ep07 SER_ROM_24_2713888 The Legend of Shen Li, Ep08 SER_ROM_24_2713889 The Legend of Shen Li, Ep09 SER_ROM_24_2713890 The Legend of Shen Li, Ep10 SER_ROM_24_2713891 The Legend of Shen Li, Ep11 SER_ROM_24_2713892 The Legend of Shen Li, Ep12 SER_ROM_24_2713893 The Legend of Shen Li, Ep13 SER_ROM_24_2713894 The Legend of Shen Li, Ep14 SER_ROM_24_2713895 The Legend of Shen Li, Ep15 SER_ROM_24_2713896 The Legend of Shen Li, Ep16 SER_ROM_24_2713897 The Legend of Shen Li, Ep17 SER_ROM_24_2713898 The Legend of Shen Li, Ep18 SER_ROM_24_2713899 The Legend of Shen Li, Ep19 SER_ROM_24_2713900 The Legend of Shen Li, Ep20 SER_ROM_24_2713901 The Legend of Shen Li, Ep21 SER_ROM_24_2713902 The Legend of Shen Li, Ep22 SER_ROM_24_2713903 The Legend of Shen Li, Ep23 SER_ROM_24_2713904 The Legend of Shen Li, Ep24 SER_ROM_24_2713905 The Legend of Shen Li, Ep25 SER_ROM_24_2713906 The Legend of Shen Li, Ep26 SER_ROM_24_2713907 The Legend of Shen Li, Ep27 SER_ROM_24_2713908 The Legend of Shen Li, Ep28 SER_ROM_24_2713909 The Legend of Shen Li, Ep29 SER_ROM_24_2713910 The Legend of Shen Li, Ep30 SER_ROM_24_2713911 The Legend of Shen Li, Ep31 SER_ROM_24_2713912 The Legend of Shen Li, Ep32 SER_ROM_24_2713913 The Legend of Shen Li, Ep33 SER_ROM_24_2713914 The Legend of Shen Li, Ep34 SER_ROM_24_2713915 The Legend of Shen Li, Ep35 SER_ROM_24_2713916 The Legend of Shen Li, Ep36 SER_ROM_24_2713917 The Legend of Shen Li, Ep37 SER_ROM_24_2713918 The Legend of Shen Li, Ep38 SER_ROM_24_2713919 The Legend of Shen Li, Ep39 | C22: Legend of Shen Li | D22: Dữ Phượng Hành | E22: NCM | F22: New Classic Media/HDBQ Legend of Shen Li | G22: China | H22: 2023 | I22: 39 | J22: 42 | K22: =(I22*J22)/60 | L22: 39 | M22: Custom, Xianxia, Romance | N22: Romance | O22: 45369 | P22: 47194 | Q22: 45369 | R22: K+ACTION | S22: 48 | T22: Yes | U22: Yes | V22: Yes | W22: Yes | X22: Yes | Y22: Yes | Z22: Yes | AA22: Yes | AB22: Yes | AC22: 45369 | AD22: 47194 | AE22: Unlimited run | AF22: 2 | AG22: 45370 | AI22: Yes | AJ22: Yes | AK22: Phim Song song | AL22: Phim còn hạn từ 2026 | AM22: The Legend of Shen Li (Dữ phượng hành) | AO22: =SUMIF('TK 15661.Bản quyền phim '!F:F,'KK2. Series'!C22,'TK 15661.Bản quyền phim '!K:K) | AP22: =COUNTIF('242.BQ Phim VOD'!$C$5:$C$8,'KK2. Series'!AM22) | AQ22: =COUNTIF('TK 15666. Phim SX'!$C$6:$C$13,'KK2. Series'!AM22) | AR22: =COUNTIF('TK 15661.Bản quyền phim '!F:F,'KK2. Series'!AM22) | AT22: =SUM(AP22:AS22) | AZ22: ✓ Found
A23: 17 | B23: EP01 – SER_HIS_22_2685963 EP02 – SER_HIS_22_2685964 EP03 – SER_HIS_22_2685965 EP04 – SER_HIS_22_2685966 EP05 – SER_HIS_22_2685967 EP06 – SER_HIS_22_2685968 EP07 – SER_HIS_22_2685969 EP08 – SER_HIS_22_2685970 EP09 – SER_HIS_22_2685971 EP10 – SER_HIS_22_2685972 EP11 – SER_HIS_22_2685973 EP12 – SER_HIS_22_2685974 EP13 – SER_HIS_22_2685975 EP14 – SER_HIS_22_2685976 EP15 – SER_HIS_22_2685977 EP16 – SER_HIS_22_2685978 EP17 – SER_HIS_22_2685979 EP18 – SER_HIS_22_2685980 EP19 – SER_HIS_22_2685981 EP20 – SER_HIS_22_2685982 EP21 – SER_HIS_22_2685983 EP22 – SER_HIS_22_2685984 EP23 – SER_HIS_22_2685985 EP24 – SER_HIS_22_2685986 | C23: The Wind Blows from Longxi | D23: Phong khởi Lũng Tây | E23: TKL | F23: 131/2022/HDBQ/VSTV_TKL | G23: China | H23: 2022 | I23: 24 | J23: 45 | K23: =(I23*J23)/60 | L23: =I23 | M23: Historical, Mystery, Crime, War | N23: Action, Adventure | O23: 44937 | P23: 46032 | Q23: 44937 | R23: K+LIFE | S23: Exclusive All TV Rights the first 6 months of LP Non-exclusive with All Catch-up TV Rights; All VOD Rights during LP | T23: No | U23: Yes | V23: Yes | W23: Yes | X23: Yes | Y23: Yes | Z23: Yes | AA23: Yes | AB23: Yes | AC23: 44937 | AD23: 46032 | AE23: 6 | AF23: 4 | AG23: 45829 | AH23: =AE23-AF23 | AI23: Yes | AJ23: Yes | AL23: Phim còn hạn từ 2026 | AM23: The Wind Blows From Long Xi (Phong khởi Lũng Tây) | AO23: =SUMIF('TK 15661.Bản quyền phim '!F:F,'KK2. Series'!C23,'TK 15661.Bản quyền phim '!K:K) | AP23: =COUNTIF('242.BQ Phim VOD'!$C$5:$C$8,'KK2. Series'!AM23) | AQ23: =COUNTIF('TK 15666. Phim SX'!$C$6:$C$13,'KK2. Series'!AM23) | AR23: =COUNTIF('TK 15661.Bản quyền phim '!F:F,'KK2. Series'!AM23) | AT23: =SUM(AP23:AS23) | AZ23: ✓ Found
A24: 18 | B24: Night Has Come — bản Voice EP01 – SER_THR_23_2710046 EP02 – SER_THR_23_2710047 EP03 – SER_THR_23_2710048 EP04 – SER_THR_23_2710049 EP05 – SER_THR_23_2710050 EP06 – SER_THR_23_2710051 EP07 – SER_THR_23_2710052 EP08 – SER_THR_23_2710053 EP09 – SER_THR_23_2710054 EP10 – SER_THR_23_2710055 EP11 – SER_THR_23_2710056 EP12 – SER_THR_23_2710057 Night Has Come — bản Sub EP01 – SER_THR_23_2707998 EP02 – SER_THR_23_2707999 EP03 – SER_THR_23_2708000 EP04 – SER_THR_23_2708001 EP05 – SER_THR_23_2708002 EP06 – SER_THR_23_2708003 EP07 – SER_THR_23_2708004 EP08 – SER_THR_23_2708005 EP09 – SER_THR_23_2708006 EP10 – SER_THR_23_2708007 EP11 – SER_THR_23_2708008 EP12 – SER_THR_23_2708009 | C24: Night Has Come | D24: Màn đêm kinh hoàng | E24: LG U+ | F24: /Night Has Come | G24: Korea | H24: 2023 | I24: 12 | J24: 30 | K24: =(I24*J24)/60 | L24: =I24 | M24: Mystery, Thriller | N24: Crime, Thriller | O24: 45264 | P24: 46724 | Q24: 45264 | R24: K+ACTION | S24: Exclusive All TV and All VOD Rights during LP. | T24: Yes | U24: Yes | V24: Yes | W24: Yes | X24: Yes | Y24: Yes | Z24: Yes | AA24: Yes | AB24: Yes | AC24: 45264 | AD24: 46724 | AE24: Unlimited | AF24: 5 | AG24: 45799 | AI24: Yes | AJ24: Yes | AK24: Phim Song song | AL24: Phim còn hạn từ 2026 | AM24: Night Has Come | AO24: =SUMIF('TK 15661.Bản quyền phim '!F:F,'KK2. Series'!C24,'TK 15661.Bản quyền phim '!K:K) | AP24: =COUNTIF('242.BQ Phim VOD'!$C$5:$C$8,'KK2. Series'!AM24) | AQ24: =COUNTIF('TK 15666. Phim SX'!$C$6:$C$13,'KK2. Series'!AM24) | AR24: =COUNTIF('TK 15661.Bản quyền phim '!F:F,'KK2. Series'!AM24) | AT24: =SUM(AP24:AS24) | AZ24: ✓ Found
A25: 19 | B25: EP01 – SER_COS_22_2667367 EP02 – SER_COS_22_2667368 EP03 – SER_COS_22_2667369 EP04 – SER_COS_22_2667370 EP05 – SER_COS_22_2667371 EP06 – SER_COS_22_2667372 EP07 – SER_COS_22_2667373 EP08 – SER_COS_22_2667374 EP09 – SER_COS_22_2667375 EP10 – SER_COS_22_2667376 EP11 – SER_COS_22_2667377 EP12 – SER_COS_22_2667378 EP13 – SER_COS_22_2667379 EP14 – SER_COS_22_2667380 EP15 – SER_COS_22_2667381 EP16 – SER_COS_22_2667382 EP17 – SER_COS_22_2667383 EP18 – SER_COS_22_2667384 EP19 – SER_COS_22_2667385 EP20 – SER_COS_22_2667386 EP21 – SER_COS_22_2667387 EP22 – SER_COS_22_2667388 EP23 – SER_COS_22_2667389 EP24 – SER_COS_22_2667390 EP25 – SER_COS_22_2667391 EP26 – SER_COS_22_2667392 EP27 – SER_COS_22_2667393 EP28 – SER_COS_22_2667394 EP29 – SER_COS_22_2667395 EP30 – SER_COS_22_2667396 EP31 – SER_COS_22_2667397 EP32 – SER_COS_22_2667398 EP33 – SER_COS_22_2667399 EP34 – SER_COS_22_2667400 EP35 – SER_COS_22_2667401 EP36 – SER_COS_22_2667402 EP37 – SER_COS_22_2667403 EP38 – SER_COS_22_2667404 EP39 – SER_COS_22_2667405 | C25: Luo Yang | D25: Lạc Dương | E25: iQiYi | F25: 99/2023/HDBQ/VSTV-IQIYI | G25: China | H25: 2021 | I25: 39 | J25: 45 | K25: =(I25*J25)/60 | L25: =I25 | M25: Crime, Thriller | N25: Crime, Thriller | O25: 44638 | P25: 46098 | Q25: 44642 | R25: K+LIFE | S25: Exclusive all TV Rights Non ex SVOD + TVOD | T25: No | U25: Yes | V25: Yes | W25: Yes | X25: Yes | Y25: Yes | Z25: Yes | AA25: No | AB25: No | AC25: 44638 | AD25: 46098 | AE25: Unlimited | AF25: 15 | AG25: 45602 | AH25: Unlimited | AI25: Yes | AJ25: Yes | AL25: Phim còn hạn từ 2026 | AM25: Luo Yang (Lạc Dương) | AO25: =SUMIF('TK 15661.Bản quyền phim '!F:F,'KK2. Series'!C25,'TK 15661.Bản quyền phim '!K:K) | AP25: =COUNTIF('242.BQ Phim VOD'!$C$5:$C$8,'KK2. Series'!AM25) | AQ25: =COUNTIF('TK 15666. Phim SX'!$C$6:$C$13,'KK2. Series'!AM25) | AR25: =COUNTIF('TK 15661.Bản quyền phim '!F:F,'KK2. Series'!AM25) | AT25: =SUM(AP25:AS25) | AZ25: ✓ Found
A26: 20 | B26: sub: EP01 – SER_FAN_23_2691051 EP02 – SER_FAN_23_2691052 EP03 – SER_FAN_23_2691053 EP04 – SER_FAN_23_2691054 EP05 – SER_FAN_23_2691055 EP06 – SER_FAN_23_2691056 EP07 – SER_FAN_23_2691057 EP08 – SER_FAN_23_2691058 EP09 – SER_FAN_23_2691059 EP10 – SER_FAN_23_2691060 EP11 – SER_FAN_23_2691061 EP12 – SER_FAN_23_2691062 Voice: EP01 (edited) – SER_FAN_23_2694150 EP02 (edited) – SER_FAN_23_2694151 EP03 (edited) – SER_FAN_23_2694152 EP04 (edited) – SER_FAN_23_2694153 EP05 (edited) – SER_FAN_23_2694154 EP06 (edited) – SER_FAN_23_2694155 EP07 (edited) – SER_FAN_23_2694156 EP08 (edited) – SER_FAN_23_2694157 EP09 (edited) – SER_FAN_23_2694158 EP10 (edited) – SER_FAN_23_2694159 EP11 (edited) – SER_FAN_23_2694160 EP12 (edited) – SER_FAN_23_2694161 EP13 (edited) – SER_FAN_23_2694162 EP14 (edited) – SER_FAN_23_2694163 EP15 (edited) – SER_FAN_23_2694164 EP16 (edited) – SER_FAN_23_2694165 EP17 (edited) – SER_FAN_23_2694166 EP18 (edited) – SER_FAN_23_2694167 | C26: Delivery Man | D26: Taxi ma quái | E26: PCCW VUCLIP | F26: PCCW VUCLIP/2023/HDBQ The Secret Romantic Guesthouse | G26: Korea | H26: 2022 | I26: 12 | J26: 70 | K26: =(I26*J26)/60 | L26: 18 | M26: Comedy, fantasy, supernatural | N26: Crime, Thriller | O26: 44986 | P26: 46446 | Q26: 44986 | R26: K+LIFE | S26: Exclusive All TV Rights during LP and Exclusive All VOD rights for first 4 months | T26: Yes | U26: Yes | V26: Yes | W26: Yes | X26: Yes | Y26: Yes | Z26: Yes | AA26: Yes | AB26: Yes | AC26: 44986 | AD26: 46446 | AE26: 8 | AF26: 8 | AG26: 45432 | AH26: =AE26-AF26 | AI26: Yes | AJ26: Yes | AK26: Phim Song song | AL26: Phim còn hạn từ 2026 | AM26: Delivery Man | AO26: =SUMIF('TK 15661.Bản quyền phim '!F:F,'KK2. Series'!C26,'TK 15661.Bản quyền phim '!K:K) | AP26: =COUNTIF('242.BQ Phim VOD'!$C$5:$C$8,'KK2. Series'!AM26) | AQ26: =COUNTIF('TK 15666. Phim SX'!$C$6:$C$13,'KK2. Series'!AM26) | AR26: =COUNTIF('TK 15661.Bản quyền phim '!F:F,'KK2. Series'!AM26) | AT26: =SUM(AP26:AS26) | AZ26: ✓ Found
A27: 21 | B27: EP01 – SER_COS_23_2698582 EP02 – SER_COS_23_2698583 EP03 – SER_COS_23_2698584 EP04 – SER_COS_23_2698585 EP05 – SER_COS_23_2698586 EP06 – SER_COS_23_2698587 EP07 – SER_COS_23_2698588 EP08 – SER_COS_23_2698589 EP09 – SER_COS_23_2698590 EP10 – SER_COS_23_2698591 EP11 – SER_COS_23_2698592 EP12 – SER_COS_23_2698593 EP13 – SER_COS_23_2698594 EP14 – SER_COS_23_2698595 | C27: Under the Microscope | D27: Đại Minh dưới kính hiển vi | E27: iQiYi | F27: 87/2023/HDBQ/VSTV-IQIYI | G27: China | H27: 2023 | I27: 14 | J27: 45 | K27: =(I27*J27)/60 | L27: =I27 | M27: Historical, Mystery, Crime | N27: Crime, Thriller | O27: 45108 | P27: 46569 | Q27: 45126 | R27: K+LIFE | S27: Exclusive all Pay TV Rights, Non exclusive all SVOD + TVOD rights during LP | T27: No | U27: Yes | V27: Yes | W27: Yes | X27: No | Y27: No | Z27: Yes | AA27: Yes | AB27: No | AC27: 45108 | AD27: 46569 | AE27: Unlimited | AF27: 7 | AG27: 45437 | AH27: Unlimited | AI27: Yes | AJ27: Yes | AL27: Phim còn hạn từ 2026 | AM27: Under the Microscope | AO27: =SUMIF('TK 15661.Bản quyền phim '!F:F,'KK2. Series'!C27,'TK 15661.Bản quyền phim '!K:K) | AP27: =COUNTIF('242.BQ Phim VOD'!$C$5:$C$8,'KK2. Series'!AM27) | AQ27: =COUNTIF('TK 15666. Phim SX'!$C$6:$C$13,'KK2. Series'!AM27) | AR27: =COUNTIF('TK 15661.Bản quyền phim '!F:F,'KK2. Series'!AM27) | AT27: =SUM(AP27:AS27) | AZ27: ✓ Found
A28: 22 | B28: EP01 – SER_ACT_22_2686518 EP02 – SER_ACT_22_2686519 EP03 – SER_ACT_22_2686520 EP04 – SER_ACT_22_2686521 EP05 – SER_ACT_22_2686522 EP06 – SER_ACT_22_2686523 EP07 – SER_ACT_22_2686524 EP08 – SER_ACT_22_2686525 EP09 – SER_ACT_22_2686526 EP10 – SER_ACT_22_2686527 EP11 – SER_ACT_22_2686528 EP12 – SER_ACT_22_2686529 EP13 – SER_ACT_22_2686530 EP14 – SER_ACT_22_2686531 EP15 – SER_ACT_22_2686532 EP16 – SER_ACT_22_2686533 EP17 – SER_ACT_22_2686534 EP18 – SER_ACT_22_2686535 EP19 – SER_ACT_22_2686536 EP20 – SER_ACT_22_2686537 EP21 – SER_ACT_22_2686538 EP22 – SER_ACT_22_2686539 EP23 – SER_ACT_22_2686540 EP24 – SER_ACT_22_2686541 | C28: Are You Safe | D28: Bạn có an toàn | E28: Youhug Media | F28: 132A/2022/HDBQ/VSTV_Youhug media | G28: China | H28: 2022 | I28: 24 | J28: 45 | K28: =(I28*J28)/60 | L28: =I28 | M28: Action, Suspense, Crime, Thriller, Drama | N28: Crime, Thriller | O28: 44971 | P28: 46796 | Q28: 44985 | R28: K+LIFE | S28: Exclusive All TV Rights and Non-exclusive with All Catch-up TV Rights; All VOD Rights during LP | T28: No | U28: Yes | V28: Yes | W28: Yes | X28: Yes | Y28: Yes | Z28: Yes | AA28: Yes | AB28: Yes | AC28: 44971 | AD28: 46796 | AE28: Unlimited | AF28: 8 | AG28: 45457 | AH28: Unlimited | AI28: Yes | AJ28: Yes | AL28: Phim còn hạn từ 2026 | AM28: Are You Safe | AO28: =SUMIF('TK 15661.Bản quyền phim '!F:F,'KK2. Series'!C28,'TK 15661.Bản quyền phim '!K:K) | AP28: =COUNTIF('242.BQ Phim VOD'!$C$5:$C$8,'KK2. Series'!AM28) | AQ28: =COUNTIF('TK 15666. Phim SX'!$C$6:$C$13,'KK2. Series'!AM28) | AR28: =COUNTIF('TK 15661.Bản quyền phim '!F:F,'KK2. Series'!AM28) | AT28: =SUM(AP28:AS28) | AZ28: ✓ Found
A29: 23 | B29: Voice: EP01 – SER_ACT_2696867 EP02 – SER_ACT_2696868 EP03 – SER_ACT_2696869 EP04 – SER_ACT_2696870 EP05 – SER_ACT_2696871 EP06 – SER_ACT_2696872 EP07 – SER_ACT_2696873 EP08 – SER_ACT_2696874 EP09 – SER_ACT_2696875 EP10 – SER_ACT_2696876 EP11 – SER_ACT_2696877 EP12 – SER_ACT_2696878 EP13 – SER_ACT_2696879 EP14 – SER_ACT_2696880 EP15 – SER_ACT_2696881 EP16 – SER_ACT_2696882 EP17 – SER_ACT_2696883 EP18 – SER_ACT_2696884 EP19 – SER_ACT_2696885 EP20 – SER_ACT_2696886 EP21 – SER_ACT_2696887 EP22 – SER_ACT_2696888 EP23 – SER_ACT_2696889 EP24 – SER_ACT_2696890 Sub: EP01 – SER_ACT_2690473 EP02 – SER_ACT_2690474 EP03 – SER_ACT_2690475 EP04 – SER_ACT_2690476 EP05 – SER_ACT_2690477 EP06 – SER_ACT_2690478 EP07 – SER_ACT_2690479 EP08 – SER_ACT_2690480 EP09 – SER_ACT_2690481 EP10 – SER_ACT_2690482 EP11 – SER_ACT_2690483 EP12 – SER_ACT_2690484 EP13 – SER_ACT_2690485 EP14 – SER_ACT_2690486 EP15 – SER_ACT_2690487 EP16 – SER_ACT_2690488 | C29: Taxi Driver Season 2 | D29: Ẩn danh 2 | E29: PCCW VUCLIP | F29: PCCW VUCLIP/2023/HDBQ The Secret Romantic Guesthouse | G29: Korea | H29: 2022 | I29: 16 | J29: 70 | K29: =(I29*J29)/60 | L29: 24 | M29: Action, Crime | N29: Crime, Thriller | O29: 44974 | P29: 46434 | Q29: 44974 | R29: K+LIFE | S29: Exclusive All TV Rights during LP and Exclusive All VOD rights for first 4 months | T29: Yes | U29: Yes | V29: Yes | W29: Yes | X29: Yes | Y29: Yes | Z29: Yes | AA29: Yes | AB29: Yes | AC29: 44974 | AD29: 46434 | AE29: 8 | AF29: 3 | AG29: 45457 | AH29: =AE29-AF29 | AI29: Yes | AJ29: Yes | AK29: Phim Song song | AL29: Phim còn hạn từ 2026 | AM29: Taxi Driver Season 2 | AO29: =SUMIF('TK 15661.Bản quyền phim '!F:F,'KK2. Series'!C29,'TK 15661.Bản quyền phim '!K:K) | AP29: =COUNTIF('242.BQ Phim VOD'!$C$5:$C$8,'KK2. Series'!AM29) | AQ29: =COUNTIF('TK 15666. Phim SX'!$C$6:$C$13,'KK2. Series'!AM29) | AR29: =COUNTIF('TK 15661.Bản quyền phim '!F:F,'KK2. Series'!AM29) | AT29: =SUM(AP29:AS29) | AZ29: ⚠ Partial (38/40 clips)
A30: 24 | B30: EP01 – SER_THR_23_2690901 EP02 – SER_THR_23_2690902 EP03 – SER_THR_23_2690903 EP04 – SER_THR_23_2690904 EP05 – SER_THR_23_2690905 EP06 – SER_THR_23_2690906 EP07 – SER_THR_23_2690907 EP08 – SER_THR_23_2690908 EP09 – SER_THR_23_2690909 EP10 – SER_THR_23_2690910 EP11 – SER_THR_23_2690911 EP12 – SER_THR_23_2690912 EP13 – SER_THR_23_2690913 EP14 – SER_THR_23_2690914 EP15 – SER_THR_23_2690915 EP16 – SER_THR_23_2690916 EP17 – SER_THR_23_2690917 EP18 – SER_THR_23_2690918 EP19 – SER_THR_23_2690919 EP20 – SER_THR_23_2690920 EP21 – SER_THR_23_2690921 EP22 – SER_THR_23_2690922 EP23 – SER_THR_23_2690923 EP24 – SER_THR_23_2690924 EP25 – SER_THR_23_2690925 EP26 – SER_THR_23_2690926 EP27 – SER_THR_23_2690927 EP28 – SER_THR_23_2690928 EP29 – SER_THR_23_2690929 EP30 – SER_THR_23_2690930 EP31 – SER_THR_23_2690931 EP32 – SER_THR_23_2690932 EP33 – SER_THR_23_2690933 EP34 – SER_THR_23_2690934 EP35 – SER_THR_23_2690935 EP36 – SER_THR_23_2690936 | C30: Strange Tales of Tang Dynasty | D30: Đường Triều Quỷ Sự Lục | E30: HT | F30: 59/2023/HDBQ/VSTV-HT | G30: China | H30: 2022 | I30: 36 | J30: 45 | K30: =(I30*J30)/60 | L30: =I30 | M30: =M29 | N30: Crime, Thriller | O30: 45015 | P30: 46110 | Q30: 45015 | R30: K+LIFE | S30: Exclusive All TV Rights for 6 months and Non exclusive All SVOD and TVOD during LP | T30: No | U30: Yes | V30: Yes | W30: Yes | X30: No | Y30: No | Z30: Yes | AA30: No | AB30: No | AC30: 45015 | AD30: 46110 | AE30: 6 | AF30: 3 | AG30: 45459 | AH30: =AE30-AF30 | AI30: Yes | AJ30: Yes | AL30: Phim còn hạn từ 2026 | AM30: Strange Tales of Tang Dynasty (Đường triều qủy sự lục) | AN30: Strange Tales of Tang Dynasty (Đường triều qủy sự lụ) | AO30: =SUMIF('TK 15661.Bản quyền phim '!F:F,'KK2. Series'!C30,'TK 15661.Bản quyền phim '!K:K) | AP30: =COUNTIF('242.BQ Phim VOD'!$C$5:$C$8,'KK2. Series'!AM30) | AQ30: =COUNTIF('TK 15666. Phim SX'!$C$6:$C$13,'KK2. Series'!AM30) | AR30: =COUNTIF('TK 15661.Bản quyền phim '!F:F,'KK2. Series'!AM30) | AT30: =SUM(AP30:AS30) | AZ30: ✓ Found
