Workbook
Name ad_cpm: Assumptions!$B$31
Name ad_impressions_base: Assumptions!$B$32
Name adoption_max: Assumptions!$B$18
Name adoption_midpoint: Assumptions!$B$19
Name adoption_steepness: Assumptions!$B$20
Name ap_days: Assumptions!$B$71
Name ar_days: Assumptions!$B$70
Name audit_fee: Assumptions!$B$34
Name base_year: Assumptions!$B$6
Name bhxh_rate: Assumptions!$B$62
Name capex_backend: 'Initial Investment'!$B$5
Name capex_cloud_setup: 'Initial Investment'!$B$4
Name capex_contingency: 'Initial Investment'!$B$13
Name capex_data_platform: 'Initial Investment'!$B$7
Name capex_devops: 'Initial Investment'!$B$11
Name capex_frontend: 'Initial Investment'!$B$6
Name capex_integration: 'Initial Investment'!$B$10
Name capex_maintenance_pct: Assumptions!$B$39
Name capex_security_setup: 'Initial Investment'!$B$8
Name capex_testing: 'Initial Investment'!$B$12
Name capex_total: 'Initial Investment'!$B$15
Name capex_ux_design: 'Initial Investment'!$B$9
Name cert_fee_escalation: Assumptions!$B$27
Name cert_fee_yr1: Assumptions!$B$26
Name churn_rate: Assumptions!$B$22
Name cit_rate: Assumptions!$B$67
Name cloud_elasticity: Assumptions!$B$82
Name cloud_gmv_factor: Assumptions!$B$77
Name cloud_per_1M_vcr: Assumptions!$B$43
Name daas_price: Assumptions!$B$30
Name depreciation_years: Assumptions!$B$69
Name discount_rate: Assumptions!$B$68
Name ecom_growth_rate: Assumptions!$B$14
Name ecom_market_base: Assumptions!$B$13
Name hr_bizops_per_100_ent: Assumptions!$B$81
Name marketing_growth: Assumptions!$B$41
Name mkt_efficiency_per_100: Assumptions!$B$78
Name opex_branding: Assumptions!$B$47
Name opex_cloud_base: Assumptions!$B$42
Name opex_contingency_pct: Assumptions!$B$53
Name opex_external: Assumptions!$B$45
Name opex_legal: Assumptions!$B$46
Name opex_marketing: Assumptions!$B$40
Name opex_partner_mgmt: Assumptions!$B$52
Name opex_pilot_eval: Assumptions!$B$49
Name opex_security: Assumptions!$B$48
Name opex_support_per_ent: Assumptions!$B$51
Name payment_proc_pct: Assumptions!$B$50
Name pilot_count: Assumptions!$B$21
Name platform_market_share: Assumptions!$B$29
Name recruit_cost_pct: Assumptions!$B$63
Name salary_bizops: Assumptions!$B$59
Name salary_data: Assumptions!$B$60
Name salary_dev: Assumptions!$B$58
Name salary_escalation: Assumptions!$B$61
Name salary_mgmt: Assumptions!$B$57
Name SAM_enterprises: Assumptions!$B$12
Name stage2_gate: Assumptions!$B$72
Name start_month: Assumptions!$B$7
Name support_discount: Assumptions!$B$80

Sheet Guide
A1: VISIT VIETNAM — FINANCIAL MODEL v5 — GUIDE
A2: v5.0 | 2026-03-21 | Added cascading relationships + Sensitivity Analysis
A3: SHEET DIRECTORY
A4: Sheet | B4: Purpose | C4: Notes
A5: Guide | B5: Model documentation, named ranges list, formula patterns, instructions | C5: Read first
A6: Assumptions | B6: 49 named ranges. ALL inputs live here (yellow cells). | C6: Only edit yellow cells
A7: Initial Investment | B7: 10 CAPEX items → capex_total. Depreciation schedule. | C7: capex_total used everywhere
A8: HR Plan | B8: 4 depts × 42 periods. Salary = headcount × named_salary × (1+escalation)^yrs × (1+bhxh) | C8: Yellow = editable headcount
A9: Market Sizing | B9: S-curve adoption. Year fracs from base_year+start_month. VCR projections. | C9: No hardcoded years
A10: Revenue Schedule | B10: 6 streams. Stage 2 gated on stage2_gate. | C10: All named range formulas
A11: Cost Schedule | B11: CAPEX (Initial Investment) + OPEX (HR Plan + 10 categories + contingency) | C11: Cross-sheet references
A12: P&L | B12: Revenue → COGS → GP → OPEX → EBITDA → D&A → EBIT → CIT → NI + margins | C12: capex_total/depreciation_years
A13: Cash Flow | B13: OCF + ICF → FCF + Cumulative. Working capital via ar_days. | C13: All named ranges
A14: DCF & Returns | B14: Annual FCF, NPV(discount_rate,...), IRR, ROI, max cash burn | C14: Single NPV formula
A15: Scenarios | B15: 5 scenarios: Worst/Bear/Base/Bull/Best. Copy column → Assumptions. | C15: Shows why v2 had 214% IRR
... A17: Budget 2026 | B17: Monthly Jan-Dec. Same structure, HR scales to 22 FTE. | C17: Approval-ready
A19: NAMED RANGES (49 total)
A20: Name | B20: Description | C20: Example formula usage
A21: base_year | B21: Project start year | C21: Year frac = base_year + (start_month-1+idx)/12
A22: adoption_max | B22: S-curve ceiling | C22: MAX(pilot_count, adoption_max/(1+EXP(...)))
A23: cert_fee_yr1 | B23: Annual cert fee (M VND) | C23: net_ent × cert_fee_yr1 × (1+escalation)^yrs
A24: capex_total | B24: Total CAPEX (from Initial Investment) | C24: capex_total/depreciation_years for D&A
A25: depreciation_years | B25: Depreciation period | C25: capex_total/depreciation_years/period_divisor
A26: salary_bizops | B26: BizOps monthly salary | C26: headcount × salary_bizops × months × (1+escalation)^yrs × (1+bhxh)
A27: bhxh_rate | B27: Social insurance rate | C27: Multiplied on all salary costs
A28: cit_rate | B28: Corporate income tax | C28: IF(EBIT>0, -EBIT×cit_rate, 0)
A29: discount_rate | B29: WACC | C29: NPV(discount_rate, FCF_array)
A30: stage2_gate | B30: Min enterprises for Stage 2 | C30: IF(net_ent >= stage2_gate, tx_rev, 0)
A33: GLOSSARY — KEY TERMS & ABBREVIATIONS
A34: Term | B34: Full Name / Meaning | C34: In this model
A35: NPV | B35: Net Present Value | C35: Sum of all future cash flows discounted to today. Positive = project creates value.
A36: IRR | B36: Internal Rate of Return | C36: Discount rate at which NPV = 0. Higher = better return. Compare vs WACC.
A37: WACC | B37: Weighted Average Cost of Capital | C37: Minimum return investors expect. Used as discount_rate (15% Base).
A38: ROI | B38: Return on Investment | C38: (Cumulative CF + Investment) / Investment. How much you get back per VND invested.
A39: EBITDA | B39: Earnings Before Interest, Tax, Depreciation & Amortization | C39: Operating profit before non-cash charges and tax. Key profitability metric.
A40: EBIT | B40: Earnings Before Interest & Tax | C40: =EBITDA -@Depreciation. Pre-@tax profit.
A41: CIT | B41: Corporate Income Tax | C41: Vietnamese standard rate = 20%. Applied only when EBIT > 0.
A42: FCF | B42: Free Cash Flow | C42: =@Operating CF +@ Investing CF. Cash actually available after all spending.
A43: D&A | B43: Depreciation & Amortization | C43: Non-cash expense spreading CAPEX over useful life (5 years here).
A44: NOPAT | B44: Net Operating Profit After Tax
A45: CAPEX | B45: Capital Expenditure | C45: One-time investment in assets (platform dev 5,280M). Depreciated over time.
A46: OPEX | B46: Operating Expenditure | C46: Ongoing costs: HR, marketing, cloud, legal, etc. Expensed immediately.
A47: COGS | B47: Cost of Goods Sold | C47: Direct costs tied to revenue: payment processing fees (2.5% of tx revenue).
A48: BHXH | B48: Bảo hiểm xã hội (Social Insurance) | C48: Employer pays ~21.5%: BHXH 17.5% + BHYT 3% + BHTN 1%.
A49: TAM | B49: Total Addressable Market | C49: All tourism enterprises in Vietnam (~40,000).
A50: SAM | B50: Serviceable Addressable Market | C50: Digitally active, certifiable subset (~15,000).
A51: SOM | B51: Serviceable Obtainable Market | C51: What VV can realistically capture (= adoption_max).
A52: GMV | B52: Gross Merchandise Value | C52: Total value of transactions flowing through the platform.
A53: VCR | B53: Visitor Certified Records | C53: Data records generated per enterprise. Basis for DaaS pricing.
A54: S-curve | B54: Logistic Growth Curve | C54: Adoption follows slow→fast→slow pattern. Formula: max/(1+EXP(-k*(t-midpoint)))
A55: Stage 1 | B55: Certification Platform (2025-2027) | C55: Revenue from cert fees, training, audits. Doesn't need transaction volume.
A56: Stage 2 | B56: Transaction Platform (2028-2030) | C56: Revenue from tx fees, DaaS, ads. Gated: needs ≥300 enterprises (stage2_gate).
A57: Gate | B57: Stage 2 activation threshold
A58: Churn | B58: Non-renewal rate | C58: % of enterprises that leave each year. Reduces net_enterprises.
A59: CAC | B59: Customer Acquisition Cost | C59: Marketing spend / new enterprises acquired. Not explicitly modeled.
A60: LTV | B60: Lifetime Value | C60: Total revenue from one enterprise over its lifetime. = ARPU / churn_rate.
A61: ARPU | B61: Average Revenue Per User | C61: Total revenue / net_enterprises. Annual revenue per certified enterprise.
A62: Named Range | B62: Excel defined name for a cell | C62: e.g. cert_fee_yr1 → Assumptions!$B$26. Used in formulas for clarity.
A63: Placeholder | B63: Yellow cell with blue font | C63: Editable input value. Change it → entire model recalculates.
A66: v5.0 CHANGES (2026-03-21)
A67: 1. Added CASCADING RELATIONSHIPS section to Assumptions (6 new named ranges):
A68: cloud_gmv_factor, mkt_efficiency_per_100, support_scale_threshold,
A69: support_discount, hr_bizops_per_100_ent, cloud_elasticity
A70: 2. Updated Cost Schedule formulas:
A71: • Cloud: now includes GMV-based cost (market_share → cloud) + elasticity
A72: • Marketing: efficiency scaling (more ent → lower cost/ent, floor 50%)
A73: • Support: economies of scale (past threshold → 30% cost reduction)
A74: 3. Added IMPACT MAP in Assumptions showing full cascade chain:
A75: adoption_max → revenue + HR + support + cloud
A76: platform_market_share → tx revenue + cloud + COGS
A77: churn_rate → net_ent → all linked items
... A82: 5. Added Sensitivity sheet to sheets list in Guide

Sheet Assumptions
A1: VISIT VIETNAM — FINANCIAL MODEL v5 — ASSUMPTIONS
A2: v5.0 | Yellow=inputs | Blue=placeholder | Named ranges in all formulas | NEW: Cascading relationships at bottom
A4: TIMING
A5: Parameter | B5: Value | C5: Unit | D5: Notes
A6: Base year | B6: 2025 | C6: Year | D6: Project start year
A7: Start month | B7: 7 | C7: Month | D7: July=7
A9: MARKET DATA
A10: Parameter | B10: Value | C10: Unit | D10: Notes
A11: Total tourism enterprises | B11: 40000 | D11: GSO/VNAT
A12: Serviceable enterprises | B12: 15000 | D12: Digitally active
A13: E-commerce tourism market (base yr) | B13: 82500 | C13: Bn VND | D13: e-Conomy SEA
A14: E-tourism YoY growth | B14: 0.08 | C14: % | D14: Historical
A16: ADOPTION S-CURVE
A17: Parameter | B17: Value | C17: Unit | D17: Notes
A18: Maximum enterprises (ceiling) | B18: 1200 | D18: S-curve asymptote (v3: was 3000)
A19: Midpoint year | B19: 2028 | C19: Year | D19: Inflection point
A20: Steepness factor | B20: 0.9 | D20: v3: was 1.2
A21: Starting enterprises | B21: 15 | D21: Pilot partners
A22: Annual non-renewal rate | B22: 0.2 | C22: % | D22: v3: was 0.15
A24: PRICING
A25: Parameter | B25: Value | C25: Unit | D25: Notes
A26: Certification fee/enterprise/yr | B26: 25 | C26: M VND | D26: v3: was 30M
A27: Cert fee annual increase | B27: 0.05 | C27: % | D27: v3: was 0.08
A28: Transaction fee (% of GMV) | B28: 0.02 | C28: % | D28: Platform commission
A29: % e-tourism GMV via VV | B29: 0.02 | C29: % | D29: v3: was 0.02
A30: DaaS price per M VCR | B30: 30 | C30: M VND | D30: v3: was 50
A31: Advertising CPM | B31: 150 | C31: K VND | D31: B2B benchmark
A32: Monthly impressions (K) | B32: 500 | C32: K | D32: Scales w/ enterprises
A33: Training fee per engagement | B33: 15 | C33: M VND | D33: NEW stream
A34: Audit fee per certification | B34: 10 | C34: M VND | D34: NEW stream
A35: % enterprises buying training | B35: 0.3 | C35: % | D35: Estimated
A37: COST PARAMETERS
A38: Parameter | B38: Value | C38: Unit | D38: Notes
A39: Maintenance (% of CAPEX/yr) | B39: 0.18 | C39: % | D39: Industry 15-20%
A40: Marketing (annual base) | B40: 7000 | C40: M VND | D40: v3: was 6000
A41: Marketing annual growth | B41: 0.15 | C41: % | D41: v3: was 0.10
A42: Cloud base (annual) | B42: 3250 | C42: M VND | D42: From original data
A43: Cloud cost per M VCR | B43: 8 | C43: M VND | D43: v3: was 5
A44: VCR per enterprise/month | B44: 10000 | C44: records | D44: Traffic estimate
A45: External affairs (annual) | B45: 400 | C45: M VND | D45: Current data
A46: Legal & compliance (annual) | B46: 240 | C46: M VND | D46: Current data
A47: Branding & events (annual) | B47: 4000 | C47: M VND | D47: Current data
A48: Security/pentest (annual) | B48: 250 | C48: M VND | D48: Current data
A49: Pilot evaluation (Y1 only) | B49: 200 | C49: M VND | D49: One-time
A50: Payment gateway fee | B50: 0.025 | C50: % | D50: COGS on tx revenue
... A53: Contingency (% total OPEX) | B53: 0.1 | C53: % | D53: Buffer
A55: HR PARAMETERS
A56: Parameter | B56: Value | C56: Unit | D56: Notes
A57: Avg monthly — Management | B57: 45 | C57: M VND | D57: Director/PM
A58: Avg monthly — Development | B58: 35 | C58: M VND | D58: Engineers
A59: Avg monthly — BizOps | B59: 20 | C59: M VND | D59: BD/support
A60: Avg monthly — Data/Analytics | B60: 40 | C60: M VND | D60: Data eng
A61: Annual salary increase | B61: 0.1 | C61: % | D61: VN market
A62: Social insurance (employer) | B62: 0.215 | C62: % | D62: BHXH+BHYT+BHTN
A63: Recruitment fee (% Y1 sal) | B63: 0.2 | C63: % | D63: Headhunter
A65: FINANCIAL PARAMETERS
A66: Parameter | B66: Value | C66: Unit | D66: Notes
A67: Corporate income tax | B67: 0.2 | C67: % | D67: Vietnamese law
A68: Discount rate (WACC) | B68: 0.15 | C68: % | D68: v3: was 0.12
A69: Depreciation period | B69: 5 | C69: Years | D69: Straight-line
A70: Accounts receivable days | B70: 45 | C70: Days | D70: Collection period
A71: Accounts payable days | B71: 30 | C71: Days | D71: Payment terms
A72: Stage 2 gate (min enterprises) | B72: 300 | D72: Activate tx fees
A75: CASCADING RELATIONSHIPS (how assumptions affect each other)
A76: Parameter | B76: Value | C76: Unit | D76: Cascade logic
A77: Cloud cost per Bn VND GMV processed | B77: 0.5 | C77: Tr VND/Bn | D77: ↑ market_share → ↑ GMV → ↑ cloud cost. Formula: GMV × this factor
A78: Marketing cost reduction per 100 enterprises | B78: 0.02 | C78: %/100 ent | D78: ↑ adoption → ↓ marketing/ent. Formula: marketing × MAX(0.5, 1 - ent×factor/100)
A79: Enterprises threshold for economies of scale | B79: 500 | C79: enterprises | D79: When net_ent > threshold → support cost drops by support_discount
A80: Support cost reduction after threshold | B80: 0.3 | C80: ratio | D80: ↑ ent past threshold → support/ent × (1 - discount). Economies of scale.
A81: BizOps staff needed per 100 enterprises (floor) | B81: 2 | C81: people/100 | D81: ↑ adoption → ↑ BizOps needed. Floor = MAX(manual_hc, ent×ratio/100)
A82: Cloud cost elasticity to enterprise count | B82: 1.2 | C82: factor | D82: VCR cost scales by ent^elasticity instead of linear. >1 = super-linear.
A85: IMPACT MAP — How market_share cascades to costs
A86: adoption_max ↑ | B86: → net_enterprises ↑ | C86: → HR BizOps headcount ↑ (hr_bizops_per_100_ent) | D86: → HR Cost ↑
C87: → VCR volume ↑ (vcr_per_enterprise × net_ent) | D87: → Cloud Cost ↑ (cloud_per_1M_vcr)
C88: → Support demand ↑ (opex_support_per_ent × net_ent) | D88: → OPEX ↑
C89: → Marketing efficiency ↑ (cost/ent decreases) | D89: → Per-unit OPEX ↓
C90: → Cert/Training/Audit revenue ↑ | D90: → Revenue ↑
A92: platform_market_share ↑ | B92: → GMV through platform ↑ | C92: → Transaction fees ↑ (tx_take_rate × GMV) | D92: → Revenue ↑
C93: → Cloud processing load ↑ (cloud_gmv_factor × GMV) | D93: → Cloud Cost ↑
C94: → Payment processing fees ↑ (payment_proc_pct × tx_rev) | D94: → COGS ↑
C95: → DaaS & Ads potential ↑ | D95: → Revenue ↑
A97: churn_rate ↑ | B97: → net_enterprises ↓ | C97: → All enterprise-linked revenue ↓ | D97: → Revenue ↓
C98: → Need more new sales to replace | D98: → Marketing cost pressure ↑
C99: → Support & HR needs more stable | D99: → Cost stays high vs falling revenue

Sheet Initial Investment
A1: INITIAL INVESTMENT — CAPEX BREAKDOWN (M VND)
A3: CAPEX Item | B3: Amount (M VND) | C3: Timing | D3: Notes
A4: Cloud infrastructure setup | B4: 800 | C4: H2 2025 | D4: AWS/GCP initial
A5: Backend development | B5: 1200 | C5: H2 2025 | D5: API, DB, core
A6: Frontend + mobile | B6: 900 | C6: H2 2025 | D6: Web + mobile
A7: Data platform | B7: 600 | C7: H2 2025 | D7: Pipeline, analytics
A8: Security infrastructure | B8: 250 | C8: H2 2025 | D8: Pentest, auth
A9: UX/UI design | B9: 350 | C9: H2 2025 | D9: Design system
A10: 3rd-party integrations | B10: 400 | C10: H2 2025 | D10: Payment, OTA APIs
A11: DevOps & CI/CD | B11: 280 | C11: H2 2025 | D11: Deploy pipeline
A12: QA & testing | B12: 200 | C12: H2 2025 | D12: Auto + load test
A13: CAPEX contingency (10%) | B13: 300 | C13: H2 2025 | D13: Buffer
A15: TOTAL INITIAL CAPEX | B15: =SUM(B4:B13) -> 5280
A17: DEPRECIATION SCHEDULE
A18: Year | B18: Annual D&A | C18: Accum D&A | D18: Net Book Value
A19: 2025 | B19: =capex_total/depreciation_years -> 1056 | C19: =B19 -> 1056 | D19: =capex_total-C19 -> 4224
A20: 2026 | B20: =capex_total/depreciation_years -> 1056 | C20: =C19+B20 -> 2112 | D20: =capex_total-C20 -> 3168
A21: 2027 | B21: =capex_total/depreciation_years -> 1056 | C21: =C20+B21 -> 3168 | D21: =capex_total-C21 -> 2112
A22: 2028 | B22: =capex_total/depreciation_years -> 1056 | C22: =C21+B22 -> 4224 | D22: =capex_total-C22 -> 1056
A23: 2029 | B23: =capex_total/depreciation_years -> 1056 | C23: =C22+B23 -> 5280 | D23: =capex_total-C23 -> 0
A24: 2030 | B24: =0 -> 0 | C24: =C23+B24 -> 5280 | D24: =capex_total-C24 -> 0

Sheet HR Plan
A1: HR PLAN — HEADCOUNT & COST
A3: Dept / Item | B3: Unit | C3: Jul 2025 | D3: Aug 2025 | E3: Sep 2025 | F3: Oct 2025 | G3: Nov 2025 | H3: Dec 2025 | I3: Jan 2026 | J3: Feb 2026 | K3: Mar 2026 | L3: Apr 2026 | M3: May 2026 | N3: Jun 2026 | O3: Jul 2026 | P3: Aug 2026 | Q3: Sep 2026 | R3: Oct 2026 | S3: Nov 2026 | T3: Dec 2026 | U3: Jan 2027 | V3: Feb 2027 | W3: Mar 2027 | X3: Apr 2027 | Y3: May 2027 | Z3: Jun 2027 | AA3: Jul 2027 | AB3: Aug 2027 | AC3: Sep 2027 | AD3: Oct 2027 | AE3: Nov 2027 | AF3: Dec 2027 | AG3: Q1 2028 | AH3: Q2 2028 | AI3: Q3 2028 | AJ3: Q4 2028 | AK3: Q1 2029 | AL3: Q2 2029 | AM3: Q3 2029 | AN3: Q4 2029 | AO3: Q1 2030 | AP3: Q2 2030 | AQ3: Q3 2030 | AR3: Q4 2030
A4: HEADCOUNT
A5: Management | B5: people | C5: 2 | D5: 2 | E5: 2 | F5: 2 | G5: 2 | H5: 2 | I5: 2 | J5: 2 | K5: 2 | L5: 2 | M5: 2 | N5: 2 | O5: 2 | P5: 2 | Q5: 2 | R5: 2 | S5: 2 | T5: 2 | U5: 3 | V5: 3 | W5: 3 | X5: 3 | Y5: 3 | Z5: 3 | AA5: 3 | AB5: 3 | AC5: 3 | AD5: 3 | AE5: 3 | AF5: 3 | AG5: 3 | AH5: 3 | AI5: 3 | AJ5: 3 | AK5: 4 | AL5: 4 | AM5: 4 | AN5: 4 | AO5: 4 | AP5: 4 | AQ5: 4 | AR5: 4
A6: Development | B6: people | C6: 12 | D6: 12 | E6: 12 | F6: 12 | G6: 12 | H6: 12 | I6: 12 | J6: 12 | K6: 12 | L6: 12 | M6: 12 | N6: 12 | O6: 12 | P6: 12 | Q6: 12 | R6: 12 | S6: 12 | T6: 12 | U6: 14 | V6: 14 | W6: 14 | X6: 14 | Y6: 14 | Z6: 14 | AA6: 14 | AB6: 14 | AC6: 14 | AD6: 14 | AE6: 14 | AF6: 14 | AG6: 16 | AH6: 16 | AI6: 16 | AJ6: 16 | AK6: 18 | AL6: 18 | AM6: 18 | AN6: 18 | AO6: 20 | AP6: 20 | AQ6: 20 | AR6: 20
A7: Biz Ops | B7: people | C7: 2 | D7: 2 | E7: 2 | F7: 2 | G7: 2 | H7: 2 | I7: 6 | J7: 6 | K7: 6 | L7: 6 | M7: 6 | N7: 6 | O7: 6 | P7: 6 | Q7: 6 | R7: 6 | S7: 6 | T7: 6 | U7: 10 | V7: 10 | W7: 10 | X7: 10 | Y7: 10 | Z7: 10 | AA7: 10 | AB7: 10 | AC7: 10 | AD7: 10 | AE7: 10 | AF7: 10 | AG7: 18 | AH7: 18 | AI7: 18 | AJ7: 18 | AK7: 28 | AL7: 28 | AM7: 28 | AN7: 28 | AO7: 35 | AP7: 35 | AQ7: 35 | AR7: 35
A8: Data & Analytics | B8: people | C8: 0 | D8: 0 | E8: 0 | F8: 0 | G8: 0 | H8: 0 | I8: 2 | J8: 2 | K8: 2 | L8: 2 | M8: 2 | N8: 2 | O8: 2 | P8: 2 | Q8: 2 | R8: 2 | S8: 2 | T8: 2 | U8: 3 | V8: 3 | W8: 3 | X8: 3 | Y8: 3 | Z8: 3 | AA8: 3 | AB8: 3 | AC8: 3 | AD8: 3 | AE8: 3 | AF8: 3 | AG8: 4 | AH8: 4 | AI8: 4 | AJ8: 4 | AK8: 5 | AL8: 5 | AM8: 5 | AN8: 5 | AO8: 6 | AP8: 6 | AQ8: 6 | AR8: 6
A9: TOTAL HEADCOUNT | B9: people | C9: =C5+C6+C7+C8 -> 16 | D9: =D5+D6+D7+D8 -> 16 | E9: =E5+E6+E7+E8 -> 16 | F9: =F5+F6+F7+F8 -> 16 | G9: =G5+G6+G7+G8 -> 16 | H9: =H5+H6+H7+H8 -> 16 | I9: =I5+I6+I7+I8 -> 22 | J9: =J5+J6+J7+J8 -> 22 | ... AR9: =AR5+AR6+AR7+AR8 -> 65
A11: NEW HIRES
A12: New hires | B12: people | C12: =C9 -> 16 | D12: =MAX(0,D9-C9) -> 0 | E12: =MAX(0,E9-D9) -> 0 | F12: =MAX(0,F9-E9) -> 0 | G12: =MAX(0,G9-F9) -> 0 | H12: =MAX(0,H9-G9) -> 0 | I12: =MAX(0,I9-H9) -> 6 | J12: =MAX(0,J9-I9) -> 0 | K12: =MAX(0,K9-J9) -> 0 | ... AR12: =MAX(0,AR9-AQ9) -> 0
A14: SALARY COST (M VND)
A15: Management cost | B15: M VND | C15: =C5*salary_mgmt*1*(1+salary_escalation)^0*(1+bhxh_rate) -> 109.35 | D15: =D5*salary_mgmt*1*(1+salary_escalation)^0*(1+bhxh_rate) -> 109.35 | E15: =E5*salary_mgmt*1*(1+salary_escalation)^0*(1+bhxh_rate) -> 109.35 | F15: =F5*salary_mgmt*1*(1+salary_escalation)^0*(1+bhxh_rate) -> 109.35 | G15: =G5*salary_mgmt*1*(1+salary_escalation)^0*(1+bhxh_rate) -> 109.35 | H15: =H5*salary_mgmt*1*(1+salary_escalation)^0*(1+bhxh_rate) -> 109.35 | I15: =I5*salary_mgmt*1*(1+salary_escalation)^1*(1+bhxh_rate) -> 120.285 | J15: =J5*salary_mgmt*1*(1+salary_escalation)^1*(1+bhxh_rate) -> 120.285 | K15: =K5*salary_mgmt*1*(1+salary_escalation)^1*(1+bhxh_rate) -> 120.285 | L15: =L5*salary_mgmt*1*(1+salary_escalation)^1*(1+bhxh_rate) -> 120.285 | M15: =M5*salary_mgmt*1*(1+salary_escalation)^1*(1+bhxh_rate) -> 120.285 | N15: =N5*salary_mgmt*1*(1+salary_escalation)^1*(1+bhxh_rate) -> 120.285 | O15: =O5*salary_mgmt*1*(1+salary_escalation)^1*(1+bhxh_rate) -> 120.285 | P15: =P5*salary_mgmt*1*(1+salary_escalation)^1*(1+bhxh_rate) -> 120.285 | ... T15: =T5*salary_mgmt*1*(1+salary_escalation)^1*(1+bhxh_rate) -> 120.285 | U15: =U5*salary_mgmt*1*(1+salary_escalation)^2*(1+bhxh_rate) -> 198.47025 | V15: =V5*salary_mgmt*1*(1+salary_escalation)^2*(1+bhxh_rate) -> 198.47025 | W15: =W5*salary_mgmt*1*(1+salary_escalation)^2*(1+bhxh_rate) -> 198.47025 | X15: =X5*salary_mgmt*1*(1+salary_escalation)^2*(1+bhxh_rate) -> 198.47025 | Y15: =Y5*salary_mgmt*1*(1+salary_escalation)^2*(1+bhxh_rate) -> 198.47025 | Z15: =Z5*salary_mgmt*1*(1+salary_escalation)^2*(1+bhxh_rate) -> 198.47025 | AA15: =AA5*salary_mgmt*1*(1+salary_escalation)^2*(1+bhxh_rate) -> 198.47025 | AB15: =AB5*salary_mgmt*1*(1+salary_escalation)^2*(1+bhxh_rate) -> 198.47025 | ... AF15: =AF5*salary_mgmt*1*(1+salary_escalation)^2*(1+bhxh_rate) -> 198.47025 | AG15: =AG5*salary_mgmt*3*(1+salary_escalation)^3*(1+bhxh_rate) -> 654.95183 | AH15: =AH5*salary_mgmt*3*(1+salary_escalation)^3*(1+bhxh_rate) -> 654.95183 | AI15: =AI5*salary_mgmt*3*(1+salary_escalation)^3*(1+bhxh_rate) -> 654.95183 | AJ15: =AJ5*salary_mgmt*3*(1+salary_escalation)^3*(1+bhxh_rate) -> 654.95183 | AK15: =AK5*salary_mgmt*3*(1+salary_escalation)^4*(1+bhxh_rate) -> 960.59601 | AL15: =AL5*salary_mgmt*3*(1+salary_escalation)^4*(1+bhxh_rate) -> 960.59601 | AM15: =AM5*salary_mgmt*3*(1+salary_escalation)^4*(1+bhxh_rate) -> 960.59601 | AN15: =AN5*salary_mgmt*3*(1+salary_escalation)^4*(1+bhxh_rate) -> 960.59601 | AO15: =AO5*salary_mgmt*3*(1+salary_escalation)^5*(1+bhxh_rate) -> 1056.6556 | AP15: =AP5*salary_mgmt*3*(1+salary_escalation)^5*(1+bhxh_rate) -> 1056.6556 | AQ15: =AQ5*salary_mgmt*3*(1+salary_escalation)^5*(1+bhxh_rate) -> 1056.6556 | AR15: =AR5*salary_mgmt*3*(1+salary_escalation)^5*(1+bhxh_rate) -> 1056.6556
A16: Development cost | B16: M VND | C16: =C6*salary_dev*1*(1+salary_escalation)^0*(1+bhxh_rate) -> 510.3 | D16: =D6*salary_dev*1*(1+salary_escalation)^0*(1+bhxh_rate) -> 510.3 | E16: =E6*salary_dev*1*(1+salary_escalation)^0*(1+bhxh_rate) -> 510.3 | F16: =F6*salary_dev*1*(1+salary_escalation)^0*(1+bhxh_rate) -> 510.3 | G16: =G6*salary_dev*1*(1+salary_escalation)^0*(1+bhxh_rate) -> 510.3 | H16: =H6*salary_dev*1*(1+salary_escalation)^0*(1+bhxh_rate) -> 510.3 | I16: =I6*salary_dev*1*(1+salary_escalation)^1*(1+bhxh_rate) -> 561.33 | J16: =J6*salary_dev*1*(1+salary_escalation)^1*(1+bhxh_rate) -> 561.33 | K16: =K6*salary_dev*1*(1+salary_escalation)^1*(1+bhxh_rate) -> 561.33 | L16: =L6*salary_dev*1*(1+salary_escalation)^1*(1+bhxh_rate) -> 561.33 | M16: =M6*salary_dev*1*(1+salary_escalation)^1*(1+bhxh_rate) -> 561.33 | N16: =N6*salary_dev*1*(1+salary_escalation)^1*(1+bhxh_rate) -> 561.33 | O16: =O6*salary_dev*1*(1+salary_escalation)^1*(1+bhxh_rate) -> 561.33 | P16: =P6*salary_dev*1*(1+salary_escalation)^1*(1+bhxh_rate) -> 561.33 | ... T16: =T6*salary_dev*1*(1+salary_escalation)^1*(1+bhxh_rate) -> 561.33 | U16: =U6*salary_dev*1*(1+salary_escalation)^2*(1+bhxh_rate) -> 720.3735 | V16: =V6*salary_dev*1*(1+salary_escalation)^2*(1+bhxh_rate) -> 720.3735 | W16: =W6*salary_dev*1*(1+salary_escalation)^2*(1+bhxh_rate) -> 720.3735 | X16: =X6*salary_dev*1*(1+salary_escalation)^2*(1+bhxh_rate) -> 720.3735 | Y16: =Y6*salary_dev*1*(1+salary_escalation)^2*(1+bhxh_rate) -> 720.3735 | Z16: =Z6*salary_dev*1*(1+salary_escalation)^2*(1+bhxh_rate) -> 720.3735 | AA16: =AA6*salary_dev*1*(1+salary_escalation)^2*(1+bhxh_rate) -> 720.3735 | AB16: =AB6*salary_dev*1*(1+salary_escalation)^2*(1+bhxh_rate) -> 720.3735 | ... AF16: =AF6*salary_dev*1*(1+salary_escalation)^2*(1+bhxh_rate) -> 720.3735 | AG16: =AG6*salary_dev*3*(1+salary_escalation)^3*(1+bhxh_rate) -> 2716.8372 | AH16: =AH6*salary_dev*3*(1+salary_escalation)^3*(1+bhxh_rate) -> 2716.8372 | AI16: =AI6*salary_dev*3*(1+salary_escalation)^3*(1+bhxh_rate) -> 2716.8372 | AJ16: =AJ6*salary_dev*3*(1+salary_escalation)^3*(1+bhxh_rate) -> 2716.8372 | AK16: =AK6*salary_dev*3*(1+salary_escalation)^4*(1+bhxh_rate) -> 3362.086 | AL16: =AL6*salary_dev*3*(1+salary_escalation)^4*(1+bhxh_rate) -> 3362.086 | AM16: =AM6*salary_dev*3*(1+salary_escalation)^4*(1+bhxh_rate) -> 3362.086 | AN16: =AN6*salary_dev*3*(1+salary_escalation)^4*(1+bhxh_rate) -> 3362.086 | AO16: =AO6*salary_dev*3*(1+salary_escalation)^5*(1+bhxh_rate) -> 4109.2163 | AP16: =AP6*salary_dev*3*(1+salary_escalation)^5*(1+bhxh_rate) -> 4109.2163 | AQ16: =AQ6*salary_dev*3*(1+salary_escalation)^5*(1+bhxh_rate) -> 4109.2163 | AR16: =AR6*salary_dev*3*(1+salary_escalation)^5*(1+bhxh_rate) -> 4109.2163
A17: Biz Ops cost | B17: M VND | C17: =C7*salary_bizops*1*(1+salary_escalation)^0*(1+bhxh_rate) -> 48.6 | D17: =D7*salary_bizops*1*(1+salary_escalation)^0*(1+bhxh_rate) -> 48.6 | E17: =E7*salary_bizops*1*(1+salary_escalation)^0*(1+bhxh_rate) -> 48.6 | F17: =F7*salary_bizops*1*(1+salary_escalation)^0*(1+bhxh_rate) -> 48.6 | G17: =G7*salary_bizops*1*(1+salary_escalation)^0*(1+bhxh_rate) -> 48.6 | H17: =H7*salary_bizops*1*(1+salary_escalation)^0*(1+bhxh_rate) -> 48.6 | I17: =I7*salary_bizops*1*(1+salary_escalation)^1*(1+bhxh_rate) -> 160.38 | J17: =J7*salary_bizops*1*(1+salary_escalation)^1*(1+bhxh_rate) -> 160.38 | K17: =K7*salary_bizops*1*(1+salary_escalation)^1*(1+bhxh_rate) -> 160.38 | L17: =L7*salary_bizops*1*(1+salary_escalation)^1*(1+bhxh_rate) -> 160.38 | M17: =M7*salary_bizops*1*(1+salary_escalation)^1*(1+bhxh_rate) -> 160.38 | N17: =N7*salary_bizops*1*(1+salary_escalation)^1*(1+bhxh_rate) -> 160.38 | O17: =O7*salary_bizops*1*(1+salary_escalation)^1*(1+bhxh_rate) -> 160.38 | P17: =P7*salary_bizops*1*(1+salary_escalation)^1*(1+bhxh_rate) -> 160.38 | ... T17: =T7*salary_bizops*1*(1+salary_escalation)^1*(1+bhxh_rate) -> 160.38 | U17: =U7*salary_bizops*1*(1+salary_escalation)^2*(1+bhxh_rate) -> 294.03 | V17: =V7*salary_bizops*1*(1+salary_escalation)^2*(1+bhxh_rate) -> 294.03 | W17: =W7*salary_bizops*1*(1+salary_escalation)^2*(1+bhxh_rate) -> 294.03 | X17: =X7*salary_bizops*1*(1+salary_escalation)^2*(1+bhxh_rate) -> 294.03 | Y17: =Y7*salary_bizops*1*(1+salary_escalation)^2*(1+bhxh_rate) -> 294.03 | Z17: =Z7*salary_bizops*1*(1+salary_escalation)^2*(1+bhxh_rate) -> 294.03 | AA17: =AA7*salary_bizops*1*(1+salary_escalation)^2*(1+bhxh_rate) -> 294.03 | AB17: =AB7*salary_bizops*1*(1+salary_escalation)^2*(1+bhxh_rate) -> 294.03 | ... AF17: =AF7*salary_bizops*1*(1+salary_escalation)^2*(1+bhxh_rate) -> 294.03 | AG17: =AG7*salary_bizops*3*(1+salary_escalation)^3*(1+bhxh_rate) -> 1746.5382 | AH17: =AH7*salary_bizops*3*(1+salary_escalation)^3*(1+bhxh_rate) -> 1746.5382 | AI17: =AI7*salary_bizops*3*(1+salary_escalation)^3*(1+bhxh_rate) -> 1746.5382 | AJ17: =AJ7*salary_bizops*3*(1+salary_escalation)^3*(1+bhxh_rate) -> 1746.5382 | AK17: =AK7*salary_bizops*3*(1+salary_escalation)^4*(1+bhxh_rate) -> 2988.5209 | AL17: =AL7*salary_bizops*3*(1+salary_escalation)^4*(1+bhxh_rate) -> 2988.5209 | AM17: =AM7*salary_bizops*3*(1+salary_escalation)^4*(1+bhxh_rate) -> 2988.5209 | AN17: =AN7*salary_bizops*3*(1+salary_escalation)^4*(1+bhxh_rate) -> 2988.5209 | AO17: =AO7*salary_bizops*3*(1+salary_escalation)^5*(1+bhxh_rate) -> 4109.2163 | AP17: =AP7*salary_bizops*3*(1+salary_escalation)^5*(1+bhxh_rate) -> 4109.2163 | AQ17: =AQ7*salary_bizops*3*(1+salary_escalation)^5*(1+bhxh_rate) -> 4109.2163 | AR17: =AR7*salary_bizops*3*(1+salary_escalation)^5*(1+bhxh_rate) -> 4109.2163
A18: Data & Analytics cost | B18: M VND | C18: =C8*salary_data*1*(1+salary_escalation)^0*(1+bhxh_rate) -> 0 | D18: =D8*salary_data*1*(1+salary_escalation)^0*(1+bhxh_rate) -> 0 | E18: =E8*salary_data*1*(1+salary_escalation)^0*(1+bhxh_rate) -> 0 | F18: =F8*salary_data*1*(1+salary_escalation)^0*(1+bhxh_rate) -> 0 | G18: =G8*salary_data*1*(1+salary_escalation)^0*(1+bhxh_rate) -> 0 | H18: =H8*salary_data*1*(1+salary_escalation)^0*(1+bhxh_rate) -> 0 | I18: =I8*salary_data*1*(1+salary_escalation)^1*(1+bhxh_rate) -> 106.92 | J18: =J8*salary_data*1*(1+salary_escalation)^1*(1+bhxh_rate) -> 106.92 | K18: =K8*salary_data*1*(1+salary_escalation)^1*(1+bhxh_rate) -> 106.92 | L18: =L8*salary_data*1*(1+salary_escalation)^1*(1+bhxh_rate) -> 106.92 | M18: =M8*salary_data*1*(1+salary_escalation)^1*(1+bhxh_rate) -> 106.92 | N18: =N8*salary_data*1*(1+salary_escalation)^1*(1+bhxh_rate) -> 106.92 | O18: =O8*salary_data*1*(1+salary_escalation)^1*(1+bhxh_rate) -> 106.92 | P18: =P8*salary_data*1*(1+salary_escalation)^1*(1+bhxh_rate) -> 106.92 | ... T18: =T8*salary_data*1*(1+salary_escalation)^1*(1+bhxh_rate) -> 106.92 | U18: =U8*salary_data*1*(1+salary_escalation)^2*(1+bhxh_rate) -> 176.418 | V18: =V8*salary_data*1*(1+salary_escalation)^2*(1+bhxh_rate) -> 176.418 | W18: =W8*salary_data*1*(1+salary_escalation)^2*(1+bhxh_rate) -> 176.418 | X18: =X8*salary_data*1*(1+salary_escalation)^2*(1+bhxh_rate) -> 176.418 | Y18: =Y8*salary_data*1*(1+salary_escalation)^2*(1+bhxh_rate) -> 176.418 | Z18: =Z8*salary_data*1*(1+salary_escalation)^2*(1+bhxh_rate) -> 176.418 | AA18: =AA8*salary_data*1*(1+salary_escalation)^2*(1+bhxh_rate) -> 176.418 | AB18: =AB8*salary_data*1*(1+salary_escalation)^2*(1+bhxh_rate) -> 176.418 | ... AF18: =AF8*salary_data*1*(1+salary_escalation)^2*(1+bhxh_rate) -> 176.418 | AG18: =AG8*salary_data*3*(1+salary_escalation)^3*(1+bhxh_rate) -> 776.2392 | AH18: =AH8*salary_data*3*(1+salary_escalation)^3*(1+bhxh_rate) -> 776.2392 | AI18: =AI8*salary_data*3*(1+salary_escalation)^3*(1+bhxh_rate) -> 776.2392 | AJ18: =AJ8*salary_data*3*(1+salary_escalation)^3*(1+bhxh_rate) -> 776.2392 | AK18: =AK8*salary_data*3*(1+salary_escalation)^4*(1+bhxh_rate) -> 1067.3289 | AL18: =AL8*salary_data*3*(1+salary_escalation)^4*(1+bhxh_rate) -> 1067.3289 | AM18: =AM8*salary_data*3*(1+salary_escalation)^4*(1+bhxh_rate) -> 1067.3289 | AN18: =AN8*salary_data*3*(1+salary_escalation)^4*(1+bhxh_rate) -> 1067.3289 | AO18: =AO8*salary_data*3*(1+salary_escalation)^5*(1+bhxh_rate) -> 1408.8741 | AP18: =AP8*salary_data*3*(1+salary_escalation)^5*(1+bhxh_rate) -> 1408.8741 | AQ18: =AQ8*salary_data*3*(1+salary_escalation)^5*(1+bhxh_rate) -> 1408.8741 | AR18: =AR8*salary_data*3*(1+salary_escalation)^5*(1+bhxh_rate) -> 1408.8741
A19: TOTAL SALARY | B19: M VND | C19: =C15+C16+C17+C18 -> 668.25 | D19: =D15+D16+D17+D18 -> 668.25 | E19: =E15+E16+E17+E18 -> 668.25 | F19: =F15+F16+F17+F18 -> 668.25 | G19: =G15+G16+G17+G18 -> 668.25 | H19: =H15+H16+H17+H18 -> 668.25 | I19: =I15+I16+I17+I18 -> 948.915 | J19: =J15+J16+J17+J18 -> 948.915 | ... AR19: =AR15+AR16+AR17+AR18 -> 10683.962
A20: Recruitment | B20: M VND | C20: =C12*30*12*recruit_cost_pct -> 1152 | D20: =D12*30*12*recruit_cost_pct -> 0 | E20: =E12*30*12*recruit_cost_pct -> 0 | F20: =F12*30*12*recruit_cost_pct -> 0 | G20: =G12*30*12*recruit_cost_pct -> 0 | H20: =H12*30*12*recruit_cost_pct -> 0 | I20: =I12*30*12*recruit_cost_pct -> 432 | J20: =J12*30*12*recruit_cost_pct -> 0 | ... AR20: =AR12*30*12*recruit_cost_pct -> 0
A21: TOTAL HR COST | B21: M VND | C21: =C19+C20 -> 1820.25 | D21: =D19+D20 -> 668.25 | E21: =E19+E20 -> 668.25 | F21: =F19+F20 -> 668.25 | G21: =G19+G20 -> 668.25 | H21: =H19+H20 -> 668.25 | I21: =I19+I20 -> 1380.915 | J21: =J19+J20 -> 948.915 | ... AR21: =AR19+AR20 -> 10683.962

Sheet Market Sizing
A1: MARKET SIZING & ADOPTION
A3: Period index | B3: idx | C3: 0 | D3: 1 | E3: 2 | F3: 3 | G3: 4 | H3: 5 | I3: 6 | J3: 7 | K3: 8 | L3: 9 | M3: 10 | N3: 11 | O3: 12 | P3: 13 | Q3: 14 | R3: 15 | S3: 16 | T3: 17 | U3: 18 | V3: 19 | W3: 20 | X3: 21 | Y3: 22 | Z3: 23 | AA3: 24 | AB3: 25 | AC3: 26 | AD3: 27 | AE3: 28 | AF3: 29 | AG3: 30 | AH3: 31 | AI3: 32 | AJ3: 33 | AK3: 34 | AL3: 35 | AM3: 36 | AN3: 37 | AO3: 38 | AP3: 39 | AQ3: 40 | AR3: 41
A4: Year fraction | B4: year | C4: =base_year+(start_month-1+C3)/12 -> 2025.5 | D4: =base_year+(start_month-1+D3)/12 -> 2025.5833 | E4: =base_year+(start_month-1+E3)/12 -> 2025.6667 | F4: =base_year+(start_month-1+F3)/12 -> 2025.75 | G4: =base_year+(start_month-1+G3)/12 -> 2025.8333 | H4: =base_year+(start_month-1+H3)/12 -> 2025.9167 | I4: =base_year+(start_month-1+I3)/12 -> 2026 | J4: =base_year+(start_month-1+J3)/12 -> 2026.0833 | ... AF4: =base_year+(start_month-1+AF3)/12 -> 2027.9167 | AG4: =2028+(1-0.5)/12 -> 2028.0417 | AH4: =2028+(4-0.5)/12 -> 2028.2917 | AI4: =2028+(7-0.5)/12 -> 2028.5417 | AJ4: =2028+(10-0.5)/12 -> 2028.7917 | AK4: =2028+(13-0.5)/12 -> 2029.0417 | AL4: =2028+(16-0.5)/12 -> 2029.2917 | AM4: =2028+(19-0.5)/12 -> 2029.5417 | AN4: =2028+(22-0.5)/12 -> 2029.7917 | AO4: =2028+(25-0.5)/12 -> 2030.0417 | AP4: =2028+(28-0.5)/12 -> 2030.2917 | AQ4: =2028+(31-0.5)/12 -> 2030.5417 | AR4: =2028+(34-0.5)/12 -> 2030.7917
A5: Years from base | B5: yrs | C5: =FLOOR(C4-base_year,1) -> 0 | D5: =FLOOR(D4-base_year,1) -> 0 | E5: =FLOOR(E4-base_year,1) -> 0 | F5: =FLOOR(F4-base_year,1) -> 0 | G5: =FLOOR(G4-base_year,1) -> 0 | H5: =FLOOR(H4-base_year,1) -> 0 | I5: =FLOOR(I4-base_year,1) -> 1 | J5: =FLOOR(J4-base_year,1) -> 1 | ... AR5: =FLOOR(AR4-base_year,1) -> 5
A6: Period divisor | B6: div | C6: 12 | D6: 12 | E6: 12 | F6: 12 | G6: 12 | H6: 12 | I6: 12 | J6: 12 | K6: 12 | L6: 12 | M6: 12 | N6: 12 | O6: 12 | P6: 12 | Q6: 12 | R6: 12 | S6: 12 | T6: 12 | U6: 12 | V6: 12 | W6: 12 | X6: 12 | Y6: 12 | Z6: 12 | AA6: 12 | AB6: 12 | AC6: 12 | AD6: 12 | AE6: 12 | AF6: 12 | AG6: 4 | AH6: 4 | AI6: 4 | AJ6: 4 | AK6: 4 | AL6: 4 | AM6: 4 | AN6: 4 | AO6: 4 | AP6: 4 | AQ6: 4 | AR6: 4
A7: Months in period | B7: mon | C7: 1 | D7: 1 | E7: 1 | F7: 1 | G7: 1 | H7: 1 | I7: 1 | J7: 1 | K7: 1 | L7: 1 | M7: 1 | N7: 1 | O7: 1 | P7: 1 | Q7: 1 | R7: 1 | S7: 1 | T7: 1 | U7: 1 | V7: 1 | W7: 1 | X7: 1 | Y7: 1 | Z7: 1 | AA7: 1 | AB7: 1 | AC7: 1 | AD7: 1 | AE7: 1 | AF7: 1 | AG7: 3 | AH7: 3 | AI7: 3 | AJ7: 3 | AK7: 3 | AL7: 3 | AM7: 3 | AN7: 3 | AO7: 3 | AP7: 3 | AQ7: 3 | AR7: 3
A9: Metric | B9: Unit | C9: Jul 2025 | D9: Aug 2025 | E9: Sep 2025 | F9: Oct 2025 | G9: Nov 2025 | H9: Dec 2025 | I9: Jan 2026 | J9: Feb 2026 | K9: Mar 2026 | L9: Apr 2026 | M9: May 2026 | N9: Jun 2026 | O9: Jul 2026 | P9: Aug 2026 | Q9: Sep 2026 | R9: Oct 2026 | S9: Nov 2026 | T9: Dec 2026 | U9: Jan 2027 | V9: Feb 2027 | W9: Mar 2027 | X9: Apr 2027 | Y9: May 2027 | Z9: Jun 2027 | AA9: Jul 2027 | AB9: Aug 2027 | AC9: Sep 2027 | AD9: Oct 2027 | AE9: Nov 2027 | AF9: Dec 2027 | AG9: Q1 2028 | AH9: Q2 2028 | AI9: Q3 2028 | AJ9: Q4 2028 | AK9: Q1 2029 | AL9: Q2 2029 | AM9: Q3 2029 | AN9: Q4 2029 | AO9: Q1 2030 | AP9: Q2 2030 | AQ9: Q3 2030 | AR9: Q4 2030
A10: E-commerce tourism market | B10: Bn VND | C10: =ecom_market_base*(1+ecom_growth_rate)^C5/C6 -> 6875 | D10: =ecom_market_base*(1+ecom_growth_rate)^D5/D6 -> 6875 | E10: =ecom_market_base*(1+ecom_growth_rate)^E5/E6 -> 6875 | F10: =ecom_market_base*(1+ecom_growth_rate)^F5/F6 -> 6875 | G10: =ecom_market_base*(1+ecom_growth_rate)^G5/G6 -> 6875 | H10: =ecom_market_base*(1+ecom_growth_rate)^H5/H6 -> 6875 | I10: =ecom_market_base*(1+ecom_growth_rate)^I5/I6 -> 7425 | J10: =ecom_market_base*(1+ecom_growth_rate)^J5/J6 -> 7425 | ... AR10: =ecom_market_base*(1+ecom_growth_rate)^AR5/AR6 -> 30304.892
A12: S-CURVE ADOPTION
A13: Gross enterprises | B13: cnt | C13: =MAX(pilot_count,adoption_max/(1+EXP(-adoption_steepness*(C4-adoption_midpoint)))) -> 114.41936 | D13: =MAX(pilot_count,adoption_max/(1+EXP(-adoption_steepness*(D4-adoption_midpoint)))) -> 122.42168 | E13: =MAX(pilot_count,adoption_max/(1+EXP(-adoption_steepness*(E4-adoption_midpoint)))) -> 130.91619 | F13: =MAX(pilot_count,adoption_max/(1+EXP(-adoption_steepness*(F4-adoption_midpoint)))) -> 139.92356 | G13: =MAX(pilot_count,adoption_max/(1+EXP(-adoption_steepness*(G4-adoption_midpoint)))) -> 149.46403 | H13: =MAX(pilot_count,adoption_max/(1+EXP(-adoption_steepness*(H4-adoption_midpoint)))) -> 159.55709 | I13: =MAX(pilot_count,adoption_max/(1+EXP(-adoption_steepness*(I4-adoption_midpoint)))) -> 170.22128 | J13: =MAX(pilot_count,adoption_max/(1+EXP(-adoption_steepness*(J4-adoption_midpoint)))) -> 181.4739 | ... AR13: =MAX(pilot_count,adoption_max/(1+EXP(-adoption_steepness*(AR4-adoption_midpoint)))) -> 1110.0162
A14: Churned | B14: cnt | C14: =0 -> 0 | D14: =ROUND(D13*churn_rate/D6,0) -> 2 | E14: =ROUND(E13*churn_rate/E6,0) -> 2 | F14: =ROUND(F13*churn_rate/F6,0) -> 2 | G14: =ROUND(G13*churn_rate/G6,0) -> 2 | H14: =ROUND(H13*churn_rate/H6,0) -> 3 | I14: =ROUND(I13*churn_rate/I6,0) -> 3 | J14: =ROUND(J13*churn_rate/J6,0) -> 3 | K14: =ROUND(K13*churn_rate/K6,0) -> 3 | ... AR14: =ROUND(AR13*churn_rate/AR6,0) -> 56
A15: Net active enterprises | B15: cnt | C15: =C13-C14 -> 114.41936 | D15: =D13-D14 -> 120.42168 | E15: =E13-E14 -> 128.91619 | F15: =F13-F14 -> 137.92356 | G15: =G13-G14 -> 147.46403 | H15: =H13-H14 -> 156.55709 | I15: =I13-I14 -> 167.22128 | J15: =J13-J14 -> 178.4739 | ... AR15: =AR13-AR14 -> 1054.0162
A16: New enterprises | B16: cnt | C16: =C15 -> 114.41936 | D16: =MAX(0,D15-C15) -> 6.0023251 | E16: =MAX(0,E15-D15) -> 8.4945024 | F16: =MAX(0,F15-E15) -> 9.0073776 | G16: =MAX(0,G15-F15) -> 9.5404668 | H16: =MAX(0,H15-G15) -> 9.0930584 | I16: =MAX(0,I15-H15) -> 10.66419 | J16: =MAX(0,J15-I15) -> 11.252625 | K16: =MAX(0,K15-J15) -> 11.856836 | ... AR16: =MAX(0,AR15-AQ15) -> 18.612393
A17: VCR (M records) | B17: M | C17: =C15*vcr_per_enterprise*C7/1000000 -> 1.1441936 | D17: =D15*vcr_per_enterprise*D7/1000000 -> 1.2042168 | E17: =E15*vcr_per_enterprise*E7/1000000 -> 1.2891619 | F17: =F15*vcr_per_enterprise*F7/1000000 -> 1.3792356 | G17: =G15*vcr_per_enterprise*G7/1000000 -> 1.4746403 | H17: =H15*vcr_per_enterprise*H7/1000000 -> 1.5655709 | I17: =I15*vcr_per_enterprise*I7/1000000 -> 1.6722128 | J17: =J15*vcr_per_enterprise*J7/1000000 -> 1.784739 | ... AR17: =AR15*vcr_per_enterprise*AR7/1000000 -> 31.620485

Sheet Revenue Schedule
A1: REVENUE SCHEDULE (M VND)
A3: Item | B3: Unit | C3: Jul 2025 | D3: Aug 2025 | E3: Sep 2025 | F3: Oct 2025 | G3: Nov 2025 | H3: Dec 2025 | I3: Jan 2026 | J3: Feb 2026 | K3: Mar 2026 | L3: Apr 2026 | M3: May 2026 | N3: Jun 2026 | O3: Jul 2026 | P3: Aug 2026 | Q3: Sep 2026 | R3: Oct 2026 | S3: Nov 2026 | T3: Dec 2026 | U3: Jan 2027 | V3: Feb 2027 | W3: Mar 2027 | X3: Apr 2027 | Y3: May 2027 | Z3: Jun 2027 | AA3: Jul 2027 | AB3: Aug 2027 | AC3: Sep 2027 | AD3: Oct 2027 | AE3: Nov 2027 | AF3: Dec 2027 | AG3: Q1 2028 | AH3: Q2 2028 | AI3: Q3 2028 | AJ3: Q4 2028 | AK3: Q1 2029 | AL3: Q2 2029 | AM3: Q3 2029 | AN3: Q4 2029 | AO3: Q1 2030 | AP3: Q2 2030 | AQ3: Q3 2030 | AR3: Q4 2030
A4: STAGE 1
A5: Certification fees | B5: M VND | C5: ='Market Sizing'!C15*cert_fee_yr1*(1+cert_fee_escalation)^'Market Sizing'!C5/'Market Sizing'!C6 -> 238.37366 | D5: ='Market Sizing'!D15*cert_fee_yr1*(1+cert_fee_escalation)^'Market Sizing'!D5/'Market Sizing'!D6 -> 250.87851 | E5: ='Market Sizing'!E15*cert_fee_yr1*(1+cert_fee_escalation)^'Market Sizing'!E5/'Market Sizing'!E6 -> 268.57539 | F5: ='Market Sizing'!F15*cert_fee_yr1*(1+cert_fee_escalation)^'Market Sizing'!F5/'Market Sizing'!F6 -> 287.34076 | G5: ='Market Sizing'!G15*cert_fee_yr1*(1+cert_fee_escalation)^'Market Sizing'!G5/'Market Sizing'!G6 -> 307.21673 | H5: ='Market Sizing'!H15*cert_fee_yr1*(1+cert_fee_escalation)^'Market Sizing'!H5/'Market Sizing'!H6 -> 326.1606 | I5: ='Market Sizing'!I15*cert_fee_yr1*(1+cert_fee_escalation)^'Market Sizing'!I5/'Market Sizing'!I6 -> 365.79655 | J5: ='Market Sizing'!J15*cert_fee_yr1*(1+cert_fee_escalation)^'Market Sizing'!J5/'Market Sizing'!J6 -> 390.41166 | ... AR5: ='Market Sizing'!AR15*cert_fee_yr1*(1+cert_fee_escalation)^'Market Sizing'!AR5/'Market Sizing'!AR6 -> 8407.6339
A6: Training | B6: M VND | C6: ='Market Sizing'!C15*training_pct*training_fee/'Market Sizing'!C6 -> 42.907259 | D6: ='Market Sizing'!D15*training_pct*training_fee/'Market Sizing'!D6 -> 45.158131 | E6: ='Market Sizing'!E15*training_pct*training_fee/'Market Sizing'!E6 -> 48.34357 | F6: ='Market Sizing'!F15*training_pct*training_fee/'Market Sizing'!F6 -> 51.721336 | G6: ='Market Sizing'!G15*training_pct*training_fee/'Market Sizing'!G6 -> 55.299011 | H6: ='Market Sizing'!H15*training_pct*training_fee/'Market Sizing'!H6 -> 58.708908 | I6: ='Market Sizing'!I15*training_pct*training_fee/'Market Sizing'!I6 -> 62.707979 | J6: ='Market Sizing'!J15*training_pct*training_fee/'Market Sizing'!J6 -> 66.927714 | ... AR6: ='Market Sizing'!AR15*training_pct*training_fee/'Market Sizing'!AR6 -> 1185.7682
A7: Audit fees | B7: M VND | C7: ='Market Sizing'!C15*audit_fee/'Market Sizing'!C6 -> 95.349465 | D7: ='Market Sizing'!D15*audit_fee/'Market Sizing'!D6 -> 100.3514 | E7: ='Market Sizing'!E15*audit_fee/'Market Sizing'!E6 -> 107.43015 | F7: ='Market Sizing'!F15*audit_fee/'Market Sizing'!F6 -> 114.9363 | G7: ='Market Sizing'!G15*audit_fee/'Market Sizing'!G6 -> 122.88669 | H7: ='Market Sizing'!H15*audit_fee/'Market Sizing'!H6 -> 130.46424 | I7: ='Market Sizing'!I15*audit_fee/'Market Sizing'!I6 -> 139.35106 | J7: ='Market Sizing'!J15*audit_fee/'Market Sizing'!J6 -> 148.72825 | ... AR7: ='Market Sizing'!AR15*audit_fee/'Market Sizing'!AR6 -> 2635.0405
A8: Subtotal Stage 1 | C8: =SUM(C5:C7) -> 376.63039 | D8: =SUM(D5:D7) -> 396.38804 | E8: =SUM(E5:E7) -> 424.34911 | F8: =SUM(F5:F7) -> 453.99839 | G8: =SUM(G5:G7) -> 485.40243 | H8: =SUM(H5:H7) -> 515.33375 | I8: =SUM(I5:I7) -> 567.85559 | J8: =SUM(J5:J7) -> 606.06763 | ... AR8: =SUM(AR5:AR7) -> 12228.443
A10: STAGE 2 (gated)
A11: Transaction fees | B11: M VND | C11: =IF('Market Sizing'!C15>=stage2_gate,'Market Sizing'!C10*platform_market_share*tx_take_rate*1000,0) -> 0 | D11: =IF('Market Sizing'!D15>=stage2_gate,'Market Sizing'!D10*platform_market_share*tx_take_rate*1000,0) -> 0 | E11: =IF('Market Sizing'!E15>=stage2_gate,'Market Sizing'!E10*platform_market_share*tx_take_rate*1000,0) -> 0 | F11: =IF('Market Sizing'!F15>=stage2_gate,'Market Sizing'!F10*platform_market_share*tx_take_rate*1000,0) -> 0 | G11: =IF('Market Sizing'!G15>=stage2_gate,'Market Sizing'!G10*platform_market_share*tx_take_rate*1000,0) -> 0 | H11: =IF('Market Sizing'!H15>=stage2_gate,'Market Sizing'!H10*platform_market_share*tx_take_rate*1000,0) -> 0 | I11: =IF('Market Sizing'!I15>=stage2_gate,'Market Sizing'!I10*platform_market_share*tx_take_rate*1000,0) -> 0 | J11: =IF('Market Sizing'!J15>=stage2_gate,'Market Sizing'!J10*platform_market_share*tx_take_rate*1000,0) -> 0 | ... AR11: =IF('Market Sizing'!AR15>=stage2_gate,'Market Sizing'!AR10*platform_market_share*tx_take_rate*1000,0) -> 12121.957
A12: DaaS | B12: M VND | C12: =IF('Market Sizing'!C15>=stage2_gate,'Market Sizing'!C17*daas_price,0) -> 0 | D12: =IF('Market Sizing'!D15>=stage2_gate,'Market Sizing'!D17*daas_price,0) -> 0 | E12: =IF('Market Sizing'!E15>=stage2_gate,'Market Sizing'!E17*daas_price,0) -> 0 | F12: =IF('Market Sizing'!F15>=stage2_gate,'Market Sizing'!F17*daas_price,0) -> 0 | G12: =IF('Market Sizing'!G15>=stage2_gate,'Market Sizing'!G17*daas_price,0) -> 0 | H12: =IF('Market Sizing'!H15>=stage2_gate,'Market Sizing'!H17*daas_price,0) -> 0 | I12: =IF('Market Sizing'!I15>=stage2_gate,'Market Sizing'!I17*daas_price,0) -> 0 | J12: =IF('Market Sizing'!J15>=stage2_gate,'Market Sizing'!J17*daas_price,0) -> 0 | ... AR12: =IF('Market Sizing'!AR15>=stage2_gate,'Market Sizing'!AR17*daas_price,0) -> 948.61456
A13: Advertising | B13: M VND | C13: =IF('Market Sizing'!C15>=stage2_gate,ad_impressions_base*'Market Sizing'!C7*'Market Sizing'!C15/1000*ad_cpm/1000,0) -> 0 | D13: =IF('Market Sizing'!D15>=stage2_gate,ad_impressions_base*'Market Sizing'!D7*'Market Sizing'!D15/1000*ad_cpm/1000,0) -> 0 | E13: =IF('Market Sizing'!E15>=stage2_gate,ad_impressions_base*'Market Sizing'!E7*'Market Sizing'!E15/1000*ad_cpm/1000,0) -> 0 | F13: =IF('Market Sizing'!F15>=stage2_gate,ad_impressions_base*'Market Sizing'!F7*'Market Sizing'!F15/1000*ad_cpm/1000,0) -> 0 | G13: =IF('Market Sizing'!G15>=stage2_gate,ad_impressions_base*'Market Sizing'!G7*'Market Sizing'!G15/1000*ad_cpm/1000,0) -> 0 | H13: =IF('Market Sizing'!H15>=stage2_gate,ad_impressions_base*'Market Sizing'!H7*'Market Sizing'!H15/1000*ad_cpm/1000,0) -> 0 | I13: =IF('Market Sizing'!I15>=stage2_gate,ad_impressions_base*'Market Sizing'!I7*'Market Sizing'!I15/1000*ad_cpm/1000,0) -> 0 | J13: =IF('Market Sizing'!J15>=stage2_gate,ad_impressions_base*'Market Sizing'!J7*'Market Sizing'!J15/1000*ad_cpm/1000,0) -> 0 | ... AR13: =IF('Market Sizing'!AR15>=stage2_gate,ad_impressions_base*'Market Sizing'!AR7*'Market Sizing'!AR15/1000*ad_cpm/1000,0) -> 237.15364
A14: Subtotal Stage 2 | C14: =SUM(C11:C13) -> 0 | D14: =SUM(D11:D13) -> 0 | E14: =SUM(E11:E13) -> 0 | F14: =SUM(F11:F13) -> 0 | G14: =SUM(G11:G13) -> 0 | H14: =SUM(H11:H13) -> 0 | I14: =SUM(I11:I13) -> 0 | J14: =SUM(J11:J13) -> 0 | ... AR14: =SUM(AR11:AR13) -> 13307.725
A16: TOTAL REVENUE | C16: =C8+C14 -> 376.63039 | D16: =D8+D14 -> 396.38804 | E16: =E8+E14 -> 424.34911 | F16: =F8+F14 -> 453.99839 | G16: =G8+G14 -> 485.40243 | H16: =H8+H14 -> 515.33375 | I16: =I8+I14 -> 567.85559 | J16: =J8+J14 -> 606.06763 | ... AR16: =AR8+AR14 -> 25536.167
A18: COGS
A19: Payment processing | B19: M VND | C19: =C11*payment_proc_pct -> 0 | D19: =D11*payment_proc_pct -> 0 | E19: =E11*payment_proc_pct -> 0 | F19: =F11*payment_proc_pct -> 0 | G19: =G11*payment_proc_pct -> 0 | H19: =H11*payment_proc_pct -> 0 | I19: =I11*payment_proc_pct -> 0 | J19: =J11*payment_proc_pct -> 0 | ... AR19: =AR11*payment_proc_pct -> 303.04892
A20: TOTAL COGS | C20: =C19 -> 0 | D20: =D19 -> 0 | E20: =E19 -> 0 | F20: =F19 -> 0 | G20: =G19 -> 0 | H20: =H19 -> 0 | I20: =I19 -> 0 | J20: =J19 -> 0 | ... AR20: =AR19 -> 303.04892

Sheet Cost Schedule
A1: COST SCHEDULE (M VND)
A3: Item | B3: Unit | C3: Jul 2025 | D3: Aug 2025 | E3: Sep 2025 | F3: Oct 2025 | G3: Nov 2025 | H3: Dec 2025 | I3: Jan 2026 | J3: Feb 2026 | K3: Mar 2026 | L3: Apr 2026 | M3: May 2026 | N3: Jun 2026 | O3: Jul 2026 | P3: Aug 2026 | Q3: Sep 2026 | R3: Oct 2026 | S3: Nov 2026 | T3: Dec 2026 | U3: Jan 2027 | V3: Feb 2027 | W3: Mar 2027 | X3: Apr 2027 | Y3: May 2027 | Z3: Jun 2027 | AA3: Jul 2027 | AB3: Aug 2027 | AC3: Sep 2027 | AD3: Oct 2027 | AE3: Nov 2027 | AF3: Dec 2027 | AG3: Q1 2028 | AH3: Q2 2028 | AI3: Q3 2028 | AJ3: Q4 2028 | AK3: Q1 2029 | AL3: Q2 2029 | AM3: Q3 2029 | AN3: Q4 2029 | AO3: Q1 2030 | AP3: Q2 2030 | AQ3: Q3 2030 | AR3: Q4 2030
A4: CAPEX
A5: Platform dev | B5: M VND | C5: =capex_total/6 -> 880 | D5: =capex_total/6 -> 880 | E5: =capex_total/6 -> 880 | F5: =capex_total/6 -> 880 | G5: =capex_total/6 -> 880 | H5: =capex_total/6 -> 880 | I5: =0 -> 0 | J5: =0 -> 0 | K5: =0 -> 0 | L5: =0 -> 0 | M5: =0 -> 0 | N5: =0 -> 0 | O5: =0 -> 0 | P5: =0 -> 0 | ... AR5: =0 -> 0
A6: Maintenance | B6: M VND | C6: =0 -> 0 | D6: =0 -> 0 | E6: =0 -> 0 | F6: =0 -> 0 | G6: =0 -> 0 | H6: =0 -> 0 | I6: =capex_total*capex_maintenance_pct/'Market Sizing'!I6 -> 79.2 | J6: =capex_total*capex_maintenance_pct/'Market Sizing'!J6 -> 79.2 | K6: =capex_total*capex_maintenance_pct/'Market Sizing'!K6 -> 79.2 | L6: =capex_total*capex_maintenance_pct/'Market Sizing'!L6 -> 79.2 | M6: =capex_total*capex_maintenance_pct/'Market Sizing'!M6 -> 79.2 | N6: =capex_total*capex_maintenance_pct/'Market Sizing'!N6 -> 79.2 | O6: =capex_total*capex_maintenance_pct/'Market Sizing'!O6 -> 79.2 | P6: =capex_total*capex_maintenance_pct/'Market Sizing'!P6 -> 79.2 | ... AR6: =capex_total*capex_maintenance_pct/'Market Sizing'!AR6 -> 237.6
A7: TOTAL CAPEX | C7: =C5+C6 -> 880 | D7: =D5+D6 -> 880 | E7: =E5+E6 -> 880 | F7: =F5+F6 -> 880 | G7: =G5+G6 -> 880 | H7: =H5+H6 -> 880 | I7: =I5+I6 -> 79.2 | J7: =J5+J6 -> 79.2 | ... AR7: =AR5+AR6 -> 237.6
A9: OPEX
A10: HR (from HR Plan) | B10: M VND | C10: ='HR Plan'!C21 -> 1820.25 | D10: ='HR Plan'!D21 -> 668.25 | E10: ='HR Plan'!E21 -> 668.25 | F10: ='HR Plan'!F21 -> 668.25 | G10: ='HR Plan'!G21 -> 668.25 | H10: ='HR Plan'!H21 -> 668.25 | I10: ='HR Plan'!I21 -> 1380.915 | J10: ='HR Plan'!J21 -> 948.915 | ... AR10: ='HR Plan'!AR21 -> 10683.962
A11: Marketing | B11: M VND | C11: =opex_marketing*(1+marketing_growth)^'Market Sizing'!C5/'Market Sizing'!C6*MAX(0.5,1-'Market Sizing'!C15*mkt_efficiency_per_100/100) -> 569.98441 | D11: =opex_marketing*(1+marketing_growth)^'Market Sizing'!D5/'Market Sizing'!D6*MAX(0.5,1-'Market Sizing'!D15*mkt_efficiency_per_100/100) -> 569.28414 | E11: =opex_marketing*(1+marketing_growth)^'Market Sizing'!E5/'Market Sizing'!E6*MAX(0.5,1-'Market Sizing'!E15*mkt_efficiency_per_100/100) -> 568.29311 | F11: =opex_marketing*(1+marketing_growth)^'Market Sizing'!F5/'Market Sizing'!F6*MAX(0.5,1-'Market Sizing'!F15*mkt_efficiency_per_100/100) -> 567.24225 | G11: =opex_marketing*(1+marketing_growth)^'Market Sizing'!G5/'Market Sizing'!G6*MAX(0.5,1-'Market Sizing'!G15*mkt_efficiency_per_100/100) -> 566.1292 | H11: =opex_marketing*(1+marketing_growth)^'Market Sizing'!H5/'Market Sizing'!H6*MAX(0.5,1-'Market Sizing'!H15*mkt_efficiency_per_100/100) -> 565.06834 | I11: =opex_marketing*(1+marketing_growth)^'Market Sizing'!I5/'Market Sizing'!I6*MAX(0.5,1-'Market Sizing'!I15*mkt_efficiency_per_100/100) -> 648.39781 | J11: =opex_marketing*(1+marketing_growth)^'Market Sizing'!J5/'Market Sizing'!J6*MAX(0.5,1-'Market Sizing'!J15*mkt_efficiency_per_100/100) -> 646.88808 | ... AR11: =opex_marketing*(1+marketing_growth)^'Market Sizing'!AR5/'Market Sizing'!AR6*MAX(0.5,1-'Market Sizing'!AR15*mkt_efficiency_per_100/100) -> 2777.874
A12: Branding & events | B12: M VND | C12: =opex_branding/'Market Sizing'!C6 -> 333.33333 | D12: =opex_branding/'Market Sizing'!D6 -> 333.33333 | E12: =opex_branding/'Market Sizing'!E6 -> 333.33333 | F12: =opex_branding/'Market Sizing'!F6 -> 333.33333 | G12: =opex_branding/'Market Sizing'!G6 -> 333.33333 | H12: =opex_branding/'Market Sizing'!H6 -> 333.33333 | I12: =opex_branding/'Market Sizing'!I6 -> 333.33333 | J12: =opex_branding/'Market Sizing'!J6 -> 333.33333 | ... AR12: =opex_branding/'Market Sizing'!AR6 -> 1000
A13: Cloud & infra | B13: M VND | C13: =opex_cloud_base/'Market Sizing'!C6+'Market Sizing'!C17*cloud_per_1M_vcr*('Market Sizing'!C15/100)^(cloud_elasticity-1)+'Market Sizing'!C10*platform_market_share*cloud_gmv_factor -> 348.98683 | D13: =opex_cloud_base/'Market Sizing'!D6+'Market Sizing'!D17*cloud_per_1M_vcr*('Market Sizing'!D15/100)^(cloud_elasticity-1)+'Market Sizing'!D10*platform_market_share*cloud_gmv_factor -> 349.58185 | E13: =opex_cloud_base/'Market Sizing'!E6+'Market Sizing'!E17*cloud_per_1M_vcr*('Market Sizing'!E15/100)^(cloud_elasticity-1)+'Market Sizing'!E10*platform_market_share*cloud_gmv_factor -> 350.43406 | F13: =opex_cloud_base/'Market Sizing'!F6+'Market Sizing'!F17*cloud_per_1M_vcr*('Market Sizing'!F15/100)^(cloud_elasticity-1)+'Market Sizing'!F10*platform_market_share*cloud_gmv_factor -> 351.35007 | G13: =opex_cloud_base/'Market Sizing'!G6+'Market Sizing'!G17*cloud_per_1M_vcr*('Market Sizing'!G15/100)^(cloud_elasticity-1)+'Market Sizing'!G10*platform_market_share*cloud_gmv_factor -> 352.33342 | H13: =opex_cloud_base/'Market Sizing'!H6+'Market Sizing'!H17*cloud_per_1M_vcr*('Market Sizing'!H15/100)^(cloud_elasticity-1)+'Market Sizing'!H10*platform_market_share*cloud_gmv_factor -> 353.2826 | I13: =opex_cloud_base/'Market Sizing'!I6+'Market Sizing'!I17*cloud_per_1M_vcr*('Market Sizing'!I15/100)^(cloud_elasticity-1)+'Market Sizing'!I10*platform_market_share*cloud_gmv_factor -> 359.90987 | J13: =opex_cloud_base/'Market Sizing'!J6+'Market Sizing'!J17*cloud_per_1M_vcr*('Market Sizing'!J15/100)^(cloud_elasticity-1)+'Market Sizing'!J10*platform_market_share*cloud_gmv_factor -> 361.11504 | ... AR13: =opex_cloud_base/'Market Sizing'!AR6+'Market Sizing'!AR17*cloud_per_1M_vcr*('Market Sizing'!AR15/100)^(cloud_elasticity-1)+'Market Sizing'!AR10*platform_market_share*cloud_gmv_factor -> 1520.7102
A14: Security | B14: M VND | C14: =opex_security/'Market Sizing'!C6 -> 20.833333 | D14: =opex_security/'Market Sizing'!D6 -> 20.833333 | E14: =opex_security/'Market Sizing'!E6 -> 20.833333 | F14: =opex_security/'Market Sizing'!F6 -> 20.833333 | G14: =opex_security/'Market Sizing'!G6 -> 20.833333 | H14: =opex_security/'Market Sizing'!H6 -> 20.833333 | I14: =opex_security/'Market Sizing'!I6 -> 20.833333 | J14: =opex_security/'Market Sizing'!J6 -> 20.833333 | ... AR14: =opex_security/'Market Sizing'!AR6 -> 62.5
A15: External affairs | B15: M VND | C15: =opex_external/'Market Sizing'!C6 -> 33.333333 | D15: =opex_external/'Market Sizing'!D6 -> 33.333333 | E15: =opex_external/'Market Sizing'!E6 -> 33.333333 | F15: =opex_external/'Market Sizing'!F6 -> 33.333333 | G15: =opex_external/'Market Sizing'!G6 -> 33.333333 | H15: =opex_external/'Market Sizing'!H6 -> 33.333333 | I15: =opex_external/'Market Sizing'!I6 -> 33.333333 | J15: =opex_external/'Market Sizing'!J6 -> 33.333333 | ... AR15: =opex_external/'Market Sizing'!AR6 -> 100
A16: Legal & compliance | B16: M VND | C16: =opex_legal/'Market Sizing'!C6 -> 20 | D16: =opex_legal/'Market Sizing'!D6 -> 20 | E16: =opex_legal/'Market Sizing'!E6 -> 20 | F16: =opex_legal/'Market Sizing'!F6 -> 20 | G16: =opex_legal/'Market Sizing'!G6 -> 20 | H16: =opex_legal/'Market Sizing'!H6 -> 20 | I16: =opex_legal/'Market Sizing'!I6 -> 20 | J16: =opex_legal/'Market Sizing'!J6 -> 20 | ... AR16: =opex_legal/'Market Sizing'!AR6 -> 60
A17: Pilot eval (Y1) | B17: M VND | C17: =opex_pilot_eval/'Market Sizing'!C6 -> 16.666667 | D17: =opex_pilot_eval/'Market Sizing'!D6 -> 16.666667 | E17: =opex_pilot_eval/'Market Sizing'!E6 -> 16.666667 | F17: =opex_pilot_eval/'Market Sizing'!F6 -> 16.666667 | G17: =opex_pilot_eval/'Market Sizing'!G6 -> 16.666667 | H17: =opex_pilot_eval/'Market Sizing'!H6 -> 16.666667 | I17: =0 -> 0 | J17: =0 -> 0 | K17: =0 -> 0 | L17: =0 -> 0 | M17: =0 -> 0 | N17: =0 -> 0 | O17: =0 -> 0 | P17: =0 -> 0 | ... AR17: =0 -> 0
A18: Partner mgmt | B18: M VND | C18: =opex_partner_mgmt/'Market Sizing'!C6 -> 41.666667 | D18: =opex_partner_mgmt/'Market Sizing'!D6 -> 41.666667 | E18: =opex_partner_mgmt/'Market Sizing'!E6 -> 41.666667 | F18: =opex_partner_mgmt/'Market Sizing'!F6 -> 41.666667 | G18: =opex_partner_mgmt/'Market Sizing'!G6 -> 41.666667 | H18: =opex_partner_mgmt/'Market Sizing'!H6 -> 41.666667 | I18: =opex_partner_mgmt/'Market Sizing'!I6 -> 41.666667 | J18: =opex_partner_mgmt/'Market Sizing'!J6 -> 41.666667 | ... AR18: =opex_partner_mgmt/'Market Sizing'!AR6 -> 125
A19: Customer support | B19: M VND | C19: ='Market Sizing'!C15*opex_support_per_ent*IF('Market Sizing'!C15>support_scale_threshold,1-support_discount,1)/'Market Sizing'!C6 -> 19.069893 | D19: ='Market Sizing'!D15*opex_support_per_ent*IF('Market Sizing'!D15>support_scale_threshold,1-support_discount,1)/'Market Sizing'!D6 -> 20.070281 | E19: ='Market Sizing'!E15*opex_support_per_ent*IF('Market Sizing'!E15>support_scale_threshold,1-support_discount,1)/'Market Sizing'!E6 -> 21.486031 | F19: ='Market Sizing'!F15*opex_support_per_ent*IF('Market Sizing'!F15>support_scale_threshold,1-support_discount,1)/'Market Sizing'!F6 -> 22.98726 | G19: ='Market Sizing'!G15*opex_support_per_ent*IF('Market Sizing'!G15>support_scale_threshold,1-support_discount,1)/'Market Sizing'!G6 -> 24.577338 | H19: ='Market Sizing'!H15*opex_support_per_ent*IF('Market Sizing'!H15>support_scale_threshold,1-support_discount,1)/'Market Sizing'!H6 -> 26.092848 | I19: ='Market Sizing'!I15*opex_support_per_ent*IF('Market Sizing'!I15>support_scale_threshold,1-support_discount,1)/'Market Sizing'!I6 -> 27.870213 | J19: ='Market Sizing'!J15*opex_support_per_ent*IF('Market Sizing'!J15>support_scale_threshold,1-support_discount,1)/'Market Sizing'!J6 -> 29.745651 | ... AR19: ='Market Sizing'!AR15*opex_support_per_ent*IF('Market Sizing'!AR15>support_scale_threshold,1-support_discount,1)/'Market Sizing'!AR6 -> 368.90566
A20: OPEX Subtotal | C20: =SUM(C10:C19) -> 3224.1245 | D20: =SUM(D10:D19) -> 2073.0196 | E20: =SUM(E10:E19) -> 2074.2965 | F20: =SUM(F10:F19) -> 2075.6629 | G20: =SUM(G10:G19) -> 2077.1233 | H20: =SUM(H10:H19) -> 2078.5271 | I20: =SUM(I10:I19) -> 2866.2596 | J20: =SUM(J10:J19) -> 2435.8304 | ... AR20: =SUM(AR10:AR19) -> 16698.952
A21: Contingency | B21: M VND | C21: =C20*opex_contingency_pct -> 322.41245 | D21: =D20*opex_contingency_pct -> 207.30196 | E21: =E20*opex_contingency_pct -> 207.42965 | F21: =F20*opex_contingency_pct -> 207.56629 | G21: =G20*opex_contingency_pct -> 207.71233 | H21: =H20*opex_contingency_pct -> 207.85271 | I21: =I20*opex_contingency_pct -> 286.62596 | J21: =J20*opex_contingency_pct -> 243.58304 | ... AR21: =AR20*opex_contingency_pct -> 1669.8952
A22: TOTAL OPEX | C22: =C20+C21 -> 3546.5369 | D22: =D20+D21 -> 2280.3216 | E22: =E20+E21 -> 2281.7262 | F22: =F20+F21 -> 2283.2292 | G22: =G20+G21 -> 2284.8356 | H22: =H20+H21 -> 2286.3798 | I22: =I20+I21 -> 3152.8855 | J22: =J20+J21 -> 2679.4135 | ... AR22: =AR20+AR21 -> 18368.847
A24: TOTAL COSTS | C24: =C7+C22 -> 4426.5369 | D24: =D7+D22 -> 3160.3216 | E24: =E7+E22 -> 3161.7262 | F24: =F7+F22 -> 3163.2292 | G24: =G7+G22 -> 3164.8356 | H24: =H7+H22 -> 3166.3798 | I24: =I7+I22 -> 3232.0855 | J24: =J7+J22 -> 2758.6135 | ... AR24: =AR7+AR22 -> 18606.447

Sheet P&L
A1: P&L (M VND)
A3: Item | B3: Unit | C3: Jul 2025 | D3: Aug 2025 | E3: Sep 2025 | F3: Oct 2025 | G3: Nov 2025 | H3: Dec 2025 | I3: Jan 2026 | J3: Feb 2026 | K3: Mar 2026 | L3: Apr 2026 | M3: May 2026 | N3: Jun 2026 | O3: Jul 2026 | P3: Aug 2026 | Q3: Sep 2026 | R3: Oct 2026 | S3: Nov 2026 | T3: Dec 2026 | U3: Jan 2027 | V3: Feb 2027 | W3: Mar 2027 | X3: Apr 2027 | Y3: May 2027 | Z3: Jun 2027 | AA3: Jul 2027 | AB3: Aug 2027 | AC3: Sep 2027 | AD3: Oct 2027 | AE3: Nov 2027 | AF3: Dec 2027 | AG3: Q1 2028 | AH3: Q2 2028 | AI3: Q3 2028 | AJ3: Q4 2028 | AK3: Q1 2029 | AL3: Q2 2029 | AM3: Q3 2029 | AN3: Q4 2029 | AO3: Q1 2030 | AP3: Q2 2030 | AQ3: Q3 2030 | AR3: Q4 2030
A4: Revenue | C4: ='Revenue Schedule'!C16 -> 376.63039 | D4: ='Revenue Schedule'!D16 -> 396.38804 | E4: ='Revenue Schedule'!E16 -> 424.34911 | F4: ='Revenue Schedule'!F16 -> 453.99839 | G4: ='Revenue Schedule'!G16 -> 485.40243 | H4: ='Revenue Schedule'!H16 -> 515.33375 | I4: ='Revenue Schedule'!I16 -> 567.85559 | J4: ='Revenue Schedule'!J16 -> 606.06763 | ... AR4: ='Revenue Schedule'!AR16 -> 25536.167
A5: COGS | C5: =-'Revenue Schedule'!C20 -> 0 | D5: =-'Revenue Schedule'!D20 -> 0 | E5: =-'Revenue Schedule'!E20 -> 0 | F5: =-'Revenue Schedule'!F20 -> 0 | G5: =-'Revenue Schedule'!G20 -> 0 | H5: =-'Revenue Schedule'!H20 -> 0 | I5: =-'Revenue Schedule'!I20 -> 0 | J5: =-'Revenue Schedule'!J20 -> 0 | ... AR5: =-'Revenue Schedule'!AR20 -> -303.04892
A6: GROSS PROFIT | C6: =C4+C5 -> 376.63039 | D6: =D4+D5 -> 396.38804 | E6: =E4+E5 -> 424.34911 | F6: =F4+F5 -> 453.99839 | G6: =G4+G5 -> 485.40243 | H6: =H4+H5 -> 515.33375 | I6: =I4+I5 -> 567.85559 | J6: =J4+J5 -> 606.06763 | ... AR6: =AR4+AR5 -> 25233.118
A8: OPEX | C8: =-'Cost Schedule'!C22 -> -3546.5369 | D8: =-'Cost Schedule'!D22 -> -2280.3216 | E8: =-'Cost Schedule'!E22 -> -2281.7262 | F8: =-'Cost Schedule'!F22 -> -2283.2292 | G8: =-'Cost Schedule'!G22 -> -2284.8356 | H8: =-'Cost Schedule'!H22 -> -2286.3798 | I8: =-'Cost Schedule'!I22 -> -3152.8855 | J8: =-'Cost Schedule'!J22 -> -2679.4135 | ... AR8: =-'Cost Schedule'!AR22 -> -18368.847
A9: EBITDA | C9: =C6+C8 -> -3169.9065 | D9: =D6+D8 -> -1883.9335 | E9: =E6+E8 -> -1857.3771 | F9: =F6+F8 -> -1829.2308 | G9: =G6+G8 -> -1799.4332 | H9: =H6+H8 -> -1771.0461 | I9: =I6+I8 -> -2585.0299 | J9: =J6+J8 -> -2073.3459 | ... AR9: =AR6+AR8 -> 6864.271
A10: Depreciation | C10: =-capex_total/depreciation_years/'Market Sizing'!C6 -> -88 | D10: =-capex_total/depreciation_years/'Market Sizing'!D6 -> -88 | E10: =-capex_total/depreciation_years/'Market Sizing'!E6 -> -88 | F10: =-capex_total/depreciation_years/'Market Sizing'!F6 -> -88 | G10: =-capex_total/depreciation_years/'Market Sizing'!G6 -> -88 | H10: =-capex_total/depreciation_years/'Market Sizing'!H6 -> -88 | I10: =-capex_total/depreciation_years/'Market Sizing'!I6 -> -88 | J10: =-capex_total/depreciation_years/'Market Sizing'!J6 -> -88 | ... AN10: =-capex_total/depreciation_years/'Market Sizing'!AN6 -> -264 | AO10: =0 -> 0 | AP10: =0 -> 0 | AQ10: =0 -> 0 | AR10: =0 -> 0
A11: EBIT | C11: =C9+C10 -> -3257.9065 | D11: =D9+D10 -> -1971.9335 | E11: =E9+E10 -> -1945.3771 | F11: =F9+F10 -> -1917.2308 | G11: =G9+G10 -> -1887.4332 | H11: =H9+H10 -> -1859.0461 | I11: =I9+I10 -> -2673.0299 | J11: =J9+J10 -> -2161.3459 | ... AR11: =AR9+AR10 -> 6864.271
A12: Tax (CIT) | C12: =IF(C11>0,-C11*cit_rate,0) -> 0 | D12: =IF(D11>0,-D11*cit_rate,0) -> 0 | E12: =IF(E11>0,-E11*cit_rate,0) -> 0 | F12: =IF(F11>0,-F11*cit_rate,0) -> 0 | G12: =IF(G11>0,-G11*cit_rate,0) -> 0 | H12: =IF(H11>0,-H11*cit_rate,0) -> 0 | I12: =IF(I11>0,-I11*cit_rate,0) -> 0 | J12: =IF(J11>0,-J11*cit_rate,0) -> 0 | ... AR12: =IF(AR11>0,-AR11*cit_rate,0) -> -1372.8542
A13: NET INCOME | C13: =C11+C12 -> -3257.9065 | D13: =D11+D12 -> -1971.9335 | E13: =E11+E12 -> -1945.3771 | F13: =F11+F12 -> -1917.2308 | G13: =G11+G12 -> -1887.4332 | H13: =H11+H12 -> -1859.0461 | I13: =I11+I12 -> -2673.0299 | J13: =J11+J12 -> -2161.3459 | ... AR13: =AR11+AR12 -> 5491.4168
A15: MARGINS
A16: Gross margin | C16: =IF(C4=0,0,C6/C4) -> 1 | D16: =IF(D4=0,0,D6/D4) -> 1 | E16: =IF(E4=0,0,E6/E4) -> 1 | F16: =IF(F4=0,0,F6/F4) -> 1 | G16: =IF(G4=0,0,G6/G4) -> 1 | H16: =IF(H4=0,0,H6/H4) -> 1 | I16: =IF(I4=0,0,I6/I4) -> 1 | J16: =IF(J4=0,0,J6/J4) -> 1 | ... AR16: =IF(AR4=0,0,AR6/AR4) -> 0.98813256
A17: EBITDA margin | C17: =IF(C4=0,0,C9/C4) -> -8.4164917 | D17: =IF(D4=0,0,D9/D4) -> -4.7527507 | E17: =IF(E4=0,0,E9/E4) -> -4.3770024 | F17: =IF(F4=0,0,F9/F4) -> -4.029157 | G17: =IF(G4=0,0,G9/G4) -> -3.7070955 | H17: =IF(H4=0,0,H9/H4) -> -3.4366973 | I17: =IF(I4=0,0,I9/I4) -> -4.5522664 | J17: =IF(J4=0,0,J9/J4) -> -3.420981 | ... AR17: =IF(AR4=0,0,AR9/AR4) -> 0.26880584
A18: Net margin | C18: =IF(C4=0,0,C13/C4) -> -8.6501425 | D18: =IF(D4=0,0,D13/D4) -> -4.9747553 | E18: =IF(E4=0,0,E13/E4) -> -4.5843788 | F18: =IF(F4=0,0,F13/F4) -> -4.2229903 | G18: =IF(G4=0,0,G13/G4) -> -3.8883884 | H18: =IF(H4=0,0,H13/H4) -> -3.6074604 | I18: =IF(I4=0,0,I13/I4) -> -4.7072354 | J18: =IF(J4=0,0,J13/J4) -> -3.5661793 | ... AR18: =IF(AR4=0,0,AR13/AR4) -> 0.21504467

Sheet Cash Flow
A1: CASH FLOW (M VND)
A3: Item | B3: Unit | C3: Jul 2025 | D3: Aug 2025 | E3: Sep 2025 | F3: Oct 2025 | G3: Nov 2025 | H3: Dec 2025 | I3: Jan 2026 | J3: Feb 2026 | K3: Mar 2026 | L3: Apr 2026 | M3: May 2026 | N3: Jun 2026 | O3: Jul 2026 | P3: Aug 2026 | Q3: Sep 2026 | R3: Oct 2026 | S3: Nov 2026 | T3: Dec 2026 | U3: Jan 2027 | V3: Feb 2027 | W3: Mar 2027 | X3: Apr 2027 | Y3: May 2027 | Z3: Jun 2027 | AA3: Jul 2027 | AB3: Aug 2027 | AC3: Sep 2027 | AD3: Oct 2027 | AE3: Nov 2027 | AF3: Dec 2027 | AG3: Q1 2028 | AH3: Q2 2028 | AI3: Q3 2028 | AJ3: Q4 2028 | AK3: Q1 2029 | AL3: Q2 2029 | AM3: Q3 2029 | AN3: Q4 2029 | AO3: Q1 2030 | AP3: Q2 2030 | AQ3: Q3 2030 | AR3: Q4 2030
A4: Operating CF
A5: Net income | C5: ='P&L'!C13 -> -3257.9065 | D5: ='P&L'!D13 -> -1971.9335 | E5: ='P&L'!E13 -> -1945.3771 | F5: ='P&L'!F13 -> -1917.2308 | G5: ='P&L'!G13 -> -1887.4332 | H5: ='P&L'!H13 -> -1859.0461 | I5: ='P&L'!I13 -> -2673.0299 | J5: ='P&L'!J13 -> -2161.3459 | ... AR5: ='P&L'!AR13 -> 5491.4168
A6: Add: D&A | C6: =-'P&L'!C10 -> 88 | D6: =-'P&L'!D10 -> 88 | E6: =-'P&L'!E10 -> 88 | F6: =-'P&L'!F10 -> 88 | G6: =-'P&L'!G10 -> 88 | H6: =-'P&L'!H10 -> 88 | I6: =-'P&L'!I10 -> 88 | J6: =-'P&L'!J10 -> 88 | ... AR6: =-'P&L'!AR10 -> 0
A7: Working capital chg | C7: =-'P&L'!C4*ar_days/365 -> -46.433883 | D7: =-('P&L'!D4-'P&L'!C4)*ar_days/365 -> -2.4358751 | E7: =-('P&L'!E4-'P&L'!D4)*ar_days/365 -> -3.4472553 | F7: =-('P&L'!F4-'P&L'!E4)*ar_days/365 -> -3.6553912 | G7: =-('P&L'!G4-'P&L'!F4)*ar_days/365 -> -3.8717305 | H7: =-('P&L'!H4-'P&L'!G4)*ar_days/365 -> -3.6901624 | I7: =-('P&L'!I4-'P&L'!H4)*ar_days/365 -> -6.4752954 | J7: =-('P&L'!J4-'P&L'!I4)*ar_days/365 -> -4.7110734 | K7: =-('P&L'!K4-'P&L'!J4)*ar_days/365 -> -4.9640351 | ... AR7: =-('P&L'!AR4-'P&L'!AQ4)*ar_days/365 -> -29.203823
A8: OPERATING CF | C8: =C5+C6+C7 -> -3216.3404 | D8: =D5+D6+D7 -> -1886.3694 | E8: =E5+E6+E7 -> -1860.8243 | F8: =F5+F6+F7 -> -1832.8862 | G8: =G5+G6+G7 -> -1803.3049 | H8: =H5+H6+H7 -> -1774.7362 | I8: =I5+I6+I7 -> -2591.5052 | J8: =J5+J6+J7 -> -2078.0569 | ... AR8: =AR5+AR6+AR7 -> 5462.213
A10: Investing CF
A11: CAPEX | C11: =-'Cost Schedule'!C7 -> -880 | D11: =-'Cost Schedule'!D7 -> -880 | E11: =-'Cost Schedule'!E7 -> -880 | F11: =-'Cost Schedule'!F7 -> -880 | G11: =-'Cost Schedule'!G7 -> -880 | H11: =-'Cost Schedule'!H7 -> -880 | I11: =-'Cost Schedule'!I7 -> -79.2 | J11: =-'Cost Schedule'!J7 -> -79.2 | ... AR11: =-'Cost Schedule'!AR7 -> -237.6
A12: INVESTING CF | C12: =C11 -> -880 | D12: =D11 -> -880 | E12: =E11 -> -880 | F12: =F11 -> -880 | G12: =G11 -> -880 | H12: =H11 -> -880 | I12: =I11 -> -79.2 | J12: =J11 -> -79.2 | ... AR12: =AR11 -> -237.6
A14: FREE CASH FLOW | C14: =C8+C12 -> -4096.3404 | D14: =D8+D12 -> -2766.3694 | E14: =E8+E12 -> -2740.8243 | F14: =F8+F12 -> -2712.8862 | G14: =G8+G12 -> -2683.3049 | H14: =H8+H12 -> -2654.7362 | I14: =I8+I12 -> -2670.7052 | J14: =J8+J12 -> -2157.2569 | ... AR14: =AR8+AR12 -> 5224.613
A15: Cumulative CF | C15: =C14 -> -4096.3404 | D15: =C15+D14 -> -6862.7098 | E15: =D15+E14 -> -9603.5341 | F15: =E15+F14 -> -12316.42 | G15: =F15+G14 -> -14999.725 | H15: =G15+H14 -> -17654.462 | I15: =H15+I14 -> -20325.167 | J15: =I15+J14 -> -22482.424 | K15: =J15+K14 -> -24601.509 | ... AR15: =AQ15+AR14 -> 30785.857

Sheet DCF & Returns
A1: DCF & RETURNS
A3: Annual FCF
A4: Year | B4: FCF (M VND)
A5: H2_2025 | B5: =SUM('Cash Flow'!C14:H14) -> -17654.462
A6: Y2026 | B6: =SUM('Cash Flow'!I14:T14) -> -18875.413
A7: Y2027 | B7: =SUM('Cash Flow'!U14:AF14) -> 13682.584
A8: Y2028 | B8: =SUM('Cash Flow'!AG14:AJ14) -> 16056.843
A9: Y2029 | B9: =SUM('Cash Flow'!AK14:AN14) -> 18842.165
A10: Y2030 | B10: =SUM('Cash Flow'!AO14:AR14) -> 18734.14
A12: Metrics
A13: NPV | B13: =NPV(discount_rate,B6:B10)+B5 -> 6923.0172
A14: IRR | B14: =IFERROR(IRR(B5:B10),"N/A") -> 0.22434518
A15: Max cash burn | B15: =-MIN('Cash Flow'!C15:'Cash Flow'!AR15) -> 38221.553
A16: ROI | B16: =IF(B15=0,0,('Cash Flow'!AR15+B15)/B15) -> 1.805458
A17: CIT rate | B17: =cit_rate -> 0.2
A18: WACC | B18: =discount_rate -> 0.15

Sheet Sensitivity
A1: SENSITIVITY ANALYSIS
A2: v5.0 | Shows how each parameter change affects NPV, IRR, and key outputs
A4: ONE-AT-A-TIME SENSITIVITY (vs BASE CASE)
A5: Parameter | B5: Named Range | C5: -30% | D5: -15% | E5: BASE | F5: +15% | G5: +30% | H5: Impact Direction
A6: Max enterprises | B6: adoption_max | C6: =adoption_max*0.7 -> 840 | D6: =adoption_max*0.85 -> 1020 | E6: =adoption_max*1 -> 1200 | F6: =adoption_max*1.15 -> 1380 | G6: =adoption_max*1.3 -> 1560 | H6: ↑ adoption → ↑ all revenue, ↑ HR/support costs, trigger Stage 2 earlier
A7: Platform market share | B7: platform_market_share | C7: =platform_market_share*0.7 -> 0.014 | D7: =platform_market_share*0.85 -> 0.017 | E7: =platform_market_share*1 -> 0.02 | F7: =platform_market_share*1.15 -> 0.023 | G7: =platform_market_share*1.3 -> 0.026 | H7: ↑ share → ↑ tx/DaaS/ads revenue, ↑ cloud costs, ↑ COGS
A8: Churn rate | B8: churn_rate | C8: =churn_rate*0.7 -> 0.14 | D8: =churn_rate*0.85 -> 0.17 | E8: =churn_rate*1 -> 0.2 | F8: =churn_rate*1.15 -> 0.23 | G8: =churn_rate*1.3 -> 0.26 | H8: ↑ churn → ↓ net ent → ↓ all revenue. Inverse impact.
A9: Cert fee (Tr/yr) | B9: cert_fee_yr1 | C9: =cert_fee_yr1*0.7 -> 17.5 | D9: =cert_fee_yr1*0.85 -> 21.25 | E9: =cert_fee_yr1*1 -> 25 | F9: =cert_fee_yr1*1.15 -> 28.75 | G9: =cert_fee_yr1*1.3 -> 32.5 | H9: ↑ fee → ↑ cert revenue directly. But may ↑ churn.
A10: Cert escalation | B10: cert_fee_escalation | C10: =cert_fee_escalation*0.7 -> 0.035 | D10: =cert_fee_escalation*0.85 -> 0.0425 | E10: =cert_fee_escalation*1 -> 0.05 | F10: =cert_fee_escalation*1.15 -> 0.0575 | G10: =cert_fee_escalation*1.3 -> 0.065 | H10: ↑ escalation → ↑ revenue in later years (compound).
A11: WACC (discount rate) | B11: discount_rate | C11: =discount_rate*0.7 -> 0.105 | D11: =discount_rate*0.85 -> 0.1275 | E11: =discount_rate*1 -> 0.15 | F11: =discount_rate*1.15 -> 0.1725 | G11: =discount_rate*1.3 -> 0.195 | H11: ↑ WACC → ↓ NPV (future CFs worth less). No effect on operations.
A12: Marketing base | B12: opex_marketing | C12: =opex_marketing*0.7 -> 4900 | D12: =opex_marketing*0.85 -> 5950 | E12: =opex_marketing*1 -> 7000 | F12: =opex_marketing*1.15 -> 8050 | G12: =opex_marketing*1.3 -> 9100 | H12: ↑ marketing → ↓ profit. But needed to drive adoption.
A13: S-curve steepness | B13: adoption_steepness | C13: =adoption_steepness*0.7 -> 0.63 | D13: =adoption_steepness*0.85 -> 0.765 | E13: =adoption_steepness*1 -> 0.9 | F13: =adoption_steepness*1.15 -> 1.035 | G13: =adoption_steepness*1.3 -> 1.17 | H13: ↑ steepness → faster adoption around midpoint.
A14: Stage 2 gate | B14: stage2_gate | C14: =stage2_gate*0.7 -> 210 | D14: =stage2_gate*0.85 -> 255 | E14: =stage2_gate*1 -> 300 | F14: =stage2_gate*1.15 -> 345 | G14: =stage2_gate*1.3 -> 390 | H14: ↑ gate → later Stage 2 activation → ↓ tx revenue.
A15: Cloud base cost | B15: opex_cloud_base | C15: =opex_cloud_base*0.7 -> 2275 | D15: =opex_cloud_base*0.85 -> 2762.5 | E15: =opex_cloud_base*1 -> 3250 | F15: =opex_cloud_base*1.15 -> 3737.5 | G15: =opex_cloud_base*1.3 -> 4225 | H15: ↑ cloud → ↓ profit. Scales with VCR and GMV.
A16: BHXH rate | B16: bhxh_rate | C16: =bhxh_rate*0.7 -> 0.1505 | D16: =bhxh_rate*0.85 -> 0.18275 | E16: =bhxh_rate*1 -> 0.215 | F16: =bhxh_rate*1.15 -> 0.24725 | G16: =bhxh_rate*1.3 -> 0.2795 | H16: ↑ BHXH → ↑ all salary costs → ↓ profit.
A17: CIT rate | B17: cit_rate | C17: =cit_rate*0.7 -> 0.14 | D17: =cit_rate*0.85 -> 0.17 | E17: =cit_rate*1 -> 0.2 | F17: =cit_rate*1.15 -> 0.23 | G17: =cit_rate*1.3 -> 0.26 | H17: ↑ tax → ↓ net income. Only when profitable.
A20: TWO-WAY TABLE: NPV sensitivity to adoption_max × platform_market_share
A21: Manually run: change both params in Assumptions → record NPV from DCF sheet
A22: adoption_max ↓ \ mkt_share → | B22: 0.001 | C22: 0.003 | D22: 0.005 | E22: 0.008 | F22: 0.01 | G22: 0.015 | H22: 0.02
A23: 200
A24: 400
A25: 600
A26: 800
A27: 1000
A28: 1200 | D28: ← BASE
A29: 1500
A30: 2000
A31: 3000
A34: TWO-WAY TABLE: NPV sensitivity to adoption_max × churn_rate
A35: Manually run: change both params in Assumptions → record NPV from DCF sheet
A36: adoption_max ↓ \ churn → | B36: 0.05 | C36: 0.1 | D36: 0.15 | E36: 0.2 | F36: 0.25 | G36: 0.3 | H36: 0.35
A37: 200
A38: 400
A39: 600
A40: 800
A41: 1000
A42: 1200 | E42: ← BASE
A43: 1500
A44: 2000
A45: 3000
A48: CASCADING IMPACT SUMMARY — How market_share changes ripple through the model
A49: If market_share changes... | B49: 0.1% (Worst) | C49: 0.3% (Bear) | D49: 0.5% (Base) | E49: 1.0% (Bull) | F49: 2.0% (Best)
A50: GMV through platform (2030, Bn VND) | B50: =ecom_market_base*(1+ecom_growth_rate)^5*0.001 -> 121.21957 | C50: =ecom_market_base*(1+ecom_growth_rate)^5*0.003 -> 363.6587 | D50: =ecom_market_base*(1+ecom_growth_rate)^5*platform_market_share -> 2424.3913 | E50: =ecom_market_base*(1+ecom_growth_rate)^5*0.01 -> 1212.1957 | F50: =ecom_market_base*(1+ecom_growth_rate)^5*0.02 -> 2424.3913
A51: Tx fee revenue (2030, Tr VND/yr) | B51: =ecom_market_base*(1+ecom_growth_rate)^5*0.001*tx_take_rate*1000 -> 2424.3913 | C51: =ecom_market_base*(1+ecom_growth_rate)^5*0.003*tx_take_rate*1000 -> 7273.174 | D51: =ecom_market_base*(1+ecom_growth_rate)^5*platform_market_share*tx_take_rate*1000 -> 48487.827 | E51: =ecom_market_base*(1+ecom_growth_rate)^5*0.01*tx_take_rate*1000 -> 24243.913 | F51: =ecom_market_base*(1+ecom_growth_rate)^5*0.02*tx_take_rate*1000 -> 48487.827
A52: Additional cloud cost from GMV (Tr/yr) | B52: =ecom_market_base*(1+ecom_growth_rate)^5*0.001*cloud_gmv_factor -> 60.609783 | C52: =ecom_market_base*(1+ecom_growth_rate)^5*0.003*cloud_gmv_factor -> 181.82935 | D52: =ecom_market_base*(1+ecom_growth_rate)^5*platform_market_share*cloud_gmv_factor -> 1212.1957 | E52: =ecom_market_base*(1+ecom_growth_rate)^5*0.01*cloud_gmv_factor -> 606.09783 | F52: =ecom_market_base*(1+ecom_growth_rate)^5*0.02*cloud_gmv_factor -> 1212.1957
A53: Payment processing COGS (Tr/yr) | B53: =ecom_market_base*(1+ecom_growth_rate)^5*0.001*tx_take_rate*1000*payment_proc_pct -> 60.609783 | C53: =ecom_market_base*(1+ecom_growth_rate)^5*0.003*tx_take_rate*1000*payment_proc_pct -> 181.82935 | D53: =ecom_market_base*(1+ecom_growth_rate)^5*platform_market_share*tx_take_rate*1000*payment_proc_pct -> 1212.1957 | E53: =ecom_market_base*(1+ecom_growth_rate)^5*0.01*tx_take_rate*1000*payment_proc_pct -> 606.09783 | F53: =ecom_market_base*(1+ecom_growth_rate)^5*0.02*tx_take_rate*1000*payment_proc_pct -> 1212.1957
A54: Net revenue impact vs base (Tr/yr) | B54: =(0.001-platform_market_share)*ecom_market_base*(1+ecom_growth_rate)^5*tx_take_rate*1000*(1-payment_proc_pct) -> -44911.849 | C54: =(0.003-platform_market_share)*ecom_market_base*(1+ecom_growth_rate)^5*tx_take_rate*1000*(1-payment_proc_pct) -> -40184.286 | D54: =0 -> 0 | E54: =(0.01-platform_market_share)*ecom_market_base*(1+ecom_growth_rate)^5*tx_take_rate*1000*(1-payment_proc_pct) -> -23637.815 | F54: =(0.02-platform_market_share)*ecom_market_base*(1+ecom_growth_rate)^5*tx_take_rate*1000*(1-payment_proc_pct) -> 0
A57: HOW TO USE THIS SHEET
A58: 1. ONE-AT-A-TIME SENSITIVITY: Shows parameter values at each % variation.
A59: → Change one param in Assumptions → check NPV in 'DCF & Returns' → record here.
A60: 2. TWO-WAY TABLES: Test combinations of two parameters simultaneously.
A61: → Set both params in Assumptions → check NPV → fill the cell.
A62: → The '← BASE' cell marks current assumption values.
A63: 3. CASCADING IMPACT SUMMARY: Shows computed impacts of market_share changes.
A64: → These use formulas — values auto-update when you change Assumptions.
A65: 4. TIP: Use Excel's Data → What-If Analysis → Data Table for automated sensitivity.
A66: → Select NPV cell as 'Result cell', param cells as Row/Column input cells.

Sheet Scenarios
A1: SCENARIO ANALYSIS
A2: Copy values from a column into Assumptions.
A4: Parameter | B4: WORST | C4: BEAR | D4: BASE | E4: BULL | F4: BEST
A5: adoption_max | B5: 200 | C5: 600 | D5: =adoption_max -> 1200 | E5: 2000 | F5: 3500
A6: adoption_steepness | B6: 0.5 | C6: 0.7 | D6: =adoption_steepness -> 0.9 | E6: 1.2 | F6: 1.5
A7: churn_rate | B7: 0.35 | C7: 0.25 | D7: =churn_rate -> 0.2 | E7: 0.15 | F7: 0.1
A8: platform_market_share | B8: 0.001 | C8: 0.003 | D8: =platform_market_share -> 0.02 | E8: 0.01 | F8: 0.02
A9: cert_fee_yr1 | B9: 15 | C9: 20 | D9: =cert_fee_yr1 -> 25 | E9: 30 | F9: 40
A10: cert_fee_escalation | B10: 0 | C10: 0.03 | D10: =cert_fee_escalation -> 0.05 | E10: 0.08 | F10: 0.12
A11: tx_take_rate | B11: 0.01 | C11: 0.015 | D11: =tx_take_rate -> 0.02 | E11: 0.025 | F11: 0.03
A12: opex_marketing | B12: 8000 | C12: 7500 | D12: =opex_marketing -> 7000 | E12: 6000 | F12: 5000
A13: discount_rate | B13: 0.2 | C13: 0.18 | D13: =discount_rate -> 0.15 | E13: 0.12 | F13: 0.1
A14: stage2_gate | B14: 500 | C14: 400 | D14: =stage2_gate -> 300 | E14: 200 | F14: 150
A17: 🔑 KEY DRIVERS — WHAT AFFECTS NPV/IRR THE MOST
A19: The model's NPV and IRR are most sensitive to these 3 factors, in order of impact:
A21: 1. ADOPTION MAX (adoption_max) — #1 DRIVER
A22: This is the S-curve ceiling: maximum enterprises that will ever certify.
A23: Every revenue stream depends on enterprise count. Cert fees, training, audit — all linear to enterprises.
A24: Stage 2 (transaction fees, DaaS, ads) also depends on crossing the gate threshold.
A25: Doubling adoption_max roughly doubles total revenue while costs only grow ~30-40%.
A26: → Worst: 200 = project never gains traction. Best: 3,500 = becomes the standard.
A28: 2. PLATFORM MARKET SHARE (platform_market_share) — #2 DRIVER
A29: % of Vietnam's e-tourism GMV that flows through the VV platform.
A30: Vietnam e-tourism = ~82,500 Bn VND (2025), growing 8%/yr → ~121,000 Bn by 2030.
A31: Even 0.1% difference = 121 Bn VND difference in GMV → 2.4 Bn in tx fees at 2% take rate.
... A95: ↳ 150 vs 500 gate = 1-2 year difference in Stage 2 activation

Sheet Budget 2025
A1: BUDGET 2025 (M VND)
A3: Item | B3: Unit | C3: Jul | D3: Aug | E3: Sep | F3: Oct | G3: Nov | H3: Dec | I3: TOTAL
A4: REVENUE
A5: Cert fees | B5: M VND | C5: =MAX(pilot_count,adoption_max/(1+EXP(-adoption_steepness*(2025.542-adoption_midpoint))))*cert_fee_yr1*(1+cert_fee_escalation)^0/12 -> 246.65066 | D5: =MAX(pilot_count,adoption_max/(1+EXP(-adoption_steepness*(2025.625-adoption_midpoint))))*cert_fee_yr1*(1+cert_fee_escalation)^0/12 -> 263.76273 | E5: =MAX(pilot_count,adoption_max/(1+EXP(-adoption_steepness*(2025.708-adoption_midpoint))))*cert_fee_yr1*(1+cert_fee_escalation)^0/12 -> 281.91347 | F5: =MAX(pilot_count,adoption_max/(1+EXP(-adoption_steepness*(2025.792-adoption_midpoint))))*cert_fee_yr1*(1+cert_fee_escalation)^0/12 -> 301.38351 | G5: =MAX(pilot_count,adoption_max/(1+EXP(-adoption_steepness*(2025.875-adoption_midpoint))))*cert_fee_yr1*(1+cert_fee_escalation)^0/12 -> 321.75063 | H5: =MAX(pilot_count,adoption_max/(1+EXP(-adoption_steepness*(2025.958-adoption_midpoint))))*cert_fee_yr1*(1+cert_fee_escalation)^0/12 -> 343.27923 | I5: =SUM(C5:H5) -> 1758.7402
A6: Training | B6: M VND | C6: =MAX(pilot_count,adoption_max/(1+EXP(-adoption_steepness*(2025.542-adoption_midpoint))))*training_pct*training_fee/12 -> 44.397118 | D6: =MAX(pilot_count,adoption_max/(1+EXP(-adoption_steepness*(2025.625-adoption_midpoint))))*training_pct*training_fee/12 -> 47.477291 | E6: =MAX(pilot_count,adoption_max/(1+EXP(-adoption_steepness*(2025.708-adoption_midpoint))))*training_pct*training_fee/12 -> 50.744425 | F6: =MAX(pilot_count,adoption_max/(1+EXP(-adoption_steepness*(2025.792-adoption_midpoint))))*training_pct*training_fee/12 -> 54.249032 | G6: =MAX(pilot_count,adoption_max/(1+EXP(-adoption_steepness*(2025.875-adoption_midpoint))))*training_pct*training_fee/12 -> 57.915113 | H6: =MAX(pilot_count,adoption_max/(1+EXP(-adoption_steepness*(2025.958-adoption_midpoint))))*training_pct*training_fee/12 -> 61.790261 | I6: =SUM(C6:H6) -> 316.57324
A7: Audit | B7: M VND | C7: =MAX(pilot_count,adoption_max/(1+EXP(-adoption_steepness*(2025.542-adoption_midpoint))))*audit_fee/12 -> 98.660262 | D7: =MAX(pilot_count,adoption_max/(1+EXP(-adoption_steepness*(2025.625-adoption_midpoint))))*audit_fee/12 -> 105.50509 | E7: =MAX(pilot_count,adoption_max/(1+EXP(-adoption_steepness*(2025.708-adoption_midpoint))))*audit_fee/12 -> 112.76539 | F7: =MAX(pilot_count,adoption_max/(1+EXP(-adoption_steepness*(2025.792-adoption_midpoint))))*audit_fee/12 -> 120.5534 | G7: =MAX(pilot_count,adoption_max/(1+EXP(-adoption_steepness*(2025.875-adoption_midpoint))))*audit_fee/12 -> 128.70025 | H7: =MAX(pilot_count,adoption_max/(1+EXP(-adoption_steepness*(2025.958-adoption_midpoint))))*audit_fee/12 -> 137.31169 | I7: =SUM(C7:H7) -> 703.49609
A8: TOTAL REVENUE | C8: =SUM(C5:C7) -> 389.70804 | D8: =SUM(D5:D7) -> 416.74511 | E8: =SUM(E5:E7) -> 445.42328 | F8: =SUM(F5:F7) -> 476.18595 | G8: =SUM(G5:G7) -> 508.36599 | H8: =SUM(H5:H7) -> 542.38118 | I8: =SUM(C8:H8) -> 2778.8095
A10: CAPEX
A11: Cloud setup | B11: M VND | C11: =capex_cloud_setup/6 -> 133.33333 | D11: =capex_cloud_setup/6 -> 133.33333 | E11: =capex_cloud_setup/6 -> 133.33333 | F11: =capex_cloud_setup/6 -> 133.33333 | G11: =capex_cloud_setup/6 -> 133.33333 | H11: =capex_cloud_setup/6 -> 133.33333 | I11: =SUM(C11:H11) -> 800
A12: Backend dev | B12: M VND | C12: =capex_backend/6 -> 200 | D12: =capex_backend/6 -> 200 | E12: =capex_backend/6 -> 200 | F12: =capex_backend/6 -> 200 | G12: =capex_backend/6 -> 200 | H12: =capex_backend/6 -> 200 | I12: =SUM(C12:H12) -> 1200
A13: Frontend+mobile | B13: M VND | C13: =capex_frontend/6 -> 150 | D13: =capex_frontend/6 -> 150 | E13: =capex_frontend/6 -> 150 | F13: =capex_frontend/6 -> 150 | G13: =capex_frontend/6 -> 150 | H13: =capex_frontend/6 -> 150 | I13: =SUM(C13:H13) -> 900
A14: Data platform | B14: M VND | C14: =capex_data_platform/6 -> 100 | D14: =capex_data_platform/6 -> 100 | E14: =capex_data_platform/6 -> 100 | F14: =capex_data_platform/6 -> 100 | G14: =capex_data_platform/6 -> 100 | H14: =capex_data_platform/6 -> 100 | I14: =SUM(C14:H14) -> 600
A15: Security | B15: M VND | C15: =capex_security_setup/6 -> 41.666667 | D15: =capex_security_setup/6 -> 41.666667 | E15: =capex_security_setup/6 -> 41.666667 | F15: =capex_security_setup/6 -> 41.666667 | G15: =capex_security_setup/6 -> 41.666667 | H15: =capex_security_setup/6 -> 41.666667 | I15: =SUM(C15:H15) -> 250
A16: UX/UI design | B16: M VND | C16: =capex_ux_design/6 -> 58.333333 | D16: =capex_ux_design/6 -> 58.333333 | E16: =capex_ux_design/6 -> 58.333333 | F16: =capex_ux_design/6 -> 58.333333 | G16: =capex_ux_design/6 -> 58.333333 | H16: =capex_ux_design/6 -> 58.333333 | I16: =SUM(C16:H16) -> 350
A17: Integrations | B17: M VND | C17: =capex_integration/6 -> 66.666667 | D17: =capex_integration/6 -> 66.666667 | E17: =capex_integration/6 -> 66.666667 | F17: =capex_integration/6 -> 66.666667 | G17: =capex_integration/6 -> 66.666667 | H17: =capex_integration/6 -> 66.666667 | I17: =SUM(C17:H17) -> 400
A18: DevOps | B18: M VND | C18: =capex_devops/6 -> 46.666667 | D18: =capex_devops/6 -> 46.666667 | E18: =capex_devops/6 -> 46.666667 | F18: =capex_devops/6 -> 46.666667 | G18: =capex_devops/6 -> 46.666667 | H18: =capex_devops/6 -> 46.666667 | I18: =SUM(C18:H18) -> 280
A19: QA testing | B19: M VND | C19: =capex_testing/6 -> 33.333333 | D19: =capex_testing/6 -> 33.333333 | E19: =capex_testing/6 -> 33.333333 | F19: =capex_testing/6 -> 33.333333 | G19: =capex_testing/6 -> 33.333333 | H19: =capex_testing/6 -> 33.333333 | I19: =SUM(C19:H19) -> 200
A20: Contingency | B20: M VND | C20: =capex_contingency/6 -> 50 | D20: =capex_contingency/6 -> 50 | E20: =capex_contingency/6 -> 50 | F20: =capex_contingency/6 -> 50 | G20: =capex_contingency/6 -> 50 | H20: =capex_contingency/6 -> 50 | I20: =SUM(C20:H20) -> 300
A21: TOTAL CAPEX | C21: =SUM(C11:C20) -> 880 | D21: =SUM(D11:D20) -> 880 | E21: =SUM(E11:E20) -> 880 | F21: =SUM(F11:F20) -> 880 | G21: =SUM(G11:G20) -> 880 | H21: =SUM(H11:H20) -> 880 | I21: =SUM(C21:H21) -> 5280
A23: OPEX
A24: HR — Mgmt(2) | B24: M VND | C24: =salary_mgmt*2*(1+salary_escalation)^0*(1+bhxh_rate) -> 109.35 | D24: =salary_mgmt*2*(1+salary_escalation)^0*(1+bhxh_rate) -> 109.35 | E24: =salary_mgmt*2*(1+salary_escalation)^0*(1+bhxh_rate) -> 109.35 | F24: =salary_mgmt*2*(1+salary_escalation)^0*(1+bhxh_rate) -> 109.35 | G24: =salary_mgmt*2*(1+salary_escalation)^0*(1+bhxh_rate) -> 109.35 | H24: =salary_mgmt*2*(1+salary_escalation)^0*(1+bhxh_rate) -> 109.35 | I24: =SUM(C24:H24) -> 656.1
A25: HR — Dev(12) | B25: M VND | C25: =salary_dev*12*(1+salary_escalation)^0*(1+bhxh_rate) -> 510.3 | D25: =salary_dev*12*(1+salary_escalation)^0*(1+bhxh_rate) -> 510.3 | E25: =salary_dev*12*(1+salary_escalation)^0*(1+bhxh_rate) -> 510.3 | F25: =salary_dev*12*(1+salary_escalation)^0*(1+bhxh_rate) -> 510.3 | G25: =salary_dev*12*(1+salary_escalation)^0*(1+bhxh_rate) -> 510.3 | H25: =salary_dev*12*(1+salary_escalation)^0*(1+bhxh_rate) -> 510.3 | I25: =SUM(C25:H25) -> 3061.8
A26: HR — BizOps(2) | B26: M VND | C26: =salary_bizops*2*(1+salary_escalation)^0*(1+bhxh_rate) -> 48.6 | D26: =salary_bizops*2*(1+salary_escalation)^0*(1+bhxh_rate) -> 48.6 | E26: =salary_bizops*2*(1+salary_escalation)^0*(1+bhxh_rate) -> 48.6 | F26: =salary_bizops*2*(1+salary_escalation)^0*(1+bhxh_rate) -> 48.6 | G26: =salary_bizops*2*(1+salary_escalation)^0*(1+bhxh_rate) -> 48.6 | H26: =salary_bizops*2*(1+salary_escalation)^0*(1+bhxh_rate) -> 48.6 | I26: =SUM(C26:H26) -> 291.6
A27: Recruitment | B27: M VND | C27: =16*30*12*recruit_cost_pct -> 1152 | D27: =0 -> 0 | E27: =0 -> 0 | F27: =0 -> 0 | G27: =0 -> 0 | H27: =0 -> 0 | I27: =SUM(C27:H27) -> 1152
A28: Marketing | B28: M VND | C28: =opex_marketing*(1+marketing_growth)^0/12 -> 583.33333 | D28: =opex_marketing*(1+marketing_growth)^0/12 -> 583.33333 | E28: =opex_marketing*(1+marketing_growth)^0/12 -> 583.33333 | F28: =opex_marketing*(1+marketing_growth)^0/12 -> 583.33333 | G28: =opex_marketing*(1+marketing_growth)^0/12 -> 583.33333 | H28: =opex_marketing*(1+marketing_growth)^0/12 -> 583.33333 | I28: =SUM(C28:H28) -> 3500
A29: Branding | B29: M VND | C29: =opex_branding/12 -> 333.33333 | D29: =opex_branding/12 -> 333.33333 | E29: =opex_branding/12 -> 333.33333 | F29: =opex_branding/12 -> 333.33333 | G29: =opex_branding/12 -> 333.33333 | H29: =opex_branding/12 -> 333.33333 | I29: =SUM(C29:H29) -> 2000
A30: Cloud | B30: M VND | C30: =opex_cloud_base/12 -> 270.83333 | D30: =opex_cloud_base/12 -> 270.83333 | E30: =opex_cloud_base/12 -> 270.83333 | F30: =opex_cloud_base/12 -> 270.83333 | G30: =opex_cloud_base/12 -> 270.83333 | H30: =opex_cloud_base/12 -> 270.83333 | I30: =SUM(C30:H30) -> 1625
A31: Security | B31: M VND | C31: =opex_security/12 -> 20.833333 | D31: =opex_security/12 -> 20.833333 | E31: =opex_security/12 -> 20.833333 | F31: =opex_security/12 -> 20.833333 | G31: =opex_security/12 -> 20.833333 | H31: =opex_security/12 -> 20.833333 | I31: =SUM(C31:H31) -> 125
A32: External | B32: M VND | C32: =opex_external/12 -> 33.333333 | D32: =opex_external/12 -> 33.333333 | E32: =opex_external/12 -> 33.333333 | F32: =opex_external/12 -> 33.333333 | G32: =opex_external/12 -> 33.333333 | H32: =opex_external/12 -> 33.333333 | I32: =SUM(C32:H32) -> 200
A33: Legal | B33: M VND | C33: =opex_legal/12 -> 20 | D33: =opex_legal/12 -> 20 | E33: =opex_legal/12 -> 20 | F33: =opex_legal/12 -> 20 | G33: =opex_legal/12 -> 20 | H33: =opex_legal/12 -> 20 | I33: =SUM(C33:H33) -> 120
A34: Partner mgmt | B34: M VND | C34: =opex_partner_mgmt/12 -> 41.666667 | D34: =opex_partner_mgmt/12 -> 41.666667 | E34: =opex_partner_mgmt/12 -> 41.666667 | F34: =opex_partner_mgmt/12 -> 41.666667 | G34: =opex_partner_mgmt/12 -> 41.666667 | H34: =opex_partner_mgmt/12 -> 41.666667 | I34: =SUM(C34:H34) -> 250
A35: Pilot eval | B35: M VND | C35: =opex_pilot_eval/6 -> 33.333333 | D35: =opex_pilot_eval/6 -> 33.333333 | E35: =opex_pilot_eval/6 -> 33.333333 | F35: =opex_pilot_eval/6 -> 33.333333 | G35: =opex_pilot_eval/6 -> 33.333333 | H35: =opex_pilot_eval/6 -> 33.333333 | I35: =SUM(C35:H35) -> 200
A36: Customer support | B36: M VND | C36: =MAX(pilot_count,adoption_max/(1+EXP(-adoption_steepness*(2025.542-adoption_midpoint))))*opex_support_per_ent/12 -> 19.732052 | D36: =MAX(pilot_count,adoption_max/(1+EXP(-adoption_steepness*(2025.625-adoption_midpoint))))*opex_support_per_ent/12 -> 21.101018 | E36: =MAX(pilot_count,adoption_max/(1+EXP(-adoption_steepness*(2025.708-adoption_midpoint))))*opex_support_per_ent/12 -> 22.553078 | F36: =MAX(pilot_count,adoption_max/(1+EXP(-adoption_steepness*(2025.792-adoption_midpoint))))*opex_support_per_ent/12 -> 24.110681 | G36: =MAX(pilot_count,adoption_max/(1+EXP(-adoption_steepness*(2025.875-adoption_midpoint))))*opex_support_per_ent/12 -> 25.74005 | H36: =MAX(pilot_count,adoption_max/(1+EXP(-adoption_steepness*(2025.958-adoption_midpoint))))*opex_support_per_ent/12 -> 27.462338 | I36: =SUM(C36:H36) -> 140.69922
A37: OPEX Subtotal | C37: =SUM(C24:C36) -> 3176.6487 | D37: =SUM(D24:D36) -> 2026.0177 | E37: =SUM(E24:E36) -> 2027.4697 | F37: =SUM(F24:F36) -> 2029.0273 | G37: =SUM(G24:G36) -> 2030.6567 | H37: =SUM(H24:H36) -> 2032.379 | I37: =SUM(C37:H37) -> 13322.199
A38: Contingency | B38: M VND | C38: =C37*opex_contingency_pct -> 317.66487 | D38: =D37*opex_contingency_pct -> 202.60177 | E38: =E37*opex_contingency_pct -> 202.74697 | F38: =F37*opex_contingency_pct -> 202.90273 | G38: =G37*opex_contingency_pct -> 203.06567 | H38: =H37*opex_contingency_pct -> 203.2379 | I38: =SUM(C38:H38) -> 1332.2199
A39: TOTAL OPEX | C39: =C37+C38 -> 3494.3136 | D39: =D37+D38 -> 2228.6195 | E39: =E37+E38 -> 2230.2167 | F39: =F37+F38 -> 2231.9301 | G39: =G37+G38 -> 2233.7224 | H39: =H37+H38 -> 2235.6169 | I39: =SUM(C39:H39) -> 14654.419
A41: SUMMARY
A42: Revenue | C42: =C8 -> 389.70804 | D42: =D8 -> 416.74511 | E42: =E8 -> 445.42328 | F42: =F8 -> 476.18595 | G42: =G8 -> 508.36599 | H42: =H8 -> 542.38118 | I42: =SUM(C42:H42) -> 2778.8095
A43: CAPEX | C43: =C21 -> 880 | D43: =D21 -> 880 | E43: =E21 -> 880 | F43: =F21 -> 880 | G43: =G21 -> 880 | H43: =H21 -> 880 | I43: =SUM(C43:H43) -> 5280
A44: OPEX | C44: =C39 -> 3494.3136 | D44: =D39 -> 2228.6195 | E44: =E39 -> 2230.2167 | F44: =F39 -> 2231.9301 | G44: =G39 -> 2233.7224 | H44: =H39 -> 2235.6169 | I44: =SUM(C44:H44) -> 14654.419
A45: TOTAL BUDGET | C45: =C43+C44 -> 4374.3136 | D45: =D43+D44 -> 3108.6195 | E45: =E43+E44 -> 3110.2167 | F45: =F43+F44 -> 3111.9301 | G45: =G43+G44 -> 3113.7224 | H45: =H43+H44 -> 3115.6169 | I45: =SUM(C45:H45) -> 19934.419
A46: NET (Rev-Budget) | C46: =C42-C45 -> -3984.6056 | D46: =D42-D45 -> -2691.8743 | E46: =E42-E45 -> -2664.7934 | F46: =F42-F45 -> -2635.7441 | G46: =G42-G45 -> -2605.3564 | H46: =H42-H45 -> -2573.2357 | I46: =SUM(C46:H46) -> -17155.61
A47: Cumulative | C47: =C46 -> -3984.6056 | D47: =C47+D46 -> -6676.4799 | E47: =D47+E46 -> -9341.2733 | F47: =E47+F46 -> -11977.017 | G47: =F47+G46 -> -14582.374 | H47: =G47+H46 -> -17155.61 | I47: =H47 -> -17155.61

Sheet Budget 2026
A1: BUDGET 2026 (M VND)
A3: Item | B3: Unit | C3: Jan | D3: Feb | E3: Mar | F3: Apr | G3: May | H3: Jun | I3: Jul | J3: Aug | K3: Sep | L3: Oct | M3: Nov | N3: Dec | O3: TOTAL
A4: REVENUE
A5: Cert fees | B5: M VND | C5: =MAX(pilot_count,adoption_max/(1+EXP(-adoption_steepness*(2026.042-adoption_midpoint))))*cert_fee_yr1*(1+cert_fee_escalation)^1/12 -> 384.60193 | D5: =MAX(pilot_count,adoption_max/(1+EXP(-adoption_steepness*(2026.125-adoption_midpoint))))*cert_fee_yr1*(1+cert_fee_escalation)^1/12 -> 409.77536 | E5: =MAX(pilot_count,adoption_max/(1+EXP(-adoption_steepness*(2026.208-adoption_midpoint))))*cert_fee_yr1*(1+cert_fee_escalation)^1/12 -> 436.27561 | F5: =MAX(pilot_count,adoption_max/(1+EXP(-adoption_steepness*(2026.292-adoption_midpoint))))*cert_fee_yr1*(1+cert_fee_escalation)^1/12 -> 464.47454 | G5: =MAX(pilot_count,adoption_max/(1+EXP(-adoption_steepness*(2026.375-adoption_midpoint))))*cert_fee_yr1*(1+cert_fee_escalation)^1/12 -> 493.72379 | H5: =MAX(pilot_count,adoption_max/(1+EXP(-adoption_steepness*(2026.458-adoption_midpoint))))*cert_fee_yr1*(1+cert_fee_escalation)^1/12 -> 524.36792 | I5: =MAX(pilot_count,adoption_max/(1+EXP(-adoption_steepness*(2026.542-adoption_midpoint))))*cert_fee_yr1*(1+cert_fee_escalation)^1/12 -> 556.81221 | J5: =MAX(pilot_count,adoption_max/(1+EXP(-adoption_steepness*(2026.625-adoption_midpoint))))*cert_fee_yr1*(1+cert_fee_escalation)^1/12 -> 590.28755 | K5: =MAX(pilot_count,adoption_max/(1+EXP(-adoption_steepness*(2026.708-adoption_midpoint))))*cert_fee_yr1*(1+cert_fee_escalation)^1/12 -> 625.16707 | L5: =MAX(pilot_count,adoption_max/(1+EXP(-adoption_steepness*(2026.792-adoption_midpoint))))*cert_fee_yr1*(1+cert_fee_escalation)^1/12 -> 661.883 | M5: =MAX(pilot_count,adoption_max/(1+EXP(-adoption_steepness*(2026.875-adoption_midpoint))))*cert_fee_yr1*(1+cert_fee_escalation)^1/12 -> 699.53856 | N5: =MAX(pilot_count,adoption_max/(1+EXP(-adoption_steepness*(2026.958-adoption_midpoint))))*cert_fee_yr1*(1+cert_fee_escalation)^1/12 -> 738.53048 | O5: =SUM(C5:N5) -> 6585.438
A6: Training | B6: M VND | C6: =MAX(pilot_count,adoption_max/(1+EXP(-adoption_steepness*(2026.042-adoption_midpoint))))*training_pct*training_fee/12 -> 65.931759 | D6: =MAX(pilot_count,adoption_max/(1+EXP(-adoption_steepness*(2026.125-adoption_midpoint))))*training_pct*training_fee/12 -> 70.247204 | E6: =MAX(pilot_count,adoption_max/(1+EXP(-adoption_steepness*(2026.208-adoption_midpoint))))*training_pct*training_fee/12 -> 74.790105 | F6: =MAX(pilot_count,adoption_max/(1+EXP(-adoption_steepness*(2026.292-adoption_midpoint))))*training_pct*training_fee/12 -> 79.624206 | G6: =MAX(pilot_count,adoption_max/(1+EXP(-adoption_steepness*(2026.375-adoption_midpoint))))*training_pct*training_fee/12 -> 84.638365 | H6: =MAX(pilot_count,adoption_max/(1+EXP(-adoption_steepness*(2026.458-adoption_midpoint))))*training_pct*training_fee/12 -> 89.891643 | I6: =MAX(pilot_count,adoption_max/(1+EXP(-adoption_steepness*(2026.542-adoption_midpoint))))*training_pct*training_fee/12 -> 95.453522 | J6: =MAX(pilot_count,adoption_max/(1+EXP(-adoption_steepness*(2026.625-adoption_midpoint))))*training_pct*training_fee/12 -> 101.19215 | K6: =MAX(pilot_count,adoption_max/(1+EXP(-adoption_steepness*(2026.708-adoption_midpoint))))*training_pct*training_fee/12 -> 107.1715 | L6: =MAX(pilot_count,adoption_max/(1+EXP(-adoption_steepness*(2026.792-adoption_midpoint))))*training_pct*training_fee/12 -> 113.46566 | M6: =MAX(pilot_count,adoption_max/(1+EXP(-adoption_steepness*(2026.875-adoption_midpoint))))*training_pct*training_fee/12 -> 119.9209 | N6: =MAX(pilot_count,adoption_max/(1+EXP(-adoption_steepness*(2026.958-adoption_midpoint))))*training_pct*training_fee/12 -> 126.60523 | O6: =SUM(C6:N6) -> 1128.9322
A7: Audit | B7: M VND | C7: =MAX(pilot_count,adoption_max/(1+EXP(-adoption_steepness*(2026.042-adoption_midpoint))))*audit_fee/12 -> 146.51502 | D7: =MAX(pilot_count,adoption_max/(1+EXP(-adoption_steepness*(2026.125-adoption_midpoint))))*audit_fee/12 -> 156.1049 | E7: =MAX(pilot_count,adoption_max/(1+EXP(-adoption_steepness*(2026.208-adoption_midpoint))))*audit_fee/12 -> 166.20023 | F7: =MAX(pilot_count,adoption_max/(1+EXP(-adoption_steepness*(2026.292-adoption_midpoint))))*audit_fee/12 -> 176.94268 | G7: =MAX(pilot_count,adoption_max/(1+EXP(-adoption_steepness*(2026.375-adoption_midpoint))))*audit_fee/12 -> 188.08525 | H7: =MAX(pilot_count,adoption_max/(1+EXP(-adoption_steepness*(2026.458-adoption_midpoint))))*audit_fee/12 -> 199.75921 | I7: =MAX(pilot_count,adoption_max/(1+EXP(-adoption_steepness*(2026.542-adoption_midpoint))))*audit_fee/12 -> 212.11894 | J7: =MAX(pilot_count,adoption_max/(1+EXP(-adoption_steepness*(2026.625-adoption_midpoint))))*audit_fee/12 -> 224.87145 | K7: =MAX(pilot_count,adoption_max/(1+EXP(-adoption_steepness*(2026.708-adoption_midpoint))))*audit_fee/12 -> 238.15888 | L7: =MAX(pilot_count,adoption_max/(1+EXP(-adoption_steepness*(2026.792-adoption_midpoint))))*audit_fee/12 -> 252.1459 | M7: =MAX(pilot_count,adoption_max/(1+EXP(-adoption_steepness*(2026.875-adoption_midpoint))))*audit_fee/12 -> 266.49088 | N7: =MAX(pilot_count,adoption_max/(1+EXP(-adoption_steepness*(2026.958-adoption_midpoint))))*audit_fee/12 -> 281.34495 | O7: =SUM(C7:N7) -> 2508.7383
A8: TOTAL REVENUE | C8: =SUM(C5:C7) -> 597.0487 | D8: =SUM(D5:D7) -> 636.12746 | E8: =SUM(E5:E7) -> 677.26595 | F8: =SUM(F5:F7) -> 721.04143 | G8: =SUM(G5:G7) -> 766.44741 | H8: =SUM(H5:H7) -> 814.01877 | I8: =SUM(I5:I7) -> 864.38467 | J8: =SUM(J5:J7) -> 916.35115 | ... N8: =SUM(N5:N7) -> 1146.4807 | O8: =SUM(C8:N8) -> 10223.109
A10: CAPEX
A11: Maintenance | B11: M VND | C11: =capex_total*capex_maintenance_pct/12 -> 79.2 | D11: =capex_total*capex_maintenance_pct/12 -> 79.2 | E11: =capex_total*capex_maintenance_pct/12 -> 79.2 | F11: =capex_total*capex_maintenance_pct/12 -> 79.2 | G11: =capex_total*capex_maintenance_pct/12 -> 79.2 | H11: =capex_total*capex_maintenance_pct/12 -> 79.2 | I11: =capex_total*capex_maintenance_pct/12 -> 79.2 | J11: =capex_total*capex_maintenance_pct/12 -> 79.2 | ... N11: =capex_total*capex_maintenance_pct/12 -> 79.2 | O11: =SUM(C11:N11) -> 950.4
A12: TOTAL CAPEX | C12: =SUM(C11:C11) -> 79.2 | D12: =SUM(D11:D11) -> 79.2 | E12: =SUM(E11:E11) -> 79.2 | F12: =SUM(F11:F11) -> 79.2 | G12: =SUM(G11:G11) -> 79.2 | H12: =SUM(H11:H11) -> 79.2 | I12: =SUM(I11:I11) -> 79.2 | J12: =SUM(J11:J11) -> 79.2 | ... N12: =SUM(N11:N11) -> 79.2 | O12: =SUM(C12:N12) -> 950.4
A14: OPEX
A15: HR — Mgmt(2) | B15: M VND | C15: =salary_mgmt*2*(1+salary_escalation)^1*(1+bhxh_rate) -> 120.285 | D15: =salary_mgmt*2*(1+salary_escalation)^1*(1+bhxh_rate) -> 120.285 | E15: =salary_mgmt*2*(1+salary_escalation)^1*(1+bhxh_rate) -> 120.285 | F15: =salary_mgmt*2*(1+salary_escalation)^1*(1+bhxh_rate) -> 120.285 | G15: =salary_mgmt*2*(1+salary_escalation)^1*(1+bhxh_rate) -> 120.285 | H15: =salary_mgmt*2*(1+salary_escalation)^1*(1+bhxh_rate) -> 120.285 | I15: =salary_mgmt*2*(1+salary_escalation)^1*(1+bhxh_rate) -> 120.285 | J15: =salary_mgmt*2*(1+salary_escalation)^1*(1+bhxh_rate) -> 120.285 | ... N15: =salary_mgmt*2*(1+salary_escalation)^1*(1+bhxh_rate) -> 120.285 | O15: =SUM(C15:N15) -> 1443.42
A16: HR — Dev(12) | B16: M VND | C16: =salary_dev*12*(1+salary_escalation)^1*(1+bhxh_rate) -> 561.33 | D16: =salary_dev*12*(1+salary_escalation)^1*(1+bhxh_rate) -> 561.33 | E16: =salary_dev*12*(1+salary_escalation)^1*(1+bhxh_rate) -> 561.33 | F16: =salary_dev*12*(1+salary_escalation)^1*(1+bhxh_rate) -> 561.33 | G16: =salary_dev*12*(1+salary_escalation)^1*(1+bhxh_rate) -> 561.33 | H16: =salary_dev*12*(1+salary_escalation)^1*(1+bhxh_rate) -> 561.33 | I16: =salary_dev*12*(1+salary_escalation)^1*(1+bhxh_rate) -> 561.33 | J16: =salary_dev*12*(1+salary_escalation)^1*(1+bhxh_rate) -> 561.33 | ... N16: =salary_dev*12*(1+salary_escalation)^1*(1+bhxh_rate) -> 561.33 | O16: =SUM(C16:N16) -> 6735.96
A17: HR — BizOps(6) | B17: M VND | C17: =salary_bizops*6*(1+salary_escalation)^1*(1+bhxh_rate) -> 160.38 | D17: =salary_bizops*6*(1+salary_escalation)^1*(1+bhxh_rate) -> 160.38 | E17: =salary_bizops*6*(1+salary_escalation)^1*(1+bhxh_rate) -> 160.38 | F17: =salary_bizops*6*(1+salary_escalation)^1*(1+bhxh_rate) -> 160.38 | G17: =salary_bizops*6*(1+salary_escalation)^1*(1+bhxh_rate) -> 160.38 | H17: =salary_bizops*6*(1+salary_escalation)^1*(1+bhxh_rate) -> 160.38 | I17: =salary_bizops*6*(1+salary_escalation)^1*(1+bhxh_rate) -> 160.38 | J17: =salary_bizops*6*(1+salary_escalation)^1*(1+bhxh_rate) -> 160.38 | ... N17: =salary_bizops*6*(1+salary_escalation)^1*(1+bhxh_rate) -> 160.38 | O17: =SUM(C17:N17) -> 1924.56
A18: HR — Data(2) | B18: M VND | C18: =salary_data*2*(1+salary_escalation)^1*(1+bhxh_rate) -> 106.92 | D18: =salary_data*2*(1+salary_escalation)^1*(1+bhxh_rate) -> 106.92 | E18: =salary_data*2*(1+salary_escalation)^1*(1+bhxh_rate) -> 106.92 | F18: =salary_data*2*(1+salary_escalation)^1*(1+bhxh_rate) -> 106.92 | G18: =salary_data*2*(1+salary_escalation)^1*(1+bhxh_rate) -> 106.92 | H18: =salary_data*2*(1+salary_escalation)^1*(1+bhxh_rate) -> 106.92 | I18: =salary_data*2*(1+salary_escalation)^1*(1+bhxh_rate) -> 106.92 | J18: =salary_data*2*(1+salary_escalation)^1*(1+bhxh_rate) -> 106.92 | ... N18: =salary_data*2*(1+salary_escalation)^1*(1+bhxh_rate) -> 106.92 | O18: =SUM(C18:N18) -> 1283.04
A19: Recruitment | B19: M VND | C19: =6*30*12*recruit_cost_pct -> 432 | D19: =0 -> 0 | E19: =0 -> 0 | F19: =0 -> 0 | G19: =0 -> 0 | H19: =0 -> 0 | I19: =0 -> 0 | J19: =0 -> 0 | K19: =0 -> 0 | ... N19: =0 -> 0 | O19: =SUM(C19:N19) -> 432
A20: Marketing | B20: M VND | C20: =opex_marketing*(1+marketing_growth)^1/12 -> 670.83333 | D20: =opex_marketing*(1+marketing_growth)^1/12 -> 670.83333 | E20: =opex_marketing*(1+marketing_growth)^1/12 -> 670.83333 | F20: =opex_marketing*(1+marketing_growth)^1/12 -> 670.83333 | G20: =opex_marketing*(1+marketing_growth)^1/12 -> 670.83333 | H20: =opex_marketing*(1+marketing_growth)^1/12 -> 670.83333 | I20: =opex_marketing*(1+marketing_growth)^1/12 -> 670.83333 | J20: =opex_marketing*(1+marketing_growth)^1/12 -> 670.83333 | ... N20: =opex_marketing*(1+marketing_growth)^1/12 -> 670.83333 | O20: =SUM(C20:N20) -> 8050
A21: Branding | B21: M VND | C21: =opex_branding/12 -> 333.33333 | D21: =opex_branding/12 -> 333.33333 | E21: =opex_branding/12 -> 333.33333 | F21: =opex_branding/12 -> 333.33333 | G21: =opex_branding/12 -> 333.33333 | H21: =opex_branding/12 -> 333.33333 | I21: =opex_branding/12 -> 333.33333 | J21: =opex_branding/12 -> 333.33333 | ... N21: =opex_branding/12 -> 333.33333 | O21: =SUM(C21:N21) -> 4000
A22: Cloud | B22: M VND | C22: =opex_cloud_base/12 -> 270.83333 | D22: =opex_cloud_base/12 -> 270.83333 | E22: =opex_cloud_base/12 -> 270.83333 | F22: =opex_cloud_base/12 -> 270.83333 | G22: =opex_cloud_base/12 -> 270.83333 | H22: =opex_cloud_base/12 -> 270.83333 | I22: =opex_cloud_base/12 -> 270.83333 | J22: =opex_cloud_base/12 -> 270.83333 | ... N22: =opex_cloud_base/12 -> 270.83333 | O22: =SUM(C22:N22) -> 3250
A23: Security | B23: M VND | C23: =opex_security/12 -> 20.833333 | D23: =opex_security/12 -> 20.833333 | E23: =opex_security/12 -> 20.833333 | F23: =opex_security/12 -> 20.833333 | G23: =opex_security/12 -> 20.833333 | H23: =opex_security/12 -> 20.833333 | I23: =opex_security/12 -> 20.833333 | J23: =opex_security/12 -> 20.833333 | ... N23: =opex_security/12 -> 20.833333 | O23: =SUM(C23:N23) -> 250
A24: External | B24: M VND | C24: =opex_external/12 -> 33.333333 | D24: =opex_external/12 -> 33.333333 | E24: =opex_external/12 -> 33.333333 | F24: =opex_external/12 -> 33.333333 | G24: =opex_external/12 -> 33.333333 | H24: =opex_external/12 -> 33.333333 | I24: =opex_external/12 -> 33.333333 | J24: =opex_external/12 -> 33.333333 | ... N24: =opex_external/12 -> 33.333333 | O24: =SUM(C24:N24) -> 400
A25: Legal | B25: M VND | C25: =opex_legal/12 -> 20 | D25: =opex_legal/12 -> 20 | E25: =opex_legal/12 -> 20 | F25: =opex_legal/12 -> 20 | G25: =opex_legal/12 -> 20 | H25: =opex_legal/12 -> 20 | I25: =opex_legal/12 -> 20 | J25: =opex_legal/12 -> 20 | ... N25: =opex_legal/12 -> 20 | O25: =SUM(C25:N25) -> 240
A26: Partner mgmt | B26: M VND | C26: =opex_partner_mgmt/12 -> 41.666667 | D26: =opex_partner_mgmt/12 -> 41.666667 | E26: =opex_partner_mgmt/12 -> 41.666667 | F26: =opex_partner_mgmt/12 -> 41.666667 | G26: =opex_partner_mgmt/12 -> 41.666667 | H26: =opex_partner_mgmt/12 -> 41.666667 | I26: =opex_partner_mgmt/12 -> 41.666667 | J26: =opex_partner_mgmt/12 -> 41.666667 | ... N26: =opex_partner_mgmt/12 -> 41.666667 | O26: =SUM(C26:N26) -> 500
A27: Customer support | B27: M VND | C27: =MAX(pilot_count,adoption_max/(1+EXP(-adoption_steepness*(2026.042-adoption_midpoint))))*opex_support_per_ent/12 -> 29.303004 | D27: =MAX(pilot_count,adoption_max/(1+EXP(-adoption_steepness*(2026.125-adoption_midpoint))))*opex_support_per_ent/12 -> 31.220979 | E27: =MAX(pilot_count,adoption_max/(1+EXP(-adoption_steepness*(2026.208-adoption_midpoint))))*opex_support_per_ent/12 -> 33.240047 | F27: =MAX(pilot_count,adoption_max/(1+EXP(-adoption_steepness*(2026.292-adoption_midpoint))))*opex_support_per_ent/12 -> 35.388536 | G27: =MAX(pilot_count,adoption_max/(1+EXP(-adoption_steepness*(2026.375-adoption_midpoint))))*opex_support_per_ent/12 -> 37.617051 | H27: =MAX(pilot_count,adoption_max/(1+EXP(-adoption_steepness*(2026.458-adoption_midpoint))))*opex_support_per_ent/12 -> 39.951841 | I27: =MAX(pilot_count,adoption_max/(1+EXP(-adoption_steepness*(2026.542-adoption_midpoint))))*opex_support_per_ent/12 -> 42.423787 | J27: =MAX(pilot_count,adoption_max/(1+EXP(-adoption_steepness*(2026.625-adoption_midpoint))))*opex_support_per_ent/12 -> 44.974289 | K27: =MAX(pilot_count,adoption_max/(1+EXP(-adoption_steepness*(2026.708-adoption_midpoint))))*opex_support_per_ent/12 -> 47.631777 | L27: =MAX(pilot_count,adoption_max/(1+EXP(-adoption_steepness*(2026.792-adoption_midpoint))))*opex_support_per_ent/12 -> 50.429181 | M27: =MAX(pilot_count,adoption_max/(1+EXP(-adoption_steepness*(2026.875-adoption_midpoint))))*opex_support_per_ent/12 -> 53.298176 | N27: =MAX(pilot_count,adoption_max/(1+EXP(-adoption_steepness*(2026.958-adoption_midpoint))))*opex_support_per_ent/12 -> 56.268989 | O27: =SUM(C27:N27) -> 501.74766
A28: OPEX Subtotal | C28: =SUM(C15:C27) -> 2801.0513 | D28: =SUM(D15:D27) -> 2370.9693 | E28: =SUM(E15:E27) -> 2372.9884 | F28: =SUM(F15:F27) -> 2375.1369 | G28: =SUM(G15:G27) -> 2377.3654 | H28: =SUM(H15:H27) -> 2379.7002 | I28: =SUM(I15:I27) -> 2382.1721 | J28: =SUM(J15:J27) -> 2384.7226 | ... N28: =SUM(N15:N27) -> 2396.0173 | O28: =SUM(C28:N28) -> 29010.728
A29: Contingency | B29: M VND | C29: =C28*opex_contingency_pct -> 280.10513 | D29: =D28*opex_contingency_pct -> 237.09693 | E29: =E28*opex_contingency_pct -> 237.29884 | F29: =F28*opex_contingency_pct -> 237.51369 | G29: =G28*opex_contingency_pct -> 237.73654 | H29: =H28*opex_contingency_pct -> 237.97002 | I29: =I28*opex_contingency_pct -> 238.21721 | J29: =J28*opex_contingency_pct -> 238.47226 | ... N29: =N28*opex_contingency_pct -> 239.60173 | O29: =SUM(C29:N29) -> 2901.0728
A30: TOTAL OPEX | C30: =C28+C29 -> 3081.1565 | D30: =D28+D29 -> 2608.0662 | E30: =E28+E29 -> 2610.2872 | F30: =F28+F29 -> 2612.6506 | G30: =G28+G29 -> 2615.1019 | H30: =H28+H29 -> 2617.6702 | I30: =I28+I29 -> 2620.3893 | J30: =J28+J29 -> 2623.1949 | ... N30: =N28+N29 -> 2635.6191 | O30: =SUM(C30:N30) -> 31911.8
A32: SUMMARY
A33: Revenue | C33: =C8 -> 597.0487 | D33: =D8 -> 636.12746 | E33: =E8 -> 677.26595 | F33: =F8 -> 721.04143 | G33: =G8 -> 766.44741 | H33: =H8 -> 814.01877 | I33: =I8 -> 864.38467 | J33: =J8 -> 916.35115 | ... N33: =N8 -> 1146.4807 | O33: =SUM(C33:N33) -> 10223.109
A34: CAPEX | C34: =C12 -> 79.2 | D34: =D12 -> 79.2 | E34: =E12 -> 79.2 | F34: =F12 -> 79.2 | G34: =G12 -> 79.2 | H34: =H12 -> 79.2 | I34: =I12 -> 79.2 | J34: =J12 -> 79.2 | ... N34: =N12 -> 79.2 | O34: =SUM(C34:N34) -> 950.4
A35: OPEX | C35: =C30 -> 3081.1565 | D35: =D30 -> 2608.0662 | E35: =E30 -> 2610.2872 | F35: =F30 -> 2612.6506 | G35: =G30 -> 2615.1019 | H35: =H30 -> 2617.6702 | I35: =I30 -> 2620.3893 | J35: =J30 -> 2623.1949 | ... N35: =N30 -> 2635.6191 | O35: =SUM(C35:N35) -> 31911.8
A36: TOTAL BUDGET | C36: =C34+C35 -> 3160.3565 | D36: =D34+D35 -> 2687.2662 | E36: =E34+E35 -> 2689.4872 | F36: =F34+F35 -> 2691.8506 | G36: =G34+G35 -> 2694.3019 | H36: =H34+H35 -> 2696.8702 | I36: =I34+I35 -> 2699.5893 | J36: =J34+J35 -> 2702.3949 | ... N36: =N34+N35 -> 2714.8191 | O36: =SUM(C36:N36) -> 32862.2
A37: NET (Rev-Budget) | C37: =C33-C36 -> -2563.3078 | D37: =D33-D36 -> -2051.1388 | E37: =E33-E36 -> -2012.2213 | F37: =F33-F36 -> -1970.8091 | G37: =G33-G36 -> -1927.8545 | H37: =H33-H36 -> -1882.8514 | I37: =I33-I36 -> -1835.2047 | J37: =J33-J36 -> -1786.0437 | ... N37: =N33-N36 -> -1568.3384 | O37: =SUM(C37:N37) -> -22639.092
A38: Cumulative | C38: =C37 -> -2563.3078 | D38: =C38+D37 -> -4614.4466 | E38: =D38+E37 -> -6626.6678 | F38: =E38+F37 -> -8597.477 | G38: =F38+G37 -> -10525.331 | H38: =G38+H37 -> -12408.183 | I38: =H38+I37 -> -14243.388 | J38: =I38+J37 -> -16029.431 | K38: =J38+K37 -> -17764.252 | ... N38: =M38+N37 -> -22639.092 | O38: =N38 -> -22639.092
