Workbook
Name ad_cpm: Assumptions!$B$31
Name ad_impressions_base: Assumptions!$B$32
Name adoption_max: Assumptions!$B$18
Name adoption_midpoint: Assumptions!$B$19
Name adoption_steepness: Assumptions!$B$20
Name ap_days: Assumptions!$B$71
Name ar_days: Assumptions!$B$70
Name audit_fee: Assumptions!$B$34
Name base_year: Assumptions!$B$6
Name bhxh_rate: Assumptions!$B$62
Name bizops_floor: Assumptions!$B$83
Name capex_backend: 'Initial Investment'!$B$5
Name capex_cloud_setup: 'Initial Investment'!$B$4
Name capex_contingency: 'Initial Investment'!$B$13
Name capex_data_platform: 'Initial Investment'!$B$7
Name capex_devops: 'Initial Investment'!$B$11
Name capex_frontend: 'Initial Investment'!$B$6
Name capex_integration: 'Initial Investment'!$B$10
Name capex_maintenance_pct: Assumptions!$B$39
Name capex_security_setup: 'Initial Investment'!$B$8
Name capex_testing: 'Initial Investment'!$B$12
Name capex_total: 'Initial Investment'!$B$15
Name capex_ux_design: 'Initial Investment'!$B$9
Name cert_fee_escalation: Assumptions!$B$27
Name cert_fee_yr1: Assumptions!$B$26
Name churn_rate: Assumptions!$B$22
Name cit_rate: Assumptions!$B$67
Name cloud_elasticity: Assumptions!$B$82
Name cloud_gmv_factor: Assumptions!$B$77
Name cloud_per_1M_vcr: Assumptions!$B$43
Name daas_price: Assumptions!$B$30
Name depreciation_years: Assumptions!$B$69
Name discount_rate: Assumptions!$B$68
Name ecom_growth_rate: Assumptions!$B$14
Name ecom_market_base: Assumptions!$B$13
Name hr_bizops_per_100_ent: Assumptions!$B$81
Name marketing_growth: Assumptions!$B$41
Name mkt_efficiency_per_100: Assumptions!$B$78
Name opex_branding: Assumptions!$B$47
Name opex_cloud_base: Assumptions!$B$42
Name opex_contingency_pct: Assumptions!$B$53
Name opex_external: Assumptions!$B$45
Name opex_legal: Assumptions!$B$46
Name opex_marketing: Assumptions!$B$40
Name opex_partner_mgmt: Assumptions!$B$52
Name opex_pilot_eval: Assumptions!$B$49
Name opex_security: Assumptions!$B$48
Name opex_support_per_ent: Assumptions!$B$51
Name payment_proc_pct: Assumptions!$B$50
Name pilot_count: Assumptions!$B$21
Name platform_market_share: Assumptions!$B$29
Name recruit_cost_pct: Assumptions!$B$63
Name salary_bizops: Assumptions!$B$59
Name salary_data: Assumptions!$B$60
Name salary_dev: Assumptions!$B$58
Name salary_escalation: Assumptions!$B$61
Name salary_mgmt: Assumptions!$B$57
Name SAM_enterprises: Assumptions!$B$12
Name stage2_gate: Assumptions!$B$72
Name start_month: Assumptions!$B$7

Sheet Guide
A1: VISIT VIETNAM — FINANCIAL MODEL v6 — HƯỚNG DẪN TOÀN DIỆN
A2: v6.1 | 2026-03-21 | Revenue timing + cascading relationships + sensitivity + 55 named ranges
A4: 1. DANH SÁCH CÁC SHEET (14 sheets)
A5: Sheet | B5: Mục đích | C5: Ghi chú quan trọng
A6: Guide | B6: Hướng dẫn toàn diện: thuật ngữ, công thức, cách dùng | C6: Đọc trước khi dùng mô hình
A7: Assumptions | B7: 55 named ranges — TẤT CẢ đầu vào tập trung tại đây | C7: Chỉ sửa ô vàng (nền vàng, chữ xanh)
A8: Initial Investment | B8: 10 hạng mục CAPEX → named range capex_total = 5,280 Tr VND | C8: Khấu hao 5 năm đường thẳng
A9: HR Plan | B9: 4 bộ phận × 42 kỳ. BizOps tự scale theo số DN | C9: Lương = hc × salary × (1+esc)^yr × (1+bhxh)
A10: Market Sizing | B10: S-curve tăng trưởng DN + 6 hàng tham chiếu thời gian | C10: Year fraction tính từ base_year + start_month
A11: Revenue Schedule | B11: 6 nguồn DT. Tất cả gated bởi months_to_first_revenue | C11: =0 trước khi đạt tháng bắt đầu doanh thu
A12: Cost Schedule | B12: CAPEX + OPEX (10 mục + dự phòng). Cloud scales theo GMV | C12: Marketing giảm hiệu quả theo DN, Support economies of scale
A13: P&L | B13: DT → Giá vốn → LN gộp → OPEX → EBITDA → KH → Thuế TNDN → LN ròng | C13: CIT 20% chỉ khi EBIT > 0
A14: Cash Flow | B14: ĐTHĐ + ĐTĐT → DTTD + Lũy kế. Vốn lưu động qua ar_days | C14: OCF + ICF = FCF
A15: DCF & Returns | B15: FCF theo năm, NPV, IRR, ROI, đốt tiền max | C15: NPV = NPV(discount_rate, FCF)
A16: Sensitivity | B16: 235 ô NPV tính sẵn: 1-at-a-time + 3 bảng 2 chiều | C16: Tất cả dùng named ranges, tự cập nhật
A17: Scenarios | B17: 5 kịch bản + giải thích yếu tố ảnh hưởng + mô tả chi tiết | C17: Copy giá trị vào Assumptions để thử
A18: Budget 2025 | B18: Ngân sách tháng 7-12/2025 chi tiết | C18: Dùng cho phê duyệt ngân sách
A19: Budget 2026 | B19: Ngân sách tháng 1-12/2026 chi tiết | C19: Dùng cho phê duyệt ngân sách
A21: 2. CÁCH SỬ DỤNG (8 bước)
A22: Bước | B22: Hành động | C22: Chi tiết
A23: Bước 1 | B23: Mở sheet Assumptions | C23: Đây là nơi DUY NHẤT bạn cần sửa
A24: Bước 2 | B24: Sửa ô vàng (nền vàng, chữ xanh) | C24: Ô trắng = công thức, KHÔNG sửa
A25: Bước 3 | B25: Đặt months_to_first_revenue | C25: 0 = DT ngay tháng đầu, 3 = 3 tháng setup, 6 = nửa năm
A26: Bước 4 | B26: Kiểm tra P&L | C26: Xem các năm nào lỗ, năm nào lãi
A27: Bước 5 | B27: Kiểm tra Cash Flow | C27: Xem dòng tiền lũy kế, đốt tiền max
A28: Bước 6 | B28: Kiểm tra DCF & Returns | C28: NPV dương = dự án tạo giá trị, IRR > WACC = đáng đầu tư
A29: Bước 7 | B29: Xem Sensitivity | C29: Biết tham số nào ảnh hưởng NPV nhiều nhất
A30: Bước 8 | B30: Thử kịch bản | C30: Copy giá trị từ Scenarios vào Assumptions → xem kết quả
A32: 3. QUY ƯỚC Ô (Cell Color Convention)
A33: Màu nền / chữ | B33: Ý nghĩa | C33: Hành động
A34: Nền VÀNG + chữ XANH | B34: Đầu vào (placeholder) — giá trị bạn có thể thay đổi | C34: SỬA giá trị tại đây
A35: Nền XANH LÁ + chữ ĐEN ĐẬM | B35: Tổng / Subtotal — công thức SUM hoặc tổng hợp | C35: KHÔNG sửa
A36: Nền XANH ĐẬM + chữ TRẮNG | B36: Tiêu đề cột hoặc mục | C36: KHÔNG sửa
A37: Nền TRẮNG + chữ ĐEN | B37: Công thức tính toán — tự cập nhật | C37: KHÔNG sửa
A38: Nền XANH NHẠT + chữ ĐẬM | B38: Tiêu đề phần (section header) | C38: KHÔNG sửa
A39: Nền VÀNG NHẠT + chữ NÂU | B39: Tham số quan hệ cascading | C39: SỬA được
A41: 4. DANH SÁCH NAMED RANGES (55 tham số)
A42: Named Range | B42: Mô tả + Giá trị mặc định | C42: Công thức sử dụng (ví dụ)
A43: THỜI GIAN
A44: base_year | B44: Năm gốc = 2025 | C44: Year frac = base_year + (start_month-1+idx)/12
A45: start_month | B45: Tháng bắt đầu = 7 (Tháng 7) | C45: Cùng base_year tính year fraction
A46: months_to_first_revenue | B46: Tháng setup trước DT = 3 (DT từ tháng 10/2025) | C46: IF(idx >= months_to_first_revenue, revenue, 0)
A47: THỊ TRƯỜNG
A48: TAM_enterprises | B48: Tổng DN du lịch VN = 40,000 | C48: Tham khảo, không dùng trực tiếp
A49: SAM_enterprises | B49: DN phục vụ được = 15,000 | C49: Tham khảo, adoption_max < SAM
A50: ecom_market_base | B50: TMĐT du lịch gốc = 82,500 Tỷ VND | C50: ecom × (1+growth)^yr = thị trường tương lai
A51: ecom_growth_rate | B51: Tăng trưởng TMĐT = 8%/năm | C51: ecom_market_base × (1+rate)^years
A52: ĐƯỜNG CONG S
A53: adoption_max | B53: Trần DN = 1,200 (#1 driver) | C53: max/(1+EXP(-steepness*(year-midpoint)))
A54: adoption_midpoint | B54: Năm uốn = 2028 | C54: Điểm tăng nhanh nhất trên S-curve
A55: adoption_steepness | B55: Hệ số dốc = 0.9 | C55: Cao hơn = tăng nhanh hơn quanh midpoint
A56: pilot_count | B56: DN thí điểm = 15 | C56: =MAX(pilot_count, S_curve_result)
A57: churn_rate | B57: Tỷ lệ rời bỏ = 20%/năm (#3 driver) | C57: churned = gross × churn / div
A58: GIÁ DỊCH VỤ
A59: cert_fee_yr1 | B59: Phí chứng nhận = 25 Tr/DN/năm | C59: net × cert × (1+esc)^yr / div
A60: cert_fee_escalation | B60: Tăng phí = 5%/năm | C60: Compound: (1+0.05)^5 = tăng 28% sau 5 năm
A61: tx_take_rate | B61: Hoa hồng GD = 2% GMV | C61: ecom × market_share × take_rate × 1000
A62: platform_market_share | B62: Thị phần GMV = 0.5% (#2 driver) | C62: Chỉ áp dụng khi net_ent ≥ stage2_gate
A63: daas_price | B63: Giá DaaS = 30 Tr/triệu VCR | C63: VCR_millions × daas_price
A64: ad_cpm | B64: CPM quảng cáo = 150K VND | C64: impressions × ent × CPM / 1000
A65: ad_impressions_base | B65: Lượt QC/tháng = 500K | C65: Nhân với số DN và số tháng
A66: training_fee | B66: Phí đào tạo = 15 Tr/phiên | C66: net × training_pct × fee / div
A67: audit_fee | B67: Phí kiểm toán = 10 Tr | C67: net × audit_fee / div
A68: training_pct | B68: % DN mua ĐT = 30% | C68: Tỷ lệ cross-sell
A69: CHI PHÍ
A70: capex_maintenance_pct | B70: Bảo trì = 18% CAPEX/năm | C70: capex_total × 0.18 / div (từ 2026)
A71: opex_marketing | B71: Marketing gốc = 7,000 Tr/năm | C71: mkt × (1+growth)^yr × efficiency_factor / div
A72: marketing_growth | B72: Tăng marketing = 15%/năm | C72: Compound growth applied annually
A73: opex_cloud_base | B73: Cloud gốc = 3,250 Tr/năm | C73: cloud/div + VCR×per_1M + GMV×gmv_factor
A74: cloud_per_1M_vcr | B74: Cloud biến đổi = 8 Tr/triệu VCR | C74: Tỷ lệ theo traffic
A75: vcr_per_enterprise | B75: VCR/DN/tháng = 10,000 bản ghi | C75: net_ent × vcr × months / 1M = VCR_millions
A76: opex_external | B76: Đối ngoại = 400 Tr/năm | C76: Chia đều theo kỳ: 400/div
A77: opex_legal | B77: Pháp lý = 240 Tr/năm | C77: Chia đều theo kỳ: 240/div
A78: opex_branding | B78: Thương hiệu = 4,000 Tr/năm | C78: Chia đều: 4000/div
A79: opex_security | B79: Bảo mật = 250 Tr/năm | C79: Chia đều: 250/div
A80: opex_pilot_eval | B80: Thí điểm = 200 Tr (chỉ giai đoạn setup) | C80: Chỉ khi idx < months_to_first_revenue
A81: payment_proc_pct | B81: Phí cổng TT = 2.5% | C81: COGS = tx_revenue × 2.5%
... A84: opex_contingency_pct | B84: Dự phòng = 10% OPEX | C84: Buffer: OPEX_sub × 10%
A85: NHÂN SỰ
A86: salary_mgmt | B86: Lương QL = 45 Tr/tháng | C86: hc × 45 × months × (1+esc)^yr × (1+bhxh)
A87: salary_dev | B87: Lương PT = 35 Tr/tháng | C87: Tương tự salary_mgmt
A88: salary_bizops | B88: Lương VH = 20 Tr/tháng | C88: BizOps hc scales theo DN
A89: salary_data | B89: Lương DL = 40 Tr/tháng | C89: Tương tự salary_mgmt
A90: salary_escalation | B90: Tăng lương = 10%/năm | C90: (1+0.10)^years = compound
A91: bhxh_rate | B91: BHXH phần DN = 21.5% | C91: BHXH 17.5% + BHYT 3% + BHTN 1%
A92: recruit_cost_pct | B92: Phí tuyển = 20% lương năm | C92: new_hire × 30 × 12 × 20%
A93: TÀI CHÍNH
A94: cit_rate | B94: Thuế TNDN = 20% | C94: IF(EBIT>0, -EBIT×20%, 0)
A95: discount_rate | B95: WACC = 15% | C95: NPV(15%, FCF_array)
A96: depreciation_years | B96: Khấu hao = 5 năm | C96: capex_total / 5 / div per period
A97: ar_days | B97: Phải thu = 45 ngày | C97: Working capital = ΔRevenue × 45/365
A98: ap_days | B98: Phải trả = 30 ngày | C98: Hiện chưa dùng trong model
A99: stage2_gate | B99: Ngưỡng GĐ2 = 300 DN | C99: IF(net ≥ 300, Stage2_revenue, 0)
A100: QUAN HỆ CASCADING
A101: cloud_gmv_factor | B101: Cloud/Bn GMV = 0.5 Tr | C101: Cloud += ecom × share × 0.5
A102: mkt_efficiency_per_100 | B102: Giảm mkt/100 DN = 2% | C102: mkt × MAX(0.5, 1 - ent×2%/100)
A103: support_scale_threshold | B103: Ngưỡng economies = 500 DN | C103: IF(ent>500, cost×0.7, cost)
A104: support_discount | B104: Giảm support = 30% | C104: Khi > 500 DN: support × (1-0.3)
A105: hr_bizops_per_100_ent | B105: BizOps/100 DN = 2.0 | C105: MAX(floor, ent × 2 / 100)
A106: cloud_elasticity | B106: Elasticity cloud = 1.2 | C106: VCR × (ent/100)^0.2 = super-linear
...

Sheet Assumptions
A1: VISIT VIETNAM — FINANCIAL MODEL v6 — ASSUMPTIONS
A2: v6.1 | Revenue timing control + cascading relationships + 55 named ranges
A4: TIMING
A5: Parameter | B5: Value | C5: Unit | D5: Notes
A6: Base year | B6: 2025 | C6: Year | D6: Project start year
A7: Start month | B7: 7 | C7: Month | D7: July=7
A9: MARKET DATA
A10: Parameter | B10: Value | C10: Unit | D10: Notes
A11: Total tourism enterprises | B11: 40000 | D11: GSO/VNAT
A12: Serviceable enterprises | B12: 15000 | D12: Digitally active
A13: E-commerce tourism market (base yr) | B13: 82500 | C13: Bn VND | D13: e-Conomy SEA
A14: E-tourism YoY growth | B14: 0.08 | C14: % | D14: Historical
A16: ADOPTION S-CURVE
A17: Parameter | B17: Value | C17: Unit | D17: Notes
A18: Maximum enterprises (ceiling) | B18: 1200 | D18: S-curve asymptote (v3: was 3000)
A19: Midpoint year | B19: 2028 | C19: Year | D19: Inflection point
A20: Steepness factor | B20: 0.9 | D20: v3: was 1.2
A21: Starting enterprises | B21: 15 | D21: Pilot partners
A22: Annual non-renewal rate | B22: 0.2 | C22: % | D22: v3: was 0.15
A24: PRICING
A25: Parameter | B25: Value | C25: Unit | D25: Notes
A26: Certification fee/enterprise/yr | B26: 25 | C26: M VND | D26: v3: was 30M
A27: Cert fee annual increase | B27: 0.05 | C27: % | D27: v3: was 0.08
A28: Transaction fee (% of GMV) | B28: 0.02 | C28: % | D28: Platform commission
A29: % e-tourism GMV via VV | B29: 0.02 | C29: % | D29: v3: was 0.02
A30: DaaS price per M VCR | B30: 30 | C30: M VND | D30: v3: was 50
A31: Advertising CPM | B31: 150 | C31: K VND | D31: B2B benchmark
A32: Monthly impressions (K) | B32: 500 | C32: K | D32: Scales w/ enterprises
A33: Training fee per engagement | B33: 15 | C33: M VND | D33: NEW stream
A34: Audit fee per certification | B34: 10 | C34: M VND | D34: NEW stream
A35: % enterprises buying training | B35: 0.3 | C35: % | D35: Estimated
A37: COST PARAMETERS
A38: Parameter | B38: Value | C38: Unit | D38: Notes
A39: Maintenance (% of CAPEX/yr) | B39: 0.18 | C39: % | D39: Industry 15-20%
A40: Marketing (annual base) | B40: 7000 | C40: M VND | D40: v3: was 6000
A41: Marketing annual growth | B41: 0.15 | C41: % | D41: v3: was 0.10
A42: Cloud base (annual) | B42: 3250 | C42: M VND | D42: From original data
A43: Cloud cost per M VCR | B43: 8 | C43: M VND | D43: v3: was 5
A44: VCR per enterprise/month | B44: 10000 | C44: records | D44: Traffic estimate
A45: External affairs (annual) | B45: 400 | C45: M VND | D45: Current data
A46: Legal & compliance (annual) | B46: 240 | C46: M VND | D46: Current data
A47: Branding & events (annual) | B47: 4000 | C47: M VND | D47: Current data
A48: Security/pentest (annual) | B48: 250 | C48: M VND | D48: Current data
A49: Pilot evaluation (Y1 only) | B49: 200 | C49: M VND | D49: One-time
A50: Payment gateway fee | B50: 0.025 | C50: % | D50: COGS on tx revenue
... A53: Contingency (% total OPEX) | B53: 0.1 | C53: % | D53: Buffer
A55: HR PARAMETERS
A56: Parameter | B56: Value | C56: Unit | D56: Notes
A57: Avg monthly — Management | B57: 45 | C57: M VND | D57: Director/PM
A58: Avg monthly — Development | B58: 35 | C58: M VND | D58: Engineers
A59: Avg monthly — BizOps | B59: 20 | C59: M VND | D59: BD/support
A60: Avg monthly — Data/Analytics | B60: 40 | C60: M VND | D60: Data eng
A61: Annual salary increase | B61: 0.1 | C61: % | D61: VN market
A62: Social insurance (employer) | B62: 0.215 | C62: % | D62: BHXH+BHYT+BHTN
A63: Recruitment fee (% Y1 sal) | B63: 0.2 | C63: % | D63: Headhunter
A65: FINANCIAL PARAMETERS
A66: Parameter | B66: Value | C66: Unit | D66: Notes
A67: Corporate income tax | B67: 0.2 | C67: % | D67: Vietnamese law
A68: Discount rate (WACC) | B68: 0.15 | C68: % | D68: v3: was 0.12
A69: Depreciation period | B69: 5 | C69: Years | D69: Straight-line
A70: Accounts receivable days | B70: 45 | C70: Days | D70: Collection period
A71: Accounts payable days | B71: 30 | C71: Days | D71: Payment terms
A72: Stage 2 gate (min enterprises) | B72: 300 | D72: Activate tx fees
A75: CASCADING RELATIONSHIPS (how assumptions affect each other)
A76: Parameter | B76: Value | C76: Unit | D76: Cascade logic
A77: Cloud cost per Bn VND GMV processed | B77: 0.5 | C77: Tr VND/Bn | D77: ↑ market_share → ↑ GMV → ↑ cloud cost. Formula: GMV × this factor
A78: Marketing cost reduction per 100 enterprises | B78: 0.02 | C78: %/100 ent | D78: ↑ adoption → ↓ marketing/ent. Formula: marketing × MAX(0.5, 1 - ent×factor/100)
A79: Enterprises threshold for economies of scale | B79: 500 | C79: enterprises | D79: When net_ent > threshold → support cost drops by support_discount
A80: Support cost reduction after threshold | B80: 0.3 | C80: ratio | D80: ↑ ent past threshold → support/ent × (1 - discount). Economies of scale.
A81: BizOps staff needed per 100 enterprises (floor) | B81: 2 | C81: people/100 | D81: ↑ adoption → ↑ BizOps needed. Floor = MAX(manual_hc, ent×ratio/100)
A82: Cloud cost elasticity to enterprise count | B82: 1.2 | C82: factor | D82: VCR cost scales by ent^elasticity instead of linear. >1 = super-linear.
A83: BizOps minimum floor headcount | B83: 2 | C83: people | D83: MIN BizOps before scaling kicks in
A85: IMPACT MAP — How market_share cascades to costs
A86: adoption_max ↑ | B86: → net_enterprises ↑ | C86: → HR BizOps headcount ↑ (hr_bizops_per_100_ent) | D86: → HR Cost ↑
C87: → VCR volume ↑ (vcr_per_enterprise × net_ent) | D87: → Cloud Cost ↑ (cloud_per_1M_vcr)
C88: → Support demand ↑ (opex_support_per_ent × net_ent) | D88: → OPEX ↑
C89: → Marketing efficiency ↑ (cost/ent decreases) | D89: → Per-unit OPEX ↓
C90: → Cert/Training/Audit revenue ↑ | D90: → Revenue ↑
A92: platform_market_share ↑ | B92: → GMV through platform ↑ | C92: → Transaction fees ↑ (tx_take_rate × GMV) | D92: → Revenue ↑
C93: → Cloud processing load ↑ (cloud_gmv_factor × GMV) | D93: → Cloud Cost ↑
C94: → Payment processing fees ↑ (payment_proc_pct × tx_rev) | D94: → COGS ↑
C95: → DaaS & Ads potential ↑ | D95: → Revenue ↑
A97: churn_rate ↑ | B97: → net_enterprises ↓ | C97: → All enterprise-linked revenue ↓ | D97: → Revenue ↓
C98: → Need more new sales to replace | D98: → Marketing cost pressure ↑
C99: → Support & HR needs more stable | D99: → Cost stays high vs falling revenue
A101: REVENUE TIMING
A102: Parameter | B102: Value | C102: Unit | D102: Notes
A103: Months before first revenue | B103: 3 | C103: months | D103: 0=revenue from day 1, 3=3 months setup (Oct 2025), 6=Jan 2026
A104: Revenue active flag formula | B104: Used in Revenue/Cost sheets | D104: IF(period_idx >= months_to_first_revenue, 1, 0) — auto gate for all revenue

Sheet Initial Investment
A1: INITIAL INVESTMENT — CAPEX BREAKDOWN (M VND)
A3: CAPEX Item | B3: Amount (M VND) | C3: Timing | D3: Notes
A4: Cloud infrastructure setup | B4: 800 | C4: H2 2025 | D4: AWS/GCP initial
A5: Backend development | B5: 1200 | C5: H2 2025 | D5: API, DB, core
A6: Frontend + mobile | B6: 900 | C6: H2 2025 | D6: Web + mobile
A7: Data platform | B7: 600 | C7: H2 2025 | D7: Pipeline, analytics
A8: Security infrastructure | B8: 250 | C8: H2 2025 | D8: Pentest, auth
A9: UX/UI design | B9: 350 | C9: H2 2025 | D9: Design system
A10: 3rd-party integrations | B10: 400 | C10: H2 2025 | D10: Payment, OTA APIs
A11: DevOps & CI/CD | B11: 280 | C11: H2 2025 | D11: Deploy pipeline
A12: QA & testing | B12: 200 | C12: H2 2025 | D12: Auto + load test
A13: CAPEX contingency (10%) | B13: 300 | C13: H2 2025 | D13: Buffer
A15: TOTAL INITIAL CAPEX | B15: =SUM(B4:B13)
A17: DEPRECIATION SCHEDULE
A18: Year | B18: Annual D&A | C18: Accum D&A | D18: Net Book Value
A19: 2025 | B19: =capex_total/depreciation_years | C19: =B19 | D19: =capex_total-C19
A20: 2026 | B20: =capex_total/depreciation_years | C20: =C19+B20 | D20: =capex_total-C20
A21: 2027 | B21: =capex_total/depreciation_years | C21: =C20+B21 | D21: =capex_total-C21
A22: 2028 | B22: =capex_total/depreciation_years | C22: =C21+B22 | D22: =capex_total-C22
A23: 2029 | B23: =capex_total/depreciation_years | C23: =C22+B23 | D23: =capex_total-C23
A24: 2030 | B24: =0 | C24: =C23+B24 | D24: =capex_total-C24

Sheet HR Plan
A1: HR PLAN — HEADCOUNT & COST
A3: Dept / Item | B3: Unit | C3: Jul 2025 | D3: Aug 2025 | E3: Sep 2025 | F3: Oct 2025 | G3: Nov 2025 | H3: Dec 2025 | I3: Jan 2026 | J3: Feb 2026 | K3: Mar 2026 | L3: Apr 2026 | M3: May 2026 | N3: Jun 2026 | O3: Jul 2026 | P3: Aug 2026 | Q3: Sep 2026 | R3: Oct 2026 | S3: Nov 2026 | T3: Dec 2026 | U3: Jan 2027 | V3: Feb 2027 | W3: Mar 2027 | X3: Apr 2027 | Y3: May 2027 | Z3: Jun 2027 | AA3: Jul 2027 | AB3: Aug 2027 | AC3: Sep 2027 | AD3: Oct 2027 | AE3: Nov 2027 | AF3: Dec 2027 | AG3: Q1 2028 | AH3: Q2 2028 | AI3: Q3 2028 | AJ3: Q4 2028 | AK3: Q1 2029 | AL3: Q2 2029 | AM3: Q3 2029 | AN3: Q4 2029 | AO3: Q1 2030 | AP3: Q2 2030 | AQ3: Q3 2030 | AR3: Q4 2030
A4: HEADCOUNT
A5: Management | B5: people | C5: 2 | D5: 2 | E5: 2 | F5: 2 | G5: 2 | H5: 2 | I5: 2 | J5: 2 | K5: 2 | L5: 2 | M5: 2 | N5: 2 | O5: 2 | P5: 2 | Q5: 2 | R5: 2 | S5: 2 | T5: 2 | U5: 3 | V5: 3 | W5: 3 | X5: 3 | Y5: 3 | Z5: 3 | AA5: 3 | AB5: 3 | AC5: 3 | AD5: 3 | AE5: 3 | AF5: 3 | AG5: 3 | AH5: 3 | AI5: 3 | AJ5: 3 | AK5: 4 | AL5: 4 | AM5: 4 | AN5: 4 | AO5: 4 | AP5: 4 | AQ5: 4 | AR5: 4
A6: Development | B6: people | C6: 12 | D6: 12 | E6: 12 | F6: 12 | G6: 12 | H6: 12 | I6: 12 | J6: 12 | K6: 12 | L6: 12 | M6: 12 | N6: 12 | O6: 12 | P6: 12 | Q6: 12 | R6: 12 | S6: 12 | T6: 12 | U6: 14 | V6: 14 | W6: 14 | X6: 14 | Y6: 14 | Z6: 14 | AA6: 14 | AB6: 14 | AC6: 14 | AD6: 14 | AE6: 14 | AF6: 14 | AG6: 16 | AH6: 16 | AI6: 16 | AJ6: 16 | AK6: 18 | AL6: 18 | AM6: 18 | AN6: 18 | AO6: 20 | AP6: 20 | AQ6: 20 | AR6: 20
A7: Biz Ops (scaled) | B7: people | C7: =MAX(bizops_floor,ROUND('Market Sizing'!C15*hr_bizops_per_100_ent/100,0)) | D7: =MAX(bizops_floor,ROUND('Market Sizing'!D15*hr_bizops_per_100_ent/100,0)) | E7: =MAX(bizops_floor,ROUND('Market Sizing'!E15*hr_bizops_per_100_ent/100,0)) | F7: =MAX(bizops_floor,ROUND('Market Sizing'!F15*hr_bizops_per_100_ent/100,0)) | G7: =MAX(bizops_floor,ROUND('Market Sizing'!G15*hr_bizops_per_100_ent/100,0)) | H7: =MAX(bizops_floor,ROUND('Market Sizing'!H15*hr_bizops_per_100_ent/100,0)) | I7: =MAX(bizops_floor,ROUND('Market Sizing'!I15*hr_bizops_per_100_ent/100,0)) | J7: =MAX(bizops_floor,ROUND('Market Sizing'!J15*hr_bizops_per_100_ent/100,0)) | ... AR7: =MAX(bizops_floor,ROUND('Market Sizing'!AR15*hr_bizops_per_100_ent/100,0))
A8: Data & Analytics | B8: people | C8: 0 | D8: 0 | E8: 0 | F8: 0 | G8: 0 | H8: 0 | I8: 2 | J8: 2 | K8: 2 | L8: 2 | M8: 2 | N8: 2 | O8: 2 | P8: 2 | Q8: 2 | R8: 2 | S8: 2 | T8: 2 | U8: 3 | V8: 3 | W8: 3 | X8: 3 | Y8: 3 | Z8: 3 | AA8: 3 | AB8: 3 | AC8: 3 | AD8: 3 | AE8: 3 | AF8: 3 | AG8: 4 | AH8: 4 | AI8: 4 | AJ8: 4 | AK8: 5 | AL8: 5 | AM8: 5 | AN8: 5 | AO8: 6 | AP8: 6 | AQ8: 6 | AR8: 6
A9: TOTAL HEADCOUNT | B9: people | C9: =C5+C6+C7+C8 | D9: =D5+D6+D7+D8 | E9: =E5+E6+E7+E8 | F9: =F5+F6+F7+F8 | G9: =G5+G6+G7+G8 | H9: =H5+H6+H7+H8 | I9: =I5+I6+I7+I8 | J9: =J5+J6+J7+J8 | ... AR9: =AR5+AR6+AR7+AR8
A11: NEW HIRES
A12: New hires | B12: people | C12: =C9 | D12: =MAX(0,D9-C9) | E12: =MAX(0,E9-D9) | F12: =MAX(0,F9-E9) | G12: =MAX(0,G9-F9) | H12: =MAX(0,H9-G9) | I12: =MAX(0,I9-H9) | J12: =MAX(0,J9-I9) | K12: =MAX(0,K9-J9) | ... AR12: =MAX(0,AR9-AQ9)
A14: SALARY COST (M VND)
A15: Management cost | B15: M VND | C15: =C5*salary_mgmt*1*(1+salary_escalation)^0*(1+bhxh_rate) | D15: =D5*salary_mgmt*1*(1+salary_escalation)^0*(1+bhxh_rate) | E15: =E5*salary_mgmt*1*(1+salary_escalation)^0*(1+bhxh_rate) | F15: =F5*salary_mgmt*1*(1+salary_escalation)^0*(1+bhxh_rate) | G15: =G5*salary_mgmt*1*(1+salary_escalation)^0*(1+bhxh_rate) | H15: =H5*salary_mgmt*1*(1+salary_escalation)^0*(1+bhxh_rate) | I15: =I5*salary_mgmt*1*(1+salary_escalation)^1*(1+bhxh_rate) | J15: =J5*salary_mgmt*1*(1+salary_escalation)^1*(1+bhxh_rate) | K15: =K5*salary_mgmt*1*(1+salary_escalation)^1*(1+bhxh_rate) | L15: =L5*salary_mgmt*1*(1+salary_escalation)^1*(1+bhxh_rate) | M15: =M5*salary_mgmt*1*(1+salary_escalation)^1*(1+bhxh_rate) | N15: =N5*salary_mgmt*1*(1+salary_escalation)^1*(1+bhxh_rate) | O15: =O5*salary_mgmt*1*(1+salary_escalation)^1*(1+bhxh_rate) | P15: =P5*salary_mgmt*1*(1+salary_escalation)^1*(1+bhxh_rate) | ... T15: =T5*salary_mgmt*1*(1+salary_escalation)^1*(1+bhxh_rate) | U15: =U5*salary_mgmt*1*(1+salary_escalation)^2*(1+bhxh_rate) | V15: =V5*salary_mgmt*1*(1+salary_escalation)^2*(1+bhxh_rate) | W15: =W5*salary_mgmt*1*(1+salary_escalation)^2*(1+bhxh_rate) | X15: =X5*salary_mgmt*1*(1+salary_escalation)^2*(1+bhxh_rate) | Y15: =Y5*salary_mgmt*1*(1+salary_escalation)^2*(1+bhxh_rate) | Z15: =Z5*salary_mgmt*1*(1+salary_escalation)^2*(1+bhxh_rate) | AA15: =AA5*salary_mgmt*1*(1+salary_escalation)^2*(1+bhxh_rate) | AB15: =AB5*salary_mgmt*1*(1+salary_escalation)^2*(1+bhxh_rate) | ... AF15: =AF5*salary_mgmt*1*(1+salary_escalation)^2*(1+bhxh_rate) | AG15: =AG5*salary_mgmt*3*(1+salary_escalation)^3*(1+bhxh_rate) | AH15: =AH5*salary_mgmt*3*(1+salary_escalation)^3*(1+bhxh_rate) | AI15: =AI5*salary_mgmt*3*(1+salary_escalation)^3*(1+bhxh_rate) | AJ15: =AJ5*salary_mgmt*3*(1+salary_escalation)^3*(1+bhxh_rate) | AK15: =AK5*salary_mgmt*3*(1+salary_escalation)^4*(1+bhxh_rate) | AL15: =AL5*salary_mgmt*3*(1+salary_escalation)^4*(1+bhxh_rate) | AM15: =AM5*salary_mgmt*3*(1+salary_escalation)^4*(1+bhxh_rate) | AN15: =AN5*salary_mgmt*3*(1+salary_escalation)^4*(1+bhxh_rate) | AO15: =AO5*salary_mgmt*3*(1+salary_escalation)^5*(1+bhxh_rate) | AP15: =AP5*salary_mgmt*3*(1+salary_escalation)^5*(1+bhxh_rate) | AQ15: =AQ5*salary_mgmt*3*(1+salary_escalation)^5*(1+bhxh_rate) | AR15: =AR5*salary_mgmt*3*(1+salary_escalation)^5*(1+bhxh_rate)
A16: Development cost | B16: M VND | C16: =C6*salary_dev*1*(1+salary_escalation)^0*(1+bhxh_rate) | D16: =D6*salary_dev*1*(1+salary_escalation)^0*(1+bhxh_rate) | E16: =E6*salary_dev*1*(1+salary_escalation)^0*(1+bhxh_rate) | F16: =F6*salary_dev*1*(1+salary_escalation)^0*(1+bhxh_rate) | G16: =G6*salary_dev*1*(1+salary_escalation)^0*(1+bhxh_rate) | H16: =H6*salary_dev*1*(1+salary_escalation)^0*(1+bhxh_rate) | I16: =I6*salary_dev*1*(1+salary_escalation)^1*(1+bhxh_rate) | J16: =J6*salary_dev*1*(1+salary_escalation)^1*(1+bhxh_rate) | K16: =K6*salary_dev*1*(1+salary_escalation)^1*(1+bhxh_rate) | L16: =L6*salary_dev*1*(1+salary_escalation)^1*(1+bhxh_rate) | M16: =M6*salary_dev*1*(1+salary_escalation)^1*(1+bhxh_rate) | N16: =N6*salary_dev*1*(1+salary_escalation)^1*(1+bhxh_rate) | O16: =O6*salary_dev*1*(1+salary_escalation)^1*(1+bhxh_rate) | P16: =P6*salary_dev*1*(1+salary_escalation)^1*(1+bhxh_rate) | ... T16: =T6*salary_dev*1*(1+salary_escalation)^1*(1+bhxh_rate) | U16: =U6*salary_dev*1*(1+salary_escalation)^2*(1+bhxh_rate) | V16: =V6*salary_dev*1*(1+salary_escalation)^2*(1+bhxh_rate) | W16: =W6*salary_dev*1*(1+salary_escalation)^2*(1+bhxh_rate) | X16: =X6*salary_dev*1*(1+salary_escalation)^2*(1+bhxh_rate) | Y16: =Y6*salary_dev*1*(1+salary_escalation)^2*(1+bhxh_rate) | Z16: =Z6*salary_dev*1*(1+salary_escalation)^2*(1+bhxh_rate) | AA16: =AA6*salary_dev*1*(1+salary_escalation)^2*(1+bhxh_rate) | AB16: =AB6*salary_dev*1*(1+salary_escalation)^2*(1+bhxh_rate) | ... AF16: =AF6*salary_dev*1*(1+salary_escalation)^2*(1+bhxh_rate) | AG16: =AG6*salary_dev*3*(1+salary_escalation)^3*(1+bhxh_rate) | AH16: =AH6*salary_dev*3*(1+salary_escalation)^3*(1+bhxh_rate) | AI16: =AI6*salary_dev*3*(1+salary_escalation)^3*(1+bhxh_rate) | AJ16: =AJ6*salary_dev*3*(1+salary_escalation)^3*(1+bhxh_rate) | AK16: =AK6*salary_dev*3*(1+salary_escalation)^4*(1+bhxh_rate) | AL16: =AL6*salary_dev*3*(1+salary_escalation)^4*(1+bhxh_rate) | AM16: =AM6*salary_dev*3*(1+salary_escalation)^4*(1+bhxh_rate) | AN16: =AN6*salary_dev*3*(1+salary_escalation)^4*(1+bhxh_rate) | AO16: =AO6*salary_dev*3*(1+salary_escalation)^5*(1+bhxh_rate) | AP16: =AP6*salary_dev*3*(1+salary_escalation)^5*(1+bhxh_rate) | AQ16: =AQ6*salary_dev*3*(1+salary_escalation)^5*(1+bhxh_rate) | AR16: =AR6*salary_dev*3*(1+salary_escalation)^5*(1+bhxh_rate)
A17: Biz Ops cost | B17: M VND | C17: =C7*salary_bizops*1*(1+salary_escalation)^0*(1+bhxh_rate) | D17: =D7*salary_bizops*1*(1+salary_escalation)^0*(1+bhxh_rate) | E17: =E7*salary_bizops*1*(1+salary_escalation)^0*(1+bhxh_rate) | F17: =F7*salary_bizops*1*(1+salary_escalation)^0*(1+bhxh_rate) | G17: =G7*salary_bizops*1*(1+salary_escalation)^0*(1+bhxh_rate) | H17: =H7*salary_bizops*1*(1+salary_escalation)^0*(1+bhxh_rate) | I17: =I7*salary_bizops*1*(1+salary_escalation)^1*(1+bhxh_rate) | J17: =J7*salary_bizops*1*(1+salary_escalation)^1*(1+bhxh_rate) | K17: =K7*salary_bizops*1*(1+salary_escalation)^1*(1+bhxh_rate) | L17: =L7*salary_bizops*1*(1+salary_escalation)^1*(1+bhxh_rate) | M17: =M7*salary_bizops*1*(1+salary_escalation)^1*(1+bhxh_rate) | N17: =N7*salary_bizops*1*(1+salary_escalation)^1*(1+bhxh_rate) | O17: =O7*salary_bizops*1*(1+salary_escalation)^1*(1+bhxh_rate) | P17: =P7*salary_bizops*1*(1+salary_escalation)^1*(1+bhxh_rate) | ... T17: =T7*salary_bizops*1*(1+salary_escalation)^1*(1+bhxh_rate) | U17: =U7*salary_bizops*1*(1+salary_escalation)^2*(1+bhxh_rate) | V17: =V7*salary_bizops*1*(1+salary_escalation)^2*(1+bhxh_rate) | W17: =W7*salary_bizops*1*(1+salary_escalation)^2*(1+bhxh_rate) | X17: =X7*salary_bizops*1*(1+salary_escalation)^2*(1+bhxh_rate) | Y17: =Y7*salary_bizops*1*(1+salary_escalation)^2*(1+bhxh_rate) | Z17: =Z7*salary_bizops*1*(1+salary_escalation)^2*(1+bhxh_rate) | AA17: =AA7*salary_bizops*1*(1+salary_escalation)^2*(1+bhxh_rate) | AB17: =AB7*salary_bizops*1*(1+salary_escalation)^2*(1+bhxh_rate) | ... AF17: =AF7*salary_bizops*1*(1+salary_escalation)^2*(1+bhxh_rate) | AG17: =AG7*salary_bizops*3*(1+salary_escalation)^3*(1+bhxh_rate) | AH17: =AH7*salary_bizops*3*(1+salary_escalation)^3*(1+bhxh_rate) | AI17: =AI7*salary_bizops*3*(1+salary_escalation)^3*(1+bhxh_rate) | AJ17: =AJ7*salary_bizops*3*(1+salary_escalation)^3*(1+bhxh_rate) | AK17: =AK7*salary_bizops*3*(1+salary_escalation)^4*(1+bhxh_rate) | AL17: =AL7*salary_bizops*3*(1+salary_escalation)^4*(1+bhxh_rate) | AM17: =AM7*salary_bizops*3*(1+salary_escalation)^4*(1+bhxh_rate) | AN17: =AN7*salary_bizops*3*(1+salary_escalation)^4*(1+bhxh_rate) | AO17: =AO7*salary_bizops*3*(1+salary_escalation)^5*(1+bhxh_rate) | AP17: =AP7*salary_bizops*3*(1+salary_escalation)^5*(1+bhxh_rate) | AQ17: =AQ7*salary_bizops*3*(1+salary_escalation)^5*(1+bhxh_rate) | AR17: =AR7*salary_bizops*3*(1+salary_escalation)^5*(1+bhxh_rate)
A18: Data & Analytics cost | B18: M VND | C18: =C8*salary_data*1*(1+salary_escalation)^0*(1+bhxh_rate) | D18: =D8*salary_data*1*(1+salary_escalation)^0*(1+bhxh_rate) | E18: =E8*salary_data*1*(1+salary_escalation)^0*(1+bhxh_rate) | F18: =F8*salary_data*1*(1+salary_escalation)^0*(1+bhxh_rate) | G18: =G8*salary_data*1*(1+salary_escalation)^0*(1+bhxh_rate) | H18: =H8*salary_data*1*(1+salary_escalation)^0*(1+bhxh_rate) | I18: =I8*salary_data*1*(1+salary_escalation)^1*(1+bhxh_rate) | J18: =J8*salary_data*1*(1+salary_escalation)^1*(1+bhxh_rate) | K18: =K8*salary_data*1*(1+salary_escalation)^1*(1+bhxh_rate) | L18: =L8*salary_data*1*(1+salary_escalation)^1*(1+bhxh_rate) | M18: =M8*salary_data*1*(1+salary_escalation)^1*(1+bhxh_rate) | N18: =N8*salary_data*1*(1+salary_escalation)^1*(1+bhxh_rate) | O18: =O8*salary_data*1*(1+salary_escalation)^1*(1+bhxh_rate) | P18: =P8*salary_data*1*(1+salary_escalation)^1*(1+bhxh_rate) | ... T18: =T8*salary_data*1*(1+salary_escalation)^1*(1+bhxh_rate) | U18: =U8*salary_data*1*(1+salary_escalation)^2*(1+bhxh_rate) | V18: =V8*salary_data*1*(1+salary_escalation)^2*(1+bhxh_rate) | W18: =W8*salary_data*1*(1+salary_escalation)^2*(1+bhxh_rate) | X18: =X8*salary_data*1*(1+salary_escalation)^2*(1+bhxh_rate) | Y18: =Y8*salary_data*1*(1+salary_escalation)^2*(1+bhxh_rate) | Z18: =Z8*salary_data*1*(1+salary_escalation)^2*(1+bhxh_rate) | AA18: =AA8*salary_data*1*(1+salary_escalation)^2*(1+bhxh_rate) | AB18: =AB8*salary_data*1*(1+salary_escalation)^2*(1+bhxh_rate) | ... AF18: =AF8*salary_data*1*(1+salary_escalation)^2*(1+bhxh_rate) | AG18: =AG8*salary_data*3*(1+salary_escalation)^3*(1+bhxh_rate) | AH18: =AH8*salary_data*3*(1+salary_escalation)^3*(1+bhxh_rate) | AI18: =AI8*salary_data*3*(1+salary_escalation)^3*(1+bhxh_rate) | AJ18: =AJ8*salary_data*3*(1+salary_escalation)^3*(1+bhxh_rate) | AK18: =AK8*salary_data*3*(1+salary_escalation)^4*(1+bhxh_rate) | AL18: =AL8*salary_data*3*(1+salary_escalation)^4*(1+bhxh_rate) | AM18: =AM8*salary_data*3*(1+salary_escalation)^4*(1+bhxh_rate) | AN18: =AN8*salary_data*3*(1+salary_escalation)^4*(1+bhxh_rate) | AO18: =AO8*salary_data*3*(1+salary_escalation)^5*(1+bhxh_rate) | AP18: =AP8*salary_data*3*(1+salary_escalation)^5*(1+bhxh_rate) | AQ18: =AQ8*salary_data*3*(1+salary_escalation)^5*(1+bhxh_rate) | AR18: =AR8*salary_data*3*(1+salary_escalation)^5*(1+bhxh_rate)
A19: TOTAL SALARY | B19: M VND | C19: =C15+C16+C17+C18 | D19: =D15+D16+D17+D18 | E19: =E15+E16+E17+E18 | F19: =F15+F16+F17+F18 | G19: =G15+G16+G17+G18 | H19: =H15+H16+H17+H18 | I19: =I15+I16+I17+I18 | J19: =J15+J16+J17+J18 | ... AR19: =AR15+AR16+AR17+AR18
A20: Recruitment | B20: M VND | C20: =C12*30*12*recruit_cost_pct | D20: =D12*30*12*recruit_cost_pct | E20: =E12*30*12*recruit_cost_pct | F20: =F12*30*12*recruit_cost_pct | G20: =G12*30*12*recruit_cost_pct | H20: =H12*30*12*recruit_cost_pct | I20: =I12*30*12*recruit_cost_pct | J20: =J12*30*12*recruit_cost_pct | ... AR20: =AR12*30*12*recruit_cost_pct
A21: TOTAL HR COST | B21: M VND | C21: =C19+C20 | D21: =D19+D20 | E21: =E19+E20 | F21: =F19+F20 | G21: =G19+G20 | H21: =H19+H20 | I21: =I19+I20 | J21: =J19+J20 | ... AR21: =AR19+AR20

Sheet Market Sizing
A1: MARKET SIZING & ADOPTION
A3: Period index | B3: idx | C3: 0 | D3: 1 | E3: 2 | F3: 3 | G3: 4 | H3: 5 | I3: 6 | J3: 7 | K3: 8 | L3: 9 | M3: 10 | N3: 11 | O3: 12 | P3: 13 | Q3: 14 | R3: 15 | S3: 16 | T3: 17 | U3: 18 | V3: 19 | W3: 20 | X3: 21 | Y3: 22 | Z3: 23 | AA3: 24 | AB3: 25 | AC3: 26 | AD3: 27 | AE3: 28 | AF3: 29 | AG3: 30 | AH3: 31 | AI3: 32 | AJ3: 33 | AK3: 34 | AL3: 35 | AM3: 36 | AN3: 37 | AO3: 38 | AP3: 39 | AQ3: 40 | AR3: 41
A4: Year fraction | B4: year | C4: =base_year+(start_month-1+C3)/12 | D4: =base_year+(start_month-1+D3)/12 | E4: =base_year+(start_month-1+E3)/12 | F4: =base_year+(start_month-1+F3)/12 | G4: =base_year+(start_month-1+G3)/12 | H4: =base_year+(start_month-1+H3)/12 | I4: =base_year+(start_month-1+I3)/12 | J4: =base_year+(start_month-1+J3)/12 | ... AF4: =base_year+(start_month-1+AF3)/12 | AG4: =2028+(1-0.5)/12 | AH4: =2028+(4-0.5)/12 | AI4: =2028+(7-0.5)/12 | AJ4: =2028+(10-0.5)/12 | AK4: =2028+(13-0.5)/12 | AL4: =2028+(16-0.5)/12 | AM4: =2028+(19-0.5)/12 | AN4: =2028+(22-0.5)/12 | AO4: =2028+(25-0.5)/12 | AP4: =2028+(28-0.5)/12 | AQ4: =2028+(31-0.5)/12 | AR4: =2028+(34-0.5)/12
A5: Years from base | B5: yrs | C5: =FLOOR(C4-base_year,1) | D5: =FLOOR(D4-base_year,1) | E5: =FLOOR(E4-base_year,1) | F5: =FLOOR(F4-base_year,1) | G5: =FLOOR(G4-base_year,1) | H5: =FLOOR(H4-base_year,1) | I5: =FLOOR(I4-base_year,1) | J5: =FLOOR(J4-base_year,1) | ... AR5: =FLOOR(AR4-base_year,1)
A6: Period divisor | B6: div | C6: 12 | D6: 12 | E6: 12 | F6: 12 | G6: 12 | H6: 12 | I6: 12 | J6: 12 | K6: 12 | L6: 12 | M6: 12 | N6: 12 | O6: 12 | P6: 12 | Q6: 12 | R6: 12 | S6: 12 | T6: 12 | U6: 12 | V6: 12 | W6: 12 | X6: 12 | Y6: 12 | Z6: 12 | AA6: 12 | AB6: 12 | AC6: 12 | AD6: 12 | AE6: 12 | AF6: 12 | AG6: 4 | AH6: 4 | AI6: 4 | AJ6: 4 | AK6: 4 | AL6: 4 | AM6: 4 | AN6: 4 | AO6: 4 | AP6: 4 | AQ6: 4 | AR6: 4
A7: Months in period | B7: mon | C7: 1 | D7: 1 | E7: 1 | F7: 1 | G7: 1 | H7: 1 | I7: 1 | J7: 1 | K7: 1 | L7: 1 | M7: 1 | N7: 1 | O7: 1 | P7: 1 | Q7: 1 | R7: 1 | S7: 1 | T7: 1 | U7: 1 | V7: 1 | W7: 1 | X7: 1 | Y7: 1 | Z7: 1 | AA7: 1 | AB7: 1 | AC7: 1 | AD7: 1 | AE7: 1 | AF7: 1 | AG7: 3 | AH7: 3 | AI7: 3 | AJ7: 3 | AK7: 3 | AL7: 3 | AM7: 3 | AN7: 3 | AO7: 3 | AP7: 3 | AQ7: 3 | AR7: 3
A9: Metric | B9: Unit | C9: Jul 2025 | D9: Aug 2025 | E9: Sep 2025 | F9: Oct 2025 | G9: Nov 2025 | H9: Dec 2025 | I9: Jan 2026 | J9: Feb 2026 | K9: Mar 2026 | L9: Apr 2026 | M9: May 2026 | N9: Jun 2026 | O9: Jul 2026 | P9: Aug 2026 | Q9: Sep 2026 | R9: Oct 2026 | S9: Nov 2026 | T9: Dec 2026 | U9: Jan 2027 | V9: Feb 2027 | W9: Mar 2027 | X9: Apr 2027 | Y9: May 2027 | Z9: Jun 2027 | AA9: Jul 2027 | AB9: Aug 2027 | AC9: Sep 2027 | AD9: Oct 2027 | AE9: Nov 2027 | AF9: Dec 2027 | AG9: Q1 2028 | AH9: Q2 2028 | AI9: Q3 2028 | AJ9: Q4 2028 | AK9: Q1 2029 | AL9: Q2 2029 | AM9: Q3 2029 | AN9: Q4 2029 | AO9: Q1 2030 | AP9: Q2 2030 | AQ9: Q3 2030 | AR9: Q4 2030
A10: E-commerce tourism market | B10: Bn VND | C10: =ecom_market_base*(1+ecom_growth_rate)^C5/C6 | D10: =ecom_market_base*(1+ecom_growth_rate)^D5/D6 | E10: =ecom_market_base*(1+ecom_growth_rate)^E5/E6 | F10: =ecom_market_base*(1+ecom_growth_rate)^F5/F6 | G10: =ecom_market_base*(1+ecom_growth_rate)^G5/G6 | H10: =ecom_market_base*(1+ecom_growth_rate)^H5/H6 | I10: =ecom_market_base*(1+ecom_growth_rate)^I5/I6 | J10: =ecom_market_base*(1+ecom_growth_rate)^J5/J6 | ... AR10: =ecom_market_base*(1+ecom_growth_rate)^AR5/AR6
A12: S-CURVE ADOPTION
A13: Gross enterprises | B13: cnt | C13: =MAX(pilot_count,adoption_max/(1+EXP(-adoption_steepness*(C4-adoption_midpoint)))) | D13: =MAX(pilot_count,adoption_max/(1+EXP(-adoption_steepness*(D4-adoption_midpoint)))) | E13: =MAX(pilot_count,adoption_max/(1+EXP(-adoption_steepness*(E4-adoption_midpoint)))) | F13: =MAX(pilot_count,adoption_max/(1+EXP(-adoption_steepness*(F4-adoption_midpoint)))) | G13: =MAX(pilot_count,adoption_max/(1+EXP(-adoption_steepness*(G4-adoption_midpoint)))) | H13: =MAX(pilot_count,adoption_max/(1+EXP(-adoption_steepness*(H4-adoption_midpoint)))) | I13: =MAX(pilot_count,adoption_max/(1+EXP(-adoption_steepness*(I4-adoption_midpoint)))) | J13: =MAX(pilot_count,adoption_max/(1+EXP(-adoption_steepness*(J4-adoption_midpoint)))) | ... AR13: =MAX(pilot_count,adoption_max/(1+EXP(-adoption_steepness*(AR4-adoption_midpoint))))
A14: Churned | B14: cnt | C14: =0 | D14: =ROUND(D13*churn_rate/D6,0) | E14: =ROUND(E13*churn_rate/E6,0) | F14: =ROUND(F13*churn_rate/F6,0) | G14: =ROUND(G13*churn_rate/G6,0) | H14: =ROUND(H13*churn_rate/H6,0) | I14: =ROUND(I13*churn_rate/I6,0) | J14: =ROUND(J13*churn_rate/J6,0) | K14: =ROUND(K13*churn_rate/K6,0) | ... AR14: =ROUND(AR13*churn_rate/AR6,0)
A15: Net active enterprises | B15: cnt | C15: =C13-C14 | D15: =D13-D14 | E15: =E13-E14 | F15: =F13-F14 | G15: =G13-G14 | H15: =H13-H14 | I15: =I13-I14 | J15: =J13-J14 | ... AR15: =AR13-AR14
A16: New enterprises | B16: cnt | C16: =C15 | D16: =MAX(0,D15-C15) | E16: =MAX(0,E15-D15) | F16: =MAX(0,F15-E15) | G16: =MAX(0,G15-F15) | H16: =MAX(0,H15-G15) | I16: =MAX(0,I15-H15) | J16: =MAX(0,J15-I15) | K16: =MAX(0,K15-J15) | ... AR16: =MAX(0,AR15-AQ15)
A17: VCR (M records) | B17: M | C17: =C15*vcr_per_enterprise*C7/1000000 | D17: =D15*vcr_per_enterprise*D7/1000000 | E17: =E15*vcr_per_enterprise*E7/1000000 | F17: =F15*vcr_per_enterprise*F7/1000000 | G17: =G15*vcr_per_enterprise*G7/1000000 | H17: =H15*vcr_per_enterprise*H7/1000000 | I17: =I15*vcr_per_enterprise*I7/1000000 | J17: =J15*vcr_per_enterprise*J7/1000000 | ... AR17: =AR15*vcr_per_enterprise*AR7/1000000

Sheet Revenue Schedule
A1: REVENUE SCHEDULE (M VND)
A3: Item | B3: Unit | C3: Jul 2025 | D3: Aug 2025 | E3: Sep 2025 | F3: Oct 2025 | G3: Nov 2025 | H3: Dec 2025 | I3: Jan 2026 | J3: Feb 2026 | K3: Mar 2026 | L3: Apr 2026 | M3: May 2026 | N3: Jun 2026 | O3: Jul 2026 | P3: Aug 2026 | Q3: Sep 2026 | R3: Oct 2026 | S3: Nov 2026 | T3: Dec 2026 | U3: Jan 2027 | V3: Feb 2027 | W3: Mar 2027 | X3: Apr 2027 | Y3: May 2027 | Z3: Jun 2027 | AA3: Jul 2027 | AB3: Aug 2027 | AC3: Sep 2027 | AD3: Oct 2027 | AE3: Nov 2027 | AF3: Dec 2027 | AG3: Q1 2028 | AH3: Q2 2028 | AI3: Q3 2028 | AJ3: Q4 2028 | AK3: Q1 2029 | AL3: Q2 2029 | AM3: Q3 2029 | AN3: Q4 2029 | AO3: Q1 2030 | AP3: Q2 2030 | AQ3: Q3 2030 | AR3: Q4 2030
A4: STAGE 1
A5: Certification fees | B5: M VND | C5: =IF('Market Sizing'!C3>=months_to_first_revenue,1,0)*'Market Sizing'!C15*cert_fee_yr1*(1+cert_fee_escalation)^'Market Sizing'!C5/'Market Sizing'!C6 | D5: =IF('Market Sizing'!D3>=months_to_first_revenue,1,0)*'Market Sizing'!D15*cert_fee_yr1*(1+cert_fee_escalation)^'Market Sizing'!D5/'Market Sizing'!D6 | E5: =IF('Market Sizing'!E3>=months_to_first_revenue,1,0)*'Market Sizing'!E15*cert_fee_yr1*(1+cert_fee_escalation)^'Market Sizing'!E5/'Market Sizing'!E6 | F5: =IF('Market Sizing'!F3>=months_to_first_revenue,1,0)*'Market Sizing'!F15*cert_fee_yr1*(1+cert_fee_escalation)^'Market Sizing'!F5/'Market Sizing'!F6 | G5: =IF('Market Sizing'!G3>=months_to_first_revenue,1,0)*'Market Sizing'!G15*cert_fee_yr1*(1+cert_fee_escalation)^'Market Sizing'!G5/'Market Sizing'!G6 | H5: =IF('Market Sizing'!H3>=months_to_first_revenue,1,0)*'Market Sizing'!H15*cert_fee_yr1*(1+cert_fee_escalation)^'Market Sizing'!H5/'Market Sizing'!H6 | I5: =IF('Market Sizing'!I3>=months_to_first_revenue,1,0)*'Market Sizing'!I15*cert_fee_yr1*(1+cert_fee_escalation)^'Market Sizing'!I5/'Market Sizing'!I6 | J5: =IF('Market Sizing'!J3>=months_to_first_revenue,1,0)*'Market Sizing'!J15*cert_fee_yr1*(1+cert_fee_escalation)^'Market Sizing'!J5/'Market Sizing'!J6 | ... AR5: =IF('Market Sizing'!AR3>=months_to_first_revenue,1,0)*'Market Sizing'!AR15*cert_fee_yr1*(1+cert_fee_escalation)^'Market Sizing'!AR5/'Market Sizing'!AR6
A6: Training | B6: M VND | C6: =IF('Market Sizing'!C3>=months_to_first_revenue,1,0)*'Market Sizing'!C15*training_pct*training_fee/'Market Sizing'!C6 | D6: =IF('Market Sizing'!D3>=months_to_first_revenue,1,0)*'Market Sizing'!D15*training_pct*training_fee/'Market Sizing'!D6 | E6: =IF('Market Sizing'!E3>=months_to_first_revenue,1,0)*'Market Sizing'!E15*training_pct*training_fee/'Market Sizing'!E6 | F6: =IF('Market Sizing'!F3>=months_to_first_revenue,1,0)*'Market Sizing'!F15*training_pct*training_fee/'Market Sizing'!F6 | G6: =IF('Market Sizing'!G3>=months_to_first_revenue,1,0)*'Market Sizing'!G15*training_pct*training_fee/'Market Sizing'!G6 | H6: =IF('Market Sizing'!H3>=months_to_first_revenue,1,0)*'Market Sizing'!H15*training_pct*training_fee/'Market Sizing'!H6 | I6: =IF('Market Sizing'!I3>=months_to_first_revenue,1,0)*'Market Sizing'!I15*training_pct*training_fee/'Market Sizing'!I6 | J6: =IF('Market Sizing'!J3>=months_to_first_revenue,1,0)*'Market Sizing'!J15*training_pct*training_fee/'Market Sizing'!J6 | ... AR6: =IF('Market Sizing'!AR3>=months_to_first_revenue,1,0)*'Market Sizing'!AR15*training_pct*training_fee/'Market Sizing'!AR6
A7: Audit fees | B7: M VND | C7: =IF('Market Sizing'!C3>=months_to_first_revenue,1,0)*'Market Sizing'!C15*audit_fee/'Market Sizing'!C6 | D7: =IF('Market Sizing'!D3>=months_to_first_revenue,1,0)*'Market Sizing'!D15*audit_fee/'Market Sizing'!D6 | E7: =IF('Market Sizing'!E3>=months_to_first_revenue,1,0)*'Market Sizing'!E15*audit_fee/'Market Sizing'!E6 | F7: =IF('Market Sizing'!F3>=months_to_first_revenue,1,0)*'Market Sizing'!F15*audit_fee/'Market Sizing'!F6 | G7: =IF('Market Sizing'!G3>=months_to_first_revenue,1,0)*'Market Sizing'!G15*audit_fee/'Market Sizing'!G6 | H7: =IF('Market Sizing'!H3>=months_to_first_revenue,1,0)*'Market Sizing'!H15*audit_fee/'Market Sizing'!H6 | I7: =IF('Market Sizing'!I3>=months_to_first_revenue,1,0)*'Market Sizing'!I15*audit_fee/'Market Sizing'!I6 | J7: =IF('Market Sizing'!J3>=months_to_first_revenue,1,0)*'Market Sizing'!J15*audit_fee/'Market Sizing'!J6 | ... AR7: =IF('Market Sizing'!AR3>=months_to_first_revenue,1,0)*'Market Sizing'!AR15*audit_fee/'Market Sizing'!AR6
A8: Subtotal Stage 1 | C8: =SUM(C5:C7) | D8: =SUM(D5:D7) | E8: =SUM(E5:E7) | F8: =SUM(F5:F7) | G8: =SUM(G5:G7) | H8: =SUM(H5:H7) | I8: =SUM(I5:I7) | J8: =SUM(J5:J7) | ... AR8: =SUM(AR5:AR7)
A10: STAGE 2 (gated)
A11: Transaction fees | B11: M VND | C11: =IF(AND(IF('Market Sizing'!C3>=months_to_first_revenue,1,0)=1,'Market Sizing'!C15>=stage2_gate),'Market Sizing'!C10*platform_market_share*tx_take_rate*1000,0) | D11: =IF(AND(IF('Market Sizing'!D3>=months_to_first_revenue,1,0)=1,'Market Sizing'!D15>=stage2_gate),'Market Sizing'!D10*platform_market_share*tx_take_rate*1000,0) | E11: =IF(AND(IF('Market Sizing'!E3>=months_to_first_revenue,1,0)=1,'Market Sizing'!E15>=stage2_gate),'Market Sizing'!E10*platform_market_share*tx_take_rate*1000,0) | F11: =IF(AND(IF('Market Sizing'!F3>=months_to_first_revenue,1,0)=1,'Market Sizing'!F15>=stage2_gate),'Market Sizing'!F10*platform_market_share*tx_take_rate*1000,0) | G11: =IF(AND(IF('Market Sizing'!G3>=months_to_first_revenue,1,0)=1,'Market Sizing'!G15>=stage2_gate),'Market Sizing'!G10*platform_market_share*tx_take_rate*1000,0) | H11: =IF(AND(IF('Market Sizing'!H3>=months_to_first_revenue,1,0)=1,'Market Sizing'!H15>=stage2_gate),'Market Sizing'!H10*platform_market_share*tx_take_rate*1000,0) | I11: =IF(AND(IF('Market Sizing'!I3>=months_to_first_revenue,1,0)=1,'Market Sizing'!I15>=stage2_gate),'Market Sizing'!I10*platform_market_share*tx_take_rate*1000,0) | J11: =IF(AND(IF('Market Sizing'!J3>=months_to_first_revenue,1,0)=1,'Market Sizing'!J15>=stage2_gate),'Market Sizing'!J10*platform_market_share*tx_take_rate*1000,0) | ... AR11: =IF(AND(IF('Market Sizing'!AR3>=months_to_first_revenue,1,0)=1,'Market Sizing'!AR15>=stage2_gate),'Market Sizing'!AR10*platform_market_share*tx_take_rate*1000,0)
A12: DaaS | B12: M VND | C12: =IF(AND(IF('Market Sizing'!C3>=months_to_first_revenue,1,0)=1,'Market Sizing'!C15>=stage2_gate),'Market Sizing'!C17*daas_price,0) | D12: =IF(AND(IF('Market Sizing'!D3>=months_to_first_revenue,1,0)=1,'Market Sizing'!D15>=stage2_gate),'Market Sizing'!D17*daas_price,0) | E12: =IF(AND(IF('Market Sizing'!E3>=months_to_first_revenue,1,0)=1,'Market Sizing'!E15>=stage2_gate),'Market Sizing'!E17*daas_price,0) | F12: =IF(AND(IF('Market Sizing'!F3>=months_to_first_revenue,1,0)=1,'Market Sizing'!F15>=stage2_gate),'Market Sizing'!F17*daas_price,0) | G12: =IF(AND(IF('Market Sizing'!G3>=months_to_first_revenue,1,0)=1,'Market Sizing'!G15>=stage2_gate),'Market Sizing'!G17*daas_price,0) | H12: =IF(AND(IF('Market Sizing'!H3>=months_to_first_revenue,1,0)=1,'Market Sizing'!H15>=stage2_gate),'Market Sizing'!H17*daas_price,0) | I12: =IF(AND(IF('Market Sizing'!I3>=months_to_first_revenue,1,0)=1,'Market Sizing'!I15>=stage2_gate),'Market Sizing'!I17*daas_price,0) | J12: =IF(AND(IF('Market Sizing'!J3>=months_to_first_revenue,1,0)=1,'Market Sizing'!J15>=stage2_gate),'Market Sizing'!J17*daas_price,0) | ... AR12: =IF(AND(IF('Market Sizing'!AR3>=months_to_first_revenue,1,0)=1,'Market Sizing'!AR15>=stage2_gate),'Market Sizing'!AR17*daas_price,0)
A13: Advertising | B13: M VND | C13: =IF(AND(IF('Market Sizing'!C3>=months_to_first_revenue,1,0)=1,'Market Sizing'!C15>=stage2_gate),ad_impressions_base*'Market Sizing'!C7*'Market Sizing'!C15/1000*ad_cpm/1000,0) | D13: =IF(AND(IF('Market Sizing'!D3>=months_to_first_revenue,1,0)=1,'Market Sizing'!D15>=stage2_gate),ad_impressions_base*'Market Sizing'!D7*'Market Sizing'!D15/1000*ad_cpm/1000,0) | E13: =IF(AND(IF('Market Sizing'!E3>=months_to_first_revenue,1,0)=1,'Market Sizing'!E15>=stage2_gate),ad_impressions_base*'Market Sizing'!E7*'Market Sizing'!E15/1000*ad_cpm/1000,0) | F13: =IF(AND(IF('Market Sizing'!F3>=months_to_first_revenue,1,0)=1,'Market Sizing'!F15>=stage2_gate),ad_impressions_base*'Market Sizing'!F7*'Market Sizing'!F15/1000*ad_cpm/1000,0) | G13: =IF(AND(IF('Market Sizing'!G3>=months_to_first_revenue,1,0)=1,'Market Sizing'!G15>=stage2_gate),ad_impressions_base*'Market Sizing'!G7*'Market Sizing'!G15/1000*ad_cpm/1000,0) | H13: =IF(AND(IF('Market Sizing'!H3>=months_to_first_revenue,1,0)=1,'Market Sizing'!H15>=stage2_gate),ad_impressions_base*'Market Sizing'!H7*'Market Sizing'!H15/1000*ad_cpm/1000,0) | I13: =IF(AND(IF('Market Sizing'!I3>=months_to_first_revenue,1,0)=1,'Market Sizing'!I15>=stage2_gate),ad_impressions_base*'Market Sizing'!I7*'Market Sizing'!I15/1000*ad_cpm/1000,0) | J13: =IF(AND(IF('Market Sizing'!J3>=months_to_first_revenue,1,0)=1,'Market Sizing'!J15>=stage2_gate),ad_impressions_base*'Market Sizing'!J7*'Market Sizing'!J15/1000*ad_cpm/1000,0) | ... AR13: =IF(AND(IF('Market Sizing'!AR3>=months_to_first_revenue,1,0)=1,'Market Sizing'!AR15>=stage2_gate),ad_impressions_base*'Market Sizing'!AR7*'Market Sizing'!AR15/1000*ad_cpm/1000,0)
A14: Subtotal Stage 2 | C14: =SUM(C11:C13) | D14: =SUM(D11:D13) | E14: =SUM(E11:E13) | F14: =SUM(F11:F13) | G14: =SUM(G11:G13) | H14: =SUM(H11:H13) | I14: =SUM(I11:I13) | J14: =SUM(J11:J13) | ... AR14: =SUM(AR11:AR13)
A16: TOTAL REVENUE | C16: =C8+C14 | D16: =D8+D14 | E16: =E8+E14 | F16: =F8+F14 | G16: =G8+G14 | H16: =H8+H14 | I16: =I8+I14 | J16: =J8+J14 | ... AR16: =AR8+AR14
A18: COGS
A19: Payment processing | B19: M VND | C19: =C11*payment_proc_pct | D19: =D11*payment_proc_pct | E19: =E11*payment_proc_pct | F19: =F11*payment_proc_pct | G19: =G11*payment_proc_pct | H19: =H11*payment_proc_pct | I19: =I11*payment_proc_pct | J19: =J11*payment_proc_pct | ... AR19: =AR11*payment_proc_pct
A20: TOTAL COGS | C20: =C19 | D20: =D19 | E20: =E19 | F20: =F19 | G20: =G19 | H20: =H19 | I20: =I19 | J20: =J19 | ... AR20: =AR19

Sheet Cost Schedule
A1: COST SCHEDULE (M VND)
A3: Item | B3: Unit | C3: Jul 2025 | D3: Aug 2025 | E3: Sep 2025 | F3: Oct 2025 | G3: Nov 2025 | H3: Dec 2025 | I3: Jan 2026 | J3: Feb 2026 | K3: Mar 2026 | L3: Apr 2026 | M3: May 2026 | N3: Jun 2026 | O3: Jul 2026 | P3: Aug 2026 | Q3: Sep 2026 | R3: Oct 2026 | S3: Nov 2026 | T3: Dec 2026 | U3: Jan 2027 | V3: Feb 2027 | W3: Mar 2027 | X3: Apr 2027 | Y3: May 2027 | Z3: Jun 2027 | AA3: Jul 2027 | AB3: Aug 2027 | AC3: Sep 2027 | AD3: Oct 2027 | AE3: Nov 2027 | AF3: Dec 2027 | AG3: Q1 2028 | AH3: Q2 2028 | AI3: Q3 2028 | AJ3: Q4 2028 | AK3: Q1 2029 | AL3: Q2 2029 | AM3: Q3 2029 | AN3: Q4 2029 | AO3: Q1 2030 | AP3: Q2 2030 | AQ3: Q3 2030 | AR3: Q4 2030
A4: CAPEX
A5: Platform dev | B5: M VND | C5: =capex_total/6 | D5: =capex_total/6 | E5: =capex_total/6 | F5: =capex_total/6 | G5: =capex_total/6 | H5: =capex_total/6 | I5: =0 | J5: =0 | K5: =0 | L5: =0 | M5: =0 | N5: =0 | O5: =0 | P5: =0 | ... AR5: =0
A6: Maintenance | B6: M VND | C6: =0 | D6: =0 | E6: =0 | F6: =0 | G6: =0 | H6: =0 | I6: =capex_total*capex_maintenance_pct/'Market Sizing'!I6 | J6: =capex_total*capex_maintenance_pct/'Market Sizing'!J6 | K6: =capex_total*capex_maintenance_pct/'Market Sizing'!K6 | L6: =capex_total*capex_maintenance_pct/'Market Sizing'!L6 | M6: =capex_total*capex_maintenance_pct/'Market Sizing'!M6 | N6: =capex_total*capex_maintenance_pct/'Market Sizing'!N6 | O6: =capex_total*capex_maintenance_pct/'Market Sizing'!O6 | P6: =capex_total*capex_maintenance_pct/'Market Sizing'!P6 | ... AR6: =capex_total*capex_maintenance_pct/'Market Sizing'!AR6
A7: TOTAL CAPEX | C7: =C5+C6 | D7: =D5+D6 | E7: =E5+E6 | F7: =F5+F6 | G7: =G5+G6 | H7: =H5+H6 | I7: =I5+I6 | J7: =J5+J6 | ... AR7: =AR5+AR6
A9: OPEX
A10: HR (from HR Plan) | B10: M VND | C10: ='HR Plan'!C21 | D10: ='HR Plan'!D21 | E10: ='HR Plan'!E21 | F10: ='HR Plan'!F21 | G10: ='HR Plan'!G21 | H10: ='HR Plan'!H21 | I10: ='HR Plan'!I21 | J10: ='HR Plan'!J21 | ... AR10: ='HR Plan'!AR21
A11: Marketing | B11: M VND | C11: =opex_marketing*(1+marketing_growth)^'Market Sizing'!C5/'Market Sizing'!C6*MAX(0.5,1-'Market Sizing'!C15*mkt_efficiency_per_100/100) | D11: =opex_marketing*(1+marketing_growth)^'Market Sizing'!D5/'Market Sizing'!D6*MAX(0.5,1-'Market Sizing'!D15*mkt_efficiency_per_100/100) | E11: =opex_marketing*(1+marketing_growth)^'Market Sizing'!E5/'Market Sizing'!E6*MAX(0.5,1-'Market Sizing'!E15*mkt_efficiency_per_100/100) | F11: =opex_marketing*(1+marketing_growth)^'Market Sizing'!F5/'Market Sizing'!F6*MAX(0.5,1-'Market Sizing'!F15*mkt_efficiency_per_100/100) | G11: =opex_marketing*(1+marketing_growth)^'Market Sizing'!G5/'Market Sizing'!G6*MAX(0.5,1-'Market Sizing'!G15*mkt_efficiency_per_100/100) | H11: =opex_marketing*(1+marketing_growth)^'Market Sizing'!H5/'Market Sizing'!H6*MAX(0.5,1-'Market Sizing'!H15*mkt_efficiency_per_100/100) | I11: =opex_marketing*(1+marketing_growth)^'Market Sizing'!I5/'Market Sizing'!I6*MAX(0.5,1-'Market Sizing'!I15*mkt_efficiency_per_100/100) | J11: =opex_marketing*(1+marketing_growth)^'Market Sizing'!J5/'Market Sizing'!J6*MAX(0.5,1-'Market Sizing'!J15*mkt_efficiency_per_100/100) | ... AR11: =opex_marketing*(1+marketing_growth)^'Market Sizing'!AR5/'Market Sizing'!AR6*MAX(0.5,1-'Market Sizing'!AR15*mkt_efficiency_per_100/100)
A12: Branding & events | B12: M VND | C12: =opex_branding/'Market Sizing'!C6 | D12: =opex_branding/'Market Sizing'!D6 | E12: =opex_branding/'Market Sizing'!E6 | F12: =opex_branding/'Market Sizing'!F6 | G12: =opex_branding/'Market Sizing'!G6 | H12: =opex_branding/'Market Sizing'!H6 | I12: =opex_branding/'Market Sizing'!I6 | J12: =opex_branding/'Market Sizing'!J6 | ... AR12: =opex_branding/'Market Sizing'!AR6
A13: Cloud & infra | B13: M VND | C13: =opex_cloud_base/'Market Sizing'!C6+'Market Sizing'!C17*cloud_per_1M_vcr*('Market Sizing'!C15/100)^(cloud_elasticity-1)+'Market Sizing'!C10*platform_market_share*cloud_gmv_factor | D13: =opex_cloud_base/'Market Sizing'!D6+'Market Sizing'!D17*cloud_per_1M_vcr*('Market Sizing'!D15/100)^(cloud_elasticity-1)+'Market Sizing'!D10*platform_market_share*cloud_gmv_factor | E13: =opex_cloud_base/'Market Sizing'!E6+'Market Sizing'!E17*cloud_per_1M_vcr*('Market Sizing'!E15/100)^(cloud_elasticity-1)+'Market Sizing'!E10*platform_market_share*cloud_gmv_factor | F13: =opex_cloud_base/'Market Sizing'!F6+'Market Sizing'!F17*cloud_per_1M_vcr*('Market Sizing'!F15/100)^(cloud_elasticity-1)+'Market Sizing'!F10*platform_market_share*cloud_gmv_factor | G13: =opex_cloud_base/'Market Sizing'!G6+'Market Sizing'!G17*cloud_per_1M_vcr*('Market Sizing'!G15/100)^(cloud_elasticity-1)+'Market Sizing'!G10*platform_market_share*cloud_gmv_factor | H13: =opex_cloud_base/'Market Sizing'!H6+'Market Sizing'!H17*cloud_per_1M_vcr*('Market Sizing'!H15/100)^(cloud_elasticity-1)+'Market Sizing'!H10*platform_market_share*cloud_gmv_factor | I13: =opex_cloud_base/'Market Sizing'!I6+'Market Sizing'!I17*cloud_per_1M_vcr*('Market Sizing'!I15/100)^(cloud_elasticity-1)+'Market Sizing'!I10*platform_market_share*cloud_gmv_factor | J13: =opex_cloud_base/'Market Sizing'!J6+'Market Sizing'!J17*cloud_per_1M_vcr*('Market Sizing'!J15/100)^(cloud_elasticity-1)+'Market Sizing'!J10*platform_market_share*cloud_gmv_factor | ... AR13: =opex_cloud_base/'Market Sizing'!AR6+'Market Sizing'!AR17*cloud_per_1M_vcr*('Market Sizing'!AR15/100)^(cloud_elasticity-1)+'Market Sizing'!AR10*platform_market_share*cloud_gmv_factor
A14: Security | B14: M VND | C14: =opex_security/'Market Sizing'!C6 | D14: =opex_security/'Market Sizing'!D6 | E14: =opex_security/'Market Sizing'!E6 | F14: =opex_security/'Market Sizing'!F6 | G14: =opex_security/'Market Sizing'!G6 | H14: =opex_security/'Market Sizing'!H6 | I14: =opex_security/'Market Sizing'!I6 | J14: =opex_security/'Market Sizing'!J6 | ... AR14: =opex_security/'Market Sizing'!AR6
A15: External affairs | B15: M VND | C15: =opex_external/'Market Sizing'!C6 | D15: =opex_external/'Market Sizing'!D6 | E15: =opex_external/'Market Sizing'!E6 | F15: =opex_external/'Market Sizing'!F6 | G15: =opex_external/'Market Sizing'!G6 | H15: =opex_external/'Market Sizing'!H6 | I15: =opex_external/'Market Sizing'!I6 | J15: =opex_external/'Market Sizing'!J6 | ... AR15: =opex_external/'Market Sizing'!AR6
A16: Legal & compliance | B16: M VND | C16: =opex_legal/'Market Sizing'!C6 | D16: =opex_legal/'Market Sizing'!D6 | E16: =opex_legal/'Market Sizing'!E6 | F16: =opex_legal/'Market Sizing'!F6 | G16: =opex_legal/'Market Sizing'!G6 | H16: =opex_legal/'Market Sizing'!H6 | I16: =opex_legal/'Market Sizing'!I6 | J16: =opex_legal/'Market Sizing'!J6 | ... AR16: =opex_legal/'Market Sizing'!AR6
A17: Pilot eval (Y1) | B17: M VND | C17: =IF('Market Sizing'!C3<months_to_first_revenue,opex_pilot_eval/'Market Sizing'!C6,0) | D17: =IF('Market Sizing'!D3<months_to_first_revenue,opex_pilot_eval/'Market Sizing'!D6,0) | E17: =IF('Market Sizing'!E3<months_to_first_revenue,opex_pilot_eval/'Market Sizing'!E6,0) | F17: =IF('Market Sizing'!F3<months_to_first_revenue,opex_pilot_eval/'Market Sizing'!F6,0) | G17: =IF('Market Sizing'!G3<months_to_first_revenue,opex_pilot_eval/'Market Sizing'!G6,0) | H17: =IF('Market Sizing'!H3<months_to_first_revenue,opex_pilot_eval/'Market Sizing'!H6,0) | I17: =IF('Market Sizing'!I3<months_to_first_revenue,opex_pilot_eval/'Market Sizing'!I6,0) | J17: =IF('Market Sizing'!J3<months_to_first_revenue,opex_pilot_eval/'Market Sizing'!J6,0) | ... AR17: =IF('Market Sizing'!AR3<months_to_first_revenue,opex_pilot_eval/'Market Sizing'!AR6,0)
A18: Partner mgmt | B18: M VND | C18: =opex_partner_mgmt/'Market Sizing'!C6 | D18: =opex_partner_mgmt/'Market Sizing'!D6 | E18: =opex_partner_mgmt/'Market Sizing'!E6 | F18: =opex_partner_mgmt/'Market Sizing'!F6 | G18: =opex_partner_mgmt/'Market Sizing'!G6 | H18: =opex_partner_mgmt/'Market Sizing'!H6 | I18: =opex_partner_mgmt/'Market Sizing'!I6 | J18: =opex_partner_mgmt/'Market Sizing'!J6 | ... AR18: =opex_partner_mgmt/'Market Sizing'!AR6
A19: Customer support | B19: M VND | C19: =IF('Market Sizing'!C3>=months_to_first_revenue,1,0)*'Market Sizing'!C15*opex_support_per_ent*IF('Market Sizing'!C15>support_scale_threshold,1-support_discount,1)/'Market Sizing'!C6 | D19: =IF('Market Sizing'!D3>=months_to_first_revenue,1,0)*'Market Sizing'!D15*opex_support_per_ent*IF('Market Sizing'!D15>support_scale_threshold,1-support_discount,1)/'Market Sizing'!D6 | E19: =IF('Market Sizing'!E3>=months_to_first_revenue,1,0)*'Market Sizing'!E15*opex_support_per_ent*IF('Market Sizing'!E15>support_scale_threshold,1-support_discount,1)/'Market Sizing'!E6 | F19: =IF('Market Sizing'!F3>=months_to_first_revenue,1,0)*'Market Sizing'!F15*opex_support_per_ent*IF('Market Sizing'!F15>support_scale_threshold,1-support_discount,1)/'Market Sizing'!F6 | G19: =IF('Market Sizing'!G3>=months_to_first_revenue,1,0)*'Market Sizing'!G15*opex_support_per_ent*IF('Market Sizing'!G15>support_scale_threshold,1-support_discount,1)/'Market Sizing'!G6 | H19: =IF('Market Sizing'!H3>=months_to_first_revenue,1,0)*'Market Sizing'!H15*opex_support_per_ent*IF('Market Sizing'!H15>support_scale_threshold,1-support_discount,1)/'Market Sizing'!H6 | I19: =IF('Market Sizing'!I3>=months_to_first_revenue,1,0)*'Market Sizing'!I15*opex_support_per_ent*IF('Market Sizing'!I15>support_scale_threshold,1-support_discount,1)/'Market Sizing'!I6 | J19: =IF('Market Sizing'!J3>=months_to_first_revenue,1,0)*'Market Sizing'!J15*opex_support_per_ent*IF('Market Sizing'!J15>support_scale_threshold,1-support_discount,1)/'Market Sizing'!J6 | ... AR19: =IF('Market Sizing'!AR3>=months_to_first_revenue,1,0)*'Market Sizing'!AR15*opex_support_per_ent*IF('Market Sizing'!AR15>support_scale_threshold,1-support_discount,1)/'Market Sizing'!AR6
A20: OPEX Subtotal | C20: =SUM(C10:C19) | D20: =SUM(D10:D19) | E20: =SUM(E10:E19) | F20: =SUM(F10:F19) | G20: =SUM(G10:G19) | H20: =SUM(H10:H19) | I20: =SUM(I10:I19) | J20: =SUM(J10:J19) | ... AR20: =SUM(AR10:AR19)
A21: Contingency | B21: M VND | C21: =C20*opex_contingency_pct | D21: =D20*opex_contingency_pct | E21: =E20*opex_contingency_pct | F21: =F20*opex_contingency_pct | G21: =G20*opex_contingency_pct | H21: =H20*opex_contingency_pct | I21: =I20*opex_contingency_pct | J21: =J20*opex_contingency_pct | ... AR21: =AR20*opex_contingency_pct
A22: TOTAL OPEX | C22: =C20+C21 | D22: =D20+D21 | E22: =E20+E21 | F22: =F20+F21 | G22: =G20+G21 | H22: =H20+H21 | I22: =I20+I21 | J22: =J20+J21 | ... AR22: =AR20+AR21
A24: TOTAL COSTS | C24: =C7+C22 | D24: =D7+D22 | E24: =E7+E22 | F24: =F7+F22 | G24: =G7+G22 | H24: =H7+H22 | I24: =I7+I22 | J24: =J7+J22 | ... AR24: =AR7+AR22

Sheet P&L
A1: P&L (M VND)
A3: Item | B3: Unit | C3: Jul 2025 | D3: Aug 2025 | E3: Sep 2025 | F3: Oct 2025 | G3: Nov 2025 | H3: Dec 2025 | I3: Jan 2026 | J3: Feb 2026 | K3: Mar 2026 | L3: Apr 2026 | M3: May 2026 | N3: Jun 2026 | O3: Jul 2026 | P3: Aug 2026 | Q3: Sep 2026 | R3: Oct 2026 | S3: Nov 2026 | T3: Dec 2026 | U3: Jan 2027 | V3: Feb 2027 | W3: Mar 2027 | X3: Apr 2027 | Y3: May 2027 | Z3: Jun 2027 | AA3: Jul 2027 | AB3: Aug 2027 | AC3: Sep 2027 | AD3: Oct 2027 | AE3: Nov 2027 | AF3: Dec 2027 | AG3: Q1 2028 | AH3: Q2 2028 | AI3: Q3 2028 | AJ3: Q4 2028 | AK3: Q1 2029 | AL3: Q2 2029 | AM3: Q3 2029 | AN3: Q4 2029 | AO3: Q1 2030 | AP3: Q2 2030 | AQ3: Q3 2030 | AR3: Q4 2030
A4: Revenue | C4: ='Revenue Schedule'!C16 | D4: ='Revenue Schedule'!D16 | E4: ='Revenue Schedule'!E16 | F4: ='Revenue Schedule'!F16 | G4: ='Revenue Schedule'!G16 | H4: ='Revenue Schedule'!H16 | I4: ='Revenue Schedule'!I16 | J4: ='Revenue Schedule'!J16 | ... AR4: ='Revenue Schedule'!AR16
A5: COGS | C5: =-'Revenue Schedule'!C20 | D5: =-'Revenue Schedule'!D20 | E5: =-'Revenue Schedule'!E20 | F5: =-'Revenue Schedule'!F20 | G5: =-'Revenue Schedule'!G20 | H5: =-'Revenue Schedule'!H20 | I5: =-'Revenue Schedule'!I20 | J5: =-'Revenue Schedule'!J20 | ... AR5: =-'Revenue Schedule'!AR20
A6: GROSS PROFIT | C6: =C4+C5 | D6: =D4+D5 | E6: =E4+E5 | F6: =F4+F5 | G6: =G4+G5 | H6: =H4+H5 | I6: =I4+I5 | J6: =J4+J5 | ... AR6: =AR4+AR5
A8: OPEX | C8: =-'Cost Schedule'!C22 | D8: =-'Cost Schedule'!D22 | E8: =-'Cost Schedule'!E22 | F8: =-'Cost Schedule'!F22 | G8: =-'Cost Schedule'!G22 | H8: =-'Cost Schedule'!H22 | I8: =-'Cost Schedule'!I22 | J8: =-'Cost Schedule'!J22 | ... AR8: =-'Cost Schedule'!AR22
A9: EBITDA | C9: =C6+C8 | D9: =D6+D8 | E9: =E6+E8 | F9: =F6+F8 | G9: =G6+G8 | H9: =H6+H8 | I9: =I6+I8 | J9: =J6+J8 | ... AR9: =AR6+AR8
A10: Depreciation | C10: =-capex_total/depreciation_years/'Market Sizing'!C6 | D10: =-capex_total/depreciation_years/'Market Sizing'!D6 | E10: =-capex_total/depreciation_years/'Market Sizing'!E6 | F10: =-capex_total/depreciation_years/'Market Sizing'!F6 | G10: =-capex_total/depreciation_years/'Market Sizing'!G6 | H10: =-capex_total/depreciation_years/'Market Sizing'!H6 | I10: =-capex_total/depreciation_years/'Market Sizing'!I6 | J10: =-capex_total/depreciation_years/'Market Sizing'!J6 | ... AN10: =-capex_total/depreciation_years/'Market Sizing'!AN6 | AO10: =0 | AP10: =0 | AQ10: =0 | AR10: =0
A11: EBIT | C11: =C9+C10 | D11: =D9+D10 | E11: =E9+E10 | F11: =F9+F10 | G11: =G9+G10 | H11: =H9+H10 | I11: =I9+I10 | J11: =J9+J10 | ... AR11: =AR9+AR10
A12: Tax (CIT) | C12: =IF(C11>0,-C11*cit_rate,0) | D12: =IF(D11>0,-D11*cit_rate,0) | E12: =IF(E11>0,-E11*cit_rate,0) | F12: =IF(F11>0,-F11*cit_rate,0) | G12: =IF(G11>0,-G11*cit_rate,0) | H12: =IF(H11>0,-H11*cit_rate,0) | I12: =IF(I11>0,-I11*cit_rate,0) | J12: =IF(J11>0,-J11*cit_rate,0) | ... AR12: =IF(AR11>0,-AR11*cit_rate,0)
A13: NET INCOME | C13: =C11+C12 | D13: =D11+D12 | E13: =E11+E12 | F13: =F11+F12 | G13: =G11+G12 | H13: =H11+H12 | I13: =I11+I12 | J13: =J11+J12 | ... AR13: =AR11+AR12
A15: MARGINS
A16: Gross margin | C16: =IF(C4=0,0,C6/C4) | D16: =IF(D4=0,0,D6/D4) | E16: =IF(E4=0,0,E6/E4) | F16: =IF(F4=0,0,F6/F4) | G16: =IF(G4=0,0,G6/G4) | H16: =IF(H4=0,0,H6/H4) | I16: =IF(I4=0,0,I6/I4) | J16: =IF(J4=0,0,J6/J4) | ... AR16: =IF(AR4=0,0,AR6/AR4)
A17: EBITDA margin | C17: =IF(C4=0,0,C9/C4) | D17: =IF(D4=0,0,D9/D4) | E17: =IF(E4=0,0,E9/E4) | F17: =IF(F4=0,0,F9/F4) | G17: =IF(G4=0,0,G9/G4) | H17: =IF(H4=0,0,H9/H4) | I17: =IF(I4=0,0,I9/I4) | J17: =IF(J4=0,0,J9/J4) | ... AR17: =IF(AR4=0,0,AR9/AR4)
A18: Net margin | C18: =IF(C4=0,0,C13/C4) | D18: =IF(D4=0,0,D13/D4) | E18: =IF(E4=0,0,E13/E4) | F18: =IF(F4=0,0,F13/F4) | G18: =IF(G4=0,0,G13/G4) | H18: =IF(H4=0,0,H13/H4) | I18: =IF(I4=0,0,I13/I4) | J18: =IF(J4=0,0,J13/J4) | ... AR18: =IF(AR4=0,0,AR13/AR4)

Sheet Cash Flow
A1: CASH FLOW (M VND)
A3: Item | B3: Unit | C3: Jul 2025 | D3: Aug 2025 | E3: Sep 2025 | F3: Oct 2025 | G3: Nov 2025 | H3: Dec 2025 | I3: Jan 2026 | J3: Feb 2026 | K3: Mar 2026 | L3: Apr 2026 | M3: May 2026 | N3: Jun 2026 | O3: Jul 2026 | P3: Aug 2026 | Q3: Sep 2026 | R3: Oct 2026 | S3: Nov 2026 | T3: Dec 2026 | U3: Jan 2027 | V3: Feb 2027 | W3: Mar 2027 | X3: Apr 2027 | Y3: May 2027 | Z3: Jun 2027 | AA3: Jul 2027 | AB3: Aug 2027 | AC3: Sep 2027 | AD3: Oct 2027 | AE3: Nov 2027 | AF3: Dec 2027 | AG3: Q1 2028 | AH3: Q2 2028 | AI3: Q3 2028 | AJ3: Q4 2028 | AK3: Q1 2029 | AL3: Q2 2029 | AM3: Q3 2029 | AN3: Q4 2029 | AO3: Q1 2030 | AP3: Q2 2030 | AQ3: Q3 2030 | AR3: Q4 2030
A4: Operating CF
A5: Net income | C5: ='P&L'!C13 | D5: ='P&L'!D13 | E5: ='P&L'!E13 | F5: ='P&L'!F13 | G5: ='P&L'!G13 | H5: ='P&L'!H13 | I5: ='P&L'!I13 | J5: ='P&L'!J13 | ... AR5: ='P&L'!AR13
A6: Add: D&A | C6: =-'P&L'!C10 | D6: =-'P&L'!D10 | E6: =-'P&L'!E10 | F6: =-'P&L'!F10 | G6: =-'P&L'!G10 | H6: =-'P&L'!H10 | I6: =-'P&L'!I10 | J6: =-'P&L'!J10 | ... AR6: =-'P&L'!AR10
A7: Working capital chg | C7: =-'P&L'!C4*ar_days/365 | D7: =-('P&L'!D4-'P&L'!C4)*ar_days/365 | E7: =-('P&L'!E4-'P&L'!D4)*ar_days/365 | F7: =-('P&L'!F4-'P&L'!E4)*ar_days/365 | G7: =-('P&L'!G4-'P&L'!F4)*ar_days/365 | H7: =-('P&L'!H4-'P&L'!G4)*ar_days/365 | I7: =-('P&L'!I4-'P&L'!H4)*ar_days/365 | J7: =-('P&L'!J4-'P&L'!I4)*ar_days/365 | K7: =-('P&L'!K4-'P&L'!J4)*ar_days/365 | ... AR7: =-('P&L'!AR4-'P&L'!AQ4)*ar_days/365
A8: OPERATING CF | C8: =C5+C6+C7 | D8: =D5+D6+D7 | E8: =E5+E6+E7 | F8: =F5+F6+F7 | G8: =G5+G6+G7 | H8: =H5+H6+H7 | I8: =I5+I6+I7 | J8: =J5+J6+J7 | ... AR8: =AR5+AR6+AR7
A10: Investing CF
A11: CAPEX | C11: =-'Cost Schedule'!C7 | D11: =-'Cost Schedule'!D7 | E11: =-'Cost Schedule'!E7 | F11: =-'Cost Schedule'!F7 | G11: =-'Cost Schedule'!G7 | H11: =-'Cost Schedule'!H7 | I11: =-'Cost Schedule'!I7 | J11: =-'Cost Schedule'!J7 | ... AR11: =-'Cost Schedule'!AR7
A12: INVESTING CF | C12: =C11 | D12: =D11 | E12: =E11 | F12: =F11 | G12: =G11 | H12: =H11 | I12: =I11 | J12: =J11 | ... AR12: =AR11
A14: FREE CASH FLOW | C14: =C8+C12 | D14: =D8+D12 | E14: =E8+E12 | F14: =F8+F12 | G14: =G8+G12 | H14: =H8+H12 | I14: =I8+I12 | J14: =J8+J12 | ... AR14: =AR8+AR12
A15: Cumulative CF | C15: =C14 | D15: =C15+D14 | E15: =D15+E14 | F15: =E15+F14 | G15: =F15+G14 | H15: =G15+H14 | I15: =H15+I14 | J15: =I15+J14 | K15: =J15+K14 | ... AR15: =AQ15+AR14

Sheet DCF & Returns
A1: DCF & RETURNS
A3: Annual FCF
A4: Year | B4: FCF (M VND)
A5: H2_2025 | B5: =SUM('Cash Flow'!C14:H14)
A6: Y2026 | B6: =SUM('Cash Flow'!I14:T14)
A7: Y2027 | B7: =SUM('Cash Flow'!U14:AF14)
A8: Y2028 | B8: =SUM('Cash Flow'!AG14:AJ14)
A9: Y2029 | B9: =SUM('Cash Flow'!AK14:AN14)
A10: Y2030 | B10: =SUM('Cash Flow'!AO14:AR14)
A12: Metrics
A13: NPV | B13: =NPV(discount_rate,B6:B10)+B5
A14: IRR | B14: =IFERROR(IRR(B5:B10),"N/A")
A15: Max cash burn | B15: =-MIN('Cash Flow'!C15:'Cash Flow'!AR15)
A16: ROI | B16: =IF(B15=0,0,('Cash Flow'!AR15+B15)/B15)
A17: CIT rate | B17: =cit_rate
A18: WACC | B18: =discount_rate

Sheet Sensitivity
A1: SENSITIVITY ANALYSIS — v6 (computed NPV)
A3: ONE-AT-A-TIME SENSITIVITY — Approximate NPV Impact (Tr VND)
A4: Parameter | B4: -30% | C4: -15% | D4: BASE | E4: +15% | F4: +30% | G4: Value @Base | H4: Impact ↑ or ↓
A5: Max enterprises (adoption_max) | B5: =((((adoption_max*0.7/(1+EXP(-adoption_steepness*(2028-adoption_midpoint)))*(1-churn_rate))*(cert_fee_yr1*(1+cert_fee_escalation)^2.5+training_pct*training_fee+audit_fee)*5)+(IF((adoption_max*0.7/(1+EXP(-adoption_steepness*(2028-adoption_midpoint)))*(1-churn_rate))>=stage2_gate,ecom_market_base*(1+ecom_growth_rate)^4*platform_market_share*tx_take_rate*1000*3,0))-((IF((adoption_max*0.7/(1+EXP(-adoption_steepness*(2028-adoption_midpoint)))*(1-churn_rate))>=stage2_gate,ecom_market_base*(1+ecom_growth_rate)^4*platform_market_share*tx_take_rate*1000*3,0))*payment_proc_pct)-(capex_total+(33*30*12*(1+bhxh_rate)*(1+salary_escalation)^2*5)+(opex_marketing*(1+marketing_growth)^2*5)+(opex_cloud_base*5+(adoption_max*0.7/(1+EXP(-adoption_steepness*(2028-adoption_midpoint)))*(1-churn_rate))*vcr_per_enterprise*12*cloud_per_1M_vcr/1000000*5)+((opex_branding+opex_external+opex_legal+opex_security+opex_partner_mgmt)*5)+(capex_total*capex_maintenance_pct*4)))*(1-cit_rate))/(1+discount_rate)^2.5 | C5: =((((adoption_max*0.85/(1+EXP(-adoption_steepness*(2028-adoption_midpoint)))*(1-churn_rate))*(cert_fee_yr1*(1+cert_fee_escalation)^2.5+training_pct*training_fee+audit_fee)*5)+(IF((adoption_max*0.85/(1+EXP(-adoption_steepness*(2028-adoption_midpoint)))*(1-churn_rate))>=stage2_gate,ecom_market_base*(1+ecom_growth_rate)^4*platform_market_share*tx_take_rate*1000*3,0))-((IF((adoption_max*0.85/(1+EXP(-adoption_steepness*(2028-adoption_midpoint)))*(1-churn_rate))>=stage2_gate,ecom_market_base*(1+ecom_growth_rate)^4*platform_market_share*tx_take_rate*1000*3,0))*payment_proc_pct)-(capex_total+(33*30*12*(1+bhxh_rate)*(1+salary_escalation)^2*5)+(opex_marketing*(1+marketing_growth)^2*5)+(opex_cloud_base*5+(adoption_max*0.85/(1+EXP(-adoption_steepness*(2028-adoption_midpoint)))*(1-churn_rate))*vcr_per_enterprise*12*cloud_per_1M_vcr/1000000*5)+((opex_branding+opex_external+opex_legal+opex_security+opex_partner_mgmt)*5)+(capex_total*capex_maintenance_pct*4)))*(1-cit_rate))/(1+discount_rate)^2.5 | D5: =((((adoption_max*1/(1+EXP(-adoption_steepness*(2028-adoption_midpoint)))*(1-churn_rate))*(cert_fee_yr1*(1+cert_fee_escalation)^2.5+training_pct*training_fee+audit_fee)*5)+(IF((adoption_max*1/(1+EXP(-adoption_steepness*(2028-adoption_midpoint)))*(1-churn_rate))>=stage2_gate,ecom_market_base*(1+ecom_growth_rate)^4*platform_market_share*tx_take_rate*1000*3,0))-((IF((adoption_max*1/(1+EXP(-adoption_steepness*(2028-adoption_midpoint)))*(1-churn_rate))>=stage2_gate,ecom_market_base*(1+ecom_growth_rate)^4*platform_market_share*tx_take_rate*1000*3,0))*payment_proc_pct)-(capex_total+(33*30*12*(1+bhxh_rate)*(1+salary_escalation)^2*5)+(opex_marketing*(1+marketing_growth)^2*5)+(opex_cloud_base*5+(adoption_max*1/(1+EXP(-adoption_steepness*(2028-adoption_midpoint)))*(1-churn_rate))*vcr_per_enterprise*12*cloud_per_1M_vcr/1000000*5)+((opex_branding+opex_external+opex_legal+opex_security+opex_partner_mgmt)*5)+(capex_total*capex_maintenance_pct*4)))*(1-cit_rate))/(1+discount_rate)^2.5 | E5: =((((adoption_max*1.15/(1+EXP(-adoption_steepness*(2028-adoption_midpoint)))*(1-churn_rate))*(cert_fee_yr1*(1+cert_fee_escalation)^2.5+training_pct*training_fee+audit_fee)*5)+(IF((adoption_max*1.15/(1+EXP(-adoption_steepness*(2028-adoption_midpoint)))*(1-churn_rate))>=stage2_gate,ecom_market_base*(1+ecom_growth_rate)^4*platform_market_share*tx_take_rate*1000*3,0))-((IF((adoption_max*1.15/(1+EXP(-adoption_steepness*(2028-adoption_midpoint)))*(1-churn_rate))>=stage2_gate,ecom_market_base*(1+ecom_growth_rate)^4*platform_market_share*tx_take_rate*1000*3,0))*payment_proc_pct)-(capex_total+(33*30*12*(1+bhxh_rate)*(1+salary_escalation)^2*5)+(opex_marketing*(1+marketing_growth)^2*5)+(opex_cloud_base*5+(adoption_max*1.15/(1+EXP(-adoption_steepness*(2028-adoption_midpoint)))*(1-churn_rate))*vcr_per_enterprise*12*cloud_per_1M_vcr/1000000*5)+((opex_branding+opex_external+opex_legal+opex_security+opex_partner_mgmt)*5)+(capex_total*capex_maintenance_pct*4)))*(1-cit_rate))/(1+discount_rate)^2.5 | F5: =((((adoption_max*1.3/(1+EXP(-adoption_steepness*(2028-adoption_midpoint)))*(1-churn_rate))*(cert_fee_yr1*(1+cert_fee_escalation)^2.5+training_pct*training_fee+audit_fee)*5)+(IF((adoption_max*1.3/(1+EXP(-adoption_steepness*(2028-adoption_midpoint)))*(1-churn_rate))>=stage2_gate,ecom_market_base*(1+ecom_growth_rate)^4*platform_market_share*tx_take_rate*1000*3,0))-((IF((adoption_max*1.3/(1+EXP(-adoption_steepness*(2028-adoption_midpoint)))*(1-churn_rate))>=stage2_gate,ecom_market_base*(1+ecom_growth_rate)^4*platform_market_share*tx_take_rate*1000*3,0))*payment_proc_pct)-(capex_total+(33*30*12*(1+bhxh_rate)*(1+salary_escalation)^2*5)+(opex_marketing*(1+marketing_growth)^2*5)+(opex_cloud_base*5+(adoption_max*1.3/(1+EXP(-adoption_steepness*(2028-adoption_midpoint)))*(1-churn_rate))*vcr_per_enterprise*12*cloud_per_1M_vcr/1000000*5)+((opex_branding+opex_external+opex_legal+opex_security+opex_partner_mgmt)*5)+(capex_total*capex_maintenance_pct*4)))*(1-cit_rate))/(1+discount_rate)^2.5 | G5: =adoption_max | H5: ↑ adoption → ↑ all revenue
A6: Market share (platform_market_share) | B6: =((((adoption_max/(1+EXP(-adoption_steepness*(2028-adoption_midpoint)))*(1-churn_rate))*(cert_fee_yr1*(1+cert_fee_escalation)^2.5+training_pct*training_fee+audit_fee)*5)+(IF((adoption_max/(1+EXP(-adoption_steepness*(2028-adoption_midpoint)))*(1-churn_rate))>=stage2_gate,ecom_market_base*(1+ecom_growth_rate)^4*platform_market_share*0.7*tx_take_rate*1000*3,0))-((IF((adoption_max/(1+EXP(-adoption_steepness*(2028-adoption_midpoint)))*(1-churn_rate))>=stage2_gate,ecom_market_base*(1+ecom_growth_rate)^4*platform_market_share*0.7*tx_take_rate*1000*3,0))*payment_proc_pct)-(capex_total+(33*30*12*(1+bhxh_rate)*(1+salary_escalation)^2*5)+(opex_marketing*(1+marketing_growth)^2*5)+(opex_cloud_base*5+(adoption_max/(1+EXP(-adoption_steepness*(2028-adoption_midpoint)))*(1-churn_rate))*vcr_per_enterprise*12*cloud_per_1M_vcr/1000000*5)+((opex_branding+opex_external+opex_legal+opex_security+opex_partner_mgmt)*5)+(capex_total*capex_maintenance_pct*4)))*(1-cit_rate))/(1+discount_rate)^2.5 | C6: =((((adoption_max/(1+EXP(-adoption_steepness*(2028-adoption_midpoint)))*(1-churn_rate))*(cert_fee_yr1*(1+cert_fee_escalation)^2.5+training_pct*training_fee+audit_fee)*5)+(IF((adoption_max/(1+EXP(-adoption_steepness*(2028-adoption_midpoint)))*(1-churn_rate))>=stage2_gate,ecom_market_base*(1+ecom_growth_rate)^4*platform_market_share*0.85*tx_take_rate*1000*3,0))-((IF((adoption_max/(1+EXP(-adoption_steepness*(2028-adoption_midpoint)))*(1-churn_rate))>=stage2_gate,ecom_market_base*(1+ecom_growth_rate)^4*platform_market_share*0.85*tx_take_rate*1000*3,0))*payment_proc_pct)-(capex_total+(33*30*12*(1+bhxh_rate)*(1+salary_escalation)^2*5)+(opex_marketing*(1+marketing_growth)^2*5)+(opex_cloud_base*5+(adoption_max/(1+EXP(-adoption_steepness*(2028-adoption_midpoint)))*(1-churn_rate))*vcr_per_enterprise*12*cloud_per_1M_vcr/1000000*5)+((opex_branding+opex_external+opex_legal+opex_security+opex_partner_mgmt)*5)+(capex_total*capex_maintenance_pct*4)))*(1-cit_rate))/(1+discount_rate)^2.5 | D6: =((((adoption_max/(1+EXP(-adoption_steepness*(2028-adoption_midpoint)))*(1-churn_rate))*(cert_fee_yr1*(1+cert_fee_escalation)^2.5+training_pct*training_fee+audit_fee)*5)+(IF((adoption_max/(1+EXP(-adoption_steepness*(2028-adoption_midpoint)))*(1-churn_rate))>=stage2_gate,ecom_market_base*(1+ecom_growth_rate)^4*platform_market_share*1*tx_take_rate*1000*3,0))-((IF((adoption_max/(1+EXP(-adoption_steepness*(2028-adoption_midpoint)))*(1-churn_rate))>=stage2_gate,ecom_market_base*(1+ecom_growth_rate)^4*platform_market_share*1*tx_take_rate*1000*3,0))*payment_proc_pct)-(capex_total+(33*30*12*(1+bhxh_rate)*(1+salary_escalation)^2*5)+(opex_marketing*(1+marketing_growth)^2*5)+(opex_cloud_base*5+(adoption_max/(1+EXP(-adoption_steepness*(2028-adoption_midpoint)))*(1-churn_rate))*vcr_per_enterprise*12*cloud_per_1M_vcr/1000000*5)+((opex_branding+opex_external+opex_legal+opex_security+opex_partner_mgmt)*5)+(capex_total*capex_maintenance_pct*4)))*(1-cit_rate))/(1+discount_rate)^2.5 | E6: =((((adoption_max/(1+EXP(-adoption_steepness*(2028-adoption_midpoint)))*(1-churn_rate))*(cert_fee_yr1*(1+cert_fee_escalation)^2.5+training_pct*training_fee+audit_fee)*5)+(IF((adoption_max/(1+EXP(-adoption_steepness*(2028-adoption_midpoint)))*(1-churn_rate))>=stage2_gate,ecom_market_base*(1+ecom_growth_rate)^4*platform_market_share*1.15*tx_take_rate*1000*3,0))-((IF((adoption_max/(1+EXP(-adoption_steepness*(2028-adoption_midpoint)))*(1-churn_rate))>=stage2_gate,ecom_market_base*(1+ecom_growth_rate)^4*platform_market_share*1.15*tx_take_rate*1000*3,0))*payment_proc_pct)-(capex_total+(33*30*12*(1+bhxh_rate)*(1+salary_escalation)^2*5)+(opex_marketing*(1+marketing_growth)^2*5)+(opex_cloud_base*5+(adoption_max/(1+EXP(-adoption_steepness*(2028-adoption_midpoint)))*(1-churn_rate))*vcr_per_enterprise*12*cloud_per_1M_vcr/1000000*5)+((opex_branding+opex_external+opex_legal+opex_security+opex_partner_mgmt)*5)+(capex_total*capex_maintenance_pct*4)))*(1-cit_rate))/(1+discount_rate)^2.5 | F6: =((((adoption_max/(1+EXP(-adoption_steepness*(2028-adoption_midpoint)))*(1-churn_rate))*(cert_fee_yr1*(1+cert_fee_escalation)^2.5+training_pct*training_fee+audit_fee)*5)+(IF((adoption_max/(1+EXP(-adoption_steepness*(2028-adoption_midpoint)))*(1-churn_rate))>=stage2_gate,ecom_market_base*(1+ecom_growth_rate)^4*platform_market_share*1.3*tx_take_rate*1000*3,0))-((IF((adoption_max/(1+EXP(-adoption_steepness*(2028-adoption_midpoint)))*(1-churn_rate))>=stage2_gate,ecom_market_base*(1+ecom_growth_rate)^4*platform_market_share*1.3*tx_take_rate*1000*3,0))*payment_proc_pct)-(capex_total+(33*30*12*(1+bhxh_rate)*(1+salary_escalation)^2*5)+(opex_marketing*(1+marketing_growth)^2*5)+(opex_cloud_base*5+(adoption_max/(1+EXP(-adoption_steepness*(2028-adoption_midpoint)))*(1-churn_rate))*vcr_per_enterprise*12*cloud_per_1M_vcr/1000000*5)+((opex_branding+opex_external+opex_legal+opex_security+opex_partner_mgmt)*5)+(capex_total*capex_maintenance_pct*4)))*(1-cit_rate))/(1+discount_rate)^2.5 | G6: =platform_market_share | H6: ↑ share → ↑ Stage 2 rev
A7: Churn rate | B7: =((((adoption_max/(1+EXP(-adoption_steepness*(2028-adoption_midpoint)))*(1-churn_rate*0.7))*(cert_fee_yr1*(1+cert_fee_escalation)^2.5+training_pct*training_fee+audit_fee)*5)+(IF((adoption_max/(1+EXP(-adoption_steepness*(2028-adoption_midpoint)))*(1-churn_rate*0.7))>=stage2_gate,ecom_market_base*(1+ecom_growth_rate)^4*platform_market_share*tx_take_rate*1000*3,0))-((IF((adoption_max/(1+EXP(-adoption_steepness*(2028-adoption_midpoint)))*(1-churn_rate*0.7))>=stage2_gate,ecom_market_base*(1+ecom_growth_rate)^4*platform_market_share*tx_take_rate*1000*3,0))*payment_proc_pct)-(capex_total+(33*30*12*(1+bhxh_rate)*(1+salary_escalation)^2*5)+(opex_marketing*(1+marketing_growth)^2*5)+(opex_cloud_base*5+(adoption_max/(1+EXP(-adoption_steepness*(2028-adoption_midpoint)))*(1-churn_rate*0.7))*vcr_per_enterprise*12*cloud_per_1M_vcr/1000000*5)+((opex_branding+opex_external+opex_legal+opex_security+opex_partner_mgmt)*5)+(capex_total*capex_maintenance_pct*4)))*(1-cit_rate))/(1+discount_rate)^2.5 | C7: =((((adoption_max/(1+EXP(-adoption_steepness*(2028-adoption_midpoint)))*(1-churn_rate*0.85))*(cert_fee_yr1*(1+cert_fee_escalation)^2.5+training_pct*training_fee+audit_fee)*5)+(IF((adoption_max/(1+EXP(-adoption_steepness*(2028-adoption_midpoint)))*(1-churn_rate*0.85))>=stage2_gate,ecom_market_base*(1+ecom_growth_rate)^4*platform_market_share*tx_take_rate*1000*3,0))-((IF((adoption_max/(1+EXP(-adoption_steepness*(2028-adoption_midpoint)))*(1-churn_rate*0.85))>=stage2_gate,ecom_market_base*(1+ecom_growth_rate)^4*platform_market_share*tx_take_rate*1000*3,0))*payment_proc_pct)-(capex_total+(33*30*12*(1+bhxh_rate)*(1+salary_escalation)^2*5)+(opex_marketing*(1+marketing_growth)^2*5)+(opex_cloud_base*5+(adoption_max/(1+EXP(-adoption_steepness*(2028-adoption_midpoint)))*(1-churn_rate*0.85))*vcr_per_enterprise*12*cloud_per_1M_vcr/1000000*5)+((opex_branding+opex_external+opex_legal+opex_security+opex_partner_mgmt)*5)+(capex_total*capex_maintenance_pct*4)))*(1-cit_rate))/(1+discount_rate)^2.5 | D7: =((((adoption_max/(1+EXP(-adoption_steepness*(2028-adoption_midpoint)))*(1-churn_rate*1))*(cert_fee_yr1*(1+cert_fee_escalation)^2.5+training_pct*training_fee+audit_fee)*5)+(IF((adoption_max/(1+EXP(-adoption_steepness*(2028-adoption_midpoint)))*(1-churn_rate*1))>=stage2_gate,ecom_market_base*(1+ecom_growth_rate)^4*platform_market_share*tx_take_rate*1000*3,0))-((IF((adoption_max/(1+EXP(-adoption_steepness*(2028-adoption_midpoint)))*(1-churn_rate*1))>=stage2_gate,ecom_market_base*(1+ecom_growth_rate)^4*platform_market_share*tx_take_rate*1000*3,0))*payment_proc_pct)-(capex_total+(33*30*12*(1+bhxh_rate)*(1+salary_escalation)^2*5)+(opex_marketing*(1+marketing_growth)^2*5)+(opex_cloud_base*5+(adoption_max/(1+EXP(-adoption_steepness*(2028-adoption_midpoint)))*(1-churn_rate*1))*vcr_per_enterprise*12*cloud_per_1M_vcr/1000000*5)+((opex_branding+opex_external+opex_legal+opex_security+opex_partner_mgmt)*5)+(capex_total*capex_maintenance_pct*4)))*(1-cit_rate))/(1+discount_rate)^2.5 | E7: =((((adoption_max/(1+EXP(-adoption_steepness*(2028-adoption_midpoint)))*(1-churn_rate*1.15))*(cert_fee_yr1*(1+cert_fee_escalation)^2.5+training_pct*training_fee+audit_fee)*5)+(IF((adoption_max/(1+EXP(-adoption_steepness*(2028-adoption_midpoint)))*(1-churn_rate*1.15))>=stage2_gate,ecom_market_base*(1+ecom_growth_rate)^4*platform_market_share*tx_take_rate*1000*3,0))-((IF((adoption_max/(1+EXP(-adoption_steepness*(2028-adoption_midpoint)))*(1-churn_rate*1.15))>=stage2_gate,ecom_market_base*(1+ecom_growth_rate)^4*platform_market_share*tx_take_rate*1000*3,0))*payment_proc_pct)-(capex_total+(33*30*12*(1+bhxh_rate)*(1+salary_escalation)^2*5)+(opex_marketing*(1+marketing_growth)^2*5)+(opex_cloud_base*5+(adoption_max/(1+EXP(-adoption_steepness*(2028-adoption_midpoint)))*(1-churn_rate*1.15))*vcr_per_enterprise*12*cloud_per_1M_vcr/1000000*5)+((opex_branding+opex_external+opex_legal+opex_security+opex_partner_mgmt)*5)+(capex_total*capex_maintenance_pct*4)))*(1-cit_rate))/(1+discount_rate)^2.5 | F7: =((((adoption_max/(1+EXP(-adoption_steepness*(2028-adoption_midpoint)))*(1-churn_rate*1.3))*(cert_fee_yr1*(1+cert_fee_escalation)^2.5+training_pct*training_fee+audit_fee)*5)+(IF((adoption_max/(1+EXP(-adoption_steepness*(2028-adoption_midpoint)))*(1-churn_rate*1.3))>=stage2_gate,ecom_market_base*(1+ecom_growth_rate)^4*platform_market_share*tx_take_rate*1000*3,0))-((IF((adoption_max/(1+EXP(-adoption_steepness*(2028-adoption_midpoint)))*(1-churn_rate*1.3))>=stage2_gate,ecom_market_base*(1+ecom_growth_rate)^4*platform_market_share*tx_take_rate*1000*3,0))*payment_proc_pct)-(capex_total+(33*30*12*(1+bhxh_rate)*(1+salary_escalation)^2*5)+(opex_marketing*(1+marketing_growth)^2*5)+(opex_cloud_base*5+(adoption_max/(1+EXP(-adoption_steepness*(2028-adoption_midpoint)))*(1-churn_rate*1.3))*vcr_per_enterprise*12*cloud_per_1M_vcr/1000000*5)+((opex_branding+opex_external+opex_legal+opex_security+opex_partner_mgmt)*5)+(capex_total*capex_maintenance_pct*4)))*(1-cit_rate))/(1+discount_rate)^2.5 | G7: =churn_rate | H7: ↑ churn → ↓ net ent
A8: Cert fee (Tr/yr) | B8: =((((adoption_max/(1+EXP(-adoption_steepness*(2028-adoption_midpoint)))*(1-churn_rate))*(cert_fee_yr1*0.7*(1+cert_fee_escalation)^2.5+training_pct*training_fee+audit_fee)*5)+(IF((adoption_max/(1+EXP(-adoption_steepness*(2028-adoption_midpoint)))*(1-churn_rate))>=stage2_gate,ecom_market_base*(1+ecom_growth_rate)^4*platform_market_share*tx_take_rate*1000*3,0))-((IF((adoption_max/(1+EXP(-adoption_steepness*(2028-adoption_midpoint)))*(1-churn_rate))>=stage2_gate,ecom_market_base*(1+ecom_growth_rate)^4*platform_market_share*tx_take_rate*1000*3,0))*payment_proc_pct)-(capex_total+(33*30*12*(1+bhxh_rate)*(1+salary_escalation)^2*5)+(opex_marketing*(1+marketing_growth)^2*5)+(opex_cloud_base*5+(adoption_max/(1+EXP(-adoption_steepness*(2028-adoption_midpoint)))*(1-churn_rate))*vcr_per_enterprise*12*cloud_per_1M_vcr/1000000*5)+((opex_branding+opex_external+opex_legal+opex_security+opex_partner_mgmt)*5)+(capex_total*capex_maintenance_pct*4)))*(1-cit_rate))/(1+discount_rate)^2.5 | C8: =((((adoption_max/(1+EXP(-adoption_steepness*(2028-adoption_midpoint)))*(1-churn_rate))*(cert_fee_yr1*0.85*(1+cert_fee_escalation)^2.5+training_pct*training_fee+audit_fee)*5)+(IF((adoption_max/(1+EXP(-adoption_steepness*(2028-adoption_midpoint)))*(1-churn_rate))>=stage2_gate,ecom_market_base*(1+ecom_growth_rate)^4*platform_market_share*tx_take_rate*1000*3,0))-((IF((adoption_max/(1+EXP(-adoption_steepness*(2028-adoption_midpoint)))*(1-churn_rate))>=stage2_gate,ecom_market_base*(1+ecom_growth_rate)^4*platform_market_share*tx_take_rate*1000*3,0))*payment_proc_pct)-(capex_total+(33*30*12*(1+bhxh_rate)*(1+salary_escalation)^2*5)+(opex_marketing*(1+marketing_growth)^2*5)+(opex_cloud_base*5+(adoption_max/(1+EXP(-adoption_steepness*(2028-adoption_midpoint)))*(1-churn_rate))*vcr_per_enterprise*12*cloud_per_1M_vcr/1000000*5)+((opex_branding+opex_external+opex_legal+opex_security+opex_partner_mgmt)*5)+(capex_total*capex_maintenance_pct*4)))*(1-cit_rate))/(1+discount_rate)^2.5 | D8: =((((adoption_max/(1+EXP(-adoption_steepness*(2028-adoption_midpoint)))*(1-churn_rate))*(cert_fee_yr1*1*(1+cert_fee_escalation)^2.5+training_pct*training_fee+audit_fee)*5)+(IF((adoption_max/(1+EXP(-adoption_steepness*(2028-adoption_midpoint)))*(1-churn_rate))>=stage2_gate,ecom_market_base*(1+ecom_growth_rate)^4*platform_market_share*tx_take_rate*1000*3,0))-((IF((adoption_max/(1+EXP(-adoption_steepness*(2028-adoption_midpoint)))*(1-churn_rate))>=stage2_gate,ecom_market_base*(1+ecom_growth_rate)^4*platform_market_share*tx_take_rate*1000*3,0))*payment_proc_pct)-(capex_total+(33*30*12*(1+bhxh_rate)*(1+salary_escalation)^2*5)+(opex_marketing*(1+marketing_growth)^2*5)+(opex_cloud_base*5+(adoption_max/(1+EXP(-adoption_steepness*(2028-adoption_midpoint)))*(1-churn_rate))*vcr_per_enterprise*12*cloud_per_1M_vcr/1000000*5)+((opex_branding+opex_external+opex_legal+opex_security+opex_partner_mgmt)*5)+(capex_total*capex_maintenance_pct*4)))*(1-cit_rate))/(1+discount_rate)^2.5 | E8: =((((adoption_max/(1+EXP(-adoption_steepness*(2028-adoption_midpoint)))*(1-churn_rate))*(cert_fee_yr1*1.15*(1+cert_fee_escalation)^2.5+training_pct*training_fee+audit_fee)*5)+(IF((adoption_max/(1+EXP(-adoption_steepness*(2028-adoption_midpoint)))*(1-churn_rate))>=stage2_gate,ecom_market_base*(1+ecom_growth_rate)^4*platform_market_share*tx_take_rate*1000*3,0))-((IF((adoption_max/(1+EXP(-adoption_steepness*(2028-adoption_midpoint)))*(1-churn_rate))>=stage2_gate,ecom_market_base*(1+ecom_growth_rate)^4*platform_market_share*tx_take_rate*1000*3,0))*payment_proc_pct)-(capex_total+(33*30*12*(1+bhxh_rate)*(1+salary_escalation)^2*5)+(opex_marketing*(1+marketing_growth)^2*5)+(opex_cloud_base*5+(adoption_max/(1+EXP(-adoption_steepness*(2028-adoption_midpoint)))*(1-churn_rate))*vcr_per_enterprise*12*cloud_per_1M_vcr/1000000*5)+((opex_branding+opex_external+opex_legal+opex_security+opex_partner_mgmt)*5)+(capex_total*capex_maintenance_pct*4)))*(1-cit_rate))/(1+discount_rate)^2.5 | F8: =((((adoption_max/(1+EXP(-adoption_steepness*(2028-adoption_midpoint)))*(1-churn_rate))*(cert_fee_yr1*1.3*(1+cert_fee_escalation)^2.5+training_pct*training_fee+audit_fee)*5)+(IF((adoption_max/(1+EXP(-adoption_steepness*(2028-adoption_midpoint)))*(1-churn_rate))>=stage2_gate,ecom_market_base*(1+ecom_growth_rate)^4*platform_market_share*tx_take_rate*1000*3,0))-((IF((adoption_max/(1+EXP(-adoption_steepness*(2028-adoption_midpoint)))*(1-churn_rate))>=stage2_gate,ecom_market_base*(1+ecom_growth_rate)^4*platform_market_share*tx_take_rate*1000*3,0))*payment_proc_pct)-(capex_total+(33*30*12*(1+bhxh_rate)*(1+salary_escalation)^2*5)+(opex_marketing*(1+marketing_growth)^2*5)+(opex_cloud_base*5+(adoption_max/(1+EXP(-adoption_steepness*(2028-adoption_midpoint)))*(1-churn_rate))*vcr_per_enterprise*12*cloud_per_1M_vcr/1000000*5)+((opex_branding+opex_external+opex_legal+opex_security+opex_partner_mgmt)*5)+(capex_total*capex_maintenance_pct*4)))*(1-cit_rate))/(1+discount_rate)^2.5 | G8: =cert_fee_yr1 | H8: ↑ fee → ↑ Stage 1 rev
A9: Cert escalation | B9: =((((adoption_max/(1+EXP(-adoption_steepness*(2028-adoption_midpoint)))*(1-churn_rate))*(cert_fee_yr1*(1+cert_fee_escalation*0.7)^2.5+training_pct*training_fee+audit_fee)*5)+(IF((adoption_max/(1+EXP(-adoption_steepness*(2028-adoption_midpoint)))*(1-churn_rate))>=stage2_gate,ecom_market_base*(1+ecom_growth_rate)^4*platform_market_share*tx_take_rate*1000*3,0))-((IF((adoption_max/(1+EXP(-adoption_steepness*(2028-adoption_midpoint)))*(1-churn_rate))>=stage2_gate,ecom_market_base*(1+ecom_growth_rate)^4*platform_market_share*tx_take_rate*1000*3,0))*payment_proc_pct)-(capex_total+(33*30*12*(1+bhxh_rate)*(1+salary_escalation)^2*5)+(opex_marketing*(1+marketing_growth)^2*5)+(opex_cloud_base*5+(adoption_max/(1+EXP(-adoption_steepness*(2028-adoption_midpoint)))*(1-churn_rate))*vcr_per_enterprise*12*cloud_per_1M_vcr/1000000*5)+((opex_branding+opex_external+opex_legal+opex_security+opex_partner_mgmt)*5)+(capex_total*capex_maintenance_pct*4)))*(1-cit_rate))/(1+discount_rate)^2.5 | C9: =((((adoption_max/(1+EXP(-adoption_steepness*(2028-adoption_midpoint)))*(1-churn_rate))*(cert_fee_yr1*(1+cert_fee_escalation*0.85)^2.5+training_pct*training_fee+audit_fee)*5)+(IF((adoption_max/(1+EXP(-adoption_steepness*(2028-adoption_midpoint)))*(1-churn_rate))>=stage2_gate,ecom_market_base*(1+ecom_growth_rate)^4*platform_market_share*tx_take_rate*1000*3,0))-((IF((adoption_max/(1+EXP(-adoption_steepness*(2028-adoption_midpoint)))*(1-churn_rate))>=stage2_gate,ecom_market_base*(1+ecom_growth_rate)^4*platform_market_share*tx_take_rate*1000*3,0))*payment_proc_pct)-(capex_total+(33*30*12*(1+bhxh_rate)*(1+salary_escalation)^2*5)+(opex_marketing*(1+marketing_growth)^2*5)+(opex_cloud_base*5+(adoption_max/(1+EXP(-adoption_steepness*(2028-adoption_midpoint)))*(1-churn_rate))*vcr_per_enterprise*12*cloud_per_1M_vcr/1000000*5)+((opex_branding+opex_external+opex_legal+opex_security+opex_partner_mgmt)*5)+(capex_total*capex_maintenance_pct*4)))*(1-cit_rate))/(1+discount_rate)^2.5 | D9: =((((adoption_max/(1+EXP(-adoption_steepness*(2028-adoption_midpoint)))*(1-churn_rate))*(cert_fee_yr1*(1+cert_fee_escalation*1)^2.5+training_pct*training_fee+audit_fee)*5)+(IF((adoption_max/(1+EXP(-adoption_steepness*(2028-adoption_midpoint)))*(1-churn_rate))>=stage2_gate,ecom_market_base*(1+ecom_growth_rate)^4*platform_market_share*tx_take_rate*1000*3,0))-((IF((adoption_max/(1+EXP(-adoption_steepness*(2028-adoption_midpoint)))*(1-churn_rate))>=stage2_gate,ecom_market_base*(1+ecom_growth_rate)^4*platform_market_share*tx_take_rate*1000*3,0))*payment_proc_pct)-(capex_total+(33*30*12*(1+bhxh_rate)*(1+salary_escalation)^2*5)+(opex_marketing*(1+marketing_growth)^2*5)+(opex_cloud_base*5+(adoption_max/(1+EXP(-adoption_steepness*(2028-adoption_midpoint)))*(1-churn_rate))*vcr_per_enterprise*12*cloud_per_1M_vcr/1000000*5)+((opex_branding+opex_external+opex_legal+opex_security+opex_partner_mgmt)*5)+(capex_total*capex_maintenance_pct*4)))*(1-cit_rate))/(1+discount_rate)^2.5 | E9: =((((adoption_max/(1+EXP(-adoption_steepness*(2028-adoption_midpoint)))*(1-churn_rate))*(cert_fee_yr1*(1+cert_fee_escalation*1.15)^2.5+training_pct*training_fee+audit_fee)*5)+(IF((adoption_max/(1+EXP(-adoption_steepness*(2028-adoption_midpoint)))*(1-churn_rate))>=stage2_gate,ecom_market_base*(1+ecom_growth_rate)^4*platform_market_share*tx_take_rate*1000*3,0))-((IF((adoption_max/(1+EXP(-adoption_steepness*(2028-adoption_midpoint)))*(1-churn_rate))>=stage2_gate,ecom_market_base*(1+ecom_growth_rate)^4*platform_market_share*tx_take_rate*1000*3,0))*payment_proc_pct)-(capex_total+(33*30*12*(1+bhxh_rate)*(1+salary_escalation)^2*5)+(opex_marketing*(1+marketing_growth)^2*5)+(opex_cloud_base*5+(adoption_max/(1+EXP(-adoption_steepness*(2028-adoption_midpoint)))*(1-churn_rate))*vcr_per_enterprise*12*cloud_per_1M_vcr/1000000*5)+((opex_branding+opex_external+opex_legal+opex_security+opex_partner_mgmt)*5)+(capex_total*capex_maintenance_pct*4)))*(1-cit_rate))/(1+discount_rate)^2.5 | F9: =((((adoption_max/(1+EXP(-adoption_steepness*(2028-adoption_midpoint)))*(1-churn_rate))*(cert_fee_yr1*(1+cert_fee_escalation*1.3)^2.5+training_pct*training_fee+audit_fee)*5)+(IF((adoption_max/(1+EXP(-adoption_steepness*(2028-adoption_midpoint)))*(1-churn_rate))>=stage2_gate,ecom_market_base*(1+ecom_growth_rate)^4*platform_market_share*tx_take_rate*1000*3,0))-((IF((adoption_max/(1+EXP(-adoption_steepness*(2028-adoption_midpoint)))*(1-churn_rate))>=stage2_gate,ecom_market_base*(1+ecom_growth_rate)^4*platform_market_share*tx_take_rate*1000*3,0))*payment_proc_pct)-(capex_total+(33*30*12*(1+bhxh_rate)*(1+salary_escalation)^2*5)+(opex_marketing*(1+marketing_growth)^2*5)+(opex_cloud_base*5+(adoption_max/(1+EXP(-adoption_steepness*(2028-adoption_midpoint)))*(1-churn_rate))*vcr_per_enterprise*12*cloud_per_1M_vcr/1000000*5)+((opex_branding+opex_external+opex_legal+opex_security+opex_partner_mgmt)*5)+(capex_total*capex_maintenance_pct*4)))*(1-cit_rate))/(1+discount_rate)^2.5 | G9: =cert_fee_escalation | H9: ↑ esc → ↑ later rev
A10: WACC (discount_rate) | B10: =((((adoption_max/(1+EXP(-adoption_steepness*(2028-adoption_midpoint)))*(1-churn_rate))*(cert_fee_yr1*(1+cert_fee_escalation)^2.5+training_pct*training_fee+audit_fee)*5)+(IF((adoption_max/(1+EXP(-adoption_steepness*(2028-adoption_midpoint)))*(1-churn_rate))>=stage2_gate,ecom_market_base*(1+ecom_growth_rate)^4*platform_market_share*tx_take_rate*1000*3,0))-((IF((adoption_max/(1+EXP(-adoption_steepness*(2028-adoption_midpoint)))*(1-churn_rate))>=stage2_gate,ecom_market_base*(1+ecom_growth_rate)^4*platform_market_share*tx_take_rate*1000*3,0))*payment_proc_pct)-(capex_total+(33*30*12*(1+bhxh_rate)*(1+salary_escalation)^2*5)+(opex_marketing*(1+marketing_growth)^2*5)+(opex_cloud_base*5+(adoption_max/(1+EXP(-adoption_steepness*(2028-adoption_midpoint)))*(1-churn_rate))*vcr_per_enterprise*12*cloud_per_1M_vcr/1000000*5)+((opex_branding+opex_external+opex_legal+opex_security+opex_partner_mgmt)*5)+(capex_total*capex_maintenance_pct*4)))*(1-cit_rate))/(1+discount_rate*0.7)^2.5 | C10: =((((adoption_max/(1+EXP(-adoption_steepness*(2028-adoption_midpoint)))*(1-churn_rate))*(cert_fee_yr1*(1+cert_fee_escalation)^2.5+training_pct*training_fee+audit_fee)*5)+(IF((adoption_max/(1+EXP(-adoption_steepness*(2028-adoption_midpoint)))*(1-churn_rate))>=stage2_gate,ecom_market_base*(1+ecom_growth_rate)^4*platform_market_share*tx_take_rate*1000*3,0))-((IF((adoption_max/(1+EXP(-adoption_steepness*(2028-adoption_midpoint)))*(1-churn_rate))>=stage2_gate,ecom_market_base*(1+ecom_growth_rate)^4*platform_market_share*tx_take_rate*1000*3,0))*payment_proc_pct)-(capex_total+(33*30*12*(1+bhxh_rate)*(1+salary_escalation)^2*5)+(opex_marketing*(1+marketing_growth)^2*5)+(opex_cloud_base*5+(adoption_max/(1+EXP(-adoption_steepness*(2028-adoption_midpoint)))*(1-churn_rate))*vcr_per_enterprise*12*cloud_per_1M_vcr/1000000*5)+((opex_branding+opex_external+opex_legal+opex_security+opex_partner_mgmt)*5)+(capex_total*capex_maintenance_pct*4)))*(1-cit_rate))/(1+discount_rate*0.85)^2.5 | D10: =((((adoption_max/(1+EXP(-adoption_steepness*(2028-adoption_midpoint)))*(1-churn_rate))*(cert_fee_yr1*(1+cert_fee_escalation)^2.5+training_pct*training_fee+audit_fee)*5)+(IF((adoption_max/(1+EXP(-adoption_steepness*(2028-adoption_midpoint)))*(1-churn_rate))>=stage2_gate,ecom_market_base*(1+ecom_growth_rate)^4*platform_market_share*tx_take_rate*1000*3,0))-((IF((adoption_max/(1+EXP(-adoption_steepness*(2028-adoption_midpoint)))*(1-churn_rate))>=stage2_gate,ecom_market_base*(1+ecom_growth_rate)^4*platform_market_share*tx_take_rate*1000*3,0))*payment_proc_pct)-(capex_total+(33*30*12*(1+bhxh_rate)*(1+salary_escalation)^2*5)+(opex_marketing*(1+marketing_growth)^2*5)+(opex_cloud_base*5+(adoption_max/(1+EXP(-adoption_steepness*(2028-adoption_midpoint)))*(1-churn_rate))*vcr_per_enterprise*12*cloud_per_1M_vcr/1000000*5)+((opex_branding+opex_external+opex_legal+opex_security+opex_partner_mgmt)*5)+(capex_total*capex_maintenance_pct*4)))*(1-cit_rate))/(1+discount_rate*1)^2.5 | E10: =((((adoption_max/(1+EXP(-adoption_steepness*(2028-adoption_midpoint)))*(1-churn_rate))*(cert_fee_yr1*(1+cert_fee_escalation)^2.5+training_pct*training_fee+audit_fee)*5)+(IF((adoption_max/(1+EXP(-adoption_steepness*(2028-adoption_midpoint)))*(1-churn_rate))>=stage2_gate,ecom_market_base*(1+ecom_growth_rate)^4*platform_market_share*tx_take_rate*1000*3,0))-((IF((adoption_max/(1+EXP(-adoption_steepness*(2028-adoption_midpoint)))*(1-churn_rate))>=stage2_gate,ecom_market_base*(1+ecom_growth_rate)^4*platform_market_share*tx_take_rate*1000*3,0))*payment_proc_pct)-(capex_total+(33*30*12*(1+bhxh_rate)*(1+salary_escalation)^2*5)+(opex_marketing*(1+marketing_growth)^2*5)+(opex_cloud_base*5+(adoption_max/(1+EXP(-adoption_steepness*(2028-adoption_midpoint)))*(1-churn_rate))*vcr_per_enterprise*12*cloud_per_1M_vcr/1000000*5)+((opex_branding+opex_external+opex_legal+opex_security+opex_partner_mgmt)*5)+(capex_total*capex_maintenance_pct*4)))*(1-cit_rate))/(1+discount_rate*1.15)^2.5 | F10: =((((adoption_max/(1+EXP(-adoption_steepness*(2028-adoption_midpoint)))*(1-churn_rate))*(cert_fee_yr1*(1+cert_fee_escalation)^2.5+training_pct*training_fee+audit_fee)*5)+(IF((adoption_max/(1+EXP(-adoption_steepness*(2028-adoption_midpoint)))*(1-churn_rate))>=stage2_gate,ecom_market_base*(1+ecom_growth_rate)^4*platform_market_share*tx_take_rate*1000*3,0))-((IF((adoption_max/(1+EXP(-adoption_steepness*(2028-adoption_midpoint)))*(1-churn_rate))>=stage2_gate,ecom_market_base*(1+ecom_growth_rate)^4*platform_market_share*tx_take_rate*1000*3,0))*payment_proc_pct)-(capex_total+(33*30*12*(1+bhxh_rate)*(1+salary_escalation)^2*5)+(opex_marketing*(1+marketing_growth)^2*5)+(opex_cloud_base*5+(adoption_max/(1+EXP(-adoption_steepness*(2028-adoption_midpoint)))*(1-churn_rate))*vcr_per_enterprise*12*cloud_per_1M_vcr/1000000*5)+((opex_branding+opex_external+opex_legal+opex_security+opex_partner_mgmt)*5)+(capex_total*capex_maintenance_pct*4)))*(1-cit_rate))/(1+discount_rate*1.3)^2.5 | G10: =discount_rate | H10: ↑ WACC → ↓ NPV
A11: Marketing base | B11: =((((adoption_max/(1+EXP(-adoption_steepness*(2028-adoption_midpoint)))*(1-churn_rate))*(cert_fee_yr1*(1+cert_fee_escalation)^2.5+training_pct*training_fee+audit_fee)*5)+(IF((adoption_max/(1+EXP(-adoption_steepness*(2028-adoption_midpoint)))*(1-churn_rate))>=stage2_gate,ecom_market_base*(1+ecom_growth_rate)^4*platform_market_share*tx_take_rate*1000*3,0))-((IF((adoption_max/(1+EXP(-adoption_steepness*(2028-adoption_midpoint)))*(1-churn_rate))>=stage2_gate,ecom_market_base*(1+ecom_growth_rate)^4*platform_market_share*tx_take_rate*1000*3,0))*payment_proc_pct)-(capex_total+(33*30*12*(1+bhxh_rate)*(1+salary_escalation)^2*5)+(opex_marketing*0.7*(1+marketing_growth)^2*5)+(opex_cloud_base*5+(adoption_max/(1+EXP(-adoption_steepness*(2028-adoption_midpoint)))*(1-churn_rate))*vcr_per_enterprise*12*cloud_per_1M_vcr/1000000*5)+((opex_branding+opex_external+opex_legal+opex_security+opex_partner_mgmt)*5)+(capex_total*capex_maintenance_pct*4)))*(1-cit_rate))/(1+discount_rate)^2.5 | C11: =((((adoption_max/(1+EXP(-adoption_steepness*(2028-adoption_midpoint)))*(1-churn_rate))*(cert_fee_yr1*(1+cert_fee_escalation)^2.5+training_pct*training_fee+audit_fee)*5)+(IF((adoption_max/(1+EXP(-adoption_steepness*(2028-adoption_midpoint)))*(1-churn_rate))>=stage2_gate,ecom_market_base*(1+ecom_growth_rate)^4*platform_market_share*tx_take_rate*1000*3,0))-((IF((adoption_max/(1+EXP(-adoption_steepness*(2028-adoption_midpoint)))*(1-churn_rate))>=stage2_gate,ecom_market_base*(1+ecom_growth_rate)^4*platform_market_share*tx_take_rate*1000*3,0))*payment_proc_pct)-(capex_total+(33*30*12*(1+bhxh_rate)*(1+salary_escalation)^2*5)+(opex_marketing*0.85*(1+marketing_growth)^2*5)+(opex_cloud_base*5+(adoption_max/(1+EXP(-adoption_steepness*(2028-adoption_midpoint)))*(1-churn_rate))*vcr_per_enterprise*12*cloud_per_1M_vcr/1000000*5)+((opex_branding+opex_external+opex_legal+opex_security+opex_partner_mgmt)*5)+(capex_total*capex_maintenance_pct*4)))*(1-cit_rate))/(1+discount_rate)^2.5 | D11: =((((adoption_max/(1+EXP(-adoption_steepness*(2028-adoption_midpoint)))*(1-churn_rate))*(cert_fee_yr1*(1+cert_fee_escalation)^2.5+training_pct*training_fee+audit_fee)*5)+(IF((adoption_max/(1+EXP(-adoption_steepness*(2028-adoption_midpoint)))*(1-churn_rate))>=stage2_gate,ecom_market_base*(1+ecom_growth_rate)^4*platform_market_share*tx_take_rate*1000*3,0))-((IF((adoption_max/(1+EXP(-adoption_steepness*(2028-adoption_midpoint)))*(1-churn_rate))>=stage2_gate,ecom_market_base*(1+ecom_growth_rate)^4*platform_market_share*tx_take_rate*1000*3,0))*payment_proc_pct)-(capex_total+(33*30*12*(1+bhxh_rate)*(1+salary_escalation)^2*5)+(opex_marketing*1*(1+marketing_growth)^2*5)+(opex_cloud_base*5+(adoption_max/(1+EXP(-adoption_steepness*(2028-adoption_midpoint)))*(1-churn_rate))*vcr_per_enterprise*12*cloud_per_1M_vcr/1000000*5)+((opex_branding+opex_external+opex_legal+opex_security+opex_partner_mgmt)*5)+(capex_total*capex_maintenance_pct*4)))*(1-cit_rate))/(1+discount_rate)^2.5 | E11: =((((adoption_max/(1+EXP(-adoption_steepness*(2028-adoption_midpoint)))*(1-churn_rate))*(cert_fee_yr1*(1+cert_fee_escalation)^2.5+training_pct*training_fee+audit_fee)*5)+(IF((adoption_max/(1+EXP(-adoption_steepness*(2028-adoption_midpoint)))*(1-churn_rate))>=stage2_gate,ecom_market_base*(1+ecom_growth_rate)^4*platform_market_share*tx_take_rate*1000*3,0))-((IF((adoption_max/(1+EXP(-adoption_steepness*(2028-adoption_midpoint)))*(1-churn_rate))>=stage2_gate,ecom_market_base*(1+ecom_growth_rate)^4*platform_market_share*tx_take_rate*1000*3,0))*payment_proc_pct)-(capex_total+(33*30*12*(1+bhxh_rate)*(1+salary_escalation)^2*5)+(opex_marketing*1.15*(1+marketing_growth)^2*5)+(opex_cloud_base*5+(adoption_max/(1+EXP(-adoption_steepness*(2028-adoption_midpoint)))*(1-churn_rate))*vcr_per_enterprise*12*cloud_per_1M_vcr/1000000*5)+((opex_branding+opex_external+opex_legal+opex_security+opex_partner_mgmt)*5)+(capex_total*capex_maintenance_pct*4)))*(1-cit_rate))/(1+discount_rate)^2.5 | F11: =((((adoption_max/(1+EXP(-adoption_steepness*(2028-adoption_midpoint)))*(1-churn_rate))*(cert_fee_yr1*(1+cert_fee_escalation)^2.5+training_pct*training_fee+audit_fee)*5)+(IF((adoption_max/(1+EXP(-adoption_steepness*(2028-adoption_midpoint)))*(1-churn_rate))>=stage2_gate,ecom_market_base*(1+ecom_growth_rate)^4*platform_market_share*tx_take_rate*1000*3,0))-((IF((adoption_max/(1+EXP(-adoption_steepness*(2028-adoption_midpoint)))*(1-churn_rate))>=stage2_gate,ecom_market_base*(1+ecom_growth_rate)^4*platform_market_share*tx_take_rate*1000*3,0))*payment_proc_pct)-(capex_total+(33*30*12*(1+bhxh_rate)*(1+salary_escalation)^2*5)+(opex_marketing*1.3*(1+marketing_growth)^2*5)+(opex_cloud_base*5+(adoption_max/(1+EXP(-adoption_steepness*(2028-adoption_midpoint)))*(1-churn_rate))*vcr_per_enterprise*12*cloud_per_1M_vcr/1000000*5)+((opex_branding+opex_external+opex_legal+opex_security+opex_partner_mgmt)*5)+(capex_total*capex_maintenance_pct*4)))*(1-cit_rate))/(1+discount_rate)^2.5 | G11: =opex_marketing | H11: ↑ mkt → ↓ profit
A12: S-curve steepness | B12: =((((adoption_max/(1+EXP(-adoption_steepness*0.7*(2028-adoption_midpoint)))*(1-churn_rate))*(cert_fee_yr1*(1+cert_fee_escalation)^2.5+training_pct*training_fee+audit_fee)*5)+(IF((adoption_max/(1+EXP(-adoption_steepness*0.7*(2028-adoption_midpoint)))*(1-churn_rate))>=stage2_gate,ecom_market_base*(1+ecom_growth_rate)^4*platform_market_share*tx_take_rate*1000*3,0))-((IF((adoption_max/(1+EXP(-adoption_steepness*0.7*(2028-adoption_midpoint)))*(1-churn_rate))>=stage2_gate,ecom_market_base*(1+ecom_growth_rate)^4*platform_market_share*tx_take_rate*1000*3,0))*payment_proc_pct)-(capex_total+(33*30*12*(1+bhxh_rate)*(1+salary_escalation)^2*5)+(opex_marketing*(1+marketing_growth)^2*5)+(opex_cloud_base*5+(adoption_max/(1+EXP(-adoption_steepness*0.7*(2028-adoption_midpoint)))*(1-churn_rate))*vcr_per_enterprise*12*cloud_per_1M_vcr/1000000*5)+((opex_branding+opex_external+opex_legal+opex_security+opex_partner_mgmt)*5)+(capex_total*capex_maintenance_pct*4)))*(1-cit_rate))/(1+discount_rate)^2.5 | C12: =((((adoption_max/(1+EXP(-adoption_steepness*0.85*(2028-adoption_midpoint)))*(1-churn_rate))*(cert_fee_yr1*(1+cert_fee_escalation)^2.5+training_pct*training_fee+audit_fee)*5)+(IF((adoption_max/(1+EXP(-adoption_steepness*0.85*(2028-adoption_midpoint)))*(1-churn_rate))>=stage2_gate,ecom_market_base*(1+ecom_growth_rate)^4*platform_market_share*tx_take_rate*1000*3,0))-((IF((adoption_max/(1+EXP(-adoption_steepness*0.85*(2028-adoption_midpoint)))*(1-churn_rate))>=stage2_gate,ecom_market_base*(1+ecom_growth_rate)^4*platform_market_share*tx_take_rate*1000*3,0))*payment_proc_pct)-(capex_total+(33*30*12*(1+bhxh_rate)*(1+salary_escalation)^2*5)+(opex_marketing*(1+marketing_growth)^2*5)+(opex_cloud_base*5+(adoption_max/(1+EXP(-adoption_steepness*0.85*(2028-adoption_midpoint)))*(1-churn_rate))*vcr_per_enterprise*12*cloud_per_1M_vcr/1000000*5)+((opex_branding+opex_external+opex_legal+opex_security+opex_partner_mgmt)*5)+(capex_total*capex_maintenance_pct*4)))*(1-cit_rate))/(1+discount_rate)^2.5 | D12: =((((adoption_max/(1+EXP(-adoption_steepness*1*(2028-adoption_midpoint)))*(1-churn_rate))*(cert_fee_yr1*(1+cert_fee_escalation)^2.5+training_pct*training_fee+audit_fee)*5)+(IF((adoption_max/(1+EXP(-adoption_steepness*1*(2028-adoption_midpoint)))*(1-churn_rate))>=stage2_gate,ecom_market_base*(1+ecom_growth_rate)^4*platform_market_share*tx_take_rate*1000*3,0))-((IF((adoption_max/(1+EXP(-adoption_steepness*1*(2028-adoption_midpoint)))*(1-churn_rate))>=stage2_gate,ecom_market_base*(1+ecom_growth_rate)^4*platform_market_share*tx_take_rate*1000*3,0))*payment_proc_pct)-(capex_total+(33*30*12*(1+bhxh_rate)*(1+salary_escalation)^2*5)+(opex_marketing*(1+marketing_growth)^2*5)+(opex_cloud_base*5+(adoption_max/(1+EXP(-adoption_steepness*1*(2028-adoption_midpoint)))*(1-churn_rate))*vcr_per_enterprise*12*cloud_per_1M_vcr/1000000*5)+((opex_branding+opex_external+opex_legal+opex_security+opex_partner_mgmt)*5)+(capex_total*capex_maintenance_pct*4)))*(1-cit_rate))/(1+discount_rate)^2.5 | E12: =((((adoption_max/(1+EXP(-adoption_steepness*1.15*(2028-adoption_midpoint)))*(1-churn_rate))*(cert_fee_yr1*(1+cert_fee_escalation)^2.5+training_pct*training_fee+audit_fee)*5)+(IF((adoption_max/(1+EXP(-adoption_steepness*1.15*(2028-adoption_midpoint)))*(1-churn_rate))>=stage2_gate,ecom_market_base*(1+ecom_growth_rate)^4*platform_market_share*tx_take_rate*1000*3,0))-((IF((adoption_max/(1+EXP(-adoption_steepness*1.15*(2028-adoption_midpoint)))*(1-churn_rate))>=stage2_gate,ecom_market_base*(1+ecom_growth_rate)^4*platform_market_share*tx_take_rate*1000*3,0))*payment_proc_pct)-(capex_total+(33*30*12*(1+bhxh_rate)*(1+salary_escalation)^2*5)+(opex_marketing*(1+marketing_growth)^2*5)+(opex_cloud_base*5+(adoption_max/(1+EXP(-adoption_steepness*1.15*(2028-adoption_midpoint)))*(1-churn_rate))*vcr_per_enterprise*12*cloud_per_1M_vcr/1000000*5)+((opex_branding+opex_external+opex_legal+opex_security+opex_partner_mgmt)*5)+(capex_total*capex_maintenance_pct*4)))*(1-cit_rate))/(1+discount_rate)^2.5 | F12: =((((adoption_max/(1+EXP(-adoption_steepness*1.3*(2028-adoption_midpoint)))*(1-churn_rate))*(cert_fee_yr1*(1+cert_fee_escalation)^2.5+training_pct*training_fee+audit_fee)*5)+(IF((adoption_max/(1+EXP(-adoption_steepness*1.3*(2028-adoption_midpoint)))*(1-churn_rate))>=stage2_gate,ecom_market_base*(1+ecom_growth_rate)^4*platform_market_share*tx_take_rate*1000*3,0))-((IF((adoption_max/(1+EXP(-adoption_steepness*1.3*(2028-adoption_midpoint)))*(1-churn_rate))>=stage2_gate,ecom_market_base*(1+ecom_growth_rate)^4*platform_market_share*tx_take_rate*1000*3,0))*payment_proc_pct)-(capex_total+(33*30*12*(1+bhxh_rate)*(1+salary_escalation)^2*5)+(opex_marketing*(1+marketing_growth)^2*5)+(opex_cloud_base*5+(adoption_max/(1+EXP(-adoption_steepness*1.3*(2028-adoption_midpoint)))*(1-churn_rate))*vcr_per_enterprise*12*cloud_per_1M_vcr/1000000*5)+((opex_branding+opex_external+opex_legal+opex_security+opex_partner_mgmt)*5)+(capex_total*capex_maintenance_pct*4)))*(1-cit_rate))/(1+discount_rate)^2.5 | G12: =adoption_steepness | H12: ↑ steep → faster adopt
A13: Stage 2 gate | B13: =((((adoption_max/(1+EXP(-adoption_steepness*(2028-adoption_midpoint)))*(1-churn_rate))*(cert_fee_yr1*(1+cert_fee_escalation)^2.5+training_pct*training_fee+audit_fee)*5)+(IF((adoption_max/(1+EXP(-adoption_steepness*(2028-adoption_midpoint)))*(1-churn_rate))>=stage2_gate*0.7,ecom_market_base*(1+ecom_growth_rate)^4*platform_market_share*tx_take_rate*1000*3,0))-((IF((adoption_max/(1+EXP(-adoption_steepness*(2028-adoption_midpoint)))*(1-churn_rate))>=stage2_gate*0.7,ecom_market_base*(1+ecom_growth_rate)^4*platform_market_share*tx_take_rate*1000*3,0))*payment_proc_pct)-(capex_total+(33*30*12*(1+bhxh_rate)*(1+salary_escalation)^2*5)+(opex_marketing*(1+marketing_growth)^2*5)+(opex_cloud_base*5+(adoption_max/(1+EXP(-adoption_steepness*(2028-adoption_midpoint)))*(1-churn_rate))*vcr_per_enterprise*12*cloud_per_1M_vcr/1000000*5)+((opex_branding+opex_external+opex_legal+opex_security+opex_partner_mgmt)*5)+(capex_total*capex_maintenance_pct*4)))*(1-cit_rate))/(1+discount_rate)^2.5 | C13: =((((adoption_max/(1+EXP(-adoption_steepness*(2028-adoption_midpoint)))*(1-churn_rate))*(cert_fee_yr1*(1+cert_fee_escalation)^2.5+training_pct*training_fee+audit_fee)*5)+(IF((adoption_max/(1+EXP(-adoption_steepness*(2028-adoption_midpoint)))*(1-churn_rate))>=stage2_gate*0.85,ecom_market_base*(1+ecom_growth_rate)^4*platform_market_share*tx_take_rate*1000*3,0))-((IF((adoption_max/(1+EXP(-adoption_steepness*(2028-adoption_midpoint)))*(1-churn_rate))>=stage2_gate*0.85,ecom_market_base*(1+ecom_growth_rate)^4*platform_market_share*tx_take_rate*1000*3,0))*payment_proc_pct)-(capex_total+(33*30*12*(1+bhxh_rate)*(1+salary_escalation)^2*5)+(opex_marketing*(1+marketing_growth)^2*5)+(opex_cloud_base*5+(adoption_max/(1+EXP(-adoption_steepness*(2028-adoption_midpoint)))*(1-churn_rate))*vcr_per_enterprise*12*cloud_per_1M_vcr/1000000*5)+((opex_branding+opex_external+opex_legal+opex_security+opex_partner_mgmt)*5)+(capex_total*capex_maintenance_pct*4)))*(1-cit_rate))/(1+discount_rate)^2.5 | D13: =((((adoption_max/(1+EXP(-adoption_steepness*(2028-adoption_midpoint)))*(1-churn_rate))*(cert_fee_yr1*(1+cert_fee_escalation)^2.5+training_pct*training_fee+audit_fee)*5)+(IF((adoption_max/(1+EXP(-adoption_steepness*(2028-adoption_midpoint)))*(1-churn_rate))>=stage2_gate*1,ecom_market_base*(1+ecom_growth_rate)^4*platform_market_share*tx_take_rate*1000*3,0))-((IF((adoption_max/(1+EXP(-adoption_steepness*(2028-adoption_midpoint)))*(1-churn_rate))>=stage2_gate*1,ecom_market_base*(1+ecom_growth_rate)^4*platform_market_share*tx_take_rate*1000*3,0))*payment_proc_pct)-(capex_total+(33*30*12*(1+bhxh_rate)*(1+salary_escalation)^2*5)+(opex_marketing*(1+marketing_growth)^2*5)+(opex_cloud_base*5+(adoption_max/(1+EXP(-adoption_steepness*(2028-adoption_midpoint)))*(1-churn_rate))*vcr_per_enterprise*12*cloud_per_1M_vcr/1000000*5)+((opex_branding+opex_external+opex_legal+opex_security+opex_partner_mgmt)*5)+(capex_total*capex_maintenance_pct*4)))*(1-cit_rate))/(1+discount_rate)^2.5 | E13: =((((adoption_max/(1+EXP(-adoption_steepness*(2028-adoption_midpoint)))*(1-churn_rate))*(cert_fee_yr1*(1+cert_fee_escalation)^2.5+training_pct*training_fee+audit_fee)*5)+(IF((adoption_max/(1+EXP(-adoption_steepness*(2028-adoption_midpoint)))*(1-churn_rate))>=stage2_gate*1.15,ecom_market_base*(1+ecom_growth_rate)^4*platform_market_share*tx_take_rate*1000*3,0))-((IF((adoption_max/(1+EXP(-adoption_steepness*(2028-adoption_midpoint)))*(1-churn_rate))>=stage2_gate*1.15,ecom_market_base*(1+ecom_growth_rate)^4*platform_market_share*tx_take_rate*1000*3,0))*payment_proc_pct)-(capex_total+(33*30*12*(1+bhxh_rate)*(1+salary_escalation)^2*5)+(opex_marketing*(1+marketing_growth)^2*5)+(opex_cloud_base*5+(adoption_max/(1+EXP(-adoption_steepness*(2028-adoption_midpoint)))*(1-churn_rate))*vcr_per_enterprise*12*cloud_per_1M_vcr/1000000*5)+((opex_branding+opex_external+opex_legal+opex_security+opex_partner_mgmt)*5)+(capex_total*capex_maintenance_pct*4)))*(1-cit_rate))/(1+discount_rate)^2.5 | F13: =((((adoption_max/(1+EXP(-adoption_steepness*(2028-adoption_midpoint)))*(1-churn_rate))*(cert_fee_yr1*(1+cert_fee_escalation)^2.5+training_pct*training_fee+audit_fee)*5)+(IF((adoption_max/(1+EXP(-adoption_steepness*(2028-adoption_midpoint)))*(1-churn_rate))>=stage2_gate*1.3,ecom_market_base*(1+ecom_growth_rate)^4*platform_market_share*tx_take_rate*1000*3,0))-((IF((adoption_max/(1+EXP(-adoption_steepness*(2028-adoption_midpoint)))*(1-churn_rate))>=stage2_gate*1.3,ecom_market_base*(1+ecom_growth_rate)^4*platform_market_share*tx_take_rate*1000*3,0))*payment_proc_pct)-(capex_total+(33*30*12*(1+bhxh_rate)*(1+salary_escalation)^2*5)+(opex_marketing*(1+marketing_growth)^2*5)+(opex_cloud_base*5+(adoption_max/(1+EXP(-adoption_steepness*(2028-adoption_midpoint)))*(1-churn_rate))*vcr_per_enterprise*12*cloud_per_1M_vcr/1000000*5)+((opex_branding+opex_external+opex_legal+opex_security+opex_partner_mgmt)*5)+(capex_total*capex_maintenance_pct*4)))*(1-cit_rate))/(1+discount_rate)^2.5 | G13: =stage2_gate | H13: ↑ gate → later Stage 2
A14: Cloud base cost | B14: =((((adoption_max/(1+EXP(-adoption_steepness*(2028-adoption_midpoint)))*(1-churn_rate))*(cert_fee_yr1*(1+cert_fee_escalation)^2.5+training_pct*training_fee+audit_fee)*5)+(IF((adoption_max/(1+EXP(-adoption_steepness*(2028-adoption_midpoint)))*(1-churn_rate))>=stage2_gate,ecom_market_base*(1+ecom_growth_rate)^4*platform_market_share*tx_take_rate*1000*3,0))-((IF((adoption_max/(1+EXP(-adoption_steepness*(2028-adoption_midpoint)))*(1-churn_rate))>=stage2_gate,ecom_market_base*(1+ecom_growth_rate)^4*platform_market_share*tx_take_rate*1000*3,0))*payment_proc_pct)-(capex_total+(33*30*12*(1+bhxh_rate)*(1+salary_escalation)^2*5)+(opex_marketing*(1+marketing_growth)^2*5)+(opex_cloud_base*0.7*5+(adoption_max/(1+EXP(-adoption_steepness*(2028-adoption_midpoint)))*(1-churn_rate))*vcr_per_enterprise*12*cloud_per_1M_vcr/1000000*5)+((opex_branding+opex_external+opex_legal+opex_security+opex_partner_mgmt)*5)+(capex_total*capex_maintenance_pct*4)))*(1-cit_rate))/(1+discount_rate)^2.5 | C14: =((((adoption_max/(1+EXP(-adoption_steepness*(2028-adoption_midpoint)))*(1-churn_rate))*(cert_fee_yr1*(1+cert_fee_escalation)^2.5+training_pct*training_fee+audit_fee)*5)+(IF((adoption_max/(1+EXP(-adoption_steepness*(2028-adoption_midpoint)))*(1-churn_rate))>=stage2_gate,ecom_market_base*(1+ecom_growth_rate)^4*platform_market_share*tx_take_rate*1000*3,0))-((IF((adoption_max/(1+EXP(-adoption_steepness*(2028-adoption_midpoint)))*(1-churn_rate))>=stage2_gate,ecom_market_base*(1+ecom_growth_rate)^4*platform_market_share*tx_take_rate*1000*3,0))*payment_proc_pct)-(capex_total+(33*30*12*(1+bhxh_rate)*(1+salary_escalation)^2*5)+(opex_marketing*(1+marketing_growth)^2*5)+(opex_cloud_base*0.85*5+(adoption_max/(1+EXP(-adoption_steepness*(2028-adoption_midpoint)))*(1-churn_rate))*vcr_per_enterprise*12*cloud_per_1M_vcr/1000000*5)+((opex_branding+opex_external+opex_legal+opex_security+opex_partner_mgmt)*5)+(capex_total*capex_maintenance_pct*4)))*(1-cit_rate))/(1+discount_rate)^2.5 | D14: =((((adoption_max/(1+EXP(-adoption_steepness*(2028-adoption_midpoint)))*(1-churn_rate))*(cert_fee_yr1*(1+cert_fee_escalation)^2.5+training_pct*training_fee+audit_fee)*5)+(IF((adoption_max/(1+EXP(-adoption_steepness*(2028-adoption_midpoint)))*(1-churn_rate))>=stage2_gate,ecom_market_base*(1+ecom_growth_rate)^4*platform_market_share*tx_take_rate*1000*3,0))-((IF((adoption_max/(1+EXP(-adoption_steepness*(2028-adoption_midpoint)))*(1-churn_rate))>=stage2_gate,ecom_market_base*(1+ecom_growth_rate)^4*platform_market_share*tx_take_rate*1000*3,0))*payment_proc_pct)-(capex_total+(33*30*12*(1+bhxh_rate)*(1+salary_escalation)^2*5)+(opex_marketing*(1+marketing_growth)^2*5)+(opex_cloud_base*1*5+(adoption_max/(1+EXP(-adoption_steepness*(2028-adoption_midpoint)))*(1-churn_rate))*vcr_per_enterprise*12*cloud_per_1M_vcr/1000000*5)+((opex_branding+opex_external+opex_legal+opex_security+opex_partner_mgmt)*5)+(capex_total*capex_maintenance_pct*4)))*(1-cit_rate))/(1+discount_rate)^2.5 | E14: =((((adoption_max/(1+EXP(-adoption_steepness*(2028-adoption_midpoint)))*(1-churn_rate))*(cert_fee_yr1*(1+cert_fee_escalation)^2.5+training_pct*training_fee+audit_fee)*5)+(IF((adoption_max/(1+EXP(-adoption_steepness*(2028-adoption_midpoint)))*(1-churn_rate))>=stage2_gate,ecom_market_base*(1+ecom_growth_rate)^4*platform_market_share*tx_take_rate*1000*3,0))-((IF((adoption_max/(1+EXP(-adoption_steepness*(2028-adoption_midpoint)))*(1-churn_rate))>=stage2_gate,ecom_market_base*(1+ecom_growth_rate)^4*platform_market_share*tx_take_rate*1000*3,0))*payment_proc_pct)-(capex_total+(33*30*12*(1+bhxh_rate)*(1+salary_escalation)^2*5)+(opex_marketing*(1+marketing_growth)^2*5)+(opex_cloud_base*1.15*5+(adoption_max/(1+EXP(-adoption_steepness*(2028-adoption_midpoint)))*(1-churn_rate))*vcr_per_enterprise*12*cloud_per_1M_vcr/1000000*5)+((opex_branding+opex_external+opex_legal+opex_security+opex_partner_mgmt)*5)+(capex_total*capex_maintenance_pct*4)))*(1-cit_rate))/(1+discount_rate)^2.5 | F14: =((((adoption_max/(1+EXP(-adoption_steepness*(2028-adoption_midpoint)))*(1-churn_rate))*(cert_fee_yr1*(1+cert_fee_escalation)^2.5+training_pct*training_fee+audit_fee)*5)+(IF((adoption_max/(1+EXP(-adoption_steepness*(2028-adoption_midpoint)))*(1-churn_rate))>=stage2_gate,ecom_market_base*(1+ecom_growth_rate)^4*platform_market_share*tx_take_rate*1000*3,0))-((IF((adoption_max/(1+EXP(-adoption_steepness*(2028-adoption_midpoint)))*(1-churn_rate))>=stage2_gate,ecom_market_base*(1+ecom_growth_rate)^4*platform_market_share*tx_take_rate*1000*3,0))*payment_proc_pct)-(capex_total+(33*30*12*(1+bhxh_rate)*(1+salary_escalation)^2*5)+(opex_marketing*(1+marketing_growth)^2*5)+(opex_cloud_base*1.3*5+(adoption_max/(1+EXP(-adoption_steepness*(2028-adoption_midpoint)))*(1-churn_rate))*vcr_per_enterprise*12*cloud_per_1M_vcr/1000000*5)+((opex_branding+opex_external+opex_legal+opex_security+opex_partner_mgmt)*5)+(capex_total*capex_maintenance_pct*4)))*(1-cit_rate))/(1+discount_rate)^2.5 | G14: =opex_cloud_base | H14: ↑ cloud → ↓ profit
A15: BHXH rate | B15: =((((adoption_max/(1+EXP(-adoption_steepness*(2028-adoption_midpoint)))*(1-churn_rate))*(cert_fee_yr1*(1+cert_fee_escalation)^2.5+training_pct*training_fee+audit_fee)*5)+(IF((adoption_max/(1+EXP(-adoption_steepness*(2028-adoption_midpoint)))*(1-churn_rate))>=stage2_gate,ecom_market_base*(1+ecom_growth_rate)^4*platform_market_share*tx_take_rate*1000*3,0))-((IF((adoption_max/(1+EXP(-adoption_steepness*(2028-adoption_midpoint)))*(1-churn_rate))>=stage2_gate,ecom_market_base*(1+ecom_growth_rate)^4*platform_market_share*tx_take_rate*1000*3,0))*payment_proc_pct)-(capex_total+(33*30*12*(1+bhxh_rate*0.7)*(1+salary_escalation)^2*5)+(opex_marketing*(1+marketing_growth)^2*5)+(opex_cloud_base*5+(adoption_max/(1+EXP(-adoption_steepness*(2028-adoption_midpoint)))*(1-churn_rate))*vcr_per_enterprise*12*cloud_per_1M_vcr/1000000*5)+((opex_branding+opex_external+opex_legal+opex_security+opex_partner_mgmt)*5)+(capex_total*capex_maintenance_pct*4)))*(1-cit_rate))/(1+discount_rate)^2.5 | C15: =((((adoption_max/(1+EXP(-adoption_steepness*(2028-adoption_midpoint)))*(1-churn_rate))*(cert_fee_yr1*(1+cert_fee_escalation)^2.5+training_pct*training_fee+audit_fee)*5)+(IF((adoption_max/(1+EXP(-adoption_steepness*(2028-adoption_midpoint)))*(1-churn_rate))>=stage2_gate,ecom_market_base*(1+ecom_growth_rate)^4*platform_market_share*tx_take_rate*1000*3,0))-((IF((adoption_max/(1+EXP(-adoption_steepness*(2028-adoption_midpoint)))*(1-churn_rate))>=stage2_gate,ecom_market_base*(1+ecom_growth_rate)^4*platform_market_share*tx_take_rate*1000*3,0))*payment_proc_pct)-(capex_total+(33*30*12*(1+bhxh_rate*0.85)*(1+salary_escalation)^2*5)+(opex_marketing*(1+marketing_growth)^2*5)+(opex_cloud_base*5+(adoption_max/(1+EXP(-adoption_steepness*(2028-adoption_midpoint)))*(1-churn_rate))*vcr_per_enterprise*12*cloud_per_1M_vcr/1000000*5)+((opex_branding+opex_external+opex_legal+opex_security+opex_partner_mgmt)*5)+(capex_total*capex_maintenance_pct*4)))*(1-cit_rate))/(1+discount_rate)^2.5 | D15: =((((adoption_max/(1+EXP(-adoption_steepness*(2028-adoption_midpoint)))*(1-churn_rate))*(cert_fee_yr1*(1+cert_fee_escalation)^2.5+training_pct*training_fee+audit_fee)*5)+(IF((adoption_max/(1+EXP(-adoption_steepness*(2028-adoption_midpoint)))*(1-churn_rate))>=stage2_gate,ecom_market_base*(1+ecom_growth_rate)^4*platform_market_share*tx_take_rate*1000*3,0))-((IF((adoption_max/(1+EXP(-adoption_steepness*(2028-adoption_midpoint)))*(1-churn_rate))>=stage2_gate,ecom_market_base*(1+ecom_growth_rate)^4*platform_market_share*tx_take_rate*1000*3,0))*payment_proc_pct)-(capex_total+(33*30*12*(1+bhxh_rate*1)*(1+salary_escalation)^2*5)+(opex_marketing*(1+marketing_growth)^2*5)+(opex_cloud_base*5+(adoption_max/(1+EXP(-adoption_steepness*(2028-adoption_midpoint)))*(1-churn_rate))*vcr_per_enterprise*12*cloud_per_1M_vcr/1000000*5)+((opex_branding+opex_external+opex_legal+opex_security+opex_partner_mgmt)*5)+(capex_total*capex_maintenance_pct*4)))*(1-cit_rate))/(1+discount_rate)^2.5 | E15: =((((adoption_max/(1+EXP(-adoption_steepness*(2028-adoption_midpoint)))*(1-churn_rate))*(cert_fee_yr1*(1+cert_fee_escalation)^2.5+training_pct*training_fee+audit_fee)*5)+(IF((adoption_max/(1+EXP(-adoption_steepness*(2028-adoption_midpoint)))*(1-churn_rate))>=stage2_gate,ecom_market_base*(1+ecom_growth_rate)^4*platform_market_share*tx_take_rate*1000*3,0))-((IF((adoption_max/(1+EXP(-adoption_steepness*(2028-adoption_midpoint)))*(1-churn_rate))>=stage2_gate,ecom_market_base*(1+ecom_growth_rate)^4*platform_market_share*tx_take_rate*1000*3,0))*payment_proc_pct)-(capex_total+(33*30*12*(1+bhxh_rate*1.15)*(1+salary_escalation)^2*5)+(opex_marketing*(1+marketing_growth)^2*5)+(opex_cloud_base*5+(adoption_max/(1+EXP(-adoption_steepness*(2028-adoption_midpoint)))*(1-churn_rate))*vcr_per_enterprise*12*cloud_per_1M_vcr/1000000*5)+((opex_branding+opex_external+opex_legal+opex_security+opex_partner_mgmt)*5)+(capex_total*capex_maintenance_pct*4)))*(1-cit_rate))/(1+discount_rate)^2.5 | F15: =((((adoption_max/(1+EXP(-adoption_steepness*(2028-adoption_midpoint)))*(1-churn_rate))*(cert_fee_yr1*(1+cert_fee_escalation)^2.5+training_pct*training_fee+audit_fee)*5)+(IF((adoption_max/(1+EXP(-adoption_steepness*(2028-adoption_midpoint)))*(1-churn_rate))>=stage2_gate,ecom_market_base*(1+ecom_growth_rate)^4*platform_market_share*tx_take_rate*1000*3,0))-((IF((adoption_max/(1+EXP(-adoption_steepness*(2028-adoption_midpoint)))*(1-churn_rate))>=stage2_gate,ecom_market_base*(1+ecom_growth_rate)^4*platform_market_share*tx_take_rate*1000*3,0))*payment_proc_pct)-(capex_total+(33*30*12*(1+bhxh_rate*1.3)*(1+salary_escalation)^2*5)+(opex_marketing*(1+marketing_growth)^2*5)+(opex_cloud_base*5+(adoption_max/(1+EXP(-adoption_steepness*(2028-adoption_midpoint)))*(1-churn_rate))*vcr_per_enterprise*12*cloud_per_1M_vcr/1000000*5)+((opex_branding+opex_external+opex_legal+opex_security+opex_partner_mgmt)*5)+(capex_total*capex_maintenance_pct*4)))*(1-cit_rate))/(1+discount_rate)^2.5 | G15: =bhxh_rate | H15: ↑ BHXH → ↑ HR cost
A16: CIT rate | B16: =((((adoption_max/(1+EXP(-adoption_steepness*(2028-adoption_midpoint)))*(1-churn_rate))*(cert_fee_yr1*(1+cert_fee_escalation)^2.5+training_pct*training_fee+audit_fee)*5)+(IF((adoption_max/(1+EXP(-adoption_steepness*(2028-adoption_midpoint)))*(1-churn_rate))>=stage2_gate,ecom_market_base*(1+ecom_growth_rate)^4*platform_market_share*tx_take_rate*1000*3,0))-((IF((adoption_max/(1+EXP(-adoption_steepness*(2028-adoption_midpoint)))*(1-churn_rate))>=stage2_gate,ecom_market_base*(1+ecom_growth_rate)^4*platform_market_share*tx_take_rate*1000*3,0))*payment_proc_pct)-(capex_total+(33*30*12*(1+bhxh_rate)*(1+salary_escalation)^2*5)+(opex_marketing*(1+marketing_growth)^2*5)+(opex_cloud_base*5+(adoption_max/(1+EXP(-adoption_steepness*(2028-adoption_midpoint)))*(1-churn_rate))*vcr_per_enterprise*12*cloud_per_1M_vcr/1000000*5)+((opex_branding+opex_external+opex_legal+opex_security+opex_partner_mgmt)*5)+(capex_total*capex_maintenance_pct*4)))*(1-cit_rate*0.7))/(1+discount_rate)^2.5 | C16: =((((adoption_max/(1+EXP(-adoption_steepness*(2028-adoption_midpoint)))*(1-churn_rate))*(cert_fee_yr1*(1+cert_fee_escalation)^2.5+training_pct*training_fee+audit_fee)*5)+(IF((adoption_max/(1+EXP(-adoption_steepness*(2028-adoption_midpoint)))*(1-churn_rate))>=stage2_gate,ecom_market_base*(1+ecom_growth_rate)^4*platform_market_share*tx_take_rate*1000*3,0))-((IF((adoption_max/(1+EXP(-adoption_steepness*(2028-adoption_midpoint)))*(1-churn_rate))>=stage2_gate,ecom_market_base*(1+ecom_growth_rate)^4*platform_market_share*tx_take_rate*1000*3,0))*payment_proc_pct)-(capex_total+(33*30*12*(1+bhxh_rate)*(1+salary_escalation)^2*5)+(opex_marketing*(1+marketing_growth)^2*5)+(opex_cloud_base*5+(adoption_max/(1+EXP(-adoption_steepness*(2028-adoption_midpoint)))*(1-churn_rate))*vcr_per_enterprise*12*cloud_per_1M_vcr/1000000*5)+((opex_branding+opex_external+opex_legal+opex_security+opex_partner_mgmt)*5)+(capex_total*capex_maintenance_pct*4)))*(1-cit_rate*0.85))/(1+discount_rate)^2.5 | D16: =((((adoption_max/(1+EXP(-adoption_steepness*(2028-adoption_midpoint)))*(1-churn_rate))*(cert_fee_yr1*(1+cert_fee_escalation)^2.5+training_pct*training_fee+audit_fee)*5)+(IF((adoption_max/(1+EXP(-adoption_steepness*(2028-adoption_midpoint)))*(1-churn_rate))>=stage2_gate,ecom_market_base*(1+ecom_growth_rate)^4*platform_market_share*tx_take_rate*1000*3,0))-((IF((adoption_max/(1+EXP(-adoption_steepness*(2028-adoption_midpoint)))*(1-churn_rate))>=stage2_gate,ecom_market_base*(1+ecom_growth_rate)^4*platform_market_share*tx_take_rate*1000*3,0))*payment_proc_pct)-(capex_total+(33*30*12*(1+bhxh_rate)*(1+salary_escalation)^2*5)+(opex_marketing*(1+marketing_growth)^2*5)+(opex_cloud_base*5+(adoption_max/(1+EXP(-adoption_steepness*(2028-adoption_midpoint)))*(1-churn_rate))*vcr_per_enterprise*12*cloud_per_1M_vcr/1000000*5)+((opex_branding+opex_external+opex_legal+opex_security+opex_partner_mgmt)*5)+(capex_total*capex_maintenance_pct*4)))*(1-cit_rate*1))/(1+discount_rate)^2.5 | E16: =((((adoption_max/(1+EXP(-adoption_steepness*(2028-adoption_midpoint)))*(1-churn_rate))*(cert_fee_yr1*(1+cert_fee_escalation)^2.5+training_pct*training_fee+audit_fee)*5)+(IF((adoption_max/(1+EXP(-adoption_steepness*(2028-adoption_midpoint)))*(1-churn_rate))>=stage2_gate,ecom_market_base*(1+ecom_growth_rate)^4*platform_market_share*tx_take_rate*1000*3,0))-((IF((adoption_max/(1+EXP(-adoption_steepness*(2028-adoption_midpoint)))*(1-churn_rate))>=stage2_gate,ecom_market_base*(1+ecom_growth_rate)^4*platform_market_share*tx_take_rate*1000*3,0))*payment_proc_pct)-(capex_total+(33*30*12*(1+bhxh_rate)*(1+salary_escalation)^2*5)+(opex_marketing*(1+marketing_growth)^2*5)+(opex_cloud_base*5+(adoption_max/(1+EXP(-adoption_steepness*(2028-adoption_midpoint)))*(1-churn_rate))*vcr_per_enterprise*12*cloud_per_1M_vcr/1000000*5)+((opex_branding+opex_external+opex_legal+opex_security+opex_partner_mgmt)*5)+(capex_total*capex_maintenance_pct*4)))*(1-cit_rate*1.15))/(1+discount_rate)^2.5 | F16: =((((adoption_max/(1+EXP(-adoption_steepness*(2028-adoption_midpoint)))*(1-churn_rate))*(cert_fee_yr1*(1+cert_fee_escalation)^2.5+training_pct*training_fee+audit_fee)*5)+(IF((adoption_max/(1+EXP(-adoption_steepness*(2028-adoption_midpoint)))*(1-churn_rate))>=stage2_gate,ecom_market_base*(1+ecom_growth_rate)^4*platform_market_share*tx_take_rate*1000*3,0))-((IF((adoption_max/(1+EXP(-adoption_steepness*(2028-adoption_midpoint)))*(1-churn_rate))>=stage2_gate,ecom_market_base*(1+ecom_growth_rate)^4*platform_market_share*tx_take_rate*1000*3,0))*payment_proc_pct)-(capex_total+(33*30*12*(1+bhxh_rate)*(1+salary_escalation)^2*5)+(opex_marketing*(1+marketing_growth)^2*5)+(opex_cloud_base*5+(adoption_max/(1+EXP(-adoption_steepness*(2028-adoption_midpoint)))*(1-churn_rate))*vcr_per_enterprise*12*cloud_per_1M_vcr/1000000*5)+((opex_branding+opex_external+opex_legal+opex_security+opex_partner_mgmt)*5)+(capex_total*capex_maintenance_pct*4)))*(1-cit_rate*1.3))/(1+discount_rate)^2.5 | G16: =cit_rate | H16: ↑ tax → ↓ net income
A19: TWO-WAY NPV: adoption_max × platform_market_share (Tr VND)
A20: adoption ↓ \ mkt_share → | B20: 0.001 | C20: 0.003 | D20: 0.005 | E20: 0.008 | F20: 0.01 | G20: 0.015 | H20: 0.02
A21: 200 | B21: =((((200/(1+EXP(-adoption_steepness*(2028-adoption_midpoint)))*(1-churn_rate))*(cert_fee_yr1*(1+cert_fee_escalation)^2.5+training_pct*training_fee+audit_fee)*5)+(IF((200/(1+EXP(-adoption_steepness*(2028-adoption_midpoint)))*(1-churn_rate))>=stage2_gate,ecom_market_base*(1+ecom_growth_rate)^4*0.001*tx_take_rate*1000*3,0))-((IF((200/(1+EXP(-adoption_steepness*(2028-adoption_midpoint)))*(1-churn_rate))>=stage2_gate,ecom_market_base*(1+ecom_growth_rate)^4*0.001*tx_take_rate*1000*3,0))*payment_proc_pct)-(capex_total+(33*30*12*(1+bhxh_rate)*(1+salary_escalation)^2*5)+(opex_marketing*(1+marketing_growth)^2*5)+(opex_cloud_base*5+(200/(1+EXP(-adoption_steepness*(2028-adoption_midpoint)))*(1-churn_rate))*vcr_per_enterprise*12*cloud_per_1M_vcr/1000000*5)+((opex_branding+opex_external+opex_legal+opex_security+opex_partner_mgmt)*5)+(capex_total*capex_maintenance_pct*4)))*(1-cit_rate))/(1+discount_rate)^2.5 | C21: =((((200/(1+EXP(-adoption_steepness*(2028-adoption_midpoint)))*(1-churn_rate))*(cert_fee_yr1*(1+cert_fee_escalation)^2.5+training_pct*training_fee+audit_fee)*5)+(IF((200/(1+EXP(-adoption_steepness*(2028-adoption_midpoint)))*(1-churn_rate))>=stage2_gate,ecom_market_base*(1+ecom_growth_rate)^4*0.003*tx_take_rate*1000*3,0))-((IF((200/(1+EXP(-adoption_steepness*(2028-adoption_midpoint)))*(1-churn_rate))>=stage2_gate,ecom_market_base*(1+ecom_growth_rate)^4*0.003*tx_take_rate*1000*3,0))*payment_proc_pct)-(capex_total+(33*30*12*(1+bhxh_rate)*(1+salary_escalation)^2*5)+(opex_marketing*(1+marketing_growth)^2*5)+(opex_cloud_base*5+(200/(1+EXP(-adoption_steepness*(2028-adoption_midpoint)))*(1-churn_rate))*vcr_per_enterprise*12*cloud_per_1M_vcr/1000000*5)+((opex_branding+opex_external+opex_legal+opex_security+opex_partner_mgmt)*5)+(capex_total*capex_maintenance_pct*4)))*(1-cit_rate))/(1+discount_rate)^2.5 | D21: =((((200/(1+EXP(-adoption_steepness*(2028-adoption_midpoint)))*(1-churn_rate))*(cert_fee_yr1*(1+cert_fee_escalation)^2.5+training_pct*training_fee+audit_fee)*5)+(IF((200/(1+EXP(-adoption_steepness*(2028-adoption_midpoint)))*(1-churn_rate))>=stage2_gate,ecom_market_base*(1+ecom_growth_rate)^4*0.005*tx_take_rate*1000*3,0))-((IF((200/(1+EXP(-adoption_steepness*(2028-adoption_midpoint)))*(1-churn_rate))>=stage2_gate,ecom_market_base*(1+ecom_growth_rate)^4*0.005*tx_take_rate*1000*3,0))*payment_proc_pct)-(capex_total+(33*30*12*(1+bhxh_rate)*(1+salary_escalation)^2*5)+(opex_marketing*(1+marketing_growth)^2*5)+(opex_cloud_base*5+(200/(1+EXP(-adoption_steepness*(2028-adoption_midpoint)))*(1-churn_rate))*vcr_per_enterprise*12*cloud_per_1M_vcr/1000000*5)+((opex_branding+opex_external+opex_legal+opex_security+opex_partner_mgmt)*5)+(capex_total*capex_maintenance_pct*4)))*(1-cit_rate))/(1+discount_rate)^2.5 | E21: =((((200/(1+EXP(-adoption_steepness*(2028-adoption_midpoint)))*(1-churn_rate))*(cert_fee_yr1*(1+cert_fee_escalation)^2.5+training_pct*training_fee+audit_fee)*5)+(IF((200/(1+EXP(-adoption_steepness*(2028-adoption_midpoint)))*(1-churn_rate))>=stage2_gate,ecom_market_base*(1+ecom_growth_rate)^4*0.008*tx_take_rate*1000*3,0))-((IF((200/(1+EXP(-adoption_steepness*(2028-adoption_midpoint)))*(1-churn_rate))>=stage2_gate,ecom_market_base*(1+ecom_growth_rate)^4*0.008*tx_take_rate*1000*3,0))*payment_proc_pct)-(capex_total+(33*30*12*(1+bhxh_rate)*(1+salary_escalation)^2*5)+(opex_marketing*(1+marketing_growth)^2*5)+(opex_cloud_base*5+(200/(1+EXP(-adoption_steepness*(2028-adoption_midpoint)))*(1-churn_rate))*vcr_per_enterprise*12*cloud_per_1M_vcr/1000000*5)+((opex_branding+opex_external+opex_legal+opex_security+opex_partner_mgmt)*5)+(capex_total*capex_maintenance_pct*4)))*(1-cit_rate))/(1+discount_rate)^2.5 | F21: =((((200/(1+EXP(-adoption_steepness*(2028-adoption_midpoint)))*(1-churn_rate))*(cert_fee_yr1*(1+cert_fee_escalation)^2.5+training_pct*training_fee+audit_fee)*5)+(IF((200/(1+EXP(-adoption_steepness*(2028-adoption_midpoint)))*(1-churn_rate))>=stage2_gate,ecom_market_base*(1+ecom_growth_rate)^4*0.01*tx_take_rate*1000*3,0))-((IF((200/(1+EXP(-adoption_steepness*(2028-adoption_midpoint)))*(1-churn_rate))>=stage2_gate,ecom_market_base*(1+ecom_growth_rate)^4*0.01*tx_take_rate*1000*3,0))*payment_proc_pct)-(capex_total+(33*30*12*(1+bhxh_rate)*(1+salary_escalation)^2*5)+(opex_marketing*(1+marketing_growth)^2*5)+(opex_cloud_base*5+(200/(1+EXP(-adoption_steepness*(2028-adoption_midpoint)))*(1-churn_rate))*vcr_per_enterprise*12*cloud_per_1M_vcr/1000000*5)+((opex_branding+opex_external+opex_legal+opex_security+opex_partner_mgmt)*5)+(capex_total*capex_maintenance_pct*4)))*(1-cit_rate))/(1+discount_rate)^2.5 | G21: =((((200/(1+EXP(-adoption_steepness*(2028-adoption_midpoint)))*(1-churn_rate))*(cert_fee_yr1*(1+cert_fee_escalation)^2.5+training_pct*training_fee+audit_fee)*5)+(IF((200/(1+EXP(-adoption_steepness*(2028-adoption_midpoint)))*(1-churn_rate))>=stage2_gate,ecom_market_base*(1+ecom_growth_rate)^4*0.015*tx_take_rate*1000*3,0))-((IF((200/(1+EXP(-adoption_steepness*(2028-adoption_midpoint)))*(1-churn_rate))>=stage2_gate,ecom_market_base*(1+ecom_growth_rate)^4*0.015*tx_take_rate*1000*3,0))*payment_proc_pct)-(capex_total+(33*30*12*(1+bhxh_rate)*(1+salary_escalation)^2*5)+(opex_marketing*(1+marketing_growth)^2*5)+(opex_cloud_base*5+(200/(1+EXP(-adoption_steepness*(2028-adoption_midpoint)))*(1-churn_rate))*vcr_per_enterprise*12*cloud_per_1M_vcr/1000000*5)+((opex_branding+opex_external+opex_legal+opex_security+opex_partner_mgmt)*5)+(capex_total*capex_maintenance_pct*4)))*(1-cit_rate))/(1+discount_rate)^2.5 | H21: =((((200/(1+EXP(-adoption_steepness*(2028-adoption_midpoint)))*(1-churn_rate))*(cert_fee_yr1*(1+cert_fee_escalation)^2.5+training_pct*training_fee+audit_fee)*5)+(IF((200/(1+EXP(-adoption_steepness*(2028-adoption_midpoint)))*(1-churn_rate))>=stage2_gate,ecom_market_base*(1+ecom_growth_rate)^4*0.02*tx_take_rate*1000*3,0))-((IF((200/(1+EXP(-adoption_steepness*(2028-adoption_midpoint)))*(1-churn_rate))>=stage2_gate,ecom_market_base*(1+ecom_growth_rate)^4*0.02*tx_take_rate*1000*3,0))*payment_proc_pct)-(capex_total+(33*30*12*(1+bhxh_rate)*(1+salary_escalation)^2*5)+(opex_marketing*(1+marketing_growth)^2*5)+(opex_cloud_base*5+(200/(1+EXP(-adoption_steepness*(2028-adoption_midpoint)))*(1-churn_rate))*vcr_per_enterprise*12*cloud_per_1M_vcr/1000000*5)+((opex_branding+opex_external+opex_legal+opex_security+opex_partner_mgmt)*5)+(capex_total*capex_maintenance_pct*4)))*(1-cit_rate))/(1+discount_rate)^2.5
A22: 400 | B22: =((((400/(1+EXP(-adoption_steepness*(2028-adoption_midpoint)))*(1-churn_rate))*(cert_fee_yr1*(1+cert_fee_escalation)^2.5+training_pct*training_fee+audit_fee)*5)+(IF((400/(1+EXP(-adoption_steepness*(2028-adoption_midpoint)))*(1-churn_rate))>=stage2_gate,ecom_market_base*(1+ecom_growth_rate)^4*0.001*tx_take_rate*1000*3,0))-((IF((400/(1+EXP(-adoption_steepness*(2028-adoption_midpoint)))*(1-churn_rate))>=stage2_gate,ecom_market_base*(1+ecom_growth_rate)^4*0.001*tx_take_rate*1000*3,0))*payment_proc_pct)-(capex_total+(33*30*12*(1+bhxh_rate)*(1+salary_escalation)^2*5)+(opex_marketing*(1+marketing_growth)^2*5)+(opex_cloud_base*5+(400/(1+EXP(-adoption_steepness*(2028-adoption_midpoint)))*(1-churn_rate))*vcr_per_enterprise*12*cloud_per_1M_vcr/1000000*5)+((opex_branding+opex_external+opex_legal+opex_security+opex_partner_mgmt)*5)+(capex_total*capex_maintenance_pct*4)))*(1-cit_rate))/(1+discount_rate)^2.5 | C22: =((((400/(1+EXP(-adoption_steepness*(2028-adoption_midpoint)))*(1-churn_rate))*(cert_fee_yr1*(1+cert_fee_escalation)^2.5+training_pct*training_fee+audit_fee)*5)+(IF((400/(1+EXP(-adoption_steepness*(2028-adoption_midpoint)))*(1-churn_rate))>=stage2_gate,ecom_market_base*(1+ecom_growth_rate)^4*0.003*tx_take_rate*1000*3,0))-((IF((400/(1+EXP(-adoption_steepness*(2028-adoption_midpoint)))*(1-churn_rate))>=stage2_gate,ecom_market_base*(1+ecom_growth_rate)^4*0.003*tx_take_rate*1000*3,0))*payment_proc_pct)-(capex_total+(33*30*12*(1+bhxh_rate)*(1+salary_escalation)^2*5)+(opex_marketing*(1+marketing_growth)^2*5)+(opex_cloud_base*5+(400/(1+EXP(-adoption_steepness*(2028-adoption_midpoint)))*(1-churn_rate))*vcr_per_enterprise*12*cloud_per_1M_vcr/1000000*5)+((opex_branding+opex_external+opex_legal+opex_security+opex_partner_mgmt)*5)+(capex_total*capex_maintenance_pct*4)))*(1-cit_rate))/(1+discount_rate)^2.5 | D22: =((((400/(1+EXP(-adoption_steepness*(2028-adoption_midpoint)))*(1-churn_rate))*(cert_fee_yr1*(1+cert_fee_escalation)^2.5+training_pct*training_fee+audit_fee)*5)+(IF((400/(1+EXP(-adoption_steepness*(2028-adoption_midpoint)))*(1-churn_rate))>=stage2_gate,ecom_market_base*(1+ecom_growth_rate)^4*0.005*tx_take_rate*1000*3,0))-((IF((400/(1+EXP(-adoption_steepness*(2028-adoption_midpoint)))*(1-churn_rate))>=stage2_gate,ecom_market_base*(1+ecom_growth_rate)^4*0.005*tx_take_rate*1000*3,0))*payment_proc_pct)-(capex_total+(33*30*12*(1+bhxh_rate)*(1+salary_escalation)^2*5)+(opex_marketing*(1+marketing_growth)^2*5)+(opex_cloud_base*5+(400/(1+EXP(-adoption_steepness*(2028-adoption_midpoint)))*(1-churn_rate))*vcr_per_enterprise*12*cloud_per_1M_vcr/1000000*5)+((opex_branding+opex_external+opex_legal+opex_security+opex_partner_mgmt)*5)+(capex_total*capex_maintenance_pct*4)))*(1-cit_rate))/(1+discount_rate)^2.5 | E22: =((((400/(1+EXP(-adoption_steepness*(2028-adoption_midpoint)))*(1-churn_rate))*(cert_fee_yr1*(1+cert_fee_escalation)^2.5+training_pct*training_fee+audit_fee)*5)+(IF((400/(1+EXP(-adoption_steepness*(2028-adoption_midpoint)))*(1-churn_rate))>=stage2_gate,ecom_market_base*(1+ecom_growth_rate)^4*0.008*tx_take_rate*1000*3,0))-((IF((400/(1+EXP(-adoption_steepness*(2028-adoption_midpoint)))*(1-churn_rate))>=stage2_gate,ecom_market_base*(1+ecom_growth_rate)^4*0.008*tx_take_rate*1000*3,0))*payment_proc_pct)-(capex_total+(33*30*12*(1+bhxh_rate)*(1+salary_escalation)^2*5)+(opex_marketing*(1+marketing_growth)^2*5)+(opex_cloud_base*5+(400/(1+EXP(-adoption_steepness*(2028-adoption_midpoint)))*(1-churn_rate))*vcr_per_enterprise*12*cloud_per_1M_vcr/1000000*5)+((opex_branding+opex_external+opex_legal+opex_security+opex_partner_mgmt)*5)+(capex_total*capex_maintenance_pct*4)))*(1-cit_rate))/(1+discount_rate)^2.5 | F22: =((((400/(1+EXP(-adoption_steepness*(2028-adoption_midpoint)))*(1-churn_rate))*(cert_fee_yr1*(1+cert_fee_escalation)^2.5+training_pct*training_fee+audit_fee)*5)+(IF((400/(1+EXP(-adoption_steepness*(2028-adoption_midpoint)))*(1-churn_rate))>=stage2_gate,ecom_market_base*(1+ecom_growth_rate)^4*0.01*tx_take_rate*1000*3,0))-((IF((400/(1+EXP(-adoption_steepness*(2028-adoption_midpoint)))*(1-churn_rate))>=stage2_gate,ecom_market_base*(1+ecom_growth_rate)^4*0.01*tx_take_rate*1000*3,0))*payment_proc_pct)-(capex_total+(33*30*12*(1+bhxh_rate)*(1+salary_escalation)^2*5)+(opex_marketing*(1+marketing_growth)^2*5)+(opex_cloud_base*5+(400/(1+EXP(-adoption_steepness*(2028-adoption_midpoint)))*(1-churn_rate))*vcr_per_enterprise*12*cloud_per_1M_vcr/1000000*5)+((opex_branding+opex_external+opex_legal+opex_security+opex_partner_mgmt)*5)+(capex_total*capex_maintenance_pct*4)))*(1-cit_rate))/(1+discount_rate)^2.5 | G22: =((((400/(1+EXP(-adoption_steepness*(2028-adoption_midpoint)))*(1-churn_rate))*(cert_fee_yr1*(1+cert_fee_escalation)^2.5+training_pct*training_fee+audit_fee)*5)+(IF((400/(1+EXP(-adoption_steepness*(2028-adoption_midpoint)))*(1-churn_rate))>=stage2_gate,ecom_market_base*(1+ecom_growth_rate)^4*0.015*tx_take_rate*1000*3,0))-((IF((400/(1+EXP(-adoption_steepness*(2028-adoption_midpoint)))*(1-churn_rate))>=stage2_gate,ecom_market_base*(1+ecom_growth_rate)^4*0.015*tx_take_rate*1000*3,0))*payment_proc_pct)-(capex_total+(33*30*12*(1+bhxh_rate)*(1+salary_escalation)^2*5)+(opex_marketing*(1+marketing_growth)^2*5)+(opex_cloud_base*5+(400/(1+EXP(-adoption_steepness*(2028-adoption_midpoint)))*(1-churn_rate))*vcr_per_enterprise*12*cloud_per_1M_vcr/1000000*5)+((opex_branding+opex_external+opex_legal+opex_security+opex_partner_mgmt)*5)+(capex_total*capex_maintenance_pct*4)))*(1-cit_rate))/(1+discount_rate)^2.5 | H22: =((((400/(1+EXP(-adoption_steepness*(2028-adoption_midpoint)))*(1-churn_rate))*(cert_fee_yr1*(1+cert_fee_escalation)^2.5+training_pct*training_fee+audit_fee)*5)+(IF((400/(1+EXP(-adoption_steepness*(2028-adoption_midpoint)))*(1-churn_rate))>=stage2_gate,ecom_market_base*(1+ecom_growth_rate)^4*0.02*tx_take_rate*1000*3,0))-((IF((400/(1+EXP(-adoption_steepness*(2028-adoption_midpoint)))*(1-churn_rate))>=stage2_gate,ecom_market_base*(1+ecom_growth_rate)^4*0.02*tx_take_rate*1000*3,0))*payment_proc_pct)-(capex_total+(33*30*12*(1+bhxh_rate)*(1+salary_escalation)^2*5)+(opex_marketing*(1+marketing_growth)^2*5)+(opex_cloud_base*5+(400/(1+EXP(-adoption_steepness*(2028-adoption_midpoint)))*(1-churn_rate))*vcr_per_enterprise*12*cloud_per_1M_vcr/1000000*5)+((opex_branding+opex_external+opex_legal+opex_security+opex_partner_mgmt)*5)+(capex_total*capex_maintenance_pct*4)))*(1-cit_rate))/(1+discount_rate)^2.5
A23: 600 | B23: =((((600/(1+EXP(-adoption_steepness*(2028-adoption_midpoint)))*(1-churn_rate))*(cert_fee_yr1*(1+cert_fee_escalation)^2.5+training_pct*training_fee+audit_fee)*5)+(IF((600/(1+EXP(-adoption_steepness*(2028-adoption_midpoint)))*(1-churn_rate))>=stage2_gate,ecom_market_base*(1+ecom_growth_rate)^4*0.001*tx_take_rate*1000*3,0))-((IF((600/(1+EXP(-adoption_steepness*(2028-adoption_midpoint)))*(1-churn_rate))>=stage2_gate,ecom_market_base*(1+ecom_growth_rate)^4*0.001*tx_take_rate*1000*3,0))*payment_proc_pct)-(capex_total+(33*30*12*(1+bhxh_rate)*(1+salary_escalation)^2*5)+(opex_marketing*(1+marketing_growth)^2*5)+(opex_cloud_base*5+(600/(1+EXP(-adoption_steepness*(2028-adoption_midpoint)))*(1-churn_rate))*vcr_per_enterprise*12*cloud_per_1M_vcr/1000000*5)+((opex_branding+opex_external+opex_legal+opex_security+opex_partner_mgmt)*5)+(capex_total*capex_maintenance_pct*4)))*(1-cit_rate))/(1+discount_rate)^2.5 | C23: =((((600/(1+EXP(-adoption_steepness*(2028-adoption_midpoint)))*(1-churn_rate))*(cert_fee_yr1*(1+cert_fee_escalation)^2.5+training_pct*training_fee+audit_fee)*5)+(IF((600/(1+EXP(-adoption_steepness*(2028-adoption_midpoint)))*(1-churn_rate))>=stage2_gate,ecom_market_base*(1+ecom_growth_rate)^4*0.003*tx_take_rate*1000*3,0))-((IF((600/(1+EXP(-adoption_steepness*(2028-adoption_midpoint)))*(1-churn_rate))>=stage2_gate,ecom_market_base*(1+ecom_growth_rate)^4*0.003*tx_take_rate*1000*3,0))*payment_proc_pct)-(capex_total+(33*30*12*(1+bhxh_rate)*(1+salary_escalation)^2*5)+(opex_marketing*(1+marketing_growth)^2*5)+(opex_cloud_base*5+(600/(1+EXP(-adoption_steepness*(2028-adoption_midpoint)))*(1-churn_rate))*vcr_per_enterprise*12*cloud_per_1M_vcr/1000000*5)+((opex_branding+opex_external+opex_legal+opex_security+opex_partner_mgmt)*5)+(capex_total*capex_maintenance_pct*4)))*(1-cit_rate))/(1+discount_rate)^2.5 | D23: =((((600/(1+EXP(-adoption_steepness*(2028-adoption_midpoint)))*(1-churn_rate))*(cert_fee_yr1*(1+cert_fee_escalation)^2.5+training_pct*training_fee+audit_fee)*5)+(IF((600/(1+EXP(-adoption_steepness*(2028-adoption_midpoint)))*(1-churn_rate))>=stage2_gate,ecom_market_base*(1+ecom_growth_rate)^4*0.005*tx_take_rate*1000*3,0))-((IF((600/(1+EXP(-adoption_steepness*(2028-adoption_midpoint)))*(1-churn_rate))>=stage2_gate,ecom_market_base*(1+ecom_growth_rate)^4*0.005*tx_take_rate*1000*3,0))*payment_proc_pct)-(capex_total+(33*30*12*(1+bhxh_rate)*(1+salary_escalation)^2*5)+(opex_marketing*(1+marketing_growth)^2*5)+(opex_cloud_base*5+(600/(1+EXP(-adoption_steepness*(2028-adoption_midpoint)))*(1-churn_rate))*vcr_per_enterprise*12*cloud_per_1M_vcr/1000000*5)+((opex_branding+opex_external+opex_legal+opex_security+opex_partner_mgmt)*5)+(capex_total*capex_maintenance_pct*4)))*(1-cit_rate))/(1+discount_rate)^2.5 | E23: =((((600/(1+EXP(-adoption_steepness*(2028-adoption_midpoint)))*(1-churn_rate))*(cert_fee_yr1*(1+cert_fee_escalation)^2.5+training_pct*training_fee+audit_fee)*5)+(IF((600/(1+EXP(-adoption_steepness*(2028-adoption_midpoint)))*(1-churn_rate))>=stage2_gate,ecom_market_base*(1+ecom_growth_rate)^4*0.008*tx_take_rate*1000*3,0))-((IF((600/(1+EXP(-adoption_steepness*(2028-adoption_midpoint)))*(1-churn_rate))>=stage2_gate,ecom_market_base*(1+ecom_growth_rate)^4*0.008*tx_take_rate*1000*3,0))*payment_proc_pct)-(capex_total+(33*30*12*(1+bhxh_rate)*(1+salary_escalation)^2*5)+(opex_marketing*(1+marketing_growth)^2*5)+(opex_cloud_base*5+(600/(1+EXP(-adoption_steepness*(2028-adoption_midpoint)))*(1-churn_rate))*vcr_per_enterprise*12*cloud_per_1M_vcr/1000000*5)+((opex_branding+opex_external+opex_legal+opex_security+opex_partner_mgmt)*5)+(capex_total*capex_maintenance_pct*4)))*(1-cit_rate))/(1+discount_rate)^2.5 | F23: =((((600/(1+EXP(-adoption_steepness*(2028-adoption_midpoint)))*(1-churn_rate))*(cert_fee_yr1*(1+cert_fee_escalation)^2.5+training_pct*training_fee+audit_fee)*5)+(IF((600/(1+EXP(-adoption_steepness*(2028-adoption_midpoint)))*(1-churn_rate))>=stage2_gate,ecom_market_base*(1+ecom_growth_rate)^4*0.01*tx_take_rate*1000*3,0))-((IF((600/(1+EXP(-adoption_steepness*(2028-adoption_midpoint)))*(1-churn_rate))>=stage2_gate,ecom_market_base*(1+ecom_growth_rate)^4*0.01*tx_take_rate*1000*3,0))*payment_proc_pct)-(capex_total+(33*30*12*(1+bhxh_rate)*(1+salary_escalation)^2*5)+(opex_marketing*(1+marketing_growth)^2*5)+(opex_cloud_base*5+(600/(1+EXP(-adoption_steepness*(2028-adoption_midpoint)))*(1-churn_rate))*vcr_per_enterprise*12*cloud_per_1M_vcr/1000000*5)+((opex_branding+opex_external+opex_legal+opex_security+opex_partner_mgmt)*5)+(capex_total*capex_maintenance_pct*4)))*(1-cit_rate))/(1+discount_rate)^2.5 | G23: =((((600/(1+EXP(-adoption_steepness*(2028-adoption_midpoint)))*(1-churn_rate))*(cert_fee_yr1*(1+cert_fee_escalation)^2.5+training_pct*training_fee+audit_fee)*5)+(IF((600/(1+EXP(-adoption_steepness*(2028-adoption_midpoint)))*(1-churn_rate))>=stage2_gate,ecom_market_base*(1+ecom_growth_rate)^4*0.015*tx_take_rate*1000*3,0))-((IF((600/(1+EXP(-adoption_steepness*(2028-adoption_midpoint)))*(1-churn_rate))>=stage2_gate,ecom_market_base*(1+ecom_growth_rate)^4*0.015*tx_take_rate*1000*3,0))*payment_proc_pct)-(capex_total+(33*30*12*(1+bhxh_rate)*(1+salary_escalation)^2*5)+(opex_marketing*(1+marketing_growth)^2*5)+(opex_cloud_base*5+(600/(1+EXP(-adoption_steepness*(2028-adoption_midpoint)))*(1-churn_rate))*vcr_per_enterprise*12*cloud_per_1M_vcr/1000000*5)+((opex_branding+opex_external+opex_legal+opex_security+opex_partner_mgmt)*5)+(capex_total*capex_maintenance_pct*4)))*(1-cit_rate))/(1+discount_rate)^2.5 | H23: =((((600/(1+EXP(-adoption_steepness*(2028-adoption_midpoint)))*(1-churn_rate))*(cert_fee_yr1*(1+cert_fee_escalation)^2.5+training_pct*training_fee+audit_fee)*5)+(IF((600/(1+EXP(-adoption_steepness*(2028-adoption_midpoint)))*(1-churn_rate))>=stage2_gate,ecom_market_base*(1+ecom_growth_rate)^4*0.02*tx_take_rate*1000*3,0))-((IF((600/(1+EXP(-adoption_steepness*(2028-adoption_midpoint)))*(1-churn_rate))>=stage2_gate,ecom_market_base*(1+ecom_growth_rate)^4*0.02*tx_take_rate*1000*3,0))*payment_proc_pct)-(capex_total+(33*30*12*(1+bhxh_rate)*(1+salary_escalation)^2*5)+(opex_marketing*(1+marketing_growth)^2*5)+(opex_cloud_base*5+(600/(1+EXP(-adoption_steepness*(2028-adoption_midpoint)))*(1-churn_rate))*vcr_per_enterprise*12*cloud_per_1M_vcr/1000000*5)+((opex_branding+opex_external+opex_legal+opex_security+opex_partner_mgmt)*5)+(capex_total*capex_maintenance_pct*4)))*(1-cit_rate))/(1+discount_rate)^2.5
A24: 800 | B24: =((((800/(1+EXP(-adoption_steepness*(2028-adoption_midpoint)))*(1-churn_rate))*(cert_fee_yr1*(1+cert_fee_escalation)^2.5+training_pct*training_fee+audit_fee)*5)+(IF((800/(1+EXP(-adoption_steepness*(2028-adoption_midpoint)))*(1-churn_rate))>=stage2_gate,ecom_market_base*(1+ecom_growth_rate)^4*0.001*tx_take_rate*1000*3,0))-((IF((800/(1+EXP(-adoption_steepness*(2028-adoption_midpoint)))*(1-churn_rate))>=stage2_gate,ecom_market_base*(1+ecom_growth_rate)^4*0.001*tx_take_rate*1000*3,0))*payment_proc_pct)-(capex_total+(33*30*12*(1+bhxh_rate)*(1+salary_escalation)^2*5)+(opex_marketing*(1+marketing_growth)^2*5)+(opex_cloud_base*5+(800/(1+EXP(-adoption_steepness*(2028-adoption_midpoint)))*(1-churn_rate))*vcr_per_enterprise*12*cloud_per_1M_vcr/1000000*5)+((opex_branding+opex_external+opex_legal+opex_security+opex_partner_mgmt)*5)+(capex_total*capex_maintenance_pct*4)))*(1-cit_rate))/(1+discount_rate)^2.5 | C24: =((((800/(1+EXP(-adoption_steepness*(2028-adoption_midpoint)))*(1-churn_rate))*(cert_fee_yr1*(1+cert_fee_escalation)^2.5+training_pct*training_fee+audit_fee)*5)+(IF((800/(1+EXP(-adoption_steepness*(2028-adoption_midpoint)))*(1-churn_rate))>=stage2_gate,ecom_market_base*(1+ecom_growth_rate)^4*0.003*tx_take_rate*1000*3,0))-((IF((800/(1+EXP(-adoption_steepness*(2028-adoption_midpoint)))*(1-churn_rate))>=stage2_gate,ecom_market_base*(1+ecom_growth_rate)^4*0.003*tx_take_rate*1000*3,0))*payment_proc_pct)-(capex_total+(33*30*12*(1+bhxh_rate)*(1+salary_escalation)^2*5)+(opex_marketing*(1+marketing_growth)^2*5)+(opex_cloud_base*5+(800/(1+EXP(-adoption_steepness*(2028-adoption_midpoint)))*(1-churn_rate))*vcr_per_enterprise*12*cloud_per_1M_vcr/1000000*5)+((opex_branding+opex_external+opex_legal+opex_security+opex_partner_mgmt)*5)+(capex_total*capex_maintenance_pct*4)))*(1-cit_rate))/(1+discount_rate)^2.5 | D24: =((((800/(1+EXP(-adoption_steepness*(2028-adoption_midpoint)))*(1-churn_rate))*(cert_fee_yr1*(1+cert_fee_escalation)^2.5+training_pct*training_fee+audit_fee)*5)+(IF((800/(1+EXP(-adoption_steepness*(2028-adoption_midpoint)))*(1-churn_rate))>=stage2_gate,ecom_market_base*(1+ecom_growth_rate)^4*0.005*tx_take_rate*1000*3,0))-((IF((800/(1+EXP(-adoption_steepness*(2028-adoption_midpoint)))*(1-churn_rate))>=stage2_gate,ecom_market_base*(1+ecom_growth_rate)^4*0.005*tx_take_rate*1000*3,0))*payment_proc_pct)-(capex_total+(33*30*12*(1+bhxh_rate)*(1+salary_escalation)^2*5)+(opex_marketing*(1+marketing_growth)^2*5)+(opex_cloud_base*5+(800/(1+EXP(-adoption_steepness*(2028-adoption_midpoint)))*(1-churn_rate))*vcr_per_enterprise*12*cloud_per_1M_vcr/1000000*5)+((opex_branding+opex_external+opex_legal+opex_security+opex_partner_mgmt)*5)+(capex_total*capex_maintenance_pct*4)))*(1-cit_rate))/(1+discount_rate)^2.5 | E24: =((((800/(1+EXP(-adoption_steepness*(2028-adoption_midpoint)))*(1-churn_rate))*(cert_fee_yr1*(1+cert_fee_escalation)^2.5+training_pct*training_fee+audit_fee)*5)+(IF((800/(1+EXP(-adoption_steepness*(2028-adoption_midpoint)))*(1-churn_rate))>=stage2_gate,ecom_market_base*(1+ecom_growth_rate)^4*0.008*tx_take_rate*1000*3,0))-((IF((800/(1+EXP(-adoption_steepness*(2028-adoption_midpoint)))*(1-churn_rate))>=stage2_gate,ecom_market_base*(1+ecom_growth_rate)^4*0.008*tx_take_rate*1000*3,0))*payment_proc_pct)-(capex_total+(33*30*12*(1+bhxh_rate)*(1+salary_escalation)^2*5)+(opex_marketing*(1+marketing_growth)^2*5)+(opex_cloud_base*5+(800/(1+EXP(-adoption_steepness*(2028-adoption_midpoint)))*(1-churn_rate))*vcr_per_enterprise*12*cloud_per_1M_vcr/1000000*5)+((opex_branding+opex_external+opex_legal+opex_security+opex_partner_mgmt)*5)+(capex_total*capex_maintenance_pct*4)))*(1-cit_rate))/(1+discount_rate)^2.5 | F24: =((((800/(1+EXP(-adoption_steepness*(2028-adoption_midpoint)))*(1-churn_rate))*(cert_fee_yr1*(1+cert_fee_escalation)^2.5+training_pct*training_fee+audit_fee)*5)+(IF((800/(1+EXP(-adoption_steepness*(2028-adoption_midpoint)))*(1-churn_rate))>=stage2_gate,ecom_market_base*(1+ecom_growth_rate)^4*0.01*tx_take_rate*1000*3,0))-((IF((800/(1+EXP(-adoption_steepness*(2028-adoption_midpoint)))*(1-churn_rate))>=stage2_gate,ecom_market_base*(1+ecom_growth_rate)^4*0.01*tx_take_rate*1000*3,0))*payment_proc_pct)-(capex_total+(33*30*12*(1+bhxh_rate)*(1+salary_escalation)^2*5)+(opex_marketing*(1+marketing_growth)^2*5)+(opex_cloud_base*5+(800/(1+EXP(-adoption_steepness*(2028-adoption_midpoint)))*(1-churn_rate))*vcr_per_enterprise*12*cloud_per_1M_vcr/1000000*5)+((opex_branding+opex_external+opex_legal+opex_security+opex_partner_mgmt)*5)+(capex_total*capex_maintenance_pct*4)))*(1-cit_rate))/(1+discount_rate)^2.5 | G24: =((((800/(1+EXP(-adoption_steepness*(2028-adoption_midpoint)))*(1-churn_rate))*(cert_fee_yr1*(1+cert_fee_escalation)^2.5+training_pct*training_fee+audit_fee)*5)+(IF((800/(1+EXP(-adoption_steepness*(2028-adoption_midpoint)))*(1-churn_rate))>=stage2_gate,ecom_market_base*(1+ecom_growth_rate)^4*0.015*tx_take_rate*1000*3,0))-((IF((800/(1+EXP(-adoption_steepness*(2028-adoption_midpoint)))*(1-churn_rate))>=stage2_gate,ecom_market_base*(1+ecom_growth_rate)^4*0.015*tx_take_rate*1000*3,0))*payment_proc_pct)-(capex_total+(33*30*12*(1+bhxh_rate)*(1+salary_escalation)^2*5)+(opex_marketing*(1+marketing_growth)^2*5)+(opex_cloud_base*5+(800/(1+EXP(-adoption_steepness*(2028-adoption_midpoint)))*(1-churn_rate))*vcr_per_enterprise*12*cloud_per_1M_vcr/1000000*5)+((opex_branding+opex_external+opex_legal+opex_security+opex_partner_mgmt)*5)+(capex_total*capex_maintenance_pct*4)))*(1-cit_rate))/(1+discount_rate)^2.5 | H24: =((((800/(1+EXP(-adoption_steepness*(2028-adoption_midpoint)))*(1-churn_rate))*(cert_fee_yr1*(1+cert_fee_escalation)^2.5+training_pct*training_fee+audit_fee)*5)+(IF((800/(1+EXP(-adoption_steepness*(2028-adoption_midpoint)))*(1-churn_rate))>=stage2_gate,ecom_market_base*(1+ecom_growth_rate)^4*0.02*tx_take_rate*1000*3,0))-((IF((800/(1+EXP(-adoption_steepness*(2028-adoption_midpoint)))*(1-churn_rate))>=stage2_gate,ecom_market_base*(1+ecom_growth_rate)^4*0.02*tx_take_rate*1000*3,0))*payment_proc_pct)-(capex_total+(33*30*12*(1+bhxh_rate)*(1+salary_escalation)^2*5)+(opex_marketing*(1+marketing_growth)^2*5)+(opex_cloud_base*5+(800/(1+EXP(-adoption_steepness*(2028-adoption_midpoint)))*(1-churn_rate))*vcr_per_enterprise*12*cloud_per_1M_vcr/1000000*5)+((opex_branding+opex_external+opex_legal+opex_security+opex_partner_mgmt)*5)+(capex_total*capex_maintenance_pct*4)))*(1-cit_rate))/(1+discount_rate)^2.5
A25: 1000 | B25: =((((1000/(1+EXP(-adoption_steepness*(2028-adoption_midpoint)))*(1-churn_rate))*(cert_fee_yr1*(1+cert_fee_escalation)^2.5+training_pct*training_fee+audit_fee)*5)+(IF((1000/(1+EXP(-adoption_steepness*(2028-adoption_midpoint)))*(1-churn_rate))>=stage2_gate,ecom_market_base*(1+ecom_growth_rate)^4*0.001*tx_take_rate*1000*3,0))-((IF((1000/(1+EXP(-adoption_steepness*(2028-adoption_midpoint)))*(1-churn_rate))>=stage2_gate,ecom_market_base*(1+ecom_growth_rate)^4*0.001*tx_take_rate*1000*3,0))*payment_proc_pct)-(capex_total+(33*30*12*(1+bhxh_rate)*(1+salary_escalation)^2*5)+(opex_marketing*(1+marketing_growth)^2*5)+(opex_cloud_base*5+(1000/(1+EXP(-adoption_steepness*(2028-adoption_midpoint)))*(1-churn_rate))*vcr_per_enterprise*12*cloud_per_1M_vcr/1000000*5)+((opex_branding+opex_external+opex_legal+opex_security+opex_partner_mgmt)*5)+(capex_total*capex_maintenance_pct*4)))*(1-cit_rate))/(1+discount_rate)^2.5 | C25: =((((1000/(1+EXP(-adoption_steepness*(2028-adoption_midpoint)))*(1-churn_rate))*(cert_fee_yr1*(1+cert_fee_escalation)^2.5+training_pct*training_fee+audit_fee)*5)+(IF((1000/(1+EXP(-adoption_steepness*(2028-adoption_midpoint)))*(1-churn_rate))>=stage2_gate,ecom_market_base*(1+ecom_growth_rate)^4*0.003*tx_take_rate*1000*3,0))-((IF((1000/(1+EXP(-adoption_steepness*(2028-adoption_midpoint)))*(1-churn_rate))>=stage2_gate,ecom_market_base*(1+ecom_growth_rate)^4*0.003*tx_take_rate*1000*3,0))*payment_proc_pct)-(capex_total+(33*30*12*(1+bhxh_rate)*(1+salary_escalation)^2*5)+(opex_marketing*(1+marketing_growth)^2*5)+(opex_cloud_base*5+(1000/(1+EXP(-adoption_steepness*(2028-adoption_midpoint)))*(1-churn_rate))*vcr_per_enterprise*12*cloud_per_1M_vcr/1000000*5)+((opex_branding+opex_external+opex_legal+opex_security+opex_partner_mgmt)*5)+(capex_total*capex_maintenance_pct*4)))*(1-cit_rate))/(1+discount_rate)^2.5 | D25: =((((1000/(1+EXP(-adoption_steepness*(2028-adoption_midpoint)))*(1-churn_rate))*(cert_fee_yr1*(1+cert_fee_escalation)^2.5+training_pct*training_fee+audit_fee)*5)+(IF((1000/(1+EXP(-adoption_steepness*(2028-adoption_midpoint)))*(1-churn_rate))>=stage2_gate,ecom_market_base*(1+ecom_growth_rate)^4*0.005*tx_take_rate*1000*3,0))-((IF((1000/(1+EXP(-adoption_steepness*(2028-adoption_midpoint)))*(1-churn_rate))>=stage2_gate,ecom_market_base*(1+ecom_growth_rate)^4*0.005*tx_take_rate*1000*3,0))*payment_proc_pct)-(capex_total+(33*30*12*(1+bhxh_rate)*(1+salary_escalation)^2*5)+(opex_marketing*(1+marketing_growth)^2*5)+(opex_cloud_base*5+(1000/(1+EXP(-adoption_steepness*(2028-adoption_midpoint)))*(1-churn_rate))*vcr_per_enterprise*12*cloud_per_1M_vcr/1000000*5)+((opex_branding+opex_external+opex_legal+opex_security+opex_partner_mgmt)*5)+(capex_total*capex_maintenance_pct*4)))*(1-cit_rate))/(1+discount_rate)^2.5 | E25: =((((1000/(1+EXP(-adoption_steepness*(2028-adoption_midpoint)))*(1-churn_rate))*(cert_fee_yr1*(1+cert_fee_escalation)^2.5+training_pct*training_fee+audit_fee)*5)+(IF((1000/(1+EXP(-adoption_steepness*(2028-adoption_midpoint)))*(1-churn_rate))>=stage2_gate,ecom_market_base*(1+ecom_growth_rate)^4*0.008*tx_take_rate*1000*3,0))-((IF((1000/(1+EXP(-adoption_steepness*(2028-adoption_midpoint)))*(1-churn_rate))>=stage2_gate,ecom_market_base*(1+ecom_growth_rate)^4*0.008*tx_take_rate*1000*3,0))*payment_proc_pct)-(capex_total+(33*30*12*(1+bhxh_rate)*(1+salary_escalation)^2*5)+(opex_marketing*(1+marketing_growth)^2*5)+(opex_cloud_base*5+(1000/(1+EXP(-adoption_steepness*(2028-adoption_midpoint)))*(1-churn_rate))*vcr_per_enterprise*12*cloud_per_1M_vcr/1000000*5)+((opex_branding+opex_external+opex_legal+opex_security+opex_partner_mgmt)*5)+(capex_total*capex_maintenance_pct*4)))*(1-cit_rate))/(1+discount_rate)^2.5 | F25: =((((1000/(1+EXP(-adoption_steepness*(2028-adoption_midpoint)))*(1-churn_rate))*(cert_fee_yr1*(1+cert_fee_escalation)^2.5+training_pct*training_fee+audit_fee)*5)+(IF((1000/(1+EXP(-adoption_steepness*(2028-adoption_midpoint)))*(1-churn_rate))>=stage2_gate,ecom_market_base*(1+ecom_growth_rate)^4*0.01*tx_take_rate*1000*3,0))-((IF((1000/(1+EXP(-adoption_steepness*(2028-adoption_midpoint)))*(1-churn_rate))>=stage2_gate,ecom_market_base*(1+ecom_growth_rate)^4*0.01*tx_take_rate*1000*3,0))*payment_proc_pct)-(capex_total+(33*30*12*(1+bhxh_rate)*(1+salary_escalation)^2*5)+(opex_marketing*(1+marketing_growth)^2*5)+(opex_cloud_base*5+(1000/(1+EXP(-adoption_steepness*(2028-adoption_midpoint)))*(1-churn_rate))*vcr_per_enterprise*12*cloud_per_1M_vcr/1000000*5)+((opex_branding+opex_external+opex_legal+opex_security+opex_partner_mgmt)*5)+(capex_total*capex_maintenance_pct*4)))*(1-cit_rate))/(1+discount_rate)^2.5 | G25: =((((1000/(1+EXP(-adoption_steepness*(2028-adoption_midpoint)))*(1-churn_rate))*(cert_fee_yr1*(1+cert_fee_escalation)^2.5+training_pct*training_fee+audit_fee)*5)+(IF((1000/(1+EXP(-adoption_steepness*(2028-adoption_midpoint)))*(1-churn_rate))>=stage2_gate,ecom_market_base*(1+ecom_growth_rate)^4*0.015*tx_take_rate*1000*3,0))-((IF((1000/(1+EXP(-adoption_steepness*(2028-adoption_midpoint)))*(1-churn_rate))>=stage2_gate,ecom_market_base*(1+ecom_growth_rate)^4*0.015*tx_take_rate*1000*3,0))*payment_proc_pct)-(capex_total+(33*30*12*(1+bhxh_rate)*(1+salary_escalation)^2*5)+(opex_marketing*(1+marketing_growth)^2*5)+(opex_cloud_base*5+(1000/(1+EXP(-adoption_steepness*(2028-adoption_midpoint)))*(1-churn_rate))*vcr_per_enterprise*12*cloud_per_1M_vcr/1000000*5)+((opex_branding+opex_external+opex_legal+opex_security+opex_partner_mgmt)*5)+(capex_total*capex_maintenance_pct*4)))*(1-cit_rate))/(1+discount_rate)^2.5 | H25: =((((1000/(1+EXP(-adoption_steepness*(2028-adoption_midpoint)))*(1-churn_rate))*(cert_fee_yr1*(1+cert_fee_escalation)^2.5+training_pct*training_fee+audit_fee)*5)+(IF((1000/(1+EXP(-adoption_steepness*(2028-adoption_midpoint)))*(1-churn_rate))>=stage2_gate,ecom_market_base*(1+ecom_growth_rate)^4*0.02*tx_take_rate*1000*3,0))-((IF((1000/(1+EXP(-adoption_steepness*(2028-adoption_midpoint)))*(1-churn_rate))>=stage2_gate,ecom_market_base*(1+ecom_growth_rate)^4*0.02*tx_take_rate*1000*3,0))*payment_proc_pct)-(capex_total+(33*30*12*(1+bhxh_rate)*(1+salary_escalation)^2*5)+(opex_marketing*(1+marketing_growth)^2*5)+(opex_cloud_base*5+(1000/(1+EXP(-adoption_steepness*(2028-adoption_midpoint)))*(1-churn_rate))*vcr_per_enterprise*12*cloud_per_1M_vcr/1000000*5)+((opex_branding+opex_external+opex_legal+opex_security+opex_partner_mgmt)*5)+(capex_total*capex_maintenance_pct*4)))*(1-cit_rate))/(1+discount_rate)^2.5
A26: 1200 | B26: =((((1200/(1+EXP(-adoption_steepness*(2028-adoption_midpoint)))*(1-churn_rate))*(cert_fee_yr1*(1+cert_fee_escalation)^2.5+training_pct*training_fee+audit_fee)*5)+(IF((1200/(1+EXP(-adoption_steepness*(2028-adoption_midpoint)))*(1-churn_rate))>=stage2_gate,ecom_market_base*(1+ecom_growth_rate)^4*0.001*tx_take_rate*1000*3,0))-((IF((1200/(1+EXP(-adoption_steepness*(2028-adoption_midpoint)))*(1-churn_rate))>=stage2_gate,ecom_market_base*(1+ecom_growth_rate)^4*0.001*tx_take_rate*1000*3,0))*payment_proc_pct)-(capex_total+(33*30*12*(1+bhxh_rate)*(1+salary_escalation)^2*5)+(opex_marketing*(1+marketing_growth)^2*5)+(opex_cloud_base*5+(1200/(1+EXP(-adoption_steepness*(2028-adoption_midpoint)))*(1-churn_rate))*vcr_per_enterprise*12*cloud_per_1M_vcr/1000000*5)+((opex_branding+opex_external+opex_legal+opex_security+opex_partner_mgmt)*5)+(capex_total*capex_maintenance_pct*4)))*(1-cit_rate))/(1+discount_rate)^2.5 | C26: =((((1200/(1+EXP(-adoption_steepness*(2028-adoption_midpoint)))*(1-churn_rate))*(cert_fee_yr1*(1+cert_fee_escalation)^2.5+training_pct*training_fee+audit_fee)*5)+(IF((1200/(1+EXP(-adoption_steepness*(2028-adoption_midpoint)))*(1-churn_rate))>=stage2_gate,ecom_market_base*(1+ecom_growth_rate)^4*0.003*tx_take_rate*1000*3,0))-((IF((1200/(1+EXP(-adoption_steepness*(2028-adoption_midpoint)))*(1-churn_rate))>=stage2_gate,ecom_market_base*(1+ecom_growth_rate)^4*0.003*tx_take_rate*1000*3,0))*payment_proc_pct)-(capex_total+(33*30*12*(1+bhxh_rate)*(1+salary_escalation)^2*5)+(opex_marketing*(1+marketing_growth)^2*5)+(opex_cloud_base*5+(1200/(1+EXP(-adoption_steepness*(2028-adoption_midpoint)))*(1-churn_rate))*vcr_per_enterprise*12*cloud_per_1M_vcr/1000000*5)+((opex_branding+opex_external+opex_legal+opex_security+opex_partner_mgmt)*5)+(capex_total*capex_maintenance_pct*4)))*(1-cit_rate))/(1+discount_rate)^2.5 | D26: =((((1200/(1+EXP(-adoption_steepness*(2028-adoption_midpoint)))*(1-churn_rate))*(cert_fee_yr1*(1+cert_fee_escalation)^2.5+training_pct*training_fee+audit_fee)*5)+(IF((1200/(1+EXP(-adoption_steepness*(2028-adoption_midpoint)))*(1-churn_rate))>=stage2_gate,ecom_market_base*(1+ecom_growth_rate)^4*0.005*tx_take_rate*1000*3,0))-((IF((1200/(1+EXP(-adoption_steepness*(2028-adoption_midpoint)))*(1-churn_rate))>=stage2_gate,ecom_market_base*(1+ecom_growth_rate)^4*0.005*tx_take_rate*1000*3,0))*payment_proc_pct)-(capex_total+(33*30*12*(1+bhxh_rate)*(1+salary_escalation)^2*5)+(opex_marketing*(1+marketing_growth)^2*5)+(opex_cloud_base*5+(1200/(1+EXP(-adoption_steepness*(2028-adoption_midpoint)))*(1-churn_rate))*vcr_per_enterprise*12*cloud_per_1M_vcr/1000000*5)+((opex_branding+opex_external+opex_legal+opex_security+opex_partner_mgmt)*5)+(capex_total*capex_maintenance_pct*4)))*(1-cit_rate))/(1+discount_rate)^2.5 | E26: =((((1200/(1+EXP(-adoption_steepness*(2028-adoption_midpoint)))*(1-churn_rate))*(cert_fee_yr1*(1+cert_fee_escalation)^2.5+training_pct*training_fee+audit_fee)*5)+(IF((1200/(1+EXP(-adoption_steepness*(2028-adoption_midpoint)))*(1-churn_rate))>=stage2_gate,ecom_market_base*(1+ecom_growth_rate)^4*0.008*tx_take_rate*1000*3,0))-((IF((1200/(1+EXP(-adoption_steepness*(2028-adoption_midpoint)))*(1-churn_rate))>=stage2_gate,ecom_market_base*(1+ecom_growth_rate)^4*0.008*tx_take_rate*1000*3,0))*payment_proc_pct)-(capex_total+(33*30*12*(1+bhxh_rate)*(1+salary_escalation)^2*5)+(opex_marketing*(1+marketing_growth)^2*5)+(opex_cloud_base*5+(1200/(1+EXP(-adoption_steepness*(2028-adoption_midpoint)))*(1-churn_rate))*vcr_per_enterprise*12*cloud_per_1M_vcr/1000000*5)+((opex_branding+opex_external+opex_legal+opex_security+opex_partner_mgmt)*5)+(capex_total*capex_maintenance_pct*4)))*(1-cit_rate))/(1+discount_rate)^2.5 | F26: =((((1200/(1+EXP(-adoption_steepness*(2028-adoption_midpoint)))*(1-churn_rate))*(cert_fee_yr1*(1+cert_fee_escalation)^2.5+training_pct*training_fee+audit_fee)*5)+(IF((1200/(1+EXP(-adoption_steepness*(2028-adoption_midpoint)))*(1-churn_rate))>=stage2_gate,ecom_market_base*(1+ecom_growth_rate)^4*0.01*tx_take_rate*1000*3,0))-((IF((1200/(1+EXP(-adoption_steepness*(2028-adoption_midpoint)))*(1-churn_rate))>=stage2_gate,ecom_market_base*(1+ecom_growth_rate)^4*0.01*tx_take_rate*1000*3,0))*payment_proc_pct)-(capex_total+(33*30*12*(1+bhxh_rate)*(1+salary_escalation)^2*5)+(opex_marketing*(1+marketing_growth)^2*5)+(opex_cloud_base*5+(1200/(1+EXP(-adoption_steepness*(2028-adoption_midpoint)))*(1-churn_rate))*vcr_per_enterprise*12*cloud_per_1M_vcr/1000000*5)+((opex_branding+opex_external+opex_legal+opex_security+opex_partner_mgmt)*5)+(capex_total*capex_maintenance_pct*4)))*(1-cit_rate))/(1+discount_rate)^2.5 | G26: =((((1200/(1+EXP(-adoption_steepness*(2028-adoption_midpoint)))*(1-churn_rate))*(cert_fee_yr1*(1+cert_fee_escalation)^2.5+training_pct*training_fee+audit_fee)*5)+(IF((1200/(1+EXP(-adoption_steepness*(2028-adoption_midpoint)))*(1-churn_rate))>=stage2_gate,ecom_market_base*(1+ecom_growth_rate)^4*0.015*tx_take_rate*1000*3,0))-((IF((1200/(1+EXP(-adoption_steepness*(2028-adoption_midpoint)))*(1-churn_rate))>=stage2_gate,ecom_market_base*(1+ecom_growth_rate)^4*0.015*tx_take_rate*1000*3,0))*payment_proc_pct)-(capex_total+(33*30*12*(1+bhxh_rate)*(1+salary_escalation)^2*5)+(opex_marketing*(1+marketing_growth)^2*5)+(opex_cloud_base*5+(1200/(1+EXP(-adoption_steepness*(2028-adoption_midpoint)))*(1-churn_rate))*vcr_per_enterprise*12*cloud_per_1M_vcr/1000000*5)+((opex_branding+opex_external+opex_legal+opex_security+opex_partner_mgmt)*5)+(capex_total*capex_maintenance_pct*4)))*(1-cit_rate))/(1+discount_rate)^2.5 | H26: =((((1200/(1+EXP(-adoption_steepness*(2028-adoption_midpoint)))*(1-churn_rate))*(cert_fee_yr1*(1+cert_fee_escalation)^2.5+training_pct*training_fee+audit_fee)*5)+(IF((1200/(1+EXP(-adoption_steepness*(2028-adoption_midpoint)))*(1-churn_rate))>=stage2_gate,ecom_market_base*(1+ecom_growth_rate)^4*0.02*tx_take_rate*1000*3,0))-((IF((1200/(1+EXP(-adoption_steepness*(2028-adoption_midpoint)))*(1-churn_rate))>=stage2_gate,ecom_market_base*(1+ecom_growth_rate)^4*0.02*tx_take_rate*1000*3,0))*payment_proc_pct)-(capex_total+(33*30*12*(1+bhxh_rate)*(1+salary_escalation)^2*5)+(opex_marketing*(1+marketing_growth)^2*5)+(opex_cloud_base*5+(1200/(1+EXP(-adoption_steepness*(2028-adoption_midpoint)))*(1-churn_rate))*vcr_per_enterprise*12*cloud_per_1M_vcr/1000000*5)+((opex_branding+opex_external+opex_legal+opex_security+opex_partner_mgmt)*5)+(capex_total*capex_maintenance_pct*4)))*(1-cit_rate))/(1+discount_rate)^2.5
A27: 1500 | B27: =((((1500/(1+EXP(-adoption_steepness*(2028-adoption_midpoint)))*(1-churn_rate))*(cert_fee_yr1*(1+cert_fee_escalation)^2.5+training_pct*training_fee+audit_fee)*5)+(IF((1500/(1+EXP(-adoption_steepness*(2028-adoption_midpoint)))*(1-churn_rate))>=stage2_gate,ecom_market_base*(1+ecom_growth_rate)^4*0.001*tx_take_rate*1000*3,0))-((IF((1500/(1+EXP(-adoption_steepness*(2028-adoption_midpoint)))*(1-churn_rate))>=stage2_gate,ecom_market_base*(1+ecom_growth_rate)^4*0.001*tx_take_rate*1000*3,0))*payment_proc_pct)-(capex_total+(33*30*12*(1+bhxh_rate)*(1+salary_escalation)^2*5)+(opex_marketing*(1+marketing_growth)^2*5)+(opex_cloud_base*5+(1500/(1+EXP(-adoption_steepness*(2028-adoption_midpoint)))*(1-churn_rate))*vcr_per_enterprise*12*cloud_per_1M_vcr/1000000*5)+((opex_branding+opex_external+opex_legal+opex_security+opex_partner_mgmt)*5)+(capex_total*capex_maintenance_pct*4)))*(1-cit_rate))/(1+discount_rate)^2.5 | C27: =((((1500/(1+EXP(-adoption_steepness*(2028-adoption_midpoint)))*(1-churn_rate))*(cert_fee_yr1*(1+cert_fee_escalation)^2.5+training_pct*training_fee+audit_fee)*5)+(IF((1500/(1+EXP(-adoption_steepness*(2028-adoption_midpoint)))*(1-churn_rate))>=stage2_gate,ecom_market_base*(1+ecom_growth_rate)^4*0.003*tx_take_rate*1000*3,0))-((IF((1500/(1+EXP(-adoption_steepness*(2028-adoption_midpoint)))*(1-churn_rate))>=stage2_gate,ecom_market_base*(1+ecom_growth_rate)^4*0.003*tx_take_rate*1000*3,0))*payment_proc_pct)-(capex_total+(33*30*12*(1+bhxh_rate)*(1+salary_escalation)^2*5)+(opex_marketing*(1+marketing_growth)^2*5)+(opex_cloud_base*5+(1500/(1+EXP(-adoption_steepness*(2028-adoption_midpoint)))*(1-churn_rate))*vcr_per_enterprise*12*cloud_per_1M_vcr/1000000*5)+((opex_branding+opex_external+opex_legal+opex_security+opex_partner_mgmt)*5)+(capex_total*capex_maintenance_pct*4)))*(1-cit_rate))/(1+discount_rate)^2.5 | D27: =((((1500/(1+EXP(-adoption_steepness*(2028-adoption_midpoint)))*(1-churn_rate))*(cert_fee_yr1*(1+cert_fee_escalation)^2.5+training_pct*training_fee+audit_fee)*5)+(IF((1500/(1+EXP(-adoption_steepness*(2028-adoption_midpoint)))*(1-churn_rate))>=stage2_gate,ecom_market_base*(1+ecom_growth_rate)^4*0.005*tx_take_rate*1000*3,0))-((IF((1500/(1+EXP(-adoption_steepness*(2028-adoption_midpoint)))*(1-churn_rate))>=stage2_gate,ecom_market_base*(1+ecom_growth_rate)^4*0.005*tx_take_rate*1000*3,0))*payment_proc_pct)-(capex_total+(33*30*12*(1+bhxh_rate)*(1+salary_escalation)^2*5)+(opex_marketing*(1+marketing_growth)^2*5)+(opex_cloud_base*5+(1500/(1+EXP(-adoption_steepness*(2028-adoption_midpoint)))*(1-churn_rate))*vcr_per_enterprise*12*cloud_per_1M_vcr/1000000*5)+((opex_branding+opex_external+opex_legal+opex_security+opex_partner_mgmt)*5)+(capex_total*capex_maintenance_pct*4)))*(1-cit_rate))/(1+discount_rate)^2.5 | E27: =((((1500/(1+EXP(-adoption_steepness*(2028-adoption_midpoint)))*(1-churn_rate))*(cert_fee_yr1*(1+cert_fee_escalation)^2.5+training_pct*training_fee+audit_fee)*5)+(IF((1500/(1+EXP(-adoption_steepness*(2028-adoption_midpoint)))*(1-churn_rate))>=stage2_gate,ecom_market_base*(1+ecom_growth_rate)^4*0.008*tx_take_rate*1000*3,0))-((IF((1500/(1+EXP(-adoption_steepness*(2028-adoption_midpoint)))*(1-churn_rate))>=stage2_gate,ecom_market_base*(1+ecom_growth_rate)^4*0.008*tx_take_rate*1000*3,0))*payment_proc_pct)-(capex_total+(33*30*12*(1+bhxh_rate)*(1+salary_escalation)^2*5)+(opex_marketing*(1+marketing_growth)^2*5)+(opex_cloud_base*5+(1500/(1+EXP(-adoption_steepness*(2028-adoption_midpoint)))*(1-churn_rate))*vcr_per_enterprise*12*cloud_per_1M_vcr/1000000*5)+((opex_branding+opex_external+opex_legal+opex_security+opex_partner_mgmt)*5)+(capex_total*capex_maintenance_pct*4)))*(1-cit_rate))/(1+discount_rate)^2.5 | F27: =((((1500/(1+EXP(-adoption_steepness*(2028-adoption_midpoint)))*(1-churn_rate))*(cert_fee_yr1*(1+cert_fee_escalation)^2.5+training_pct*training_fee+audit_fee)*5)+(IF((1500/(1+EXP(-adoption_steepness*(2028-adoption_midpoint)))*(1-churn_rate))>=stage2_gate,ecom_market_base*(1+ecom_growth_rate)^4*0.01*tx_take_rate*1000*3,0))-((IF((1500/(1+EXP(-adoption_steepness*(2028-adoption_midpoint)))*(1-churn_rate))>=stage2_gate,ecom_market_base*(1+ecom_growth_rate)^4*0.01*tx_take_rate*1000*3,0))*payment_proc_pct)-(capex_total+(33*30*12*(1+bhxh_rate)*(1+salary_escalation)^2*5)+(opex_marketing*(1+marketing_growth)^2*5)+(opex_cloud_base*5+(1500/(1+EXP(-adoption_steepness*(2028-adoption_midpoint)))*(1-churn_rate))*vcr_per_enterprise*12*cloud_per_1M_vcr/1000000*5)+((opex_branding+opex_external+opex_legal+opex_security+opex_partner_mgmt)*5)+(capex_total*capex_maintenance_pct*4)))*(1-cit_rate))/(1+discount_rate)^2.5 | G27: =((((1500/(1+EXP(-adoption_steepness*(2028-adoption_midpoint)))*(1-churn_rate))*(cert_fee_yr1*(1+cert_fee_escalation)^2.5+training_pct*training_fee+audit_fee)*5)+(IF((1500/(1+EXP(-adoption_steepness*(2028-adoption_midpoint)))*(1-churn_rate))>=stage2_gate,ecom_market_base*(1+ecom_growth_rate)^4*0.015*tx_take_rate*1000*3,0))-((IF((1500/(1+EXP(-adoption_steepness*(2028-adoption_midpoint)))*(1-churn_rate))>=stage2_gate,ecom_market_base*(1+ecom_growth_rate)^4*0.015*tx_take_rate*1000*3,0))*payment_proc_pct)-(capex_total+(33*30*12*(1+bhxh_rate)*(1+salary_escalation)^2*5)+(opex_marketing*(1+marketing_growth)^2*5)+(opex_cloud_base*5+(1500/(1+EXP(-adoption_steepness*(2028-adoption_midpoint)))*(1-churn_rate))*vcr_per_enterprise*12*cloud_per_1M_vcr/1000000*5)+((opex_branding+opex_external+opex_legal+opex_security+opex_partner_mgmt)*5)+(capex_total*capex_maintenance_pct*4)))*(1-cit_rate))/(1+discount_rate)^2.5 | H27: =((((1500/(1+EXP(-adoption_steepness*(2028-adoption_midpoint)))*(1-churn_rate))*(cert_fee_yr1*(1+cert_fee_escalation)^2.5+training_pct*training_fee+audit_fee)*5)+(IF((1500/(1+EXP(-adoption_steepness*(2028-adoption_midpoint)))*(1-churn_rate))>=stage2_gate,ecom_market_base*(1+ecom_growth_rate)^4*0.02*tx_take_rate*1000*3,0))-((IF((1500/(1+EXP(-adoption_steepness*(2028-adoption_midpoint)))*(1-churn_rate))>=stage2_gate,ecom_market_base*(1+ecom_growth_rate)^4*0.02*tx_take_rate*1000*3,0))*payment_proc_pct)-(capex_total+(33*30*12*(1+bhxh_rate)*(1+salary_escalation)^2*5)+(opex_marketing*(1+marketing_growth)^2*5)+(opex_cloud_base*5+(1500/(1+EXP(-adoption_steepness*(2028-adoption_midpoint)))*(1-churn_rate))*vcr_per_enterprise*12*cloud_per_1M_vcr/1000000*5)+((opex_branding+opex_external+opex_legal+opex_security+opex_partner_mgmt)*5)+(capex_total*capex_maintenance_pct*4)))*(1-cit_rate))/(1+discount_rate)^2.5
A28: 2000 | B28: =((((2000/(1+EXP(-adoption_steepness*(2028-adoption_midpoint)))*(1-churn_rate))*(cert_fee_yr1*(1+cert_fee_escalation)^2.5+training_pct*training_fee+audit_fee)*5)+(IF((2000/(1+EXP(-adoption_steepness*(2028-adoption_midpoint)))*(1-churn_rate))>=stage2_gate,ecom_market_base*(1+ecom_growth_rate)^4*0.001*tx_take_rate*1000*3,0))-((IF((2000/(1+EXP(-adoption_steepness*(2028-adoption_midpoint)))*(1-churn_rate))>=stage2_gate,ecom_market_base*(1+ecom_growth_rate)^4*0.001*tx_take_rate*1000*3,0))*payment_proc_pct)-(capex_total+(33*30*12*(1+bhxh_rate)*(1+salary_escalation)^2*5)+(opex_marketing*(1+marketing_growth)^2*5)+(opex_cloud_base*5+(2000/(1+EXP(-adoption_steepness*(2028-adoption_midpoint)))*(1-churn_rate))*vcr_per_enterprise*12*cloud_per_1M_vcr/1000000*5)+((opex_branding+opex_external+opex_legal+opex_security+opex_partner_mgmt)*5)+(capex_total*capex_maintenance_pct*4)))*(1-cit_rate))/(1+discount_rate)^2.5 | C28: =((((2000/(1+EXP(-adoption_steepness*(2028-adoption_midpoint)))*(1-churn_rate))*(cert_fee_yr1*(1+cert_fee_escalation)^2.5+training_pct*training_fee+audit_fee)*5)+(IF((2000/(1+EXP(-adoption_steepness*(2028-adoption_midpoint)))*(1-churn_rate))>=stage2_gate,ecom_market_base*(1+ecom_growth_rate)^4*0.003*tx_take_rate*1000*3,0))-((IF((2000/(1+EXP(-adoption_steepness*(2028-adoption_midpoint)))*(1-churn_rate))>=stage2_gate,ecom_market_base*(1+ecom_growth_rate)^4*0.003*tx_take_rate*1000*3,0))*payment_proc_pct)-(capex_total+(33*30*12*(1+bhxh_rate)*(1+salary_escalation)^2*5)+(opex_marketing*(1+marketing_growth)^2*5)+(opex_cloud_base*5+(2000/(1+EXP(-adoption_steepness*(2028-adoption_midpoint)))*(1-churn_rate))*vcr_per_enterprise*12*cloud_per_1M_vcr/1000000*5)+((opex_branding+opex_external+opex_legal+opex_security+opex_partner_mgmt)*5)+(capex_total*capex_maintenance_pct*4)))*(1-cit_rate))/(1+discount_rate)^2.5 | D28: =((((2000/(1+EXP(-adoption_steepness*(2028-adoption_midpoint)))*(1-churn_rate))*(cert_fee_yr1*(1+cert_fee_escalation)^2.5+training_pct*training_fee+audit_fee)*5)+(IF((2000/(1+EXP(-adoption_steepness*(2028-adoption_midpoint)))*(1-churn_rate))>=stage2_gate,ecom_market_base*(1+ecom_growth_rate)^4*0.005*tx_take_rate*1000*3,0))-((IF((2000/(1+EXP(-adoption_steepness*(2028-adoption_midpoint)))*(1-churn_rate))>=stage2_gate,ecom_market_base*(1+ecom_growth_rate)^4*0.005*tx_take_rate*1000*3,0))*payment_proc_pct)-(capex_total+(33*30*12*(1+bhxh_rate)*(1+salary_escalation)^2*5)+(opex_marketing*(1+marketing_growth)^2*5)+(opex_cloud_base*5+(2000/(1+EXP(-adoption_steepness*(2028-adoption_midpoint)))*(1-churn_rate))*vcr_per_enterprise*12*cloud_per_1M_vcr/1000000*5)+((opex_branding+opex_external+opex_legal+opex_security+opex_partner_mgmt)*5)+(capex_total*capex_maintenance_pct*4)))*(1-cit_rate))/(1+discount_rate)^2.5 | E28: =((((2000/(1+EXP(-adoption_steepness*(2028-adoption_midpoint)))*(1-churn_rate))*(cert_fee_yr1*(1+cert_fee_escalation)^2.5+training_pct*training_fee+audit_fee)*5)+(IF((2000/(1+EXP(-adoption_steepness*(2028-adoption_midpoint)))*(1-churn_rate))>=stage2_gate,ecom_market_base*(1+ecom_growth_rate)^4*0.008*tx_take_rate*1000*3,0))-((IF((2000/(1+EXP(-adoption_steepness*(2028-adoption_midpoint)))*(1-churn_rate))>=stage2_gate,ecom_market_base*(1+ecom_growth_rate)^4*0.008*tx_take_rate*1000*3,0))*payment_proc_pct)-(capex_total+(33*30*12*(1+bhxh_rate)*(1+salary_escalation)^2*5)+(opex_marketing*(1+marketing_growth)^2*5)+(opex_cloud_base*5+(2000/(1+EXP(-adoption_steepness*(2028-adoption_midpoint)))*(1-churn_rate))*vcr_per_enterprise*12*cloud_per_1M_vcr/1000000*5)+((opex_branding+opex_external+opex_legal+opex_security+opex_partner_mgmt)*5)+(capex_total*capex_maintenance_pct*4)))*(1-cit_rate))/(1+discount_rate)^2.5 | F28: =((((2000/(1+EXP(-adoption_steepness*(2028-adoption_midpoint)))*(1-churn_rate))*(cert_fee_yr1*(1+cert_fee_escalation)^2.5+training_pct*training_fee+audit_fee)*5)+(IF((2000/(1+EXP(-adoption_steepness*(2028-adoption_midpoint)))*(1-churn_rate))>=stage2_gate,ecom_market_base*(1+ecom_growth_rate)^4*0.01*tx_take_rate*1000*3,0))-((IF((2000/(1+EXP(-adoption_steepness*(2028-adoption_midpoint)))*(1-churn_rate))>=stage2_gate,ecom_market_base*(1+ecom_growth_rate)^4*0.01*tx_take_rate*1000*3,0))*payment_proc_pct)-(capex_total+(33*30*12*(1+bhxh_rate)*(1+salary_escalation)^2*5)+(opex_marketing*(1+marketing_growth)^2*5)+(opex_cloud_base*5+(2000/(1+EXP(-adoption_steepness*(2028-adoption_midpoint)))*(1-churn_rate))*vcr_per_enterprise*12*cloud_per_1M_vcr/1000000*5)+((opex_branding+opex_external+opex_legal+opex_security+opex_partner_mgmt)*5)+(capex_total*capex_maintenance_pct*4)))*(1-cit_rate))/(1+discount_rate)^2.5 | G28: =((((2000/(1+EXP(-adoption_steepness*(2028-adoption_midpoint)))*(1-churn_rate))*(cert_fee_yr1*(1+cert_fee_escalation)^2.5+training_pct*training_fee+audit_fee)*5)+(IF((2000/(1+EXP(-adoption_steepness*(2028-adoption_midpoint)))*(1-churn_rate))>=stage2_gate,ecom_market_base*(1+ecom_growth_rate)^4*0.015*tx_take_rate*1000*3,0))-((IF((2000/(1+EXP(-adoption_steepness*(2028-adoption_midpoint)))*(1-churn_rate))>=stage2_gate,ecom_market_base*(1+ecom_growth_rate)^4*0.015*tx_take_rate*1000*3,0))*payment_proc_pct)-(capex_total+(33*30*12*(1+bhxh_rate)*(1+salary_escalation)^2*5)+(opex_marketing*(1+marketing_growth)^2*5)+(opex_cloud_base*5+(2000/(1+EXP(-adoption_steepness*(2028-adoption_midpoint)))*(1-churn_rate))*vcr_per_enterprise*12*cloud_per_1M_vcr/1000000*5)+((opex_branding+opex_external+opex_legal+opex_security+opex_partner_mgmt)*5)+(capex_total*capex_maintenance_pct*4)))*(1-cit_rate))/(1+discount_rate)^2.5 | H28: =((((2000/(1+EXP(-adoption_steepness*(2028-adoption_midpoint)))*(1-churn_rate))*(cert_fee_yr1*(1+cert_fee_escalation)^2.5+training_pct*training_fee+audit_fee)*5)+(IF((2000/(1+EXP(-adoption_steepness*(2028-adoption_midpoint)))*(1-churn_rate))>=stage2_gate,ecom_market_base*(1+ecom_growth_rate)^4*0.02*tx_take_rate*1000*3,0))-((IF((2000/(1+EXP(-adoption_steepness*(2028-adoption_midpoint)))*(1-churn_rate))>=stage2_gate,ecom_market_base*(1+ecom_growth_rate)^4*0.02*tx_take_rate*1000*3,0))*payment_proc_pct)-(capex_total+(33*30*12*(1+bhxh_rate)*(1+salary_escalation)^2*5)+(opex_marketing*(1+marketing_growth)^2*5)+(opex_cloud_base*5+(2000/(1+EXP(-adoption_steepness*(2028-adoption_midpoint)))*(1-churn_rate))*vcr_per_enterprise*12*cloud_per_1M_vcr/1000000*5)+((opex_branding+opex_external+opex_legal+opex_security+opex_partner_mgmt)*5)+(capex_total*capex_maintenance_pct*4)))*(1-cit_rate))/(1+discount_rate)^2.5
A29: 3000 | B29: =((((3000/(1+EXP(-adoption_steepness*(2028-adoption_midpoint)))*(1-churn_rate))*(cert_fee_yr1*(1+cert_fee_escalation)^2.5+training_pct*training_fee+audit_fee)*5)+(IF((3000/(1+EXP(-adoption_steepness*(2028-adoption_midpoint)))*(1-churn_rate))>=stage2_gate,ecom_market_base*(1+ecom_growth_rate)^4*0.001*tx_take_rate*1000*3,0))-((IF((3000/(1+EXP(-adoption_steepness*(2028-adoption_midpoint)))*(1-churn_rate))>=stage2_gate,ecom_market_base*(1+ecom_growth_rate)^4*0.001*tx_take_rate*1000*3,0))*payment_proc_pct)-(capex_total+(33*30*12*(1+bhxh_rate)*(1+salary_escalation)^2*5)+(opex_marketing*(1+marketing_growth)^2*5)+(opex_cloud_base*5+(3000/(1+EXP(-adoption_steepness*(2028-adoption_midpoint)))*(1-churn_rate))*vcr_per_enterprise*12*cloud_per_1M_vcr/1000000*5)+((opex_branding+opex_external+opex_legal+opex_security+opex_partner_mgmt)*5)+(capex_total*capex_maintenance_pct*4)))*(1-cit_rate))/(1+discount_rate)^2.5 | C29: =((((3000/(1+EXP(-adoption_steepness*(2028-adoption_midpoint)))*(1-churn_rate))*(cert_fee_yr1*(1+cert_fee_escalation)^2.5+training_pct*training_fee+audit_fee)*5)+(IF((3000/(1+EXP(-adoption_steepness*(2028-adoption_midpoint)))*(1-churn_rate))>=stage2_gate,ecom_market_base*(1+ecom_growth_rate)^4*0.003*tx_take_rate*1000*3,0))-((IF((3000/(1+EXP(-adoption_steepness*(2028-adoption_midpoint)))*(1-churn_rate))>=stage2_gate,ecom_market_base*(1+ecom_growth_rate)^4*0.003*tx_take_rate*1000*3,0))*payment_proc_pct)-(capex_total+(33*30*12*(1+bhxh_rate)*(1+salary_escalation)^2*5)+(opex_marketing*(1+marketing_growth)^2*5)+(opex_cloud_base*5+(3000/(1+EXP(-adoption_steepness*(2028-adoption_midpoint)))*(1-churn_rate))*vcr_per_enterprise*12*cloud_per_1M_vcr/1000000*5)+((opex_branding+opex_external+opex_legal+opex_security+opex_partner_mgmt)*5)+(capex_total*capex_maintenance_pct*4)))*(1-cit_rate))/(1+discount_rate)^2.5 | D29: =((((3000/(1+EXP(-adoption_steepness*(2028-adoption_midpoint)))*(1-churn_rate))*(cert_fee_yr1*(1+cert_fee_escalation)^2.5+training_pct*training_fee+audit_fee)*5)+(IF((3000/(1+EXP(-adoption_steepness*(2028-adoption_midpoint)))*(1-churn_rate))>=stage2_gate,ecom_market_base*(1+ecom_growth_rate)^4*0.005*tx_take_rate*1000*3,0))-((IF((3000/(1+EXP(-adoption_steepness*(2028-adoption_midpoint)))*(1-churn_rate))>=stage2_gate,ecom_market_base*(1+ecom_growth_rate)^4*0.005*tx_take_rate*1000*3,0))*payment_proc_pct)-(capex_total+(33*30*12*(1+bhxh_rate)*(1+salary_escalation)^2*5)+(opex_marketing*(1+marketing_growth)^2*5)+(opex_cloud_base*5+(3000/(1+EXP(-adoption_steepness*(2028-adoption_midpoint)))*(1-churn_rate))*vcr_per_enterprise*12*cloud_per_1M_vcr/1000000*5)+((opex_branding+opex_external+opex_legal+opex_security+opex_partner_mgmt)*5)+(capex_total*capex_maintenance_pct*4)))*(1-cit_rate))/(1+discount_rate)^2.5 | E29: =((((3000/(1+EXP(-adoption_steepness*(2028-adoption_midpoint)))*(1-churn_rate))*(cert_fee_yr1*(1+cert_fee_escalation)^2.5+training_pct*training_fee+audit_fee)*5)+(IF((3000/(1+EXP(-adoption_steepness*(2028-adoption_midpoint)))*(1-churn_rate))>=stage2_gate,ecom_market_base*(1+ecom_growth_rate)^4*0.008*tx_take_rate*1000*3,0))-((IF((3000/(1+EXP(-adoption_steepness*(2028-adoption_midpoint)))*(1-churn_rate))>=stage2_gate,ecom_market_base*(1+ecom_growth_rate)^4*0.008*tx_take_rate*1000*3,0))*payment_proc_pct)-(capex_total+(33*30*12*(1+bhxh_rate)*(1+salary_escalation)^2*5)+(opex_marketing*(1+marketing_growth)^2*5)+(opex_cloud_base*5+(3000/(1+EXP(-adoption_steepness*(2028-adoption_midpoint)))*(1-churn_rate))*vcr_per_enterprise*12*cloud_per_1M_vcr/1000000*5)+((opex_branding+opex_external+opex_legal+opex_security+opex_partner_mgmt)*5)+(capex_total*capex_maintenance_pct*4)))*(1-cit_rate))/(1+discount_rate)^2.5 | F29: =((((3000/(1+EXP(-adoption_steepness*(2028-adoption_midpoint)))*(1-churn_rate))*(cert_fee_yr1*(1+cert_fee_escalation)^2.5+training_pct*training_fee+audit_fee)*5)+(IF((3000/(1+EXP(-adoption_steepness*(2028-adoption_midpoint)))*(1-churn_rate))>=stage2_gate,ecom_market_base*(1+ecom_growth_rate)^4*0.01*tx_take_rate*1000*3,0))-((IF((3000/(1+EXP(-adoption_steepness*(2028-adoption_midpoint)))*(1-churn_rate))>=stage2_gate,ecom_market_base*(1+ecom_growth_rate)^4*0.01*tx_take_rate*1000*3,0))*payment_proc_pct)-(capex_total+(33*30*12*(1+bhxh_rate)*(1+salary_escalation)^2*5)+(opex_marketing*(1+marketing_growth)^2*5)+(opex_cloud_base*5+(3000/(1+EXP(-adoption_steepness*(2028-adoption_midpoint)))*(1-churn_rate))*vcr_per_enterprise*12*cloud_per_1M_vcr/1000000*5)+((opex_branding+opex_external+opex_legal+opex_security+opex_partner_mgmt)*5)+(capex_total*capex_maintenance_pct*4)))*(1-cit_rate))/(1+discount_rate)^2.5 | G29: =((((3000/(1+EXP(-adoption_steepness*(2028-adoption_midpoint)))*(1-churn_rate))*(cert_fee_yr1*(1+cert_fee_escalation)^2.5+training_pct*training_fee+audit_fee)*5)+(IF((3000/(1+EXP(-adoption_steepness*(2028-adoption_midpoint)))*(1-churn_rate))>=stage2_gate,ecom_market_base*(1+ecom_growth_rate)^4*0.015*tx_take_rate*1000*3,0))-((IF((3000/(1+EXP(-adoption_steepness*(2028-adoption_midpoint)))*(1-churn_rate))>=stage2_gate,ecom_market_base*(1+ecom_growth_rate)^4*0.015*tx_take_rate*1000*3,0))*payment_proc_pct)-(capex_total+(33*30*12*(1+bhxh_rate)*(1+salary_escalation)^2*5)+(opex_marketing*(1+marketing_growth)^2*5)+(opex_cloud_base*5+(3000/(1+EXP(-adoption_steepness*(2028-adoption_midpoint)))*(1-churn_rate))*vcr_per_enterprise*12*cloud_per_1M_vcr/1000000*5)+((opex_branding+opex_external+opex_legal+opex_security+opex_partner_mgmt)*5)+(capex_total*capex_maintenance_pct*4)))*(1-cit_rate))/(1+discount_rate)^2.5 | H29: =((((3000/(1+EXP(-adoption_steepness*(2028-adoption_midpoint)))*(1-churn_rate))*(cert_fee_yr1*(1+cert_fee_escalation)^2.5+training_pct*training_fee+audit_fee)*5)+(IF((3000/(1+EXP(-adoption_steepness*(2028-adoption_midpoint)))*(1-churn_rate))>=stage2_gate,ecom_market_base*(1+ecom_growth_rate)^4*0.02*tx_take_rate*1000*3,0))-((IF((3000/(1+EXP(-adoption_steepness*(2028-adoption_midpoint)))*(1-churn_rate))>=stage2_gate,ecom_market_base*(1+ecom_growth_rate)^4*0.02*tx_take_rate*1000*3,0))*payment_proc_pct)-(capex_total+(33*30*12*(1+bhxh_rate)*(1+salary_escalation)^2*5)+(opex_marketing*(1+marketing_growth)^2*5)+(opex_cloud_base*5+(3000/(1+EXP(-adoption_steepness*(2028-adoption_midpoint)))*(1-churn_rate))*vcr_per_enterprise*12*cloud_per_1M_vcr/1000000*5)+((opex_branding+opex_external+opex_legal+opex_security+opex_partner_mgmt)*5)+(capex_total*capex_maintenance_pct*4)))*(1-cit_rate))/(1+discount_rate)^2.5
A32: TWO-WAY NPV: adoption_max × churn_rate (Tr VND)
A33: adoption ↓ \ churn → | B33: 0.05 | C33: 0.1 | D33: 0.15 | E33: 0.2 | F33: 0.25 | G33: 0.3 | H33: 0.35
A34: 200 | B34: =((((200/(1+EXP(-adoption_steepness*(2028-adoption_midpoint)))*(1-0.05))*(cert_fee_yr1*(1+cert_fee_escalation)^2.5+training_pct*training_fee+audit_fee)*5)+(IF((200/(1+EXP(-adoption_steepness*(2028-adoption_midpoint)))*(1-0.05))>=stage2_gate,ecom_market_base*(1+ecom_growth_rate)^4*platform_market_share*tx_take_rate*1000*3,0))-((IF((200/(1+EXP(-adoption_steepness*(2028-adoption_midpoint)))*(1-0.05))>=stage2_gate,ecom_market_base*(1+ecom_growth_rate)^4*platform_market_share*tx_take_rate*1000*3,0))*payment_proc_pct)-(capex_total+(33*30*12*(1+bhxh_rate)*(1+salary_escalation)^2*5)+(opex_marketing*(1+marketing_growth)^2*5)+(opex_cloud_base*5+(200/(1+EXP(-adoption_steepness*(2028-adoption_midpoint)))*(1-0.05))*vcr_per_enterprise*12*cloud_per_1M_vcr/1000000*5)+((opex_branding+opex_external+opex_legal+opex_security+opex_partner_mgmt)*5)+(capex_total*capex_maintenance_pct*4)))*(1-cit_rate))/(1+discount_rate)^2.5 | C34: =((((200/(1+EXP(-adoption_steepness*(2028-adoption_midpoint)))*(1-0.1))*(cert_fee_yr1*(1+cert_fee_escalation)^2.5+training_pct*training_fee+audit_fee)*5)+(IF((200/(1+EXP(-adoption_steepness*(2028-adoption_midpoint)))*(1-0.1))>=stage2_gate,ecom_market_base*(1+ecom_growth_rate)^4*platform_market_share*tx_take_rate*1000*3,0))-((IF((200/(1+EXP(-adoption_steepness*(2028-adoption_midpoint)))*(1-0.1))>=stage2_gate,ecom_market_base*(1+ecom_growth_rate)^4*platform_market_share*tx_take_rate*1000*3,0))*payment_proc_pct)-(capex_total+(33*30*12*(1+bhxh_rate)*(1+salary_escalation)^2*5)+(opex_marketing*(1+marketing_growth)^2*5)+(opex_cloud_base*5+(200/(1+EXP(-adoption_steepness*(2028-adoption_midpoint)))*(1-0.1))*vcr_per_enterprise*12*cloud_per_1M_vcr/1000000*5)+((opex_branding+opex_external+opex_legal+opex_security+opex_partner_mgmt)*5)+(capex_total*capex_maintenance_pct*4)))*(1-cit_rate))/(1+discount_rate)^2.5 | D34: =((((200/(1+EXP(-adoption_steepness*(2028-adoption_midpoint)))*(1-0.15))*(cert_fee_yr1*(1+cert_fee_escalation)^2.5+training_pct*training_fee+audit_fee)*5)+(IF((200/(1+EXP(-adoption_steepness*(2028-adoption_midpoint)))*(1-0.15))>=stage2_gate,ecom_market_base*(1+ecom_growth_rate)^4*platform_market_share*tx_take_rate*1000*3,0))-((IF((200/(1+EXP(-adoption_steepness*(2028-adoption_midpoint)))*(1-0.15))>=stage2_gate,ecom_market_base*(1+ecom_growth_rate)^4*platform_market_share*tx_take_rate*1000*3,0))*payment_proc_pct)-(capex_total+(33*30*12*(1+bhxh_rate)*(1+salary_escalation)^2*5)+(opex_marketing*(1+marketing_growth)^2*5)+(opex_cloud_base*5+(200/(1+EXP(-adoption_steepness*(2028-adoption_midpoint)))*(1-0.15))*vcr_per_enterprise*12*cloud_per_1M_vcr/1000000*5)+((opex_branding+opex_external+opex_legal+opex_security+opex_partner_mgmt)*5)+(capex_total*capex_maintenance_pct*4)))*(1-cit_rate))/(1+discount_rate)^2.5 | E34: =((((200/(1+EXP(-adoption_steepness*(2028-adoption_midpoint)))*(1-0.2))*(cert_fee_yr1*(1+cert_fee_escalation)^2.5+training_pct*training_fee+audit_fee)*5)+(IF((200/(1+EXP(-adoption_steepness*(2028-adoption_midpoint)))*(1-0.2))>=stage2_gate,ecom_market_base*(1+ecom_growth_rate)^4*platform_market_share*tx_take_rate*1000*3,0))-((IF((200/(1+EXP(-adoption_steepness*(2028-adoption_midpoint)))*(1-0.2))>=stage2_gate,ecom_market_base*(1+ecom_growth_rate)^4*platform_market_share*tx_take_rate*1000*3,0))*payment_proc_pct)-(capex_total+(33*30*12*(1+bhxh_rate)*(1+salary_escalation)^2*5)+(opex_marketing*(1+marketing_growth)^2*5)+(opex_cloud_base*5+(200/(1+EXP(-adoption_steepness*(2028-adoption_midpoint)))*(1-0.2))*vcr_per_enterprise*12*cloud_per_1M_vcr/1000000*5)+((opex_branding+opex_external+opex_legal+opex_security+opex_partner_mgmt)*5)+(capex_total*capex_maintenance_pct*4)))*(1-cit_rate))/(1+discount_rate)^2.5 | F34: =((((200/(1+EXP(-adoption_steepness*(2028-adoption_midpoint)))*(1-0.25))*(cert_fee_yr1*(1+cert_fee_escalation)^2.5+training_pct*training_fee+audit_fee)*5)+(IF((200/(1+EXP(-adoption_steepness*(2028-adoption_midpoint)))*(1-0.25))>=stage2_gate,ecom_market_base*(1+ecom_growth_rate)^4*platform_market_share*tx_take_rate*1000*3,0))-((IF((200/(1+EXP(-adoption_steepness*(2028-adoption_midpoint)))*(1-0.25))>=stage2_gate,ecom_market_base*(1+ecom_growth_rate)^4*platform_market_share*tx_take_rate*1000*3,0))*payment_proc_pct)-(capex_total+(33*30*12*(1+bhxh_rate)*(1+salary_escalation)^2*5)+(opex_marketing*(1+marketing_growth)^2*5)+(opex_cloud_base*5+(200/(1+EXP(-adoption_steepness*(2028-adoption_midpoint)))*(1-0.25))*vcr_per_enterprise*12*cloud_per_1M_vcr/1000000*5)+((opex_branding+opex_external+opex_legal+opex_security+opex_partner_mgmt)*5)+(capex_total*capex_maintenance_pct*4)))*(1-cit_rate))/(1+discount_rate)^2.5 | G34: =((((200/(1+EXP(-adoption_steepness*(2028-adoption_midpoint)))*(1-0.3))*(cert_fee_yr1*(1+cert_fee_escalation)^2.5+training_pct*training_fee+audit_fee)*5)+(IF((200/(1+EXP(-adoption_steepness*(2028-adoption_midpoint)))*(1-0.3))>=stage2_gate,ecom_market_base*(1+ecom_growth_rate)^4*platform_market_share*tx_take_rate*1000*3,0))-((IF((200/(1+EXP(-adoption_steepness*(2028-adoption_midpoint)))*(1-0.3))>=stage2_gate,ecom_market_base*(1+ecom_growth_rate)^4*platform_market_share*tx_take_rate*1000*3,0))*payment_proc_pct)-(capex_total+(33*30*12*(1+bhxh_rate)*(1+salary_escalation)^2*5)+(opex_marketing*(1+marketing_growth)^2*5)+(opex_cloud_base*5+(200/(1+EXP(-adoption_steepness*(2028-adoption_midpoint)))*(1-0.3))*vcr_per_enterprise*12*cloud_per_1M_vcr/1000000*5)+((opex_branding+opex_external+opex_legal+opex_security+opex_partner_mgmt)*5)+(capex_total*capex_maintenance_pct*4)))*(1-cit_rate))/(1+discount_rate)^2.5 | H34: =((((200/(1+EXP(-adoption_steepness*(2028-adoption_midpoint)))*(1-0.35))*(cert_fee_yr1*(1+cert_fee_escalation)^2.5+training_pct*training_fee+audit_fee)*5)+(IF((200/(1+EXP(-adoption_steepness*(2028-adoption_midpoint)))*(1-0.35))>=stage2_gate,ecom_market_base*(1+ecom_growth_rate)^4*platform_market_share*tx_take_rate*1000*3,0))-((IF((200/(1+EXP(-adoption_steepness*(2028-adoption_midpoint)))*(1-0.35))>=stage2_gate,ecom_market_base*(1+ecom_growth_rate)^4*platform_market_share*tx_take_rate*1000*3,0))*payment_proc_pct)-(capex_total+(33*30*12*(1+bhxh_rate)*(1+salary_escalation)^2*5)+(opex_marketing*(1+marketing_growth)^2*5)+(opex_cloud_base*5+(200/(1+EXP(-adoption_steepness*(2028-adoption_midpoint)))*(1-0.35))*vcr_per_enterprise*12*cloud_per_1M_vcr/1000000*5)+((opex_branding+opex_external+opex_legal+opex_security+opex_partner_mgmt)*5)+(capex_total*capex_maintenance_pct*4)))*(1-cit_rate))/(1+discount_rate)^2.5
A35: 400 | B35: =((((400/(1+EXP(-adoption_steepness*(2028-adoption_midpoint)))*(1-0.05))*(cert_fee_yr1*(1+cert_fee_escalation)^2.5+training_pct*training_fee+audit_fee)*5)+(IF((400/(1+EXP(-adoption_steepness*(2028-adoption_midpoint)))*(1-0.05))>=stage2_gate,ecom_market_base*(1+ecom_growth_rate)^4*platform_market_share*tx_take_rate*1000*3,0))-((IF((400/(1+EXP(-adoption_steepness*(2028-adoption_midpoint)))*(1-0.05))>=stage2_gate,ecom_market_base*(1+ecom_growth_rate)^4*platform_market_share*tx_take_rate*1000*3,0))*payment_proc_pct)-(capex_total+(33*30*12*(1+bhxh_rate)*(1+salary_escalation)^2*5)+(opex_marketing*(1+marketing_growth)^2*5)+(opex_cloud_base*5+(400/(1+EXP(-adoption_steepness*(2028-adoption_midpoint)))*(1-0.05))*vcr_per_enterprise*12*cloud_per_1M_vcr/1000000*5)+((opex_branding+opex_external+opex_legal+opex_security+opex_partner_mgmt)*5)+(capex_total*capex_maintenance_pct*4)))*(1-cit_rate))/(1+discount_rate)^2.5 | C35: =((((400/(1+EXP(-adoption_steepness*(2028-adoption_midpoint)))*(1-0.1))*(cert_fee_yr1*(1+cert_fee_escalation)^2.5+training_pct*training_fee+audit_fee)*5)+(IF((400/(1+EXP(-adoption_steepness*(2028-adoption_midpoint)))*(1-0.1))>=stage2_gate,ecom_market_base*(1+ecom_growth_rate)^4*platform_market_share*tx_take_rate*1000*3,0))-((IF((400/(1+EXP(-adoption_steepness*(2028-adoption_midpoint)))*(1-0.1))>=stage2_gate,ecom_market_base*(1+ecom_growth_rate)^4*platform_market_share*tx_take_rate*1000*3,0))*payment_proc_pct)-(capex_total+(33*30*12*(1+bhxh_rate)*(1+salary_escalation)^2*5)+(opex_marketing*(1+marketing_growth)^2*5)+(opex_cloud_base*5+(400/(1+EXP(-adoption_steepness*(2028-adoption_midpoint)))*(1-0.1))*vcr_per_enterprise*12*cloud_per_1M_vcr/1000000*5)+((opex_branding+opex_external+opex_legal+opex_security+opex_partner_mgmt)*5)+(capex_total*capex_maintenance_pct*4)))*(1-cit_rate))/(1+discount_rate)^2.5 | D35: =((((400/(1+EXP(-adoption_steepness*(2028-adoption_midpoint)))*(1-0.15))*(cert_fee_yr1*(1+cert_fee_escalation)^2.5+training_pct*training_fee+audit_fee)*5)+(IF((400/(1+EXP(-adoption_steepness*(2028-adoption_midpoint)))*(1-0.15))>=stage2_gate,ecom_market_base*(1+ecom_growth_rate)^4*platform_market_share*tx_take_rate*1000*3,0))-((IF((400/(1+EXP(-adoption_steepness*(2028-adoption_midpoint)))*(1-0.15))>=stage2_gate,ecom_market_base*(1+ecom_growth_rate)^4*platform_market_share*tx_take_rate*1000*3,0))*payment_proc_pct)-(capex_total+(33*30*12*(1+bhxh_rate)*(1+salary_escalation)^2*5)+(opex_marketing*(1+marketing_growth)^2*5)+(opex_cloud_base*5+(400/(1+EXP(-adoption_steepness*(2028-adoption_midpoint)))*(1-0.15))*vcr_per_enterprise*12*cloud_per_1M_vcr/1000000*5)+((opex_branding+opex_external+opex_legal+opex_security+opex_partner_mgmt)*5)+(capex_total*capex_maintenance_pct*4)))*(1-cit_rate))/(1+discount_rate)^2.5 | E35: =((((400/(1+EXP(-adoption_steepness*(2028-adoption_midpoint)))*(1-0.2))*(cert_fee_yr1*(1+cert_fee_escalation)^2.5+training_pct*training_fee+audit_fee)*5)+(IF((400/(1+EXP(-adoption_steepness*(2028-adoption_midpoint)))*(1-0.2))>=stage2_gate,ecom_market_base*(1+ecom_growth_rate)^4*platform_market_share*tx_take_rate*1000*3,0))-((IF((400/(1+EXP(-adoption_steepness*(2028-adoption_midpoint)))*(1-0.2))>=stage2_gate,ecom_market_base*(1+ecom_growth_rate)^4*platform_market_share*tx_take_rate*1000*3,0))*payment_proc_pct)-(capex_total+(33*30*12*(1+bhxh_rate)*(1+salary_escalation)^2*5)+(opex_marketing*(1+marketing_growth)^2*5)+(opex_cloud_base*5+(400/(1+EXP(-adoption_steepness*(2028-adoption_midpoint)))*(1-0.2))*vcr_per_enterprise*12*cloud_per_1M_vcr/1000000*5)+((opex_branding+opex_external+opex_legal+opex_security+opex_partner_mgmt)*5)+(capex_total*capex_maintenance_pct*4)))*(1-cit_rate))/(1+discount_rate)^2.5 | F35: =((((400/(1+EXP(-adoption_steepness*(2028-adoption_midpoint)))*(1-0.25))*(cert_fee_yr1*(1+cert_fee_escalation)^2.5+training_pct*training_fee+audit_fee)*5)+(IF((400/(1+EXP(-adoption_steepness*(2028-adoption_midpoint)))*(1-0.25))>=stage2_gate,ecom_market_base*(1+ecom_growth_rate)^4*platform_market_share*tx_take_rate*1000*3,0))-((IF((400/(1+EXP(-adoption_steepness*(2028-adoption_midpoint)))*(1-0.25))>=stage2_gate,ecom_market_base*(1+ecom_growth_rate)^4*platform_market_share*tx_take_rate*1000*3,0))*payment_proc_pct)-(capex_total+(33*30*12*(1+bhxh_rate)*(1+salary_escalation)^2*5)+(opex_marketing*(1+marketing_growth)^2*5)+(opex_cloud_base*5+(400/(1+EXP(-adoption_steepness*(2028-adoption_midpoint)))*(1-0.25))*vcr_per_enterprise*12*cloud_per_1M_vcr/1000000*5)+((opex_branding+opex_external+opex_legal+opex_security+opex_partner_mgmt)*5)+(capex_total*capex_maintenance_pct*4)))*(1-cit_rate))/(1+discount_rate)^2.5 | G35: =((((400/(1+EXP(-adoption_steepness*(2028-adoption_midpoint)))*(1-0.3))*(cert_fee_yr1*(1+cert_fee_escalation)^2.5+training_pct*training_fee+audit_fee)*5)+(IF((400/(1+EXP(-adoption_steepness*(2028-adoption_midpoint)))*(1-0.3))>=stage2_gate,ecom_market_base*(1+ecom_growth_rate)^4*platform_market_share*tx_take_rate*1000*3,0))-((IF((400/(1+EXP(-adoption_steepness*(2028-adoption_midpoint)))*(1-0.3))>=stage2_gate,ecom_market_base*(1+ecom_growth_rate)^4*platform_market_share*tx_take_rate*1000*3,0))*payment_proc_pct)-(capex_total+(33*30*12*(1+bhxh_rate)*(1+salary_escalation)^2*5)+(opex_marketing*(1+marketing_growth)^2*5)+(opex_cloud_base*5+(400/(1+EXP(-adoption_steepness*(2028-adoption_midpoint)))*(1-0.3))*vcr_per_enterprise*12*cloud_per_1M_vcr/1000000*5)+((opex_branding+opex_external+opex_legal+opex_security+opex_partner_mgmt)*5)+(capex_total*capex_maintenance_pct*4)))*(1-cit_rate))/(1+discount_rate)^2.5 | H35: =((((400/(1+EXP(-adoption_steepness*(2028-adoption_midpoint)))*(1-0.35))*(cert_fee_yr1*(1+cert_fee_escalation)^2.5+training_pct*training_fee+audit_fee)*5)+(IF((400/(1+EXP(-adoption_steepness*(2028-adoption_midpoint)))*(1-0.35))>=stage2_gate,ecom_market_base*(1+ecom_growth_rate)^4*platform_market_share*tx_take_rate*1000*3,0))-((IF((400/(1+EXP(-adoption_steepness*(2028-adoption_midpoint)))*(1-0.35))>=stage2_gate,ecom_market_base*(1+ecom_growth_rate)^4*platform_market_share*tx_take_rate*1000*3,0))*payment_proc_pct)-(capex_total+(33*30*12*(1+bhxh_rate)*(1+salary_escalation)^2*5)+(opex_marketing*(1+marketing_growth)^2*5)+(opex_cloud_base*5+(400/(1+EXP(-adoption_steepness*(2028-adoption_midpoint)))*(1-0.35))*vcr_per_enterprise*12*cloud_per_1M_vcr/1000000*5)+((opex_branding+opex_external+opex_legal+opex_security+opex_partner_mgmt)*5)+(capex_total*capex_maintenance_pct*4)))*(1-cit_rate))/(1+discount_rate)^2.5
