Workbook
Name ad_cpm: Assumptions!$B$31
Name ad_impressions_base: Assumptions!$B$32
Name adoption_max: Assumptions!$B$18
Name adoption_midpoint: Assumptions!$B$19
Name adoption_steepness: Assumptions!$B$20
Name ap_days: Assumptions!$B$71
Name ar_days: Assumptions!$B$70
Name audit_fee: Assumptions!$B$34
Name base_year: Assumptions!$B$6
Name bhxh_rate: Assumptions!$B$62
Name capex_backend: 'Đầu tư ban đầu'!$B$5
Name capex_cloud_setup: 'Đầu tư ban đầu'!$B$4
Name capex_contingency: 'Đầu tư ban đầu'!$B$13
Name capex_data_platform: 'Đầu tư ban đầu'!$B$7
Name capex_devops: 'Đầu tư ban đầu'!$B$11
Name capex_frontend: 'Đầu tư ban đầu'!$B$6
Name capex_integration: 'Đầu tư ban đầu'!$B$10
Name capex_maintenance_pct: Assumptions!$B$39
Name capex_security_setup: 'Đầu tư ban đầu'!$B$8
Name capex_testing: 'Đầu tư ban đầu'!$B$12
Name capex_total: 'Đầu tư ban đầu'!$B$15
Name capex_ux_design: 'Đầu tư ban đầu'!$B$9
Name cert_fee_escalation: Assumptions!$B$27
Name cert_fee_yr1: Assumptions!$B$26
Name churn_rate: Assumptions!$B$22
Name cit_rate: Assumptions!$B$67
Name cloud_per_1M_vcr: Assumptions!$B$43
Name daas_price: Assumptions!$B$30
Name depreciation_years: Assumptions!$B$69
Name discount_rate: Assumptions!$B$68
Name ecom_growth_rate: Assumptions!$B$14
Name ecom_market_base: Assumptions!$B$13
Name marketing_growth: Assumptions!$B$41
Name opex_branding: Assumptions!$B$47
Name opex_cloud_base: Assumptions!$B$42
Name opex_contingency_pct: Assumptions!$B$53
Name opex_external: Assumptions!$B$45
Name opex_legal: Assumptions!$B$46
Name opex_marketing: Assumptions!$B$40
Name opex_partner_mgmt: Assumptions!$B$52
Name opex_pilot_eval: Assumptions!$B$49
Name opex_security: Assumptions!$B$48
Name opex_support_per_ent: Assumptions!$B$51
Name payment_proc_pct: Assumptions!$B$50
Name pilot_count: Assumptions!$B$21
Name platform_market_share: Assumptions!$B$29
Name recruit_cost_pct: Assumptions!$B$63
Name salary_bizops: Assumptions!$B$59
Name salary_data: Assumptions!$B$60
Name salary_dev: Assumptions!$B$58
Name salary_escalation: Assumptions!$B$61
Name salary_mgmt: Assumptions!$B$57
Name SAM_enterprises: Assumptions!$B$12
Name stage2_gate: Assumptions!$B$72
Name start_month: Assumptions!$B$7
Name TAM_enterprises: Assumptions!$B$11
Name training_fee: Assumptions!$B$33
Name training_pct: Assumptions!$B$35
Name tx_take_rate: Assumptions!$B$28
Name vcr_per_enterprise: Assumptions!$B$44

Sheet Hướng dẫn
A1: VISIT VIETNAM — MÔ HÌNH TÀI CHÍNH v4 — HƯỚNG DẪN
A2: v4.0 | 21/03/2026 | Phiên bản tiếng Việt
A4: DANH SÁCH CÁC TRANG
A5: Trang | B5: Mục đích | C5: Ghi chú
A6: Hướng dẫn | B6: Giải thích mô hình, thuật ngữ, công thức, cách sử dụng | C6: Đọc trước
A7: Assumptions | B7: 49 named ranges. MỌI đầu vào ở đây (ô vàng). | C7: Chỉ sửa ô vàng
A8: Đầu tư ban đầu | B8: 10 hạng mục CAPEX → capex_total. Lịch khấu hao. | C8: capex_total dùng khắp nơi
A9: Nhân sự | B9: 4 bộ phận × 42 kỳ. Lương = biên chế × named_salary × tăng × BHXH | C9: Ô vàng = biên chế
A10: Quy mô thị trường | B10: Đường cong S tăng trưởng DN. Year fracs từ base_year. | C10: Không hardcode năm
A11: Doanh thu | B11: 6 nguồn thu. GĐ2 kích hoạt khi đạt ngưỡng stage2_gate. | C11: Named ranges trong formulas
A12: Chi phí | B12: CAPEX (Đầu tư) + OPEX (Nhân sự + 10 danh mục + dự phòng) | C12: Liên kết chéo trang
A13: Kết quả KD | B13: DT → Giá vốn → LN gộp → OPEX → EBITDA → KH → EBIT → Thuế 20% → LN ròng | C13: Thuế TNDN 20%
A14: Dòng tiền | B14: ĐTHĐ + ĐTĐT → DTTD + Lũy kế. Vốn lưu động qua ar_days. | C14: Named ranges
A15: Thẩm định | B15: FCF theo năm, NPV, IRR, ROI. Dùng discount_rate. | C15: Công thức NPV duy nhất
A16: Kịch bản | B16: 5 kịch bản với giải thích chi tiết + yếu tố ảnh hưởng lớn nhất. | C16: Copy vào Assumptions chạy
... A18: Ngân sách 2026 | B18: Ngân sách tháng 1-12/2026. Cùng cấu trúc, NS tăng. | C18: Sẵn sàng duyệt
A20: THUẬT NGỮ
A21: Thuật ngữ | B21: Tên đầy đủ / Ý nghĩa | C21: Trong mô hình này
A22: NPV | B22: Giá trị hiện tại ròng | C22: Tổng dòng tiền tương lai chiết khấu về hiện tại. Dương = tạo giá trị.
A23: IRR | B23: Tỷ suất hoàn vốn nội bộ | C23: Tỷ suất chiết khấu khi NPV = 0. Cao hơn = lợi nhuận tốt hơn.
A24: WACC | B24: Chi phí vốn bình quân gia quyền | C24: Lợi nhuận tối thiểu NĐT kỳ vọng. Dùng làm discount_rate (15% cơ sở).
A25: ROI | B25: Lợi nhuận trên đầu tư | C25: (Dòng tiền lũy kế + Đầu tư) / Đầu tư.
A26: EBITDA | B26: LN trước lãi, thuế, khấu hao | C26: Lợi nhuận hoạt động trước chi phí phi tiền mặt và thuế.
A27: EBIT | B27: LN trước lãi và thuế | C27: =@EBITDA -@ Khấu hao. Lợi nhuận trước thuế.
A28: Thuế TNDN | B28: Thuế thu nhập doanh nghiệp | C28: Thuế suất chuẩn VN = 20%. Chỉ áp dụng khi EBIT > 0.
A29: FCF | B29: Dòng tiền tự do | C29: =@ĐTHĐ +@ ĐTĐT. Tiền thực sự có sẵn sau mọi chi tiêu.
A30: CAPEX | B30: Chi phí đầu tư | C30: Đầu tư 1 lần vào tài sản (nền tảng 5.280Tr). Khấu hao dần.
A31: OPEX | B31: Chi phí hoạt động | C31: Chi phí liên tục: NS, marketing, cloud, pháp lý... Ghi nhận ngay.
A32: COGS | B32: Giá vốn hàng bán | C32: Chi phí trực tiếp gắn với DT: phí thanh toán (2.5% DT giao dịch).
... A42: Churn | B42: Tỷ lệ rời bỏ | C42: % DN không gia hạn mỗi năm. Giảm net_enterprises.

Sheet Assumptions
A1: VISIT VIETNAM — MÔ HÌNH TÀI CHÍNH v4 — GIẢ ĐỊNH | F1: NPV | G1: IRR
A2: Ô vàng = giá trị có thể chỉnh | Chữ xanh = placeholder | Named ranges trong mọi công thức | F2: ='Thẩm định'!B13 -> 6313.5008 | G2: ='Thẩm định'!B14 -> 0.22064428
A4: THỜI GIAN
A5: Tham số | B5: Giá trị | C5: Đơn vị | D5: Ghi chú
A6: Năm cơ sở | B6: 2025 | C6: Năm | D6: Năm bắt đầu dự án
A7: Tháng bắt đầu | B7: 7 | C7: Tháng | D7: Tháng 7
A9: DỮ LIỆU THỊ TRƯỜNG
A10: Tham số | B10: Giá trị | C10: Đơn vị | D10: Ghi chú
A11: Tổng doanh nghiệp du lịch VN | B11: 40000 | D11: GSO/VNAT
A12: DN có thể phục vụ | B12: 15000 | D12: Hoạt động số
A13: Thị trường TMĐT du lịch (năm gốc) | B13: 82500 | C13: Tỷ VND | D13: e-Conomy SEA
A14: Tăng trưởng TMĐT du lịch/năm | B14: 0.08 | C14: % | D14: Dữ liệu lịch sử
A16: ĐƯỜNG CONG TĂNG TRƯỞNG (S-CURVE)
A17: Tham số | B17: Giá trị | C17: Đơn vị | D17: Ghi chú
A18: Trần doanh nghiệp (tối đa) | B18: 1200 | D18: Tiệm cận S-curve
A19: Năm tăng trưởng nhanh nhất | B19: 2028 | C19: Năm | D19: Điểm uốn
A20: Hệ số dốc | B20: 0.9 | D20: Cao hơn = dốc hơn
A21: DN ban đầu (thí điểm) | B21: 15 | D21: Đối tác thí điểm
A22: Tỷ lệ không gia hạn/năm | B22: 0.2 | C22: % | D22: Churn chứng nhận
A24: GIÁ DỊCH VỤ
A25: Tham số | B25: Giá trị | C25: Đơn vị | D25: Ghi chú
A26: Phí chứng nhận/DN/năm | B26: 25 | C26: Tr VND | D26: Gói thuê bao năm
A27: Tăng phí chứng nhận/năm | B27: 0.05 | C27: % | D27: Tăng giá
A28: Phí giao dịch (% GMV) | B28: 0.02 | C28: % | D28: Hoa hồng nền tảng
A29: % GMV TMĐT du lịch qua VV | B29: 0.02 | C29: % | D29: Mục tiêu thực tế
A30: Giá DaaS/triệu VCR | B30: 30 | C30: Tr VND | D30: Thuê bao dữ liệu
A31: CPM quảng cáo | B31: 150 | C31: K VND | D31: Benchmark B2B
A32: Lượt hiển thị QC/tháng (K) | B32: 500 | C32: K | D32: Tỷ lệ theo DN
A33: Phí đào tạo/phiên | B33: 15 | C33: Tr VND | D33: Nguồn thu MỚI
A34: Phí kiểm toán chứng nhận | B34: 10 | C34: Tr VND | D34: Nguồn thu MỚI
A35: % DN mua đào tạo | B35: 0.3 | C35: % | D35: Ước tính
A37: THAM SỐ CHI PHÍ
A38: Tham số | B38: Giá trị | C38: Đơn vị | D38: Ghi chú
A39: Bảo trì (% CAPEX/năm) | B39: 0.18 | C39: % | D39: Chuẩn ngành 15-20%
A40: Marketing (cơ sở/năm) | B40: 7000 | C40: Tr VND | D40: Dữ liệu gốc
A41: Tăng trưởng marketing/năm | B41: 0.15 | C41: % | D41: Tăng theo tham vọng
A42: Cloud cơ sở (năm) | B42: 3250 | C42: Tr VND | D42: Dữ liệu gốc
A43: Chi phí cloud/triệu VCR | B43: 8 | C43: Tr VND | D43: Chi phí biến đổi
A44: VCR/DN/tháng | B44: 10000 | C44: bản ghi | D44: Ước tính lưu lượng
A45: Đối ngoại (năm) | B45: 400 | C45: Tr VND | D45: Dữ liệu gốc
A46: Pháp lý & tuân thủ (năm) | B46: 240 | C46: Tr VND | D46: Dữ liệu gốc
A47: Thương hiệu & sự kiện (năm) | B47: 4000 | C47: Tr VND | D47: Dữ liệu gốc
A48: Bảo mật/pentest (năm) | B48: 250 | C48: Tr VND | D48: Dữ liệu gốc
A49: Đánh giá thí điểm (chỉ Y1) | B49: 200 | C49: Tr VND | D49: Chi phí 1 lần
A50: Phí cổng thanh toán | B50: 0.025 | C50: % | D50: Giá vốn giao dịch
... A53: Dự phòng (% tổng OPEX) | B53: 0.1 | C53: % | D53: Đệm rủi ro
A55: THAM SỐ NHÂN SỰ
A56: Tham số | B56: Giá trị | C56: Đơn vị | D56: Ghi chú
A57: Lương TB/tháng — Quản lý | B57: 45 | C57: Tr VND | D57: GĐ/PM
A58: Lương TB/tháng — Phát triển | B58: 35 | C58: Tr VND | D58: Kỹ sư
A59: Lương TB/tháng — Vận hành KD | B59: 20 | C59: Tr VND | D59: BD/hỗ trợ
A60: Lương TB/tháng — Dữ liệu | B60: 40 | C60: Tr VND | D60: Data eng
A61: Tăng lương hàng năm | B61: 0.1 | C61: % | D61: Thị trường VN
A62: Bảo hiểm XH (phần DN) | B62: 0.215 | C62: % | D62: BHXH+BHYT+BHTN
A63: Phí tuyển dụng (% lương Y1) | B63: 0.2 | C63: % | D63: Headhunter
A65: THAM SỐ TÀI CHÍNH
A66: Tham số | B66: Giá trị | C66: Đơn vị | D66: Ghi chú
A67: Thuế TNDN | B67: 0.2 | C67: % | D67: Luật VN
A68: Tỷ suất chiết khấu (WACC) | B68: 0.15 | C68: % | D68: Điều chỉnh rủi ro
A69: Thời gian khấu hao | B69: 5 | C69: Năm | D69: Đường thẳng
A70: Số ngày phải thu | B70: 45 | C70: Ngày | D70: Kỳ thu tiền
A71: Số ngày phải trả | B71: 30 | C71: Ngày | D71: Kỳ thanh toán
A72: Ngưỡng Giai đoạn 2 (DN tối thiểu) | B72: 300 | D72: Kích hoạt phí GD

Sheet Đầu tư ban đầu
A1: ĐẦU TƯ BAN ĐẦU — CHI TIẾT CAPEX (Tr VND)
A3: Hạng mục CAPEX | B3: Số tiền (Tr VND) | C3: Thời điểm | D3: Ghi chú
A4: Hạ tầng Cloud | B4: 800 | C4: H2 2025 | D4: Setup AWS/GCP ban đầu
A5: Phát triển Backend | B5: 1200 | C5: H2 2025 | D5: API, DB, logic lõi
A6: Frontend + mobile | B6: 900 | C6: H2 2025 | D6: Web + ứng dụng di động
A7: Nền tảng dữ liệu | B7: 600 | C7: H2 2025 | D7: Pipeline, phân tích
A8: Hạ tầng bảo mật | B8: 250 | C8: H2 2025 | D8: Pentest, xác thực
A9: Thiết kế UX/UI | B9: 350 | C9: H2 2025 | D9: Design system
A10: Tích hợp bên thứ 3 | B10: 400 | C10: H2 2025 | D10: Cổng TT, API OTA
A11: DevOps & CI/CD | B11: 280 | C11: H2 2025 | D11: Pipeline triển khai
A12: QA & kiểm thử | B12: 200 | C12: H2 2025 | D12: Kiểm thử tự động
A13: Dự phòng CAPEX (10%) | B13: 300 | C13: H2 2025 | D13: Đệm phát sinh
A15: TỔNG ĐẦU TƯ BAN ĐẦU | B15: =SUM(B4:B13) -> 5280
A17: LỊCH KHẤU HAO
A18: Năm | B18: Khấu hao/năm | C18: Khấu hao lũy kế | D18: Giá trị còn lại
A19: 2025 | B19: =capex_total/depreciation_years -> 1056 | C19: =B19 -> 1056 | D19: =capex_total-C19 -> 4224
A20: 2026 | B20: =capex_total/depreciation_years -> 1056 | C20: =C19+B20 -> 2112 | D20: =capex_total-C20 -> 3168
A21: 2027 | B21: =capex_total/depreciation_years -> 1056 | C21: =C20+B21 -> 3168 | D21: =capex_total-C21 -> 2112
A22: 2028 | B22: =capex_total/depreciation_years -> 1056 | C22: =C21+B22 -> 4224 | D22: =capex_total-C22 -> 1056
A23: 2029 | B23: =capex_total/depreciation_years -> 1056 | C23: =C22+B23 -> 5280 | D23: =capex_total-C23 -> 0
A24: 2030 | B24: =0 -> 0 | C24: =C23+B24 -> 5280 | D24: =capex_total-C24 -> 0

Sheet Nhân sự
A1: KẾ HOẠCH NHÂN SỰ — BIÊN CHẾ & CHI PHÍ
A3: Bộ phận / Hạng mục | B3: ĐVT | C3: Th7 2025 | D3: Th8 2025 | E3: Th9 2025 | F3: Th10 2025 | G3: Th11 2025 | H3: Th12 2025 | I3: Th1 2026 | J3: Th2 2026 | K3: Th3 2026 | L3: Th4 2026 | M3: Th5 2026 | N3: Th6 2026 | O3: Th7 2026 | P3: Th8 2026 | Q3: Th9 2026 | R3: Th10 2026 | S3: Th11 2026 | T3: Th12 2026 | U3: Th1 2027 | V3: Th2 2027 | W3: Th3 2027 | X3: Th4 2027 | Y3: Th5 2027 | Z3: Th6 2027 | AA3: Th7 2027 | AB3: Th8 2027 | AC3: Th9 2027 | AD3: Th10 2027 | AE3: Th11 2027 | AF3: Th12 2027 | AG3: Q1 2028 | AH3: Q2 2028 | AI3: Q3 2028 | AJ3: Q4 2028 | AK3: Q1 2029 | AL3: Q2 2029 | AM3: Q3 2029 | AN3: Q4 2029 | AO3: Q1 2030 | AP3: Q2 2030 | AQ3: Q3 2030 | AR3: Q4 2030
A4: SỐ LƯỢNG NHÂN SỰ
A5: Quản lý | B5: người | C5: 2 | D5: 2 | E5: 2 | F5: 2 | G5: 2 | H5: 2 | I5: 2 | J5: 2 | K5: 2 | L5: 2 | M5: 2 | N5: 2 | O5: 2 | P5: 2 | Q5: 2 | R5: 2 | S5: 2 | T5: 2 | U5: 3 | V5: 3 | W5: 3 | X5: 3 | Y5: 3 | Z5: 3 | AA5: 3 | AB5: 3 | AC5: 3 | AD5: 3 | AE5: 3 | AF5: 3 | AG5: 3 | AH5: 3 | AI5: 3 | AJ5: 3 | AK5: 4 | AL5: 4 | AM5: 4 | AN5: 4 | AO5: 4 | AP5: 4 | AQ5: 4 | AR5: 4
A6: Phát triển | B6: người | C6: 12 | D6: 12 | E6: 12 | F6: 12 | G6: 12 | H6: 12 | I6: 12 | J6: 12 | K6: 12 | L6: 12 | M6: 12 | N6: 12 | O6: 12 | P6: 12 | Q6: 12 | R6: 12 | S6: 12 | T6: 12 | U6: 14 | V6: 14 | W6: 14 | X6: 14 | Y6: 14 | Z6: 14 | AA6: 14 | AB6: 14 | AC6: 14 | AD6: 14 | AE6: 14 | AF6: 14 | AG6: 16 | AH6: 16 | AI6: 16 | AJ6: 16 | AK6: 18 | AL6: 18 | AM6: 18 | AN6: 18 | AO6: 20 | AP6: 20 | AQ6: 20 | AR6: 20
A7: Vận hành KD | B7: người | C7: 2 | D7: 2 | E7: 2 | F7: 2 | G7: 2 | H7: 2 | I7: 6 | J7: 6 | K7: 6 | L7: 6 | M7: 6 | N7: 6 | O7: 6 | P7: 6 | Q7: 6 | R7: 6 | S7: 6 | T7: 6 | U7: 10 | V7: 10 | W7: 10 | X7: 10 | Y7: 10 | Z7: 10 | AA7: 10 | AB7: 10 | AC7: 10 | AD7: 10 | AE7: 10 | AF7: 10 | AG7: 18 | AH7: 18 | AI7: 18 | AJ7: 18 | AK7: 28 | AL7: 28 | AM7: 28 | AN7: 28 | AO7: 35 | AP7: 35 | AQ7: 35 | AR7: 35
A8: Dữ liệu & Phân tích | B8: người | C8: 0 | D8: 0 | E8: 0 | F8: 0 | G8: 0 | H8: 0 | I8: 2 | J8: 2 | K8: 2 | L8: 2 | M8: 2 | N8: 2 | O8: 2 | P8: 2 | Q8: 2 | R8: 2 | S8: 2 | T8: 2 | U8: 3 | V8: 3 | W8: 3 | X8: 3 | Y8: 3 | Z8: 3 | AA8: 3 | AB8: 3 | AC8: 3 | AD8: 3 | AE8: 3 | AF8: 3 | AG8: 4 | AH8: 4 | AI8: 4 | AJ8: 4 | AK8: 5 | AL8: 5 | AM8: 5 | AN8: 5 | AO8: 6 | AP8: 6 | AQ8: 6 | AR8: 6
A9: TỔNG NHÂN SỰ | B9: người | C9: =C5+C6+C7+C8 -> 16 | D9: =D5+D6+D7+D8 -> 16 | E9: =E5+E6+E7+E8 -> 16 | F9: =F5+F6+F7+F8 -> 16 | G9: =G5+G6+G7+G8 -> 16 | H9: =H5+H6+H7+H8 -> 16 | I9: =I5+I6+I7+I8 -> 22 | J9: =J5+J6+J7+J8 -> 22 | ... AR9: =AR5+AR6+AR7+AR8 -> 65
A11: TUYỂN MỚI
A12: Tuyển mới | B12: người | C12: =C9 -> 16 | D12: =MAX(0,D9-C9) -> 0 | E12: =MAX(0,E9-D9) -> 0 | F12: =MAX(0,F9-E9) -> 0 | G12: =MAX(0,G9-F9) -> 0 | H12: =MAX(0,H9-G9) -> 0 | I12: =MAX(0,I9-H9) -> 6 | J12: =MAX(0,J9-I9) -> 0 | K12: =MAX(0,K9-J9) -> 0 | ... AR12: =MAX(0,AR9-AQ9) -> 0
A14: CHI PHÍ LƯƠNG (Tr VND)
A15: CP Quản lý | B15: Tr VND | C15: =C5*salary_mgmt*1*(1+salary_escalation)^0*(1+bhxh_rate) -> 109.35 | D15: =D5*salary_mgmt*1*(1+salary_escalation)^0*(1+bhxh_rate) -> 109.35 | E15: =E5*salary_mgmt*1*(1+salary_escalation)^0*(1+bhxh_rate) -> 109.35 | F15: =F5*salary_mgmt*1*(1+salary_escalation)^0*(1+bhxh_rate) -> 109.35 | G15: =G5*salary_mgmt*1*(1+salary_escalation)^0*(1+bhxh_rate) -> 109.35 | H15: =H5*salary_mgmt*1*(1+salary_escalation)^0*(1+bhxh_rate) -> 109.35 | I15: =I5*salary_mgmt*1*(1+salary_escalation)^1*(1+bhxh_rate) -> 120.285 | J15: =J5*salary_mgmt*1*(1+salary_escalation)^1*(1+bhxh_rate) -> 120.285 | K15: =K5*salary_mgmt*1*(1+salary_escalation)^1*(1+bhxh_rate) -> 120.285 | L15: =L5*salary_mgmt*1*(1+salary_escalation)^1*(1+bhxh_rate) -> 120.285 | M15: =M5*salary_mgmt*1*(1+salary_escalation)^1*(1+bhxh_rate) -> 120.285 | N15: =N5*salary_mgmt*1*(1+salary_escalation)^1*(1+bhxh_rate) -> 120.285 | O15: =O5*salary_mgmt*1*(1+salary_escalation)^1*(1+bhxh_rate) -> 120.285 | P15: =P5*salary_mgmt*1*(1+salary_escalation)^1*(1+bhxh_rate) -> 120.285 | ... T15: =T5*salary_mgmt*1*(1+salary_escalation)^1*(1+bhxh_rate) -> 120.285 | U15: =U5*salary_mgmt*1*(1+salary_escalation)^2*(1+bhxh_rate) -> 198.47025 | V15: =V5*salary_mgmt*1*(1+salary_escalation)^2*(1+bhxh_rate) -> 198.47025 | W15: =W5*salary_mgmt*1*(1+salary_escalation)^2*(1+bhxh_rate) -> 198.47025 | X15: =X5*salary_mgmt*1*(1+salary_escalation)^2*(1+bhxh_rate) -> 198.47025 | Y15: =Y5*salary_mgmt*1*(1+salary_escalation)^2*(1+bhxh_rate) -> 198.47025 | Z15: =Z5*salary_mgmt*1*(1+salary_escalation)^2*(1+bhxh_rate) -> 198.47025 | AA15: =AA5*salary_mgmt*1*(1+salary_escalation)^2*(1+bhxh_rate) -> 198.47025 | AB15: =AB5*salary_mgmt*1*(1+salary_escalation)^2*(1+bhxh_rate) -> 198.47025 | ... AF15: =AF5*salary_mgmt*1*(1+salary_escalation)^2*(1+bhxh_rate) -> 198.47025 | AG15: =AG5*salary_mgmt*3*(1+salary_escalation)^3*(1+bhxh_rate) -> 654.95183 | AH15: =AH5*salary_mgmt*3*(1+salary_escalation)^3*(1+bhxh_rate) -> 654.95183 | AI15: =AI5*salary_mgmt*3*(1+salary_escalation)^3*(1+bhxh_rate) -> 654.95183 | AJ15: =AJ5*salary_mgmt*3*(1+salary_escalation)^3*(1+bhxh_rate) -> 654.95183 | AK15: =AK5*salary_mgmt*3*(1+salary_escalation)^4*(1+bhxh_rate) -> 960.59601 | AL15: =AL5*salary_mgmt*3*(1+salary_escalation)^4*(1+bhxh_rate) -> 960.59601 | AM15: =AM5*salary_mgmt*3*(1+salary_escalation)^4*(1+bhxh_rate) -> 960.59601 | AN15: =AN5*salary_mgmt*3*(1+salary_escalation)^4*(1+bhxh_rate) -> 960.59601 | AO15: =AO5*salary_mgmt*3*(1+salary_escalation)^5*(1+bhxh_rate) -> 1056.6556 | AP15: =AP5*salary_mgmt*3*(1+salary_escalation)^5*(1+bhxh_rate) -> 1056.6556 | AQ15: =AQ5*salary_mgmt*3*(1+salary_escalation)^5*(1+bhxh_rate) -> 1056.6556 | AR15: =AR5*salary_mgmt*3*(1+salary_escalation)^5*(1+bhxh_rate) -> 1056.6556
A16: CP Phát triển | B16: Tr VND | C16: =C6*salary_dev*1*(1+salary_escalation)^0*(1+bhxh_rate) -> 510.3 | D16: =D6*salary_dev*1*(1+salary_escalation)^0*(1+bhxh_rate) -> 510.3 | E16: =E6*salary_dev*1*(1+salary_escalation)^0*(1+bhxh_rate) -> 510.3 | F16: =F6*salary_dev*1*(1+salary_escalation)^0*(1+bhxh_rate) -> 510.3 | G16: =G6*salary_dev*1*(1+salary_escalation)^0*(1+bhxh_rate) -> 510.3 | H16: =H6*salary_dev*1*(1+salary_escalation)^0*(1+bhxh_rate) -> 510.3 | I16: =I6*salary_dev*1*(1+salary_escalation)^1*(1+bhxh_rate) -> 561.33 | J16: =J6*salary_dev*1*(1+salary_escalation)^1*(1+bhxh_rate) -> 561.33 | K16: =K6*salary_dev*1*(1+salary_escalation)^1*(1+bhxh_rate) -> 561.33 | L16: =L6*salary_dev*1*(1+salary_escalation)^1*(1+bhxh_rate) -> 561.33 | M16: =M6*salary_dev*1*(1+salary_escalation)^1*(1+bhxh_rate) -> 561.33 | N16: =N6*salary_dev*1*(1+salary_escalation)^1*(1+bhxh_rate) -> 561.33 | O16: =O6*salary_dev*1*(1+salary_escalation)^1*(1+bhxh_rate) -> 561.33 | P16: =P6*salary_dev*1*(1+salary_escalation)^1*(1+bhxh_rate) -> 561.33 | ... T16: =T6*salary_dev*1*(1+salary_escalation)^1*(1+bhxh_rate) -> 561.33 | U16: =U6*salary_dev*1*(1+salary_escalation)^2*(1+bhxh_rate) -> 720.3735 | V16: =V6*salary_dev*1*(1+salary_escalation)^2*(1+bhxh_rate) -> 720.3735 | W16: =W6*salary_dev*1*(1+salary_escalation)^2*(1+bhxh_rate) -> 720.3735 | X16: =X6*salary_dev*1*(1+salary_escalation)^2*(1+bhxh_rate) -> 720.3735 | Y16: =Y6*salary_dev*1*(1+salary_escalation)^2*(1+bhxh_rate) -> 720.3735 | Z16: =Z6*salary_dev*1*(1+salary_escalation)^2*(1+bhxh_rate) -> 720.3735 | AA16: =AA6*salary_dev*1*(1+salary_escalation)^2*(1+bhxh_rate) -> 720.3735 | AB16: =AB6*salary_dev*1*(1+salary_escalation)^2*(1+bhxh_rate) -> 720.3735 | ... AF16: =AF6*salary_dev*1*(1+salary_escalation)^2*(1+bhxh_rate) -> 720.3735 | AG16: =AG6*salary_dev*3*(1+salary_escalation)^3*(1+bhxh_rate) -> 2716.8372 | AH16: =AH6*salary_dev*3*(1+salary_escalation)^3*(1+bhxh_rate) -> 2716.8372 | AI16: =AI6*salary_dev*3*(1+salary_escalation)^3*(1+bhxh_rate) -> 2716.8372 | AJ16: =AJ6*salary_dev*3*(1+salary_escalation)^3*(1+bhxh_rate) -> 2716.8372 | AK16: =AK6*salary_dev*3*(1+salary_escalation)^4*(1+bhxh_rate) -> 3362.086 | AL16: =AL6*salary_dev*3*(1+salary_escalation)^4*(1+bhxh_rate) -> 3362.086 | AM16: =AM6*salary_dev*3*(1+salary_escalation)^4*(1+bhxh_rate) -> 3362.086 | AN16: =AN6*salary_dev*3*(1+salary_escalation)^4*(1+bhxh_rate) -> 3362.086 | AO16: =AO6*salary_dev*3*(1+salary_escalation)^5*(1+bhxh_rate) -> 4109.2163 | AP16: =AP6*salary_dev*3*(1+salary_escalation)^5*(1+bhxh_rate) -> 4109.2163 | AQ16: =AQ6*salary_dev*3*(1+salary_escalation)^5*(1+bhxh_rate) -> 4109.2163 | AR16: =AR6*salary_dev*3*(1+salary_escalation)^5*(1+bhxh_rate) -> 4109.2163
A17: CP Vận hành KD | B17: Tr VND | C17: =C7*salary_bizops*1*(1+salary_escalation)^0*(1+bhxh_rate) -> 48.6 | D17: =D7*salary_bizops*1*(1+salary_escalation)^0*(1+bhxh_rate) -> 48.6 | E17: =E7*salary_bizops*1*(1+salary_escalation)^0*(1+bhxh_rate) -> 48.6 | F17: =F7*salary_bizops*1*(1+salary_escalation)^0*(1+bhxh_rate) -> 48.6 | G17: =G7*salary_bizops*1*(1+salary_escalation)^0*(1+bhxh_rate) -> 48.6 | H17: =H7*salary_bizops*1*(1+salary_escalation)^0*(1+bhxh_rate) -> 48.6 | I17: =I7*salary_bizops*1*(1+salary_escalation)^1*(1+bhxh_rate) -> 160.38 | J17: =J7*salary_bizops*1*(1+salary_escalation)^1*(1+bhxh_rate) -> 160.38 | K17: =K7*salary_bizops*1*(1+salary_escalation)^1*(1+bhxh_rate) -> 160.38 | L17: =L7*salary_bizops*1*(1+salary_escalation)^1*(1+bhxh_rate) -> 160.38 | M17: =M7*salary_bizops*1*(1+salary_escalation)^1*(1+bhxh_rate) -> 160.38 | N17: =N7*salary_bizops*1*(1+salary_escalation)^1*(1+bhxh_rate) -> 160.38 | O17: =O7*salary_bizops*1*(1+salary_escalation)^1*(1+bhxh_rate) -> 160.38 | P17: =P7*salary_bizops*1*(1+salary_escalation)^1*(1+bhxh_rate) -> 160.38 | ... T17: =T7*salary_bizops*1*(1+salary_escalation)^1*(1+bhxh_rate) -> 160.38 | U17: =U7*salary_bizops*1*(1+salary_escalation)^2*(1+bhxh_rate) -> 294.03 | V17: =V7*salary_bizops*1*(1+salary_escalation)^2*(1+bhxh_rate) -> 294.03 | W17: =W7*salary_bizops*1*(1+salary_escalation)^2*(1+bhxh_rate) -> 294.03 | X17: =X7*salary_bizops*1*(1+salary_escalation)^2*(1+bhxh_rate) -> 294.03 | Y17: =Y7*salary_bizops*1*(1+salary_escalation)^2*(1+bhxh_rate) -> 294.03 | Z17: =Z7*salary_bizops*1*(1+salary_escalation)^2*(1+bhxh_rate) -> 294.03 | AA17: =AA7*salary_bizops*1*(1+salary_escalation)^2*(1+bhxh_rate) -> 294.03 | AB17: =AB7*salary_bizops*1*(1+salary_escalation)^2*(1+bhxh_rate) -> 294.03 | ... AF17: =AF7*salary_bizops*1*(1+salary_escalation)^2*(1+bhxh_rate) -> 294.03 | AG17: =AG7*salary_bizops*3*(1+salary_escalation)^3*(1+bhxh_rate) -> 1746.5382 | AH17: =AH7*salary_bizops*3*(1+salary_escalation)^3*(1+bhxh_rate) -> 1746.5382 | AI17: =AI7*salary_bizops*3*(1+salary_escalation)^3*(1+bhxh_rate) -> 1746.5382 | AJ17: =AJ7*salary_bizops*3*(1+salary_escalation)^3*(1+bhxh_rate) -> 1746.5382 | AK17: =AK7*salary_bizops*3*(1+salary_escalation)^4*(1+bhxh_rate) -> 2988.5209 | AL17: =AL7*salary_bizops*3*(1+salary_escalation)^4*(1+bhxh_rate) -> 2988.5209 | AM17: =AM7*salary_bizops*3*(1+salary_escalation)^4*(1+bhxh_rate) -> 2988.5209 | AN17: =AN7*salary_bizops*3*(1+salary_escalation)^4*(1+bhxh_rate) -> 2988.5209 | AO17: =AO7*salary_bizops*3*(1+salary_escalation)^5*(1+bhxh_rate) -> 4109.2163 | AP17: =AP7*salary_bizops*3*(1+salary_escalation)^5*(1+bhxh_rate) -> 4109.2163 | AQ17: =AQ7*salary_bizops*3*(1+salary_escalation)^5*(1+bhxh_rate) -> 4109.2163 | AR17: =AR7*salary_bizops*3*(1+salary_escalation)^5*(1+bhxh_rate) -> 4109.2163
A18: CP Dữ liệu & Phân tích | B18: Tr VND | C18: =C8*salary_data*1*(1+salary_escalation)^0*(1+bhxh_rate) -> 0 | D18: =D8*salary_data*1*(1+salary_escalation)^0*(1+bhxh_rate) -> 0 | E18: =E8*salary_data*1*(1+salary_escalation)^0*(1+bhxh_rate) -> 0 | F18: =F8*salary_data*1*(1+salary_escalation)^0*(1+bhxh_rate) -> 0 | G18: =G8*salary_data*1*(1+salary_escalation)^0*(1+bhxh_rate) -> 0 | H18: =H8*salary_data*1*(1+salary_escalation)^0*(1+bhxh_rate) -> 0 | I18: =I8*salary_data*1*(1+salary_escalation)^1*(1+bhxh_rate) -> 106.92 | J18: =J8*salary_data*1*(1+salary_escalation)^1*(1+bhxh_rate) -> 106.92 | K18: =K8*salary_data*1*(1+salary_escalation)^1*(1+bhxh_rate) -> 106.92 | L18: =L8*salary_data*1*(1+salary_escalation)^1*(1+bhxh_rate) -> 106.92 | M18: =M8*salary_data*1*(1+salary_escalation)^1*(1+bhxh_rate) -> 106.92 | N18: =N8*salary_data*1*(1+salary_escalation)^1*(1+bhxh_rate) -> 106.92 | O18: =O8*salary_data*1*(1+salary_escalation)^1*(1+bhxh_rate) -> 106.92 | P18: =P8*salary_data*1*(1+salary_escalation)^1*(1+bhxh_rate) -> 106.92 | ... T18: =T8*salary_data*1*(1+salary_escalation)^1*(1+bhxh_rate) -> 106.92 | U18: =U8*salary_data*1*(1+salary_escalation)^2*(1+bhxh_rate) -> 176.418 | V18: =V8*salary_data*1*(1+salary_escalation)^2*(1+bhxh_rate) -> 176.418 | W18: =W8*salary_data*1*(1+salary_escalation)^2*(1+bhxh_rate) -> 176.418 | X18: =X8*salary_data*1*(1+salary_escalation)^2*(1+bhxh_rate) -> 176.418 | Y18: =Y8*salary_data*1*(1+salary_escalation)^2*(1+bhxh_rate) -> 176.418 | Z18: =Z8*salary_data*1*(1+salary_escalation)^2*(1+bhxh_rate) -> 176.418 | AA18: =AA8*salary_data*1*(1+salary_escalation)^2*(1+bhxh_rate) -> 176.418 | AB18: =AB8*salary_data*1*(1+salary_escalation)^2*(1+bhxh_rate) -> 176.418 | ... AF18: =AF8*salary_data*1*(1+salary_escalation)^2*(1+bhxh_rate) -> 176.418 | AG18: =AG8*salary_data*3*(1+salary_escalation)^3*(1+bhxh_rate) -> 776.2392 | AH18: =AH8*salary_data*3*(1+salary_escalation)^3*(1+bhxh_rate) -> 776.2392 | AI18: =AI8*salary_data*3*(1+salary_escalation)^3*(1+bhxh_rate) -> 776.2392 | AJ18: =AJ8*salary_data*3*(1+salary_escalation)^3*(1+bhxh_rate) -> 776.2392 | AK18: =AK8*salary_data*3*(1+salary_escalation)^4*(1+bhxh_rate) -> 1067.3289 | AL18: =AL8*salary_data*3*(1+salary_escalation)^4*(1+bhxh_rate) -> 1067.3289 | AM18: =AM8*salary_data*3*(1+salary_escalation)^4*(1+bhxh_rate) -> 1067.3289 | AN18: =AN8*salary_data*3*(1+salary_escalation)^4*(1+bhxh_rate) -> 1067.3289 | AO18: =AO8*salary_data*3*(1+salary_escalation)^5*(1+bhxh_rate) -> 1408.8741 | AP18: =AP8*salary_data*3*(1+salary_escalation)^5*(1+bhxh_rate) -> 1408.8741 | AQ18: =AQ8*salary_data*3*(1+salary_escalation)^5*(1+bhxh_rate) -> 1408.8741 | AR18: =AR8*salary_data*3*(1+salary_escalation)^5*(1+bhxh_rate) -> 1408.8741
A19: TỔNG LƯƠNG | B19: Tr VND | C19: =C15+C16+C17+C18 -> 668.25 | D19: =D15+D16+D17+D18 -> 668.25 | E19: =E15+E16+E17+E18 -> 668.25 | F19: =F15+F16+F17+F18 -> 668.25 | G19: =G15+G16+G17+G18 -> 668.25 | H19: =H15+H16+H17+H18 -> 668.25 | I19: =I15+I16+I17+I18 -> 948.915 | J19: =J15+J16+J17+J18 -> 948.915 | ... AR19: =AR15+AR16+AR17+AR18 -> 10683.962
A20: Tuyển dụng | B20: Tr VND | C20: =C12*30*12*recruit_cost_pct -> 1152 | D20: =D12*30*12*recruit_cost_pct -> 0 | E20: =E12*30*12*recruit_cost_pct -> 0 | F20: =F12*30*12*recruit_cost_pct -> 0 | G20: =G12*30*12*recruit_cost_pct -> 0 | H20: =H12*30*12*recruit_cost_pct -> 0 | I20: =I12*30*12*recruit_cost_pct -> 432 | J20: =J12*30*12*recruit_cost_pct -> 0 | ... AR20: =AR12*30*12*recruit_cost_pct -> 0
A21: TỔNG CHI PHÍ NHÂN SỰ | B21: Tr VND | C21: =C19+C20 -> 1820.25 | D21: =D19+D20 -> 668.25 | E21: =E19+E20 -> 668.25 | F21: =F19+F20 -> 668.25 | G21: =G19+G20 -> 668.25 | H21: =H19+H20 -> 668.25 | I21: =I19+I20 -> 1380.915 | J21: =J19+J20 -> 948.915 | ... AR21: =AR19+AR20 -> 10683.962

Sheet Quy mô thị trường
A1: QUY MÔ THỊ TRƯỜNG & TĂNG TRƯỞNG
A3: Chỉ số kỳ | B3: idx | C3: 0 | D3: 1 | E3: 2 | F3: 3 | G3: 4 | H3: 5 | I3: 6 | J3: 7 | K3: 8 | L3: 9 | M3: 10 | N3: 11 | O3: 12 | P3: 13 | Q3: 14 | R3: 15 | S3: 16 | T3: 17 | U3: 18 | V3: 19 | W3: 20 | X3: 21 | Y3: 22 | Z3: 23 | AA3: 24 | AB3: 25 | AC3: 26 | AD3: 27 | AE3: 28 | AF3: 29 | AG3: 30 | AH3: 31 | AI3: 32 | AJ3: 33 | AK3: 34 | AL3: 35 | AM3: 36 | AN3: 37 | AO3: 38 | AP3: 39 | AQ3: 40 | AR3: 41
A4: Năm phân số | B4: năm | C4: =base_year+(start_month-1+C3)/12 -> 2025.5 | D4: =base_year+(start_month-1+D3)/12 -> 2025.5833 | E4: =base_year+(start_month-1+E3)/12 -> 2025.6667 | F4: =base_year+(start_month-1+F3)/12 -> 2025.75 | G4: =base_year+(start_month-1+G3)/12 -> 2025.8333 | H4: =base_year+(start_month-1+H3)/12 -> 2025.9167 | I4: =base_year+(start_month-1+I3)/12 -> 2026 | J4: =base_year+(start_month-1+J3)/12 -> 2026.0833 | ... AF4: =base_year+(start_month-1+AF3)/12 -> 2027.9167 | AG4: =2028+(1-0.5)/12 -> 2028.0417 | AH4: =2028+(4-0.5)/12 -> 2028.2917 | AI4: =2028+(7-0.5)/12 -> 2028.5417 | AJ4: =2028+(10-0.5)/12 -> 2028.7917 | AK4: =2028+(13-0.5)/12 -> 2029.0417 | AL4: =2028+(16-0.5)/12 -> 2029.2917 | AM4: =2028+(19-0.5)/12 -> 2029.5417 | AN4: =2028+(22-0.5)/12 -> 2029.7917 | AO4: =2028+(25-0.5)/12 -> 2030.0417 | AP4: =2028+(28-0.5)/12 -> 2030.2917 | AQ4: =2028+(31-0.5)/12 -> 2030.5417 | AR4: =2028+(34-0.5)/12 -> 2030.7917
A5: Năm từ gốc | B5: năm | C5: =FLOOR(C4-base_year,1) -> 0 | D5: =FLOOR(D4-base_year,1) -> 0 | E5: =FLOOR(E4-base_year,1) -> 0 | F5: =FLOOR(F4-base_year,1) -> 0 | G5: =FLOOR(G4-base_year,1) -> 0 | H5: =FLOOR(H4-base_year,1) -> 0 | I5: =FLOOR(I4-base_year,1) -> 1 | J5: =FLOOR(J4-base_year,1) -> 1 | ... AR5: =FLOOR(AR4-base_year,1) -> 5
A6: Ước số kỳ | B6: chia | C6: 12 | D6: 12 | E6: 12 | F6: 12 | G6: 12 | H6: 12 | I6: 12 | J6: 12 | K6: 12 | L6: 12 | M6: 12 | N6: 12 | O6: 12 | P6: 12 | Q6: 12 | R6: 12 | S6: 12 | T6: 12 | U6: 12 | V6: 12 | W6: 12 | X6: 12 | Y6: 12 | Z6: 12 | AA6: 12 | AB6: 12 | AC6: 12 | AD6: 12 | AE6: 12 | AF6: 12 | AG6: 4 | AH6: 4 | AI6: 4 | AJ6: 4 | AK6: 4 | AL6: 4 | AM6: 4 | AN6: 4 | AO6: 4 | AP6: 4 | AQ6: 4 | AR6: 4
A7: Số tháng/kỳ | B7: tháng | C7: 1 | D7: 1 | E7: 1 | F7: 1 | G7: 1 | H7: 1 | I7: 1 | J7: 1 | K7: 1 | L7: 1 | M7: 1 | N7: 1 | O7: 1 | P7: 1 | Q7: 1 | R7: 1 | S7: 1 | T7: 1 | U7: 1 | V7: 1 | W7: 1 | X7: 1 | Y7: 1 | Z7: 1 | AA7: 1 | AB7: 1 | AC7: 1 | AD7: 1 | AE7: 1 | AF7: 1 | AG7: 3 | AH7: 3 | AI7: 3 | AJ7: 3 | AK7: 3 | AL7: 3 | AM7: 3 | AN7: 3 | AO7: 3 | AP7: 3 | AQ7: 3 | AR7: 3
A9: Hạng mục | B9: ĐVT | C9: Th7 2025 | D9: Th8 2025 | E9: Th9 2025 | F9: Th10 2025 | G9: Th11 2025 | H9: Th12 2025 | I9: Th1 2026 | J9: Th2 2026 | K9: Th3 2026 | L9: Th4 2026 | M9: Th5 2026 | N9: Th6 2026 | O9: Th7 2026 | P9: Th8 2026 | Q9: Th9 2026 | R9: Th10 2026 | S9: Th11 2026 | T9: Th12 2026 | U9: Th1 2027 | V9: Th2 2027 | W9: Th3 2027 | X9: Th4 2027 | Y9: Th5 2027 | Z9: Th6 2027 | AA9: Th7 2027 | AB9: Th8 2027 | AC9: Th9 2027 | AD9: Th10 2027 | AE9: Th11 2027 | AF9: Th12 2027 | AG9: Q1 2028 | AH9: Q2 2028 | AI9: Q3 2028 | AJ9: Q4 2028 | AK9: Q1 2029 | AL9: Q2 2029 | AM9: Q3 2029 | AN9: Q4 2029 | AO9: Q1 2030 | AP9: Q2 2030 | AQ9: Q3 2030 | AR9: Q4 2030
A10: TT TMĐT du lịch | B10: Tỷ VND | C10: =ecom_market_base*(1+ecom_growth_rate)^C5/C6 -> 6875 | D10: =ecom_market_base*(1+ecom_growth_rate)^D5/D6 -> 6875 | E10: =ecom_market_base*(1+ecom_growth_rate)^E5/E6 -> 6875 | F10: =ecom_market_base*(1+ecom_growth_rate)^F5/F6 -> 6875 | G10: =ecom_market_base*(1+ecom_growth_rate)^G5/G6 -> 6875 | H10: =ecom_market_base*(1+ecom_growth_rate)^H5/H6 -> 6875 | I10: =ecom_market_base*(1+ecom_growth_rate)^I5/I6 -> 7425 | J10: =ecom_market_base*(1+ecom_growth_rate)^J5/J6 -> 7425 | ... AR10: =ecom_market_base*(1+ecom_growth_rate)^AR5/AR6 -> 30304.892
A12: TĂNG TRƯỞNG DN (S-CURVE)
A13: DN thô (S-curve) | B13: DN | C13: =MAX(pilot_count,adoption_max/(1+EXP(-adoption_steepness*(C4-adoption_midpoint)))) -> 114.41936 | D13: =MAX(pilot_count,adoption_max/(1+EXP(-adoption_steepness*(D4-adoption_midpoint)))) -> 122.42168 | E13: =MAX(pilot_count,adoption_max/(1+EXP(-adoption_steepness*(E4-adoption_midpoint)))) -> 130.91619 | F13: =MAX(pilot_count,adoption_max/(1+EXP(-adoption_steepness*(F4-adoption_midpoint)))) -> 139.92356 | G13: =MAX(pilot_count,adoption_max/(1+EXP(-adoption_steepness*(G4-adoption_midpoint)))) -> 149.46403 | H13: =MAX(pilot_count,adoption_max/(1+EXP(-adoption_steepness*(H4-adoption_midpoint)))) -> 159.55709 | I13: =MAX(pilot_count,adoption_max/(1+EXP(-adoption_steepness*(I4-adoption_midpoint)))) -> 170.22128 | J13: =MAX(pilot_count,adoption_max/(1+EXP(-adoption_steepness*(J4-adoption_midpoint)))) -> 181.4739 | ... AR13: =MAX(pilot_count,adoption_max/(1+EXP(-adoption_steepness*(AR4-adoption_midpoint)))) -> 1110.0162
A14: DN rời bỏ | B14: DN | C14: =0 -> 0 | D14: =ROUND(D13*churn_rate/D6,0) -> 2 | E14: =ROUND(E13*churn_rate/E6,0) -> 2 | F14: =ROUND(F13*churn_rate/F6,0) -> 2 | G14: =ROUND(G13*churn_rate/G6,0) -> 2 | H14: =ROUND(H13*churn_rate/H6,0) -> 3 | I14: =ROUND(I13*churn_rate/I6,0) -> 3 | J14: =ROUND(J13*churn_rate/J6,0) -> 3 | K14: =ROUND(K13*churn_rate/K6,0) -> 3 | ... AR14: =ROUND(AR13*churn_rate/AR6,0) -> 56
A15: DN hoạt động ròng | B15: DN | C15: =C13-C14 -> 114.41936 | D15: =D13-D14 -> 120.42168 | E15: =E13-E14 -> 128.91619 | F15: =F13-F14 -> 137.92356 | G15: =G13-G14 -> 147.46403 | H15: =H13-H14 -> 156.55709 | I15: =I13-I14 -> 167.22128 | J15: =J13-J14 -> 178.4739 | ... AR15: =AR13-AR14 -> 1054.0162
A16: DN mới/kỳ | B16: DN | C16: =C15 -> 114.41936 | D16: =MAX(0,D15-C15) -> 6.0023251 | E16: =MAX(0,E15-D15) -> 8.4945024 | F16: =MAX(0,F15-E15) -> 9.0073776 | G16: =MAX(0,G15-F15) -> 9.5404668 | H16: =MAX(0,H15-G15) -> 9.0930584 | I16: =MAX(0,I15-H15) -> 10.66419 | J16: =MAX(0,J15-I15) -> 11.252625 | K16: =MAX(0,K15-J15) -> 11.856836 | ... AR16: =MAX(0,AR15-AQ15) -> 18.612393
A17: VCR (triệu bản ghi) | B17: Tr | C17: =C15*vcr_per_enterprise*C7/1000000 -> 1.1441936 | D17: =D15*vcr_per_enterprise*D7/1000000 -> 1.2042168 | E17: =E15*vcr_per_enterprise*E7/1000000 -> 1.2891619 | F17: =F15*vcr_per_enterprise*F7/1000000 -> 1.3792356 | G17: =G15*vcr_per_enterprise*G7/1000000 -> 1.4746403 | H17: =H15*vcr_per_enterprise*H7/1000000 -> 1.5655709 | I17: =I15*vcr_per_enterprise*I7/1000000 -> 1.6722128 | J17: =J15*vcr_per_enterprise*J7/1000000 -> 1.784739 | ... AR17: =AR15*vcr_per_enterprise*AR7/1000000 -> 31.620485

Sheet Doanh thu
A1: BẢNG DOANH THU (Tr VND)
A3: Hạng mục | B3: ĐVT | C3: Th7 2025 | D3: Th8 2025 | E3: Th9 2025 | F3: Th10 2025 | G3: Th11 2025 | H3: Th12 2025 | I3: Th1 2026 | J3: Th2 2026 | K3: Th3 2026 | L3: Th4 2026 | M3: Th5 2026 | N3: Th6 2026 | O3: Th7 2026 | P3: Th8 2026 | Q3: Th9 2026 | R3: Th10 2026 | S3: Th11 2026 | T3: Th12 2026 | U3: Th1 2027 | V3: Th2 2027 | W3: Th3 2027 | X3: Th4 2027 | Y3: Th5 2027 | Z3: Th6 2027 | AA3: Th7 2027 | AB3: Th8 2027 | AC3: Th9 2027 | AD3: Th10 2027 | AE3: Th11 2027 | AF3: Th12 2027 | AG3: Q1 2028 | AH3: Q2 2028 | AI3: Q3 2028 | AJ3: Q4 2028 | AK3: Q1 2029 | AL3: Q2 2029 | AM3: Q3 2029 | AN3: Q4 2029 | AO3: Q1 2030 | AP3: Q2 2030 | AQ3: Q3 2030 | AR3: Q4 2030
A4: GIAI ĐOẠN 1
A5: Phí chứng nhận | B5: Tr VND | C5: ='Quy mô thị trường'!C15*cert_fee_yr1*(1+cert_fee_escalation)^'Quy mô thị trường'!C5/'Quy mô thị trường'!C6 -> 238.37366 | D5: ='Quy mô thị trường'!D15*cert_fee_yr1*(1+cert_fee_escalation)^'Quy mô thị trường'!D5/'Quy mô thị trường'!D6 -> 250.87851 | E5: ='Quy mô thị trường'!E15*cert_fee_yr1*(1+cert_fee_escalation)^'Quy mô thị trường'!E5/'Quy mô thị trường'!E6 -> 268.57539 | F5: ='Quy mô thị trường'!F15*cert_fee_yr1*(1+cert_fee_escalation)^'Quy mô thị trường'!F5/'Quy mô thị trường'!F6 -> 287.34076 | G5: ='Quy mô thị trường'!G15*cert_fee_yr1*(1+cert_fee_escalation)^'Quy mô thị trường'!G5/'Quy mô thị trường'!G6 -> 307.21673 | H5: ='Quy mô thị trường'!H15*cert_fee_yr1*(1+cert_fee_escalation)^'Quy mô thị trường'!H5/'Quy mô thị trường'!H6 -> 326.1606 | I5: ='Quy mô thị trường'!I15*cert_fee_yr1*(1+cert_fee_escalation)^'Quy mô thị trường'!I5/'Quy mô thị trường'!I6 -> 365.79655 | J5: ='Quy mô thị trường'!J15*cert_fee_yr1*(1+cert_fee_escalation)^'Quy mô thị trường'!J5/'Quy mô thị trường'!J6 -> 390.41166 | ... AR5: ='Quy mô thị trường'!AR15*cert_fee_yr1*(1+cert_fee_escalation)^'Quy mô thị trường'!AR5/'Quy mô thị trường'!AR6 -> 8407.6339
A6: Đào tạo & tư vấn | B6: Tr VND | C6: ='Quy mô thị trường'!C15*training_pct*training_fee/'Quy mô thị trường'!C6 -> 42.907259 | D6: ='Quy mô thị trường'!D15*training_pct*training_fee/'Quy mô thị trường'!D6 -> 45.158131 | E6: ='Quy mô thị trường'!E15*training_pct*training_fee/'Quy mô thị trường'!E6 -> 48.34357 | F6: ='Quy mô thị trường'!F15*training_pct*training_fee/'Quy mô thị trường'!F6 -> 51.721336 | G6: ='Quy mô thị trường'!G15*training_pct*training_fee/'Quy mô thị trường'!G6 -> 55.299011 | H6: ='Quy mô thị trường'!H15*training_pct*training_fee/'Quy mô thị trường'!H6 -> 58.708908 | I6: ='Quy mô thị trường'!I15*training_pct*training_fee/'Quy mô thị trường'!I6 -> 62.707979 | J6: ='Quy mô thị trường'!J15*training_pct*training_fee/'Quy mô thị trường'!J6 -> 66.927714 | ... AR6: ='Quy mô thị trường'!AR15*training_pct*training_fee/'Quy mô thị trường'!AR6 -> 1185.7682
A7: Phí kiểm toán | B7: Tr VND | C7: ='Quy mô thị trường'!C15*audit_fee/'Quy mô thị trường'!C6 -> 95.349465 | D7: ='Quy mô thị trường'!D15*audit_fee/'Quy mô thị trường'!D6 -> 100.3514 | E7: ='Quy mô thị trường'!E15*audit_fee/'Quy mô thị trường'!E6 -> 107.43015 | F7: ='Quy mô thị trường'!F15*audit_fee/'Quy mô thị trường'!F6 -> 114.9363 | G7: ='Quy mô thị trường'!G15*audit_fee/'Quy mô thị trường'!G6 -> 122.88669 | H7: ='Quy mô thị trường'!H15*audit_fee/'Quy mô thị trường'!H6 -> 130.46424 | I7: ='Quy mô thị trường'!I15*audit_fee/'Quy mô thị trường'!I6 -> 139.35106 | J7: ='Quy mô thị trường'!J15*audit_fee/'Quy mô thị trường'!J6 -> 148.72825 | ... AR7: ='Quy mô thị trường'!AR15*audit_fee/'Quy mô thị trường'!AR6 -> 2635.0405
A8: Tổng GĐ1 | C8: =SUM(C5:C7) -> 376.63039 | D8: =SUM(D5:D7) -> 396.38804 | E8: =SUM(E5:E7) -> 424.34911 | F8: =SUM(F5:F7) -> 453.99839 | G8: =SUM(G5:G7) -> 485.40243 | H8: =SUM(H5:H7) -> 515.33375 | I8: =SUM(I5:I7) -> 567.85559 | J8: =SUM(J5:J7) -> 606.06763 | ... AR8: =SUM(AR5:AR7) -> 12228.443
A10: GIAI ĐOẠN 2 (có điều kiện)
A11: Phí giao dịch | B11: Tr VND | C11: =IF('Quy mô thị trường'!C15>=stage2_gate,'Quy mô thị trường'!C10*platform_market_share*tx_take_rate*1000,0) -> 0 | D11: =IF('Quy mô thị trường'!D15>=stage2_gate,'Quy mô thị trường'!D10*platform_market_share*tx_take_rate*1000,0) -> 0 | E11: =IF('Quy mô thị trường'!E15>=stage2_gate,'Quy mô thị trường'!E10*platform_market_share*tx_take_rate*1000,0) -> 0 | F11: =IF('Quy mô thị trường'!F15>=stage2_gate,'Quy mô thị trường'!F10*platform_market_share*tx_take_rate*1000,0) -> 0 | G11: =IF('Quy mô thị trường'!G15>=stage2_gate,'Quy mô thị trường'!G10*platform_market_share*tx_take_rate*1000,0) -> 0 | H11: =IF('Quy mô thị trường'!H15>=stage2_gate,'Quy mô thị trường'!H10*platform_market_share*tx_take_rate*1000,0) -> 0 | I11: =IF('Quy mô thị trường'!I15>=stage2_gate,'Quy mô thị trường'!I10*platform_market_share*tx_take_rate*1000,0) -> 0 | J11: =IF('Quy mô thị trường'!J15>=stage2_gate,'Quy mô thị trường'!J10*platform_market_share*tx_take_rate*1000,0) -> 0 | ... AR11: =IF('Quy mô thị trường'!AR15>=stage2_gate,'Quy mô thị trường'!AR10*platform_market_share*tx_take_rate*1000,0) -> 12121.957
A12: DaaS | B12: Tr VND | C12: =IF('Quy mô thị trường'!C15>=stage2_gate,'Quy mô thị trường'!C17*daas_price,0) -> 0 | D12: =IF('Quy mô thị trường'!D15>=stage2_gate,'Quy mô thị trường'!D17*daas_price,0) -> 0 | E12: =IF('Quy mô thị trường'!E15>=stage2_gate,'Quy mô thị trường'!E17*daas_price,0) -> 0 | F12: =IF('Quy mô thị trường'!F15>=stage2_gate,'Quy mô thị trường'!F17*daas_price,0) -> 0 | G12: =IF('Quy mô thị trường'!G15>=stage2_gate,'Quy mô thị trường'!G17*daas_price,0) -> 0 | H12: =IF('Quy mô thị trường'!H15>=stage2_gate,'Quy mô thị trường'!H17*daas_price,0) -> 0 | I12: =IF('Quy mô thị trường'!I15>=stage2_gate,'Quy mô thị trường'!I17*daas_price,0) -> 0 | J12: =IF('Quy mô thị trường'!J15>=stage2_gate,'Quy mô thị trường'!J17*daas_price,0) -> 0 | ... AR12: =IF('Quy mô thị trường'!AR15>=stage2_gate,'Quy mô thị trường'!AR17*daas_price,0) -> 948.61456
A13: Quảng cáo | B13: Tr VND | C13: =IF('Quy mô thị trường'!C15>=stage2_gate,ad_impressions_base*'Quy mô thị trường'!C7*'Quy mô thị trường'!C15/1000*ad_cpm/1000,0) -> 0 | D13: =IF('Quy mô thị trường'!D15>=stage2_gate,ad_impressions_base*'Quy mô thị trường'!D7*'Quy mô thị trường'!D15/1000*ad_cpm/1000,0) -> 0 | E13: =IF('Quy mô thị trường'!E15>=stage2_gate,ad_impressions_base*'Quy mô thị trường'!E7*'Quy mô thị trường'!E15/1000*ad_cpm/1000,0) -> 0 | F13: =IF('Quy mô thị trường'!F15>=stage2_gate,ad_impressions_base*'Quy mô thị trường'!F7*'Quy mô thị trường'!F15/1000*ad_cpm/1000,0) -> 0 | G13: =IF('Quy mô thị trường'!G15>=stage2_gate,ad_impressions_base*'Quy mô thị trường'!G7*'Quy mô thị trường'!G15/1000*ad_cpm/1000,0) -> 0 | H13: =IF('Quy mô thị trường'!H15>=stage2_gate,ad_impressions_base*'Quy mô thị trường'!H7*'Quy mô thị trường'!H15/1000*ad_cpm/1000,0) -> 0 | I13: =IF('Quy mô thị trường'!I15>=stage2_gate,ad_impressions_base*'Quy mô thị trường'!I7*'Quy mô thị trường'!I15/1000*ad_cpm/1000,0) -> 0 | J13: =IF('Quy mô thị trường'!J15>=stage2_gate,ad_impressions_base*'Quy mô thị trường'!J7*'Quy mô thị trường'!J15/1000*ad_cpm/1000,0) -> 0 | ... AR13: =IF('Quy mô thị trường'!AR15>=stage2_gate,ad_impressions_base*'Quy mô thị trường'!AR7*'Quy mô thị trường'!AR15/1000*ad_cpm/1000,0) -> 237.15364
A14: Tổng GĐ2 | C14: =SUM(C11:C13) -> 0 | D14: =SUM(D11:D13) -> 0 | E14: =SUM(E11:E13) -> 0 | F14: =SUM(F11:F13) -> 0 | G14: =SUM(G11:G13) -> 0 | H14: =SUM(H11:H13) -> 0 | I14: =SUM(I11:I13) -> 0 | J14: =SUM(J11:J13) -> 0 | ... AR14: =SUM(AR11:AR13) -> 13307.725
A16: TỔNG DOANH THU | C16: =C8+C14 -> 376.63039 | D16: =D8+D14 -> 396.38804 | E16: =E8+E14 -> 424.34911 | F16: =F8+F14 -> 453.99839 | G16: =G8+G14 -> 485.40243 | H16: =H8+H14 -> 515.33375 | I16: =I8+I14 -> 567.85559 | J16: =J8+J14 -> 606.06763 | ... AR16: =AR8+AR14 -> 25536.167
A18: GIÁ VỐN
A19: Phí thanh toán | B19: Tr VND | C19: =C11*payment_proc_pct -> 0 | D19: =D11*payment_proc_pct -> 0 | E19: =E11*payment_proc_pct -> 0 | F19: =F11*payment_proc_pct -> 0 | G19: =G11*payment_proc_pct -> 0 | H19: =H11*payment_proc_pct -> 0 | I19: =I11*payment_proc_pct -> 0 | J19: =J11*payment_proc_pct -> 0 | ... AR19: =AR11*payment_proc_pct -> 303.04892
A20: TỔNG GIÁ VỐN | C20: =C19 -> 0 | D20: =D19 -> 0 | E20: =E19 -> 0 | F20: =F19 -> 0 | G20: =G19 -> 0 | H20: =H19 -> 0 | I20: =I19 -> 0 | J20: =J19 -> 0 | ... AR20: =AR19 -> 303.04892

Sheet Chi phí
A1: BẢNG CHI PHÍ (Tr VND)
A3: Hạng mục | B3: ĐVT | C3: Th7 2025 | D3: Th8 2025 | E3: Th9 2025 | F3: Th10 2025 | G3: Th11 2025 | H3: Th12 2025 | I3: Th1 2026 | J3: Th2 2026 | K3: Th3 2026 | L3: Th4 2026 | M3: Th5 2026 | N3: Th6 2026 | O3: Th7 2026 | P3: Th8 2026 | Q3: Th9 2026 | R3: Th10 2026 | S3: Th11 2026 | T3: Th12 2026 | U3: Th1 2027 | V3: Th2 2027 | W3: Th3 2027 | X3: Th4 2027 | Y3: Th5 2027 | Z3: Th6 2027 | AA3: Th7 2027 | AB3: Th8 2027 | AC3: Th9 2027 | AD3: Th10 2027 | AE3: Th11 2027 | AF3: Th12 2027 | AG3: Q1 2028 | AH3: Q2 2028 | AI3: Q3 2028 | AJ3: Q4 2028 | AK3: Q1 2029 | AL3: Q2 2029 | AM3: Q3 2029 | AN3: Q4 2029 | AO3: Q1 2030 | AP3: Q2 2030 | AQ3: Q3 2030 | AR3: Q4 2030
A4: CAPEX
A5: Phát triển nền tảng | B5: Tr VND | C5: =capex_total/6 -> 880 | D5: =capex_total/6 -> 880 | E5: =capex_total/6 -> 880 | F5: =capex_total/6 -> 880 | G5: =capex_total/6 -> 880 | H5: =capex_total/6 -> 880 | I5: =0 -> 0 | J5: =0 -> 0 | K5: =0 -> 0 | L5: =0 -> 0 | M5: =0 -> 0 | N5: =0 -> 0 | O5: =0 -> 0 | P5: =0 -> 0 | ... AR5: =0 -> 0
A6: Bảo trì | B6: Tr VND | C6: =0 -> 0 | D6: =0 -> 0 | E6: =0 -> 0 | F6: =0 -> 0 | G6: =0 -> 0 | H6: =0 -> 0 | I6: =capex_total*capex_maintenance_pct/'Quy mô thị trường'!I6 -> 79.2 | J6: =capex_total*capex_maintenance_pct/'Quy mô thị trường'!J6 -> 79.2 | K6: =capex_total*capex_maintenance_pct/'Quy mô thị trường'!K6 -> 79.2 | L6: =capex_total*capex_maintenance_pct/'Quy mô thị trường'!L6 -> 79.2 | M6: =capex_total*capex_maintenance_pct/'Quy mô thị trường'!M6 -> 79.2 | N6: =capex_total*capex_maintenance_pct/'Quy mô thị trường'!N6 -> 79.2 | O6: =capex_total*capex_maintenance_pct/'Quy mô thị trường'!O6 -> 79.2 | P6: =capex_total*capex_maintenance_pct/'Quy mô thị trường'!P6 -> 79.2 | ... AR6: =capex_total*capex_maintenance_pct/'Quy mô thị trường'!AR6 -> 237.6
A7: TỔNG CAPEX | C7: =C5+C6 -> 880 | D7: =D5+D6 -> 880 | E7: =E5+E6 -> 880 | F7: =F5+F6 -> 880 | G7: =G5+G6 -> 880 | H7: =H5+H6 -> 880 | I7: =I5+I6 -> 79.2 | J7: =J5+J6 -> 79.2 | ... AR7: =AR5+AR6 -> 237.6
A9: OPEX
A10: Nhân sự (từ Nhân sự) | B10: Tr VND | C10: ='Nhân sự'!C21 -> 1820.25 | D10: ='Nhân sự'!D21 -> 668.25 | E10: ='Nhân sự'!E21 -> 668.25 | F10: ='Nhân sự'!F21 -> 668.25 | G10: ='Nhân sự'!G21 -> 668.25 | H10: ='Nhân sự'!H21 -> 668.25 | I10: ='Nhân sự'!I21 -> 1380.915 | J10: ='Nhân sự'!J21 -> 948.915 | ... AR10: ='Nhân sự'!AR21 -> 10683.962
A11: Marketing | B11: Tr VND | C11: =opex_marketing*(1+marketing_growth)^'Quy mô thị trường'!C5/'Quy mô thị trường'!C6 -> 583.33333 | D11: =opex_marketing*(1+marketing_growth)^'Quy mô thị trường'!D5/'Quy mô thị trường'!D6 -> 583.33333 | E11: =opex_marketing*(1+marketing_growth)^'Quy mô thị trường'!E5/'Quy mô thị trường'!E6 -> 583.33333 | F11: =opex_marketing*(1+marketing_growth)^'Quy mô thị trường'!F5/'Quy mô thị trường'!F6 -> 583.33333 | G11: =opex_marketing*(1+marketing_growth)^'Quy mô thị trường'!G5/'Quy mô thị trường'!G6 -> 583.33333 | H11: =opex_marketing*(1+marketing_growth)^'Quy mô thị trường'!H5/'Quy mô thị trường'!H6 -> 583.33333 | I11: =opex_marketing*(1+marketing_growth)^'Quy mô thị trường'!I5/'Quy mô thị trường'!I6 -> 670.83333 | J11: =opex_marketing*(1+marketing_growth)^'Quy mô thị trường'!J5/'Quy mô thị trường'!J6 -> 670.83333 | ... AR11: =opex_marketing*(1+marketing_growth)^'Quy mô thị trường'!AR5/'Quy mô thị trường'!AR6 -> 3519.8751
A12: Thương hiệu & sự kiện | B12: Tr VND | C12: =opex_branding/'Quy mô thị trường'!C6 -> 333.33333 | D12: =opex_branding/'Quy mô thị trường'!D6 -> 333.33333 | E12: =opex_branding/'Quy mô thị trường'!E6 -> 333.33333 | F12: =opex_branding/'Quy mô thị trường'!F6 -> 333.33333 | G12: =opex_branding/'Quy mô thị trường'!G6 -> 333.33333 | H12: =opex_branding/'Quy mô thị trường'!H6 -> 333.33333 | I12: =opex_branding/'Quy mô thị trường'!I6 -> 333.33333 | J12: =opex_branding/'Quy mô thị trường'!J6 -> 333.33333 | ... AR12: =opex_branding/'Quy mô thị trường'!AR6 -> 1000
A13: Cloud & hạ tầng | B13: Tr VND | C13: =opex_cloud_base/'Quy mô thị trường'!C6+'Quy mô thị trường'!C17*cloud_per_1M_vcr -> 279.98688 | D13: =opex_cloud_base/'Quy mô thị trường'!D6+'Quy mô thị trường'!D17*cloud_per_1M_vcr -> 280.46707 | E13: =opex_cloud_base/'Quy mô thị trường'!E6+'Quy mô thị trường'!E17*cloud_per_1M_vcr -> 281.14663 | F13: =opex_cloud_base/'Quy mô thị trường'!F6+'Quy mô thị trường'!F17*cloud_per_1M_vcr -> 281.86722 | G13: =opex_cloud_base/'Quy mô thị trường'!G6+'Quy mô thị trường'!G17*cloud_per_1M_vcr -> 282.63046 | H13: =opex_cloud_base/'Quy mô thị trường'!H6+'Quy mô thị trường'!H17*cloud_per_1M_vcr -> 283.3579 | I13: =opex_cloud_base/'Quy mô thị trường'!I6+'Quy mô thị trường'!I17*cloud_per_1M_vcr -> 284.21104 | J13: =opex_cloud_base/'Quy mô thị trường'!J6+'Quy mô thị trường'!J17*cloud_per_1M_vcr -> 285.11125 | ... AR13: =opex_cloud_base/'Quy mô thị trường'!AR6+'Quy mô thị trường'!AR17*cloud_per_1M_vcr -> 1065.4639
A14: Bảo mật | B14: Tr VND | C14: =opex_security/'Quy mô thị trường'!C6 -> 20.833333 | D14: =opex_security/'Quy mô thị trường'!D6 -> 20.833333 | E14: =opex_security/'Quy mô thị trường'!E6 -> 20.833333 | F14: =opex_security/'Quy mô thị trường'!F6 -> 20.833333 | G14: =opex_security/'Quy mô thị trường'!G6 -> 20.833333 | H14: =opex_security/'Quy mô thị trường'!H6 -> 20.833333 | I14: =opex_security/'Quy mô thị trường'!I6 -> 20.833333 | J14: =opex_security/'Quy mô thị trường'!J6 -> 20.833333 | ... AR14: =opex_security/'Quy mô thị trường'!AR6 -> 62.5
A15: Đối ngoại | B15: Tr VND | C15: =opex_external/'Quy mô thị trường'!C6 -> 33.333333 | D15: =opex_external/'Quy mô thị trường'!D6 -> 33.333333 | E15: =opex_external/'Quy mô thị trường'!E6 -> 33.333333 | F15: =opex_external/'Quy mô thị trường'!F6 -> 33.333333 | G15: =opex_external/'Quy mô thị trường'!G6 -> 33.333333 | H15: =opex_external/'Quy mô thị trường'!H6 -> 33.333333 | I15: =opex_external/'Quy mô thị trường'!I6 -> 33.333333 | J15: =opex_external/'Quy mô thị trường'!J6 -> 33.333333 | ... AR15: =opex_external/'Quy mô thị trường'!AR6 -> 100
A16: Pháp lý | B16: Tr VND | C16: =opex_legal/'Quy mô thị trường'!C6 -> 20 | D16: =opex_legal/'Quy mô thị trường'!D6 -> 20 | E16: =opex_legal/'Quy mô thị trường'!E6 -> 20 | F16: =opex_legal/'Quy mô thị trường'!F6 -> 20 | G16: =opex_legal/'Quy mô thị trường'!G6 -> 20 | H16: =opex_legal/'Quy mô thị trường'!H6 -> 20 | I16: =opex_legal/'Quy mô thị trường'!I6 -> 20 | J16: =opex_legal/'Quy mô thị trường'!J6 -> 20 | ... AR16: =opex_legal/'Quy mô thị trường'!AR6 -> 60
A17: Đánh giá thí điểm (Y1) | B17: Tr VND | C17: =opex_pilot_eval/'Quy mô thị trường'!C6 -> 16.666667 | D17: =opex_pilot_eval/'Quy mô thị trường'!D6 -> 16.666667 | E17: =opex_pilot_eval/'Quy mô thị trường'!E6 -> 16.666667 | F17: =opex_pilot_eval/'Quy mô thị trường'!F6 -> 16.666667 | G17: =opex_pilot_eval/'Quy mô thị trường'!G6 -> 16.666667 | H17: =opex_pilot_eval/'Quy mô thị trường'!H6 -> 16.666667 | I17: =0 -> 0 | J17: =0 -> 0 | K17: =0 -> 0 | L17: =0 -> 0 | M17: =0 -> 0 | N17: =0 -> 0 | O17: =0 -> 0 | P17: =0 -> 0 | ... AR17: =0 -> 0
A18: Quản lý đối tác | B18: Tr VND | C18: =opex_partner_mgmt/'Quy mô thị trường'!C6 -> 41.666667 | D18: =opex_partner_mgmt/'Quy mô thị trường'!D6 -> 41.666667 | E18: =opex_partner_mgmt/'Quy mô thị trường'!E6 -> 41.666667 | F18: =opex_partner_mgmt/'Quy mô thị trường'!F6 -> 41.666667 | G18: =opex_partner_mgmt/'Quy mô thị trường'!G6 -> 41.666667 | H18: =opex_partner_mgmt/'Quy mô thị trường'!H6 -> 41.666667 | I18: =opex_partner_mgmt/'Quy mô thị trường'!I6 -> 41.666667 | J18: =opex_partner_mgmt/'Quy mô thị trường'!J6 -> 41.666667 | ... AR18: =opex_partner_mgmt/'Quy mô thị trường'!AR6 -> 125
A19: Hỗ trợ khách hàng | B19: Tr VND | C19: ='Quy mô thị trường'!C15*opex_support_per_ent/'Quy mô thị trường'!C6 -> 19.069893 | D19: ='Quy mô thị trường'!D15*opex_support_per_ent/'Quy mô thị trường'!D6 -> 20.070281 | E19: ='Quy mô thị trường'!E15*opex_support_per_ent/'Quy mô thị trường'!E6 -> 21.486031 | F19: ='Quy mô thị trường'!F15*opex_support_per_ent/'Quy mô thị trường'!F6 -> 22.98726 | G19: ='Quy mô thị trường'!G15*opex_support_per_ent/'Quy mô thị trường'!G6 -> 24.577338 | H19: ='Quy mô thị trường'!H15*opex_support_per_ent/'Quy mô thị trường'!H6 -> 26.092848 | I19: ='Quy mô thị trường'!I15*opex_support_per_ent/'Quy mô thị trường'!I6 -> 27.870213 | J19: ='Quy mô thị trường'!J15*opex_support_per_ent/'Quy mô thị trường'!J6 -> 29.745651 | ... AR19: ='Quy mô thị trường'!AR15*opex_support_per_ent/'Quy mô thị trường'!AR6 -> 527.00809
A20: OPEX cộng dồn | C20: =SUM(C10:C19) -> 3168.4734 | D20: =SUM(D10:D19) -> 2017.954 | E20: =SUM(E10:E19) -> 2020.0493 | F20: =SUM(F10:F19) -> 2022.2711 | G20: =SUM(G10:G19) -> 2024.6245 | H20: =SUM(H10:H19) -> 2026.8674 | I20: =SUM(I10:I19) -> 2812.9962 | J20: =SUM(J10:J19) -> 2383.7719 | ... AR20: =SUM(AR10:AR19) -> 17143.809
A21: Dự phòng | B21: Tr VND | C21: =C20*opex_contingency_pct -> 316.84734 | D21: =D20*opex_contingency_pct -> 201.7954 | E21: =E20*opex_contingency_pct -> 202.00493 | F21: =F20*opex_contingency_pct -> 202.22711 | G21: =G20*opex_contingency_pct -> 202.46245 | H21: =H20*opex_contingency_pct -> 202.68674 | I21: =I20*opex_contingency_pct -> 281.29962 | J21: =J20*opex_contingency_pct -> 238.37719 | ... AR21: =AR20*opex_contingency_pct -> 1714.3809
A22: TỔNG OPEX | C22: =C20+C21 -> 3485.3208 | D22: =D20+D21 -> 2219.7494 | E22: =E20+E21 -> 2222.0543 | F22: =F20+F21 -> 2224.4983 | G22: =G20+G21 -> 2227.0869 | H22: =H20+H21 -> 2229.5542 | I22: =I20+I21 -> 3094.2959 | J22: =J20+J21 -> 2622.1491 | ... AR22: =AR20+AR21 -> 18858.19
A24: TỔNG CHI PHÍ | C24: =C7+C22 -> 4365.3208 | D24: =D7+D22 -> 3099.7494 | E24: =E7+E22 -> 3102.0543 | F24: =F7+F22 -> 3104.4983 | G24: =G7+G22 -> 3107.0869 | H24: =H7+H22 -> 3109.5542 | I24: =I7+I22 -> 3173.4959 | J24: =J7+J22 -> 2701.3491 | ... AR24: =AR7+AR22 -> 19095.79

Sheet Kết quả KD
A1: BÁO CÁO KẾT QUẢ KINH DOANH (Tr VND)
A3: Hạng mục | B3: ĐVT | C3: Th7 2025 | D3: Th8 2025 | E3: Th9 2025 | F3: Th10 2025 | G3: Th11 2025 | H3: Th12 2025 | I3: Th1 2026 | J3: Th2 2026 | K3: Th3 2026 | L3: Th4 2026 | M3: Th5 2026 | N3: Th6 2026 | O3: Th7 2026 | P3: Th8 2026 | Q3: Th9 2026 | R3: Th10 2026 | S3: Th11 2026 | T3: Th12 2026 | U3: Th1 2027 | V3: Th2 2027 | W3: Th3 2027 | X3: Th4 2027 | Y3: Th5 2027 | Z3: Th6 2027 | AA3: Th7 2027 | AB3: Th8 2027 | AC3: Th9 2027 | AD3: Th10 2027 | AE3: Th11 2027 | AF3: Th12 2027 | AG3: Q1 2028 | AH3: Q2 2028 | AI3: Q3 2028 | AJ3: Q4 2028 | AK3: Q1 2029 | AL3: Q2 2029 | AM3: Q3 2029 | AN3: Q4 2029 | AO3: Q1 2030 | AP3: Q2 2030 | AQ3: Q3 2030 | AR3: Q4 2030
A4: Doanh thu | C4: ='Doanh thu'!C16 -> 376.63039 | D4: ='Doanh thu'!D16 -> 396.38804 | E4: ='Doanh thu'!E16 -> 424.34911 | F4: ='Doanh thu'!F16 -> 453.99839 | G4: ='Doanh thu'!G16 -> 485.40243 | H4: ='Doanh thu'!H16 -> 515.33375 | I4: ='Doanh thu'!I16 -> 567.85559 | J4: ='Doanh thu'!J16 -> 606.06763 | ... AR4: ='Doanh thu'!AR16 -> 25536.167
A5: Giá vốn | C5: =-'Doanh thu'!C20 -> 0 | D5: =-'Doanh thu'!D20 -> 0 | E5: =-'Doanh thu'!E20 -> 0 | F5: =-'Doanh thu'!F20 -> 0 | G5: =-'Doanh thu'!G20 -> 0 | H5: =-'Doanh thu'!H20 -> 0 | I5: =-'Doanh thu'!I20 -> 0 | J5: =-'Doanh thu'!J20 -> 0 | ... AR5: =-'Doanh thu'!AR20 -> -303.04892
A6: LỢI NHUẬN GỘP | C6: =C4+C5 -> 376.63039 | D6: =D4+D5 -> 396.38804 | E6: =E4+E5 -> 424.34911 | F6: =F4+F5 -> 453.99839 | G6: =G4+G5 -> 485.40243 | H6: =H4+H5 -> 515.33375 | I6: =I4+I5 -> 567.85559 | J6: =J4+J5 -> 606.06763 | ... AR6: =AR4+AR5 -> 25233.118
A8: Chi phí hoạt động | C8: =-'Chi phí'!C22 -> -3485.3208 | D8: =-'Chi phí'!D22 -> -2219.7494 | E8: =-'Chi phí'!E22 -> -2222.0543 | F8: =-'Chi phí'!F22 -> -2224.4983 | G8: =-'Chi phí'!G22 -> -2227.0869 | H8: =-'Chi phí'!H22 -> -2229.5542 | I8: =-'Chi phí'!I22 -> -3094.2959 | J8: =-'Chi phí'!J22 -> -2622.1491 | ... AR8: =-'Chi phí'!AR22 -> -18858.19
A9: EBITDA | C9: =C6+C8 -> -3108.6904 | D9: =D6+D8 -> -1823.3614 | E9: =E6+E8 -> -1797.7051 | F9: =F6+F8 -> -1770.4999 | G9: =G6+G8 -> -1741.6845 | H9: =H6+H8 -> -1714.2204 | I9: =I6+I8 -> -2526.4403 | J9: =J6+J8 -> -2016.0815 | ... AR9: =AR6+AR8 -> 6374.9282
A10: Khấu hao | C10: =-capex_total/depreciation_years/'Quy mô thị trường'!C6 -> -88 | D10: =-capex_total/depreciation_years/'Quy mô thị trường'!D6 -> -88 | E10: =-capex_total/depreciation_years/'Quy mô thị trường'!E6 -> -88 | F10: =-capex_total/depreciation_years/'Quy mô thị trường'!F6 -> -88 | G10: =-capex_total/depreciation_years/'Quy mô thị trường'!G6 -> -88 | H10: =-capex_total/depreciation_years/'Quy mô thị trường'!H6 -> -88 | I10: =-capex_total/depreciation_years/'Quy mô thị trường'!I6 -> -88 | J10: =-capex_total/depreciation_years/'Quy mô thị trường'!J6 -> -88 | ... AN10: =-capex_total/depreciation_years/'Quy mô thị trường'!AN6 -> -264 | AO10: =0 -> 0 | AP10: =0 -> 0 | AQ10: =0 -> 0 | AR10: =0 -> 0
A11: EBIT | C11: =C9+C10 -> -3196.6904 | D11: =D9+D10 -> -1911.3614 | E11: =E9+E10 -> -1885.7051 | F11: =F9+F10 -> -1858.4999 | G11: =G9+G10 -> -1829.6845 | H11: =H9+H10 -> -1802.2204 | I11: =I9+I10 -> -2614.4403 | J11: =J9+J10 -> -2104.0815 | ... AR11: =AR9+AR10 -> 6374.9282
A12: Thuế TNDN (20%) | C12: =IF(C11>0,-C11*cit_rate,0) -> 0 | D12: =IF(D11>0,-D11*cit_rate,0) -> 0 | E12: =IF(E11>0,-E11*cit_rate,0) -> 0 | F12: =IF(F11>0,-F11*cit_rate,0) -> 0 | G12: =IF(G11>0,-G11*cit_rate,0) -> 0 | H12: =IF(H11>0,-H11*cit_rate,0) -> 0 | I12: =IF(I11>0,-I11*cit_rate,0) -> 0 | J12: =IF(J11>0,-J11*cit_rate,0) -> 0 | ... AR12: =IF(AR11>0,-AR11*cit_rate,0) -> -1274.9856
A13: LỢI NHUẬN SAU THUẾ | C13: =C11+C12 -> -3196.6904 | D13: =D11+D12 -> -1911.3614 | E13: =E11+E12 -> -1885.7051 | F13: =F11+F12 -> -1858.4999 | G13: =G11+G12 -> -1829.6845 | H13: =H11+H12 -> -1802.2204 | I13: =I11+I12 -> -2614.4403 | J13: =J11+J12 -> -2104.0815 | ... AR13: =AR11+AR12 -> 5099.9425
A15: BIÊN LỢI NHUẬN
A16: Biên gộp | C16: =IF(C4=0,0,C6/C4) -> 1 | D16: =IF(D4=0,0,D6/D4) -> 1 | E16: =IF(E4=0,0,E6/E4) -> 1 | F16: =IF(F4=0,0,F6/F4) -> 1 | G16: =IF(G4=0,0,G6/G4) -> 1 | H16: =IF(H4=0,0,H6/H4) -> 1 | I16: =IF(I4=0,0,I6/I4) -> 1 | J16: =IF(J4=0,0,J6/J4) -> 1 | ... AR16: =IF(AR4=0,0,AR6/AR4) -> 0.98813256
A17: Biên EBITDA | C17: =IF(C4=0,0,C9/C4) -> -8.2539554 | D17: =IF(D4=0,0,D9/D4) -> -4.5999404 | E17: =IF(E4=0,0,E9/E4) -> -4.2363825 | F17: =IF(F4=0,0,F9/F4) -> -3.8997932 | G17: =IF(G4=0,0,G9/G4) -> -3.5881247 | H17: =IF(H4=0,0,H9/H4) -> -3.3264276 | I17: =IF(I4=0,0,I9/I4) -> -4.4490894 | J17: =IF(J4=0,0,J9/J4) -> -3.3264959 | ... AR17: =IF(AR4=0,0,AR9/AR4) -> 0.24964311
A18: Biên ròng | C18: =IF(C4=0,0,C13/C4) -> -8.4876062 | D18: =IF(D4=0,0,D13/D4) -> -4.8219451 | E18: =IF(E4=0,0,E13/E4) -> -4.4437589 | F18: =IF(F4=0,0,F13/F4) -> -4.0936265 | G18: =IF(G4=0,0,G13/G4) -> -3.7694176 | H18: =IF(H4=0,0,H13/H4) -> -3.4971907 | I18: =IF(I4=0,0,I13/I4) -> -4.6040584 | J18: =IF(J4=0,0,J13/J4) -> -3.4716942 | ... AR18: =IF(AR4=0,0,AR13/AR4) -> 0.19971449

Sheet Dòng tiền
A1: BÁO CÁO DÒNG TIỀN (Tr VND)
A3: Hạng mục | B3: ĐVT | C3: Th7 2025 | D3: Th8 2025 | E3: Th9 2025 | F3: Th10 2025 | G3: Th11 2025 | H3: Th12 2025 | I3: Th1 2026 | J3: Th2 2026 | K3: Th3 2026 | L3: Th4 2026 | M3: Th5 2026 | N3: Th6 2026 | O3: Th7 2026 | P3: Th8 2026 | Q3: Th9 2026 | R3: Th10 2026 | S3: Th11 2026 | T3: Th12 2026 | U3: Th1 2027 | V3: Th2 2027 | W3: Th3 2027 | X3: Th4 2027 | Y3: Th5 2027 | Z3: Th6 2027 | AA3: Th7 2027 | AB3: Th8 2027 | AC3: Th9 2027 | AD3: Th10 2027 | AE3: Th11 2027 | AF3: Th12 2027 | AG3: Q1 2028 | AH3: Q2 2028 | AI3: Q3 2028 | AJ3: Q4 2028 | AK3: Q1 2029 | AL3: Q2 2029 | AM3: Q3 2029 | AN3: Q4 2029 | AO3: Q1 2030 | AP3: Q2 2030 | AQ3: Q3 2030 | AR3: Q4 2030
A4: Dòng tiền hoạt động
A5: Lợi nhuận ròng | C5: ='Kết quả KD'!C13 -> -3196.6904 | D5: ='Kết quả KD'!D13 -> -1911.3614 | E5: ='Kết quả KD'!E13 -> -1885.7051 | F5: ='Kết quả KD'!F13 -> -1858.4999 | G5: ='Kết quả KD'!G13 -> -1829.6845 | H5: ='Kết quả KD'!H13 -> -1802.2204 | I5: ='Kết quả KD'!I13 -> -2614.4403 | J5: ='Kết quả KD'!J13 -> -2104.0815 | ... AR5: ='Kết quả KD'!AR13 -> 5099.9425
A6: Cộng: Khấu hao | C6: =-'Kết quả KD'!C10 -> 88 | D6: =-'Kết quả KD'!D10 -> 88 | E6: =-'Kết quả KD'!E10 -> 88 | F6: =-'Kết quả KD'!F10 -> 88 | G6: =-'Kết quả KD'!G10 -> 88 | H6: =-'Kết quả KD'!H10 -> 88 | I6: =-'Kết quả KD'!I10 -> 88 | J6: =-'Kết quả KD'!J10 -> 88 | ... AR6: =-'Kết quả KD'!AR10 -> 0
A7: Thay đổi vốn lưu động | C7: =-'Kết quả KD'!C4*ar_days/365 -> -46.433883 | D7: =-('Kết quả KD'!D4-'Kết quả KD'!C4)*ar_days/365 -> -2.4358751 | E7: =-('Kết quả KD'!E4-'Kết quả KD'!D4)*ar_days/365 -> -3.4472553 | F7: =-('Kết quả KD'!F4-'Kết quả KD'!E4)*ar_days/365 -> -3.6553912 | G7: =-('Kết quả KD'!G4-'Kết quả KD'!F4)*ar_days/365 -> -3.8717305 | H7: =-('Kết quả KD'!H4-'Kết quả KD'!G4)*ar_days/365 -> -3.6901624 | I7: =-('Kết quả KD'!I4-'Kết quả KD'!H4)*ar_days/365 -> -6.4752954 | J7: =-('Kết quả KD'!J4-'Kết quả KD'!I4)*ar_days/365 -> -4.7110734 | K7: =-('Kết quả KD'!K4-'Kết quả KD'!J4)*ar_days/365 -> -4.9640351 | ... AR7: =-('Kết quả KD'!AR4-'Kết quả KD'!AQ4)*ar_days/365 -> -29.203823
A8: DÒNG TIỀN HOẠT ĐỘNG | C8: =C5+C6+C7 -> -3155.1243 | D8: =D5+D6+D7 -> -1825.7973 | E8: =E5+E6+E7 -> -1801.1524 | F8: =F5+F6+F7 -> -1774.1553 | G8: =G5+G6+G7 -> -1745.5562 | H8: =H5+H6+H7 -> -1717.9106 | I8: =I5+I6+I7 -> -2532.9156 | J8: =J5+J6+J7 -> -2020.7925 | ... AR8: =AR5+AR6+AR7 -> 5070.7387
A10: Dòng tiền đầu tư
A11: Đầu tư CAPEX | C11: =-'Chi phí'!C7 -> -880 | D11: =-'Chi phí'!D7 -> -880 | E11: =-'Chi phí'!E7 -> -880 | F11: =-'Chi phí'!F7 -> -880 | G11: =-'Chi phí'!G7 -> -880 | H11: =-'Chi phí'!H7 -> -880 | I11: =-'Chi phí'!I7 -> -79.2 | J11: =-'Chi phí'!J7 -> -79.2 | ... AR11: =-'Chi phí'!AR7 -> -237.6
A12: DÒNG TIỀN ĐẦU TƯ | C12: =C11 -> -880 | D12: =D11 -> -880 | E12: =E11 -> -880 | F12: =F11 -> -880 | G12: =G11 -> -880 | H12: =H11 -> -880 | I12: =I11 -> -79.2 | J12: =J11 -> -79.2 | ... AR12: =AR11 -> -237.6
A14: DÒNG TIỀN TỰ DO | C14: =C8+C12 -> -4035.1243 | D14: =D8+D12 -> -2705.7973 | E14: =E8+E12 -> -2681.1524 | F14: =F8+F12 -> -2654.1553 | G14: =G8+G12 -> -2625.5562 | H14: =H8+H12 -> -2597.9106 | I14: =I8+I12 -> -2612.1156 | J14: =J8+J12 -> -2099.9925 | ... AR14: =AR8+AR12 -> 4833.1387
A15: Dòng tiền lũy kế | C15: =C14 -> -4035.1243 | D15: =C15+D14 -> -6740.9215 | E15: =D15+E14 -> -9422.0739 | F15: =E15+F14 -> -12076.229 | G15: =F15+G14 -> -14701.785 | H15: =G15+H14 -> -17299.696 | I15: =H15+I14 -> -19911.812 | J15: =I15+J14 -> -22011.804 | K15: =J15+K14 -> -24075.003 | ... AR15: =AQ15+AR14 -> 28969.214

Sheet Thẩm định
A1: THẨM ĐỊNH DỰ ÁN & LỢI NHUẬN
A3: Dòng tiền tự do theo năm
A4: Năm | B4: FCF (Tr VND)
A5: H2_2025 | B5: =SUM('Dòng tiền'!C14:H14) -> -17299.696
A6: 2026 | B6: =SUM('Dòng tiền'!I14:T14) -> -18286.748
A7: 2027 | B7: =SUM('Dòng tiền'!U14:AF14) -> 13835.794
A8: 2028 | B8: =SUM('Dòng tiền'!AG14:AJ14) -> 15618.203
A9: 2029 | B9: =SUM('Dòng tiền'!AK14:AN14) -> 17859.746
A10: 2030 | B10: =SUM('Dòng tiền'!AO14:AR14) -> 17241.915
A12: Chỉ số chính
A13: NPV (Giá trị hiện tại ròng) | B13: =NPV(discount_rate,B6:B10)+B5 -> 6313.5008
A14: IRR (Tỷ suất hoàn vốn nội bộ) | B14: =IFERROR(IRR(B5:B10),"N/A") -> 0.22064428
A15: Đốt tiền tối đa | B15: =-MIN('Dòng tiền'!C15:'Dòng tiền'!AR15) -> 37345.888
A16: ROI (Lợi nhuận đầu tư) | B16: =IF(B15=0,0,('Dòng tiền'!AR15+B15)/B15) -> 1.7757002
A17: Thuế TNDN áp dụng | B17: =cit_rate -> 0.2
A18: Tỷ suất chiết khấu | B18: =discount_rate -> 0.15

Sheet Kịch bản
A1: PHÂN TÍCH KỊCH BẢN
A2: Sao chép giá trị từ cột kịch bản vào trang Assumptions để chạy.
A4: Tham số | B4: XẤU NHẤT | C4: THẬN TRỌNG | D4: CƠ SỞ | E4: LẠC QUAN | F4: TỐT NHẤT
A5: Trần DN (adoption_max) | B5: 200 | C5: 600 | D5: =adoption_max -> 1200 | E5: 2000 | F5: 3500
A6: Hệ số dốc S-curve | B6: 0.5 | C6: 0.7 | D6: =adoption_steepness -> 0.9 | E6: 1.2 | F6: 1.5
A7: Tỷ lệ rời bỏ | B7: 0.35 | C7: 0.25 | D7: =churn_rate -> 0.2 | E7: 0.15 | F7: 0.1
A8: Thị phần GMV | B8: 0.001 | C8: 0.003 | D8: =platform_market_share -> 0.02 | E8: 0.01 | F8: 0.02
A9: Phí chứng nhận (Tr) | B9: 15 | C9: 20 | D9: =cert_fee_yr1 -> 25 | E9: 30 | F9: 40
A10: Tăng phí/năm | B10: 0 | C10: 0.03 | D10: =cert_fee_escalation -> 0.05 | E10: 0.08 | F10: 0.12
A11: Phí giao dịch | B11: 0.01 | C11: 0.015 | D11: =tx_take_rate -> 0.02 | E11: 0.025 | F11: 0.03
A12: Marketing cơ sở (Tr) | B12: 8000 | C12: 7500 | D12: =opex_marketing -> 7000 | E12: 6000 | F12: 5000
A13: WACC | B13: 0.2 | C13: 0.18 | D13: =discount_rate -> 0.15 | E13: 0.12 | F13: 0.1
A14: Ngưỡng GĐ2 | B14: 500 | C14: 400 | D14: =stage2_gate -> 300 | E14: 200 | F14: 150
A17: 🔑 YẾU TỐ ẢNH HƯỞNG LỚN NHẤT ĐẾN NPV/IRR
A19: 3 yếu tố ảnh hưởng mạnh nhất đến kết quả mô hình:
A21: 1. TRẦN DOANH NGHIỆP (adoption_max) — YẾU TỐ SỐ 1
A22: Mọi nguồn doanh thu đều phụ thuộc số DN. Cert, đào tạo, kiểm toán — tỷ lệ thuận với DN.
A23: Giai đoạn 2 (phí giao dịch, DaaS, QC) cũng phụ thuộc vượt ngưỡng. Tăng gấp đôi DN ≈ tăng gấp đôi DT.
A24: → Xấu nhất: 200 = dự án không có sức hút. Tốt nhất: 3,500 = trở thành chuẩn ngành.
A26: 2. THỊ PHẦN GMV (platform_market_share) — YẾU TỐ SỐ 2
A27: % GMV TMĐT du lịch VN chạy qua nền tảng VV. Thị trường ~82.500 tỷ, tăng 8%/năm.
A28: Chênh 0.1% = hàng trăm tỷ VND chênh lệch GMV → hàng tỷ phí giao dịch.
A29: → Xấu nhất: 0.1% = ngách. Tốt nhất: 2% = nền tảng thống lĩnh.
A31: 3. TỶ LỆ RỜI BỎ (churn_rate) — YẾU TỐ SỐ 3
A32: % DN không gia hạn chứng nhận mỗi năm. Churn cao = phải liên tục thay thế DN đã mất.
... A61: Kết quả: Sẵn sàng IPO hoặc mục tiêu M&A. Mở rộng Đông Nam Á.

Sheet Ngân sách 2025
A1: NGÂN SÁCH 2025 (Tr VND)
A3: Hạng mục | B3: ĐVT | C3: Th7 | D3: Th8 | E3: Th9 | F3: Th10 | G3: Th11 | H3: Th12 | I3: TỔNG
A4: DOANH THU
A5: Phí chứng nhận | B5: Tr VND | C5: =MAX(pilot_count,adoption_max/(1+EXP(-adoption_steepness*(2025.542-adoption_midpoint))))*cert_fee_yr1*(1+cert_fee_escalation)^0/12 -> 246.65066 | D5: =MAX(pilot_count,adoption_max/(1+EXP(-adoption_steepness*(2025.625-adoption_midpoint))))*cert_fee_yr1*(1+cert_fee_escalation)^0/12 -> 263.76273 | E5: =MAX(pilot_count,adoption_max/(1+EXP(-adoption_steepness*(2025.708-adoption_midpoint))))*cert_fee_yr1*(1+cert_fee_escalation)^0/12 -> 281.91347 | F5: =MAX(pilot_count,adoption_max/(1+EXP(-adoption_steepness*(2025.792-adoption_midpoint))))*cert_fee_yr1*(1+cert_fee_escalation)^0/12 -> 301.38351 | G5: =MAX(pilot_count,adoption_max/(1+EXP(-adoption_steepness*(2025.875-adoption_midpoint))))*cert_fee_yr1*(1+cert_fee_escalation)^0/12 -> 321.75063 | H5: =MAX(pilot_count,adoption_max/(1+EXP(-adoption_steepness*(2025.958-adoption_midpoint))))*cert_fee_yr1*(1+cert_fee_escalation)^0/12 -> 343.27923 | I5: =SUM(C5:H5) -> 1758.7402
A6: Đào tạo | B6: Tr VND | C6: =MAX(pilot_count,adoption_max/(1+EXP(-adoption_steepness*(2025.542-adoption_midpoint))))*training_pct*training_fee/12 -> 44.397118 | D6: =MAX(pilot_count,adoption_max/(1+EXP(-adoption_steepness*(2025.625-adoption_midpoint))))*training_pct*training_fee/12 -> 47.477291 | E6: =MAX(pilot_count,adoption_max/(1+EXP(-adoption_steepness*(2025.708-adoption_midpoint))))*training_pct*training_fee/12 -> 50.744425 | F6: =MAX(pilot_count,adoption_max/(1+EXP(-adoption_steepness*(2025.792-adoption_midpoint))))*training_pct*training_fee/12 -> 54.249032 | G6: =MAX(pilot_count,adoption_max/(1+EXP(-adoption_steepness*(2025.875-adoption_midpoint))))*training_pct*training_fee/12 -> 57.915113 | H6: =MAX(pilot_count,adoption_max/(1+EXP(-adoption_steepness*(2025.958-adoption_midpoint))))*training_pct*training_fee/12 -> 61.790261 | I6: =SUM(C6:H6) -> 316.57324
A7: Kiểm toán | B7: Tr VND | C7: =MAX(pilot_count,adoption_max/(1+EXP(-adoption_steepness*(2025.542-adoption_midpoint))))*audit_fee/12 -> 98.660262 | D7: =MAX(pilot_count,adoption_max/(1+EXP(-adoption_steepness*(2025.625-adoption_midpoint))))*audit_fee/12 -> 105.50509 | E7: =MAX(pilot_count,adoption_max/(1+EXP(-adoption_steepness*(2025.708-adoption_midpoint))))*audit_fee/12 -> 112.76539 | F7: =MAX(pilot_count,adoption_max/(1+EXP(-adoption_steepness*(2025.792-adoption_midpoint))))*audit_fee/12 -> 120.5534 | G7: =MAX(pilot_count,adoption_max/(1+EXP(-adoption_steepness*(2025.875-adoption_midpoint))))*audit_fee/12 -> 128.70025 | H7: =MAX(pilot_count,adoption_max/(1+EXP(-adoption_steepness*(2025.958-adoption_midpoint))))*audit_fee/12 -> 137.31169 | I7: =SUM(C7:H7) -> 703.49609
A8: TỔNG DOANH THU | C8: =SUM(C5:C7) -> 389.70804 | D8: =SUM(D5:D7) -> 416.74511 | E8: =SUM(E5:E7) -> 445.42328 | F8: =SUM(F5:F7) -> 476.18595 | G8: =SUM(G5:G7) -> 508.36599 | H8: =SUM(H5:H7) -> 542.38118 | I8: =SUM(C8:H8) -> 2778.8095
A10: CAPEX
A11: Cloud | B11: Tr VND | C11: =capex_cloud_setup/6 -> 133.33333 | D11: =capex_cloud_setup/6 -> 133.33333 | E11: =capex_cloud_setup/6 -> 133.33333 | F11: =capex_cloud_setup/6 -> 133.33333 | G11: =capex_cloud_setup/6 -> 133.33333 | H11: =capex_cloud_setup/6 -> 133.33333 | I11: =SUM(C11:H11) -> 800
A12: Backend | B12: Tr VND | C12: =capex_backend/6 -> 200 | D12: =capex_backend/6 -> 200 | E12: =capex_backend/6 -> 200 | F12: =capex_backend/6 -> 200 | G12: =capex_backend/6 -> 200 | H12: =capex_backend/6 -> 200 | I12: =SUM(C12:H12) -> 1200
A13: Frontend | B13: Tr VND | C13: =capex_frontend/6 -> 150 | D13: =capex_frontend/6 -> 150 | E13: =capex_frontend/6 -> 150 | F13: =capex_frontend/6 -> 150 | G13: =capex_frontend/6 -> 150 | H13: =capex_frontend/6 -> 150 | I13: =SUM(C13:H13) -> 900
A14: Data | B14: Tr VND | C14: =capex_data_platform/6 -> 100 | D14: =capex_data_platform/6 -> 100 | E14: =capex_data_platform/6 -> 100 | F14: =capex_data_platform/6 -> 100 | G14: =capex_data_platform/6 -> 100 | H14: =capex_data_platform/6 -> 100 | I14: =SUM(C14:H14) -> 600
A15: Bảo mật | B15: Tr VND | C15: =capex_security_setup/6 -> 41.666667 | D15: =capex_security_setup/6 -> 41.666667 | E15: =capex_security_setup/6 -> 41.666667 | F15: =capex_security_setup/6 -> 41.666667 | G15: =capex_security_setup/6 -> 41.666667 | H15: =capex_security_setup/6 -> 41.666667 | I15: =SUM(C15:H15) -> 250
A16: UX/UI | B16: Tr VND | C16: =capex_ux_design/6 -> 58.333333 | D16: =capex_ux_design/6 -> 58.333333 | E16: =capex_ux_design/6 -> 58.333333 | F16: =capex_ux_design/6 -> 58.333333 | G16: =capex_ux_design/6 -> 58.333333 | H16: =capex_ux_design/6 -> 58.333333 | I16: =SUM(C16:H16) -> 350
A17: Tích hợp | B17: Tr VND | C17: =capex_integration/6 -> 66.666667 | D17: =capex_integration/6 -> 66.666667 | E17: =capex_integration/6 -> 66.666667 | F17: =capex_integration/6 -> 66.666667 | G17: =capex_integration/6 -> 66.666667 | H17: =capex_integration/6 -> 66.666667 | I17: =SUM(C17:H17) -> 400
A18: DevOps | B18: Tr VND | C18: =capex_devops/6 -> 46.666667 | D18: =capex_devops/6 -> 46.666667 | E18: =capex_devops/6 -> 46.666667 | F18: =capex_devops/6 -> 46.666667 | G18: =capex_devops/6 -> 46.666667 | H18: =capex_devops/6 -> 46.666667 | I18: =SUM(C18:H18) -> 280
A19: QA | B19: Tr VND | C19: =capex_testing/6 -> 33.333333 | D19: =capex_testing/6 -> 33.333333 | E19: =capex_testing/6 -> 33.333333 | F19: =capex_testing/6 -> 33.333333 | G19: =capex_testing/6 -> 33.333333 | H19: =capex_testing/6 -> 33.333333 | I19: =SUM(C19:H19) -> 200
A20: Dự phòng | B20: Tr VND | C20: =capex_contingency/6 -> 50 | D20: =capex_contingency/6 -> 50 | E20: =capex_contingency/6 -> 50 | F20: =capex_contingency/6 -> 50 | G20: =capex_contingency/6 -> 50 | H20: =capex_contingency/6 -> 50 | I20: =SUM(C20:H20) -> 300
A21: TỔNG CAPEX | C21: =SUM(C11:C20) -> 880 | D21: =SUM(D11:D20) -> 880 | E21: =SUM(E11:E20) -> 880 | F21: =SUM(F11:F20) -> 880 | G21: =SUM(G11:G20) -> 880 | H21: =SUM(H11:H20) -> 880 | I21: =SUM(C21:H21) -> 5280
A23: OPEX
A24: NS — QL(2) | B24: Tr VND | C24: =salary_mgmt*2*(1+salary_escalation)^0*(1+bhxh_rate) -> 109.35 | D24: =salary_mgmt*2*(1+salary_escalation)^0*(1+bhxh_rate) -> 109.35 | E24: =salary_mgmt*2*(1+salary_escalation)^0*(1+bhxh_rate) -> 109.35 | F24: =salary_mgmt*2*(1+salary_escalation)^0*(1+bhxh_rate) -> 109.35 | G24: =salary_mgmt*2*(1+salary_escalation)^0*(1+bhxh_rate) -> 109.35 | H24: =salary_mgmt*2*(1+salary_escalation)^0*(1+bhxh_rate) -> 109.35 | I24: =SUM(C24:H24) -> 656.1
A25: NS — PT(12) | B25: Tr VND | C25: =salary_dev*12*(1+salary_escalation)^0*(1+bhxh_rate) -> 510.3 | D25: =salary_dev*12*(1+salary_escalation)^0*(1+bhxh_rate) -> 510.3 | E25: =salary_dev*12*(1+salary_escalation)^0*(1+bhxh_rate) -> 510.3 | F25: =salary_dev*12*(1+salary_escalation)^0*(1+bhxh_rate) -> 510.3 | G25: =salary_dev*12*(1+salary_escalation)^0*(1+bhxh_rate) -> 510.3 | H25: =salary_dev*12*(1+salary_escalation)^0*(1+bhxh_rate) -> 510.3 | I25: =SUM(C25:H25) -> 3061.8
A26: NS — VHKD(2) | B26: Tr VND | C26: =salary_bizops*2*(1+salary_escalation)^0*(1+bhxh_rate) -> 48.6 | D26: =salary_bizops*2*(1+salary_escalation)^0*(1+bhxh_rate) -> 48.6 | E26: =salary_bizops*2*(1+salary_escalation)^0*(1+bhxh_rate) -> 48.6 | F26: =salary_bizops*2*(1+salary_escalation)^0*(1+bhxh_rate) -> 48.6 | G26: =salary_bizops*2*(1+salary_escalation)^0*(1+bhxh_rate) -> 48.6 | H26: =salary_bizops*2*(1+salary_escalation)^0*(1+bhxh_rate) -> 48.6 | I26: =SUM(C26:H26) -> 291.6
A27: Tuyển dụng | B27: Tr VND | C27: =16*30*12*recruit_cost_pct -> 1152 | D27: =0 -> 0 | E27: =0 -> 0 | F27: =0 -> 0 | G27: =0 -> 0 | H27: =0 -> 0 | I27: =SUM(C27:H27) -> 1152
A28: Marketing | B28: Tr VND | C28: =opex_marketing*(1+marketing_growth)^0/12 -> 583.33333 | D28: =opex_marketing*(1+marketing_growth)^0/12 -> 583.33333 | E28: =opex_marketing*(1+marketing_growth)^0/12 -> 583.33333 | F28: =opex_marketing*(1+marketing_growth)^0/12 -> 583.33333 | G28: =opex_marketing*(1+marketing_growth)^0/12 -> 583.33333 | H28: =opex_marketing*(1+marketing_growth)^0/12 -> 583.33333 | I28: =SUM(C28:H28) -> 3500
A29: Thương hiệu | B29: Tr VND | C29: =opex_branding/12 -> 333.33333 | D29: =opex_branding/12 -> 333.33333 | E29: =opex_branding/12 -> 333.33333 | F29: =opex_branding/12 -> 333.33333 | G29: =opex_branding/12 -> 333.33333 | H29: =opex_branding/12 -> 333.33333 | I29: =SUM(C29:H29) -> 2000
A30: Cloud | B30: Tr VND | C30: =opex_cloud_base/12 -> 270.83333 | D30: =opex_cloud_base/12 -> 270.83333 | E30: =opex_cloud_base/12 -> 270.83333 | F30: =opex_cloud_base/12 -> 270.83333 | G30: =opex_cloud_base/12 -> 270.83333 | H30: =opex_cloud_base/12 -> 270.83333 | I30: =SUM(C30:H30) -> 1625
A31: Bảo mật | B31: Tr VND | C31: =opex_security/12 -> 20.833333 | D31: =opex_security/12 -> 20.833333 | E31: =opex_security/12 -> 20.833333 | F31: =opex_security/12 -> 20.833333 | G31: =opex_security/12 -> 20.833333 | H31: =opex_security/12 -> 20.833333 | I31: =SUM(C31:H31) -> 125
A32: Đối ngoại | B32: Tr VND | C32: =opex_external/12 -> 33.333333 | D32: =opex_external/12 -> 33.333333 | E32: =opex_external/12 -> 33.333333 | F32: =opex_external/12 -> 33.333333 | G32: =opex_external/12 -> 33.333333 | H32: =opex_external/12 -> 33.333333 | I32: =SUM(C32:H32) -> 200
A33: Pháp lý | B33: Tr VND | C33: =opex_legal/12 -> 20 | D33: =opex_legal/12 -> 20 | E33: =opex_legal/12 -> 20 | F33: =opex_legal/12 -> 20 | G33: =opex_legal/12 -> 20 | H33: =opex_legal/12 -> 20 | I33: =SUM(C33:H33) -> 120
A34: Đối tác | B34: Tr VND | C34: =opex_partner_mgmt/12 -> 41.666667 | D34: =opex_partner_mgmt/12 -> 41.666667 | E34: =opex_partner_mgmt/12 -> 41.666667 | F34: =opex_partner_mgmt/12 -> 41.666667 | G34: =opex_partner_mgmt/12 -> 41.666667 | H34: =opex_partner_mgmt/12 -> 41.666667 | I34: =SUM(C34:H34) -> 250
A35: Thí điểm | B35: Tr VND | C35: =opex_pilot_eval/6 -> 33.333333 | D35: =opex_pilot_eval/6 -> 33.333333 | E35: =opex_pilot_eval/6 -> 33.333333 | F35: =opex_pilot_eval/6 -> 33.333333 | G35: =opex_pilot_eval/6 -> 33.333333 | H35: =opex_pilot_eval/6 -> 33.333333 | I35: =SUM(C35:H35) -> 200
A36: Hỗ trợ KH | B36: Tr VND | C36: =MAX(pilot_count,adoption_max/(1+EXP(-adoption_steepness*(2025.542-adoption_midpoint))))*opex_support_per_ent/12 -> 19.732052 | D36: =MAX(pilot_count,adoption_max/(1+EXP(-adoption_steepness*(2025.625-adoption_midpoint))))*opex_support_per_ent/12 -> 21.101018 | E36: =MAX(pilot_count,adoption_max/(1+EXP(-adoption_steepness*(2025.708-adoption_midpoint))))*opex_support_per_ent/12 -> 22.553078 | F36: =MAX(pilot_count,adoption_max/(1+EXP(-adoption_steepness*(2025.792-adoption_midpoint))))*opex_support_per_ent/12 -> 24.110681 | G36: =MAX(pilot_count,adoption_max/(1+EXP(-adoption_steepness*(2025.875-adoption_midpoint))))*opex_support_per_ent/12 -> 25.74005 | H36: =MAX(pilot_count,adoption_max/(1+EXP(-adoption_steepness*(2025.958-adoption_midpoint))))*opex_support_per_ent/12 -> 27.462338 | I36: =SUM(C36:H36) -> 140.69922
A37: OPEX cộng dồn | C37: =SUM(C24:C36) -> 3176.6487 | D37: =SUM(D24:D36) -> 2026.0177 | E37: =SUM(E24:E36) -> 2027.4697 | F37: =SUM(F24:F36) -> 2029.0273 | G37: =SUM(G24:G36) -> 2030.6567 | H37: =SUM(H24:H36) -> 2032.379 | I37: =SUM(C37:H37) -> 13322.199
A38: Dự phòng | B38: Tr VND | C38: =C37*opex_contingency_pct -> 317.66487 | D38: =D37*opex_contingency_pct -> 202.60177 | E38: =E37*opex_contingency_pct -> 202.74697 | F38: =F37*opex_contingency_pct -> 202.90273 | G38: =G37*opex_contingency_pct -> 203.06567 | H38: =H37*opex_contingency_pct -> 203.2379 | I38: =SUM(C38:H38) -> 1332.2199
A39: TỔNG OPEX | C39: =C37+C38 -> 3494.3136 | D39: =D37+D38 -> 2228.6195 | E39: =E37+E38 -> 2230.2167 | F39: =F37+F38 -> 2231.9301 | G39: =G37+G38 -> 2233.7224 | H39: =H37+H38 -> 2235.6169 | I39: =SUM(C39:H39) -> 14654.419
A41: TỔNG KẾT
A42: Doanh thu | C42: =C8 -> 389.70804 | D42: =D8 -> 416.74511 | E42: =E8 -> 445.42328 | F42: =F8 -> 476.18595 | G42: =G8 -> 508.36599 | H42: =H8 -> 542.38118 | I42: =SUM(C42:H42) -> 2778.8095
A43: CAPEX | C43: =C21 -> 880 | D43: =D21 -> 880 | E43: =E21 -> 880 | F43: =F21 -> 880 | G43: =G21 -> 880 | H43: =H21 -> 880 | I43: =SUM(C43:H43) -> 5280
A44: OPEX | C44: =C39 -> 3494.3136 | D44: =D39 -> 2228.6195 | E44: =E39 -> 2230.2167 | F44: =F39 -> 2231.9301 | G44: =G39 -> 2233.7224 | H44: =H39 -> 2235.6169 | I44: =SUM(C44:H44) -> 14654.419
A45: TỔNG NGÂN SÁCH | C45: =C43+C44 -> 4374.3136 | D45: =D43+D44 -> 3108.6195 | E45: =E43+E44 -> 3110.2167 | F45: =F43+F44 -> 3111.9301 | G45: =G43+G44 -> 3113.7224 | H45: =H43+H44 -> 3115.6169 | I45: =SUM(C45:H45) -> 19934.419
A46: RÒNG (DT - Ngân sách) | C46: =C42-C45 -> -3984.6056 | D46: =D42-D45 -> -2691.8743 | E46: =E42-E45 -> -2664.7934 | F46: =F42-F45 -> -2635.7441 | G46: =G42-G45 -> -2605.3564 | H46: =H42-H45 -> -2573.2357 | I46: =SUM(C46:H46) -> -17155.61
A47: Lũy kế | C47: =C46 -> -3984.6056 | D47: =C47+D46 -> -6676.4799 | E47: =D47+E46 -> -9341.2733 | F47: =E47+F46 -> -11977.017 | G47: =F47+G46 -> -14582.374 | H47: =G47+H46 -> -17155.61 | I47: =H47 -> -17155.61

Sheet Ngân sách 2026
A1: NGÂN SÁCH 2026 (Tr VND)
A3: Hạng mục | B3: ĐVT | C3: Th1 | D3: Th2 | E3: Th3 | F3: Th4 | G3: Th5 | H3: Th6 | I3: Th7 | J3: Th8 | K3: Th9 | L3: Th10 | M3: Th11 | N3: Th12 | O3: TỔNG
A4: DOANH THU
A5: Phí chứng nhận | B5: Tr VND | C5: =MAX(pilot_count,adoption_max/(1+EXP(-adoption_steepness*(2026.042-adoption_midpoint))))*cert_fee_yr1*(1+cert_fee_escalation)^1/12 -> 384.60193 | D5: =MAX(pilot_count,adoption_max/(1+EXP(-adoption_steepness*(2026.125-adoption_midpoint))))*cert_fee_yr1*(1+cert_fee_escalation)^1/12 -> 409.77536 | E5: =MAX(pilot_count,adoption_max/(1+EXP(-adoption_steepness*(2026.208-adoption_midpoint))))*cert_fee_yr1*(1+cert_fee_escalation)^1/12 -> 436.27561 | F5: =MAX(pilot_count,adoption_max/(1+EXP(-adoption_steepness*(2026.292-adoption_midpoint))))*cert_fee_yr1*(1+cert_fee_escalation)^1/12 -> 464.47454 | G5: =MAX(pilot_count,adoption_max/(1+EXP(-adoption_steepness*(2026.375-adoption_midpoint))))*cert_fee_yr1*(1+cert_fee_escalation)^1/12 -> 493.72379 | H5: =MAX(pilot_count,adoption_max/(1+EXP(-adoption_steepness*(2026.458-adoption_midpoint))))*cert_fee_yr1*(1+cert_fee_escalation)^1/12 -> 524.36792 | I5: =MAX(pilot_count,adoption_max/(1+EXP(-adoption_steepness*(2026.542-adoption_midpoint))))*cert_fee_yr1*(1+cert_fee_escalation)^1/12 -> 556.81221 | J5: =MAX(pilot_count,adoption_max/(1+EXP(-adoption_steepness*(2026.625-adoption_midpoint))))*cert_fee_yr1*(1+cert_fee_escalation)^1/12 -> 590.28755 | K5: =MAX(pilot_count,adoption_max/(1+EXP(-adoption_steepness*(2026.708-adoption_midpoint))))*cert_fee_yr1*(1+cert_fee_escalation)^1/12 -> 625.16707 | L5: =MAX(pilot_count,adoption_max/(1+EXP(-adoption_steepness*(2026.792-adoption_midpoint))))*cert_fee_yr1*(1+cert_fee_escalation)^1/12 -> 661.883 | M5: =MAX(pilot_count,adoption_max/(1+EXP(-adoption_steepness*(2026.875-adoption_midpoint))))*cert_fee_yr1*(1+cert_fee_escalation)^1/12 -> 699.53856 | N5: =MAX(pilot_count,adoption_max/(1+EXP(-adoption_steepness*(2026.958-adoption_midpoint))))*cert_fee_yr1*(1+cert_fee_escalation)^1/12 -> 738.53048 | O5: =SUM(C5:N5) -> 6585.438
A6: Đào tạo | B6: Tr VND | C6: =MAX(pilot_count,adoption_max/(1+EXP(-adoption_steepness*(2026.042-adoption_midpoint))))*training_pct*training_fee/12 -> 65.931759 | D6: =MAX(pilot_count,adoption_max/(1+EXP(-adoption_steepness*(2026.125-adoption_midpoint))))*training_pct*training_fee/12 -> 70.247204 | E6: =MAX(pilot_count,adoption_max/(1+EXP(-adoption_steepness*(2026.208-adoption_midpoint))))*training_pct*training_fee/12 -> 74.790105 | F6: =MAX(pilot_count,adoption_max/(1+EXP(-adoption_steepness*(2026.292-adoption_midpoint))))*training_pct*training_fee/12 -> 79.624206 | G6: =MAX(pilot_count,adoption_max/(1+EXP(-adoption_steepness*(2026.375-adoption_midpoint))))*training_pct*training_fee/12 -> 84.638365 | H6: =MAX(pilot_count,adoption_max/(1+EXP(-adoption_steepness*(2026.458-adoption_midpoint))))*training_pct*training_fee/12 -> 89.891643 | I6: =MAX(pilot_count,adoption_max/(1+EXP(-adoption_steepness*(2026.542-adoption_midpoint))))*training_pct*training_fee/12 -> 95.453522 | J6: =MAX(pilot_count,adoption_max/(1+EXP(-adoption_steepness*(2026.625-adoption_midpoint))))*training_pct*training_fee/12 -> 101.19215 | K6: =MAX(pilot_count,adoption_max/(1+EXP(-adoption_steepness*(2026.708-adoption_midpoint))))*training_pct*training_fee/12 -> 107.1715 | L6: =MAX(pilot_count,adoption_max/(1+EXP(-adoption_steepness*(2026.792-adoption_midpoint))))*training_pct*training_fee/12 -> 113.46566 | M6: =MAX(pilot_count,adoption_max/(1+EXP(-adoption_steepness*(2026.875-adoption_midpoint))))*training_pct*training_fee/12 -> 119.9209 | N6: =MAX(pilot_count,adoption_max/(1+EXP(-adoption_steepness*(2026.958-adoption_midpoint))))*training_pct*training_fee/12 -> 126.60523 | O6: =SUM(C6:N6) -> 1128.9322
A7: Kiểm toán | B7: Tr VND | C7: =MAX(pilot_count,adoption_max/(1+EXP(-adoption_steepness*(2026.042-adoption_midpoint))))*audit_fee/12 -> 146.51502 | D7: =MAX(pilot_count,adoption_max/(1+EXP(-adoption_steepness*(2026.125-adoption_midpoint))))*audit_fee/12 -> 156.1049 | E7: =MAX(pilot_count,adoption_max/(1+EXP(-adoption_steepness*(2026.208-adoption_midpoint))))*audit_fee/12 -> 166.20023 | F7: =MAX(pilot_count,adoption_max/(1+EXP(-adoption_steepness*(2026.292-adoption_midpoint))))*audit_fee/12 -> 176.94268 | G7: =MAX(pilot_count,adoption_max/(1+EXP(-adoption_steepness*(2026.375-adoption_midpoint))))*audit_fee/12 -> 188.08525 | H7: =MAX(pilot_count,adoption_max/(1+EXP(-adoption_steepness*(2026.458-adoption_midpoint))))*audit_fee/12 -> 199.75921 | I7: =MAX(pilot_count,adoption_max/(1+EXP(-adoption_steepness*(2026.542-adoption_midpoint))))*audit_fee/12 -> 212.11894 | J7: =MAX(pilot_count,adoption_max/(1+EXP(-adoption_steepness*(2026.625-adoption_midpoint))))*audit_fee/12 -> 224.87145 | K7: =MAX(pilot_count,adoption_max/(1+EXP(-adoption_steepness*(2026.708-adoption_midpoint))))*audit_fee/12 -> 238.15888 | L7: =MAX(pilot_count,adoption_max/(1+EXP(-adoption_steepness*(2026.792-adoption_midpoint))))*audit_fee/12 -> 252.1459 | M7: =MAX(pilot_count,adoption_max/(1+EXP(-adoption_steepness*(2026.875-adoption_midpoint))))*audit_fee/12 -> 266.49088 | N7: =MAX(pilot_count,adoption_max/(1+EXP(-adoption_steepness*(2026.958-adoption_midpoint))))*audit_fee/12 -> 281.34495 | O7: =SUM(C7:N7) -> 2508.7383
A8: TỔNG DOANH THU | C8: =SUM(C5:C7) -> 597.0487 | D8: =SUM(D5:D7) -> 636.12746 | E8: =SUM(E5:E7) -> 677.26595 | F8: =SUM(F5:F7) -> 721.04143 | G8: =SUM(G5:G7) -> 766.44741 | H8: =SUM(H5:H7) -> 814.01877 | I8: =SUM(I5:I7) -> 864.38467 | J8: =SUM(J5:J7) -> 916.35115 | ... N8: =SUM(N5:N7) -> 1146.4807 | O8: =SUM(C8:N8) -> 10223.109
A10: CAPEX
A11: Bảo trì | B11: Tr VND | C11: =capex_total*capex_maintenance_pct/12 -> 79.2 | D11: =capex_total*capex_maintenance_pct/12 -> 79.2 | E11: =capex_total*capex_maintenance_pct/12 -> 79.2 | F11: =capex_total*capex_maintenance_pct/12 -> 79.2 | G11: =capex_total*capex_maintenance_pct/12 -> 79.2 | H11: =capex_total*capex_maintenance_pct/12 -> 79.2 | I11: =capex_total*capex_maintenance_pct/12 -> 79.2 | J11: =capex_total*capex_maintenance_pct/12 -> 79.2 | ... N11: =capex_total*capex_maintenance_pct/12 -> 79.2 | O11: =SUM(C11:N11) -> 950.4
A12: TỔNG CAPEX | C12: =SUM(C11:C11) -> 79.2 | D12: =SUM(D11:D11) -> 79.2 | E12: =SUM(E11:E11) -> 79.2 | F12: =SUM(F11:F11) -> 79.2 | G12: =SUM(G11:G11) -> 79.2 | H12: =SUM(H11:H11) -> 79.2 | I12: =SUM(I11:I11) -> 79.2 | J12: =SUM(J11:J11) -> 79.2 | ... N12: =SUM(N11:N11) -> 79.2 | O12: =SUM(C12:N12) -> 950.4
A14: OPEX
A15: NS — QL(2) | B15: Tr VND | C15: =salary_mgmt*2*(1+salary_escalation)^1*(1+bhxh_rate) -> 120.285 | D15: =salary_mgmt*2*(1+salary_escalation)^1*(1+bhxh_rate) -> 120.285 | E15: =salary_mgmt*2*(1+salary_escalation)^1*(1+bhxh_rate) -> 120.285 | F15: =salary_mgmt*2*(1+salary_escalation)^1*(1+bhxh_rate) -> 120.285 | G15: =salary_mgmt*2*(1+salary_escalation)^1*(1+bhxh_rate) -> 120.285 | H15: =salary_mgmt*2*(1+salary_escalation)^1*(1+bhxh_rate) -> 120.285 | I15: =salary_mgmt*2*(1+salary_escalation)^1*(1+bhxh_rate) -> 120.285 | J15: =salary_mgmt*2*(1+salary_escalation)^1*(1+bhxh_rate) -> 120.285 | ... N15: =salary_mgmt*2*(1+salary_escalation)^1*(1+bhxh_rate) -> 120.285 | O15: =SUM(C15:N15) -> 1443.42
A16: NS — PT(12) | B16: Tr VND | C16: =salary_dev*12*(1+salary_escalation)^1*(1+bhxh_rate) -> 561.33 | D16: =salary_dev*12*(1+salary_escalation)^1*(1+bhxh_rate) -> 561.33 | E16: =salary_dev*12*(1+salary_escalation)^1*(1+bhxh_rate) -> 561.33 | F16: =salary_dev*12*(1+salary_escalation)^1*(1+bhxh_rate) -> 561.33 | G16: =salary_dev*12*(1+salary_escalation)^1*(1+bhxh_rate) -> 561.33 | H16: =salary_dev*12*(1+salary_escalation)^1*(1+bhxh_rate) -> 561.33 | I16: =salary_dev*12*(1+salary_escalation)^1*(1+bhxh_rate) -> 561.33 | J16: =salary_dev*12*(1+salary_escalation)^1*(1+bhxh_rate) -> 561.33 | ... N16: =salary_dev*12*(1+salary_escalation)^1*(1+bhxh_rate) -> 561.33 | O16: =SUM(C16:N16) -> 6735.96
A17: NS — VHKD(6) | B17: Tr VND | C17: =salary_bizops*6*(1+salary_escalation)^1*(1+bhxh_rate) -> 160.38 | D17: =salary_bizops*6*(1+salary_escalation)^1*(1+bhxh_rate) -> 160.38 | E17: =salary_bizops*6*(1+salary_escalation)^1*(1+bhxh_rate) -> 160.38 | F17: =salary_bizops*6*(1+salary_escalation)^1*(1+bhxh_rate) -> 160.38 | G17: =salary_bizops*6*(1+salary_escalation)^1*(1+bhxh_rate) -> 160.38 | H17: =salary_bizops*6*(1+salary_escalation)^1*(1+bhxh_rate) -> 160.38 | I17: =salary_bizops*6*(1+salary_escalation)^1*(1+bhxh_rate) -> 160.38 | J17: =salary_bizops*6*(1+salary_escalation)^1*(1+bhxh_rate) -> 160.38 | ... N17: =salary_bizops*6*(1+salary_escalation)^1*(1+bhxh_rate) -> 160.38 | O17: =SUM(C17:N17) -> 1924.56
A18: NS — DL(2) | B18: Tr VND | C18: =salary_data*2*(1+salary_escalation)^1*(1+bhxh_rate) -> 106.92 | D18: =salary_data*2*(1+salary_escalation)^1*(1+bhxh_rate) -> 106.92 | E18: =salary_data*2*(1+salary_escalation)^1*(1+bhxh_rate) -> 106.92 | F18: =salary_data*2*(1+salary_escalation)^1*(1+bhxh_rate) -> 106.92 | G18: =salary_data*2*(1+salary_escalation)^1*(1+bhxh_rate) -> 106.92 | H18: =salary_data*2*(1+salary_escalation)^1*(1+bhxh_rate) -> 106.92 | I18: =salary_data*2*(1+salary_escalation)^1*(1+bhxh_rate) -> 106.92 | J18: =salary_data*2*(1+salary_escalation)^1*(1+bhxh_rate) -> 106.92 | ... N18: =salary_data*2*(1+salary_escalation)^1*(1+bhxh_rate) -> 106.92 | O18: =SUM(C18:N18) -> 1283.04
A19: Tuyển dụng | B19: Tr VND | C19: =6*30*12*recruit_cost_pct -> 432 | D19: =0 -> 0 | E19: =0 -> 0 | F19: =0 -> 0 | G19: =0 -> 0 | H19: =0 -> 0 | I19: =0 -> 0 | J19: =0 -> 0 | K19: =0 -> 0 | ... N19: =0 -> 0 | O19: =SUM(C19:N19) -> 432
A20: Marketing | B20: Tr VND | C20: =opex_marketing*(1+marketing_growth)^1/12 -> 670.83333 | D20: =opex_marketing*(1+marketing_growth)^1/12 -> 670.83333 | E20: =opex_marketing*(1+marketing_growth)^1/12 -> 670.83333 | F20: =opex_marketing*(1+marketing_growth)^1/12 -> 670.83333 | G20: =opex_marketing*(1+marketing_growth)^1/12 -> 670.83333 | H20: =opex_marketing*(1+marketing_growth)^1/12 -> 670.83333 | I20: =opex_marketing*(1+marketing_growth)^1/12 -> 670.83333 | J20: =opex_marketing*(1+marketing_growth)^1/12 -> 670.83333 | ... N20: =opex_marketing*(1+marketing_growth)^1/12 -> 670.83333 | O20: =SUM(C20:N20) -> 8050
A21: Thương hiệu | B21: Tr VND | C21: =opex_branding/12 -> 333.33333 | D21: =opex_branding/12 -> 333.33333 | E21: =opex_branding/12 -> 333.33333 | F21: =opex_branding/12 -> 333.33333 | G21: =opex_branding/12 -> 333.33333 | H21: =opex_branding/12 -> 333.33333 | I21: =opex_branding/12 -> 333.33333 | J21: =opex_branding/12 -> 333.33333 | ... N21: =opex_branding/12 -> 333.33333 | O21: =SUM(C21:N21) -> 4000
A22: Cloud | B22: Tr VND | C22: =opex_cloud_base/12 -> 270.83333 | D22: =opex_cloud_base/12 -> 270.83333 | E22: =opex_cloud_base/12 -> 270.83333 | F22: =opex_cloud_base/12 -> 270.83333 | G22: =opex_cloud_base/12 -> 270.83333 | H22: =opex_cloud_base/12 -> 270.83333 | I22: =opex_cloud_base/12 -> 270.83333 | J22: =opex_cloud_base/12 -> 270.83333 | ... N22: =opex_cloud_base/12 -> 270.83333 | O22: =SUM(C22:N22) -> 3250
A23: Bảo mật | B23: Tr VND | C23: =opex_security/12 -> 20.833333 | D23: =opex_security/12 -> 20.833333 | E23: =opex_security/12 -> 20.833333 | F23: =opex_security/12 -> 20.833333 | G23: =opex_security/12 -> 20.833333 | H23: =opex_security/12 -> 20.833333 | I23: =opex_security/12 -> 20.833333 | J23: =opex_security/12 -> 20.833333 | ... N23: =opex_security/12 -> 20.833333 | O23: =SUM(C23:N23) -> 250
A24: Đối ngoại | B24: Tr VND | C24: =opex_external/12 -> 33.333333 | D24: =opex_external/12 -> 33.333333 | E24: =opex_external/12 -> 33.333333 | F24: =opex_external/12 -> 33.333333 | G24: =opex_external/12 -> 33.333333 | H24: =opex_external/12 -> 33.333333 | I24: =opex_external/12 -> 33.333333 | J24: =opex_external/12 -> 33.333333 | ... N24: =opex_external/12 -> 33.333333 | O24: =SUM(C24:N24) -> 400
A25: Pháp lý | B25: Tr VND | C25: =opex_legal/12 -> 20 | D25: =opex_legal/12 -> 20 | E25: =opex_legal/12 -> 20 | F25: =opex_legal/12 -> 20 | G25: =opex_legal/12 -> 20 | H25: =opex_legal/12 -> 20 | I25: =opex_legal/12 -> 20 | J25: =opex_legal/12 -> 20 | ... N25: =opex_legal/12 -> 20 | O25: =SUM(C25:N25) -> 240
A26: Đối tác | B26: Tr VND | C26: =opex_partner_mgmt/12 -> 41.666667 | D26: =opex_partner_mgmt/12 -> 41.666667 | E26: =opex_partner_mgmt/12 -> 41.666667 | F26: =opex_partner_mgmt/12 -> 41.666667 | G26: =opex_partner_mgmt/12 -> 41.666667 | H26: =opex_partner_mgmt/12 -> 41.666667 | I26: =opex_partner_mgmt/12 -> 41.666667 | J26: =opex_partner_mgmt/12 -> 41.666667 | ... N26: =opex_partner_mgmt/12 -> 41.666667 | O26: =SUM(C26:N26) -> 500
A27: Hỗ trợ KH | B27: Tr VND | C27: =MAX(pilot_count,adoption_max/(1+EXP(-adoption_steepness*(2026.042-adoption_midpoint))))*opex_support_per_ent/12 -> 29.303004 | D27: =MAX(pilot_count,adoption_max/(1+EXP(-adoption_steepness*(2026.125-adoption_midpoint))))*opex_support_per_ent/12 -> 31.220979 | E27: =MAX(pilot_count,adoption_max/(1+EXP(-adoption_steepness*(2026.208-adoption_midpoint))))*opex_support_per_ent/12 -> 33.240047 | F27: =MAX(pilot_count,adoption_max/(1+EXP(-adoption_steepness*(2026.292-adoption_midpoint))))*opex_support_per_ent/12 -> 35.388536 | G27: =MAX(pilot_count,adoption_max/(1+EXP(-adoption_steepness*(2026.375-adoption_midpoint))))*opex_support_per_ent/12 -> 37.617051 | H27: =MAX(pilot_count,adoption_max/(1+EXP(-adoption_steepness*(2026.458-adoption_midpoint))))*opex_support_per_ent/12 -> 39.951841 | I27: =MAX(pilot_count,adoption_max/(1+EXP(-adoption_steepness*(2026.542-adoption_midpoint))))*opex_support_per_ent/12 -> 42.423787 | J27: =MAX(pilot_count,adoption_max/(1+EXP(-adoption_steepness*(2026.625-adoption_midpoint))))*opex_support_per_ent/12 -> 44.974289 | K27: =MAX(pilot_count,adoption_max/(1+EXP(-adoption_steepness*(2026.708-adoption_midpoint))))*opex_support_per_ent/12 -> 47.631777 | L27: =MAX(pilot_count,adoption_max/(1+EXP(-adoption_steepness*(2026.792-adoption_midpoint))))*opex_support_per_ent/12 -> 50.429181 | M27: =MAX(pilot_count,adoption_max/(1+EXP(-adoption_steepness*(2026.875-adoption_midpoint))))*opex_support_per_ent/12 -> 53.298176 | N27: =MAX(pilot_count,adoption_max/(1+EXP(-adoption_steepness*(2026.958-adoption_midpoint))))*opex_support_per_ent/12 -> 56.268989 | O27: =SUM(C27:N27) -> 501.74766
A28: OPEX cộng dồn | C28: =SUM(C15:C27) -> 2801.0513 | D28: =SUM(D15:D27) -> 2370.9693 | E28: =SUM(E15:E27) -> 2372.9884 | F28: =SUM(F15:F27) -> 2375.1369 | G28: =SUM(G15:G27) -> 2377.3654 | H28: =SUM(H15:H27) -> 2379.7002 | I28: =SUM(I15:I27) -> 2382.1721 | J28: =SUM(J15:J27) -> 2384.7226 | ... N28: =SUM(N15:N27) -> 2396.0173 | O28: =SUM(C28:N28) -> 29010.728
A29: Dự phòng | B29: Tr VND | C29: =C28*opex_contingency_pct -> 280.10513 | D29: =D28*opex_contingency_pct -> 237.09693 | E29: =E28*opex_contingency_pct -> 237.29884 | F29: =F28*opex_contingency_pct -> 237.51369 | G29: =G28*opex_contingency_pct -> 237.73654 | H29: =H28*opex_contingency_pct -> 237.97002 | I29: =I28*opex_contingency_pct -> 238.21721 | J29: =J28*opex_contingency_pct -> 238.47226 | ... N29: =N28*opex_contingency_pct -> 239.60173 | O29: =SUM(C29:N29) -> 2901.0728
A30: TỔNG OPEX | C30: =C28+C29 -> 3081.1565 | D30: =D28+D29 -> 2608.0662 | E30: =E28+E29 -> 2610.2872 | F30: =F28+F29 -> 2612.6506 | G30: =G28+G29 -> 2615.1019 | H30: =H28+H29 -> 2617.6702 | I30: =I28+I29 -> 2620.3893 | J30: =J28+J29 -> 2623.1949 | ... N30: =N28+N29 -> 2635.6191 | O30: =SUM(C30:N30) -> 31911.8
A32: TỔNG KẾT
A33: Doanh thu | C33: =C8 -> 597.0487 | D33: =D8 -> 636.12746 | E33: =E8 -> 677.26595 | F33: =F8 -> 721.04143 | G33: =G8 -> 766.44741 | H33: =H8 -> 814.01877 | I33: =I8 -> 864.38467 | J33: =J8 -> 916.35115 | ... N33: =N8 -> 1146.4807 | O33: =SUM(C33:N33) -> 10223.109
A34: CAPEX | C34: =C12 -> 79.2 | D34: =D12 -> 79.2 | E34: =E12 -> 79.2 | F34: =F12 -> 79.2 | G34: =G12 -> 79.2 | H34: =H12 -> 79.2 | I34: =I12 -> 79.2 | J34: =J12 -> 79.2 | ... N34: =N12 -> 79.2 | O34: =SUM(C34:N34) -> 950.4
A35: OPEX | C35: =C30 -> 3081.1565 | D35: =D30 -> 2608.0662 | E35: =E30 -> 2610.2872 | F35: =F30 -> 2612.6506 | G35: =G30 -> 2615.1019 | H35: =H30 -> 2617.6702 | I35: =I30 -> 2620.3893 | J35: =J30 -> 2623.1949 | ... N35: =N30 -> 2635.6191 | O35: =SUM(C35:N35) -> 31911.8
A36: TỔNG NGÂN SÁCH | C36: =C34+C35 -> 3160.3565 | D36: =D34+D35 -> 2687.2662 | E36: =E34+E35 -> 2689.4872 | F36: =F34+F35 -> 2691.8506 | G36: =G34+G35 -> 2694.3019 | H36: =H34+H35 -> 2696.8702 | I36: =I34+I35 -> 2699.5893 | J36: =J34+J35 -> 2702.3949 | ... N36: =N34+N35 -> 2714.8191 | O36: =SUM(C36:N36) -> 32862.2
A37: RÒNG (DT - Ngân sách) | C37: =C33-C36 -> -2563.3078 | D37: =D33-D36 -> -2051.1388 | E37: =E33-E36 -> -2012.2213 | F37: =F33-F36 -> -1970.8091 | G37: =G33-G36 -> -1927.8545 | H37: =H33-H36 -> -1882.8514 | I37: =I33-I36 -> -1835.2047 | J37: =J33-J36 -> -1786.0437 | ... N37: =N33-N36 -> -1568.3384 | O37: =SUM(C37:N37) -> -22639.092
A38: Lũy kế | C38: =C37 -> -2563.3078 | D38: =C38+D37 -> -4614.4466 | E38: =D38+E37 -> -6626.6678 | F38: =E38+F37 -> -8597.477 | G38: =F38+G37 -> -10525.331 | H38: =G38+H37 -> -12408.183 | I38: =H38+I37 -> -14243.388 | J38: =I38+J37 -> -16029.431 | K38: =J38+K37 -> -17764.252 | ... N38: =M38+N37 -> -22639.092 | O38: =N38 -> -22639.092
