Workbook
Name ad_cpm: Assumptions!$B$36
Name ad_impressions_base: Assumptions!$B$37
Name adoption_max: Assumptions!$B$23
Name adoption_midpoint: Assumptions!$B$24
Name adoption_steepness: Assumptions!$B$25
Name ap_days: Assumptions!$B$76
Name ar_days: Assumptions!$B$75
Name audit_fee: Assumptions!$B$39
Name base_year: Assumptions!$B$11
Name bhxh_rate: Assumptions!$B$67
Name bizops_floor: Assumptions!$B$88
Name capex_backend: 'Initial Investment'!$B$5
Name capex_cloud_setup: 'Initial Investment'!$B$4
Name capex_contingency: 'Initial Investment'!$B$13
Name capex_data_platform: 'Initial Investment'!$B$7
Name capex_devops: 'Initial Investment'!$B$11
Name capex_frontend: 'Initial Investment'!$B$6
Name capex_integration: 'Initial Investment'!$B$10
Name capex_maintenance_pct: Assumptions!$B$44
Name capex_security_setup: 'Initial Investment'!$B$8
Name capex_testing: 'Initial Investment'!$B$12
Name capex_total: 'Initial Investment'!$B$15
Name capex_ux_design: 'Initial Investment'!$B$9
Name cert_fee_escalation: Assumptions!$B$32
Name cert_fee_yr1: Assumptions!$B$31
Name churn_rate: Assumptions!$B$27
Name cit_rate: Assumptions!$B$72
Name cloud_elasticity: Assumptions!$B$87
Name cloud_gmv_factor: Assumptions!$B$82
Name cloud_per_1M_vcr: Assumptions!$B$48
Name daas_price: Assumptions!$B$35
Name depreciation_years: Assumptions!$B$74
Name discount_rate: Assumptions!$B$73
Name ecom_growth_rate: Assumptions!$B$19
Name ecom_market_base: Assumptions!$B$18
Name hr_bizops_per_100_ent: Assumptions!$B$86
Name marketing_growth: Assumptions!$B$46
Name mkt_efficiency_per_100: Assumptions!$B$83
Name months_to_first_revenue: Assumptions!$B$6
Name opex_branding: Assumptions!$B$52
Name opex_cloud_base: Assumptions!$B$47
Name opex_contingency_pct: Assumptions!$B$58
Name opex_external: Assumptions!$B$50
Name opex_legal: Assumptions!$B$51
Name opex_marketing: Assumptions!$B$45
Name opex_partner_mgmt: Assumptions!$B$57
Name opex_pilot_eval: Assumptions!$B$54
Name opex_security: Assumptions!$B$53
Name opex_support_per_ent: Assumptions!$B$56
Name payment_proc_pct: Assumptions!$B$55
Name pilot_count: Assumptions!$B$26
Name platform_market_share: Assumptions!$B$34
Name recruit_cost_pct: Assumptions!$B$68
Name salary_bizops: Assumptions!$B$64
Name salary_data: Assumptions!$B$65
Name salary_dev: Assumptions!$B$63
Name salary_escalation: Assumptions!$B$66
Name salary_mgmt: Assumptions!$B$62
Name SAM_enterprises: Assumptions!$B$17
Name stage2_gate: Assumptions!$B$77

Sheet Guide
A1: VISIT VIETNAM — FINANCIAL MODEL v6 — HƯỚNG DẪN TOÀN DIỆN
A2: v6.1 | 2026-03-21 | Revenue timing + cascading relationships + sensitivity + 55 named ranges
A4: 1. DANH SÁCH CÁC SHEET (14 sheets)
A5: Sheet | B5: Mục đích | C5: Ghi chú quan trọng
A6: Guide | B6: Hướng dẫn toàn diện: thuật ngữ, công thức, cách dùng | C6: Đọc trước khi dùng mô hình
A7: Assumptions | B7: 55 named ranges — TẤT CẢ đầu vào tập trung tại đây | C7: Chỉ sửa ô vàng (nền vàng, chữ xanh)
A8: Initial Investment | B8: 10 hạng mục CAPEX → named range capex_total = 5,280 Tr VND | C8: Khấu hao 5 năm đường thẳng
A9: HR Plan | B9: 4 bộ phận × 42 kỳ. BizOps tự scale theo số DN | C9: Lương = hc × salary × (1+esc)^yr × (1+bhxh)
A10: Market Sizing | B10: S-curve tăng trưởng DN + 6 hàng tham chiếu thời gian | C10: Year fraction tính từ base_year + start_month
A11: Revenue Schedule | B11: 6 nguồn DT. Tất cả gated bởi months_to_first_revenue
A12: Cost Schedule | B12: CAPEX + OPEX (10 mục + dự phòng). Cloud scales theo GMV | C12: Marketing giảm hiệu quả theo DN, Support economies of scale
A13: P&L | B13: DT → Giá vốn → LN gộp → OPEX → EBITDA → KH → Thuế TNDN → LN ròng | C13: CIT 20% chỉ khi EBIT > 0
A14: Cash Flow | B14: ĐTHĐ + ĐTĐT → DTTD + Lũy kế. Vốn lưu động qua ar_days | C14: OCF + ICF = FCF
A15: DCF & Returns | B15: FCF theo năm, NPV, IRR, ROI, đốt tiền max | C15: NPV = NPV(discount_rate, FCF)
A16: Sensitivity | B16: 235 ô NPV tính sẵn: 1-at-a-time + 3 bảng 2 chiều | C16: Tất cả dùng named ranges, tự cập nhật
A17: Scenarios | B17: 5 kịch bản + giải thích yếu tố ảnh hưởng + mô tả chi tiết | C17: Copy giá trị vào Assumptions để thử
A18: Budget 2025 | B18: Ngân sách tháng 7-12/2025 chi tiết | C18: Dùng cho phê duyệt ngân sách
A19: Budget 2026 | B19: Ngân sách tháng 1-12/2026 chi tiết | C19: Dùng cho phê duyệt ngân sách
A21: 2. CÁCH SỬ DỤNG (8 bước)
A22: Bước | B22: Hành động | C22: Chi tiết
A23: Bước 1 | B23: Mở sheet Assumptions | C23: Đây là nơi DUY NHẤT bạn cần sửa
A24: Bước 2 | B24: Sửa ô vàng (nền vàng, chữ xanh) | C24: Ô trắng = công thức, KHÔNG sửa
A25: Bước 3 | B25: Đặt months_to_first_revenue | C25: 0 = DT ngay tháng đầu, 3 = 3 tháng setup, 6 = nửa năm
A26: Bước 4 | B26: Kiểm tra P&L | C26: Xem các năm nào lỗ, năm nào lãi
A27: Bước 5 | B27: Kiểm tra Cash Flow | C27: Xem dòng tiền lũy kế, đốt tiền max
A28: Bước 6 | B28: Kiểm tra DCF & Returns | C28: NPV dương = dự án tạo giá trị, IRR > WACC = đáng đầu tư
A29: Bước 7 | B29: Xem Sensitivity | C29: Biết tham số nào ảnh hưởng NPV nhiều nhất
A30: Bước 8 | B30: Thử kịch bản | C30: Copy giá trị từ Scenarios vào Assumptions → xem kết quả
A32: 3. QUY ƯỚC Ô (Cell Color Convention)
A33: Màu nền / chữ | B33: Ý nghĩa | C33: Hành động
A34: Nền VÀNG + chữ XANH | B34: Đầu vào (placeholder) — giá trị bạn có thể thay đổi | C34: SỬA giá trị tại đây
A35: Nền XANH LÁ + chữ ĐEN ĐẬM | B35: Tổng / Subtotal — công thức SUM hoặc tổng hợp | C35: KHÔNG sửa
A36: Nền XANH ĐẬM + chữ TRẮNG | B36: Tiêu đề cột hoặc mục | C36: KHÔNG sửa
A37: Nền TRẮNG + chữ ĐEN | B37: Công thức tính toán — tự cập nhật | C37: KHÔNG sửa
A38: Nền XANH NHẠT + chữ ĐẬM | B38: Tiêu đề phần (section header) | C38: KHÔNG sửa
A39: Nền VÀNG NHẠT + chữ NÂU | B39: Tham số quan hệ cascading | C39: SỬA được
A41: 4. DANH SÁCH NAMED RANGES (55 tham số)
A42: Named Range | B42: Mô tả + Giá trị mặc định | C42: Công thức sử dụng (ví dụ)
A43: THỜI GIAN
A44: base_year | B44: Năm gốc = 2025 | C44: Year frac = base_year + (start_month-1+idx)/12
A45: start_month | B45: Tháng bắt đầu = 7 (Tháng 7) | C45: Cùng base_year tính year fraction
A46: months_to_first_revenue | B46: Tháng setup trước DT = 3 (DT từ tháng 10/2025) | C46: IF(idx >= months_to_first_revenue, revenue, 0)
A47: THỊ TRƯỜNG
A48: TAM_enterprises | B48: Tổng DN du lịch VN = 40,000 | C48: Tham khảo, không dùng trực tiếp
A49: SAM_enterprises | B49: DN phục vụ được = 15,000 | C49: Tham khảo, adoption_max < SAM
A50: ecom_market_base | B50: TMĐT du lịch gốc = 82,500 Tỷ VND | C50: ecom × (1+growth)^yr = thị trường tương lai
A51: ecom_growth_rate | B51: Tăng trưởng TMĐT = 8%/năm | C51: ecom_market_base × (1+rate)^years
A52: ĐƯỜNG CONG S
A53: adoption_max | B53: Trần DN = 1,200 (#1 driver) | C53: max/(1+EXP(-steepness*(year-midpoint)))
A54: adoption_midpoint | B54: Năm uốn = 2028 | C54: Điểm tăng nhanh nhất trên S-curve
A55: adoption_steepness | B55: Hệ số dốc = 0.9 | C55: Cao hơn = tăng nhanh hơn quanh midpoint
A56: pilot_count | B56: DN thí điểm = 15 | C56: =MAX(pilot_count, S_curve_result)
A57: churn_rate | B57: Tỷ lệ rời bỏ = 20%/năm (#3 driver) | C57: churned = gross × churn / div
A58: GIÁ DỊCH VỤ
A59: cert_fee_yr1 | B59: Phí chứng nhận = 25 Tr/DN/năm | C59: net × cert × (1+esc)^yr / div
A60: cert_fee_escalation | B60: Tăng phí = 5%/năm | C60: Compound: (1+0.05)^5 = tăng 28% sau 5 năm
A61: tx_take_rate | B61: Hoa hồng GD = 2% GMV | C61: ecom × market_share × take_rate × 1000
A62: platform_market_share | B62: Thị phần GMV = 0.5% (#2 driver) | C62: Chỉ áp dụng khi net_ent ≥ stage2_gate
A63: daas_price | B63: Giá DaaS = 30 Tr/triệu VCR | C63: VCR_millions × daas_price
A64: ad_cpm | B64: CPM quảng cáo = 150K VND | C64: impressions × ent × CPM / 1000
A65: ad_impressions_base | B65: Lượt QC/tháng = 500K | C65: Nhân với số DN và số tháng
A66: training_fee | B66: Phí đào tạo = 15 Tr/phiên | C66: net × training_pct × fee / div
A67: audit_fee | B67: Phí kiểm toán = 10 Tr | C67: net × audit_fee / div
A68: training_pct | B68: % DN mua ĐT = 30% | C68: Tỷ lệ cross-sell
A69: CHI PHÍ
A70: capex_maintenance_pct | B70: Bảo trì = 18% CAPEX/năm | C70: capex_total × 0.18 / div (từ 2026)
A71: opex_marketing | B71: Marketing gốc = 7,000 Tr/năm | C71: mkt × (1+growth)^yr × efficiency_factor / div
A72: marketing_growth | B72: Tăng marketing = 15%/năm | C72: Compound growth applied annually
A73: opex_cloud_base | B73: Cloud gốc = 3,250 Tr/năm | C73: cloud/div + VCR×per_1M + GMV×gmv_factor
A74: cloud_per_1M_vcr | B74: Cloud biến đổi = 8 Tr/triệu VCR | C74: Tỷ lệ theo traffic
A75: vcr_per_enterprise | B75: VCR/DN/tháng = 10,000 bản ghi | C75: net_ent × vcr × months / 1M = VCR_millions
A76: opex_external | B76: Đối ngoại = 400 Tr/năm | C76: Chia đều theo kỳ: 400/div
A77: opex_legal | B77: Pháp lý = 240 Tr/năm | C77: Chia đều theo kỳ: 240/div
A78: opex_branding | B78: Thương hiệu = 4,000 Tr/năm | C78: Chia đều: 4000/div
A79: opex_security | B79: Bảo mật = 250 Tr/năm | C79: Chia đều: 250/div
A80: opex_pilot_eval | B80: Thí điểm = 200 Tr (chỉ giai đoạn setup) | C80: Chỉ khi idx < months_to_first_revenue
A81: payment_proc_pct | B81: Phí cổng TT = 2.5% | C81: COGS = tx_revenue × 2.5%
... A84: opex_contingency_pct | B84: Dự phòng = 10% OPEX | C84: Buffer: OPEX_sub × 10%
A85: NHÂN SỰ
A86: salary_mgmt | B86: Lương QL = 45 Tr/tháng | C86: hc × 45 × months × (1+esc)^yr × (1+bhxh)
A87: salary_dev | B87: Lương PT = 35 Tr/tháng | C87: Tương tự salary_mgmt
A88: salary_bizops | B88: Lương VH = 20 Tr/tháng | C88: BizOps hc scales theo DN
A89: salary_data | B89: Lương DL = 40 Tr/tháng | C89: Tương tự salary_mgmt
A90: salary_escalation | B90: Tăng lương = 10%/năm | C90: (1+0.10)^years = compound
A91: bhxh_rate | B91: BHXH phần DN = 21.5% | C91: BHXH 17.5% + BHYT 3% + BHTN 1%
A92: recruit_cost_pct | B92: Phí tuyển = 20% lương năm | C92: new_hire × 30 × 12 × 20%
A93: TÀI CHÍNH
A94: cit_rate | B94: Thuế TNDN = 20% | C94: IF(EBIT>0, -EBIT×20%, 0)
A95: discount_rate | B95: WACC = 15% | C95: NPV(15%, FCF_array)
A96: depreciation_years | B96: Khấu hao = 5 năm | C96: capex_total / 5 / div per period
A97: ar_days | B97: Phải thu = 45 ngày | C97: Working capital = ΔRevenue × 45/365
A98: ap_days | B98: Phải trả = 30 ngày | C98: Hiện chưa dùng trong model
A99: stage2_gate | B99: Ngưỡng GĐ2 = 300 DN | C99: IF(net ≥ 300, Stage2_revenue, 0)
A100: QUAN HỆ CASCADING
A101: cloud_gmv_factor | B101: Cloud/Bn GMV = 0.5 Tr | C101: Cloud += ecom × share × 0.5
A102: mkt_efficiency_per_100 | B102: Giảm mkt/100 DN = 2% | C102: mkt × MAX(0.5, 1 - ent×2%/100)
A103: support_scale_threshold | B103: Ngưỡng economies = 500 DN | C103: IF(ent>500, cost×0.7, cost)
A104: support_discount | B104: Giảm support = 30% | C104: Khi > 500 DN: support × (1-0.3)
A105: hr_bizops_per_100_ent | B105: BizOps/100 DN = 2.0 | C105: MAX(floor, ent × 2 / 100)
A106: cloud_elasticity | B106: Elasticity cloud = 1.2 | C106: VCR × (ent/100)^0.2 = super-linear
...

Sheet Assumptions
A1: VISIT VIETNAM — FINANCIAL MODEL v6 — ASSUMPTIONS
A2: Revenue timing control + cascading relationships + 55 named ranges
A4: REVENUE TIMING | F4: NPV | G4: IRR
A5: Parameter | B5: Value | C5: Unit | D5: Notes | F5: ='DCF & Returns'!B13 -> 9539.2161 | G5: ='DCF & Returns'!B14 -> 0.2361664
A6: Months before first revenue | B6: 10 | C6: months | D6: 0=revenue from day 1, 3=3 months setup (Oct 2025), 6=Jan 2026
A7: Revenue active flag formula | B7: Used in Revenue/Cost sheets | D7: IF(period_idx >= months_to_first_revenue, 1, 0) — auto gate for all revenue
A9: TIMING
A10: Parameter | B10: Value | C10: Unit | D10: Notes
A11: Base year | B11: 2025 | C11: Year | D11: Project start year
A12: Start month | B12: 7 | C12: Month | D12: July=7
A14: MARKET DATA
A15: Parameter | B15: Value | C15: Unit | D15: Notes
A16: Total tourism enterprises | B16: 40000 | D16: GSO/VNAT
A17: Serviceable enterprises | B17: 15000 | D17: Digitally active
A18: E-commerce tourism market (base yr) | B18: 82500 | C18: Bn VND | D18: e-Conomy SEA
A19: E-tourism YoY growth | B19: 0.08 | C19: % | D19: Historical
A21: ADOPTION S-CURVE
A22: Parameter | B22: Value | C22: Unit | D22: Notes
A23: Maximum enterprises (ceiling) | B23: 1200 | D23: S-curve asymptote
A24: Midpoint year | B24: 2028 | C24: Year | D24: Inflection point
A25: Steepness factor | B25: 0.9
A26: Starting enterprises | B26: 15 | D26: Pilot partners
A27: Annual non-renewal rate | B27: 0.2 | C27: %
A29: PRICING
A30: Parameter | B30: Value | C30: Unit | D30: Notes
A31: Certification fee/enterprise/yr | B31: 25 | C31: M VND
A32: Cert fee annual increase | B32: 0.05 | C32: %
A33: Transaction fee (% of GMV) | B33: 0.02 | C33: % | D33: Platform commission
A34: % e-tourism GMV via VV | B34: 0.02 | C34: %
A35: DaaS price per M VCR | B35: 30 | C35: M VND
A36: Advertising CPM | B36: 150 | C36: K VND | D36: B2B benchmark
A37: Monthly impressions (K) | B37: 500 | C37: K | D37: Scales w/ enterprises
A38: Training fee per engagement | B38: 15 | C38: M VND | D38: NEW stream
A39: Audit fee per certification | B39: 10 | C39: M VND | D39: NEW stream
A40: % enterprises buying training | B40: 0.3 | C40: % | D40: Estimated
A42: COST PARAMETERS
A43: Parameter | B43: Value | C43: Unit | D43: Notes
A44: Maintenance (% of CAPEX/yr) | B44: 0.18 | C44: % | D44: Industry 15-20%
A45: Marketing (annual base) | B45: 7000 | C45: M VND
A46: Marketing annual growth | B46: 0.15 | C46: %
A47: Cloud base (annual) | B47: 3250 | C47: M VND | D47: From original data
A48: Cloud cost per M VCR | B48: 8 | C48: M VND
A49: VCR per enterprise/month | B49: 10000 | C49: records | D49: Traffic estimate
A50: External affairs (annual) | B50: 400 | C50: M VND | D50: Current data
A51: Legal & compliance (annual) | B51: 240 | C51: M VND | D51: Current data
A52: Branding & events (annual) | B52: 4000 | C52: M VND | D52: Current data
A53: Security/pentest (annual) | B53: 250 | C53: M VND | D53: Current data
A54: Pilot evaluation (Y1 only) | B54: 200 | C54: M VND | D54: One-time
A55: Payment gateway fee | B55: 0.025 | C55: % | D55: COGS on tx revenue
A56: Support cost per enterprise/yr | B56: 2 | C56: M VND | D56: Scales w/ count
A57: Partner management (annual) | B57: 500 | C57: M VND | D57: Relationship mgmt
A58: Contingency (% total OPEX) | B58: 0.1 | C58: % | D58: Buffer
A60: HR PARAMETERS
A61: Parameter | B61: Value | C61: Unit | D61: Notes
A62: Avg monthly — Management | B62: 45 | C62: M VND | D62: Director/PM
A63: Avg monthly — Development | B63: 35 | C63: M VND | D63: Engineers
A64: Avg monthly — BizOps | B64: 20 | C64: M VND | D64: BD/support
A65: Avg monthly — Data/Analytics | B65: 40 | C65: M VND | D65: Data eng
A66: Annual salary increase | B66: 0.1 | C66: % | D66: VN market
A67: Social insurance (employer) | B67: 0.215 | C67: % | D67: BHXH+BHYT+BHTN
A68: Recruitment fee (% Y1 sal) | B68: 0.2 | C68: % | D68: Headhunter
A70: FINANCIAL PARAMETERS
A71: Parameter | B71: Value | C71: Unit | D71: Notes
A72: Corporate income tax | B72: 0.2 | C72: % | D72: Vietnamese law
A73: Discount rate (WACC) | B73: 0.15 | C73: %
A74: Depreciation period | B74: 5 | C74: Years | D74: Straight-line
A75: Accounts receivable days | B75: 45 | C75: Days | D75: Collection period
A76: Accounts payable days | B76: 30 | C76: Days | D76: Payment terms
A77: Stage 2 gate (min enterprises) | B77: 300 | D77: Activate tx fees
A80: CASCADING RELATIONSHIPS (how assumptions affect each other)
A81: Parameter | B81: Value | C81: Unit | D81: Cascade logic
A82: Cloud cost per Bn VND GMV processed | B82: 0.5 | C82: Tr VND/Bn | D82: ↑ market_share → ↑ GMV → ↑ cloud cost. Formula: GMV × this factor
A83: Marketing cost reduction per 100 enterprises | B83: 0.02 | C83: %/100 ent | D83: ↑ adoption → ↓ marketing/ent. Formula: marketing × MAX(0.5, 1 - ent×factor/100)
A84: Enterprises threshold for economies of scale | B84: 500 | C84: enterprises | D84: When net_ent > threshold → support cost drops by support_discount
A85: Support cost reduction after threshold | B85: 0.3 | C85: ratio | D85: ↑ ent past threshold → support/ent × (1 - discount). Economies of scale.
A86: BizOps staff needed per 100 enterprises (floor) | B86: 2 | C86: people/100 | D86: ↑ adoption → ↑ BizOps needed. Floor = MAX(manual_hc, ent×ratio/100)
A87: Cloud cost elasticity to enterprise count | B87: 1.2 | C87: factor | D87: VCR cost scales by ent^elasticity instead of linear. >1 = super-linear.
A88: BizOps minimum floor headcount | B88: 2 | C88: people | D88: MIN BizOps before scaling kicks in
A90: IMPACT MAP — How market_share cascades to costs
A91: adoption_max ↑ | B91: → net_enterprises ↑ | C91: → HR BizOps headcount ↑ (hr_bizops_per_100_ent) | D91: → HR Cost ↑
C92: → VCR volume ↑ (vcr_per_enterprise × net_ent) | D92: → Cloud Cost ↑ (cloud_per_1M_vcr)
C93: → Support demand ↑ (opex_support_per_ent × net_ent) | D93: → OPEX ↑
C94: → Marketing efficiency ↑ (cost/ent decreases) | D94: → Per-unit OPEX ↓
C95: → Cert/Training/Audit revenue ↑ | D95: → Revenue ↑
A97: platform_market_share ↑ | B97: → GMV through platform ↑ | C97: → Transaction fees ↑ (tx_take_rate × GMV) | D97: → Revenue ↑
C98: → Cloud processing load ↑ (cloud_gmv_factor × GMV) | D98: → Cloud Cost ↑
C99: → Payment processing fees ↑ (payment_proc_pct × tx_rev) | D99: → COGS ↑
C100: → DaaS & Ads potential ↑ | D100: → Revenue ↑
A102: churn_rate ↑ | B102: → net_enterprises ↓ | C102: → All enterprise-linked revenue ↓ | D102: → Revenue ↓
C103: → Need more new sales to replace | D103: → Marketing cost pressure ↑
C104: → Support & HR needs more stable | D104: → Cost stays high vs falling revenue

Sheet Initial Investment
A1: INITIAL INVESTMENT — CAPEX BREAKDOWN (M VND)
A3: CAPEX Item | B3: Amount (M VND) | C3: Timing | D3: Notes
A4: Cloud infrastructure setup | B4: 800 | C4: H2 2025 | D4: AWS/GCP initial
A5: Backend development | B5: 1200 | C5: H2 2025 | D5: API, DB, core
A6: Frontend + mobile | B6: 900 | C6: H2 2025 | D6: Web + mobile
A7: Data platform | B7: 600 | C7: H2 2025 | D7: Pipeline, analytics
A8: Security infrastructure | B8: 250 | C8: H2 2025 | D8: Pentest, auth
A9: UX/UI design | B9: 350 | C9: H2 2025 | D9: Design system
A10: 3rd-party integrations | B10: 400 | C10: H2 2025 | D10: Payment, OTA APIs
A11: DevOps & CI/CD | B11: 280 | C11: H2 2025 | D11: Deploy pipeline
A12: QA & testing | B12: 200 | C12: H2 2025 | D12: Auto + load test
A13: CAPEX contingency (10%) | B13: 300 | C13: H2 2025 | D13: Buffer
A15: TOTAL INITIAL CAPEX | B15: =SUM(B4:B13) -> 5280
A17: DEPRECIATION SCHEDULE
A18: Year | B18: Annual D&A | C18: Accum D&A | D18: Net Book Value
A19: 2025 | B19: =capex_total/depreciation_years -> 1056 | C19: =B19 -> 1056 | D19: =capex_total-C19 -> 4224
A20: 2026 | B20: =capex_total/depreciation_years -> 1056 | C20: =C19+B20 -> 2112 | D20: =capex_total-C20 -> 3168
A21: 2027 | B21: =capex_total/depreciation_years -> 1056 | C21: =C20+B21 -> 3168 | D21: =capex_total-C21 -> 2112
A22: 2028 | B22: =capex_total/depreciation_years -> 1056 | C22: =C21+B22 -> 4224 | D22: =capex_total-C22 -> 1056
A23: 2029 | B23: =capex_total/depreciation_years -> 1056 | C23: =C22+B23 -> 5280 | D23: =capex_total-C23 -> 0
A24: 2030 | B24: =0 -> 0 | C24: =C23+B24 -> 5280 | D24: =capex_total-C24 -> 0

Sheet HR Plan
A1: HR PLAN — HEADCOUNT & COST
A3: Dept / Item | B3: Unit | C3: Jul 2025 | D3: Aug 2025 | E3: Sep 2025 | F3: Oct 2025 | G3: Nov 2025 | H3: Dec 2025 | I3: Jan 2026 | J3: Feb 2026 | K3: Mar 2026 | L3: Apr 2026 | M3: May 2026 | N3: Jun 2026 | O3: Jul 2026 | P3: Aug 2026 | Q3: Sep 2026 | R3: Oct 2026 | S3: Nov 2026 | T3: Dec 2026 | U3: Jan 2027 | V3: Feb 2027 | W3: Mar 2027 | X3: Apr 2027 | Y3: May 2027 | Z3: Jun 2027 | AA3: Jul 2027 | AB3: Aug 2027 | AC3: Sep 2027 | AD3: Oct 2027 | AE3: Nov 2027 | AF3: Dec 2027 | AG3: Q1 2028 | AH3: Q2 2028 | AI3: Q3 2028 | AJ3: Q4 2028 | AK3: Q1 2029 | AL3: Q2 2029 | AM3: Q3 2029 | AN3: Q4 2029 | AO3: Q1 2030 | AP3: Q2 2030 | AQ3: Q3 2030 | AR3: Q4 2030
A4: HEADCOUNT
A5: Management | B5: people | C5: 2 | D5: 2 | E5: 2 | F5: 2 | G5: 2 | H5: 2 | I5: 2 | J5: 2 | K5: 2 | L5: 2 | M5: 2 | N5: 2 | O5: 2 | P5: 2 | Q5: 2 | R5: 2 | S5: 2 | T5: 2 | U5: 3 | V5: 3 | W5: 3 | X5: 3 | Y5: 3 | Z5: 3 | AA5: 3 | AB5: 3 | AC5: 3 | AD5: 3 | AE5: 3 | AF5: 3 | AG5: 3 | AH5: 3 | AI5: 3 | AJ5: 3 | AK5: 4 | AL5: 4 | AM5: 4 | AN5: 4 | AO5: 4 | AP5: 4 | AQ5: 4 | AR5: 4
A6: Development | B6: people | C6: 12 | D6: 12 | E6: 12 | F6: 12 | G6: 12 | H6: 12 | I6: 12 | J6: 12 | K6: 12 | L6: 12 | M6: 12 | N6: 12 | O6: 12 | P6: 12 | Q6: 12 | R6: 12 | S6: 12 | T6: 12 | U6: 14 | V6: 14 | W6: 14 | X6: 14 | Y6: 14 | Z6: 14 | AA6: 14 | AB6: 14 | AC6: 14 | AD6: 14 | AE6: 14 | AF6: 14 | AG6: 16 | AH6: 16 | AI6: 16 | AJ6: 16 | AK6: 18 | AL6: 18 | AM6: 18 | AN6: 18 | AO6: 20 | AP6: 20 | AQ6: 20 | AR6: 20
A7: Biz Ops (scaled) | B7: people | C7: =MAX(bizops_floor,ROUND('Market Sizing'!C15*hr_bizops_per_100_ent/100,0)) -> 2 | D7: =MAX(bizops_floor,ROUND('Market Sizing'!D15*hr_bizops_per_100_ent/100,0)) -> 2 | E7: =MAX(bizops_floor,ROUND('Market Sizing'!E15*hr_bizops_per_100_ent/100,0)) -> 3 | F7: =MAX(bizops_floor,ROUND('Market Sizing'!F15*hr_bizops_per_100_ent/100,0)) -> 3 | G7: =MAX(bizops_floor,ROUND('Market Sizing'!G15*hr_bizops_per_100_ent/100,0)) -> 3 | H7: =MAX(bizops_floor,ROUND('Market Sizing'!H15*hr_bizops_per_100_ent/100,0)) -> 3 | I7: =MAX(bizops_floor,ROUND('Market Sizing'!I15*hr_bizops_per_100_ent/100,0)) -> 3 | J7: =MAX(bizops_floor,ROUND('Market Sizing'!J15*hr_bizops_per_100_ent/100,0)) -> 4 | ... AR7: =MAX(bizops_floor,ROUND('Market Sizing'!AR15*hr_bizops_per_100_ent/100,0)) -> 21
A8: Data & Analytics | B8: people | C8: 0 | D8: 0 | E8: 0 | F8: 0 | G8: 0 | H8: 0 | I8: 2 | J8: 2 | K8: 2 | L8: 2 | M8: 2 | N8: 2 | O8: 2 | P8: 2 | Q8: 2 | R8: 2 | S8: 2 | T8: 2 | U8: 3 | V8: 3 | W8: 3 | X8: 3 | Y8: 3 | Z8: 3 | AA8: 3 | AB8: 3 | AC8: 3 | AD8: 3 | AE8: 3 | AF8: 3 | AG8: 4 | AH8: 4 | AI8: 4 | AJ8: 4 | AK8: 5 | AL8: 5 | AM8: 5 | AN8: 5 | AO8: 6 | AP8: 6 | AQ8: 6 | AR8: 6
A9: TOTAL HEADCOUNT | B9: people | C9: =C5+C6+C7+C8 -> 16 | D9: =D5+D6+D7+D8 -> 16 | E9: =E5+E6+E7+E8 -> 17 | F9: =F5+F6+F7+F8 -> 17 | G9: =G5+G6+G7+G8 -> 17 | H9: =H5+H6+H7+H8 -> 17 | I9: =I5+I6+I7+I8 -> 19 | J9: =J5+J6+J7+J8 -> 20 | ... AR9: =AR5+AR6+AR7+AR8 -> 51
A11: NEW HIRES
A12: New hires | B12: people | C12: =C9 -> 16 | D12: =MAX(0,D9-C9) -> 0 | E12: =MAX(0,E9-D9) -> 1 | F12: =MAX(0,F9-E9) -> 0 | G12: =MAX(0,G9-F9) -> 0 | H12: =MAX(0,H9-G9) -> 0 | I12: =MAX(0,I9-H9) -> 2 | J12: =MAX(0,J9-I9) -> 1 | K12: =MAX(0,K9-J9) -> 0 | ... AR12: =MAX(0,AR9-AQ9) -> 0
A14: SALARY COST (M VND)
A15: Management cost | B15: M VND | C15: =C5*salary_mgmt*1*(1+salary_escalation)^0*(1+bhxh_rate) -> 109.35 | D15: =D5*salary_mgmt*1*(1+salary_escalation)^0*(1+bhxh_rate) -> 109.35 | E15: =E5*salary_mgmt*1*(1+salary_escalation)^0*(1+bhxh_rate) -> 109.35 | F15: =F5*salary_mgmt*1*(1+salary_escalation)^0*(1+bhxh_rate) -> 109.35 | G15: =G5*salary_mgmt*1*(1+salary_escalation)^0*(1+bhxh_rate) -> 109.35 | H15: =H5*salary_mgmt*1*(1+salary_escalation)^0*(1+bhxh_rate) -> 109.35 | I15: =I5*salary_mgmt*1*(1+salary_escalation)^1*(1+bhxh_rate) -> 120.285 | J15: =J5*salary_mgmt*1*(1+salary_escalation)^1*(1+bhxh_rate) -> 120.285 | K15: =K5*salary_mgmt*1*(1+salary_escalation)^1*(1+bhxh_rate) -> 120.285 | L15: =L5*salary_mgmt*1*(1+salary_escalation)^1*(1+bhxh_rate) -> 120.285 | M15: =M5*salary_mgmt*1*(1+salary_escalation)^1*(1+bhxh_rate) -> 120.285 | N15: =N5*salary_mgmt*1*(1+salary_escalation)^1*(1+bhxh_rate) -> 120.285 | O15: =O5*salary_mgmt*1*(1+salary_escalation)^1*(1+bhxh_rate) -> 120.285 | P15: =P5*salary_mgmt*1*(1+salary_escalation)^1*(1+bhxh_rate) -> 120.285 | ... T15: =T5*salary_mgmt*1*(1+salary_escalation)^1*(1+bhxh_rate) -> 120.285 | U15: =U5*salary_mgmt*1*(1+salary_escalation)^2*(1+bhxh_rate) -> 198.47025 | V15: =V5*salary_mgmt*1*(1+salary_escalation)^2*(1+bhxh_rate) -> 198.47025 | W15: =W5*salary_mgmt*1*(1+salary_escalation)^2*(1+bhxh_rate) -> 198.47025 | X15: =X5*salary_mgmt*1*(1+salary_escalation)^2*(1+bhxh_rate) -> 198.47025 | Y15: =Y5*salary_mgmt*1*(1+salary_escalation)^2*(1+bhxh_rate) -> 198.47025 | Z15: =Z5*salary_mgmt*1*(1+salary_escalation)^2*(1+bhxh_rate) -> 198.47025 | AA15: =AA5*salary_mgmt*1*(1+salary_escalation)^2*(1+bhxh_rate) -> 198.47025 | AB15: =AB5*salary_mgmt*1*(1+salary_escalation)^2*(1+bhxh_rate) -> 198.47025 | ... AF15: =AF5*salary_mgmt*1*(1+salary_escalation)^2*(1+bhxh_rate) -> 198.47025 | AG15: =AG5*salary_mgmt*3*(1+salary_escalation)^3*(1+bhxh_rate) -> 654.95183 | AH15: =AH5*salary_mgmt*3*(1+salary_escalation)^3*(1+bhxh_rate) -> 654.95183 | AI15: =AI5*salary_mgmt*3*(1+salary_escalation)^3*(1+bhxh_rate) -> 654.95183 | AJ15: =AJ5*salary_mgmt*3*(1+salary_escalation)^3*(1+bhxh_rate) -> 654.95183 | AK15: =AK5*salary_mgmt*3*(1+salary_escalation)^4*(1+bhxh_rate) -> 960.59601 | AL15: =AL5*salary_mgmt*3*(1+salary_escalation)^4*(1+bhxh_rate) -> 960.59601 | AM15: =AM5*salary_mgmt*3*(1+salary_escalation)^4*(1+bhxh_rate) -> 960.59601 | AN15: =AN5*salary_mgmt*3*(1+salary_escalation)^4*(1+bhxh_rate) -> 960.59601 | AO15: =AO5*salary_mgmt*3*(1+salary_escalation)^5*(1+bhxh_rate) -> 1056.6556 | AP15: =AP5*salary_mgmt*3*(1+salary_escalation)^5*(1+bhxh_rate) -> 1056.6556 | AQ15: =AQ5*salary_mgmt*3*(1+salary_escalation)^5*(1+bhxh_rate) -> 1056.6556 | AR15: =AR5*salary_mgmt*3*(1+salary_escalation)^5*(1+bhxh_rate) -> 1056.6556
A16: Development cost | B16: M VND | C16: =C6*salary_dev*1*(1+salary_escalation)^0*(1+bhxh_rate) -> 510.3 | D16: =D6*salary_dev*1*(1+salary_escalation)^0*(1+bhxh_rate) -> 510.3 | E16: =E6*salary_dev*1*(1+salary_escalation)^0*(1+bhxh_rate) -> 510.3 | F16: =F6*salary_dev*1*(1+salary_escalation)^0*(1+bhxh_rate) -> 510.3 | G16: =G6*salary_dev*1*(1+salary_escalation)^0*(1+bhxh_rate) -> 510.3 | H16: =H6*salary_dev*1*(1+salary_escalation)^0*(1+bhxh_rate) -> 510.3 | I16: =I6*salary_dev*1*(1+salary_escalation)^1*(1+bhxh_rate) -> 561.33 | J16: =J6*salary_dev*1*(1+salary_escalation)^1*(1+bhxh_rate) -> 561.33 | K16: =K6*salary_dev*1*(1+salary_escalation)^1*(1+bhxh_rate) -> 561.33 | L16: =L6*salary_dev*1*(1+salary_escalation)^1*(1+bhxh_rate) -> 561.33 | M16: =M6*salary_dev*1*(1+salary_escalation)^1*(1+bhxh_rate) -> 561.33 | N16: =N6*salary_dev*1*(1+salary_escalation)^1*(1+bhxh_rate) -> 561.33 | O16: =O6*salary_dev*1*(1+salary_escalation)^1*(1+bhxh_rate) -> 561.33 | P16: =P6*salary_dev*1*(1+salary_escalation)^1*(1+bhxh_rate) -> 561.33 | ... T16: =T6*salary_dev*1*(1+salary_escalation)^1*(1+bhxh_rate) -> 561.33 | U16: =U6*salary_dev*1*(1+salary_escalation)^2*(1+bhxh_rate) -> 720.3735 | V16: =V6*salary_dev*1*(1+salary_escalation)^2*(1+bhxh_rate) -> 720.3735 | W16: =W6*salary_dev*1*(1+salary_escalation)^2*(1+bhxh_rate) -> 720.3735 | X16: =X6*salary_dev*1*(1+salary_escalation)^2*(1+bhxh_rate) -> 720.3735 | Y16: =Y6*salary_dev*1*(1+salary_escalation)^2*(1+bhxh_rate) -> 720.3735 | Z16: =Z6*salary_dev*1*(1+salary_escalation)^2*(1+bhxh_rate) -> 720.3735 | AA16: =AA6*salary_dev*1*(1+salary_escalation)^2*(1+bhxh_rate) -> 720.3735 | AB16: =AB6*salary_dev*1*(1+salary_escalation)^2*(1+bhxh_rate) -> 720.3735 | ... AF16: =AF6*salary_dev*1*(1+salary_escalation)^2*(1+bhxh_rate) -> 720.3735 | AG16: =AG6*salary_dev*3*(1+salary_escalation)^3*(1+bhxh_rate) -> 2716.8372 | AH16: =AH6*salary_dev*3*(1+salary_escalation)^3*(1+bhxh_rate) -> 2716.8372 | AI16: =AI6*salary_dev*3*(1+salary_escalation)^3*(1+bhxh_rate) -> 2716.8372 | AJ16: =AJ6*salary_dev*3*(1+salary_escalation)^3*(1+bhxh_rate) -> 2716.8372 | AK16: =AK6*salary_dev*3*(1+salary_escalation)^4*(1+bhxh_rate) -> 3362.086 | AL16: =AL6*salary_dev*3*(1+salary_escalation)^4*(1+bhxh_rate) -> 3362.086 | AM16: =AM6*salary_dev*3*(1+salary_escalation)^4*(1+bhxh_rate) -> 3362.086 | AN16: =AN6*salary_dev*3*(1+salary_escalation)^4*(1+bhxh_rate) -> 3362.086 | AO16: =AO6*salary_dev*3*(1+salary_escalation)^5*(1+bhxh_rate) -> 4109.2163 | AP16: =AP6*salary_dev*3*(1+salary_escalation)^5*(1+bhxh_rate) -> 4109.2163 | AQ16: =AQ6*salary_dev*3*(1+salary_escalation)^5*(1+bhxh_rate) -> 4109.2163 | AR16: =AR6*salary_dev*3*(1+salary_escalation)^5*(1+bhxh_rate) -> 4109.2163
A17: Biz Ops cost | B17: M VND | C17: =C7*salary_bizops*1*(1+salary_escalation)^0*(1+bhxh_rate) -> 48.6 | D17: =D7*salary_bizops*1*(1+salary_escalation)^0*(1+bhxh_rate) -> 48.6 | E17: =E7*salary_bizops*1*(1+salary_escalation)^0*(1+bhxh_rate) -> 72.9 | F17: =F7*salary_bizops*1*(1+salary_escalation)^0*(1+bhxh_rate) -> 72.9 | G17: =G7*salary_bizops*1*(1+salary_escalation)^0*(1+bhxh_rate) -> 72.9 | H17: =H7*salary_bizops*1*(1+salary_escalation)^0*(1+bhxh_rate) -> 72.9 | I17: =I7*salary_bizops*1*(1+salary_escalation)^1*(1+bhxh_rate) -> 80.19 | J17: =J7*salary_bizops*1*(1+salary_escalation)^1*(1+bhxh_rate) -> 106.92 | K17: =K7*salary_bizops*1*(1+salary_escalation)^1*(1+bhxh_rate) -> 106.92 | L17: =L7*salary_bizops*1*(1+salary_escalation)^1*(1+bhxh_rate) -> 106.92 | M17: =M7*salary_bizops*1*(1+salary_escalation)^1*(1+bhxh_rate) -> 106.92 | N17: =N7*salary_bizops*1*(1+salary_escalation)^1*(1+bhxh_rate) -> 133.65 | O17: =O7*salary_bizops*1*(1+salary_escalation)^1*(1+bhxh_rate) -> 133.65 | P17: =P7*salary_bizops*1*(1+salary_escalation)^1*(1+bhxh_rate) -> 133.65 | ... T17: =T7*salary_bizops*1*(1+salary_escalation)^1*(1+bhxh_rate) -> 160.38 | U17: =U7*salary_bizops*1*(1+salary_escalation)^2*(1+bhxh_rate) -> 205.821 | V17: =V7*salary_bizops*1*(1+salary_escalation)^2*(1+bhxh_rate) -> 205.821 | W17: =W7*salary_bizops*1*(1+salary_escalation)^2*(1+bhxh_rate) -> 235.224 | X17: =X7*salary_bizops*1*(1+salary_escalation)^2*(1+bhxh_rate) -> 235.224 | Y17: =Y7*salary_bizops*1*(1+salary_escalation)^2*(1+bhxh_rate) -> 235.224 | Z17: =Z7*salary_bizops*1*(1+salary_escalation)^2*(1+bhxh_rate) -> 264.627 | AA17: =AA7*salary_bizops*1*(1+salary_escalation)^2*(1+bhxh_rate) -> 264.627 | AB17: =AB7*salary_bizops*1*(1+salary_escalation)^2*(1+bhxh_rate) -> 294.03 | ... AF17: =AF7*salary_bizops*1*(1+salary_escalation)^2*(1+bhxh_rate) -> 323.433 | AG17: =AG7*salary_bizops*3*(1+salary_escalation)^3*(1+bhxh_rate) -> 1164.3588 | AH17: =AH7*salary_bizops*3*(1+salary_escalation)^3*(1+bhxh_rate) -> 1261.3887 | AI17: =AI7*salary_bizops*3*(1+salary_escalation)^3*(1+bhxh_rate) -> 1358.4186 | AJ17: =AJ7*salary_bizops*3*(1+salary_escalation)^3*(1+bhxh_rate) -> 1455.4485 | AK17: =AK7*salary_bizops*3*(1+salary_escalation)^4*(1+bhxh_rate) -> 1707.7262 | AL17: =AL7*salary_bizops*3*(1+salary_escalation)^4*(1+bhxh_rate) -> 1814.4591 | AM17: =AM7*salary_bizops*3*(1+salary_escalation)^4*(1+bhxh_rate) -> 1921.192 | AN17: =AN7*salary_bizops*3*(1+salary_escalation)^4*(1+bhxh_rate) -> 2027.9249 | AO17: =AO7*salary_bizops*3*(1+salary_escalation)^5*(1+bhxh_rate) -> 2348.1236 | AP17: =AP7*salary_bizops*3*(1+salary_escalation)^5*(1+bhxh_rate) -> 2348.1236 | AQ17: =AQ7*salary_bizops*3*(1+salary_escalation)^5*(1+bhxh_rate) -> 2465.5298 | AR17: =AR7*salary_bizops*3*(1+salary_escalation)^5*(1+bhxh_rate) -> 2465.5298
A18: Data & Analytics cost | B18: M VND | C18: =C8*salary_data*1*(1+salary_escalation)^0*(1+bhxh_rate) -> 0 | D18: =D8*salary_data*1*(1+salary_escalation)^0*(1+bhxh_rate) -> 0 | E18: =E8*salary_data*1*(1+salary_escalation)^0*(1+bhxh_rate) -> 0 | F18: =F8*salary_data*1*(1+salary_escalation)^0*(1+bhxh_rate) -> 0 | G18: =G8*salary_data*1*(1+salary_escalation)^0*(1+bhxh_rate) -> 0 | H18: =H8*salary_data*1*(1+salary_escalation)^0*(1+bhxh_rate) -> 0 | I18: =I8*salary_data*1*(1+salary_escalation)^1*(1+bhxh_rate) -> 106.92 | J18: =J8*salary_data*1*(1+salary_escalation)^1*(1+bhxh_rate) -> 106.92 | K18: =K8*salary_data*1*(1+salary_escalation)^1*(1+bhxh_rate) -> 106.92 | L18: =L8*salary_data*1*(1+salary_escalation)^1*(1+bhxh_rate) -> 106.92 | M18: =M8*salary_data*1*(1+salary_escalation)^1*(1+bhxh_rate) -> 106.92 | N18: =N8*salary_data*1*(1+salary_escalation)^1*(1+bhxh_rate) -> 106.92 | O18: =O8*salary_data*1*(1+salary_escalation)^1*(1+bhxh_rate) -> 106.92 | P18: =P8*salary_data*1*(1+salary_escalation)^1*(1+bhxh_rate) -> 106.92 | ... T18: =T8*salary_data*1*(1+salary_escalation)^1*(1+bhxh_rate) -> 106.92 | U18: =U8*salary_data*1*(1+salary_escalation)^2*(1+bhxh_rate) -> 176.418 | V18: =V8*salary_data*1*(1+salary_escalation)^2*(1+bhxh_rate) -> 176.418 | W18: =W8*salary_data*1*(1+salary_escalation)^2*(1+bhxh_rate) -> 176.418 | X18: =X8*salary_data*1*(1+salary_escalation)^2*(1+bhxh_rate) -> 176.418 | Y18: =Y8*salary_data*1*(1+salary_escalation)^2*(1+bhxh_rate) -> 176.418 | Z18: =Z8*salary_data*1*(1+salary_escalation)^2*(1+bhxh_rate) -> 176.418 | AA18: =AA8*salary_data*1*(1+salary_escalation)^2*(1+bhxh_rate) -> 176.418 | AB18: =AB8*salary_data*1*(1+salary_escalation)^2*(1+bhxh_rate) -> 176.418 | ... AF18: =AF8*salary_data*1*(1+salary_escalation)^2*(1+bhxh_rate) -> 176.418 | AG18: =AG8*salary_data*3*(1+salary_escalation)^3*(1+bhxh_rate) -> 776.2392 | AH18: =AH8*salary_data*3*(1+salary_escalation)^3*(1+bhxh_rate) -> 776.2392 | AI18: =AI8*salary_data*3*(1+salary_escalation)^3*(1+bhxh_rate) -> 776.2392 | AJ18: =AJ8*salary_data*3*(1+salary_escalation)^3*(1+bhxh_rate) -> 776.2392 | AK18: =AK8*salary_data*3*(1+salary_escalation)^4*(1+bhxh_rate) -> 1067.3289 | AL18: =AL8*salary_data*3*(1+salary_escalation)^4*(1+bhxh_rate) -> 1067.3289 | AM18: =AM8*salary_data*3*(1+salary_escalation)^4*(1+bhxh_rate) -> 1067.3289 | AN18: =AN8*salary_data*3*(1+salary_escalation)^4*(1+bhxh_rate) -> 1067.3289 | AO18: =AO8*salary_data*3*(1+salary_escalation)^5*(1+bhxh_rate) -> 1408.8741 | AP18: =AP8*salary_data*3*(1+salary_escalation)^5*(1+bhxh_rate) -> 1408.8741 | AQ18: =AQ8*salary_data*3*(1+salary_escalation)^5*(1+bhxh_rate) -> 1408.8741 | AR18: =AR8*salary_data*3*(1+salary_escalation)^5*(1+bhxh_rate) -> 1408.8741
A19: TOTAL SALARY | B19: M VND | C19: =C15+C16+C17+C18 -> 668.25 | D19: =D15+D16+D17+D18 -> 668.25 | E19: =E15+E16+E17+E18 -> 692.55 | F19: =F15+F16+F17+F18 -> 692.55 | G19: =G15+G16+G17+G18 -> 692.55 | H19: =H15+H16+H17+H18 -> 692.55 | I19: =I15+I16+I17+I18 -> 868.725 | J19: =J15+J16+J17+J18 -> 895.455 | ... AR19: =AR15+AR16+AR17+AR18 -> 9040.2758
A20: Recruitment | B20: M VND | C20: =C12*30*12*recruit_cost_pct -> 1152 | D20: =D12*30*12*recruit_cost_pct -> 0 | E20: =E12*30*12*recruit_cost_pct -> 72 | F20: =F12*30*12*recruit_cost_pct -> 0 | G20: =G12*30*12*recruit_cost_pct -> 0 | H20: =H12*30*12*recruit_cost_pct -> 0 | I20: =I12*30*12*recruit_cost_pct -> 144 | J20: =J12*30*12*recruit_cost_pct -> 72 | ... AR20: =AR12*30*12*recruit_cost_pct -> 0
A21: TOTAL HR COST | B21: M VND | C21: =C19+C20 -> 1820.25 | D21: =D19+D20 -> 668.25 | E21: =E19+E20 -> 764.55 | F21: =F19+F20 -> 692.55 | G21: =G19+G20 -> 692.55 | H21: =H19+H20 -> 692.55 | I21: =I19+I20 -> 1012.725 | J21: =J19+J20 -> 967.455 | ... AR21: =AR19+AR20 -> 9040.2758

Sheet Market Sizing
A1: MARKET SIZING & ADOPTION
A3: Period index | B3: idx | C3: 0 | D3: 1 | E3: 2 | F3: 3 | G3: 4 | H3: 5 | I3: 6 | J3: 7 | K3: 8 | L3: 9 | M3: 10 | N3: 11 | O3: 12 | P3: 13 | Q3: 14 | R3: 15 | S3: 16 | T3: 17 | U3: 18 | V3: 19 | W3: 20 | X3: 21 | Y3: 22 | Z3: 23 | AA3: 24 | AB3: 25 | AC3: 26 | AD3: 27 | AE3: 28 | AF3: 29 | AG3: 30 | AH3: 31 | AI3: 32 | AJ3: 33 | AK3: 34 | AL3: 35 | AM3: 36 | AN3: 37 | AO3: 38 | AP3: 39 | AQ3: 40 | AR3: 41
A4: Year fraction | B4: year | C4: =base_year+(start_month-1+C3)/12 -> 2025.5 | D4: =base_year+(start_month-1+D3)/12 -> 2025.5833 | E4: =base_year+(start_month-1+E3)/12 -> 2025.6667 | F4: =base_year+(start_month-1+F3)/12 -> 2025.75 | G4: =base_year+(start_month-1+G3)/12 -> 2025.8333 | H4: =base_year+(start_month-1+H3)/12 -> 2025.9167 | I4: =base_year+(start_month-1+I3)/12 -> 2026 | J4: =base_year+(start_month-1+J3)/12 -> 2026.0833 | ... AF4: =base_year+(start_month-1+AF3)/12 -> 2027.9167 | AG4: =2028+(1-0.5)/12 -> 2028.0417 | AH4: =2028+(4-0.5)/12 -> 2028.2917 | AI4: =2028+(7-0.5)/12 -> 2028.5417 | AJ4: =2028+(10-0.5)/12 -> 2028.7917 | AK4: =2028+(13-0.5)/12 -> 2029.0417 | AL4: =2028+(16-0.5)/12 -> 2029.2917 | AM4: =2028+(19-0.5)/12 -> 2029.5417 | AN4: =2028+(22-0.5)/12 -> 2029.7917 | AO4: =2028+(25-0.5)/12 -> 2030.0417 | AP4: =2028+(28-0.5)/12 -> 2030.2917 | AQ4: =2028+(31-0.5)/12 -> 2030.5417 | AR4: =2028+(34-0.5)/12 -> 2030.7917
A5: Years from base | B5: yrs | C5: =FLOOR(C4-base_year,1) -> 0 | D5: =FLOOR(D4-base_year,1) -> 0 | E5: =FLOOR(E4-base_year,1) -> 0 | F5: =FLOOR(F4-base_year,1) -> 0 | G5: =FLOOR(G4-base_year,1) -> 0 | H5: =FLOOR(H4-base_year,1) -> 0 | I5: =FLOOR(I4-base_year,1) -> 1 | J5: =FLOOR(J4-base_year,1) -> 1 | ... AR5: =FLOOR(AR4-base_year,1) -> 5
A6: Period divisor | B6: div | C6: 12 | D6: 12 | E6: 12 | F6: 12 | G6: 12 | H6: 12 | I6: 12 | J6: 12 | K6: 12 | L6: 12 | M6: 12 | N6: 12 | O6: 12 | P6: 12 | Q6: 12 | R6: 12 | S6: 12 | T6: 12 | U6: 12 | V6: 12 | W6: 12 | X6: 12 | Y6: 12 | Z6: 12 | AA6: 12 | AB6: 12 | AC6: 12 | AD6: 12 | AE6: 12 | AF6: 12 | AG6: 4 | AH6: 4 | AI6: 4 | AJ6: 4 | AK6: 4 | AL6: 4 | AM6: 4 | AN6: 4 | AO6: 4 | AP6: 4 | AQ6: 4 | AR6: 4
A7: Months in period | B7: mon | C7: 1 | D7: 1 | E7: 1 | F7: 1 | G7: 1 | H7: 1 | I7: 1 | J7: 1 | K7: 1 | L7: 1 | M7: 1 | N7: 1 | O7: 1 | P7: 1 | Q7: 1 | R7: 1 | S7: 1 | T7: 1 | U7: 1 | V7: 1 | W7: 1 | X7: 1 | Y7: 1 | Z7: 1 | AA7: 1 | AB7: 1 | AC7: 1 | AD7: 1 | AE7: 1 | AF7: 1 | AG7: 3 | AH7: 3 | AI7: 3 | AJ7: 3 | AK7: 3 | AL7: 3 | AM7: 3 | AN7: 3 | AO7: 3 | AP7: 3 | AQ7: 3 | AR7: 3
A9: Metric | B9: Unit | C9: Jul 2025 | D9: Aug 2025 | E9: Sep 2025 | F9: Oct 2025 | G9: Nov 2025 | H9: Dec 2025 | I9: Jan 2026 | J9: Feb 2026 | K9: Mar 2026 | L9: Apr 2026 | M9: May 2026 | N9: Jun 2026 | O9: Jul 2026 | P9: Aug 2026 | Q9: Sep 2026 | R9: Oct 2026 | S9: Nov 2026 | T9: Dec 2026 | U9: Jan 2027 | V9: Feb 2027 | W9: Mar 2027 | X9: Apr 2027 | Y9: May 2027 | Z9: Jun 2027 | AA9: Jul 2027 | AB9: Aug 2027 | AC9: Sep 2027 | AD9: Oct 2027 | AE9: Nov 2027 | AF9: Dec 2027 | AG9: Q1 2028 | AH9: Q2 2028 | AI9: Q3 2028 | AJ9: Q4 2028 | AK9: Q1 2029 | AL9: Q2 2029 | AM9: Q3 2029 | AN9: Q4 2029 | AO9: Q1 2030 | AP9: Q2 2030 | AQ9: Q3 2030 | AR9: Q4 2030
A10: E-commerce tourism market | B10: Bn VND | C10: =ecom_market_base*(1+ecom_growth_rate)^C5/C6 -> 6875 | D10: =ecom_market_base*(1+ecom_growth_rate)^D5/D6 -> 6875 | E10: =ecom_market_base*(1+ecom_growth_rate)^E5/E6 -> 6875 | F10: =ecom_market_base*(1+ecom_growth_rate)^F5/F6 -> 6875 | G10: =ecom_market_base*(1+ecom_growth_rate)^G5/G6 -> 6875 | H10: =ecom_market_base*(1+ecom_growth_rate)^H5/H6 -> 6875 | I10: =ecom_market_base*(1+ecom_growth_rate)^I5/I6 -> 7425 | J10: =ecom_market_base*(1+ecom_growth_rate)^J5/J6 -> 7425 | ... AR10: =ecom_market_base*(1+ecom_growth_rate)^AR5/AR6 -> 30304.892
A12: S-CURVE ADOPTION
A13: Gross enterprises | B13: cnt | C13: =MAX(pilot_count,adoption_max/(1+EXP(-adoption_steepness*(C4-adoption_midpoint)))) -> 114.41936 | D13: =MAX(pilot_count,adoption_max/(1+EXP(-adoption_steepness*(D4-adoption_midpoint)))) -> 122.42168 | E13: =MAX(pilot_count,adoption_max/(1+EXP(-adoption_steepness*(E4-adoption_midpoint)))) -> 130.91619 | F13: =MAX(pilot_count,adoption_max/(1+EXP(-adoption_steepness*(F4-adoption_midpoint)))) -> 139.92356 | G13: =MAX(pilot_count,adoption_max/(1+EXP(-adoption_steepness*(G4-adoption_midpoint)))) -> 149.46403 | H13: =MAX(pilot_count,adoption_max/(1+EXP(-adoption_steepness*(H4-adoption_midpoint)))) -> 159.55709 | I13: =MAX(pilot_count,adoption_max/(1+EXP(-adoption_steepness*(I4-adoption_midpoint)))) -> 170.22128 | J13: =MAX(pilot_count,adoption_max/(1+EXP(-adoption_steepness*(J4-adoption_midpoint)))) -> 181.4739 | ... AR13: =MAX(pilot_count,adoption_max/(1+EXP(-adoption_steepness*(AR4-adoption_midpoint)))) -> 1110.0162
A14: Churned | B14: cnt | C14: =0 -> 0 | D14: =ROUND(D13*churn_rate/D6,0) -> 2 | E14: =ROUND(E13*churn_rate/E6,0) -> 2 | F14: =ROUND(F13*churn_rate/F6,0) -> 2 | G14: =ROUND(G13*churn_rate/G6,0) -> 2 | H14: =ROUND(H13*churn_rate/H6,0) -> 3 | I14: =ROUND(I13*churn_rate/I6,0) -> 3 | J14: =ROUND(J13*churn_rate/J6,0) -> 3 | K14: =ROUND(K13*churn_rate/K6,0) -> 3 | ... AR14: =ROUND(AR13*churn_rate/AR6,0) -> 56
A15: Net active enterprises | B15: cnt | C15: =C13-C14 -> 114.41936 | D15: =D13-D14 -> 120.42168 | E15: =E13-E14 -> 128.91619 | F15: =F13-F14 -> 137.92356 | G15: =G13-G14 -> 147.46403 | H15: =H13-H14 -> 156.55709 | I15: =I13-I14 -> 167.22128 | J15: =J13-J14 -> 178.4739 | ... AR15: =AR13-AR14 -> 1054.0162
A16: New enterprises | B16: cnt | C16: =C15 -> 114.41936 | D16: =MAX(0,D15-C15) -> 6.0023251 | E16: =MAX(0,E15-D15) -> 8.4945024 | F16: =MAX(0,F15-E15) -> 9.0073776 | G16: =MAX(0,G15-F15) -> 9.5404668 | H16: =MAX(0,H15-G15) -> 9.0930584 | I16: =MAX(0,I15-H15) -> 10.66419 | J16: =MAX(0,J15-I15) -> 11.252625 | K16: =MAX(0,K15-J15) -> 11.856836 | ... AR16: =MAX(0,AR15-AQ15) -> 18.612393
A17: VCR (M records) | B17: M | C17: =C15*vcr_per_enterprise*C7/1000000 -> 1.1441936 | D17: =D15*vcr_per_enterprise*D7/1000000 -> 1.2042168 | E17: =E15*vcr_per_enterprise*E7/1000000 -> 1.2891619 | F17: =F15*vcr_per_enterprise*F7/1000000 -> 1.3792356 | G17: =G15*vcr_per_enterprise*G7/1000000 -> 1.4746403 | H17: =H15*vcr_per_enterprise*H7/1000000 -> 1.5655709 | I17: =I15*vcr_per_enterprise*I7/1000000 -> 1.6722128 | J17: =J15*vcr_per_enterprise*J7/1000000 -> 1.784739 | ... AR17: =AR15*vcr_per_enterprise*AR7/1000000 -> 31.620485

Sheet Revenue Schedule
A1: REVENUE SCHEDULE (M VND)
A3: Item | B3: Unit | C3: Jul 2025 | D3: Aug 2025 | E3: Sep 2025 | F3: Oct 2025 | G3: Nov 2025 | H3: Dec 2025 | I3: Jan 2026 | J3: Feb 2026 | K3: Mar 2026 | L3: Apr 2026 | M3: May 2026 | N3: Jun 2026 | O3: Jul 2026 | P3: Aug 2026 | Q3: Sep 2026 | R3: Oct 2026 | S3: Nov 2026 | T3: Dec 2026 | U3: Jan 2027 | V3: Feb 2027 | W3: Mar 2027 | X3: Apr 2027 | Y3: May 2027 | Z3: Jun 2027 | AA3: Jul 2027 | AB3: Aug 2027 | AC3: Sep 2027 | AD3: Oct 2027 | AE3: Nov 2027 | AF3: Dec 2027 | AG3: Q1 2028 | AH3: Q2 2028 | AI3: Q3 2028 | AJ3: Q4 2028 | AK3: Q1 2029 | AL3: Q2 2029 | AM3: Q3 2029 | AN3: Q4 2029 | AO3: Q1 2030 | AP3: Q2 2030 | AQ3: Q3 2030 | AR3: Q4 2030
A4: STAGE 1
A5: Certification fees | B5: M VND | C5: =IF('Market Sizing'!C3>=months_to_first_revenue,1,0)*'Market Sizing'!C15*cert_fee_yr1*(1+cert_fee_escalation)^'Market Sizing'!C5/'Market Sizing'!C6 -> 0 | D5: =IF('Market Sizing'!D3>=months_to_first_revenue,1,0)*'Market Sizing'!D15*cert_fee_yr1*(1+cert_fee_escalation)^'Market Sizing'!D5/'Market Sizing'!D6 -> 0 | E5: =IF('Market Sizing'!E3>=months_to_first_revenue,1,0)*'Market Sizing'!E15*cert_fee_yr1*(1+cert_fee_escalation)^'Market Sizing'!E5/'Market Sizing'!E6 -> 0 | F5: =IF('Market Sizing'!F3>=months_to_first_revenue,1,0)*'Market Sizing'!F15*cert_fee_yr1*(1+cert_fee_escalation)^'Market Sizing'!F5/'Market Sizing'!F6 -> 0 | G5: =IF('Market Sizing'!G3>=months_to_first_revenue,1,0)*'Market Sizing'!G15*cert_fee_yr1*(1+cert_fee_escalation)^'Market Sizing'!G5/'Market Sizing'!G6 -> 0 | H5: =IF('Market Sizing'!H3>=months_to_first_revenue,1,0)*'Market Sizing'!H15*cert_fee_yr1*(1+cert_fee_escalation)^'Market Sizing'!H5/'Market Sizing'!H6 -> 0 | I5: =IF('Market Sizing'!I3>=months_to_first_revenue,1,0)*'Market Sizing'!I15*cert_fee_yr1*(1+cert_fee_escalation)^'Market Sizing'!I5/'Market Sizing'!I6 -> 0 | J5: =IF('Market Sizing'!J3>=months_to_first_revenue,1,0)*'Market Sizing'!J15*cert_fee_yr1*(1+cert_fee_escalation)^'Market Sizing'!J5/'Market Sizing'!J6 -> 0 | ... AR5: =IF('Market Sizing'!AR3>=months_to_first_revenue,1,0)*'Market Sizing'!AR15*cert_fee_yr1*(1+cert_fee_escalation)^'Market Sizing'!AR5/'Market Sizing'!AR6 -> 8407.6339
A6: Training | B6: M VND | C6: =IF('Market Sizing'!C3>=months_to_first_revenue,1,0)*'Market Sizing'!C15*training_pct*training_fee/'Market Sizing'!C6 -> 0 | D6: =IF('Market Sizing'!D3>=months_to_first_revenue,1,0)*'Market Sizing'!D15*training_pct*training_fee/'Market Sizing'!D6 -> 0 | E6: =IF('Market Sizing'!E3>=months_to_first_revenue,1,0)*'Market Sizing'!E15*training_pct*training_fee/'Market Sizing'!E6 -> 0 | F6: =IF('Market Sizing'!F3>=months_to_first_revenue,1,0)*'Market Sizing'!F15*training_pct*training_fee/'Market Sizing'!F6 -> 0 | G6: =IF('Market Sizing'!G3>=months_to_first_revenue,1,0)*'Market Sizing'!G15*training_pct*training_fee/'Market Sizing'!G6 -> 0 | H6: =IF('Market Sizing'!H3>=months_to_first_revenue,1,0)*'Market Sizing'!H15*training_pct*training_fee/'Market Sizing'!H6 -> 0 | I6: =IF('Market Sizing'!I3>=months_to_first_revenue,1,0)*'Market Sizing'!I15*training_pct*training_fee/'Market Sizing'!I6 -> 0 | J6: =IF('Market Sizing'!J3>=months_to_first_revenue,1,0)*'Market Sizing'!J15*training_pct*training_fee/'Market Sizing'!J6 -> 0 | ... AR6: =IF('Market Sizing'!AR3>=months_to_first_revenue,1,0)*'Market Sizing'!AR15*training_pct*training_fee/'Market Sizing'!AR6 -> 1185.7682
A7: Audit fees | B7: M VND | C7: =IF('Market Sizing'!C3>=months_to_first_revenue,1,0)*'Market Sizing'!C15*audit_fee/'Market Sizing'!C6 -> 0 | D7: =IF('Market Sizing'!D3>=months_to_first_revenue,1,0)*'Market Sizing'!D15*audit_fee/'Market Sizing'!D6 -> 0 | E7: =IF('Market Sizing'!E3>=months_to_first_revenue,1,0)*'Market Sizing'!E15*audit_fee/'Market Sizing'!E6 -> 0 | F7: =IF('Market Sizing'!F3>=months_to_first_revenue,1,0)*'Market Sizing'!F15*audit_fee/'Market Sizing'!F6 -> 0 | G7: =IF('Market Sizing'!G3>=months_to_first_revenue,1,0)*'Market Sizing'!G15*audit_fee/'Market Sizing'!G6 -> 0 | H7: =IF('Market Sizing'!H3>=months_to_first_revenue,1,0)*'Market Sizing'!H15*audit_fee/'Market Sizing'!H6 -> 0 | I7: =IF('Market Sizing'!I3>=months_to_first_revenue,1,0)*'Market Sizing'!I15*audit_fee/'Market Sizing'!I6 -> 0 | J7: =IF('Market Sizing'!J3>=months_to_first_revenue,1,0)*'Market Sizing'!J15*audit_fee/'Market Sizing'!J6 -> 0 | ... AR7: =IF('Market Sizing'!AR3>=months_to_first_revenue,1,0)*'Market Sizing'!AR15*audit_fee/'Market Sizing'!AR6 -> 2635.0405
A8: Subtotal Stage 1 | C8: =SUM(C5:C7) -> 0 | D8: =SUM(D5:D7) -> 0 | E8: =SUM(E5:E7) -> 0 | F8: =SUM(F5:F7) -> 0 | G8: =SUM(G5:G7) -> 0 | H8: =SUM(H5:H7) -> 0 | I8: =SUM(I5:I7) -> 0 | J8: =SUM(J5:J7) -> 0 | ... AR8: =SUM(AR5:AR7) -> 12228.443
A10: STAGE 2 (gated)
A11: Transaction fees | B11: M VND | C11: =IF(AND(IF('Market Sizing'!C3>=months_to_first_revenue,1,0)=1,'Market Sizing'!C15>=stage2_gate),'Market Sizing'!C10*platform_market_share*tx_take_rate*1000,0) -> 0 | D11: =IF(AND(IF('Market Sizing'!D3>=months_to_first_revenue,1,0)=1,'Market Sizing'!D15>=stage2_gate),'Market Sizing'!D10*platform_market_share*tx_take_rate*1000,0) -> 0 | E11: =IF(AND(IF('Market Sizing'!E3>=months_to_first_revenue,1,0)=1,'Market Sizing'!E15>=stage2_gate),'Market Sizing'!E10*platform_market_share*tx_take_rate*1000,0) -> 0 | F11: =IF(AND(IF('Market Sizing'!F3>=months_to_first_revenue,1,0)=1,'Market Sizing'!F15>=stage2_gate),'Market Sizing'!F10*platform_market_share*tx_take_rate*1000,0) -> 0 | G11: =IF(AND(IF('Market Sizing'!G3>=months_to_first_revenue,1,0)=1,'Market Sizing'!G15>=stage2_gate),'Market Sizing'!G10*platform_market_share*tx_take_rate*1000,0) -> 0 | H11: =IF(AND(IF('Market Sizing'!H3>=months_to_first_revenue,1,0)=1,'Market Sizing'!H15>=stage2_gate),'Market Sizing'!H10*platform_market_share*tx_take_rate*1000,0) -> 0 | I11: =IF(AND(IF('Market Sizing'!I3>=months_to_first_revenue,1,0)=1,'Market Sizing'!I15>=stage2_gate),'Market Sizing'!I10*platform_market_share*tx_take_rate*1000,0) -> 0 | J11: =IF(AND(IF('Market Sizing'!J3>=months_to_first_revenue,1,0)=1,'Market Sizing'!J15>=stage2_gate),'Market Sizing'!J10*platform_market_share*tx_take_rate*1000,0) -> 0 | ... AR11: =IF(AND(IF('Market Sizing'!AR3>=months_to_first_revenue,1,0)=1,'Market Sizing'!AR15>=stage2_gate),'Market Sizing'!AR10*platform_market_share*tx_take_rate*1000,0) -> 12121.957
A12: DaaS | B12: M VND | C12: =IF(AND(IF('Market Sizing'!C3>=months_to_first_revenue,1,0)=1,'Market Sizing'!C15>=stage2_gate),'Market Sizing'!C17*daas_price,0) -> 0 | D12: =IF(AND(IF('Market Sizing'!D3>=months_to_first_revenue,1,0)=1,'Market Sizing'!D15>=stage2_gate),'Market Sizing'!D17*daas_price,0) -> 0 | E12: =IF(AND(IF('Market Sizing'!E3>=months_to_first_revenue,1,0)=1,'Market Sizing'!E15>=stage2_gate),'Market Sizing'!E17*daas_price,0) -> 0 | F12: =IF(AND(IF('Market Sizing'!F3>=months_to_first_revenue,1,0)=1,'Market Sizing'!F15>=stage2_gate),'Market Sizing'!F17*daas_price,0) -> 0 | G12: =IF(AND(IF('Market Sizing'!G3>=months_to_first_revenue,1,0)=1,'Market Sizing'!G15>=stage2_gate),'Market Sizing'!G17*daas_price,0) -> 0 | H12: =IF(AND(IF('Market Sizing'!H3>=months_to_first_revenue,1,0)=1,'Market Sizing'!H15>=stage2_gate),'Market Sizing'!H17*daas_price,0) -> 0 | I12: =IF(AND(IF('Market Sizing'!I3>=months_to_first_revenue,1,0)=1,'Market Sizing'!I15>=stage2_gate),'Market Sizing'!I17*daas_price,0) -> 0 | J12: =IF(AND(IF('Market Sizing'!J3>=months_to_first_revenue,1,0)=1,'Market Sizing'!J15>=stage2_gate),'Market Sizing'!J17*daas_price,0) -> 0 | ... AR12: =IF(AND(IF('Market Sizing'!AR3>=months_to_first_revenue,1,0)=1,'Market Sizing'!AR15>=stage2_gate),'Market Sizing'!AR17*daas_price,0) -> 948.61456
A13: Advertising | B13: M VND | C13: =IF(AND(IF('Market Sizing'!C3>=months_to_first_revenue,1,0)=1,'Market Sizing'!C15>=stage2_gate),ad_impressions_base*'Market Sizing'!C7*'Market Sizing'!C15/1000*ad_cpm/1000,0) -> 0 | D13: =IF(AND(IF('Market Sizing'!D3>=months_to_first_revenue,1,0)=1,'Market Sizing'!D15>=stage2_gate),ad_impressions_base*'Market Sizing'!D7*'Market Sizing'!D15/1000*ad_cpm/1000,0) -> 0 | E13: =IF(AND(IF('Market Sizing'!E3>=months_to_first_revenue,1,0)=1,'Market Sizing'!E15>=stage2_gate),ad_impressions_base*'Market Sizing'!E7*'Market Sizing'!E15/1000*ad_cpm/1000,0) -> 0 | F13: =IF(AND(IF('Market Sizing'!F3>=months_to_first_revenue,1,0)=1,'Market Sizing'!F15>=stage2_gate),ad_impressions_base*'Market Sizing'!F7*'Market Sizing'!F15/1000*ad_cpm/1000,0) -> 0 | G13: =IF(AND(IF('Market Sizing'!G3>=months_to_first_revenue,1,0)=1,'Market Sizing'!G15>=stage2_gate),ad_impressions_base*'Market Sizing'!G7*'Market Sizing'!G15/1000*ad_cpm/1000,0) -> 0 | H13: =IF(AND(IF('Market Sizing'!H3>=months_to_first_revenue,1,0)=1,'Market Sizing'!H15>=stage2_gate),ad_impressions_base*'Market Sizing'!H7*'Market Sizing'!H15/1000*ad_cpm/1000,0) -> 0 | I13: =IF(AND(IF('Market Sizing'!I3>=months_to_first_revenue,1,0)=1,'Market Sizing'!I15>=stage2_gate),ad_impressions_base*'Market Sizing'!I7*'Market Sizing'!I15/1000*ad_cpm/1000,0) -> 0 | J13: =IF(AND(IF('Market Sizing'!J3>=months_to_first_revenue,1,0)=1,'Market Sizing'!J15>=stage2_gate),ad_impressions_base*'Market Sizing'!J7*'Market Sizing'!J15/1000*ad_cpm/1000,0) -> 0 | ... AR13: =IF(AND(IF('Market Sizing'!AR3>=months_to_first_revenue,1,0)=1,'Market Sizing'!AR15>=stage2_gate),ad_impressions_base*'Market Sizing'!AR7*'Market Sizing'!AR15/1000*ad_cpm/1000,0) -> 237.15364
A14: Subtotal Stage 2 | C14: =SUM(C11:C13) -> 0 | D14: =SUM(D11:D13) -> 0 | E14: =SUM(E11:E13) -> 0 | F14: =SUM(F11:F13) -> 0 | G14: =SUM(G11:G13) -> 0 | H14: =SUM(H11:H13) -> 0 | I14: =SUM(I11:I13) -> 0 | J14: =SUM(J11:J13) -> 0 | ... AR14: =SUM(AR11:AR13) -> 13307.725
A16: TOTAL REVENUE | C16: =C8+C14 -> 0 | D16: =D8+D14 -> 0 | E16: =E8+E14 -> 0 | F16: =F8+F14 -> 0 | G16: =G8+G14 -> 0 | H16: =H8+H14 -> 0 | I16: =I8+I14 -> 0 | J16: =J8+J14 -> 0 | ... AR16: =AR8+AR14 -> 25536.167
A18: COGS
A19: Payment processing | B19: M VND | C19: =C11*payment_proc_pct -> 0 | D19: =D11*payment_proc_pct -> 0 | E19: =E11*payment_proc_pct -> 0 | F19: =F11*payment_proc_pct -> 0 | G19: =G11*payment_proc_pct -> 0 | H19: =H11*payment_proc_pct -> 0 | I19: =I11*payment_proc_pct -> 0 | J19: =J11*payment_proc_pct -> 0 | ... AR19: =AR11*payment_proc_pct -> 303.04892
A20: TOTAL COGS | C20: =C19 -> 0 | D20: =D19 -> 0 | E20: =E19 -> 0 | F20: =F19 -> 0 | G20: =G19 -> 0 | H20: =H19 -> 0 | I20: =I19 -> 0 | J20: =J19 -> 0 | ... AR20: =AR19 -> 303.04892

Sheet Cost Schedule
A1: COST SCHEDULE (M VND)
A3: Item | B3: Unit | C3: Jul 2025 | D3: Aug 2025 | E3: Sep 2025 | F3: Oct 2025 | G3: Nov 2025 | H3: Dec 2025 | I3: Jan 2026 | J3: Feb 2026 | K3: Mar 2026 | L3: Apr 2026 | M3: May 2026 | N3: Jun 2026 | O3: Jul 2026 | P3: Aug 2026 | Q3: Sep 2026 | R3: Oct 2026 | S3: Nov 2026 | T3: Dec 2026 | U3: Jan 2027 | V3: Feb 2027 | W3: Mar 2027 | X3: Apr 2027 | Y3: May 2027 | Z3: Jun 2027 | AA3: Jul 2027 | AB3: Aug 2027 | AC3: Sep 2027 | AD3: Oct 2027 | AE3: Nov 2027 | AF3: Dec 2027 | AG3: Q1 2028 | AH3: Q2 2028 | AI3: Q3 2028 | AJ3: Q4 2028 | AK3: Q1 2029 | AL3: Q2 2029 | AM3: Q3 2029 | AN3: Q4 2029 | AO3: Q1 2030 | AP3: Q2 2030 | AQ3: Q3 2030 | AR3: Q4 2030
A4: CAPEX
A5: Platform dev | B5: M VND | C5: =capex_total/6 -> 880 | D5: =capex_total/6 -> 880 | E5: =capex_total/6 -> 880 | F5: =capex_total/6 -> 880 | G5: =capex_total/6 -> 880 | H5: =capex_total/6 -> 880 | I5: =0 -> 0 | J5: =0 -> 0 | K5: =0 -> 0 | L5: =0 -> 0 | M5: =0 -> 0 | N5: =0 -> 0 | O5: =0 -> 0 | P5: =0 -> 0 | ... AR5: =0 -> 0
A6: Maintenance | B6: M VND | C6: =0 -> 0 | D6: =0 -> 0 | E6: =0 -> 0 | F6: =0 -> 0 | G6: =0 -> 0 | H6: =0 -> 0 | I6: =capex_total*capex_maintenance_pct/'Market Sizing'!I6 -> 79.2 | J6: =capex_total*capex_maintenance_pct/'Market Sizing'!J6 -> 79.2 | K6: =capex_total*capex_maintenance_pct/'Market Sizing'!K6 -> 79.2 | L6: =capex_total*capex_maintenance_pct/'Market Sizing'!L6 -> 79.2 | M6: =capex_total*capex_maintenance_pct/'Market Sizing'!M6 -> 79.2 | N6: =capex_total*capex_maintenance_pct/'Market Sizing'!N6 -> 79.2 | O6: =capex_total*capex_maintenance_pct/'Market Sizing'!O6 -> 79.2 | P6: =capex_total*capex_maintenance_pct/'Market Sizing'!P6 -> 79.2 | ... AR6: =capex_total*capex_maintenance_pct/'Market Sizing'!AR6 -> 237.6
A7: TOTAL CAPEX | C7: =C5+C6 -> 880 | D7: =D5+D6 -> 880 | E7: =E5+E6 -> 880 | F7: =F5+F6 -> 880 | G7: =G5+G6 -> 880 | H7: =H5+H6 -> 880 | I7: =I5+I6 -> 79.2 | J7: =J5+J6 -> 79.2 | ... AR7: =AR5+AR6 -> 237.6
A9: OPEX
A10: HR (from HR Plan) | B10: M VND | C10: ='HR Plan'!C21 -> 1820.25 | D10: ='HR Plan'!D21 -> 668.25 | E10: ='HR Plan'!E21 -> 764.55 | F10: ='HR Plan'!F21 -> 692.55 | G10: ='HR Plan'!G21 -> 692.55 | H10: ='HR Plan'!H21 -> 692.55 | I10: ='HR Plan'!I21 -> 1012.725 | J10: ='HR Plan'!J21 -> 967.455 | ... AR10: ='HR Plan'!AR21 -> 9040.2758
A11: Marketing | B11: M VND | C11: =opex_marketing*(1+marketing_growth)^'Market Sizing'!C5/'Market Sizing'!C6*MAX(0.5,1-'Market Sizing'!C15*mkt_efficiency_per_100/100) -> 569.98441 | D11: =opex_marketing*(1+marketing_growth)^'Market Sizing'!D5/'Market Sizing'!D6*MAX(0.5,1-'Market Sizing'!D15*mkt_efficiency_per_100/100) -> 569.28414 | E11: =opex_marketing*(1+marketing_growth)^'Market Sizing'!E5/'Market Sizing'!E6*MAX(0.5,1-'Market Sizing'!E15*mkt_efficiency_per_100/100) -> 568.29311 | F11: =opex_marketing*(1+marketing_growth)^'Market Sizing'!F5/'Market Sizing'!F6*MAX(0.5,1-'Market Sizing'!F15*mkt_efficiency_per_100/100) -> 567.24225 | G11: =opex_marketing*(1+marketing_growth)^'Market Sizing'!G5/'Market Sizing'!G6*MAX(0.5,1-'Market Sizing'!G15*mkt_efficiency_per_100/100) -> 566.1292 | H11: =opex_marketing*(1+marketing_growth)^'Market Sizing'!H5/'Market Sizing'!H6*MAX(0.5,1-'Market Sizing'!H15*mkt_efficiency_per_100/100) -> 565.06834 | I11: =opex_marketing*(1+marketing_growth)^'Market Sizing'!I5/'Market Sizing'!I6*MAX(0.5,1-'Market Sizing'!I15*mkt_efficiency_per_100/100) -> 648.39781 | J11: =opex_marketing*(1+marketing_growth)^'Market Sizing'!J5/'Market Sizing'!J6*MAX(0.5,1-'Market Sizing'!J15*mkt_efficiency_per_100/100) -> 646.88808 | ... AR11: =opex_marketing*(1+marketing_growth)^'Market Sizing'!AR5/'Market Sizing'!AR6*MAX(0.5,1-'Market Sizing'!AR15*mkt_efficiency_per_100/100) -> 2777.874
A12: Branding & events | B12: M VND | C12: =opex_branding/'Market Sizing'!C6 -> 333.33333 | D12: =opex_branding/'Market Sizing'!D6 -> 333.33333 | E12: =opex_branding/'Market Sizing'!E6 -> 333.33333 | F12: =opex_branding/'Market Sizing'!F6 -> 333.33333 | G12: =opex_branding/'Market Sizing'!G6 -> 333.33333 | H12: =opex_branding/'Market Sizing'!H6 -> 333.33333 | I12: =opex_branding/'Market Sizing'!I6 -> 333.33333 | J12: =opex_branding/'Market Sizing'!J6 -> 333.33333 | ... AR12: =opex_branding/'Market Sizing'!AR6 -> 1000
A13: Cloud & infra | B13: M VND | C13: =opex_cloud_base/'Market Sizing'!C6+'Market Sizing'!C17*cloud_per_1M_vcr*('Market Sizing'!C15/100)^(cloud_elasticity-1)+'Market Sizing'!C10*platform_market_share*cloud_gmv_factor -> 348.98683 | D13: =opex_cloud_base/'Market Sizing'!D6+'Market Sizing'!D17*cloud_per_1M_vcr*('Market Sizing'!D15/100)^(cloud_elasticity-1)+'Market Sizing'!D10*platform_market_share*cloud_gmv_factor -> 349.58185 | E13: =opex_cloud_base/'Market Sizing'!E6+'Market Sizing'!E17*cloud_per_1M_vcr*('Market Sizing'!E15/100)^(cloud_elasticity-1)+'Market Sizing'!E10*platform_market_share*cloud_gmv_factor -> 350.43406 | F13: =opex_cloud_base/'Market Sizing'!F6+'Market Sizing'!F17*cloud_per_1M_vcr*('Market Sizing'!F15/100)^(cloud_elasticity-1)+'Market Sizing'!F10*platform_market_share*cloud_gmv_factor -> 351.35007 | G13: =opex_cloud_base/'Market Sizing'!G6+'Market Sizing'!G17*cloud_per_1M_vcr*('Market Sizing'!G15/100)^(cloud_elasticity-1)+'Market Sizing'!G10*platform_market_share*cloud_gmv_factor -> 352.33342 | H13: =opex_cloud_base/'Market Sizing'!H6+'Market Sizing'!H17*cloud_per_1M_vcr*('Market Sizing'!H15/100)^(cloud_elasticity-1)+'Market Sizing'!H10*platform_market_share*cloud_gmv_factor -> 353.2826 | I13: =opex_cloud_base/'Market Sizing'!I6+'Market Sizing'!I17*cloud_per_1M_vcr*('Market Sizing'!I15/100)^(cloud_elasticity-1)+'Market Sizing'!I10*platform_market_share*cloud_gmv_factor -> 359.90987 | J13: =opex_cloud_base/'Market Sizing'!J6+'Market Sizing'!J17*cloud_per_1M_vcr*('Market Sizing'!J15/100)^(cloud_elasticity-1)+'Market Sizing'!J10*platform_market_share*cloud_gmv_factor -> 361.11504 | ... AR13: =opex_cloud_base/'Market Sizing'!AR6+'Market Sizing'!AR17*cloud_per_1M_vcr*('Market Sizing'!AR15/100)^(cloud_elasticity-1)+'Market Sizing'!AR10*platform_market_share*cloud_gmv_factor -> 1520.7102
A14: Security | B14: M VND | C14: =opex_security/'Market Sizing'!C6 -> 20.833333 | D14: =opex_security/'Market Sizing'!D6 -> 20.833333 | E14: =opex_security/'Market Sizing'!E6 -> 20.833333 | F14: =opex_security/'Market Sizing'!F6 -> 20.833333 | G14: =opex_security/'Market Sizing'!G6 -> 20.833333 | H14: =opex_security/'Market Sizing'!H6 -> 20.833333 | I14: =opex_security/'Market Sizing'!I6 -> 20.833333 | J14: =opex_security/'Market Sizing'!J6 -> 20.833333 | ... AR14: =opex_security/'Market Sizing'!AR6 -> 62.5
A15: External affairs | B15: M VND | C15: =opex_external/'Market Sizing'!C6 -> 33.333333 | D15: =opex_external/'Market Sizing'!D6 -> 33.333333 | E15: =opex_external/'Market Sizing'!E6 -> 33.333333 | F15: =opex_external/'Market Sizing'!F6 -> 33.333333 | G15: =opex_external/'Market Sizing'!G6 -> 33.333333 | H15: =opex_external/'Market Sizing'!H6 -> 33.333333 | I15: =opex_external/'Market Sizing'!I6 -> 33.333333 | J15: =opex_external/'Market Sizing'!J6 -> 33.333333 | ... AR15: =opex_external/'Market Sizing'!AR6 -> 100
A16: Legal & compliance | B16: M VND | C16: =opex_legal/'Market Sizing'!C6 -> 20 | D16: =opex_legal/'Market Sizing'!D6 -> 20 | E16: =opex_legal/'Market Sizing'!E6 -> 20 | F16: =opex_legal/'Market Sizing'!F6 -> 20 | G16: =opex_legal/'Market Sizing'!G6 -> 20 | H16: =opex_legal/'Market Sizing'!H6 -> 20 | I16: =opex_legal/'Market Sizing'!I6 -> 20 | J16: =opex_legal/'Market Sizing'!J6 -> 20 | ... AR16: =opex_legal/'Market Sizing'!AR6 -> 60
A17: Pilot eval (Y1) | B17: M VND | C17: =IF('Market Sizing'!C3<months_to_first_revenue,opex_pilot_eval/'Market Sizing'!C6,0) -> 16.666667 | D17: =IF('Market Sizing'!D3<months_to_first_revenue,opex_pilot_eval/'Market Sizing'!D6,0) -> 16.666667 | E17: =IF('Market Sizing'!E3<months_to_first_revenue,opex_pilot_eval/'Market Sizing'!E6,0) -> 16.666667 | F17: =IF('Market Sizing'!F3<months_to_first_revenue,opex_pilot_eval/'Market Sizing'!F6,0) -> 16.666667 | G17: =IF('Market Sizing'!G3<months_to_first_revenue,opex_pilot_eval/'Market Sizing'!G6,0) -> 16.666667 | H17: =IF('Market Sizing'!H3<months_to_first_revenue,opex_pilot_eval/'Market Sizing'!H6,0) -> 16.666667 | I17: =IF('Market Sizing'!I3<months_to_first_revenue,opex_pilot_eval/'Market Sizing'!I6,0) -> 16.666667 | J17: =IF('Market Sizing'!J3<months_to_first_revenue,opex_pilot_eval/'Market Sizing'!J6,0) -> 16.666667 | ... AR17: =IF('Market Sizing'!AR3<months_to_first_revenue,opex_pilot_eval/'Market Sizing'!AR6,0) -> 0
A18: Partner mgmt | B18: M VND | C18: =opex_partner_mgmt/'Market Sizing'!C6 -> 41.666667 | D18: =opex_partner_mgmt/'Market Sizing'!D6 -> 41.666667 | E18: =opex_partner_mgmt/'Market Sizing'!E6 -> 41.666667 | F18: =opex_partner_mgmt/'Market Sizing'!F6 -> 41.666667 | G18: =opex_partner_mgmt/'Market Sizing'!G6 -> 41.666667 | H18: =opex_partner_mgmt/'Market Sizing'!H6 -> 41.666667 | I18: =opex_partner_mgmt/'Market Sizing'!I6 -> 41.666667 | J18: =opex_partner_mgmt/'Market Sizing'!J6 -> 41.666667 | ... AR18: =opex_partner_mgmt/'Market Sizing'!AR6 -> 125
A19: Customer support | B19: M VND | C19: =IF('Market Sizing'!C3>=months_to_first_revenue,1,0)*'Market Sizing'!C15*opex_support_per_ent*IF('Market Sizing'!C15>support_scale_threshold,1-support_discount,1)/'Market Sizing'!C6 -> 0 | D19: =IF('Market Sizing'!D3>=months_to_first_revenue,1,0)*'Market Sizing'!D15*opex_support_per_ent*IF('Market Sizing'!D15>support_scale_threshold,1-support_discount,1)/'Market Sizing'!D6 -> 0 | E19: =IF('Market Sizing'!E3>=months_to_first_revenue,1,0)*'Market Sizing'!E15*opex_support_per_ent*IF('Market Sizing'!E15>support_scale_threshold,1-support_discount,1)/'Market Sizing'!E6 -> 0 | F19: =IF('Market Sizing'!F3>=months_to_first_revenue,1,0)*'Market Sizing'!F15*opex_support_per_ent*IF('Market Sizing'!F15>support_scale_threshold,1-support_discount,1)/'Market Sizing'!F6 -> 0 | G19: =IF('Market Sizing'!G3>=months_to_first_revenue,1,0)*'Market Sizing'!G15*opex_support_per_ent*IF('Market Sizing'!G15>support_scale_threshold,1-support_discount,1)/'Market Sizing'!G6 -> 0 | H19: =IF('Market Sizing'!H3>=months_to_first_revenue,1,0)*'Market Sizing'!H15*opex_support_per_ent*IF('Market Sizing'!H15>support_scale_threshold,1-support_discount,1)/'Market Sizing'!H6 -> 0 | I19: =IF('Market Sizing'!I3>=months_to_first_revenue,1,0)*'Market Sizing'!I15*opex_support_per_ent*IF('Market Sizing'!I15>support_scale_threshold,1-support_discount,1)/'Market Sizing'!I6 -> 0 | J19: =IF('Market Sizing'!J3>=months_to_first_revenue,1,0)*'Market Sizing'!J15*opex_support_per_ent*IF('Market Sizing'!J15>support_scale_threshold,1-support_discount,1)/'Market Sizing'!J6 -> 0 | ... AR19: =IF('Market Sizing'!AR3>=months_to_first_revenue,1,0)*'Market Sizing'!AR15*opex_support_per_ent*IF('Market Sizing'!AR15>support_scale_threshold,1-support_discount,1)/'Market Sizing'!AR6 -> 368.90566
A20: OPEX Subtotal | C20: =SUM(C10:C19) -> 3205.0546 | D20: =SUM(D10:D19) -> 2052.9493 | E20: =SUM(E10:E19) -> 2149.1105 | F20: =SUM(F10:F19) -> 2076.9757 | G20: =SUM(G10:G19) -> 2076.846 | H20: =SUM(H10:H19) -> 2076.7343 | I20: =SUM(I10:I19) -> 2486.866 | J20: =SUM(J10:J19) -> 2441.2915 | ... AR20: =SUM(AR10:AR19) -> 15055.266
A21: Contingency | B21: M VND | C21: =C20*opex_contingency_pct -> 320.50546 | D21: =D20*opex_contingency_pct -> 205.29493 | E21: =E20*opex_contingency_pct -> 214.91105 | F21: =F20*opex_contingency_pct -> 207.69757 | G21: =G20*opex_contingency_pct -> 207.6846 | H21: =H20*opex_contingency_pct -> 207.67343 | I21: =I20*opex_contingency_pct -> 248.6866 | J21: =J20*opex_contingency_pct -> 244.12915 | ... AR21: =AR20*opex_contingency_pct -> 1505.5266
A22: TOTAL OPEX | C22: =C20+C21 -> 3525.56 | D22: =D20+D21 -> 2258.2443 | E22: =E20+E21 -> 2364.0216 | F22: =F20+F21 -> 2284.6732 | G22: =G20+G21 -> 2284.5306 | H22: =H20+H21 -> 2284.4077 | I22: =I20+I21 -> 2735.5526 | J22: =J20+J21 -> 2685.4206 | ... AR22: =AR20+AR21 -> 16560.792
A24: TOTAL COSTS | C24: =C7+C22 -> 4405.56 | D24: =D7+D22 -> 3138.2443 | E24: =E7+E22 -> 3244.0216 | F24: =F7+F22 -> 3164.6732 | G24: =G7+G22 -> 3164.5306 | H24: =H7+H22 -> 3164.4077 | I24: =I7+I22 -> 2814.7526 | J24: =J7+J22 -> 2764.6206 | ... AR24: =AR7+AR22 -> 16798.392

Sheet P&L
A1: P&L (M VND)
A3: Item | B3: Unit | C3: Jul 2025 | D3: Aug 2025 | E3: Sep 2025 | F3: Oct 2025 | G3: Nov 2025 | H3: Dec 2025 | I3: Jan 2026 | J3: Feb 2026 | K3: Mar 2026 | L3: Apr 2026 | M3: May 2026 | N3: Jun 2026 | O3: Jul 2026 | P3: Aug 2026 | Q3: Sep 2026 | R3: Oct 2026 | S3: Nov 2026 | T3: Dec 2026 | U3: Jan 2027 | V3: Feb 2027 | W3: Mar 2027 | X3: Apr 2027 | Y3: May 2027 | Z3: Jun 2027 | AA3: Jul 2027 | AB3: Aug 2027 | AC3: Sep 2027 | AD3: Oct 2027 | AE3: Nov 2027 | AF3: Dec 2027 | AG3: Q1 2028 | AH3: Q2 2028 | AI3: Q3 2028 | AJ3: Q4 2028 | AK3: Q1 2029 | AL3: Q2 2029 | AM3: Q3 2029 | AN3: Q4 2029 | AO3: Q1 2030 | AP3: Q2 2030 | AQ3: Q3 2030 | AR3: Q4 2030
A4: Revenue | C4: ='Revenue Schedule'!C16 -> 0 | D4: ='Revenue Schedule'!D16 -> 0 | E4: ='Revenue Schedule'!E16 -> 0 | F4: ='Revenue Schedule'!F16 -> 0 | G4: ='Revenue Schedule'!G16 -> 0 | H4: ='Revenue Schedule'!H16 -> 0 | I4: ='Revenue Schedule'!I16 -> 0 | J4: ='Revenue Schedule'!J16 -> 0 | ... AR4: ='Revenue Schedule'!AR16 -> 25536.167
A5: COGS | C5: =-'Revenue Schedule'!C20 -> 0 | D5: =-'Revenue Schedule'!D20 -> 0 | E5: =-'Revenue Schedule'!E20 -> 0 | F5: =-'Revenue Schedule'!F20 -> 0 | G5: =-'Revenue Schedule'!G20 -> 0 | H5: =-'Revenue Schedule'!H20 -> 0 | I5: =-'Revenue Schedule'!I20 -> 0 | J5: =-'Revenue Schedule'!J20 -> 0 | ... AR5: =-'Revenue Schedule'!AR20 -> -303.04892
A6: GROSS PROFIT | C6: =C4+C5 -> 0 | D6: =D4+D5 -> 0 | E6: =E4+E5 -> 0 | F6: =F4+F5 -> 0 | G6: =G4+G5 -> 0 | H6: =H4+H5 -> 0 | I6: =I4+I5 -> 0 | J6: =J4+J5 -> 0 | ... AR6: =AR4+AR5 -> 25233.118
A8: OPEX | C8: =-'Cost Schedule'!C22 -> -3525.56 | D8: =-'Cost Schedule'!D22 -> -2258.2443 | E8: =-'Cost Schedule'!E22 -> -2364.0216 | F8: =-'Cost Schedule'!F22 -> -2284.6732 | G8: =-'Cost Schedule'!G22 -> -2284.5306 | H8: =-'Cost Schedule'!H22 -> -2284.4077 | I8: =-'Cost Schedule'!I22 -> -2735.5526 | J8: =-'Cost Schedule'!J22 -> -2685.4206 | ... AR8: =-'Cost Schedule'!AR22 -> -16560.792
A9: EBITDA | C9: =C6+C8 -> -3525.56 | D9: =D6+D8 -> -2258.2443 | E9: =E6+E8 -> -2364.0216 | F9: =F6+F8 -> -2284.6732 | G9: =G6+G8 -> -2284.5306 | H9: =H6+H8 -> -2284.4077 | I9: =I6+I8 -> -2735.5526 | J9: =J6+J8 -> -2685.4206 | ... AR9: =AR6+AR8 -> 8672.3262
A10: Depreciation | C10: =-capex_total/depreciation_years/'Market Sizing'!C6 -> -88 | D10: =-capex_total/depreciation_years/'Market Sizing'!D6 -> -88 | E10: =-capex_total/depreciation_years/'Market Sizing'!E6 -> -88 | F10: =-capex_total/depreciation_years/'Market Sizing'!F6 -> -88 | G10: =-capex_total/depreciation_years/'Market Sizing'!G6 -> -88 | H10: =-capex_total/depreciation_years/'Market Sizing'!H6 -> -88 | I10: =-capex_total/depreciation_years/'Market Sizing'!I6 -> -88 | J10: =-capex_total/depreciation_years/'Market Sizing'!J6 -> -88 | ... AN10: =-capex_total/depreciation_years/'Market Sizing'!AN6 -> -264 | AO10: =0 -> 0 | AP10: =0 -> 0 | AQ10: =0 -> 0 | AR10: =0 -> 0
A11: EBIT | C11: =C9+C10 -> -3613.56 | D11: =D9+D10 -> -2346.2443 | E11: =E9+E10 -> -2452.0216 | F11: =F9+F10 -> -2372.6732 | G11: =G9+G10 -> -2372.5306 | H11: =H9+H10 -> -2372.4077 | I11: =I9+I10 -> -2823.5526 | J11: =J9+J10 -> -2773.4206 | ... AR11: =AR9+AR10 -> 8672.3262
A12: Tax (CIT) | C12: =IF(C11>0,-C11*cit_rate,0) -> 0 | D12: =IF(D11>0,-D11*cit_rate,0) -> 0 | E12: =IF(E11>0,-E11*cit_rate,0) -> 0 | F12: =IF(F11>0,-F11*cit_rate,0) -> 0 | G12: =IF(G11>0,-G11*cit_rate,0) -> 0 | H12: =IF(H11>0,-H11*cit_rate,0) -> 0 | I12: =IF(I11>0,-I11*cit_rate,0) -> 0 | J12: =IF(J11>0,-J11*cit_rate,0) -> 0 | ... AR12: =IF(AR11>0,-AR11*cit_rate,0) -> -1734.4652
A13: NET INCOME | C13: =C11+C12 -> -3613.56 | D13: =D11+D12 -> -2346.2443 | E13: =E11+E12 -> -2452.0216 | F13: =F11+F12 -> -2372.6732 | G13: =G11+G12 -> -2372.5306 | H13: =H11+H12 -> -2372.4077 | I13: =I11+I12 -> -2823.5526 | J13: =J11+J12 -> -2773.4206 | ... AR13: =AR11+AR12 -> 6937.8609
A15: MARGINS
A16: Gross margin | C16: =IF(C4=0,0,C6/C4) -> 0 | D16: =IF(D4=0,0,D6/D4) -> 0 | E16: =IF(E4=0,0,E6/E4) -> 0 | F16: =IF(F4=0,0,F6/F4) -> 0 | G16: =IF(G4=0,0,G6/G4) -> 0 | H16: =IF(H4=0,0,H6/H4) -> 0 | I16: =IF(I4=0,0,I6/I4) -> 0 | J16: =IF(J4=0,0,J6/J4) -> 0 | ... AR16: =IF(AR4=0,0,AR6/AR4) -> 0.98813256
A17: EBITDA margin | C17: =IF(C4=0,0,C9/C4) -> 0 | D17: =IF(D4=0,0,D9/D4) -> 0 | E17: =IF(E4=0,0,E9/E4) -> 0 | F17: =IF(F4=0,0,F9/F4) -> 0 | G17: =IF(G4=0,0,G9/G4) -> 0 | H17: =IF(H4=0,0,H9/H4) -> 0 | I17: =IF(I4=0,0,I9/I4) -> 0 | J17: =IF(J4=0,0,J9/J4) -> 0 | ... AR17: =IF(AR4=0,0,AR9/AR4) -> 0.33960954
A18: Net margin | C18: =IF(C4=0,0,C13/C4) -> 0 | D18: =IF(D4=0,0,D13/D4) -> 0 | E18: =IF(E4=0,0,E13/E4) -> 0 | F18: =IF(F4=0,0,F13/F4) -> 0 | G18: =IF(G4=0,0,G13/G4) -> 0 | H18: =IF(H4=0,0,H13/H4) -> 0 | I18: =IF(I4=0,0,I13/I4) -> 0 | J18: =IF(J4=0,0,J13/J4) -> 0 | ... AR18: =IF(AR4=0,0,AR13/AR4) -> 0.27168764

Sheet Cash Flow
A1: CASH FLOW (M VND)
A3: Item | B3: Unit | C3: Jul 2025 | D3: Aug 2025 | E3: Sep 2025 | F3: Oct 2025 | G3: Nov 2025 | H3: Dec 2025 | I3: Jan 2026 | J3: Feb 2026 | K3: Mar 2026 | L3: Apr 2026 | M3: May 2026 | N3: Jun 2026 | O3: Jul 2026 | P3: Aug 2026 | Q3: Sep 2026 | R3: Oct 2026 | S3: Nov 2026 | T3: Dec 2026 | U3: Jan 2027 | V3: Feb 2027 | W3: Mar 2027 | X3: Apr 2027 | Y3: May 2027 | Z3: Jun 2027 | AA3: Jul 2027 | AB3: Aug 2027 | AC3: Sep 2027 | AD3: Oct 2027 | AE3: Nov 2027 | AF3: Dec 2027 | AG3: Q1 2028 | AH3: Q2 2028 | AI3: Q3 2028 | AJ3: Q4 2028 | AK3: Q1 2029 | AL3: Q2 2029 | AM3: Q3 2029 | AN3: Q4 2029 | AO3: Q1 2030 | AP3: Q2 2030 | AQ3: Q3 2030 | AR3: Q4 2030
A4: Operating CF
A5: Net income | C5: ='P&L'!C13 -> -3613.56 | D5: ='P&L'!D13 -> -2346.2443 | E5: ='P&L'!E13 -> -2452.0216 | F5: ='P&L'!F13 -> -2372.6732 | G5: ='P&L'!G13 -> -2372.5306 | H5: ='P&L'!H13 -> -2372.4077 | I5: ='P&L'!I13 -> -2823.5526 | J5: ='P&L'!J13 -> -2773.4206 | ... AR5: ='P&L'!AR13 -> 6937.8609
A6: Add: D&A | C6: =-'P&L'!C10 -> 88 | D6: =-'P&L'!D10 -> 88 | E6: =-'P&L'!E10 -> 88 | F6: =-'P&L'!F10 -> 88 | G6: =-'P&L'!G10 -> 88 | H6: =-'P&L'!H10 -> 88 | I6: =-'P&L'!I10 -> 88 | J6: =-'P&L'!J10 -> 88 | ... AR6: =-'P&L'!AR10 -> 0
A7: Working capital chg | C7: =-'P&L'!C4*ar_days/365 -> 0 | D7: =-('P&L'!D4-'P&L'!C4)*ar_days/365 -> 0 | E7: =-('P&L'!E4-'P&L'!D4)*ar_days/365 -> 0 | F7: =-('P&L'!F4-'P&L'!E4)*ar_days/365 -> 0 | G7: =-('P&L'!G4-'P&L'!F4)*ar_days/365 -> 0 | H7: =-('P&L'!H4-'P&L'!G4)*ar_days/365 -> 0 | I7: =-('P&L'!I4-'P&L'!H4)*ar_days/365 -> 0 | J7: =-('P&L'!J4-'P&L'!I4)*ar_days/365 -> 0 | K7: =-('P&L'!K4-'P&L'!J4)*ar_days/365 -> 0 | ... AR7: =-('P&L'!AR4-'P&L'!AQ4)*ar_days/365 -> -29.203823
A8: OPERATING CF | C8: =C5+C6+C7 -> -3525.56 | D8: =D5+D6+D7 -> -2258.2443 | E8: =E5+E6+E7 -> -2364.0216 | F8: =F5+F6+F7 -> -2284.6732 | G8: =G5+G6+G7 -> -2284.5306 | H8: =H5+H6+H7 -> -2284.4077 | I8: =I5+I6+I7 -> -2735.5526 | J8: =J5+J6+J7 -> -2685.4206 | ... AR8: =AR5+AR6+AR7 -> 6908.6571
A10: Investing CF
A11: CAPEX | C11: =-'Cost Schedule'!C7 -> -880 | D11: =-'Cost Schedule'!D7 -> -880 | E11: =-'Cost Schedule'!E7 -> -880 | F11: =-'Cost Schedule'!F7 -> -880 | G11: =-'Cost Schedule'!G7 -> -880 | H11: =-'Cost Schedule'!H7 -> -880 | I11: =-'Cost Schedule'!I7 -> -79.2 | J11: =-'Cost Schedule'!J7 -> -79.2 | ... AR11: =-'Cost Schedule'!AR7 -> -237.6
A12: INVESTING CF | C12: =C11 -> -880 | D12: =D11 -> -880 | E12: =E11 -> -880 | F12: =F11 -> -880 | G12: =G11 -> -880 | H12: =H11 -> -880 | I12: =I11 -> -79.2 | J12: =J11 -> -79.2 | ... AR12: =AR11 -> -237.6
A14: FREE CASH FLOW | C14: =C8+C12 -> -4405.56 | D14: =D8+D12 -> -3138.2443 | E14: =E8+E12 -> -3244.0216 | F14: =F8+F12 -> -3164.6732 | G14: =G8+G12 -> -3164.5306 | H14: =H8+H12 -> -3164.4077 | I14: =I8+I12 -> -2814.7526 | J14: =J8+J12 -> -2764.6206 | ... AR14: =AR8+AR12 -> 6671.0571
A15: Cumulative CF | C15: =C14 -> -4405.56 | D15: =C15+D14 -> -7543.8043 | E15: =D15+E14 -> -10787.826 | F15: =E15+F14 -> -13952.499 | G15: =F15+G14 -> -17117.03 | H15: =G15+H14 -> -20281.437 | I15: =H15+I14 -> -23096.19 | J15: =I15+J14 -> -25860.811 | K15: =J15+K14 -> -28545.896 | ... AR15: =AQ15+AR14 -> 38840.51

Sheet DCF & Returns
A1: DCF & RETURNS
A3: Annual FCF
A4: Year | B4: FCF (M VND)
A5: H2_2025 | B5: =SUM('Cash Flow'!C14:H14) -> -20281.437
A6: Y2026 | B6: =SUM('Cash Flow'!I14:T14) -> -20865.533
A7: Y2027 | B7: =SUM('Cash Flow'!U14:AF14) -> 13929.72
A8: Y2028 | B8: =SUM('Cash Flow'!AG14:AJ14) -> 17847.237
A9: Y2029 | B9: =SUM('Cash Flow'!AK14:AN14) -> 23167.173
A10: Y2030 | B10: =SUM('Cash Flow'!AO14:AR14) -> 25043.351
A12: Metrics
A13: NPV | B13: =NPV(discount_rate,B6:B10)+B5 -> 9539.2161
A14: IRR | B14: =IFERROR(IRR(B5:B10),"N/A") -> 0.2361664
A15: Max cash burn | B15: =-MIN('Cash Flow'!C15:'Cash Flow'!AR15) -> 42838.648
A16: ROI | B16: =IF(B15=0,0,('Cash Flow'!AR15+B15)/B15) -> 1.9066698
A17: CIT rate | B17: =cit_rate -> 0.2
A18: WACC | B18: =discount_rate -> 0.15

Sheet Sensitivity
A1: SENSITIVITY ANALYSIS — v6 (computed NPV)
A3: ONE-AT-A-TIME SENSITIVITY — Approximate NPV Impact (Tr VND)
A4: Parameter | B4: -30% | C4: -15% | D4: BASE | E4: +15% | F4: +30% | G4: Value @Base | H4: Impact ↑ or ↓
A5: Max enterprises (adoption_max) | B5: =((((adoption_max*0.7/(1+EXP(-adoption_steepness*(2028-adoption_midpoint)))*(1-churn_rate))*(cert_fee_yr1*(1+cert_fee_escalation)^2.5+training_pct*training_fee+audit_fee)*5)+(IF((adoption_max*0.7/(1+EXP(-adoption_steepness*(2028-adoption_midpoint)))*(1-churn_rate))>=stage2_gate,ecom_market_base*(1+ecom_growth_rate)^4*platform_market_share*tx_take_rate*1000*3,0))-((IF((adoption_max*0.7/(1+EXP(-adoption_steepness*(2028-adoption_midpoint)))*(1-churn_rate))>=stage2_gate,ecom_market_base*(1+ecom_growth_rate)^4*platform_market_share*tx_take_rate*1000*3,0))*payment_proc_pct)-(capex_total+(33*30*12*(1+bhxh_rate)*(1+salary_escalation)^2*5)+(opex_marketing*(1+marketing_growth)^2*5)+(opex_cloud_base*5+(adoption_max*0.7/(1+EXP(-adoption_steepness*(2028-adoption_midpoint)))*(1-churn_rate))*vcr_per_enterprise*12*cloud_per_1M_vcr/1000000*5)+((opex_branding+opex_external+opex_legal+opex_security+opex_partner_mgmt)*5)+(capex_total*capex_maintenance_pct*4)))*(1-cit_rate))/(1+discount_rate)^2.5 -> 8811.528 | C5: =((((adoption_max*0.85/(1+EXP(-adoption_steepness*(2028-adoption_midpoint)))*(1-churn_rate))*(cert_fee_yr1*(1+cert_fee_escalation)^2.5+training_pct*training_fee+audit_fee)*5)+(IF((adoption_max*0.85/(1+EXP(-adoption_steepness*(2028-adoption_midpoint)))*(1-churn_rate))>=stage2_gate,ecom_market_base*(1+ecom_growth_rate)^4*platform_market_share*tx_take_rate*1000*3,0))-((IF((adoption_max*0.85/(1+EXP(-adoption_steepness*(2028-adoption_midpoint)))*(1-churn_rate))>=stage2_gate,ecom_market_base*(1+ecom_growth_rate)^4*platform_market_share*tx_take_rate*1000*3,0))*payment_proc_pct)-(capex_total+(33*30*12*(1+bhxh_rate)*(1+salary_escalation)^2*5)+(opex_marketing*(1+marketing_growth)^2*5)+(opex_cloud_base*5+(adoption_max*0.85/(1+EXP(-adoption_steepness*(2028-adoption_midpoint)))*(1-churn_rate))*vcr_per_enterprise*12*cloud_per_1M_vcr/1000000*5)+((opex_branding+opex_external+opex_legal+opex_security+opex_partner_mgmt)*5)+(capex_total*capex_maintenance_pct*4)))*(1-cit_rate))/(1+discount_rate)^2.5 -> 17296.475 | D5: =((((adoption_max*1/(1+EXP(-adoption_steepness*(2028-adoption_midpoint)))*(1-churn_rate))*(cert_fee_yr1*(1+cert_fee_escalation)^2.5+training_pct*training_fee+audit_fee)*5)+(IF((adoption_max*1/(1+EXP(-adoption_steepness*(2028-adoption_midpoint)))*(1-churn_rate))>=stage2_gate,ecom_market_base*(1+ecom_growth_rate)^4*platform_market_share*tx_take_rate*1000*3,0))-((IF((adoption_max*1/(1+EXP(-adoption_steepness*(2028-adoption_midpoint)))*(1-churn_rate))>=stage2_gate,ecom_market_base*(1+ecom_growth_rate)^4*platform_market_share*tx_take_rate*1000*3,0))*payment_proc_pct)-(capex_total+(33*30*12*(1+bhxh_rate)*(1+salary_escalation)^2*5)+(opex_marketing*(1+marketing_growth)^2*5)+(opex_cloud_base*5+(adoption_max*1/(1+EXP(-adoption_steepness*(2028-adoption_midpoint)))*(1-churn_rate))*vcr_per_enterprise*12*cloud_per_1M_vcr/1000000*5)+((opex_branding+opex_external+opex_legal+opex_security+opex_partner_mgmt)*5)+(capex_total*capex_maintenance_pct*4)))*(1-cit_rate))/(1+discount_rate)^2.5 -> 25781.423 | E5: =((((adoption_max*1.15/(1+EXP(-adoption_steepness*(2028-adoption_midpoint)))*(1-churn_rate))*(cert_fee_yr1*(1+cert_fee_escalation)^2.5+training_pct*training_fee+audit_fee)*5)+(IF((adoption_max*1.15/(1+EXP(-adoption_steepness*(2028-adoption_midpoint)))*(1-churn_rate))>=stage2_gate,ecom_market_base*(1+ecom_growth_rate)^4*platform_market_share*tx_take_rate*1000*3,0))-((IF((adoption_max*1.15/(1+EXP(-adoption_steepness*(2028-adoption_midpoint)))*(1-churn_rate))>=stage2_gate,ecom_market_base*(1+ecom_growth_rate)^4*platform_market_share*tx_take_rate*1000*3,0))*payment_proc_pct)-(capex_total+(33*30*12*(1+bhxh_rate)*(1+salary_escalation)^2*5)+(opex_marketing*(1+marketing_growth)^2*5)+(opex_cloud_base*5+(adoption_max*1.15/(1+EXP(-adoption_steepness*(2028-adoption_midpoint)))*(1-churn_rate))*vcr_per_enterprise*12*cloud_per_1M_vcr/1000000*5)+((opex_branding+opex_external+opex_legal+opex_security+opex_partner_mgmt)*5)+(capex_total*capex_maintenance_pct*4)))*(1-cit_rate))/(1+discount_rate)^2.5 -> 34266.37 | F5: =((((adoption_max*1.3/(1+EXP(-adoption_steepness*(2028-adoption_midpoint)))*(1-churn_rate))*(cert_fee_yr1*(1+cert_fee_escalation)^2.5+training_pct*training_fee+audit_fee)*5)+(IF((adoption_max*1.3/(1+EXP(-adoption_steepness*(2028-adoption_midpoint)))*(1-churn_rate))>=stage2_gate,ecom_market_base*(1+ecom_growth_rate)^4*platform_market_share*tx_take_rate*1000*3,0))-((IF((adoption_max*1.3/(1+EXP(-adoption_steepness*(2028-adoption_midpoint)))*(1-churn_rate))>=stage2_gate,ecom_market_base*(1+ecom_growth_rate)^4*platform_market_share*tx_take_rate*1000*3,0))*payment_proc_pct)-(capex_total+(33*30*12*(1+bhxh_rate)*(1+salary_escalation)^2*5)+(opex_marketing*(1+marketing_growth)^2*5)+(opex_cloud_base*5+(adoption_max*1.3/(1+EXP(-adoption_steepness*(2028-adoption_midpoint)))*(1-churn_rate))*vcr_per_enterprise*12*cloud_per_1M_vcr/1000000*5)+((opex_branding+opex_external+opex_legal+opex_security+opex_partner_mgmt)*5)+(capex_total*capex_maintenance_pct*4)))*(1-cit_rate))/(1+discount_rate)^2.5 -> 42751.317 | G5: =adoption_max -> 1200 | H5: ↑ adoption → ↑ all revenue
A6: Market share (platform_market_share) | B6: =((((adoption_max/(1+EXP(-adoption_steepness*(2028-adoption_midpoint)))*(1-churn_rate))*(cert_fee_yr1*(1+cert_fee_escalation)^2.5+training_pct*training_fee+audit_fee)*5)+(IF((adoption_max/(1+EXP(-adoption_steepness*(2028-adoption_midpoint)))*(1-churn_rate))>=stage2_gate,ecom_market_base*(1+ecom_growth_rate)^4*platform_market_share*0.7*tx_take_rate*1000*3,0))-((IF((adoption_max/(1+EXP(-adoption_steepness*(2028-adoption_midpoint)))*(1-churn_rate))>=stage2_gate,ecom_market_base*(1+ecom_growth_rate)^4*platform_market_share*0.7*tx_take_rate*1000*3,0))*payment_proc_pct)-(capex_total+(33*30*12*(1+bhxh_rate)*(1+salary_escalation)^2*5)+(opex_marketing*(1+marketing_growth)^2*5)+(opex_cloud_base*5+(adoption_max/(1+EXP(-adoption_steepness*(2028-adoption_midpoint)))*(1-churn_rate))*vcr_per_enterprise*12*cloud_per_1M_vcr/1000000*5)+((opex_branding+opex_external+opex_legal+opex_security+opex_partner_mgmt)*5)+(capex_total*capex_maintenance_pct*4)))*(1-cit_rate))/(1+discount_rate)^2.5 -> 3558.4847 | C6: =((((adoption_max/(1+EXP(-adoption_steepness*(2028-adoption_midpoint)))*(1-churn_rate))*(cert_fee_yr1*(1+cert_fee_escalation)^2.5+training_pct*training_fee+audit_fee)*5)+(IF((adoption_max/(1+EXP(-adoption_steepness*(2028-adoption_midpoint)))*(1-churn_rate))>=stage2_gate,ecom_market_base*(1+ecom_growth_rate)^4*platform_market_share*0.85*tx_take_rate*1000*3,0))-((IF((adoption_max/(1+EXP(-adoption_steepness*(2028-adoption_midpoint)))*(1-churn_rate))>=stage2_gate,ecom_market_base*(1+ecom_growth_rate)^4*platform_market_share*0.85*tx_take_rate*1000*3,0))*payment_proc_pct)-(capex_total+(33*30*12*(1+bhxh_rate)*(1+salary_escalation)^2*5)+(opex_marketing*(1+marketing_growth)^2*5)+(opex_cloud_base*5+(adoption_max/(1+EXP(-adoption_steepness*(2028-adoption_midpoint)))*(1-churn_rate))*vcr_per_enterprise*12*cloud_per_1M_vcr/1000000*5)+((opex_branding+opex_external+opex_legal+opex_security+opex_partner_mgmt)*5)+(capex_total*capex_maintenance_pct*4)))*(1-cit_rate))/(1+discount_rate)^2.5 -> 14669.954 | D6: =((((adoption_max/(1+EXP(-adoption_steepness*(2028-adoption_midpoint)))*(1-churn_rate))*(cert_fee_yr1*(1+cert_fee_escalation)^2.5+training_pct*training_fee+audit_fee)*5)+(IF((adoption_max/(1+EXP(-adoption_steepness*(2028-adoption_midpoint)))*(1-churn_rate))>=stage2_gate,ecom_market_base*(1+ecom_growth_rate)^4*platform_market_share*1*tx_take_rate*1000*3,0))-((IF((adoption_max/(1+EXP(-adoption_steepness*(2028-adoption_midpoint)))*(1-churn_rate))>=stage2_gate,ecom_market_base*(1+ecom_growth_rate)^4*platform_market_share*1*tx_take_rate*1000*3,0))*payment_proc_pct)-(capex_total+(33*30*12*(1+bhxh_rate)*(1+salary_escalation)^2*5)+(opex_marketing*(1+marketing_growth)^2*5)+(opex_cloud_base*5+(adoption_max/(1+EXP(-adoption_steepness*(2028-adoption_midpoint)))*(1-churn_rate))*vcr_per_enterprise*12*cloud_per_1M_vcr/1000000*5)+((opex_branding+opex_external+opex_legal+opex_security+opex_partner_mgmt)*5)+(capex_total*capex_maintenance_pct*4)))*(1-cit_rate))/(1+discount_rate)^2.5 -> 25781.423 | E6: =((((adoption_max/(1+EXP(-adoption_steepness*(2028-adoption_midpoint)))*(1-churn_rate))*(cert_fee_yr1*(1+cert_fee_escalation)^2.5+training_pct*training_fee+audit_fee)*5)+(IF((adoption_max/(1+EXP(-adoption_steepness*(2028-adoption_midpoint)))*(1-churn_rate))>=stage2_gate,ecom_market_base*(1+ecom_growth_rate)^4*platform_market_share*1.15*tx_take_rate*1000*3,0))-((IF((adoption_max/(1+EXP(-adoption_steepness*(2028-adoption_midpoint)))*(1-churn_rate))>=stage2_gate,ecom_market_base*(1+ecom_growth_rate)^4*platform_market_share*1.15*tx_take_rate*1000*3,0))*payment_proc_pct)-(capex_total+(33*30*12*(1+bhxh_rate)*(1+salary_escalation)^2*5)+(opex_marketing*(1+marketing_growth)^2*5)+(opex_cloud_base*5+(adoption_max/(1+EXP(-adoption_steepness*(2028-adoption_midpoint)))*(1-churn_rate))*vcr_per_enterprise*12*cloud_per_1M_vcr/1000000*5)+((opex_branding+opex_external+opex_legal+opex_security+opex_partner_mgmt)*5)+(capex_total*capex_maintenance_pct*4)))*(1-cit_rate))/(1+discount_rate)^2.5 -> 36892.892 | F6: =((((adoption_max/(1+EXP(-adoption_steepness*(2028-adoption_midpoint)))*(1-churn_rate))*(cert_fee_yr1*(1+cert_fee_escalation)^2.5+training_pct*training_fee+audit_fee)*5)+(IF((adoption_max/(1+EXP(-adoption_steepness*(2028-adoption_midpoint)))*(1-churn_rate))>=stage2_gate,ecom_market_base*(1+ecom_growth_rate)^4*platform_market_share*1.3*tx_take_rate*1000*3,0))-((IF((adoption_max/(1+EXP(-adoption_steepness*(2028-adoption_midpoint)))*(1-churn_rate))>=stage2_gate,ecom_market_base*(1+ecom_growth_rate)^4*platform_market_share*1.3*tx_take_rate*1000*3,0))*payment_proc_pct)-(capex_total+(33*30*12*(1+bhxh_rate)*(1+salary_escalation)^2*5)+(opex_marketing*(1+marketing_growth)^2*5)+(opex_cloud_base*5+(adoption_max/(1+EXP(-adoption_steepness*(2028-adoption_midpoint)))*(1-churn_rate))*vcr_per_enterprise*12*cloud_per_1M_vcr/1000000*5)+((opex_branding+opex_external+opex_legal+opex_security+opex_partner_mgmt)*5)+(capex_total*capex_maintenance_pct*4)))*(1-cit_rate))/(1+discount_rate)^2.5 -> 48004.361 | G6: =platform_market_share -> 0.02 | H6: ↑ share → ↑ Stage 2 rev
A7: Churn rate | B7: =((((adoption_max/(1+EXP(-adoption_steepness*(2028-adoption_midpoint)))*(1-churn_rate*0.7))*(cert_fee_yr1*(1+cert_fee_escalation)^2.5+training_pct*training_fee+audit_fee)*5)+(IF((adoption_max/(1+EXP(-adoption_steepness*(2028-adoption_midpoint)))*(1-churn_rate*0.7))>=stage2_gate,ecom_market_base*(1+ecom_growth_rate)^4*platform_market_share*tx_take_rate*1000*3,0))-((IF((adoption_max/(1+EXP(-adoption_steepness*(2028-adoption_midpoint)))*(1-churn_rate*0.7))>=stage2_gate,ecom_market_base*(1+ecom_growth_rate)^4*platform_market_share*tx_take_rate*1000*3,0))*payment_proc_pct)-(capex_total+(33*30*12*(1+bhxh_rate)*(1+salary_escalation)^2*5)+(opex_marketing*(1+marketing_growth)^2*5)+(opex_cloud_base*5+(adoption_max/(1+EXP(-adoption_steepness*(2028-adoption_midpoint)))*(1-churn_rate*0.7))*vcr_per_enterprise*12*cloud_per_1M_vcr/1000000*5)+((opex_branding+opex_external+opex_legal+opex_security+opex_partner_mgmt)*5)+(capex_total*capex_maintenance_pct*4)))*(1-cit_rate))/(1+discount_rate)^2.5 -> 30023.896 | C7: =((((adoption_max/(1+EXP(-adoption_steepness*(2028-adoption_midpoint)))*(1-churn_rate*0.85))*(cert_fee_yr1*(1+cert_fee_escalation)^2.5+training_pct*training_fee+audit_fee)*5)+(IF((adoption_max/(1+EXP(-adoption_steepness*(2028-adoption_midpoint)))*(1-churn_rate*0.85))>=stage2_gate,ecom_market_base*(1+ecom_growth_rate)^4*platform_market_share*tx_take_rate*1000*3,0))-((IF((adoption_max/(1+EXP(-adoption_steepness*(2028-adoption_midpoint)))*(1-churn_rate*0.85))>=stage2_gate,ecom_market_base*(1+ecom_growth_rate)^4*platform_market_share*tx_take_rate*1000*3,0))*payment_proc_pct)-(capex_total+(33*30*12*(1+bhxh_rate)*(1+salary_escalation)^2*5)+(opex_marketing*(1+marketing_growth)^2*5)+(opex_cloud_base*5+(adoption_max/(1+EXP(-adoption_steepness*(2028-adoption_midpoint)))*(1-churn_rate*0.85))*vcr_per_enterprise*12*cloud_per_1M_vcr/1000000*5)+((opex_branding+opex_external+opex_legal+opex_security+opex_partner_mgmt)*5)+(capex_total*capex_maintenance_pct*4)))*(1-cit_rate))/(1+discount_rate)^2.5 -> 27902.659 | D7: =((((adoption_max/(1+EXP(-adoption_steepness*(2028-adoption_midpoint)))*(1-churn_rate*1))*(cert_fee_yr1*(1+cert_fee_escalation)^2.5+training_pct*training_fee+audit_fee)*5)+(IF((adoption_max/(1+EXP(-adoption_steepness*(2028-adoption_midpoint)))*(1-churn_rate*1))>=stage2_gate,ecom_market_base*(1+ecom_growth_rate)^4*platform_market_share*tx_take_rate*1000*3,0))-((IF((adoption_max/(1+EXP(-adoption_steepness*(2028-adoption_midpoint)))*(1-churn_rate*1))>=stage2_gate,ecom_market_base*(1+ecom_growth_rate)^4*platform_market_share*tx_take_rate*1000*3,0))*payment_proc_pct)-(capex_total+(33*30*12*(1+bhxh_rate)*(1+salary_escalation)^2*5)+(opex_marketing*(1+marketing_growth)^2*5)+(opex_cloud_base*5+(adoption_max/(1+EXP(-adoption_steepness*(2028-adoption_midpoint)))*(1-churn_rate*1))*vcr_per_enterprise*12*cloud_per_1M_vcr/1000000*5)+((opex_branding+opex_external+opex_legal+opex_security+opex_partner_mgmt)*5)+(capex_total*capex_maintenance_pct*4)))*(1-cit_rate))/(1+discount_rate)^2.5 -> 25781.423 | E7: =((((adoption_max/(1+EXP(-adoption_steepness*(2028-adoption_midpoint)))*(1-churn_rate*1.15))*(cert_fee_yr1*(1+cert_fee_escalation)^2.5+training_pct*training_fee+audit_fee)*5)+(IF((adoption_max/(1+EXP(-adoption_steepness*(2028-adoption_midpoint)))*(1-churn_rate*1.15))>=stage2_gate,ecom_market_base*(1+ecom_growth_rate)^4*platform_market_share*tx_take_rate*1000*3,0))-((IF((adoption_max/(1+EXP(-adoption_steepness*(2028-adoption_midpoint)))*(1-churn_rate*1.15))>=stage2_gate,ecom_market_base*(1+ecom_growth_rate)^4*platform_market_share*tx_take_rate*1000*3,0))*payment_proc_pct)-(capex_total+(33*30*12*(1+bhxh_rate)*(1+salary_escalation)^2*5)+(opex_marketing*(1+marketing_growth)^2*5)+(opex_cloud_base*5+(adoption_max/(1+EXP(-adoption_steepness*(2028-adoption_midpoint)))*(1-churn_rate*1.15))*vcr_per_enterprise*12*cloud_per_1M_vcr/1000000*5)+((opex_branding+opex_external+opex_legal+opex_security+opex_partner_mgmt)*5)+(capex_total*capex_maintenance_pct*4)))*(1-cit_rate))/(1+discount_rate)^2.5 -> 23660.186 | F7: =((((adoption_max/(1+EXP(-adoption_steepness*(2028-adoption_midpoint)))*(1-churn_rate*1.3))*(cert_fee_yr1*(1+cert_fee_escalation)^2.5+training_pct*training_fee+audit_fee)*5)+(IF((adoption_max/(1+EXP(-adoption_steepness*(2028-adoption_midpoint)))*(1-churn_rate*1.3))>=stage2_gate,ecom_market_base*(1+ecom_growth_rate)^4*platform_market_share*tx_take_rate*1000*3,0))-((IF((adoption_max/(1+EXP(-adoption_steepness*(2028-adoption_midpoint)))*(1-churn_rate*1.3))>=stage2_gate,ecom_market_base*(1+ecom_growth_rate)^4*platform_market_share*tx_take_rate*1000*3,0))*payment_proc_pct)-(capex_total+(33*30*12*(1+bhxh_rate)*(1+salary_escalation)^2*5)+(opex_marketing*(1+marketing_growth)^2*5)+(opex_cloud_base*5+(adoption_max/(1+EXP(-adoption_steepness*(2028-adoption_midpoint)))*(1-churn_rate*1.3))*vcr_per_enterprise*12*cloud_per_1M_vcr/1000000*5)+((opex_branding+opex_external+opex_legal+opex_security+opex_partner_mgmt)*5)+(capex_total*capex_maintenance_pct*4)))*(1-cit_rate))/(1+discount_rate)^2.5 -> 21538.949 | G7: =churn_rate -> 0.2 | H7: ↑ churn → ↓ net ent
A8: Cert fee (Tr/yr) | B8: =((((adoption_max/(1+EXP(-adoption_steepness*(2028-adoption_midpoint)))*(1-churn_rate))*(cert_fee_yr1*0.7*(1+cert_fee_escalation)^2.5+training_pct*training_fee+audit_fee)*5)+(IF((adoption_max/(1+EXP(-adoption_steepness*(2028-adoption_midpoint)))*(1-churn_rate))>=stage2_gate,ecom_market_base*(1+ecom_growth_rate)^4*platform_market_share*tx_take_rate*1000*3,0))-((IF((adoption_max/(1+EXP(-adoption_steepness*(2028-adoption_midpoint)))*(1-churn_rate))>=stage2_gate,ecom_market_base*(1+ecom_growth_rate)^4*platform_market_share*tx_take_rate*1000*3,0))*payment_proc_pct)-(capex_total+(33*30*12*(1+bhxh_rate)*(1+salary_escalation)^2*5)+(opex_marketing*(1+marketing_growth)^2*5)+(opex_cloud_base*5+(adoption_max/(1+EXP(-adoption_steepness*(2028-adoption_midpoint)))*(1-churn_rate))*vcr_per_enterprise*12*cloud_per_1M_vcr/1000000*5)+((opex_branding+opex_external+opex_legal+opex_security+opex_partner_mgmt)*5)+(capex_total*capex_maintenance_pct*4)))*(1-cit_rate))/(1+discount_rate)^2.5 -> 14310.69 | C8: =((((adoption_max/(1+EXP(-adoption_steepness*(2028-adoption_midpoint)))*(1-churn_rate))*(cert_fee_yr1*0.85*(1+cert_fee_escalation)^2.5+training_pct*training_fee+audit_fee)*5)+(IF((adoption_max/(1+EXP(-adoption_steepness*(2028-adoption_midpoint)))*(1-churn_rate))>=stage2_gate,ecom_market_base*(1+ecom_growth_rate)^4*platform_market_share*tx_take_rate*1000*3,0))-((IF((adoption_max/(1+EXP(-adoption_steepness*(2028-adoption_midpoint)))*(1-churn_rate))>=stage2_gate,ecom_market_base*(1+ecom_growth_rate)^4*platform_market_share*tx_take_rate*1000*3,0))*payment_proc_pct)-(capex_total+(33*30*12*(1+bhxh_rate)*(1+salary_escalation)^2*5)+(opex_marketing*(1+marketing_growth)^2*5)+(opex_cloud_base*5+(adoption_max/(1+EXP(-adoption_steepness*(2028-adoption_midpoint)))*(1-churn_rate))*vcr_per_enterprise*12*cloud_per_1M_vcr/1000000*5)+((opex_branding+opex_external+opex_legal+opex_security+opex_partner_mgmt)*5)+(capex_total*capex_maintenance_pct*4)))*(1-cit_rate))/(1+discount_rate)^2.5 -> 20046.057 | D8: =((((adoption_max/(1+EXP(-adoption_steepness*(2028-adoption_midpoint)))*(1-churn_rate))*(cert_fee_yr1*1*(1+cert_fee_escalation)^2.5+training_pct*training_fee+audit_fee)*5)+(IF((adoption_max/(1+EXP(-adoption_steepness*(2028-adoption_midpoint)))*(1-churn_rate))>=stage2_gate,ecom_market_base*(1+ecom_growth_rate)^4*platform_market_share*tx_take_rate*1000*3,0))-((IF((adoption_max/(1+EXP(-adoption_steepness*(2028-adoption_midpoint)))*(1-churn_rate))>=stage2_gate,ecom_market_base*(1+ecom_growth_rate)^4*platform_market_share*tx_take_rate*1000*3,0))*payment_proc_pct)-(capex_total+(33*30*12*(1+bhxh_rate)*(1+salary_escalation)^2*5)+(opex_marketing*(1+marketing_growth)^2*5)+(opex_cloud_base*5+(adoption_max/(1+EXP(-adoption_steepness*(2028-adoption_midpoint)))*(1-churn_rate))*vcr_per_enterprise*12*cloud_per_1M_vcr/1000000*5)+((opex_branding+opex_external+opex_legal+opex_security+opex_partner_mgmt)*5)+(capex_total*capex_maintenance_pct*4)))*(1-cit_rate))/(1+discount_rate)^2.5 -> 25781.423 | E8: =((((adoption_max/(1+EXP(-adoption_steepness*(2028-adoption_midpoint)))*(1-churn_rate))*(cert_fee_yr1*1.15*(1+cert_fee_escalation)^2.5+training_pct*training_fee+audit_fee)*5)+(IF((adoption_max/(1+EXP(-adoption_steepness*(2028-adoption_midpoint)))*(1-churn_rate))>=stage2_gate,ecom_market_base*(1+ecom_growth_rate)^4*platform_market_share*tx_take_rate*1000*3,0))-((IF((adoption_max/(1+EXP(-adoption_steepness*(2028-adoption_midpoint)))*(1-churn_rate))>=stage2_gate,ecom_market_base*(1+ecom_growth_rate)^4*platform_market_share*tx_take_rate*1000*3,0))*payment_proc_pct)-(capex_total+(33*30*12*(1+bhxh_rate)*(1+salary_escalation)^2*5)+(opex_marketing*(1+marketing_growth)^2*5)+(opex_cloud_base*5+(adoption_max/(1+EXP(-adoption_steepness*(2028-adoption_midpoint)))*(1-churn_rate))*vcr_per_enterprise*12*cloud_per_1M_vcr/1000000*5)+((opex_branding+opex_external+opex_legal+opex_security+opex_partner_mgmt)*5)+(capex_total*capex_maintenance_pct*4)))*(1-cit_rate))/(1+discount_rate)^2.5 -> 31516.789 | F8: =((((adoption_max/(1+EXP(-adoption_steepness*(2028-adoption_midpoint)))*(1-churn_rate))*(cert_fee_yr1*1.3*(1+cert_fee_escalation)^2.5+training_pct*training_fee+audit_fee)*5)+(IF((adoption_max/(1+EXP(-adoption_steepness*(2028-adoption_midpoint)))*(1-churn_rate))>=stage2_gate,ecom_market_base*(1+ecom_growth_rate)^4*platform_market_share*tx_take_rate*1000*3,0))-((IF((adoption_max/(1+EXP(-adoption_steepness*(2028-adoption_midpoint)))*(1-churn_rate))>=stage2_gate,ecom_market_base*(1+ecom_growth_rate)^4*platform_market_share*tx_take_rate*1000*3,0))*payment_proc_pct)-(capex_total+(33*30*12*(1+bhxh_rate)*(1+salary_escalation)^2*5)+(opex_marketing*(1+marketing_growth)^2*5)+(opex_cloud_base*5+(adoption_max/(1+EXP(-adoption_steepness*(2028-adoption_midpoint)))*(1-churn_rate))*vcr_per_enterprise*12*cloud_per_1M_vcr/1000000*5)+((opex_branding+opex_external+opex_legal+opex_security+opex_partner_mgmt)*5)+(capex_total*capex_maintenance_pct*4)))*(1-cit_rate))/(1+discount_rate)^2.5 -> 37252.155 | G8: =cert_fee_yr1 -> 25 | H8: ↑ fee → ↑ Stage 1 rev
A9: Cert escalation | B9: =((((adoption_max/(1+EXP(-adoption_steepness*(2028-adoption_midpoint)))*(1-churn_rate))*(cert_fee_yr1*(1+cert_fee_escalation*0.7)^2.5+training_pct*training_fee+audit_fee)*5)+(IF((adoption_max/(1+EXP(-adoption_steepness*(2028-adoption_midpoint)))*(1-churn_rate))>=stage2_gate,ecom_market_base*(1+ecom_growth_rate)^4*platform_market_share*tx_take_rate*1000*3,0))-((IF((adoption_max/(1+EXP(-adoption_steepness*(2028-adoption_midpoint)))*(1-churn_rate))>=stage2_gate,ecom_market_base*(1+ecom_growth_rate)^4*platform_market_share*tx_take_rate*1000*3,0))*payment_proc_pct)-(capex_total+(33*30*12*(1+bhxh_rate)*(1+salary_escalation)^2*5)+(opex_marketing*(1+marketing_growth)^2*5)+(opex_cloud_base*5+(adoption_max/(1+EXP(-adoption_steepness*(2028-adoption_midpoint)))*(1-churn_rate))*vcr_per_enterprise*12*cloud_per_1M_vcr/1000000*5)+((opex_branding+opex_external+opex_legal+opex_security+opex_partner_mgmt)*5)+(capex_total*capex_maintenance_pct*4)))*(1-cit_rate))/(1+discount_rate)^2.5 -> 24430.455 | C9: =((((adoption_max/(1+EXP(-adoption_steepness*(2028-adoption_midpoint)))*(1-churn_rate))*(cert_fee_yr1*(1+cert_fee_escalation*0.85)^2.5+training_pct*training_fee+audit_fee)*5)+(IF((adoption_max/(1+EXP(-adoption_steepness*(2028-adoption_midpoint)))*(1-churn_rate))>=stage2_gate,ecom_market_base*(1+ecom_growth_rate)^4*platform_market_share*tx_take_rate*1000*3,0))-((IF((adoption_max/(1+EXP(-adoption_steepness*(2028-adoption_midpoint)))*(1-churn_rate))>=stage2_gate,ecom_market_base*(1+ecom_growth_rate)^4*platform_market_share*tx_take_rate*1000*3,0))*payment_proc_pct)-(capex_total+(33*30*12*(1+bhxh_rate)*(1+salary_escalation)^2*5)+(opex_marketing*(1+marketing_growth)^2*5)+(opex_cloud_base*5+(adoption_max/(1+EXP(-adoption_steepness*(2028-adoption_midpoint)))*(1-churn_rate))*vcr_per_enterprise*12*cloud_per_1M_vcr/1000000*5)+((opex_branding+opex_external+opex_legal+opex_security+opex_partner_mgmt)*5)+(capex_total*capex_maintenance_pct*4)))*(1-cit_rate))/(1+discount_rate)^2.5 -> 25102.294 | D9: =((((adoption_max/(1+EXP(-adoption_steepness*(2028-adoption_midpoint)))*(1-churn_rate))*(cert_fee_yr1*(1+cert_fee_escalation*1)^2.5+training_pct*training_fee+audit_fee)*5)+(IF((adoption_max/(1+EXP(-adoption_steepness*(2028-adoption_midpoint)))*(1-churn_rate))>=stage2_gate,ecom_market_base*(1+ecom_growth_rate)^4*platform_market_share*tx_take_rate*1000*3,0))-((IF((adoption_max/(1+EXP(-adoption_steepness*(2028-adoption_midpoint)))*(1-churn_rate))>=stage2_gate,ecom_market_base*(1+ecom_growth_rate)^4*platform_market_share*tx_take_rate*1000*3,0))*payment_proc_pct)-(capex_total+(33*30*12*(1+bhxh_rate)*(1+salary_escalation)^2*5)+(opex_marketing*(1+marketing_growth)^2*5)+(opex_cloud_base*5+(adoption_max/(1+EXP(-adoption_steepness*(2028-adoption_midpoint)))*(1-churn_rate))*vcr_per_enterprise*12*cloud_per_1M_vcr/1000000*5)+((opex_branding+opex_external+opex_legal+opex_security+opex_partner_mgmt)*5)+(capex_total*capex_maintenance_pct*4)))*(1-cit_rate))/(1+discount_rate)^2.5 -> 25781.423 | E9: =((((adoption_max/(1+EXP(-adoption_steepness*(2028-adoption_midpoint)))*(1-churn_rate))*(cert_fee_yr1*(1+cert_fee_escalation*1.15)^2.5+training_pct*training_fee+audit_fee)*5)+(IF((adoption_max/(1+EXP(-adoption_steepness*(2028-adoption_midpoint)))*(1-churn_rate))>=stage2_gate,ecom_market_base*(1+ecom_growth_rate)^4*platform_market_share*tx_take_rate*1000*3,0))-((IF((adoption_max/(1+EXP(-adoption_steepness*(2028-adoption_midpoint)))*(1-churn_rate))>=stage2_gate,ecom_market_base*(1+ecom_growth_rate)^4*platform_market_share*tx_take_rate*1000*3,0))*payment_proc_pct)-(capex_total+(33*30*12*(1+bhxh_rate)*(1+salary_escalation)^2*5)+(opex_marketing*(1+marketing_growth)^2*5)+(opex_cloud_base*5+(adoption_max/(1+EXP(-adoption_steepness*(2028-adoption_midpoint)))*(1-churn_rate))*vcr_per_enterprise*12*cloud_per_1M_vcr/1000000*5)+((opex_branding+opex_external+opex_legal+opex_security+opex_partner_mgmt)*5)+(capex_total*capex_maintenance_pct*4)))*(1-cit_rate))/(1+discount_rate)^2.5 -> 26467.866 | F9: =((((adoption_max/(1+EXP(-adoption_steepness*(2028-adoption_midpoint)))*(1-churn_rate))*(cert_fee_yr1*(1+cert_fee_escalation*1.3)^2.5+training_pct*training_fee+audit_fee)*5)+(IF((adoption_max/(1+EXP(-adoption_steepness*(2028-adoption_midpoint)))*(1-churn_rate))>=stage2_gate,ecom_market_base*(1+ecom_growth_rate)^4*platform_market_share*tx_take_rate*1000*3,0))-((IF((adoption_max/(1+EXP(-adoption_steepness*(2028-adoption_midpoint)))*(1-churn_rate))>=stage2_gate,ecom_market_base*(1+ecom_growth_rate)^4*platform_market_share*tx_take_rate*1000*3,0))*payment_proc_pct)-(capex_total+(33*30*12*(1+bhxh_rate)*(1+salary_escalation)^2*5)+(opex_marketing*(1+marketing_growth)^2*5)+(opex_cloud_base*5+(adoption_max/(1+EXP(-adoption_steepness*(2028-adoption_midpoint)))*(1-churn_rate))*vcr_per_enterprise*12*cloud_per_1M_vcr/1000000*5)+((opex_branding+opex_external+opex_legal+opex_security+opex_partner_mgmt)*5)+(capex_total*capex_maintenance_pct*4)))*(1-cit_rate))/(1+discount_rate)^2.5 -> 27161.652 | G9: =cert_fee_escalation -> 0.05 | H9: ↑ esc → ↑ later rev
A10: WACC (discount_rate) | B10: =((((adoption_max/(1+EXP(-adoption_steepness*(2028-adoption_midpoint)))*(1-churn_rate))*(cert_fee_yr1*(1+cert_fee_escalation)^2.5+training_pct*training_fee+audit_fee)*5)+(IF((adoption_max/(1+EXP(-adoption_steepness*(2028-adoption_midpoint)))*(1-churn_rate))>=stage2_gate,ecom_market_base*(1+ecom_growth_rate)^4*platform_market_share*tx_take_rate*1000*3,0))-((IF((adoption_max/(1+EXP(-adoption_steepness*(2028-adoption_midpoint)))*(1-churn_rate))>=stage2_gate,ecom_market_base*(1+ecom_growth_rate)^4*platform_market_share*tx_take_rate*1000*3,0))*payment_proc_pct)-(capex_total+(33*30*12*(1+bhxh_rate)*(1+salary_escalation)^2*5)+(opex_marketing*(1+marketing_growth)^2*5)+(opex_cloud_base*5+(adoption_max/(1+EXP(-adoption_steepness*(2028-adoption_midpoint)))*(1-churn_rate))*vcr_per_enterprise*12*cloud_per_1M_vcr/1000000*5)+((opex_branding+opex_external+opex_legal+opex_security+opex_partner_mgmt)*5)+(capex_total*capex_maintenance_pct*4)))*(1-cit_rate))/(1+discount_rate*0.7)^2.5 -> 28486.939 | C10: =((((adoption_max/(1+EXP(-adoption_steepness*(2028-adoption_midpoint)))*(1-churn_rate))*(cert_fee_yr1*(1+cert_fee_escalation)^2.5+training_pct*training_fee+audit_fee)*5)+(IF((adoption_max/(1+EXP(-adoption_steepness*(2028-adoption_midpoint)))*(1-churn_rate))>=stage2_gate,ecom_market_base*(1+ecom_growth_rate)^4*platform_market_share*tx_take_rate*1000*3,0))-((IF((adoption_max/(1+EXP(-adoption_steepness*(2028-adoption_midpoint)))*(1-churn_rate))>=stage2_gate,ecom_market_base*(1+ecom_growth_rate)^4*platform_market_share*tx_take_rate*1000*3,0))*payment_proc_pct)-(capex_total+(33*30*12*(1+bhxh_rate)*(1+salary_escalation)^2*5)+(opex_marketing*(1+marketing_growth)^2*5)+(opex_cloud_base*5+(adoption_max/(1+EXP(-adoption_steepness*(2028-adoption_midpoint)))*(1-churn_rate))*vcr_per_enterprise*12*cloud_per_1M_vcr/1000000*5)+((opex_branding+opex_external+opex_legal+opex_security+opex_partner_mgmt)*5)+(capex_total*capex_maintenance_pct*4)))*(1-cit_rate))/(1+discount_rate*0.85)^2.5 -> 27086.95 | D10: =((((adoption_max/(1+EXP(-adoption_steepness*(2028-adoption_midpoint)))*(1-churn_rate))*(cert_fee_yr1*(1+cert_fee_escalation)^2.5+training_pct*training_fee+audit_fee)*5)+(IF((adoption_max/(1+EXP(-adoption_steepness*(2028-adoption_midpoint)))*(1-churn_rate))>=stage2_gate,ecom_market_base*(1+ecom_growth_rate)^4*platform_market_share*tx_take_rate*1000*3,0))-((IF((adoption_max/(1+EXP(-adoption_steepness*(2028-adoption_midpoint)))*(1-churn_rate))>=stage2_gate,ecom_market_base*(1+ecom_growth_rate)^4*platform_market_share*tx_take_rate*1000*3,0))*payment_proc_pct)-(capex_total+(33*30*12*(1+bhxh_rate)*(1+salary_escalation)^2*5)+(opex_marketing*(1+marketing_growth)^2*5)+(opex_cloud_base*5+(adoption_max/(1+EXP(-adoption_steepness*(2028-adoption_midpoint)))*(1-churn_rate))*vcr_per_enterprise*12*cloud_per_1M_vcr/1000000*5)+((opex_branding+opex_external+opex_legal+opex_security+opex_partner_mgmt)*5)+(capex_total*capex_maintenance_pct*4)))*(1-cit_rate))/(1+discount_rate*1)^2.5 -> 25781.423 | E10: =((((adoption_max/(1+EXP(-adoption_steepness*(2028-adoption_midpoint)))*(1-churn_rate))*(cert_fee_yr1*(1+cert_fee_escalation)^2.5+training_pct*training_fee+audit_fee)*5)+(IF((adoption_max/(1+EXP(-adoption_steepness*(2028-adoption_midpoint)))*(1-churn_rate))>=stage2_gate,ecom_market_base*(1+ecom_growth_rate)^4*platform_market_share*tx_take_rate*1000*3,0))-((IF((adoption_max/(1+EXP(-adoption_steepness*(2028-adoption_midpoint)))*(1-churn_rate))>=stage2_gate,ecom_market_base*(1+ecom_growth_rate)^4*platform_market_share*tx_take_rate*1000*3,0))*payment_proc_pct)-(capex_total+(33*30*12*(1+bhxh_rate)*(1+salary_escalation)^2*5)+(opex_marketing*(1+marketing_growth)^2*5)+(opex_cloud_base*5+(adoption_max/(1+EXP(-adoption_steepness*(2028-adoption_midpoint)))*(1-churn_rate))*vcr_per_enterprise*12*cloud_per_1M_vcr/1000000*5)+((opex_branding+opex_external+opex_legal+opex_security+opex_partner_mgmt)*5)+(capex_total*capex_maintenance_pct*4)))*(1-cit_rate))/(1+discount_rate*1.15)^2.5 -> 24562.318 | F10: =((((adoption_max/(1+EXP(-adoption_steepness*(2028-adoption_midpoint)))*(1-churn_rate))*(cert_fee_yr1*(1+cert_fee_escalation)^2.5+training_pct*training_fee+audit_fee)*5)+(IF((adoption_max/(1+EXP(-adoption_steepness*(2028-adoption_midpoint)))*(1-churn_rate))>=stage2_gate,ecom_market_base*(1+ecom_growth_rate)^4*platform_market_share*tx_take_rate*1000*3,0))-((IF((adoption_max/(1+EXP(-adoption_steepness*(2028-adoption_midpoint)))*(1-churn_rate))>=stage2_gate,ecom_market_base*(1+ecom_growth_rate)^4*platform_market_share*tx_take_rate*1000*3,0))*payment_proc_pct)-(capex_total+(33*30*12*(1+bhxh_rate)*(1+salary_escalation)^2*5)+(opex_marketing*(1+marketing_growth)^2*5)+(opex_cloud_base*5+(adoption_max/(1+EXP(-adoption_steepness*(2028-adoption_midpoint)))*(1-churn_rate))*vcr_per_enterprise*12*cloud_per_1M_vcr/1000000*5)+((opex_branding+opex_external+opex_legal+opex_security+opex_partner_mgmt)*5)+(capex_total*capex_maintenance_pct*4)))*(1-cit_rate))/(1+discount_rate*1.3)^2.5 -> 23422.417 | G10: =discount_rate -> 0.15 | H10: ↑ WACC → ↓ NPV
A11: Marketing base | B11: =((((adoption_max/(1+EXP(-adoption_steepness*(2028-adoption_midpoint)))*(1-churn_rate))*(cert_fee_yr1*(1+cert_fee_escalation)^2.5+training_pct*training_fee+audit_fee)*5)+(IF((adoption_max/(1+EXP(-adoption_steepness*(2028-adoption_midpoint)))*(1-churn_rate))>=stage2_gate,ecom_market_base*(1+ecom_growth_rate)^4*platform_market_share*tx_take_rate*1000*3,0))-((IF((adoption_max/(1+EXP(-adoption_steepness*(2028-adoption_midpoint)))*(1-churn_rate))>=stage2_gate,ecom_market_base*(1+ecom_growth_rate)^4*platform_market_share*tx_take_rate*1000*3,0))*payment_proc_pct)-(capex_total+(33*30*12*(1+bhxh_rate)*(1+salary_escalation)^2*5)+(opex_marketing*0.7*(1+marketing_growth)^2*5)+(opex_cloud_base*5+(adoption_max/(1+EXP(-adoption_steepness*(2028-adoption_midpoint)))*(1-churn_rate))*vcr_per_enterprise*12*cloud_per_1M_vcr/1000000*5)+((opex_branding+opex_external+opex_legal+opex_security+opex_partner_mgmt)*5)+(capex_total*capex_maintenance_pct*4)))*(1-cit_rate))/(1+discount_rate)^2.5 -> 33614.463 | C11: =((((adoption_max/(1+EXP(-adoption_steepness*(2028-adoption_midpoint)))*(1-churn_rate))*(cert_fee_yr1*(1+cert_fee_escalation)^2.5+training_pct*training_fee+audit_fee)*5)+(IF((adoption_max/(1+EXP(-adoption_steepness*(2028-adoption_midpoint)))*(1-churn_rate))>=stage2_gate,ecom_market_base*(1+ecom_growth_rate)^4*platform_market_share*tx_take_rate*1000*3,0))-((IF((adoption_max/(1+EXP(-adoption_steepness*(2028-adoption_midpoint)))*(1-churn_rate))>=stage2_gate,ecom_market_base*(1+ecom_growth_rate)^4*platform_market_share*tx_take_rate*1000*3,0))*payment_proc_pct)-(capex_total+(33*30*12*(1+bhxh_rate)*(1+salary_escalation)^2*5)+(opex_marketing*0.85*(1+marketing_growth)^2*5)+(opex_cloud_base*5+(adoption_max/(1+EXP(-adoption_steepness*(2028-adoption_midpoint)))*(1-churn_rate))*vcr_per_enterprise*12*cloud_per_1M_vcr/1000000*5)+((opex_branding+opex_external+opex_legal+opex_security+opex_partner_mgmt)*5)+(capex_total*capex_maintenance_pct*4)))*(1-cit_rate))/(1+discount_rate)^2.5 -> 29697.943 | D11: =((((adoption_max/(1+EXP(-adoption_steepness*(2028-adoption_midpoint)))*(1-churn_rate))*(cert_fee_yr1*(1+cert_fee_escalation)^2.5+training_pct*training_fee+audit_fee)*5)+(IF((adoption_max/(1+EXP(-adoption_steepness*(2028-adoption_midpoint)))*(1-churn_rate))>=stage2_gate,ecom_market_base*(1+ecom_growth_rate)^4*platform_market_share*tx_take_rate*1000*3,0))-((IF((adoption_max/(1+EXP(-adoption_steepness*(2028-adoption_midpoint)))*(1-churn_rate))>=stage2_gate,ecom_market_base*(1+ecom_growth_rate)^4*platform_market_share*tx_take_rate*1000*3,0))*payment_proc_pct)-(capex_total+(33*30*12*(1+bhxh_rate)*(1+salary_escalation)^2*5)+(opex_marketing*1*(1+marketing_growth)^2*5)+(opex_cloud_base*5+(adoption_max/(1+EXP(-adoption_steepness*(2028-adoption_midpoint)))*(1-churn_rate))*vcr_per_enterprise*12*cloud_per_1M_vcr/1000000*5)+((opex_branding+opex_external+opex_legal+opex_security+opex_partner_mgmt)*5)+(capex_total*capex_maintenance_pct*4)))*(1-cit_rate))/(1+discount_rate)^2.5 -> 25781.423 | E11: =((((adoption_max/(1+EXP(-adoption_steepness*(2028-adoption_midpoint)))*(1-churn_rate))*(cert_fee_yr1*(1+cert_fee_escalation)^2.5+training_pct*training_fee+audit_fee)*5)+(IF((adoption_max/(1+EXP(-adoption_steepness*(2028-adoption_midpoint)))*(1-churn_rate))>=stage2_gate,ecom_market_base*(1+ecom_growth_rate)^4*platform_market_share*tx_take_rate*1000*3,0))-((IF((adoption_max/(1+EXP(-adoption_steepness*(2028-adoption_midpoint)))*(1-churn_rate))>=stage2_gate,ecom_market_base*(1+ecom_growth_rate)^4*platform_market_share*tx_take_rate*1000*3,0))*payment_proc_pct)-(capex_total+(33*30*12*(1+bhxh_rate)*(1+salary_escalation)^2*5)+(opex_marketing*1.15*(1+marketing_growth)^2*5)+(opex_cloud_base*5+(adoption_max/(1+EXP(-adoption_steepness*(2028-adoption_midpoint)))*(1-churn_rate))*vcr_per_enterprise*12*cloud_per_1M_vcr/1000000*5)+((opex_branding+opex_external+opex_legal+opex_security+opex_partner_mgmt)*5)+(capex_total*capex_maintenance_pct*4)))*(1-cit_rate))/(1+discount_rate)^2.5 -> 21864.902 | F11: =((((adoption_max/(1+EXP(-adoption_steepness*(2028-adoption_midpoint)))*(1-churn_rate))*(cert_fee_yr1*(1+cert_fee_escalation)^2.5+training_pct*training_fee+audit_fee)*5)+(IF((adoption_max/(1+EXP(-adoption_steepness*(2028-adoption_midpoint)))*(1-churn_rate))>=stage2_gate,ecom_market_base*(1+ecom_growth_rate)^4*platform_market_share*tx_take_rate*1000*3,0))-((IF((adoption_max/(1+EXP(-adoption_steepness*(2028-adoption_midpoint)))*(1-churn_rate))>=stage2_gate,ecom_market_base*(1+ecom_growth_rate)^4*platform_market_share*tx_take_rate*1000*3,0))*payment_proc_pct)-(capex_total+(33*30*12*(1+bhxh_rate)*(1+salary_escalation)^2*5)+(opex_marketing*1.3*(1+marketing_growth)^2*5)+(opex_cloud_base*5+(adoption_max/(1+EXP(-adoption_steepness*(2028-adoption_midpoint)))*(1-churn_rate))*vcr_per_enterprise*12*cloud_per_1M_vcr/1000000*5)+((opex_branding+opex_external+opex_legal+opex_security+opex_partner_mgmt)*5)+(capex_total*capex_maintenance_pct*4)))*(1-cit_rate))/(1+discount_rate)^2.5 -> 17948.382 | G11: =opex_marketing -> 7000 | H11: ↑ mkt → ↓ profit
A12: S-curve steepness | B12: =((((adoption_max/(1+EXP(-adoption_steepness*0.7*(2028-adoption_midpoint)))*(1-churn_rate))*(cert_fee_yr1*(1+cert_fee_escalation)^2.5+training_pct*training_fee+audit_fee)*5)+(IF((adoption_max/(1+EXP(-adoption_steepness*0.7*(2028-adoption_midpoint)))*(1-churn_rate))>=stage2_gate,ecom_market_base*(1+ecom_growth_rate)^4*platform_market_share*tx_take_rate*1000*3,0))-((IF((adoption_max/(1+EXP(-adoption_steepness*0.7*(2028-adoption_midpoint)))*(1-churn_rate))>=stage2_gate,ecom_market_base*(1+ecom_growth_rate)^4*platform_market_share*tx_take_rate*1000*3,0))*payment_proc_pct)-(capex_total+(33*30*12*(1+bhxh_rate)*(1+salary_escalation)^2*5)+(opex_marketing*(1+marketing_growth)^2*5)+(opex_cloud_base*5+(adoption_max/(1+EXP(-adoption_steepness*0.7*(2028-adoption_midpoint)))*(1-churn_rate))*vcr_per_enterprise*12*cloud_per_1M_vcr/1000000*5)+((opex_branding+opex_external+opex_legal+opex_security+opex_partner_mgmt)*5)+(capex_total*capex_maintenance_pct*4)))*(1-cit_rate))/(1+discount_rate)^2.5 -> 25781.423 | C12: =((((adoption_max/(1+EXP(-adoption_steepness*0.85*(2028-adoption_midpoint)))*(1-churn_rate))*(cert_fee_yr1*(1+cert_fee_escalation)^2.5+training_pct*training_fee+audit_fee)*5)+(IF((adoption_max/(1+EXP(-adoption_steepness*0.85*(2028-adoption_midpoint)))*(1-churn_rate))>=stage2_gate,ecom_market_base*(1+ecom_growth_rate)^4*platform_market_share*tx_take_rate*1000*3,0))-((IF((adoption_max/(1+EXP(-adoption_steepness*0.85*(2028-adoption_midpoint)))*(1-churn_rate))>=stage2_gate,ecom_market_base*(1+ecom_growth_rate)^4*platform_market_share*tx_take_rate*1000*3,0))*payment_proc_pct)-(capex_total+(33*30*12*(1+bhxh_rate)*(1+salary_escalation)^2*5)+(opex_marketing*(1+marketing_growth)^2*5)+(opex_cloud_base*5+(adoption_max/(1+EXP(-adoption_steepness*0.85*(2028-adoption_midpoint)))*(1-churn_rate))*vcr_per_enterprise*12*cloud_per_1M_vcr/1000000*5)+((opex_branding+opex_external+opex_legal+opex_security+opex_partner_mgmt)*5)+(capex_total*capex_maintenance_pct*4)))*(1-cit_rate))/(1+discount_rate)^2.5 -> 25781.423 | D12: =((((adoption_max/(1+EXP(-adoption_steepness*1*(2028-adoption_midpoint)))*(1-churn_rate))*(cert_fee_yr1*(1+cert_fee_escalation)^2.5+training_pct*training_fee+audit_fee)*5)+(IF((adoption_max/(1+EXP(-adoption_steepness*1*(2028-adoption_midpoint)))*(1-churn_rate))>=stage2_gate,ecom_market_base*(1+ecom_growth_rate)^4*platform_market_share*tx_take_rate*1000*3,0))-((IF((adoption_max/(1+EXP(-adoption_steepness*1*(2028-adoption_midpoint)))*(1-churn_rate))>=stage2_gate,ecom_market_base*(1+ecom_growth_rate)^4*platform_market_share*tx_take_rate*1000*3,0))*payment_proc_pct)-(capex_total+(33*30*12*(1+bhxh_rate)*(1+salary_escalation)^2*5)+(opex_marketing*(1+marketing_growth)^2*5)+(opex_cloud_base*5+(adoption_max/(1+EXP(-adoption_steepness*1*(2028-adoption_midpoint)))*(1-churn_rate))*vcr_per_enterprise*12*cloud_per_1M_vcr/1000000*5)+((opex_branding+opex_external+opex_legal+opex_security+opex_partner_mgmt)*5)+(capex_total*capex_maintenance_pct*4)))*(1-cit_rate))/(1+discount_rate)^2.5 -> 25781.423 | E12: =((((adoption_max/(1+EXP(-adoption_steepness*1.15*(2028-adoption_midpoint)))*(1-churn_rate))*(cert_fee_yr1*(1+cert_fee_escalation)^2.5+training_pct*training_fee+audit_fee)*5)+(IF((adoption_max/(1+EXP(-adoption_steepness*1.15*(2028-adoption_midpoint)))*(1-churn_rate))>=stage2_gate,ecom_market_base*(1+ecom_growth_rate)^4*platform_market_share*tx_take_rate*1000*3,0))-((IF((adoption_max/(1+EXP(-adoption_steepness*1.15*(2028-adoption_midpoint)))*(1-churn_rate))>=stage2_gate,ecom_market_base*(1+ecom_growth_rate)^4*platform_market_share*tx_take_rate*1000*3,0))*payment_proc_pct)-(capex_total+(33*30*12*(1+bhxh_rate)*(1+salary_escalation)^2*5)+(opex_marketing*(1+marketing_growth)^2*5)+(opex_cloud_base*5+(adoption_max/(1+EXP(-adoption_steepness*1.15*(2028-adoption_midpoint)))*(1-churn_rate))*vcr_per_enterprise*12*cloud_per_1M_vcr/1000000*5)+((opex_branding+opex_external+opex_legal+opex_security+opex_partner_mgmt)*5)+(capex_total*capex_maintenance_pct*4)))*(1-cit_rate))/(1+discount_rate)^2.5 -> 25781.423 | F12: =((((adoption_max/(1+EXP(-adoption_steepness*1.3*(2028-adoption_midpoint)))*(1-churn_rate))*(cert_fee_yr1*(1+cert_fee_escalation)^2.5+training_pct*training_fee+audit_fee)*5)+(IF((adoption_max/(1+EXP(-adoption_steepness*1.3*(2028-adoption_midpoint)))*(1-churn_rate))>=stage2_gate,ecom_market_base*(1+ecom_growth_rate)^4*platform_market_share*tx_take_rate*1000*3,0))-((IF((adoption_max/(1+EXP(-adoption_steepness*1.3*(2028-adoption_midpoint)))*(1-churn_rate))>=stage2_gate,ecom_market_base*(1+ecom_growth_rate)^4*platform_market_share*tx_take_rate*1000*3,0))*payment_proc_pct)-(capex_total+(33*30*12*(1+bhxh_rate)*(1+salary_escalation)^2*5)+(opex_marketing*(1+marketing_growth)^2*5)+(opex_cloud_base*5+(adoption_max/(1+EXP(-adoption_steepness*1.3*(2028-adoption_midpoint)))*(1-churn_rate))*vcr_per_enterprise*12*cloud_per_1M_vcr/1000000*5)+((opex_branding+opex_external+opex_legal+opex_security+opex_partner_mgmt)*5)+(capex_total*capex_maintenance_pct*4)))*(1-cit_rate))/(1+discount_rate)^2.5 -> 25781.423 | G12: =adoption_steepness -> 0.9 | H12: ↑ steep → faster adopt
A13: Stage 2 gate | B13: =((((adoption_max/(1+EXP(-adoption_steepness*(2028-adoption_midpoint)))*(1-churn_rate))*(cert_fee_yr1*(1+cert_fee_escalation)^2.5+training_pct*training_fee+audit_fee)*5)+(IF((adoption_max/(1+EXP(-adoption_steepness*(2028-adoption_midpoint)))*(1-churn_rate))>=stage2_gate*0.7,ecom_market_base*(1+ecom_growth_rate)^4*platform_market_share*tx_take_rate*1000*3,0))-((IF((adoption_max/(1+EXP(-adoption_steepness*(2028-adoption_midpoint)))*(1-churn_rate))>=stage2_gate*0.7,ecom_market_base*(1+ecom_growth_rate)^4*platform_market_share*tx_take_rate*1000*3,0))*payment_proc_pct)-(capex_total+(33*30*12*(1+bhxh_rate)*(1+salary_escalation)^2*5)+(opex_marketing*(1+marketing_growth)^2*5)+(opex_cloud_base*5+(adoption_max/(1+EXP(-adoption_steepness*(2028-adoption_midpoint)))*(1-churn_rate))*vcr_per_enterprise*12*cloud_per_1M_vcr/1000000*5)+((opex_branding+opex_external+opex_legal+opex_security+opex_partner_mgmt)*5)+(capex_total*capex_maintenance_pct*4)))*(1-cit_rate))/(1+discount_rate)^2.5 -> 25781.423 | C13: =((((adoption_max/(1+EXP(-adoption_steepness*(2028-adoption_midpoint)))*(1-churn_rate))*(cert_fee_yr1*(1+cert_fee_escalation)^2.5+training_pct*training_fee+audit_fee)*5)+(IF((adoption_max/(1+EXP(-adoption_steepness*(2028-adoption_midpoint)))*(1-churn_rate))>=stage2_gate*0.85,ecom_market_base*(1+ecom_growth_rate)^4*platform_market_share*tx_take_rate*1000*3,0))-((IF((adoption_max/(1+EXP(-adoption_steepness*(2028-adoption_midpoint)))*(1-churn_rate))>=stage2_gate*0.85,ecom_market_base*(1+ecom_growth_rate)^4*platform_market_share*tx_take_rate*1000*3,0))*payment_proc_pct)-(capex_total+(33*30*12*(1+bhxh_rate)*(1+salary_escalation)^2*5)+(opex_marketing*(1+marketing_growth)^2*5)+(opex_cloud_base*5+(adoption_max/(1+EXP(-adoption_steepness*(2028-adoption_midpoint)))*(1-churn_rate))*vcr_per_enterprise*12*cloud_per_1M_vcr/1000000*5)+((opex_branding+opex_external+opex_legal+opex_security+opex_partner_mgmt)*5)+(capex_total*capex_maintenance_pct*4)))*(1-cit_rate))/(1+discount_rate)^2.5 -> 25781.423 | D13: =((((adoption_max/(1+EXP(-adoption_steepness*(2028-adoption_midpoint)))*(1-churn_rate))*(cert_fee_yr1*(1+cert_fee_escalation)^2.5+training_pct*training_fee+audit_fee)*5)+(IF((adoption_max/(1+EXP(-adoption_steepness*(2028-adoption_midpoint)))*(1-churn_rate))>=stage2_gate*1,ecom_market_base*(1+ecom_growth_rate)^4*platform_market_share*tx_take_rate*1000*3,0))-((IF((adoption_max/(1+EXP(-adoption_steepness*(2028-adoption_midpoint)))*(1-churn_rate))>=stage2_gate*1,ecom_market_base*(1+ecom_growth_rate)^4*platform_market_share*tx_take_rate*1000*3,0))*payment_proc_pct)-(capex_total+(33*30*12*(1+bhxh_rate)*(1+salary_escalation)^2*5)+(opex_marketing*(1+marketing_growth)^2*5)+(opex_cloud_base*5+(adoption_max/(1+EXP(-adoption_steepness*(2028-adoption_midpoint)))*(1-churn_rate))*vcr_per_enterprise*12*cloud_per_1M_vcr/1000000*5)+((opex_branding+opex_external+opex_legal+opex_security+opex_partner_mgmt)*5)+(capex_total*capex_maintenance_pct*4)))*(1-cit_rate))/(1+discount_rate)^2.5 -> 25781.423 | E13: =((((adoption_max/(1+EXP(-adoption_steepness*(2028-adoption_midpoint)))*(1-churn_rate))*(cert_fee_yr1*(1+cert_fee_escalation)^2.5+training_pct*training_fee+audit_fee)*5)+(IF((adoption_max/(1+EXP(-adoption_steepness*(2028-adoption_midpoint)))*(1-churn_rate))>=stage2_gate*1.15,ecom_market_base*(1+ecom_growth_rate)^4*platform_market_share*tx_take_rate*1000*3,0))-((IF((adoption_max/(1+EXP(-adoption_steepness*(2028-adoption_midpoint)))*(1-churn_rate))>=stage2_gate*1.15,ecom_market_base*(1+ecom_growth_rate)^4*platform_market_share*tx_take_rate*1000*3,0))*payment_proc_pct)-(capex_total+(33*30*12*(1+bhxh_rate)*(1+salary_escalation)^2*5)+(opex_marketing*(1+marketing_growth)^2*5)+(opex_cloud_base*5+(adoption_max/(1+EXP(-adoption_steepness*(2028-adoption_midpoint)))*(1-churn_rate))*vcr_per_enterprise*12*cloud_per_1M_vcr/1000000*5)+((opex_branding+opex_external+opex_legal+opex_security+opex_partner_mgmt)*5)+(capex_total*capex_maintenance_pct*4)))*(1-cit_rate))/(1+discount_rate)^2.5 -> 25781.423 | F13: =((((adoption_max/(1+EXP(-adoption_steepness*(2028-adoption_midpoint)))*(1-churn_rate))*(cert_fee_yr1*(1+cert_fee_escalation)^2.5+training_pct*training_fee+audit_fee)*5)+(IF((adoption_max/(1+EXP(-adoption_steepness*(2028-adoption_midpoint)))*(1-churn_rate))>=stage2_gate*1.3,ecom_market_base*(1+ecom_growth_rate)^4*platform_market_share*tx_take_rate*1000*3,0))-((IF((adoption_max/(1+EXP(-adoption_steepness*(2028-adoption_midpoint)))*(1-churn_rate))>=stage2_gate*1.3,ecom_market_base*(1+ecom_growth_rate)^4*platform_market_share*tx_take_rate*1000*3,0))*payment_proc_pct)-(capex_total+(33*30*12*(1+bhxh_rate)*(1+salary_escalation)^2*5)+(opex_marketing*(1+marketing_growth)^2*5)+(opex_cloud_base*5+(adoption_max/(1+EXP(-adoption_steepness*(2028-adoption_midpoint)))*(1-churn_rate))*vcr_per_enterprise*12*cloud_per_1M_vcr/1000000*5)+((opex_branding+opex_external+opex_legal+opex_security+opex_partner_mgmt)*5)+(capex_total*capex_maintenance_pct*4)))*(1-cit_rate))/(1+discount_rate)^2.5 -> 25781.423 | G13: =stage2_gate -> 300 | H13: ↑ gate → later Stage 2
A14: Cloud base cost | B14: =((((adoption_max/(1+EXP(-adoption_steepness*(2028-adoption_midpoint)))*(1-churn_rate))*(cert_fee_yr1*(1+cert_fee_escalation)^2.5+training_pct*training_fee+audit_fee)*5)+(IF((adoption_max/(1+EXP(-adoption_steepness*(2028-adoption_midpoint)))*(1-churn_rate))>=stage2_gate,ecom_market_base*(1+ecom_growth_rate)^4*platform_market_share*tx_take_rate*1000*3,0))-((IF((adoption_max/(1+EXP(-adoption_steepness*(2028-adoption_midpoint)))*(1-churn_rate))>=stage2_gate,ecom_market_base*(1+ecom_growth_rate)^4*platform_market_share*tx_take_rate*1000*3,0))*payment_proc_pct)-(capex_total+(33*30*12*(1+bhxh_rate)*(1+salary_escalation)^2*5)+(opex_marketing*(1+marketing_growth)^2*5)+(opex_cloud_base*0.7*5+(adoption_max/(1+EXP(-adoption_steepness*(2028-adoption_midpoint)))*(1-churn_rate))*vcr_per_enterprise*12*cloud_per_1M_vcr/1000000*5)+((opex_branding+opex_external+opex_legal+opex_security+opex_partner_mgmt)*5)+(capex_total*capex_maintenance_pct*4)))*(1-cit_rate))/(1+discount_rate)^2.5 -> 28531.342 | C14: =((((adoption_max/(1+EXP(-adoption_steepness*(2028-adoption_midpoint)))*(1-churn_rate))*(cert_fee_yr1*(1+cert_fee_escalation)^2.5+training_pct*training_fee+audit_fee)*5)+(IF((adoption_max/(1+EXP(-adoption_steepness*(2028-adoption_midpoint)))*(1-churn_rate))>=stage2_gate,ecom_market_base*(1+ecom_growth_rate)^4*platform_market_share*tx_take_rate*1000*3,0))-((IF((adoption_max/(1+EXP(-adoption_steepness*(2028-adoption_midpoint)))*(1-churn_rate))>=stage2_gate,ecom_market_base*(1+ecom_growth_rate)^4*platform_market_share*tx_take_rate*1000*3,0))*payment_proc_pct)-(capex_total+(33*30*12*(1+bhxh_rate)*(1+salary_escalation)^2*5)+(opex_marketing*(1+marketing_growth)^2*5)+(opex_cloud_base*0.85*5+(adoption_max/(1+EXP(-adoption_steepness*(2028-adoption_midpoint)))*(1-churn_rate))*vcr_per_enterprise*12*cloud_per_1M_vcr/1000000*5)+((opex_branding+opex_external+opex_legal+opex_security+opex_partner_mgmt)*5)+(capex_total*capex_maintenance_pct*4)))*(1-cit_rate))/(1+discount_rate)^2.5 -> 27156.382 | D14: =((((adoption_max/(1+EXP(-adoption_steepness*(2028-adoption_midpoint)))*(1-churn_rate))*(cert_fee_yr1*(1+cert_fee_escalation)^2.5+training_pct*training_fee+audit_fee)*5)+(IF((adoption_max/(1+EXP(-adoption_steepness*(2028-adoption_midpoint)))*(1-churn_rate))>=stage2_gate,ecom_market_base*(1+ecom_growth_rate)^4*platform_market_share*tx_take_rate*1000*3,0))-((IF((adoption_max/(1+EXP(-adoption_steepness*(2028-adoption_midpoint)))*(1-churn_rate))>=stage2_gate,ecom_market_base*(1+ecom_growth_rate)^4*platform_market_share*tx_take_rate*1000*3,0))*payment_proc_pct)-(capex_total+(33*30*12*(1+bhxh_rate)*(1+salary_escalation)^2*5)+(opex_marketing*(1+marketing_growth)^2*5)+(opex_cloud_base*1*5+(adoption_max/(1+EXP(-adoption_steepness*(2028-adoption_midpoint)))*(1-churn_rate))*vcr_per_enterprise*12*cloud_per_1M_vcr/1000000*5)+((opex_branding+opex_external+opex_legal+opex_security+opex_partner_mgmt)*5)+(capex_total*capex_maintenance_pct*4)))*(1-cit_rate))/(1+discount_rate)^2.5 -> 25781.423 | E14: =((((adoption_max/(1+EXP(-adoption_steepness*(2028-adoption_midpoint)))*(1-churn_rate))*(cert_fee_yr1*(1+cert_fee_escalation)^2.5+training_pct*training_fee+audit_fee)*5)+(IF((adoption_max/(1+EXP(-adoption_steepness*(2028-adoption_midpoint)))*(1-churn_rate))>=stage2_gate,ecom_market_base*(1+ecom_growth_rate)^4*platform_market_share*tx_take_rate*1000*3,0))-((IF((adoption_max/(1+EXP(-adoption_steepness*(2028-adoption_midpoint)))*(1-churn_rate))>=stage2_gate,ecom_market_base*(1+ecom_growth_rate)^4*platform_market_share*tx_take_rate*1000*3,0))*payment_proc_pct)-(capex_total+(33*30*12*(1+bhxh_rate)*(1+salary_escalation)^2*5)+(opex_marketing*(1+marketing_growth)^2*5)+(opex_cloud_base*1.15*5+(adoption_max/(1+EXP(-adoption_steepness*(2028-adoption_midpoint)))*(1-churn_rate))*vcr_per_enterprise*12*cloud_per_1M_vcr/1000000*5)+((opex_branding+opex_external+opex_legal+opex_security+opex_partner_mgmt)*5)+(capex_total*capex_maintenance_pct*4)))*(1-cit_rate))/(1+discount_rate)^2.5 -> 24406.463 | F14: =((((adoption_max/(1+EXP(-adoption_steepness*(2028-adoption_midpoint)))*(1-churn_rate))*(cert_fee_yr1*(1+cert_fee_escalation)^2.5+training_pct*training_fee+audit_fee)*5)+(IF((adoption_max/(1+EXP(-adoption_steepness*(2028-adoption_midpoint)))*(1-churn_rate))>=stage2_gate,ecom_market_base*(1+ecom_growth_rate)^4*platform_market_share*tx_take_rate*1000*3,0))-((IF((adoption_max/(1+EXP(-adoption_steepness*(2028-adoption_midpoint)))*(1-churn_rate))>=stage2_gate,ecom_market_base*(1+ecom_growth_rate)^4*platform_market_share*tx_take_rate*1000*3,0))*payment_proc_pct)-(capex_total+(33*30*12*(1+bhxh_rate)*(1+salary_escalation)^2*5)+(opex_marketing*(1+marketing_growth)^2*5)+(opex_cloud_base*1.3*5+(adoption_max/(1+EXP(-adoption_steepness*(2028-adoption_midpoint)))*(1-churn_rate))*vcr_per_enterprise*12*cloud_per_1M_vcr/1000000*5)+((opex_branding+opex_external+opex_legal+opex_security+opex_partner_mgmt)*5)+(capex_total*capex_maintenance_pct*4)))*(1-cit_rate))/(1+discount_rate)^2.5 -> 23031.503 | G14: =opex_cloud_base -> 3250 | H14: ↑ cloud → ↓ profit
A15: BHXH rate | B15: =((((adoption_max/(1+EXP(-adoption_steepness*(2028-adoption_midpoint)))*(1-churn_rate))*(cert_fee_yr1*(1+cert_fee_escalation)^2.5+training_pct*training_fee+audit_fee)*5)+(IF((adoption_max/(1+EXP(-adoption_steepness*(2028-adoption_midpoint)))*(1-churn_rate))>=stage2_gate,ecom_market_base*(1+ecom_growth_rate)^4*platform_market_share*tx_take_rate*1000*3,0))-((IF((adoption_max/(1+EXP(-adoption_steepness*(2028-adoption_midpoint)))*(1-churn_rate))>=stage2_gate,ecom_market_base*(1+ecom_growth_rate)^4*platform_market_share*tx_take_rate*1000*3,0))*payment_proc_pct)-(capex_total+(33*30*12*(1+bhxh_rate*0.7)*(1+salary_escalation)^2*5)+(opex_marketing*(1+marketing_growth)^2*5)+(opex_cloud_base*5+(adoption_max/(1+EXP(-adoption_steepness*(2028-adoption_midpoint)))*(1-churn_rate))*vcr_per_enterprise*12*cloud_per_1M_vcr/1000000*5)+((opex_branding+opex_external+opex_legal+opex_security+opex_partner_mgmt)*5)+(capex_total*capex_maintenance_pct*4)))*(1-cit_rate))/(1+discount_rate)^2.5 -> 28396.454 | C15: =((((adoption_max/(1+EXP(-adoption_steepness*(2028-adoption_midpoint)))*(1-churn_rate))*(cert_fee_yr1*(1+cert_fee_escalation)^2.5+training_pct*training_fee+audit_fee)*5)+(IF((adoption_max/(1+EXP(-adoption_steepness*(2028-adoption_midpoint)))*(1-churn_rate))>=stage2_gate,ecom_market_base*(1+ecom_growth_rate)^4*platform_market_share*tx_take_rate*1000*3,0))-((IF((adoption_max/(1+EXP(-adoption_steepness*(2028-adoption_midpoint)))*(1-churn_rate))>=stage2_gate,ecom_market_base*(1+ecom_growth_rate)^4*platform_market_share*tx_take_rate*1000*3,0))*payment_proc_pct)-(capex_total+(33*30*12*(1+bhxh_rate*0.85)*(1+salary_escalation)^2*5)+(opex_marketing*(1+marketing_growth)^2*5)+(opex_cloud_base*5+(adoption_max/(1+EXP(-adoption_steepness*(2028-adoption_midpoint)))*(1-churn_rate))*vcr_per_enterprise*12*cloud_per_1M_vcr/1000000*5)+((opex_branding+opex_external+opex_legal+opex_security+opex_partner_mgmt)*5)+(capex_total*capex_maintenance_pct*4)))*(1-cit_rate))/(1+discount_rate)^2.5 -> 27088.938 | D15: =((((adoption_max/(1+EXP(-adoption_steepness*(2028-adoption_midpoint)))*(1-churn_rate))*(cert_fee_yr1*(1+cert_fee_escalation)^2.5+training_pct*training_fee+audit_fee)*5)+(IF((adoption_max/(1+EXP(-adoption_steepness*(2028-adoption_midpoint)))*(1-churn_rate))>=stage2_gate,ecom_market_base*(1+ecom_growth_rate)^4*platform_market_share*tx_take_rate*1000*3,0))-((IF((adoption_max/(1+EXP(-adoption_steepness*(2028-adoption_midpoint)))*(1-churn_rate))>=stage2_gate,ecom_market_base*(1+ecom_growth_rate)^4*platform_market_share*tx_take_rate*1000*3,0))*payment_proc_pct)-(capex_total+(33*30*12*(1+bhxh_rate*1)*(1+salary_escalation)^2*5)+(opex_marketing*(1+marketing_growth)^2*5)+(opex_cloud_base*5+(adoption_max/(1+EXP(-adoption_steepness*(2028-adoption_midpoint)))*(1-churn_rate))*vcr_per_enterprise*12*cloud_per_1M_vcr/1000000*5)+((opex_branding+opex_external+opex_legal+opex_security+opex_partner_mgmt)*5)+(capex_total*capex_maintenance_pct*4)))*(1-cit_rate))/(1+discount_rate)^2.5 -> 25781.423 | E15: =((((adoption_max/(1+EXP(-adoption_steepness*(2028-adoption_midpoint)))*(1-churn_rate))*(cert_fee_yr1*(1+cert_fee_escalation)^2.5+training_pct*training_fee+audit_fee)*5)+(IF((adoption_max/(1+EXP(-adoption_steepness*(2028-adoption_midpoint)))*(1-churn_rate))>=stage2_gate,ecom_market_base*(1+ecom_growth_rate)^4*platform_market_share*tx_take_rate*1000*3,0))-((IF((adoption_max/(1+EXP(-adoption_steepness*(2028-adoption_midpoint)))*(1-churn_rate))>=stage2_gate,ecom_market_base*(1+ecom_growth_rate)^4*platform_market_share*tx_take_rate*1000*3,0))*payment_proc_pct)-(capex_total+(33*30*12*(1+bhxh_rate*1.15)*(1+salary_escalation)^2*5)+(opex_marketing*(1+marketing_growth)^2*5)+(opex_cloud_base*5+(adoption_max/(1+EXP(-adoption_steepness*(2028-adoption_midpoint)))*(1-churn_rate))*vcr_per_enterprise*12*cloud_per_1M_vcr/1000000*5)+((opex_branding+opex_external+opex_legal+opex_security+opex_partner_mgmt)*5)+(capex_total*capex_maintenance_pct*4)))*(1-cit_rate))/(1+discount_rate)^2.5 -> 24473.907 | F15: =((((adoption_max/(1+EXP(-adoption_steepness*(2028-adoption_midpoint)))*(1-churn_rate))*(cert_fee_yr1*(1+cert_fee_escalation)^2.5+training_pct*training_fee+audit_fee)*5)+(IF((adoption_max/(1+EXP(-adoption_steepness*(2028-adoption_midpoint)))*(1-churn_rate))>=stage2_gate,ecom_market_base*(1+ecom_growth_rate)^4*platform_market_share*tx_take_rate*1000*3,0))-((IF((adoption_max/(1+EXP(-adoption_steepness*(2028-adoption_midpoint)))*(1-churn_rate))>=stage2_gate,ecom_market_base*(1+ecom_growth_rate)^4*platform_market_share*tx_take_rate*1000*3,0))*payment_proc_pct)-(capex_total+(33*30*12*(1+bhxh_rate*1.3)*(1+salary_escalation)^2*5)+(opex_marketing*(1+marketing_growth)^2*5)+(opex_cloud_base*5+(adoption_max/(1+EXP(-adoption_steepness*(2028-adoption_midpoint)))*(1-churn_rate))*vcr_per_enterprise*12*cloud_per_1M_vcr/1000000*5)+((opex_branding+opex_external+opex_legal+opex_security+opex_partner_mgmt)*5)+(capex_total*capex_maintenance_pct*4)))*(1-cit_rate))/(1+discount_rate)^2.5 -> 23166.391 | G15: =bhxh_rate -> 0.215 | H15: ↑ BHXH → ↑ HR cost
A16: CIT rate | B16: =((((adoption_max/(1+EXP(-adoption_steepness*(2028-adoption_midpoint)))*(1-churn_rate))*(cert_fee_yr1*(1+cert_fee_escalation)^2.5+training_pct*training_fee+audit_fee)*5)+(IF((adoption_max/(1+EXP(-adoption_steepness*(2028-adoption_midpoint)))*(1-churn_rate))>=stage2_gate,ecom_market_base*(1+ecom_growth_rate)^4*platform_market_share*tx_take_rate*1000*3,0))-((IF((adoption_max/(1+EXP(-adoption_steepness*(2028-adoption_midpoint)))*(1-churn_rate))>=stage2_gate,ecom_market_base*(1+ecom_growth_rate)^4*platform_market_share*tx_take_rate*1000*3,0))*payment_proc_pct)-(capex_total+(33*30*12*(1+bhxh_rate)*(1+salary_escalation)^2*5)+(opex_marketing*(1+marketing_growth)^2*5)+(opex_cloud_base*5+(adoption_max/(1+EXP(-adoption_steepness*(2028-adoption_midpoint)))*(1-churn_rate))*vcr_per_enterprise*12*cloud_per_1M_vcr/1000000*5)+((opex_branding+opex_external+opex_legal+opex_security+opex_partner_mgmt)*5)+(capex_total*capex_maintenance_pct*4)))*(1-cit_rate*0.7))/(1+discount_rate)^2.5 -> 27715.029 | C16: =((((adoption_max/(1+EXP(-adoption_steepness*(2028-adoption_midpoint)))*(1-churn_rate))*(cert_fee_yr1*(1+cert_fee_escalation)^2.5+training_pct*training_fee+audit_fee)*5)+(IF((adoption_max/(1+EXP(-adoption_steepness*(2028-adoption_midpoint)))*(1-churn_rate))>=stage2_gate,ecom_market_base*(1+ecom_growth_rate)^4*platform_market_share*tx_take_rate*1000*3,0))-((IF((adoption_max/(1+EXP(-adoption_steepness*(2028-adoption_midpoint)))*(1-churn_rate))>=stage2_gate,ecom_market_base*(1+ecom_growth_rate)^4*platform_market_share*tx_take_rate*1000*3,0))*payment_proc_pct)-(capex_total+(33*30*12*(1+bhxh_rate)*(1+salary_escalation)^2*5)+(opex_marketing*(1+marketing_growth)^2*5)+(opex_cloud_base*5+(adoption_max/(1+EXP(-adoption_steepness*(2028-adoption_midpoint)))*(1-churn_rate))*vcr_per_enterprise*12*cloud_per_1M_vcr/1000000*5)+((opex_branding+opex_external+opex_legal+opex_security+opex_partner_mgmt)*5)+(capex_total*capex_maintenance_pct*4)))*(1-cit_rate*0.85))/(1+discount_rate)^2.5 -> 26748.226 | D16: =((((adoption_max/(1+EXP(-adoption_steepness*(2028-adoption_midpoint)))*(1-churn_rate))*(cert_fee_yr1*(1+cert_fee_escalation)^2.5+training_pct*training_fee+audit_fee)*5)+(IF((adoption_max/(1+EXP(-adoption_steepness*(2028-adoption_midpoint)))*(1-churn_rate))>=stage2_gate,ecom_market_base*(1+ecom_growth_rate)^4*platform_market_share*tx_take_rate*1000*3,0))-((IF((adoption_max/(1+EXP(-adoption_steepness*(2028-adoption_midpoint)))*(1-churn_rate))>=stage2_gate,ecom_market_base*(1+ecom_growth_rate)^4*platform_market_share*tx_take_rate*1000*3,0))*payment_proc_pct)-(capex_total+(33*30*12*(1+bhxh_rate)*(1+salary_escalation)^2*5)+(opex_marketing*(1+marketing_growth)^2*5)+(opex_cloud_base*5+(adoption_max/(1+EXP(-adoption_steepness*(2028-adoption_midpoint)))*(1-churn_rate))*vcr_per_enterprise*12*cloud_per_1M_vcr/1000000*5)+((opex_branding+opex_external+opex_legal+opex_security+opex_partner_mgmt)*5)+(capex_total*capex_maintenance_pct*4)))*(1-cit_rate*1))/(1+discount_rate)^2.5 -> 25781.423 | E16: =((((adoption_max/(1+EXP(-adoption_steepness*(2028-adoption_midpoint)))*(1-churn_rate))*(cert_fee_yr1*(1+cert_fee_escalation)^2.5+training_pct*training_fee+audit_fee)*5)+(IF((adoption_max/(1+EXP(-adoption_steepness*(2028-adoption_midpoint)))*(1-churn_rate))>=stage2_gate,ecom_market_base*(1+ecom_growth_rate)^4*platform_market_share*tx_take_rate*1000*3,0))-((IF((adoption_max/(1+EXP(-adoption_steepness*(2028-adoption_midpoint)))*(1-churn_rate))>=stage2_gate,ecom_market_base*(1+ecom_growth_rate)^4*platform_market_share*tx_take_rate*1000*3,0))*payment_proc_pct)-(capex_total+(33*30*12*(1+bhxh_rate)*(1+salary_escalation)^2*5)+(opex_marketing*(1+marketing_growth)^2*5)+(opex_cloud_base*5+(adoption_max/(1+EXP(-adoption_steepness*(2028-adoption_midpoint)))*(1-churn_rate))*vcr_per_enterprise*12*cloud_per_1M_vcr/1000000*5)+((opex_branding+opex_external+opex_legal+opex_security+opex_partner_mgmt)*5)+(capex_total*capex_maintenance_pct*4)))*(1-cit_rate*1.15))/(1+discount_rate)^2.5 -> 24814.619 | F16: =((((adoption_max/(1+EXP(-adoption_steepness*(2028-adoption_midpoint)))*(1-churn_rate))*(cert_fee_yr1*(1+cert_fee_escalation)^2.5+training_pct*training_fee+audit_fee)*5)+(IF((adoption_max/(1+EXP(-adoption_steepness*(2028-adoption_midpoint)))*(1-churn_rate))>=stage2_gate,ecom_market_base*(1+ecom_growth_rate)^4*platform_market_share*tx_take_rate*1000*3,0))-((IF((adoption_max/(1+EXP(-adoption_steepness*(2028-adoption_midpoint)))*(1-churn_rate))>=stage2_gate,ecom_market_base*(1+ecom_growth_rate)^4*platform_market_share*tx_take_rate*1000*3,0))*payment_proc_pct)-(capex_total+(33*30*12*(1+bhxh_rate)*(1+salary_escalation)^2*5)+(opex_marketing*(1+marketing_growth)^2*5)+(opex_cloud_base*5+(adoption_max/(1+EXP(-adoption_steepness*(2028-adoption_midpoint)))*(1-churn_rate))*vcr_per_enterprise*12*cloud_per_1M_vcr/1000000*5)+((opex_branding+opex_external+opex_legal+opex_security+opex_partner_mgmt)*5)+(capex_total*capex_maintenance_pct*4)))*(1-cit_rate*1.3))/(1+discount_rate)^2.5 -> 23847.816 | G16: =cit_rate -> 0.2 | H16: ↑ tax → ↓ net income
A19: TWO-WAY NPV: adoption_max × platform_market_share (Tr VND)
A20: adoption ↓ \ mkt_share → | B20: 0.001 | C20: 0.003 | D20: 0.005 | E20: 0.008 | F20: 0.01 | G20: 0.015 | H20: 0.02
A21: 200 | B21: =((((200/(1+EXP(-adoption_steepness*(2028-adoption_midpoint)))*(1-churn_rate))*(cert_fee_yr1*(1+cert_fee_escalation)^2.5+training_pct*training_fee+audit_fee)*5)+(IF((200/(1+EXP(-adoption_steepness*(2028-adoption_midpoint)))*(1-churn_rate))>=stage2_gate,ecom_market_base*(1+ecom_growth_rate)^4*0.001*tx_take_rate*1000*3,0))-((IF((200/(1+EXP(-adoption_steepness*(2028-adoption_midpoint)))*(1-churn_rate))>=stage2_gate,ecom_market_base*(1+ecom_growth_rate)^4*0.001*tx_take_rate*1000*3,0))*payment_proc_pct)-(capex_total+(33*30*12*(1+bhxh_rate)*(1+salary_escalation)^2*5)+(opex_marketing*(1+marketing_growth)^2*5)+(opex_cloud_base*5+(200/(1+EXP(-adoption_steepness*(2028-adoption_midpoint)))*(1-churn_rate))*vcr_per_enterprise*12*cloud_per_1M_vcr/1000000*5)+((opex_branding+opex_external+opex_legal+opex_security+opex_partner_mgmt)*5)+(capex_total*capex_maintenance_pct*4)))*(1-cit_rate))/(1+discount_rate)^2.5 -> -95433.633 | C21: =((((200/(1+EXP(-adoption_steepness*(2028-adoption_midpoint)))*(1-churn_rate))*(cert_fee_yr1*(1+cert_fee_escalation)^2.5+training_pct*training_fee+audit_fee)*5)+(IF((200/(1+EXP(-adoption_steepness*(2028-adoption_midpoint)))*(1-churn_rate))>=stage2_gate,ecom_market_base*(1+ecom_growth_rate)^4*0.003*tx_take_rate*1000*3,0))-((IF((200/(1+EXP(-adoption_steepness*(2028-adoption_midpoint)))*(1-churn_rate))>=stage2_gate,ecom_market_base*(1+ecom_growth_rate)^4*0.003*tx_take_rate*1000*3,0))*payment_proc_pct)-(capex_total+(33*30*12*(1+bhxh_rate)*(1+salary_escalation)^2*5)+(opex_marketing*(1+marketing_growth)^2*5)+(opex_cloud_base*5+(200/(1+EXP(-adoption_steepness*(2028-adoption_midpoint)))*(1-churn_rate))*vcr_per_enterprise*12*cloud_per_1M_vcr/1000000*5)+((opex_branding+opex_external+opex_legal+opex_security+opex_partner_mgmt)*5)+(capex_total*capex_maintenance_pct*4)))*(1-cit_rate))/(1+discount_rate)^2.5 -> -95433.633 | D21: =((((200/(1+EXP(-adoption_steepness*(2028-adoption_midpoint)))*(1-churn_rate))*(cert_fee_yr1*(1+cert_fee_escalation)^2.5+training_pct*training_fee+audit_fee)*5)+(IF((200/(1+EXP(-adoption_steepness*(2028-adoption_midpoint)))*(1-churn_rate))>=stage2_gate,ecom_market_base*(1+ecom_growth_rate)^4*0.005*tx_take_rate*1000*3,0))-((IF((200/(1+EXP(-adoption_steepness*(2028-adoption_midpoint)))*(1-churn_rate))>=stage2_gate,ecom_market_base*(1+ecom_growth_rate)^4*0.005*tx_take_rate*1000*3,0))*payment_proc_pct)-(capex_total+(33*30*12*(1+bhxh_rate)*(1+salary_escalation)^2*5)+(opex_marketing*(1+marketing_growth)^2*5)+(opex_cloud_base*5+(200/(1+EXP(-adoption_steepness*(2028-adoption_midpoint)))*(1-churn_rate))*vcr_per_enterprise*12*cloud_per_1M_vcr/1000000*5)+((opex_branding+opex_external+opex_legal+opex_security+opex_partner_mgmt)*5)+(capex_total*capex_maintenance_pct*4)))*(1-cit_rate))/(1+discount_rate)^2.5 -> -95433.633 | E21: =((((200/(1+EXP(-adoption_steepness*(2028-adoption_midpoint)))*(1-churn_rate))*(cert_fee_yr1*(1+cert_fee_escalation)^2.5+training_pct*training_fee+audit_fee)*5)+(IF((200/(1+EXP(-adoption_steepness*(2028-adoption_midpoint)))*(1-churn_rate))>=stage2_gate,ecom_market_base*(1+ecom_growth_rate)^4*0.008*tx_take_rate*1000*3,0))-((IF((200/(1+EXP(-adoption_steepness*(2028-adoption_midpoint)))*(1-churn_rate))>=stage2_gate,ecom_market_base*(1+ecom_growth_rate)^4*0.008*tx_take_rate*1000*3,0))*payment_proc_pct)-(capex_total+(33*30*12*(1+bhxh_rate)*(1+salary_escalation)^2*5)+(opex_marketing*(1+marketing_growth)^2*5)+(opex_cloud_base*5+(200/(1+EXP(-adoption_steepness*(2028-adoption_midpoint)))*(1-churn_rate))*vcr_per_enterprise*12*cloud_per_1M_vcr/1000000*5)+((opex_branding+opex_external+opex_legal+opex_security+opex_partner_mgmt)*5)+(capex_total*capex_maintenance_pct*4)))*(1-cit_rate))/(1+discount_rate)^2.5 -> -95433.633 | F21: =((((200/(1+EXP(-adoption_steepness*(2028-adoption_midpoint)))*(1-churn_rate))*(cert_fee_yr1*(1+cert_fee_escalation)^2.5+training_pct*training_fee+audit_fee)*5)+(IF((200/(1+EXP(-adoption_steepness*(2028-adoption_midpoint)))*(1-churn_rate))>=stage2_gate,ecom_market_base*(1+ecom_growth_rate)^4*0.01*tx_take_rate*1000*3,0))-((IF((200/(1+EXP(-adoption_steepness*(2028-adoption_midpoint)))*(1-churn_rate))>=stage2_gate,ecom_market_base*(1+ecom_growth_rate)^4*0.01*tx_take_rate*1000*3,0))*payment_proc_pct)-(capex_total+(33*30*12*(1+bhxh_rate)*(1+salary_escalation)^2*5)+(opex_marketing*(1+marketing_growth)^2*5)+(opex_cloud_base*5+(200/(1+EXP(-adoption_steepness*(2028-adoption_midpoint)))*(1-churn_rate))*vcr_per_enterprise*12*cloud_per_1M_vcr/1000000*5)+((opex_branding+opex_external+opex_legal+opex_security+opex_partner_mgmt)*5)+(capex_total*capex_maintenance_pct*4)))*(1-cit_rate))/(1+discount_rate)^2.5 -> -95433.633 | G21: =((((200/(1+EXP(-adoption_steepness*(2028-adoption_midpoint)))*(1-churn_rate))*(cert_fee_yr1*(1+cert_fee_escalation)^2.5+training_pct*training_fee+audit_fee)*5)+(IF((200/(1+EXP(-adoption_steepness*(2028-adoption_midpoint)))*(1-churn_rate))>=stage2_gate,ecom_market_base*(1+ecom_growth_rate)^4*0.015*tx_take_rate*1000*3,0))-((IF((200/(1+EXP(-adoption_steepness*(2028-adoption_midpoint)))*(1-churn_rate))>=stage2_gate,ecom_market_base*(1+ecom_growth_rate)^4*0.015*tx_take_rate*1000*3,0))*payment_proc_pct)-(capex_total+(33*30*12*(1+bhxh_rate)*(1+salary_escalation)^2*5)+(opex_marketing*(1+marketing_growth)^2*5)+(opex_cloud_base*5+(200/(1+EXP(-adoption_steepness*(2028-adoption_midpoint)))*(1-churn_rate))*vcr_per_enterprise*12*cloud_per_1M_vcr/1000000*5)+((opex_branding+opex_external+opex_legal+opex_security+opex_partner_mgmt)*5)+(capex_total*capex_maintenance_pct*4)))*(1-cit_rate))/(1+discount_rate)^2.5 -> -95433.633 | H21: =((((200/(1+EXP(-adoption_steepness*(2028-adoption_midpoint)))*(1-churn_rate))*(cert_fee_yr1*(1+cert_fee_escalation)^2.5+training_pct*training_fee+audit_fee)*5)+(IF((200/(1+EXP(-adoption_steepness*(2028-adoption_midpoint)))*(1-churn_rate))>=stage2_gate,ecom_market_base*(1+ecom_growth_rate)^4*0.02*tx_take_rate*1000*3,0))-((IF((200/(1+EXP(-adoption_steepness*(2028-adoption_midpoint)))*(1-churn_rate))>=stage2_gate,ecom_market_base*(1+ecom_growth_rate)^4*0.02*tx_take_rate*1000*3,0))*payment_proc_pct)-(capex_total+(33*30*12*(1+bhxh_rate)*(1+salary_escalation)^2*5)+(opex_marketing*(1+marketing_growth)^2*5)+(opex_cloud_base*5+(200/(1+EXP(-adoption_steepness*(2028-adoption_midpoint)))*(1-churn_rate))*vcr_per_enterprise*12*cloud_per_1M_vcr/1000000*5)+((opex_branding+opex_external+opex_legal+opex_security+opex_partner_mgmt)*5)+(capex_total*capex_maintenance_pct*4)))*(1-cit_rate))/(1+discount_rate)^2.5 -> -95433.633
A22: 400 | B22: =((((400/(1+EXP(-adoption_steepness*(2028-adoption_midpoint)))*(1-churn_rate))*(cert_fee_yr1*(1+cert_fee_escalation)^2.5+training_pct*training_fee+audit_fee)*5)+(IF((400/(1+EXP(-adoption_steepness*(2028-adoption_midpoint)))*(1-churn_rate))>=stage2_gate,ecom_market_base*(1+ecom_growth_rate)^4*0.001*tx_take_rate*1000*3,0))-((IF((400/(1+EXP(-adoption_steepness*(2028-adoption_midpoint)))*(1-churn_rate))>=stage2_gate,ecom_market_base*(1+ecom_growth_rate)^4*0.001*tx_take_rate*1000*3,0))*payment_proc_pct)-(capex_total+(33*30*12*(1+bhxh_rate)*(1+salary_escalation)^2*5)+(opex_marketing*(1+marketing_growth)^2*5)+(opex_cloud_base*5+(400/(1+EXP(-adoption_steepness*(2028-adoption_midpoint)))*(1-churn_rate))*vcr_per_enterprise*12*cloud_per_1M_vcr/1000000*5)+((opex_branding+opex_external+opex_legal+opex_security+opex_partner_mgmt)*5)+(capex_total*capex_maintenance_pct*4)))*(1-cit_rate))/(1+discount_rate)^2.5 -> -86005.914 | C22: =((((400/(1+EXP(-adoption_steepness*(2028-adoption_midpoint)))*(1-churn_rate))*(cert_fee_yr1*(1+cert_fee_escalation)^2.5+training_pct*training_fee+audit_fee)*5)+(IF((400/(1+EXP(-adoption_steepness*(2028-adoption_midpoint)))*(1-churn_rate))>=stage2_gate,ecom_market_base*(1+ecom_growth_rate)^4*0.003*tx_take_rate*1000*3,0))-((IF((400/(1+EXP(-adoption_steepness*(2028-adoption_midpoint)))*(1-churn_rate))>=stage2_gate,ecom_market_base*(1+ecom_growth_rate)^4*0.003*tx_take_rate*1000*3,0))*payment_proc_pct)-(capex_total+(33*30*12*(1+bhxh_rate)*(1+salary_escalation)^2*5)+(opex_marketing*(1+marketing_growth)^2*5)+(opex_cloud_base*5+(400/(1+EXP(-adoption_steepness*(2028-adoption_midpoint)))*(1-churn_rate))*vcr_per_enterprise*12*cloud_per_1M_vcr/1000000*5)+((opex_branding+opex_external+opex_legal+opex_security+opex_partner_mgmt)*5)+(capex_total*capex_maintenance_pct*4)))*(1-cit_rate))/(1+discount_rate)^2.5 -> -86005.914 | D22: =((((400/(1+EXP(-adoption_steepness*(2028-adoption_midpoint)))*(1-churn_rate))*(cert_fee_yr1*(1+cert_fee_escalation)^2.5+training_pct*training_fee+audit_fee)*5)+(IF((400/(1+EXP(-adoption_steepness*(2028-adoption_midpoint)))*(1-churn_rate))>=stage2_gate,ecom_market_base*(1+ecom_growth_rate)^4*0.005*tx_take_rate*1000*3,0))-((IF((400/(1+EXP(-adoption_steepness*(2028-adoption_midpoint)))*(1-churn_rate))>=stage2_gate,ecom_market_base*(1+ecom_growth_rate)^4*0.005*tx_take_rate*1000*3,0))*payment_proc_pct)-(capex_total+(33*30*12*(1+bhxh_rate)*(1+salary_escalation)^2*5)+(opex_marketing*(1+marketing_growth)^2*5)+(opex_cloud_base*5+(400/(1+EXP(-adoption_steepness*(2028-adoption_midpoint)))*(1-churn_rate))*vcr_per_enterprise*12*cloud_per_1M_vcr/1000000*5)+((opex_branding+opex_external+opex_legal+opex_security+opex_partner_mgmt)*5)+(capex_total*capex_maintenance_pct*4)))*(1-cit_rate))/(1+discount_rate)^2.5 -> -86005.914 | E22: =((((400/(1+EXP(-adoption_steepness*(2028-adoption_midpoint)))*(1-churn_rate))*(cert_fee_yr1*(1+cert_fee_escalation)^2.5+training_pct*training_fee+audit_fee)*5)+(IF((400/(1+EXP(-adoption_steepness*(2028-adoption_midpoint)))*(1-churn_rate))>=stage2_gate,ecom_market_base*(1+ecom_growth_rate)^4*0.008*tx_take_rate*1000*3,0))-((IF((400/(1+EXP(-adoption_steepness*(2028-adoption_midpoint)))*(1-churn_rate))>=stage2_gate,ecom_market_base*(1+ecom_growth_rate)^4*0.008*tx_take_rate*1000*3,0))*payment_proc_pct)-(capex_total+(33*30*12*(1+bhxh_rate)*(1+salary_escalation)^2*5)+(opex_marketing*(1+marketing_growth)^2*5)+(opex_cloud_base*5+(400/(1+EXP(-adoption_steepness*(2028-adoption_midpoint)))*(1-churn_rate))*vcr_per_enterprise*12*cloud_per_1M_vcr/1000000*5)+((opex_branding+opex_external+opex_legal+opex_security+opex_partner_mgmt)*5)+(capex_total*capex_maintenance_pct*4)))*(1-cit_rate))/(1+discount_rate)^2.5 -> -86005.914 | F22: =((((400/(1+EXP(-adoption_steepness*(2028-adoption_midpoint)))*(1-churn_rate))*(cert_fee_yr1*(1+cert_fee_escalation)^2.5+training_pct*training_fee+audit_fee)*5)+(IF((400/(1+EXP(-adoption_steepness*(2028-adoption_midpoint)))*(1-churn_rate))>=stage2_gate,ecom_market_base*(1+ecom_growth_rate)^4*0.01*tx_take_rate*1000*3,0))-((IF((400/(1+EXP(-adoption_steepness*(2028-adoption_midpoint)))*(1-churn_rate))>=stage2_gate,ecom_market_base*(1+ecom_growth_rate)^4*0.01*tx_take_rate*1000*3,0))*payment_proc_pct)-(capex_total+(33*30*12*(1+bhxh_rate)*(1+salary_escalation)^2*5)+(opex_marketing*(1+marketing_growth)^2*5)+(opex_cloud_base*5+(400/(1+EXP(-adoption_steepness*(2028-adoption_midpoint)))*(1-churn_rate))*vcr_per_enterprise*12*cloud_per_1M_vcr/1000000*5)+((opex_branding+opex_external+opex_legal+opex_security+opex_partner_mgmt)*5)+(capex_total*capex_maintenance_pct*4)))*(1-cit_rate))/(1+discount_rate)^2.5 -> -86005.914 | G22: =((((400/(1+EXP(-adoption_steepness*(2028-adoption_midpoint)))*(1-churn_rate))*(cert_fee_yr1*(1+cert_fee_escalation)^2.5+training_pct*training_fee+audit_fee)*5)+(IF((400/(1+EXP(-adoption_steepness*(2028-adoption_midpoint)))*(1-churn_rate))>=stage2_gate,ecom_market_base*(1+ecom_growth_rate)^4*0.015*tx_take_rate*1000*3,0))-((IF((400/(1+EXP(-adoption_steepness*(2028-adoption_midpoint)))*(1-churn_rate))>=stage2_gate,ecom_market_base*(1+ecom_growth_rate)^4*0.015*tx_take_rate*1000*3,0))*payment_proc_pct)-(capex_total+(33*30*12*(1+bhxh_rate)*(1+salary_escalation)^2*5)+(opex_marketing*(1+marketing_growth)^2*5)+(opex_cloud_base*5+(400/(1+EXP(-adoption_steepness*(2028-adoption_midpoint)))*(1-churn_rate))*vcr_per_enterprise*12*cloud_per_1M_vcr/1000000*5)+((opex_branding+opex_external+opex_legal+opex_security+opex_partner_mgmt)*5)+(capex_total*capex_maintenance_pct*4)))*(1-cit_rate))/(1+discount_rate)^2.5 -> -86005.914 | H22: =((((400/(1+EXP(-adoption_steepness*(2028-adoption_midpoint)))*(1-churn_rate))*(cert_fee_yr1*(1+cert_fee_escalation)^2.5+training_pct*training_fee+audit_fee)*5)+(IF((400/(1+EXP(-adoption_steepness*(2028-adoption_midpoint)))*(1-churn_rate))>=stage2_gate,ecom_market_base*(1+ecom_growth_rate)^4*0.02*tx_take_rate*1000*3,0))-((IF((400/(1+EXP(-adoption_steepness*(2028-adoption_midpoint)))*(1-churn_rate))>=stage2_gate,ecom_market_base*(1+ecom_growth_rate)^4*0.02*tx_take_rate*1000*3,0))*payment_proc_pct)-(capex_total+(33*30*12*(1+bhxh_rate)*(1+salary_escalation)^2*5)+(opex_marketing*(1+marketing_growth)^2*5)+(opex_cloud_base*5+(400/(1+EXP(-adoption_steepness*(2028-adoption_midpoint)))*(1-churn_rate))*vcr_per_enterprise*12*cloud_per_1M_vcr/1000000*5)+((opex_branding+opex_external+opex_legal+opex_security+opex_partner_mgmt)*5)+(capex_total*capex_maintenance_pct*4)))*(1-cit_rate))/(1+discount_rate)^2.5 -> -86005.914
A23: 600 | B23: =((((600/(1+EXP(-adoption_steepness*(2028-adoption_midpoint)))*(1-churn_rate))*(cert_fee_yr1*(1+cert_fee_escalation)^2.5+training_pct*training_fee+audit_fee)*5)+(IF((600/(1+EXP(-adoption_steepness*(2028-adoption_midpoint)))*(1-churn_rate))>=stage2_gate,ecom_market_base*(1+ecom_growth_rate)^4*0.001*tx_take_rate*1000*3,0))-((IF((600/(1+EXP(-adoption_steepness*(2028-adoption_midpoint)))*(1-churn_rate))>=stage2_gate,ecom_market_base*(1+ecom_growth_rate)^4*0.001*tx_take_rate*1000*3,0))*payment_proc_pct)-(capex_total+(33*30*12*(1+bhxh_rate)*(1+salary_escalation)^2*5)+(opex_marketing*(1+marketing_growth)^2*5)+(opex_cloud_base*5+(600/(1+EXP(-adoption_steepness*(2028-adoption_midpoint)))*(1-churn_rate))*vcr_per_enterprise*12*cloud_per_1M_vcr/1000000*5)+((opex_branding+opex_external+opex_legal+opex_security+opex_partner_mgmt)*5)+(capex_total*capex_maintenance_pct*4)))*(1-cit_rate))/(1+discount_rate)^2.5 -> -76578.195 | C23: =((((600/(1+EXP(-adoption_steepness*(2028-adoption_midpoint)))*(1-churn_rate))*(cert_fee_yr1*(1+cert_fee_escalation)^2.5+training_pct*training_fee+audit_fee)*5)+(IF((600/(1+EXP(-adoption_steepness*(2028-adoption_midpoint)))*(1-churn_rate))>=stage2_gate,ecom_market_base*(1+ecom_growth_rate)^4*0.003*tx_take_rate*1000*3,0))-((IF((600/(1+EXP(-adoption_steepness*(2028-adoption_midpoint)))*(1-churn_rate))>=stage2_gate,ecom_market_base*(1+ecom_growth_rate)^4*0.003*tx_take_rate*1000*3,0))*payment_proc_pct)-(capex_total+(33*30*12*(1+bhxh_rate)*(1+salary_escalation)^2*5)+(opex_marketing*(1+marketing_growth)^2*5)+(opex_cloud_base*5+(600/(1+EXP(-adoption_steepness*(2028-adoption_midpoint)))*(1-churn_rate))*vcr_per_enterprise*12*cloud_per_1M_vcr/1000000*5)+((opex_branding+opex_external+opex_legal+opex_security+opex_partner_mgmt)*5)+(capex_total*capex_maintenance_pct*4)))*(1-cit_rate))/(1+discount_rate)^2.5 -> -76578.195 | D23: =((((600/(1+EXP(-adoption_steepness*(2028-adoption_midpoint)))*(1-churn_rate))*(cert_fee_yr1*(1+cert_fee_escalation)^2.5+training_pct*training_fee+audit_fee)*5)+(IF((600/(1+EXP(-adoption_steepness*(2028-adoption_midpoint)))*(1-churn_rate))>=stage2_gate,ecom_market_base*(1+ecom_growth_rate)^4*0.005*tx_take_rate*1000*3,0))-((IF((600/(1+EXP(-adoption_steepness*(2028-adoption_midpoint)))*(1-churn_rate))>=stage2_gate,ecom_market_base*(1+ecom_growth_rate)^4*0.005*tx_take_rate*1000*3,0))*payment_proc_pct)-(capex_total+(33*30*12*(1+bhxh_rate)*(1+salary_escalation)^2*5)+(opex_marketing*(1+marketing_growth)^2*5)+(opex_cloud_base*5+(600/(1+EXP(-adoption_steepness*(2028-adoption_midpoint)))*(1-churn_rate))*vcr_per_enterprise*12*cloud_per_1M_vcr/1000000*5)+((opex_branding+opex_external+opex_legal+opex_security+opex_partner_mgmt)*5)+(capex_total*capex_maintenance_pct*4)))*(1-cit_rate))/(1+discount_rate)^2.5 -> -76578.195 | E23: =((((600/(1+EXP(-adoption_steepness*(2028-adoption_midpoint)))*(1-churn_rate))*(cert_fee_yr1*(1+cert_fee_escalation)^2.5+training_pct*training_fee+audit_fee)*5)+(IF((600/(1+EXP(-adoption_steepness*(2028-adoption_midpoint)))*(1-churn_rate))>=stage2_gate,ecom_market_base*(1+ecom_growth_rate)^4*0.008*tx_take_rate*1000*3,0))-((IF((600/(1+EXP(-adoption_steepness*(2028-adoption_midpoint)))*(1-churn_rate))>=stage2_gate,ecom_market_base*(1+ecom_growth_rate)^4*0.008*tx_take_rate*1000*3,0))*payment_proc_pct)-(capex_total+(33*30*12*(1+bhxh_rate)*(1+salary_escalation)^2*5)+(opex_marketing*(1+marketing_growth)^2*5)+(opex_cloud_base*5+(600/(1+EXP(-adoption_steepness*(2028-adoption_midpoint)))*(1-churn_rate))*vcr_per_enterprise*12*cloud_per_1M_vcr/1000000*5)+((opex_branding+opex_external+opex_legal+opex_security+opex_partner_mgmt)*5)+(capex_total*capex_maintenance_pct*4)))*(1-cit_rate))/(1+discount_rate)^2.5 -> -76578.195 | F23: =((((600/(1+EXP(-adoption_steepness*(2028-adoption_midpoint)))*(1-churn_rate))*(cert_fee_yr1*(1+cert_fee_escalation)^2.5+training_pct*training_fee+audit_fee)*5)+(IF((600/(1+EXP(-adoption_steepness*(2028-adoption_midpoint)))*(1-churn_rate))>=stage2_gate,ecom_market_base*(1+ecom_growth_rate)^4*0.01*tx_take_rate*1000*3,0))-((IF((600/(1+EXP(-adoption_steepness*(2028-adoption_midpoint)))*(1-churn_rate))>=stage2_gate,ecom_market_base*(1+ecom_growth_rate)^4*0.01*tx_take_rate*1000*3,0))*payment_proc_pct)-(capex_total+(33*30*12*(1+bhxh_rate)*(1+salary_escalation)^2*5)+(opex_marketing*(1+marketing_growth)^2*5)+(opex_cloud_base*5+(600/(1+EXP(-adoption_steepness*(2028-adoption_midpoint)))*(1-churn_rate))*vcr_per_enterprise*12*cloud_per_1M_vcr/1000000*5)+((opex_branding+opex_external+opex_legal+opex_security+opex_partner_mgmt)*5)+(capex_total*capex_maintenance_pct*4)))*(1-cit_rate))/(1+discount_rate)^2.5 -> -76578.195 | G23: =((((600/(1+EXP(-adoption_steepness*(2028-adoption_midpoint)))*(1-churn_rate))*(cert_fee_yr1*(1+cert_fee_escalation)^2.5+training_pct*training_fee+audit_fee)*5)+(IF((600/(1+EXP(-adoption_steepness*(2028-adoption_midpoint)))*(1-churn_rate))>=stage2_gate,ecom_market_base*(1+ecom_growth_rate)^4*0.015*tx_take_rate*1000*3,0))-((IF((600/(1+EXP(-adoption_steepness*(2028-adoption_midpoint)))*(1-churn_rate))>=stage2_gate,ecom_market_base*(1+ecom_growth_rate)^4*0.015*tx_take_rate*1000*3,0))*payment_proc_pct)-(capex_total+(33*30*12*(1+bhxh_rate)*(1+salary_escalation)^2*5)+(opex_marketing*(1+marketing_growth)^2*5)+(opex_cloud_base*5+(600/(1+EXP(-adoption_steepness*(2028-adoption_midpoint)))*(1-churn_rate))*vcr_per_enterprise*12*cloud_per_1M_vcr/1000000*5)+((opex_branding+opex_external+opex_legal+opex_security+opex_partner_mgmt)*5)+(capex_total*capex_maintenance_pct*4)))*(1-cit_rate))/(1+discount_rate)^2.5 -> -76578.195 | H23: =((((600/(1+EXP(-adoption_steepness*(2028-adoption_midpoint)))*(1-churn_rate))*(cert_fee_yr1*(1+cert_fee_escalation)^2.5+training_pct*training_fee+audit_fee)*5)+(IF((600/(1+EXP(-adoption_steepness*(2028-adoption_midpoint)))*(1-churn_rate))>=stage2_gate,ecom_market_base*(1+ecom_growth_rate)^4*0.02*tx_take_rate*1000*3,0))-((IF((600/(1+EXP(-adoption_steepness*(2028-adoption_midpoint)))*(1-churn_rate))>=stage2_gate,ecom_market_base*(1+ecom_growth_rate)^4*0.02*tx_take_rate*1000*3,0))*payment_proc_pct)-(capex_total+(33*30*12*(1+bhxh_rate)*(1+salary_escalation)^2*5)+(opex_marketing*(1+marketing_growth)^2*5)+(opex_cloud_base*5+(600/(1+EXP(-adoption_steepness*(2028-adoption_midpoint)))*(1-churn_rate))*vcr_per_enterprise*12*cloud_per_1M_vcr/1000000*5)+((opex_branding+opex_external+opex_legal+opex_security+opex_partner_mgmt)*5)+(capex_total*capex_maintenance_pct*4)))*(1-cit_rate))/(1+discount_rate)^2.5 -> -76578.195
A24: 800 | B24: =((((800/(1+EXP(-adoption_steepness*(2028-adoption_midpoint)))*(1-churn_rate))*(cert_fee_yr1*(1+cert_fee_escalation)^2.5+training_pct*training_fee+audit_fee)*5)+(IF((800/(1+EXP(-adoption_steepness*(2028-adoption_midpoint)))*(1-churn_rate))>=stage2_gate,ecom_market_base*(1+ecom_growth_rate)^4*0.001*tx_take_rate*1000*3,0))-((IF((800/(1+EXP(-adoption_steepness*(2028-adoption_midpoint)))*(1-churn_rate))>=stage2_gate,ecom_market_base*(1+ecom_growth_rate)^4*0.001*tx_take_rate*1000*3,0))*payment_proc_pct)-(capex_total+(33*30*12*(1+bhxh_rate)*(1+salary_escalation)^2*5)+(opex_marketing*(1+marketing_growth)^2*5)+(opex_cloud_base*5+(800/(1+EXP(-adoption_steepness*(2028-adoption_midpoint)))*(1-churn_rate))*vcr_per_enterprise*12*cloud_per_1M_vcr/1000000*5)+((opex_branding+opex_external+opex_legal+opex_security+opex_partner_mgmt)*5)+(capex_total*capex_maintenance_pct*4)))*(1-cit_rate))/(1+discount_rate)^2.5 -> -63446.653 | C24: =((((800/(1+EXP(-adoption_steepness*(2028-adoption_midpoint)))*(1-churn_rate))*(cert_fee_yr1*(1+cert_fee_escalation)^2.5+training_pct*training_fee+audit_fee)*5)+(IF((800/(1+EXP(-adoption_steepness*(2028-adoption_midpoint)))*(1-churn_rate))>=stage2_gate,ecom_market_base*(1+ecom_growth_rate)^4*0.003*tx_take_rate*1000*3,0))-((IF((800/(1+EXP(-adoption_steepness*(2028-adoption_midpoint)))*(1-churn_rate))>=stage2_gate,ecom_market_base*(1+ecom_growth_rate)^4*0.003*tx_take_rate*1000*3,0))*payment_proc_pct)-(capex_total+(33*30*12*(1+bhxh_rate)*(1+salary_escalation)^2*5)+(opex_marketing*(1+marketing_growth)^2*5)+(opex_cloud_base*5+(800/(1+EXP(-adoption_steepness*(2028-adoption_midpoint)))*(1-churn_rate))*vcr_per_enterprise*12*cloud_per_1M_vcr/1000000*5)+((opex_branding+opex_external+opex_legal+opex_security+opex_partner_mgmt)*5)+(capex_total*capex_maintenance_pct*4)))*(1-cit_rate))/(1+discount_rate)^2.5 -> -56039.007 | D24: =((((800/(1+EXP(-adoption_steepness*(2028-adoption_midpoint)))*(1-churn_rate))*(cert_fee_yr1*(1+cert_fee_escalation)^2.5+training_pct*training_fee+audit_fee)*5)+(IF((800/(1+EXP(-adoption_steepness*(2028-adoption_midpoint)))*(1-churn_rate))>=stage2_gate,ecom_market_base*(1+ecom_growth_rate)^4*0.005*tx_take_rate*1000*3,0))-((IF((800/(1+EXP(-adoption_steepness*(2028-adoption_midpoint)))*(1-churn_rate))>=stage2_gate,ecom_market_base*(1+ecom_growth_rate)^4*0.005*tx_take_rate*1000*3,0))*payment_proc_pct)-(capex_total+(33*30*12*(1+bhxh_rate)*(1+salary_escalation)^2*5)+(opex_marketing*(1+marketing_growth)^2*5)+(opex_cloud_base*5+(800/(1+EXP(-adoption_steepness*(2028-adoption_midpoint)))*(1-churn_rate))*vcr_per_enterprise*12*cloud_per_1M_vcr/1000000*5)+((opex_branding+opex_external+opex_legal+opex_security+opex_partner_mgmt)*5)+(capex_total*capex_maintenance_pct*4)))*(1-cit_rate))/(1+discount_rate)^2.5 -> -48631.361 | E24: =((((800/(1+EXP(-adoption_steepness*(2028-adoption_midpoint)))*(1-churn_rate))*(cert_fee_yr1*(1+cert_fee_escalation)^2.5+training_pct*training_fee+audit_fee)*5)+(IF((800/(1+EXP(-adoption_steepness*(2028-adoption_midpoint)))*(1-churn_rate))>=stage2_gate,ecom_market_base*(1+ecom_growth_rate)^4*0.008*tx_take_rate*1000*3,0))-((IF((800/(1+EXP(-adoption_steepness*(2028-adoption_midpoint)))*(1-churn_rate))>=stage2_gate,ecom_market_base*(1+ecom_growth_rate)^4*0.008*tx_take_rate*1000*3,0))*payment_proc_pct)-(capex_total+(33*30*12*(1+bhxh_rate)*(1+salary_escalation)^2*5)+(opex_marketing*(1+marketing_growth)^2*5)+(opex_cloud_base*5+(800/(1+EXP(-adoption_steepness*(2028-adoption_midpoint)))*(1-churn_rate))*vcr_per_enterprise*12*cloud_per_1M_vcr/1000000*5)+((opex_branding+opex_external+opex_legal+opex_security+opex_partner_mgmt)*5)+(capex_total*capex_maintenance_pct*4)))*(1-cit_rate))/(1+discount_rate)^2.5 -> -37519.892 | F24: =((((800/(1+EXP(-adoption_steepness*(2028-adoption_midpoint)))*(1-churn_rate))*(cert_fee_yr1*(1+cert_fee_escalation)^2.5+training_pct*training_fee+audit_fee)*5)+(IF((800/(1+EXP(-adoption_steepness*(2028-adoption_midpoint)))*(1-churn_rate))>=stage2_gate,ecom_market_base*(1+ecom_growth_rate)^4*0.01*tx_take_rate*1000*3,0))-((IF((800/(1+EXP(-adoption_steepness*(2028-adoption_midpoint)))*(1-churn_rate))>=stage2_gate,ecom_market_base*(1+ecom_growth_rate)^4*0.01*tx_take_rate*1000*3,0))*payment_proc_pct)-(capex_total+(33*30*12*(1+bhxh_rate)*(1+salary_escalation)^2*5)+(opex_marketing*(1+marketing_growth)^2*5)+(opex_cloud_base*5+(800/(1+EXP(-adoption_steepness*(2028-adoption_midpoint)))*(1-churn_rate))*vcr_per_enterprise*12*cloud_per_1M_vcr/1000000*5)+((opex_branding+opex_external+opex_legal+opex_security+opex_partner_mgmt)*5)+(capex_total*capex_maintenance_pct*4)))*(1-cit_rate))/(1+discount_rate)^2.5 -> -30112.246 | G24: =((((800/(1+EXP(-adoption_steepness*(2028-adoption_midpoint)))*(1-churn_rate))*(cert_fee_yr1*(1+cert_fee_escalation)^2.5+training_pct*training_fee+audit_fee)*5)+(IF((800/(1+EXP(-adoption_steepness*(2028-adoption_midpoint)))*(1-churn_rate))>=stage2_gate,ecom_market_base*(1+ecom_growth_rate)^4*0.015*tx_take_rate*1000*3,0))-((IF((800/(1+EXP(-adoption_steepness*(2028-adoption_midpoint)))*(1-churn_rate))>=stage2_gate,ecom_market_base*(1+ecom_growth_rate)^4*0.015*tx_take_rate*1000*3,0))*payment_proc_pct)-(capex_total+(33*30*12*(1+bhxh_rate)*(1+salary_escalation)^2*5)+(opex_marketing*(1+marketing_growth)^2*5)+(opex_cloud_base*5+(800/(1+EXP(-adoption_steepness*(2028-adoption_midpoint)))*(1-churn_rate))*vcr_per_enterprise*12*cloud_per_1M_vcr/1000000*5)+((opex_branding+opex_external+opex_legal+opex_security+opex_partner_mgmt)*5)+(capex_total*capex_maintenance_pct*4)))*(1-cit_rate))/(1+discount_rate)^2.5 -> -11593.131 | H24: =((((800/(1+EXP(-adoption_steepness*(2028-adoption_midpoint)))*(1-churn_rate))*(cert_fee_yr1*(1+cert_fee_escalation)^2.5+training_pct*training_fee+audit_fee)*5)+(IF((800/(1+EXP(-adoption_steepness*(2028-adoption_midpoint)))*(1-churn_rate))>=stage2_gate,ecom_market_base*(1+ecom_growth_rate)^4*0.02*tx_take_rate*1000*3,0))-((IF((800/(1+EXP(-adoption_steepness*(2028-adoption_midpoint)))*(1-churn_rate))>=stage2_gate,ecom_market_base*(1+ecom_growth_rate)^4*0.02*tx_take_rate*1000*3,0))*payment_proc_pct)-(capex_total+(33*30*12*(1+bhxh_rate)*(1+salary_escalation)^2*5)+(opex_marketing*(1+marketing_growth)^2*5)+(opex_cloud_base*5+(800/(1+EXP(-adoption_steepness*(2028-adoption_midpoint)))*(1-churn_rate))*vcr_per_enterprise*12*cloud_per_1M_vcr/1000000*5)+((opex_branding+opex_external+opex_legal+opex_security+opex_partner_mgmt)*5)+(capex_total*capex_maintenance_pct*4)))*(1-cit_rate))/(1+discount_rate)^2.5 -> 6925.9842
A25: 1000 | B25: =((((1000/(1+EXP(-adoption_steepness*(2028-adoption_midpoint)))*(1-churn_rate))*(cert_fee_yr1*(1+cert_fee_escalation)^2.5+training_pct*training_fee+audit_fee)*5)+(IF((1000/(1+EXP(-adoption_steepness*(2028-adoption_midpoint)))*(1-churn_rate))>=stage2_gate,ecom_market_base*(1+ecom_growth_rate)^4*0.001*tx_take_rate*1000*3,0))-((IF((1000/(1+EXP(-adoption_steepness*(2028-adoption_midpoint)))*(1-churn_rate))>=stage2_gate,ecom_market_base*(1+ecom_growth_rate)^4*0.001*tx_take_rate*1000*3,0))*payment_proc_pct)-(capex_total+(33*30*12*(1+bhxh_rate)*(1+salary_escalation)^2*5)+(opex_marketing*(1+marketing_growth)^2*5)+(opex_cloud_base*5+(1000/(1+EXP(-adoption_steepness*(2028-adoption_midpoint)))*(1-churn_rate))*vcr_per_enterprise*12*cloud_per_1M_vcr/1000000*5)+((opex_branding+opex_external+opex_legal+opex_security+opex_partner_mgmt)*5)+(capex_total*capex_maintenance_pct*4)))*(1-cit_rate))/(1+discount_rate)^2.5 -> -54018.933 | C25: =((((1000/(1+EXP(-adoption_steepness*(2028-adoption_midpoint)))*(1-churn_rate))*(cert_fee_yr1*(1+cert_fee_escalation)^2.5+training_pct*training_fee+audit_fee)*5)+(IF((1000/(1+EXP(-adoption_steepness*(2028-adoption_midpoint)))*(1-churn_rate))>=stage2_gate,ecom_market_base*(1+ecom_growth_rate)^4*0.003*tx_take_rate*1000*3,0))-((IF((1000/(1+EXP(-adoption_steepness*(2028-adoption_midpoint)))*(1-churn_rate))>=stage2_gate,ecom_market_base*(1+ecom_growth_rate)^4*0.003*tx_take_rate*1000*3,0))*payment_proc_pct)-(capex_total+(33*30*12*(1+bhxh_rate)*(1+salary_escalation)^2*5)+(opex_marketing*(1+marketing_growth)^2*5)+(opex_cloud_base*5+(1000/(1+EXP(-adoption_steepness*(2028-adoption_midpoint)))*(1-churn_rate))*vcr_per_enterprise*12*cloud_per_1M_vcr/1000000*5)+((opex_branding+opex_external+opex_legal+opex_security+opex_partner_mgmt)*5)+(capex_total*capex_maintenance_pct*4)))*(1-cit_rate))/(1+discount_rate)^2.5 -> -46611.287 | D25: =((((1000/(1+EXP(-adoption_steepness*(2028-adoption_midpoint)))*(1-churn_rate))*(cert_fee_yr1*(1+cert_fee_escalation)^2.5+training_pct*training_fee+audit_fee)*5)+(IF((1000/(1+EXP(-adoption_steepness*(2028-adoption_midpoint)))*(1-churn_rate))>=stage2_gate,ecom_market_base*(1+ecom_growth_rate)^4*0.005*tx_take_rate*1000*3,0))-((IF((1000/(1+EXP(-adoption_steepness*(2028-adoption_midpoint)))*(1-churn_rate))>=stage2_gate,ecom_market_base*(1+ecom_growth_rate)^4*0.005*tx_take_rate*1000*3,0))*payment_proc_pct)-(capex_total+(33*30*12*(1+bhxh_rate)*(1+salary_escalation)^2*5)+(opex_marketing*(1+marketing_growth)^2*5)+(opex_cloud_base*5+(1000/(1+EXP(-adoption_steepness*(2028-adoption_midpoint)))*(1-churn_rate))*vcr_per_enterprise*12*cloud_per_1M_vcr/1000000*5)+((opex_branding+opex_external+opex_legal+opex_security+opex_partner_mgmt)*5)+(capex_total*capex_maintenance_pct*4)))*(1-cit_rate))/(1+discount_rate)^2.5 -> -39203.641 | E25: =((((1000/(1+EXP(-adoption_steepness*(2028-adoption_midpoint)))*(1-churn_rate))*(cert_fee_yr1*(1+cert_fee_escalation)^2.5+training_pct*training_fee+audit_fee)*5)+(IF((1000/(1+EXP(-adoption_steepness*(2028-adoption_midpoint)))*(1-churn_rate))>=stage2_gate,ecom_market_base*(1+ecom_growth_rate)^4*0.008*tx_take_rate*1000*3,0))-((IF((1000/(1+EXP(-adoption_steepness*(2028-adoption_midpoint)))*(1-churn_rate))>=stage2_gate,ecom_market_base*(1+ecom_growth_rate)^4*0.008*tx_take_rate*1000*3,0))*payment_proc_pct)-(capex_total+(33*30*12*(1+bhxh_rate)*(1+salary_escalation)^2*5)+(opex_marketing*(1+marketing_growth)^2*5)+(opex_cloud_base*5+(1000/(1+EXP(-adoption_steepness*(2028-adoption_midpoint)))*(1-churn_rate))*vcr_per_enterprise*12*cloud_per_1M_vcr/1000000*5)+((opex_branding+opex_external+opex_legal+opex_security+opex_partner_mgmt)*5)+(capex_total*capex_maintenance_pct*4)))*(1-cit_rate))/(1+discount_rate)^2.5 -> -28092.172 | F25: =((((1000/(1+EXP(-adoption_steepness*(2028-adoption_midpoint)))*(1-churn_rate))*(cert_fee_yr1*(1+cert_fee_escalation)^2.5+training_pct*training_fee+audit_fee)*5)+(IF((1000/(1+EXP(-adoption_steepness*(2028-adoption_midpoint)))*(1-churn_rate))>=stage2_gate,ecom_market_base*(1+ecom_growth_rate)^4*0.01*tx_take_rate*1000*3,0))-((IF((1000/(1+EXP(-adoption_steepness*(2028-adoption_midpoint)))*(1-churn_rate))>=stage2_gate,ecom_market_base*(1+ecom_growth_rate)^4*0.01*tx_take_rate*1000*3,0))*payment_proc_pct)-(capex_total+(33*30*12*(1+bhxh_rate)*(1+salary_escalation)^2*5)+(opex_marketing*(1+marketing_growth)^2*5)+(opex_cloud_base*5+(1000/(1+EXP(-adoption_steepness*(2028-adoption_midpoint)))*(1-churn_rate))*vcr_per_enterprise*12*cloud_per_1M_vcr/1000000*5)+((opex_branding+opex_external+opex_legal+opex_security+opex_partner_mgmt)*5)+(capex_total*capex_maintenance_pct*4)))*(1-cit_rate))/(1+discount_rate)^2.5 -> -20684.526 | G25: =((((1000/(1+EXP(-adoption_steepness*(2028-adoption_midpoint)))*(1-churn_rate))*(cert_fee_yr1*(1+cert_fee_escalation)^2.5+training_pct*training_fee+audit_fee)*5)+(IF((1000/(1+EXP(-adoption_steepness*(2028-adoption_midpoint)))*(1-churn_rate))>=stage2_gate,ecom_market_base*(1+ecom_growth_rate)^4*0.015*tx_take_rate*1000*3,0))-((IF((1000/(1+EXP(-adoption_steepness*(2028-adoption_midpoint)))*(1-churn_rate))>=stage2_gate,ecom_market_base*(1+ecom_growth_rate)^4*0.015*tx_take_rate*1000*3,0))*payment_proc_pct)-(capex_total+(33*30*12*(1+bhxh_rate)*(1+salary_escalation)^2*5)+(opex_marketing*(1+marketing_growth)^2*5)+(opex_cloud_base*5+(1000/(1+EXP(-adoption_steepness*(2028-adoption_midpoint)))*(1-churn_rate))*vcr_per_enterprise*12*cloud_per_1M_vcr/1000000*5)+((opex_branding+opex_external+opex_legal+opex_security+opex_partner_mgmt)*5)+(capex_total*capex_maintenance_pct*4)))*(1-cit_rate))/(1+discount_rate)^2.5 -> -2165.4115 | H25: =((((1000/(1+EXP(-adoption_steepness*(2028-adoption_midpoint)))*(1-churn_rate))*(cert_fee_yr1*(1+cert_fee_escalation)^2.5+training_pct*training_fee+audit_fee)*5)+(IF((1000/(1+EXP(-adoption_steepness*(2028-adoption_midpoint)))*(1-churn_rate))>=stage2_gate,ecom_market_base*(1+ecom_growth_rate)^4*0.02*tx_take_rate*1000*3,0))-((IF((1000/(1+EXP(-adoption_steepness*(2028-adoption_midpoint)))*(1-churn_rate))>=stage2_gate,ecom_market_base*(1+ecom_growth_rate)^4*0.02*tx_take_rate*1000*3,0))*payment_proc_pct)-(capex_total+(33*30*12*(1+bhxh_rate)*(1+salary_escalation)^2*5)+(opex_marketing*(1+marketing_growth)^2*5)+(opex_cloud_base*5+(1000/(1+EXP(-adoption_steepness*(2028-adoption_midpoint)))*(1-churn_rate))*vcr_per_enterprise*12*cloud_per_1M_vcr/1000000*5)+((opex_branding+opex_external+opex_legal+opex_security+opex_partner_mgmt)*5)+(capex_total*capex_maintenance_pct*4)))*(1-cit_rate))/(1+discount_rate)^2.5 -> 16353.703
A26: 1200 | B26: =((((1200/(1+EXP(-adoption_steepness*(2028-adoption_midpoint)))*(1-churn_rate))*(cert_fee_yr1*(1+cert_fee_escalation)^2.5+training_pct*training_fee+audit_fee)*5)+(IF((1200/(1+EXP(-adoption_steepness*(2028-adoption_midpoint)))*(1-churn_rate))>=stage2_gate,ecom_market_base*(1+ecom_growth_rate)^4*0.001*tx_take_rate*1000*3,0))-((IF((1200/(1+EXP(-adoption_steepness*(2028-adoption_midpoint)))*(1-churn_rate))>=stage2_gate,ecom_market_base*(1+ecom_growth_rate)^4*0.001*tx_take_rate*1000*3,0))*payment_proc_pct)-(capex_total+(33*30*12*(1+bhxh_rate)*(1+salary_escalation)^2*5)+(opex_marketing*(1+marketing_growth)^2*5)+(opex_cloud_base*5+(1200/(1+EXP(-adoption_steepness*(2028-adoption_midpoint)))*(1-churn_rate))*vcr_per_enterprise*12*cloud_per_1M_vcr/1000000*5)+((opex_branding+opex_external+opex_legal+opex_security+opex_partner_mgmt)*5)+(capex_total*capex_maintenance_pct*4)))*(1-cit_rate))/(1+discount_rate)^2.5 -> -44591.214 | C26: =((((1200/(1+EXP(-adoption_steepness*(2028-adoption_midpoint)))*(1-churn_rate))*(cert_fee_yr1*(1+cert_fee_escalation)^2.5+training_pct*training_fee+audit_fee)*5)+(IF((1200/(1+EXP(-adoption_steepness*(2028-adoption_midpoint)))*(1-churn_rate))>=stage2_gate,ecom_market_base*(1+ecom_growth_rate)^4*0.003*tx_take_rate*1000*3,0))-((IF((1200/(1+EXP(-adoption_steepness*(2028-adoption_midpoint)))*(1-churn_rate))>=stage2_gate,ecom_market_base*(1+ecom_growth_rate)^4*0.003*tx_take_rate*1000*3,0))*payment_proc_pct)-(capex_total+(33*30*12*(1+bhxh_rate)*(1+salary_escalation)^2*5)+(opex_marketing*(1+marketing_growth)^2*5)+(opex_cloud_base*5+(1200/(1+EXP(-adoption_steepness*(2028-adoption_midpoint)))*(1-churn_rate))*vcr_per_enterprise*12*cloud_per_1M_vcr/1000000*5)+((opex_branding+opex_external+opex_legal+opex_security+opex_partner_mgmt)*5)+(capex_total*capex_maintenance_pct*4)))*(1-cit_rate))/(1+discount_rate)^2.5 -> -37183.568 | D26: =((((1200/(1+EXP(-adoption_steepness*(2028-adoption_midpoint)))*(1-churn_rate))*(cert_fee_yr1*(1+cert_fee_escalation)^2.5+training_pct*training_fee+audit_fee)*5)+(IF((1200/(1+EXP(-adoption_steepness*(2028-adoption_midpoint)))*(1-churn_rate))>=stage2_gate,ecom_market_base*(1+ecom_growth_rate)^4*0.005*tx_take_rate*1000*3,0))-((IF((1200/(1+EXP(-adoption_steepness*(2028-adoption_midpoint)))*(1-churn_rate))>=stage2_gate,ecom_market_base*(1+ecom_growth_rate)^4*0.005*tx_take_rate*1000*3,0))*payment_proc_pct)-(capex_total+(33*30*12*(1+bhxh_rate)*(1+salary_escalation)^2*5)+(opex_marketing*(1+marketing_growth)^2*5)+(opex_cloud_base*5+(1200/(1+EXP(-adoption_steepness*(2028-adoption_midpoint)))*(1-churn_rate))*vcr_per_enterprise*12*cloud_per_1M_vcr/1000000*5)+((opex_branding+opex_external+opex_legal+opex_security+opex_partner_mgmt)*5)+(capex_total*capex_maintenance_pct*4)))*(1-cit_rate))/(1+discount_rate)^2.5 -> -29775.922 | E26: =((((1200/(1+EXP(-adoption_steepness*(2028-adoption_midpoint)))*(1-churn_rate))*(cert_fee_yr1*(1+cert_fee_escalation)^2.5+training_pct*training_fee+audit_fee)*5)+(IF((1200/(1+EXP(-adoption_steepness*(2028-adoption_midpoint)))*(1-churn_rate))>=stage2_gate,ecom_market_base*(1+ecom_growth_rate)^4*0.008*tx_take_rate*1000*3,0))-((IF((1200/(1+EXP(-adoption_steepness*(2028-adoption_midpoint)))*(1-churn_rate))>=stage2_gate,ecom_market_base*(1+ecom_growth_rate)^4*0.008*tx_take_rate*1000*3,0))*payment_proc_pct)-(capex_total+(33*30*12*(1+bhxh_rate)*(1+salary_escalation)^2*5)+(opex_marketing*(1+marketing_growth)^2*5)+(opex_cloud_base*5+(1200/(1+EXP(-adoption_steepness*(2028-adoption_midpoint)))*(1-churn_rate))*vcr_per_enterprise*12*cloud_per_1M_vcr/1000000*5)+((opex_branding+opex_external+opex_legal+opex_security+opex_partner_mgmt)*5)+(capex_total*capex_maintenance_pct*4)))*(1-cit_rate))/(1+discount_rate)^2.5 -> -18664.453 | F26: =((((1200/(1+EXP(-adoption_steepness*(2028-adoption_midpoint)))*(1-churn_rate))*(cert_fee_yr1*(1+cert_fee_escalation)^2.5+training_pct*training_fee+audit_fee)*5)+(IF((1200/(1+EXP(-adoption_steepness*(2028-adoption_midpoint)))*(1-churn_rate))>=stage2_gate,ecom_market_base*(1+ecom_growth_rate)^4*0.01*tx_take_rate*1000*3,0))-((IF((1200/(1+EXP(-adoption_steepness*(2028-adoption_midpoint)))*(1-churn_rate))>=stage2_gate,ecom_market_base*(1+ecom_growth_rate)^4*0.01*tx_take_rate*1000*3,0))*payment_proc_pct)-(capex_total+(33*30*12*(1+bhxh_rate)*(1+salary_escalation)^2*5)+(opex_marketing*(1+marketing_growth)^2*5)+(opex_cloud_base*5+(1200/(1+EXP(-adoption_steepness*(2028-adoption_midpoint)))*(1-churn_rate))*vcr_per_enterprise*12*cloud_per_1M_vcr/1000000*5)+((opex_branding+opex_external+opex_legal+opex_security+opex_partner_mgmt)*5)+(capex_total*capex_maintenance_pct*4)))*(1-cit_rate))/(1+discount_rate)^2.5 -> -11256.807 | G26: =((((1200/(1+EXP(-adoption_steepness*(2028-adoption_midpoint)))*(1-churn_rate))*(cert_fee_yr1*(1+cert_fee_escalation)^2.5+training_pct*training_fee+audit_fee)*5)+(IF((1200/(1+EXP(-adoption_steepness*(2028-adoption_midpoint)))*(1-churn_rate))>=stage2_gate,ecom_market_base*(1+ecom_growth_rate)^4*0.015*tx_take_rate*1000*3,0))-((IF((1200/(1+EXP(-adoption_steepness*(2028-adoption_midpoint)))*(1-churn_rate))>=stage2_gate,ecom_market_base*(1+ecom_growth_rate)^4*0.015*tx_take_rate*1000*3,0))*payment_proc_pct)-(capex_total+(33*30*12*(1+bhxh_rate)*(1+salary_escalation)^2*5)+(opex_marketing*(1+marketing_growth)^2*5)+(opex_cloud_base*5+(1200/(1+EXP(-adoption_steepness*(2028-adoption_midpoint)))*(1-churn_rate))*vcr_per_enterprise*12*cloud_per_1M_vcr/1000000*5)+((opex_branding+opex_external+opex_legal+opex_security+opex_partner_mgmt)*5)+(capex_total*capex_maintenance_pct*4)))*(1-cit_rate))/(1+discount_rate)^2.5 -> 7262.3077 | H26: =((((1200/(1+EXP(-adoption_steepness*(2028-adoption_midpoint)))*(1-churn_rate))*(cert_fee_yr1*(1+cert_fee_escalation)^2.5+training_pct*training_fee+audit_fee)*5)+(IF((1200/(1+EXP(-adoption_steepness*(2028-adoption_midpoint)))*(1-churn_rate))>=stage2_gate,ecom_market_base*(1+ecom_growth_rate)^4*0.02*tx_take_rate*1000*3,0))-((IF((1200/(1+EXP(-adoption_steepness*(2028-adoption_midpoint)))*(1-churn_rate))>=stage2_gate,ecom_market_base*(1+ecom_growth_rate)^4*0.02*tx_take_rate*1000*3,0))*payment_proc_pct)-(capex_total+(33*30*12*(1+bhxh_rate)*(1+salary_escalation)^2*5)+(opex_marketing*(1+marketing_growth)^2*5)+(opex_cloud_base*5+(1200/(1+EXP(-adoption_steepness*(2028-adoption_midpoint)))*(1-churn_rate))*vcr_per_enterprise*12*cloud_per_1M_vcr/1000000*5)+((opex_branding+opex_external+opex_legal+opex_security+opex_partner_mgmt)*5)+(capex_total*capex_maintenance_pct*4)))*(1-cit_rate))/(1+discount_rate)^2.5 -> 25781.423
A27: 1500 | B27: =((((1500/(1+EXP(-adoption_steepness*(2028-adoption_midpoint)))*(1-churn_rate))*(cert_fee_yr1*(1+cert_fee_escalation)^2.5+training_pct*training_fee+audit_fee)*5)+(IF((1500/(1+EXP(-adoption_steepness*(2028-adoption_midpoint)))*(1-churn_rate))>=stage2_gate,ecom_market_base*(1+ecom_growth_rate)^4*0.001*tx_take_rate*1000*3,0))-((IF((1500/(1+EXP(-adoption_steepness*(2028-adoption_midpoint)))*(1-churn_rate))>=stage2_gate,ecom_market_base*(1+ecom_growth_rate)^4*0.001*tx_take_rate*1000*3,0))*payment_proc_pct)-(capex_total+(33*30*12*(1+bhxh_rate)*(1+salary_escalation)^2*5)+(opex_marketing*(1+marketing_growth)^2*5)+(opex_cloud_base*5+(1500/(1+EXP(-adoption_steepness*(2028-adoption_midpoint)))*(1-churn_rate))*vcr_per_enterprise*12*cloud_per_1M_vcr/1000000*5)+((opex_branding+opex_external+opex_legal+opex_security+opex_partner_mgmt)*5)+(capex_total*capex_maintenance_pct*4)))*(1-cit_rate))/(1+discount_rate)^2.5 -> -30449.635 | C27: =((((1500/(1+EXP(-adoption_steepness*(2028-adoption_midpoint)))*(1-churn_rate))*(cert_fee_yr1*(1+cert_fee_escalation)^2.5+training_pct*training_fee+audit_fee)*5)+(IF((1500/(1+EXP(-adoption_steepness*(2028-adoption_midpoint)))*(1-churn_rate))>=stage2_gate,ecom_market_base*(1+ecom_growth_rate)^4*0.003*tx_take_rate*1000*3,0))-((IF((1500/(1+EXP(-adoption_steepness*(2028-adoption_midpoint)))*(1-churn_rate))>=stage2_gate,ecom_market_base*(1+ecom_growth_rate)^4*0.003*tx_take_rate*1000*3,0))*payment_proc_pct)-(capex_total+(33*30*12*(1+bhxh_rate)*(1+salary_escalation)^2*5)+(opex_marketing*(1+marketing_growth)^2*5)+(opex_cloud_base*5+(1500/(1+EXP(-adoption_steepness*(2028-adoption_midpoint)))*(1-churn_rate))*vcr_per_enterprise*12*cloud_per_1M_vcr/1000000*5)+((opex_branding+opex_external+opex_legal+opex_security+opex_partner_mgmt)*5)+(capex_total*capex_maintenance_pct*4)))*(1-cit_rate))/(1+discount_rate)^2.5 -> -23041.989 | D27: =((((1500/(1+EXP(-adoption_steepness*(2028-adoption_midpoint)))*(1-churn_rate))*(cert_fee_yr1*(1+cert_fee_escalation)^2.5+training_pct*training_fee+audit_fee)*5)+(IF((1500/(1+EXP(-adoption_steepness*(2028-adoption_midpoint)))*(1-churn_rate))>=stage2_gate,ecom_market_base*(1+ecom_growth_rate)^4*0.005*tx_take_rate*1000*3,0))-((IF((1500/(1+EXP(-adoption_steepness*(2028-adoption_midpoint)))*(1-churn_rate))>=stage2_gate,ecom_market_base*(1+ecom_growth_rate)^4*0.005*tx_take_rate*1000*3,0))*payment_proc_pct)-(capex_total+(33*30*12*(1+bhxh_rate)*(1+salary_escalation)^2*5)+(opex_marketing*(1+marketing_growth)^2*5)+(opex_cloud_base*5+(1500/(1+EXP(-adoption_steepness*(2028-adoption_midpoint)))*(1-churn_rate))*vcr_per_enterprise*12*cloud_per_1M_vcr/1000000*5)+((opex_branding+opex_external+opex_legal+opex_security+opex_partner_mgmt)*5)+(capex_total*capex_maintenance_pct*4)))*(1-cit_rate))/(1+discount_rate)^2.5 -> -15634.343 | E27: =((((1500/(1+EXP(-adoption_steepness*(2028-adoption_midpoint)))*(1-churn_rate))*(cert_fee_yr1*(1+cert_fee_escalation)^2.5+training_pct*training_fee+audit_fee)*5)+(IF((1500/(1+EXP(-adoption_steepness*(2028-adoption_midpoint)))*(1-churn_rate))>=stage2_gate,ecom_market_base*(1+ecom_growth_rate)^4*0.008*tx_take_rate*1000*3,0))-((IF((1500/(1+EXP(-adoption_steepness*(2028-adoption_midpoint)))*(1-churn_rate))>=stage2_gate,ecom_market_base*(1+ecom_growth_rate)^4*0.008*tx_take_rate*1000*3,0))*payment_proc_pct)-(capex_total+(33*30*12*(1+bhxh_rate)*(1+salary_escalation)^2*5)+(opex_marketing*(1+marketing_growth)^2*5)+(opex_cloud_base*5+(1500/(1+EXP(-adoption_steepness*(2028-adoption_midpoint)))*(1-churn_rate))*vcr_per_enterprise*12*cloud_per_1M_vcr/1000000*5)+((opex_branding+opex_external+opex_legal+opex_security+opex_partner_mgmt)*5)+(capex_total*capex_maintenance_pct*4)))*(1-cit_rate))/(1+discount_rate)^2.5 -> -4522.8744 | F27: =((((1500/(1+EXP(-adoption_steepness*(2028-adoption_midpoint)))*(1-churn_rate))*(cert_fee_yr1*(1+cert_fee_escalation)^2.5+training_pct*training_fee+audit_fee)*5)+(IF((1500/(1+EXP(-adoption_steepness*(2028-adoption_midpoint)))*(1-churn_rate))>=stage2_gate,ecom_market_base*(1+ecom_growth_rate)^4*0.01*tx_take_rate*1000*3,0))-((IF((1500/(1+EXP(-adoption_steepness*(2028-adoption_midpoint)))*(1-churn_rate))>=stage2_gate,ecom_market_base*(1+ecom_growth_rate)^4*0.01*tx_take_rate*1000*3,0))*payment_proc_pct)-(capex_total+(33*30*12*(1+bhxh_rate)*(1+salary_escalation)^2*5)+(opex_marketing*(1+marketing_growth)^2*5)+(opex_cloud_base*5+(1500/(1+EXP(-adoption_steepness*(2028-adoption_midpoint)))*(1-churn_rate))*vcr_per_enterprise*12*cloud_per_1M_vcr/1000000*5)+((opex_branding+opex_external+opex_legal+opex_security+opex_partner_mgmt)*5)+(capex_total*capex_maintenance_pct*4)))*(1-cit_rate))/(1+discount_rate)^2.5 -> 2884.7715 | G27: =((((1500/(1+EXP(-adoption_steepness*(2028-adoption_midpoint)))*(1-churn_rate))*(cert_fee_yr1*(1+cert_fee_escalation)^2.5+training_pct*training_fee+audit_fee)*5)+(IF((1500/(1+EXP(-adoption_steepness*(2028-adoption_midpoint)))*(1-churn_rate))>=stage2_gate,ecom_market_base*(1+ecom_growth_rate)^4*0.015*tx_take_rate*1000*3,0))-((IF((1500/(1+EXP(-adoption_steepness*(2028-adoption_midpoint)))*(1-churn_rate))>=stage2_gate,ecom_market_base*(1+ecom_growth_rate)^4*0.015*tx_take_rate*1000*3,0))*payment_proc_pct)-(capex_total+(33*30*12*(1+bhxh_rate)*(1+salary_escalation)^2*5)+(opex_marketing*(1+marketing_growth)^2*5)+(opex_cloud_base*5+(1500/(1+EXP(-adoption_steepness*(2028-adoption_midpoint)))*(1-churn_rate))*vcr_per_enterprise*12*cloud_per_1M_vcr/1000000*5)+((opex_branding+opex_external+opex_legal+opex_security+opex_partner_mgmt)*5)+(capex_total*capex_maintenance_pct*4)))*(1-cit_rate))/(1+discount_rate)^2.5 -> 21403.886 | H27: =((((1500/(1+EXP(-adoption_steepness*(2028-adoption_midpoint)))*(1-churn_rate))*(cert_fee_yr1*(1+cert_fee_escalation)^2.5+training_pct*training_fee+audit_fee)*5)+(IF((1500/(1+EXP(-adoption_steepness*(2028-adoption_midpoint)))*(1-churn_rate))>=stage2_gate,ecom_market_base*(1+ecom_growth_rate)^4*0.02*tx_take_rate*1000*3,0))-((IF((1500/(1+EXP(-adoption_steepness*(2028-adoption_midpoint)))*(1-churn_rate))>=stage2_gate,ecom_market_base*(1+ecom_growth_rate)^4*0.02*tx_take_rate*1000*3,0))*payment_proc_pct)-(capex_total+(33*30*12*(1+bhxh_rate)*(1+salary_escalation)^2*5)+(opex_marketing*(1+marketing_growth)^2*5)+(opex_cloud_base*5+(1500/(1+EXP(-adoption_steepness*(2028-adoption_midpoint)))*(1-churn_rate))*vcr_per_enterprise*12*cloud_per_1M_vcr/1000000*5)+((opex_branding+opex_external+opex_legal+opex_security+opex_partner_mgmt)*5)+(capex_total*capex_maintenance_pct*4)))*(1-cit_rate))/(1+discount_rate)^2.5 -> 39923.001
A28: 2000 | B28: =((((2000/(1+EXP(-adoption_steepness*(2028-adoption_midpoint)))*(1-churn_rate))*(cert_fee_yr1*(1+cert_fee_escalation)^2.5+training_pct*training_fee+audit_fee)*5)+(IF((2000/(1+EXP(-adoption_steepness*(2028-adoption_midpoint)))*(1-churn_rate))>=stage2_gate,ecom_market_base*(1+ecom_growth_rate)^4*0.001*tx_take_rate*1000*3,0))-((IF((2000/(1+EXP(-adoption_steepness*(2028-adoption_midpoint)))*(1-churn_rate))>=stage2_gate,ecom_market_base*(1+ecom_growth_rate)^4*0.001*tx_take_rate*1000*3,0))*payment_proc_pct)-(capex_total+(33*30*12*(1+bhxh_rate)*(1+salary_escalation)^2*5)+(opex_marketing*(1+marketing_growth)^2*5)+(opex_cloud_base*5+(2000/(1+EXP(-adoption_steepness*(2028-adoption_midpoint)))*(1-churn_rate))*vcr_per_enterprise*12*cloud_per_1M_vcr/1000000*5)+((opex_branding+opex_external+opex_legal+opex_security+opex_partner_mgmt)*5)+(capex_total*capex_maintenance_pct*4)))*(1-cit_rate))/(1+discount_rate)^2.5 -> -6880.3373 | C28: =((((2000/(1+EXP(-adoption_steepness*(2028-adoption_midpoint)))*(1-churn_rate))*(cert_fee_yr1*(1+cert_fee_escalation)^2.5+training_pct*training_fee+audit_fee)*5)+(IF((2000/(1+EXP(-adoption_steepness*(2028-adoption_midpoint)))*(1-churn_rate))>=stage2_gate,ecom_market_base*(1+ecom_growth_rate)^4*0.003*tx_take_rate*1000*3,0))-((IF((2000/(1+EXP(-adoption_steepness*(2028-adoption_midpoint)))*(1-churn_rate))>=stage2_gate,ecom_market_base*(1+ecom_growth_rate)^4*0.003*tx_take_rate*1000*3,0))*payment_proc_pct)-(capex_total+(33*30*12*(1+bhxh_rate)*(1+salary_escalation)^2*5)+(opex_marketing*(1+marketing_growth)^2*5)+(opex_cloud_base*5+(2000/(1+EXP(-adoption_steepness*(2028-adoption_midpoint)))*(1-churn_rate))*vcr_per_enterprise*12*cloud_per_1M_vcr/1000000*5)+((opex_branding+opex_external+opex_legal+opex_security+opex_partner_mgmt)*5)+(capex_total*capex_maintenance_pct*4)))*(1-cit_rate))/(1+discount_rate)^2.5 -> 527.30864 | D28: =((((2000/(1+EXP(-adoption_steepness*(2028-adoption_midpoint)))*(1-churn_rate))*(cert_fee_yr1*(1+cert_fee_escalation)^2.5+training_pct*training_fee+audit_fee)*5)+(IF((2000/(1+EXP(-adoption_steepness*(2028-adoption_midpoint)))*(1-churn_rate))>=stage2_gate,ecom_market_base*(1+ecom_growth_rate)^4*0.005*tx_take_rate*1000*3,0))-((IF((2000/(1+EXP(-adoption_steepness*(2028-adoption_midpoint)))*(1-churn_rate))>=stage2_gate,ecom_market_base*(1+ecom_growth_rate)^4*0.005*tx_take_rate*1000*3,0))*payment_proc_pct)-(capex_total+(33*30*12*(1+bhxh_rate)*(1+salary_escalation)^2*5)+(opex_marketing*(1+marketing_growth)^2*5)+(opex_cloud_base*5+(2000/(1+EXP(-adoption_steepness*(2028-adoption_midpoint)))*(1-churn_rate))*vcr_per_enterprise*12*cloud_per_1M_vcr/1000000*5)+((opex_branding+opex_external+opex_legal+opex_security+opex_partner_mgmt)*5)+(capex_total*capex_maintenance_pct*4)))*(1-cit_rate))/(1+discount_rate)^2.5 -> 7934.9546 | E28: =((((2000/(1+EXP(-adoption_steepness*(2028-adoption_midpoint)))*(1-churn_rate))*(cert_fee_yr1*(1+cert_fee_escalation)^2.5+training_pct*training_fee+audit_fee)*5)+(IF((2000/(1+EXP(-adoption_steepness*(2028-adoption_midpoint)))*(1-churn_rate))>=stage2_gate,ecom_market_base*(1+ecom_growth_rate)^4*0.008*tx_take_rate*1000*3,0))-((IF((2000/(1+EXP(-adoption_steepness*(2028-adoption_midpoint)))*(1-churn_rate))>=stage2_gate,ecom_market_base*(1+ecom_growth_rate)^4*0.008*tx_take_rate*1000*3,0))*payment_proc_pct)-(capex_total+(33*30*12*(1+bhxh_rate)*(1+salary_escalation)^2*5)+(opex_marketing*(1+marketing_growth)^2*5)+(opex_cloud_base*5+(2000/(1+EXP(-adoption_steepness*(2028-adoption_midpoint)))*(1-churn_rate))*vcr_per_enterprise*12*cloud_per_1M_vcr/1000000*5)+((opex_branding+opex_external+opex_legal+opex_security+opex_partner_mgmt)*5)+(capex_total*capex_maintenance_pct*4)))*(1-cit_rate))/(1+discount_rate)^2.5 -> 19046.424 | F28: =((((2000/(1+EXP(-adoption_steepness*(2028-adoption_midpoint)))*(1-churn_rate))*(cert_fee_yr1*(1+cert_fee_escalation)^2.5+training_pct*training_fee+audit_fee)*5)+(IF((2000/(1+EXP(-adoption_steepness*(2028-adoption_midpoint)))*(1-churn_rate))>=stage2_gate,ecom_market_base*(1+ecom_growth_rate)^4*0.01*tx_take_rate*1000*3,0))-((IF((2000/(1+EXP(-adoption_steepness*(2028-adoption_midpoint)))*(1-churn_rate))>=stage2_gate,ecom_market_base*(1+ecom_growth_rate)^4*0.01*tx_take_rate*1000*3,0))*payment_proc_pct)-(capex_total+(33*30*12*(1+bhxh_rate)*(1+salary_escalation)^2*5)+(opex_marketing*(1+marketing_growth)^2*5)+(opex_cloud_base*5+(2000/(1+EXP(-adoption_steepness*(2028-adoption_midpoint)))*(1-churn_rate))*vcr_per_enterprise*12*cloud_per_1M_vcr/1000000*5)+((opex_branding+opex_external+opex_legal+opex_security+opex_partner_mgmt)*5)+(capex_total*capex_maintenance_pct*4)))*(1-cit_rate))/(1+discount_rate)^2.5 -> 26454.07 | G28: =((((2000/(1+EXP(-adoption_steepness*(2028-adoption_midpoint)))*(1-churn_rate))*(cert_fee_yr1*(1+cert_fee_escalation)^2.5+training_pct*training_fee+audit_fee)*5)+(IF((2000/(1+EXP(-adoption_steepness*(2028-adoption_midpoint)))*(1-churn_rate))>=stage2_gate,ecom_market_base*(1+ecom_growth_rate)^4*0.015*tx_take_rate*1000*3,0))-((IF((2000/(1+EXP(-adoption_steepness*(2028-adoption_midpoint)))*(1-churn_rate))>=stage2_gate,ecom_market_base*(1+ecom_growth_rate)^4*0.015*tx_take_rate*1000*3,0))*payment_proc_pct)-(capex_total+(33*30*12*(1+bhxh_rate)*(1+salary_escalation)^2*5)+(opex_marketing*(1+marketing_growth)^2*5)+(opex_cloud_base*5+(2000/(1+EXP(-adoption_steepness*(2028-adoption_midpoint)))*(1-churn_rate))*vcr_per_enterprise*12*cloud_per_1M_vcr/1000000*5)+((opex_branding+opex_external+opex_legal+opex_security+opex_partner_mgmt)*5)+(capex_total*capex_maintenance_pct*4)))*(1-cit_rate))/(1+discount_rate)^2.5 -> 44973.184 | H28: =((((2000/(1+EXP(-adoption_steepness*(2028-adoption_midpoint)))*(1-churn_rate))*(cert_fee_yr1*(1+cert_fee_escalation)^2.5+training_pct*training_fee+audit_fee)*5)+(IF((2000/(1+EXP(-adoption_steepness*(2028-adoption_midpoint)))*(1-churn_rate))>=stage2_gate,ecom_market_base*(1+ecom_growth_rate)^4*0.02*tx_take_rate*1000*3,0))-((IF((2000/(1+EXP(-adoption_steepness*(2028-adoption_midpoint)))*(1-churn_rate))>=stage2_gate,ecom_market_base*(1+ecom_growth_rate)^4*0.02*tx_take_rate*1000*3,0))*payment_proc_pct)-(capex_total+(33*30*12*(1+bhxh_rate)*(1+salary_escalation)^2*5)+(opex_marketing*(1+marketing_growth)^2*5)+(opex_cloud_base*5+(2000/(1+EXP(-adoption_steepness*(2028-adoption_midpoint)))*(1-churn_rate))*vcr_per_enterprise*12*cloud_per_1M_vcr/1000000*5)+((opex_branding+opex_external+opex_legal+opex_security+opex_partner_mgmt)*5)+(capex_total*capex_maintenance_pct*4)))*(1-cit_rate))/(1+discount_rate)^2.5 -> 63492.299
A29: 3000 | B29: =((((3000/(1+EXP(-adoption_steepness*(2028-adoption_midpoint)))*(1-churn_rate))*(cert_fee_yr1*(1+cert_fee_escalation)^2.5+training_pct*training_fee+audit_fee)*5)+(IF((3000/(1+EXP(-adoption_steepness*(2028-adoption_midpoint)))*(1-churn_rate))>=stage2_gate,ecom_market_base*(1+ecom_growth_rate)^4*0.001*tx_take_rate*1000*3,0))-((IF((3000/(1+EXP(-adoption_steepness*(2028-adoption_midpoint)))*(1-churn_rate))>=stage2_gate,ecom_market_base*(1+ecom_growth_rate)^4*0.001*tx_take_rate*1000*3,0))*payment_proc_pct)-(capex_total+(33*30*12*(1+bhxh_rate)*(1+salary_escalation)^2*5)+(opex_marketing*(1+marketing_growth)^2*5)+(opex_cloud_base*5+(3000/(1+EXP(-adoption_steepness*(2028-adoption_midpoint)))*(1-churn_rate))*vcr_per_enterprise*12*cloud_per_1M_vcr/1000000*5)+((opex_branding+opex_external+opex_legal+opex_security+opex_partner_mgmt)*5)+(capex_total*capex_maintenance_pct*4)))*(1-cit_rate))/(1+discount_rate)^2.5 -> 40258.259 | C29: =((((3000/(1+EXP(-adoption_steepness*(2028-adoption_midpoint)))*(1-churn_rate))*(cert_fee_yr1*(1+cert_fee_escalation)^2.5+training_pct*training_fee+audit_fee)*5)+(IF((3000/(1+EXP(-adoption_steepness*(2028-adoption_midpoint)))*(1-churn_rate))>=stage2_gate,ecom_market_base*(1+ecom_growth_rate)^4*0.003*tx_take_rate*1000*3,0))-((IF((3000/(1+EXP(-adoption_steepness*(2028-adoption_midpoint)))*(1-churn_rate))>=stage2_gate,ecom_market_base*(1+ecom_growth_rate)^4*0.003*tx_take_rate*1000*3,0))*payment_proc_pct)-(capex_total+(33*30*12*(1+bhxh_rate)*(1+salary_escalation)^2*5)+(opex_marketing*(1+marketing_growth)^2*5)+(opex_cloud_base*5+(3000/(1+EXP(-adoption_steepness*(2028-adoption_midpoint)))*(1-churn_rate))*vcr_per_enterprise*12*cloud_per_1M_vcr/1000000*5)+((opex_branding+opex_external+opex_legal+opex_security+opex_partner_mgmt)*5)+(capex_total*capex_maintenance_pct*4)))*(1-cit_rate))/(1+discount_rate)^2.5 -> 47665.905 | D29: =((((3000/(1+EXP(-adoption_steepness*(2028-adoption_midpoint)))*(1-churn_rate))*(cert_fee_yr1*(1+cert_fee_escalation)^2.5+training_pct*training_fee+audit_fee)*5)+(IF((3000/(1+EXP(-adoption_steepness*(2028-adoption_midpoint)))*(1-churn_rate))>=stage2_gate,ecom_market_base*(1+ecom_growth_rate)^4*0.005*tx_take_rate*1000*3,0))-((IF((3000/(1+EXP(-adoption_steepness*(2028-adoption_midpoint)))*(1-churn_rate))>=stage2_gate,ecom_market_base*(1+ecom_growth_rate)^4*0.005*tx_take_rate*1000*3,0))*payment_proc_pct)-(capex_total+(33*30*12*(1+bhxh_rate)*(1+salary_escalation)^2*5)+(opex_marketing*(1+marketing_growth)^2*5)+(opex_cloud_base*5+(3000/(1+EXP(-adoption_steepness*(2028-adoption_midpoint)))*(1-churn_rate))*vcr_per_enterprise*12*cloud_per_1M_vcr/1000000*5)+((opex_branding+opex_external+opex_legal+opex_security+opex_partner_mgmt)*5)+(capex_total*capex_maintenance_pct*4)))*(1-cit_rate))/(1+discount_rate)^2.5 -> 55073.551 | E29: =((((3000/(1+EXP(-adoption_steepness*(2028-adoption_midpoint)))*(1-churn_rate))*(cert_fee_yr1*(1+cert_fee_escalation)^2.5+training_pct*training_fee+audit_fee)*5)+(IF((3000/(1+EXP(-adoption_steepness*(2028-adoption_midpoint)))*(1-churn_rate))>=stage2_gate,ecom_market_base*(1+ecom_growth_rate)^4*0.008*tx_take_rate*1000*3,0))-((IF((3000/(1+EXP(-adoption_steepness*(2028-adoption_midpoint)))*(1-churn_rate))>=stage2_gate,ecom_market_base*(1+ecom_growth_rate)^4*0.008*tx_take_rate*1000*3,0))*payment_proc_pct)-(capex_total+(33*30*12*(1+bhxh_rate)*(1+salary_escalation)^2*5)+(opex_marketing*(1+marketing_growth)^2*5)+(opex_cloud_base*5+(3000/(1+EXP(-adoption_steepness*(2028-adoption_midpoint)))*(1-churn_rate))*vcr_per_enterprise*12*cloud_per_1M_vcr/1000000*5)+((opex_branding+opex_external+opex_legal+opex_security+opex_partner_mgmt)*5)+(capex_total*capex_maintenance_pct*4)))*(1-cit_rate))/(1+discount_rate)^2.5 -> 66185.02 | F29: =((((3000/(1+EXP(-adoption_steepness*(2028-adoption_midpoint)))*(1-churn_rate))*(cert_fee_yr1*(1+cert_fee_escalation)^2.5+training_pct*training_fee+audit_fee)*5)+(IF((3000/(1+EXP(-adoption_steepness*(2028-adoption_midpoint)))*(1-churn_rate))>=stage2_gate,ecom_market_base*(1+ecom_growth_rate)^4*0.01*tx_take_rate*1000*3,0))-((IF((3000/(1+EXP(-adoption_steepness*(2028-adoption_midpoint)))*(1-churn_rate))>=stage2_gate,ecom_market_base*(1+ecom_growth_rate)^4*0.01*tx_take_rate*1000*3,0))*payment_proc_pct)-(capex_total+(33*30*12*(1+bhxh_rate)*(1+salary_escalation)^2*5)+(opex_marketing*(1+marketing_growth)^2*5)+(opex_cloud_base*5+(3000/(1+EXP(-adoption_steepness*(2028-adoption_midpoint)))*(1-churn_rate))*vcr_per_enterprise*12*cloud_per_1M_vcr/1000000*5)+((opex_branding+opex_external+opex_legal+opex_security+opex_partner_mgmt)*5)+(capex_total*capex_maintenance_pct*4)))*(1-cit_rate))/(1+discount_rate)^2.5 -> 73592.666 | G29: =((((3000/(1+EXP(-adoption_steepness*(2028-adoption_midpoint)))*(1-churn_rate))*(cert_fee_yr1*(1+cert_fee_escalation)^2.5+training_pct*training_fee+audit_fee)*5)+(IF((3000/(1+EXP(-adoption_steepness*(2028-adoption_midpoint)))*(1-churn_rate))>=stage2_gate,ecom_market_base*(1+ecom_growth_rate)^4*0.015*tx_take_rate*1000*3,0))-((IF((3000/(1+EXP(-adoption_steepness*(2028-adoption_midpoint)))*(1-churn_rate))>=stage2_gate,ecom_market_base*(1+ecom_growth_rate)^4*0.015*tx_take_rate*1000*3,0))*payment_proc_pct)-(capex_total+(33*30*12*(1+bhxh_rate)*(1+salary_escalation)^2*5)+(opex_marketing*(1+marketing_growth)^2*5)+(opex_cloud_base*5+(3000/(1+EXP(-adoption_steepness*(2028-adoption_midpoint)))*(1-churn_rate))*vcr_per_enterprise*12*cloud_per_1M_vcr/1000000*5)+((opex_branding+opex_external+opex_legal+opex_security+opex_partner_mgmt)*5)+(capex_total*capex_maintenance_pct*4)))*(1-cit_rate))/(1+discount_rate)^2.5 -> 92111.781 | H29: =((((3000/(1+EXP(-adoption_steepness*(2028-adoption_midpoint)))*(1-churn_rate))*(cert_fee_yr1*(1+cert_fee_escalation)^2.5+training_pct*training_fee+audit_fee)*5)+(IF((3000/(1+EXP(-adoption_steepness*(2028-adoption_midpoint)))*(1-churn_rate))>=stage2_gate,ecom_market_base*(1+ecom_growth_rate)^4*0.02*tx_take_rate*1000*3,0))-((IF((3000/(1+EXP(-adoption_steepness*(2028-adoption_midpoint)))*(1-churn_rate))>=stage2_gate,ecom_market_base*(1+ecom_growth_rate)^4*0.02*tx_take_rate*1000*3,0))*payment_proc_pct)-(capex_total+(33*30*12*(1+bhxh_rate)*(1+salary_escalation)^2*5)+(opex_marketing*(1+marketing_growth)^2*5)+(opex_cloud_base*5+(3000/(1+EXP(-adoption_steepness*(2028-adoption_midpoint)))*(1-churn_rate))*vcr_per_enterprise*12*cloud_per_1M_vcr/1000000*5)+((opex_branding+opex_external+opex_legal+opex_security+opex_partner_mgmt)*5)+(capex_total*capex_maintenance_pct*4)))*(1-cit_rate))/(1+discount_rate)^2.5 -> 110630.9
A32: TWO-WAY NPV: adoption_max × churn_rate (Tr VND)
A33: adoption ↓ \ churn → | B33: 0.05 | C33: 0.1 | D33: 0.15 | E33: 0.2 | F33: 0.25 | G33: 0.3 | H33: 0.35
A34: 200 | B34: =((((200/(1+EXP(-adoption_steepness*(2028-adoption_midpoint)))*(1-0.05))*(cert_fee_yr1*(1+cert_fee_escalation)^2.5+training_pct*training_fee+audit_fee)*5)+(IF((200/(1+EXP(-adoption_steepness*(2028-adoption_midpoint)))*(1-0.05))>=stage2_gate,ecom_market_base*(1+ecom_growth_rate)^4*platform_market_share*tx_take_rate*1000*3,0))-((IF((200/(1+EXP(-adoption_steepness*(2028-adoption_midpoint)))*(1-0.05))>=stage2_gate,ecom_market_base*(1+ecom_growth_rate)^4*platform_market_share*tx_take_rate*1000*3,0))*payment_proc_pct)-(capex_total+(33*30*12*(1+bhxh_rate)*(1+salary_escalation)^2*5)+(opex_marketing*(1+marketing_growth)^2*5)+(opex_cloud_base*5+(200/(1+EXP(-adoption_steepness*(2028-adoption_midpoint)))*(1-0.05))*vcr_per_enterprise*12*cloud_per_1M_vcr/1000000*5)+((opex_branding+opex_external+opex_legal+opex_security+opex_partner_mgmt)*5)+(capex_total*capex_maintenance_pct*4)))*(1-cit_rate))/(1+discount_rate)^2.5 -> -93665.936 | C34: =((((200/(1+EXP(-adoption_steepness*(2028-adoption_midpoint)))*(1-0.1))*(cert_fee_yr1*(1+cert_fee_escalation)^2.5+training_pct*training_fee+audit_fee)*5)+(IF((200/(1+EXP(-adoption_steepness*(2028-adoption_midpoint)))*(1-0.1))>=stage2_gate,ecom_market_base*(1+ecom_growth_rate)^4*platform_market_share*tx_take_rate*1000*3,0))-((IF((200/(1+EXP(-adoption_steepness*(2028-adoption_midpoint)))*(1-0.1))>=stage2_gate,ecom_market_base*(1+ecom_growth_rate)^4*platform_market_share*tx_take_rate*1000*3,0))*payment_proc_pct)-(capex_total+(33*30*12*(1+bhxh_rate)*(1+salary_escalation)^2*5)+(opex_marketing*(1+marketing_growth)^2*5)+(opex_cloud_base*5+(200/(1+EXP(-adoption_steepness*(2028-adoption_midpoint)))*(1-0.1))*vcr_per_enterprise*12*cloud_per_1M_vcr/1000000*5)+((opex_branding+opex_external+opex_legal+opex_security+opex_partner_mgmt)*5)+(capex_total*capex_maintenance_pct*4)))*(1-cit_rate))/(1+discount_rate)^2.5 -> -94255.168 | D34: =((((200/(1+EXP(-adoption_steepness*(2028-adoption_midpoint)))*(1-0.15))*(cert_fee_yr1*(1+cert_fee_escalation)^2.5+training_pct*training_fee+audit_fee)*5)+(IF((200/(1+EXP(-adoption_steepness*(2028-adoption_midpoint)))*(1-0.15))>=stage2_gate,ecom_market_base*(1+ecom_growth_rate)^4*platform_market_share*tx_take_rate*1000*3,0))-((IF((200/(1+EXP(-adoption_steepness*(2028-adoption_midpoint)))*(1-0.15))>=stage2_gate,ecom_market_base*(1+ecom_growth_rate)^4*platform_market_share*tx_take_rate*1000*3,0))*payment_proc_pct)-(capex_total+(33*30*12*(1+bhxh_rate)*(1+salary_escalation)^2*5)+(opex_marketing*(1+marketing_growth)^2*5)+(opex_cloud_base*5+(200/(1+EXP(-adoption_steepness*(2028-adoption_midpoint)))*(1-0.15))*vcr_per_enterprise*12*cloud_per_1M_vcr/1000000*5)+((opex_branding+opex_external+opex_legal+opex_security+opex_partner_mgmt)*5)+(capex_total*capex_maintenance_pct*4)))*(1-cit_rate))/(1+discount_rate)^2.5 -> -94844.401 | E34: =((((200/(1+EXP(-adoption_steepness*(2028-adoption_midpoint)))*(1-0.2))*(cert_fee_yr1*(1+cert_fee_escalation)^2.5+training_pct*training_fee+audit_fee)*5)+(IF((200/(1+EXP(-adoption_steepness*(2028-adoption_midpoint)))*(1-0.2))>=stage2_gate,ecom_market_base*(1+ecom_growth_rate)^4*platform_market_share*tx_take_rate*1000*3,0))-((IF((200/(1+EXP(-adoption_steepness*(2028-adoption_midpoint)))*(1-0.2))>=stage2_gate,ecom_market_base*(1+ecom_growth_rate)^4*platform_market_share*tx_take_rate*1000*3,0))*payment_proc_pct)-(capex_total+(33*30*12*(1+bhxh_rate)*(1+salary_escalation)^2*5)+(opex_marketing*(1+marketing_growth)^2*5)+(opex_cloud_base*5+(200/(1+EXP(-adoption_steepness*(2028-adoption_midpoint)))*(1-0.2))*vcr_per_enterprise*12*cloud_per_1M_vcr/1000000*5)+((opex_branding+opex_external+opex_legal+opex_security+opex_partner_mgmt)*5)+(capex_total*capex_maintenance_pct*4)))*(1-cit_rate))/(1+discount_rate)^2.5 -> -95433.633 | F34: =((((200/(1+EXP(-adoption_steepness*(2028-adoption_midpoint)))*(1-0.25))*(cert_fee_yr1*(1+cert_fee_escalation)^2.5+training_pct*training_fee+audit_fee)*5)+(IF((200/(1+EXP(-adoption_steepness*(2028-adoption_midpoint)))*(1-0.25))>=stage2_gate,ecom_market_base*(1+ecom_growth_rate)^4*platform_market_share*tx_take_rate*1000*3,0))-((IF((200/(1+EXP(-adoption_steepness*(2028-adoption_midpoint)))*(1-0.25))>=stage2_gate,ecom_market_base*(1+ecom_growth_rate)^4*platform_market_share*tx_take_rate*1000*3,0))*payment_proc_pct)-(capex_total+(33*30*12*(1+bhxh_rate)*(1+salary_escalation)^2*5)+(opex_marketing*(1+marketing_growth)^2*5)+(opex_cloud_base*5+(200/(1+EXP(-adoption_steepness*(2028-adoption_midpoint)))*(1-0.25))*vcr_per_enterprise*12*cloud_per_1M_vcr/1000000*5)+((opex_branding+opex_external+opex_legal+opex_security+opex_partner_mgmt)*5)+(capex_total*capex_maintenance_pct*4)))*(1-cit_rate))/(1+discount_rate)^2.5 -> -96022.866 | G34: =((((200/(1+EXP(-adoption_steepness*(2028-adoption_midpoint)))*(1-0.3))*(cert_fee_yr1*(1+cert_fee_escalation)^2.5+training_pct*training_fee+audit_fee)*5)+(IF((200/(1+EXP(-adoption_steepness*(2028-adoption_midpoint)))*(1-0.3))>=stage2_gate,ecom_market_base*(1+ecom_growth_rate)^4*platform_market_share*tx_take_rate*1000*3,0))-((IF((200/(1+EXP(-adoption_steepness*(2028-adoption_midpoint)))*(1-0.3))>=stage2_gate,ecom_market_base*(1+ecom_growth_rate)^4*platform_market_share*tx_take_rate*1000*3,0))*payment_proc_pct)-(capex_total+(33*30*12*(1+bhxh_rate)*(1+salary_escalation)^2*5)+(opex_marketing*(1+marketing_growth)^2*5)+(opex_cloud_base*5+(200/(1+EXP(-adoption_steepness*(2028-adoption_midpoint)))*(1-0.3))*vcr_per_enterprise*12*cloud_per_1M_vcr/1000000*5)+((opex_branding+opex_external+opex_legal+opex_security+opex_partner_mgmt)*5)+(capex_total*capex_maintenance_pct*4)))*(1-cit_rate))/(1+discount_rate)^2.5 -> -96612.098 | H34: =((((200/(1+EXP(-adoption_steepness*(2028-adoption_midpoint)))*(1-0.35))*(cert_fee_yr1*(1+cert_fee_escalation)^2.5+training_pct*training_fee+audit_fee)*5)+(IF((200/(1+EXP(-adoption_steepness*(2028-adoption_midpoint)))*(1-0.35))>=stage2_gate,ecom_market_base*(1+ecom_growth_rate)^4*platform_market_share*tx_take_rate*1000*3,0))-((IF((200/(1+EXP(-adoption_steepness*(2028-adoption_midpoint)))*(1-0.35))>=stage2_gate,ecom_market_base*(1+ecom_growth_rate)^4*platform_market_share*tx_take_rate*1000*3,0))*payment_proc_pct)-(capex_total+(33*30*12*(1+bhxh_rate)*(1+salary_escalation)^2*5)+(opex_marketing*(1+marketing_growth)^2*5)+(opex_cloud_base*5+(200/(1+EXP(-adoption_steepness*(2028-adoption_midpoint)))*(1-0.35))*vcr_per_enterprise*12*cloud_per_1M_vcr/1000000*5)+((opex_branding+opex_external+opex_legal+opex_security+opex_partner_mgmt)*5)+(capex_total*capex_maintenance_pct*4)))*(1-cit_rate))/(1+discount_rate)^2.5 -> -97201.331
